{
  "type": "Feature",
  "properties": {
    "gn:admin1_code":"11.0",
    "gn:admin2_code":"521.0",
    "gn:asciiname":"Guldbringen",
    "gn:country_code":"NO",
    "gn:dem":883,
    "gn:feature_class":"P",
    "gn:feature_code":"PPL",
    "gn:name":"Guldbringen",
    "gn:population":0,
    "gn:timezone":"Europe/Oslo",
    "iso:country":"NO",
    "name:nor_x_preferred":[
        "Guldbringen"
    ],
    "name:nor_x_variant":[
        "Gullbringen"
    ],
    "wof:name":"Guldbringen",
    "wof:placetype":"locality"
},
  "geometry": {"coordinates":[10.61231,61.29616],"type":"Point"}
}