{
  "type": "Feature",
  "properties": {
    "iso:country":"NO",
    "name:dut_x_preferred":[
        "Langfjordbotn"
    ],
    "name:eng_x_preferred":[
        "Langfjordbotn"
    ],
    "name:fre_x_preferred":[
        "Langfjordbotn"
    ],
    "name:jav_x_preferred":[
        "Langfjordbotn"
    ],
    "name:may_x_preferred":[
        "Langfjordbotn"
    ],
    "name:nob_x_preferred":[
        "Langfjordbotn"
    ],
    "name:urd_x_preferred":[
        "\u0644\u0627\u0646\u06af\u0641\u062c\u0648\u0631\u0688\u0628\u0648\u0679\u0646\u060c \u0627\u0644\u0679\u0627"
    ],
    "qs_pg:aaroncc":"NO",
    "qs_pg:name":"Langfjordbotn",
    "qs_pg:name_adm0":"Norge",
    "qs_pg:name_adm1":"Finnmark Fylke",
    "qs_pg:photos":29,
    "qs_pg:photos_1k":6,
    "qs_pg:photos_9k":1,
    "qs_pg:photos_9r":2,
    "qs_pg:photos_all":29,
    "qs_pg:photos_sr":2,
    "qs_pg:pop_sr":0,
    "qs_pg:qs_pg_placetype":"locality",
    "qs_pg:qs_pg_placetype_gp":"Town",
    "qs_pg:woe_adm0":23424910,
    "woe:adm0_id":23424910,
    "woe:name_adm0":"Norge",
    "woe:name_adm1":"Finnmark Fylke",
    "woe:placetype":"Town",
    "wof:name":"Langfjordbotn",
    "wof:placetype":"locality"
},
  "geometry": {"coordinates":[22.2775,70.03887899999999],"type":"Point"}
}