{
  "type": "Feature",
  "properties": {
    "gn:admin1_code":"15",
    "gn:admin2_code":"1419.0",
    "gn:asciiname":"Fosse",
    "gn:country_code":"NO",
    "gn:dem":-9999,
    "gn:feature_class":"P",
    "gn:feature_code":"PPL",
    "gn:name":"Fosse",
    "gn:population":0,
    "gn:timezone":"Europe/Oslo",
    "iso:country":"NO",
    "name:ceb_x_preferred":[
        "Fosse"
    ],
    "name:deu_x_preferred":[
        "Fosse"
    ],
    "name:fra_x_preferred":[
        "Fosse"
    ],
    "name:heb_x_preferred":[
        "\u05e4\u05d5\u05e1\u05d9"
    ],
    "name:ita_x_preferred":[
        "Fosse"
    ],
    "name:nds_x_preferred":[
        "Fosse"
    ],
    "name:nld_x_preferred":[
        "Fosse"
    ],
    "name:nor_x_preferred":[
        "Fosse"
    ],
    "name:rus_x_preferred":[
        "\u0424\u043e\u0441\u0441"
    ],
    "name:srp_x_preferred":[
        "Fosse"
    ],
    "name:swe_x_preferred":[
        "Fosse"
    ],
    "name:ukr_x_preferred":[
        "\u0424\u043e\u0441\u0441"
    ],
    "name:wln_x_preferred":[
        "Fosse"
    ],
    "wof:name":"Fosse",
    "wof:placetype":"locality"
},
  "geometry": {"coordinates":[6.75,61.18333000000001],"type":"Point"}
}