{
  "type": "Feature",
  "properties": {
    "gn:admin1_code":"11.0",
    "gn:admin2_code":"520.0",
    "gn:asciiname":"Gullhaugsaetra",
    "gn:country_code":"NO",
    "gn:dem":862,
    "gn:feature_class":"P",
    "gn:feature_code":"PPL",
    "gn:name":"Gullhaugs\u00e6tra",
    "gn:population":0,
    "gn:timezone":"Europe/Oslo",
    "iso:country":"NO",
    "name:nor_x_preferred":[
        "Gullhaugs\u00e6tra"
    ],
    "wof:name":"Gullhaugsaetra",
    "wof:placetype":"locality"
},
  "geometry": {"coordinates":[10.38906,61.4206],"type":"Point"}
}