{
  "type": "Feature",
  "properties": {
    "gn:admin1_code":"21.0",
    "gn:admin2_code":"5024.0",
    "gn:asciiname":"Solbu",
    "gn:cc2":"NO",
    "gn:country_code":"NO",
    "gn:dem":160,
    "gn:feature_class":"P",
    "gn:feature_code":"PPL",
    "gn:name":"Solbu",
    "gn:population":0,
    "gn:timezone":"Europe/Oslo",
    "iso:country":"NO",
    "name:und_x_variant":[
        "Solbio",
        "Solbu"
    ],
    "wof:name":"Solbu",
    "wof:placetype":"locality"
},
  "geometry": {"coordinates":[9.79349,63.21556],"type":"Point"}
}