{
  "type": "Feature",
  "properties": {
    "gn:admin1_code":"6",
    "gn:admin2_code":"429.0",
    "gn:asciiname":"Amot",
    "gn:cc2":"NO",
    "gn:country_code":"NO",
    "gn:dem":280,
    "gn:feature_class":"P",
    "gn:feature_code":"PPL",
    "gn:name":"\u00c5mot",
    "gn:population":0,
    "gn:timezone":"Europe/Oslo",
    "iso:country":"NO",
    "name:und_x_variant":[
        "Aamot",
        "\u00c5mot"
    ],
    "wof:name":"Amot",
    "wof:placetype":"neighbourhood"
},
  "geometry": {"coordinates":[11.38333,61.13333000000001],"type":"Point"}
}