{
  "type": "Feature",
  "properties": {
    "gn:admin1_code":"19",
    "gn:admin2_code":"1003.0",
    "gn:asciiname":"Lauland",
    "gn:country_code":"NO",
    "gn:dem":57,
    "gn:feature_class":"P",
    "gn:feature_code":"PPL",
    "gn:name":"Lauland",
    "gn:population":0,
    "gn:timezone":"Europe/Oslo",
    "iso:country":"NO",
    "wof:name":"Lauland",
    "wof:placetype":"locality"
},
  "geometry": {"coordinates":[6.84812,58.13179],"type":"Point"}
}