{
  "type": "Feature",
  "properties": {
    "gn:admin1_code":"9",
    "gn:admin2_code":"1822.0",
    "gn:asciiname":"Meisfjorden",
    "gn:country_code":"NO",
    "gn:dem":40,
    "gn:feature_class":"P",
    "gn:feature_code":"PPL",
    "gn:name":"Meisfjorden",
    "gn:population":0,
    "gn:timezone":"Europe/Oslo",
    "iso:country":"NO",
    "wof:name":"Meisfjorden",
    "wof:placetype":"locality"
},
  "geometry": {"coordinates":[12.83333,66.06667],"type":"Point"}
}