{
  "type": "Feature",
  "properties": {
    "gn:admin1_code":"17.0",
    "gn:admin2_code":"828.0",
    "gn:asciiname":"Skori",
    "gn:country_code":"NO",
    "gn:dem":701,
    "gn:feature_class":"P",
    "gn:feature_code":"PPL",
    "gn:name":"Skori",
    "gn:population":0,
    "gn:timezone":"Europe/Oslo",
    "iso:country":"NO",
    "wof:name":"Skori",
    "wof:placetype":"locality"
},
  "geometry": {"coordinates":[8.35,59.65],"type":"Point"}
}