{
  "type": "Feature",
  "properties": {
    "gn:country":"NO",
    "gn:fcode":"PPLA2",
    "gn:population":0,
    "iso:country":"NO",
    "name:cat_x_preferred":[
        "Kleppest\u00f8"
    ],
    "name:dan_x_preferred":[
        "Kleppest\u00f8"
    ],
    "name:eng_x_preferred":[
        "Kleppest\u00f8"
    ],
    "name:fra_x_preferred":[
        "Kleppest\u00f8"
    ],
    "name:ita_x_preferred":[
        "Kleppest\u00f8"
    ],
    "name:jav_x_preferred":[
        "Kleppest\u00f8"
    ],
    "name:msa_x_preferred":[
        "Kleppest\u00f8"
    ],
    "name:nld_x_preferred":[
        "Kleppest\u00f8"
    ],
    "name:nno_x_preferred":[
        "Kleppest\u00f8"
    ],
    "name:nob_x_preferred":[
        "Kleppest\u00f8"
    ],
    "name:ron_x_preferred":[
        "Kleppest\u00f8"
    ],
    "name:spa_x_preferred":[
        "Kleppest\u00f8"
    ],
    "name:swe_x_preferred":[
        "Kleppest\u00f8"
    ],
    "name:swe_x_variant":[
        "Bygdin"
    ],
    "qs_pg:aaroncc":"NO",
    "qs_pg:gn_country":"NO",
    "qs_pg:gn_fcode":"PPLA2",
    "qs_pg:gn_pop":0,
    "qs_pg:name":"Kleppest\u00f8",
    "qs_pg:name_adm0":"Norge",
    "qs_pg:name_adm1":"Hordaland Fylke",
    "qs_pg:photos":1251,
    "qs_pg:photos_1k":253,
    "qs_pg:photos_9k":6,
    "qs_pg:photos_9r":7,
    "qs_pg:photos_all":1251,
    "qs_pg:photos_sr":12,
    "qs_pg:pop_sr":0,
    "qs_pg:qs_pg_placetype":"locality",
    "qs_pg:qs_pg_placetype_gp":"Town",
    "qs_pg:woe_adm0":23424910,
    "woe:adm0_id":23424910,
    "woe:name_adm0":"Norge",
    "woe:name_adm1":"Hordaland Fylke",
    "woe:placetype":"Town",
    "wof:name":"Kleppest\u00f8",
    "wof:placetype":"neighbourhood"
},
  "geometry": {"coordinates":[5.2276,60.40844],"type":"Point"}
}