{
  "type": "Feature",
  "properties": {
    "gn:admin1_code":"9.0",
    "gn:admin2_code":"1850.0",
    "gn:asciiname":"Biesseluokta",
    "gn:country_code":"NO",
    "gn:dem":1,
    "gn:feature_class":"P",
    "gn:feature_code":"PPL",
    "gn:name":"Biesseluokta",
    "gn:population":0,
    "gn:timezone":"Europe/Oslo",
    "iso:country":"NO",
    "name:nor_x_preferred":[
        "Nevervika"
    ],
    "name:smj_x_preferred":[
        "Biesseluokta"
    ],
    "wof:name":"Biesseluokta",
    "wof:placetype":"locality"
},
  "geometry": {"coordinates":[16.10628,68.12238000000001],"type":"Point"}
}