{
  "type": "Feature",
  "properties": {
    "gn:admin1_code":"19",
    "gn:admin2_code":"1037.0",
    "gn:asciiname":"Fjotland",
    "gn:country_code":"NO",
    "gn:dem":339,
    "gn:feature_class":"P",
    "gn:feature_code":"PPL",
    "gn:name":"Fjotland",
    "gn:population":0,
    "gn:timezone":"Europe/Oslo",
    "iso:country":"NO",
    "name:msa_x_preferred":[
        "Fjotland"
    ],
    "wof:name":"Fjotland",
    "wof:placetype":"locality"
},
  "geometry": {"coordinates":[6.99208,58.52643000000001],"type":"Point"}
}