{
  "type": "Feature",
  "properties": {
    "gn:admin1_code":"7.0",
    "gn:asciiname":"Viland",
    "gn:country_code":"NO",
    "gn:dem":48,
    "gn:feature_class":"P",
    "gn:feature_code":"PPL",
    "gn:name":"Viland",
    "gn:population":0,
    "gn:timezone":"Europe/Oslo",
    "iso:country":"NO",
    "wof:name":"Viland",
    "wof:placetype":"locality"
},
  "geometry": {"coordinates":[5.71667,59.58333],"type":"Point"}
}