{
  "type": "Feature",
  "properties": {
    "iso:country":"NO",
    "name:bre_x_preferred":[
        "Gola"
    ],
    "name:cat_x_preferred":[
        "Gola"
    ],
    "name:ceb_x_preferred":[
        "Gola"
    ],
    "name:deu_x_preferred":[
        "Gola"
    ],
    "name:fra_x_preferred":[
        "Gola"
    ],
    "name:heb_x_preferred":[
        "\u05d2\u05d5\u05dc\u05d4"
    ],
    "name:hun_x_preferred":[
        "Gola"
    ],
    "name:ita_x_preferred":[
        "Gola"
    ],
    "name:new_x_preferred":[
        "\u0917\u094b\u0932\u093e"
    ],
    "name:nld_x_preferred":[
        "Gola"
    ],
    "name:pol_x_preferred":[
        "Gola"
    ],
    "name:por_x_preferred":[
        "Gola"
    ],
    "name:rus_x_preferred":[
        "\u0413\u043e\u043b\u0430"
    ],
    "name:spa_x_preferred":[
        "Gola"
    ],
    "name:swe_x_preferred":[
        "Gola"
    ],
    "name:ukr_x_preferred":[
        "\u0413\u043e\u043b\u0430"
    ],
    "qs_pg:aaroncc":"NO",
    "qs_pg:name":"Gola",
    "qs_pg:name_adm0":"Norge",
    "qs_pg:name_adm1":"Oppland Fylke",
    "qs_pg:photos":82,
    "qs_pg:photos_1k":17,
    "qs_pg:photos_9k":1,
    "qs_pg:photos_9r":3,
    "qs_pg:photos_all":82,
    "qs_pg:photos_sr":3,
    "qs_pg:pop_sr":0,
    "qs_pg:qs_pg_placetype":"locality",
    "qs_pg:qs_pg_placetype_gp":"Town",
    "qs_pg:woe_adm0":23424910,
    "woe:adm0_id":23424910,
    "woe:name_adm0":"Norge",
    "woe:name_adm1":"Oppland Fylke",
    "woe:placetype":"Town",
    "wof:name":"Gola",
    "wof:placetype":"locality"
},
  "geometry": {"coordinates":[9.790111,61.49993],"type":"Point"}
}