{
  "type": "Feature",
  "properties": {
    "gn:country":"NO",
    "gn:fcode":"PPL",
    "gn:population":344,
    "iso:country":"NO",
    "name:ceb_x_preferred":[
        "Tveitsund"
    ],
    "name:eng_x_preferred":[
        "Tveitsund"
    ],
    "name:fra_x_preferred":[
        "Tveitsund"
    ],
    "name:msa_x_preferred":[
        "Tveitsund"
    ],
    "name:nld_x_preferred":[
        "Tveitsund"
    ],
    "name:ron_x_preferred":[
        "Tveitsund"
    ],
    "name:spa_x_preferred":[
        "Tveitsund"
    ],
    "qs_pg:aaroncc":"NO",
    "qs_pg:gn_country":"NO",
    "qs_pg:gn_fcode":"PPL",
    "qs_pg:gn_pop":344,
    "qs_pg:name":"Tveitsund",
    "qs_pg:name_adm0":"Norge",
    "qs_pg:name_adm1":"Telemark Fylke",
    "qs_pg:photos_9k":1,
    "qs_pg:photos_9r":1,
    "qs_pg:photos_all":1,
    "qs_pg:photos_sr":0,
    "qs_pg:pop_sr":2,
    "qs_pg:qs_pg_placetype":"locality",
    "qs_pg:qs_pg_placetype_gp":"Town",
    "qs_pg:woe_adm0":23424910,
    "woe:adm0_id":23424910,
    "woe:name_adm0":"Norge",
    "woe:name_adm1":"Telemark Fylke",
    "woe:placetype":"Town",
    "wof:name":"Tveitsund",
    "wof:placetype":"locality",
    "wof:population":344
},
  "geometry": {"coordinates":[8.52421,59.01877],"type":"Point"}
}