{
  "type": "Feature",
  "properties": {
    "gn:admin1_code":"8.0",
    "gn:admin2_code":"1560.0",
    "gn:asciiname":"Stolbygda",
    "gn:country_code":"NO",
    "gn:dem":120,
    "gn:feature_class":"P",
    "gn:feature_code":"PPL",
    "gn:name":"St\u00f8lbygda",
    "gn:population":0,
    "gn:timezone":"Europe/Oslo",
    "iso:country":"NO",
    "name:nor_x_preferred":[
        "St\u00f8lbygda"
    ],
    "wof:name":"Stolbygda",
    "wof:placetype":"locality"
},
  "geometry": {"coordinates":[8.20054,62.89508000000001],"type":"Point"}
}