{
  "type": "Feature",
  "properties": {
    "gn:admin1_code":"15.0",
    "gn:admin2_code":"1441.0",
    "gn:asciiname":"Berge Nedre",
    "gn:country_code":"NO",
    "gn:dem":180,
    "gn:feature_class":"P",
    "gn:feature_code":"PPL",
    "gn:name":"Berge Nedre",
    "gn:population":0,
    "gn:timezone":"Europe/Oslo",
    "iso:country":"NO",
    "name:nor_x_preferred":[
        "Berge Nedre"
    ],
    "wof:name":"Berge Nedre",
    "wof:placetype":"locality"
},
  "geometry": {"coordinates":[5.38688,62.0363],"type":"Point"}
}