{
  "type": "Feature",
  "properties": {
    "gn:admin1_code":"14",
    "gn:admin2_code":"1101.0",
    "gn:asciiname":"Hestad",
    "gn:country_code":"NO",
    "gn:dem":357,
    "gn:feature_class":"P",
    "gn:feature_code":"PPL",
    "gn:name":"Hestad",
    "gn:population":0,
    "gn:timezone":"Europe/Oslo",
    "iso:country":"NO",
    "name:deu_x_preferred":[
        "Hestad"
    ],
    "name:nor_x_preferred":[
        "Hestad"
    ],
    "wof:name":"Hestad",
    "wof:placetype":"locality"
},
  "geometry": {"coordinates":[6.21667,58.53333000000001],"type":"Point"}
}