{
  "type": "Feature",
  "properties": {
    "gn:admin1_code":"21.0",
    "gn:admin2_code":"5013.0",
    "gn:asciiname":"Kjerbusdalen",
    "gn:cc2":"NO",
    "gn:country_code":"NO",
    "gn:dem":55,
    "gn:feature_class":"P",
    "gn:feature_code":"PPL",
    "gn:name":"Kjerbusdalen",
    "gn:population":0,
    "gn:timezone":"Europe/Oslo",
    "iso:country":"NO",
    "name:und_x_variant":[
        "Skjerbusdal",
        "Skj\u00e6rbusdal",
        "Skj\u00e6rbostad",
        "Kjerbusdalen"
    ],
    "wof:name":"Kjerbusdalen",
    "wof:placetype":"locality"
},
  "geometry": {"coordinates":[9.08333,63.66667],"type":"Point"}
}