{
  "type": "Feature",
  "properties": {
    "gn:admin1_code":"9",
    "gn:admin2_code":"1804.0",
    "gn:asciiname":"Bliksvaer",
    "gn:cc2":"NO",
    "gn:country_code":"NO",
    "gn:dem":3,
    "gn:feature_class":"P",
    "gn:feature_code":"PPL",
    "gn:name":"Bliksv\u00e6r",
    "gn:population":0,
    "gn:timezone":"Europe/Oslo",
    "iso:country":"NO",
    "name:und_x_variant":[
        "Bliksv\u00e6r",
        "Brikksvaer",
        "Briksv\u00e6r"
    ],
    "wof:name":"Bliksvaer",
    "wof:placetype":"locality"
},
  "geometry": {"coordinates":[14.00357,67.27719],"type":"Point"}
}