{
  "type": "Feature",
  "properties": {
    "gn:admin1_code":"4.0",
    "gn:admin2_code":"619.0",
    "gn:asciiname":"Oppheim",
    "gn:cc2":"NO",
    "gn:country_code":"NO",
    "gn:dem":588,
    "gn:feature_class":"P",
    "gn:feature_code":"PPL",
    "gn:name":"Oppheim",
    "gn:population":0,
    "gn:timezone":"Europe/Oslo",
    "iso:country":"NO",
    "name:nor_x_preferred":[
        "Oppheim"
    ],
    "name:nor_x_variant":[
        "Opeim",
        "Ophejmsbygden",
        "Opheim",
        "Oppheimsbygde"
    ],
    "name:und_x_variant":[
        "Uppheim"
    ],
    "wof:name":"Oppheim",
    "wof:placetype":"locality"
},
  "geometry": {"coordinates":[8.68136,60.67211],"type":"Point"}
}