{
  "type": "Feature",
  "properties": {
    "gn:admin1_code":"18",
    "gn:admin2_code":"1924.0",
    "gn:asciiname":"Brorstad",
    "gn:country_code":"NO",
    "gn:dem":26,
    "gn:feature_class":"P",
    "gn:feature_code":"PPL",
    "gn:name":"Brorstad",
    "gn:population":0,
    "gn:timezone":"Europe/Oslo",
    "iso:country":"NO",
    "wof:name":"Brorstad",
    "wof:placetype":"locality"
},
  "geometry": {"coordinates":[18.58333,69.16667],"type":"Point"}
}