{
  "type": "Feature",
  "properties": {
    "gn:admin1_code":"21",
    "gn:admin2_code":"5033.0",
    "gn:asciiname":"Kirkvoll",
    "gn:cc2":"NO",
    "gn:country_code":"NO",
    "gn:dem":492,
    "gn:feature_class":"P",
    "gn:feature_code":"PPL",
    "gn:name":"Kirkvoll",
    "gn:population":0,
    "gn:timezone":"Europe/Oslo",
    "iso:country":"NO",
    "name:und_x_variant":[
        "Kirkvolden",
        "Kiyrkvollen",
        "Kirkvoll"
    ],
    "wof:name":"Kirkvoll",
    "wof:placetype":"locality"
},
  "geometry": {"coordinates":[11.68333,63.03333000000001],"type":"Point"}
}