{
  "type": "Feature",
  "properties": {
    "gn:admin1_code":"18",
    "gn:admin2_code":"1922.0",
    "gn:asciiname":"Bones",
    "gn:country_code":"NO",
    "gn:dem":293,
    "gn:feature_class":"P",
    "gn:feature_code":"PPL",
    "gn:name":"Bones",
    "gn:population":0,
    "gn:timezone":"Europe/Oslo",
    "iso:country":"NO",
    "wof:name":"Bones",
    "wof:placetype":"locality"
},
  "geometry": {"coordinates":[18.24338,68.64546999999999],"type":"Point"}
}