{
  "type": "Feature",
  "properties": {
    "gn:admin1_code":"21.0",
    "gn:admin2_code":"5021.0",
    "gn:asciiname":"Orstad",
    "gn:country_code":"NO",
    "gn:dem":509,
    "gn:feature_class":"P",
    "gn:feature_code":"PPL",
    "gn:name":"\u00d8rstad",
    "gn:population":0,
    "gn:timezone":"Europe/Oslo",
    "iso:country":"NO",
    "name:nor_x_preferred":[
        "\u00d8rstad"
    ],
    "wof:name":"Orstad",
    "wof:placetype":"locality"
},
  "geometry": {"coordinates":[9.61457,62.55777],"type":"Point"}
}