{
  "type": "Feature",
  "properties": {
    "gn:admin1_code":"7",
    "gn:admin2_code":"1247.0",
    "gn:asciiname":"Straumsnes",
    "gn:country_code":"NO",
    "gn:dem":3,
    "gn:feature_class":"P",
    "gn:feature_code":"PPL",
    "gn:name":"Straumsnes",
    "gn:population":0,
    "gn:timezone":"Europe/Oslo",
    "iso:country":"NO",
    "wof:name":"Straumsnes",
    "wof:placetype":"locality"
},
  "geometry": {"coordinates":[5.23306,60.45833],"type":"Point"}
}