{
  "type": "Feature",
  "properties": {
    "gn:admin1_code":"18",
    "gn:admin2_code":"1929.0",
    "gn:asciiname":"Mefjordvaer",
    "gn:country_code":"NO",
    "gn:dem":63,
    "gn:feature_class":"P",
    "gn:feature_code":"PPLL",
    "gn:name":"Mefjordv\u00e6r",
    "gn:population":0,
    "gn:timezone":"Europe/Oslo",
    "iso:country":"NO",
    "name:fra_x_preferred":[
        "Mefjordv\u00e6r"
    ],
    "name:msa_x_preferred":[
        "Mefjordv\u00e6r"
    ],
    "name:nor_x_preferred":[
        "Mefjordv\u00e6r"
    ],
    "name:spa_x_preferred":[
        "Mefjordv\u00e6r"
    ],
    "wof:name":"Mefjordvaer",
    "wof:placetype":"locality"
},
  "geometry": {"coordinates":[17.44088,69.51579],"type":"Point"}
}