{
  "type": "Feature",
  "properties": {
    "gn:admin1_code":"15",
    "gn:admin2_code":"1429.0",
    "gn:asciiname":"Hernes",
    "gn:country_code":"NO",
    "gn:dem":3,
    "gn:feature_class":"P",
    "gn:feature_code":"PPL",
    "gn:name":"Hernes",
    "gn:population":0,
    "gn:timezone":"Europe/Oslo",
    "iso:country":"NO",
    "wof:name":"Hernes",
    "wof:placetype":"locality"
},
  "geometry": {"coordinates":[5.31667,61.33333],"type":"Point"}
}