{
  "type": "Feature",
  "properties": {
    "gn:admin1_code":"4",
    "gn:admin2_code":"632.0",
    "gn:asciiname":"Kjomme",
    "gn:country_code":"NO",
    "gn:dem":210,
    "gn:feature_class":"P",
    "gn:feature_code":"PPL",
    "gn:name":"Kjomme",
    "gn:population":0,
    "gn:timezone":"Europe/Oslo",
    "iso:country":"NO",
    "wof:name":"Kjomme",
    "wof:placetype":"locality"
},
  "geometry": {"coordinates":[9.31667,59.96666999999999],"type":"Point"}
}