{
  "type": "Feature",
  "properties": {
    "gn:admin1_code":"14",
    "gn:admin2_code":"1134.0",
    "gn:asciiname":"Askvika",
    "gn:cc2":"NO",
    "gn:country_code":"NO",
    "gn:dem":297,
    "gn:feature_class":"P",
    "gn:feature_code":"PPL",
    "gn:name":"Askvika",
    "gn:population":0,
    "gn:timezone":"Europe/Oslo",
    "iso:country":"NO",
    "name:und_x_variant":[
        "Askvik",
        "Askvika"
    ],
    "wof:name":"Askvika",
    "wof:placetype":"locality"
},
  "geometry": {"coordinates":[5.95,59.38333000000001],"type":"Point"}
}