{
  "type": "Feature",
  "properties": {
    "gn:country":"NO",
    "gn:fcode":"PPL",
    "gn:population":584,
    "iso:country":"NO",
    "name:ceb_x_preferred":[
        "Sira"
    ],
    "name:dan_x_preferred":[
        "\u00c5na-Sira"
    ],
    "name:deu_x_preferred":[
        "Sira"
    ],
    "name:eng_x_preferred":[
        "Sira"
    ],
    "name:fra_x_preferred":[
        "Sira"
    ],
    "name:msa_x_preferred":[
        "Sira"
    ],
    "name:nld_x_preferred":[
        "Sira"
    ],
    "name:nno_x_preferred":[
        "\u00c5na-Sira"
    ],
    "name:nob_x_preferred":[
        "\u00c5na-Sira"
    ],
    "name:swe_x_preferred":[
        "\u00c5na-Sira"
    ],
    "name:und_x_variant":[
        "Sire"
    ],
    "qs_pg:aaroncc":"NO",
    "qs_pg:gn_country":"NO",
    "qs_pg:gn_fcode":"PPL",
    "qs_pg:gn_pop":584,
    "qs_pg:name":"Sira",
    "qs_pg:name_adm0":"Norge",
    "qs_pg:name_adm1":"Vest-Agder Fylke",
    "qs_pg:photos":12,
    "qs_pg:photos_1k":2,
    "qs_pg:photos_9k":1,
    "qs_pg:photos_9r":1,
    "qs_pg:photos_all":12,
    "qs_pg:photos_sr":1,
    "qs_pg:pop_sr":2,
    "qs_pg:qs_pg_placetype":"locality",
    "qs_pg:qs_pg_placetype_gp":"Town",
    "qs_pg:woe_adm0":23424910,
    "woe:adm0_id":23424910,
    "woe:name_adm0":"Norge",
    "woe:name_adm1":"Vest-Agder Fylke",
    "woe:placetype":"Town",
    "wof:name":"Sira",
    "wof:placetype":"locality",
    "wof:population":584
},
  "geometry": {"coordinates":[6.63333,58.41667],"type":"Point"}
}