{
  "type": "Feature",
  "properties": {
    "gn:country":"NO",
    "gn:fcode":"PPLA2",
    "gn:population":0,
    "iso:country":"NO",
    "name:dan_x_preferred":[
        "Skaland"
    ],
    "name:eng_x_preferred":[
        "Skaland"
    ],
    "name:fra_x_preferred":[
        "Skaland"
    ],
    "name:ita_x_preferred":[
        "Skaland"
    ],
    "name:msa_x_preferred":[
        "Skaland"
    ],
    "name:nld_x_preferred":[
        "Skaland"
    ],
    "name:nno_x_preferred":[
        "Skaland"
    ],
    "name:nob_x_preferred":[
        "Skaland"
    ],
    "name:ron_x_preferred":[
        "Skaland"
    ],
    "name:rus_x_preferred":[
        "\u0421\u043a\u0430\u043b\u0430\u043d\u043d"
    ],
    "name:sme_x_preferred":[
        "Skaland"
    ],
    "name:spa_x_preferred":[
        "Skaland"
    ],
    "name:swe_x_preferred":[
        "Skaland"
    ],
    "qs_pg:aaroncc":"NO",
    "qs_pg:gn_country":"NO",
    "qs_pg:gn_fcode":"PPLA2",
    "qs_pg:gn_pop":0,
    "qs_pg:name":"Skaland",
    "qs_pg:name_adm0":"Norge",
    "qs_pg:name_adm1":"Troms Fylke",
    "qs_pg:photos":177,
    "qs_pg:photos_1k":36,
    "qs_pg:photos_9k":1,
    "qs_pg:photos_9r":4,
    "qs_pg:photos_all":177,
    "qs_pg:photos_sr":4,
    "qs_pg:pop_sr":0,
    "qs_pg:qs_pg_placetype":"locality",
    "qs_pg:qs_pg_placetype_gp":"Town",
    "qs_pg:woe_adm0":23424910,
    "woe:adm0_id":23424910,
    "woe:name_adm0":"Norge",
    "woe:name_adm1":"Troms Fylke",
    "woe:placetype":"Town",
    "wof:name":"Skaland",
    "wof:placetype":"locality"
},
  "geometry": {"coordinates":[17.29832,69.44456],"type":"Point"}
}