{
  "type": "Feature",
  "properties": {
    "gn:admin1_code":"7.0",
    "gn:admin2_code":"1234.0",
    "gn:asciiname":"Spildo",
    "gn:country_code":"NO",
    "gn:dem":140,
    "gn:feature_class":"P",
    "gn:feature_code":"PPL",
    "gn:name":"Spildo",
    "gn:population":0,
    "gn:timezone":"Europe/Oslo",
    "iso:country":"NO",
    "wof:name":"Spildo",
    "wof:placetype":"locality"
},
  "geometry": {"coordinates":[6.68333,60.58333],"type":"Point"}
}