{
  "type": "Feature",
  "properties": {
    "gn:admin1_code":"11.0",
    "gn:admin2_code":"515.0",
    "gn:asciiname":"Synstlie",
    "gn:country_code":"NO",
    "gn:dem":860,
    "gn:feature_class":"P",
    "gn:feature_code":"PPL",
    "gn:name":"Synstlie",
    "gn:population":0,
    "gn:timezone":"Europe/Oslo",
    "iso:country":"NO",
    "name:nor_x_preferred":[
        "Synstlie"
    ],
    "name:nor_x_variant":[
        "Synslie"
    ],
    "wof:name":"Synstlie",
    "wof:placetype":"locality"
},
  "geometry": {"coordinates":[8.98836,61.82686],"type":"Point"}
}