{
  "type": "Feature",
  "properties": {
    "gn:admin1_code":"1.0",
    "gn:admin2_code":"220.0",
    "gn:asciiname":"Sjostrand",
    "gn:country_code":"NO",
    "gn:dem":39,
    "gn:feature_class":"P",
    "gn:feature_code":"PPL",
    "gn:name":"Sj\u00f8strand",
    "gn:population":0,
    "gn:timezone":"Europe/Oslo",
    "iso:country":"NO",
    "name:nor_x_preferred":[
        "Sj\u00f8strand"
    ],
    "wof:name":"Sjostrand",
    "wof:placetype":"locality"
},
  "geometry": {"coordinates":[10.49165,59.79751],"type":"Point"}
}