{
  "type": "Feature",
  "properties": {
    "gn:admin1_code":"15",
    "gn:admin2_code":"1432.0",
    "gn:asciiname":"Karstad",
    "gn:country_code":"NO",
    "gn:dem":241,
    "gn:feature_class":"P",
    "gn:feature_code":"PPL",
    "gn:name":"Karstad",
    "gn:population":0,
    "gn:timezone":"Europe/Oslo",
    "iso:country":"NO",
    "wof:name":"Karstad",
    "wof:placetype":"locality"
},
  "geometry": {"coordinates":[5.66667,61.43333000000001],"type":"Point"}
}