{
  "type": "Feature",
  "properties": {
    "gn:admin1_code":"15",
    "gn:admin2_code":"1443.0",
    "gn:asciiname":"Horn",
    "gn:cc2":"NO",
    "gn:country_code":"NO",
    "gn:dem":180,
    "gn:feature_class":"P",
    "gn:feature_code":"PPL",
    "gn:name":"Horn",
    "gn:population":0,
    "gn:timezone":"Europe/Oslo",
    "iso:country":"NO",
    "name:und_x_variant":[
        "Hornet",
        "Horn"
    ],
    "wof:name":"Horn",
    "wof:placetype":"locality"
},
  "geometry": {"coordinates":[5.65,61.91667],"type":"Point"}
}