{
  "type": "Feature",
  "properties": {
    "gn:admin1_code":"5.0",
    "gn:admin2_code":"2027.0",
    "gn:asciiname":"Bunes",
    "gn:country_code":"NO",
    "gn:dem":-9999,
    "gn:feature_class":"P",
    "gn:feature_code":"PPL",
    "gn:name":"Bunes",
    "gn:population":0,
    "gn:timezone":"Europe/Oslo",
    "iso:country":"NO",
    "name:nor_x_preferred":[
        "Bunes"
    ],
    "name:sme_x_preferred":[
        "Fuoiknj\u00e1rga"
    ],
    "wof:name":"Bunes",
    "wof:placetype":"locality"
},
  "geometry": {"coordinates":[28.75596,70.17045999999999],"type":"Point"}
}