{
  "type": "Feature",
  "properties": {
    "gn:gn_country":"NO",
    "gn:gn_fcode":"PPL",
    "gn:gn_pop":0,
    "iso:country":"NO",
    "name:dut_x_preferred":[
        "Spikkestad"
    ],
    "name:eng_x_preferred":[
        "Spikkestad"
    ],
    "name:fre_x_preferred":[
        "Spikkestad"
    ],
    "name:jav_x_preferred":[
        "Spikkestad"
    ],
    "name:may_x_preferred":[
        "Spikkestad"
    ],
    "name:nno_x_preferred":[
        "Spikkestad"
    ],
    "name:nob_x_preferred":[
        "Spikkestad"
    ],
    "name:swe_x_preferred":[
        "Spikkestad"
    ],
    "qs_pg:aaroncc":"NO",
    "qs_pg:gn_country":"NO",
    "qs_pg:gn_fcode":"PPL",
    "qs_pg:gn_pop":0,
    "qs_pg:name":"Spikkestad",
    "qs_pg:name_adm0":"Norge",
    "qs_pg:name_adm1":"Buskerud Fylke",
    "qs_pg:photos":27,
    "qs_pg:photos_1k":5,
    "qs_pg:photos_9k":1,
    "qs_pg:photos_9r":2,
    "qs_pg:photos_all":27,
    "qs_pg:photos_sr":2,
    "qs_pg:pop_sr":0,
    "qs_pg:qs_pg_placetype":"locality",
    "qs_pg:qs_pg_placetype_gp":"Town",
    "qs_pg:woe_adm0":23424910,
    "woe:adm0_id":23424910,
    "woe:name_adm0":"Norge",
    "woe:name_adm1":"Buskerud Fylke",
    "woe:placetype":"Town",
    "wof:name":"Spikkestad",
    "wof:placetype":"locality"
},
  "geometry": {"coordinates":[10.34011,59.74256],"type":"Point"}
}