{
  "type": "Feature",
  "properties": {
    "gn:admin1_code":"6.0",
    "gn:admin2_code":"415.0",
    "gn:asciiname":"Narsaetra",
    "gn:country_code":"NO",
    "gn:dem":447,
    "gn:feature_class":"P",
    "gn:feature_code":"PPL",
    "gn:name":"Nars\u00e6tra",
    "gn:population":0,
    "gn:timezone":"Europe/Oslo",
    "iso:country":"NO",
    "name:nor_x_preferred":[
        "Nars\u00e6tra"
    ],
    "wof:name":"Narsaetra",
    "wof:placetype":"locality"
},
  "geometry": {"coordinates":[11.40421,60.92039000000001],"type":"Point"}
}