{
  "type": "Feature",
  "properties": {
    "gn:admin1_code":"7.0",
    "gn:admin2_code":"1235.0",
    "gn:asciiname":"Rjoo",
    "gn:country_code":"NO",
    "gn:dem":605,
    "gn:feature_class":"P",
    "gn:feature_code":"PPL",
    "gn:name":"Rjoo",
    "gn:population":0,
    "gn:timezone":"Europe/Oslo",
    "iso:country":"NO",
    "wof:name":"Rjoo",
    "wof:placetype":"locality"
},
  "geometry": {"coordinates":[6.46667,60.56667],"type":"Point"}
}