{
  "type": "Feature",
  "properties": {
    "gn:admin1_code":"7",
    "gn:admin2_code":"1263.0",
    "gn:asciiname":"Hilland",
    "gn:country_code":"NO",
    "gn:dem":3,
    "gn:feature_class":"P",
    "gn:feature_code":"PPLL",
    "gn:name":"Hilland",
    "gn:population":0,
    "gn:timezone":"Europe/Oslo",
    "iso:country":"NO",
    "wof:name":"Hilland",
    "wof:placetype":"neighbourhood"
},
  "geometry": {"coordinates":[5.22,60.575],"type":"Point"}
}