{
  "type": "Feature",
  "properties": {
    "gn:admin1_code":"21",
    "gn:admin2_code":"5044.0",
    "gn:asciiname":"Flatadal",
    "gn:cc2":"NO",
    "gn:country_code":"NO",
    "gn:dem":220,
    "gn:feature_class":"P",
    "gn:feature_code":"PPL",
    "gn:name":"Fl\u00e5t\u00e5dal",
    "gn:population":0,
    "gn:timezone":"Europe/Oslo",
    "iso:country":"NO",
    "name:und_x_variant":[
        "Trongfoss",
        "Fl\u00e5t\u00e5dal"
    ],
    "wof:name":"Flatadal",
    "wof:placetype":"locality"
},
  "geometry": {"coordinates":[12.88333,64.76666999999999],"type":"Point"}
}