{
  "type": "Feature",
  "properties": {
    "iso:country":"NO",
    "name:bar_x_preferred":[
        "Overhalla"
    ],
    "name:bpy_x_preferred":[
        "\u0993\u09ad\u09c7\u09b0\u09b9\u09be\u09b2\u09cd\u09b2\u09be"
    ],
    "name:bul_x_preferred":[
        "\u041e\u0432\u0435\u0440\u0445\u0430\u043b\u0430"
    ],
    "name:cat_x_preferred":[
        "Overhalla"
    ],
    "name:dan_x_preferred":[
        "Overhalla"
    ],
    "name:deu_x_preferred":[
        "Overhalla"
    ],
    "name:eng_x_preferred":[
        "Overhalla"
    ],
    "name:epo_x_preferred":[
        "Overhalla"
    ],
    "name:eus_x_preferred":[
        "Overhalla"
    ],
    "name:fin_x_preferred":[
        "Overhalla"
    ],
    "name:fra_x_preferred":[
        "Overhalla"
    ],
    "name:ita_x_preferred":[
        "Overhalla"
    ],
    "name:jav_x_preferred":[
        "Overhalla"
    ],
    "name:lat_x_preferred":[
        "Overhalla"
    ],
    "name:lim_x_preferred":[
        "Overhalla"
    ],
    "name:msa_x_preferred":[
        "Overhalla"
    ],
    "name:nan_x_preferred":[
        "Overhalla"
    ],
    "name:nds_x_preferred":[
        "Kommun Overhalla"
    ],
    "name:nld_x_preferred":[
        "Overhalla"
    ],
    "name:nno_x_preferred":[
        "Overhalla"
    ],
    "name:nob_x_preferred":[
        "Overhalla"
    ],
    "name:pol_x_preferred":[
        "Overhalla"
    ],
    "name:por_x_preferred":[
        "Overhalla"
    ],
    "name:ron_x_preferred":[
        "Overhalla"
    ],
    "name:rus_x_preferred":[
        "\u0423\u0432\u0435\u0440\u0445\u0430\u043b\u043b\u0430"
    ],
    "name:slv_x_preferred":[
        "Overhalla"
    ],
    "name:sme_x_preferred":[
        "Overhalla"
    ],
    "name:spa_x_preferred":[
        "Overhalla"
    ],
    "name:sqi_x_preferred":[
        "Overhalla"
    ],
    "name:swa_x_preferred":[
        "Overhalla"
    ],
    "name:swe_x_preferred":[
        "Overhalla"
    ],
    "name:vie_x_preferred":[
        "Overhalla"
    ],
    "name:war_x_preferred":[
        "Overhalla"
    ],
    "name:zho_x_preferred":[
        "\u5967\u6c83\u723e\u54c8\u62c9"
    ],
    "qs_pg:aaroncc":"NO",
    "qs_pg:name":"Overhalla",
    "qs_pg:name_adm0":"Norge",
    "qs_pg:name_adm1":"Nord-Tr\u00f8ndelag Fylke",
    "qs_pg:photos":32,
    "qs_pg:photos_1k":6,
    "qs_pg:photos_9k":1,
    "qs_pg:photos_9r":2,
    "qs_pg:photos_all":32,
    "qs_pg:photos_sr":2,
    "qs_pg:pop_sr":0,
    "qs_pg:qs_pg_placetype":"locality",
    "qs_pg:qs_pg_placetype_gp":"Town",
    "qs_pg:woe_adm0":23424910,
    "woe:adm0_id":23424910,
    "woe:name_adm0":"Norge",
    "woe:name_adm1":"Nord-Tr\u00f8ndelag Fylke",
    "woe:placetype":"Town",
    "wof:name":"Overhalla",
    "wof:placetype":"locality"
},
  "geometry": {"coordinates":[11.931594,64.48437300000001],"type":"Point"}
}