{
  "type": "Feature",
  "properties": {
    "gn:admin1_code":"5.0",
    "gn:admin2_code":"2019.0",
    "gn:asciiname":"Kamoyvaer",
    "gn:cc2":"NO",
    "gn:country_code":"NO",
    "gn:dem":40,
    "gn:feature_class":"P",
    "gn:feature_code":"PPL",
    "gn:name":"Kam\u00f8yv\u00e6r",
    "gn:population":0,
    "gn:timezone":"Europe/Oslo",
    "iso:country":"NO",
    "name:deu_x_preferred":[
        "Kam\u00f8yv\u00e6r"
    ],
    "name:eng_x_preferred":[
        "Kam\u00f8yv\u00e6r"
    ],
    "name:fra_x_preferred":[
        "Kam\u00f8yv\u00e6r"
    ],
    "name:jav_x_preferred":[
        "Kam\u00f8yv\u00e6r"
    ],
    "name:msa_x_preferred":[
        "Kam\u00f8yv\u00e6r"
    ],
    "name:nno_x_preferred":[
        "Kam\u00f8yv\u00e6r"
    ],
    "name:nor_x_preferred":[
        "Kam\u00f8yv\u00e6r"
    ],
    "name:rus_x_preferred":[
        "\u041a\u0430\u043c\u0435\u0439\u0432\u0435\u0440"
    ],
    "name:und_x_variant":[
        "Kam\u00f6yver",
        "Kam\u00f6v\u00e6r"
    ],
    "wof:name":"Kamoyvaer",
    "wof:placetype":"locality"
},
  "geometry": {"coordinates":[25.90541,71.04866],"type":"Point"}
}