{
  "type": "Feature",
  "properties": {
    "gn:admin1_code":"7",
    "gn:admin2_code":"1256.0",
    "gn:asciiname":"Vikane",
    "gn:country_code":"NO",
    "gn:dem":30,
    "gn:feature_class":"P",
    "gn:feature_code":"PPLL",
    "gn:name":"Vikane",
    "gn:population":0,
    "gn:timezone":"Europe/Oslo",
    "iso:country":"NO",
    "wof:name":"Vikane",
    "wof:placetype":"locality"
},
  "geometry": {"coordinates":[5.22949,60.51197],"type":"Point"}
}