{
  "type": "Feature",
  "properties": {
    "gn:admin1_code":"5.0",
    "gn:admin2_code":"2030.0",
    "gn:asciiname":"Hakokoski",
    "gn:cc2":"NO",
    "gn:country_code":"NO",
    "gn:dem":40,
    "gn:feature_class":"P",
    "gn:feature_code":"PPL",
    "gn:name":"Hakokoski",
    "gn:population":0,
    "gn:timezone":"Europe/Oslo",
    "iso:country":"NO",
    "name:fkv_x_preferred":[
        "Hakokoski"
    ],
    "name:nor_x_preferred":[
        "Skogfoss"
    ],
    "name:und_x_variant":[
        "Skogvokterboli",
        "Skogfoss"
    ],
    "wof:name":"Hakokoski",
    "wof:placetype":"locality"
},
  "geometry": {"coordinates":[29.6935,69.37439000000001],"type":"Point"}
}