{
  "type": "Feature",
  "properties": {
    "gn:country":"NO",
    "gn:fcode":"PPL",
    "gn:population":306,
    "iso:country":"NO",
    "name:ceb_x_preferred":[
        "Ersfjord"
    ],
    "name:eng_x_preferred":[
        "Ersfjordbotn"
    ],
    "name:fra_x_preferred":[
        "Ersfjordbotn"
    ],
    "name:msa_x_preferred":[
        "Ersfjordbotn"
    ],
    "name:nld_x_preferred":[
        "Ersfjordbotn"
    ],
    "name:nno_x_preferred":[
        "Ersfjordbotn"
    ],
    "name:nob_x_preferred":[
        "Ersfjordbotn"
    ],
    "name:nor_x_preferred":[
        "Ersfjord"
    ],
    "name:nor_x_variant":[
        "Ersfjordbotn"
    ],
    "name:ron_x_preferred":[
        "Ersfjordbotn"
    ],
    "name:spa_x_preferred":[
        "Ersfjordbotn"
    ],
    "name:swe_x_preferred":[
        "Ersfjordbotn"
    ],
    "qs_pg:aaroncc":"NO",
    "qs_pg:gn_country":"NO",
    "qs_pg:gn_fcode":"PPL",
    "qs_pg:gn_pop":306,
    "qs_pg:name":"Ersfjordbotn",
    "qs_pg:name_adm0":"Norge",
    "qs_pg:name_adm1":"Troms Fylke",
    "qs_pg:photos":782,
    "qs_pg:photos_1k":158,
    "qs_pg:photos_9k":3,
    "qs_pg:photos_9r":6,
    "qs_pg:photos_all":782,
    "qs_pg:photos_sr":9,
    "qs_pg:pop_sr":2,
    "qs_pg:qs_pg_placetype":"locality",
    "qs_pg:qs_pg_placetype_gp":"Town",
    "qs_pg:woe_adm0":23424910,
    "woe:adm0_id":23424910,
    "woe:name_adm0":"Norge",
    "woe:name_adm1":"Troms Fylke",
    "woe:placetype":"Town",
    "wof:name":"Ersfjordbotn",
    "wof:placetype":"locality",
    "wof:population":306
},
  "geometry": {"coordinates":[18.61833,69.69194],"type":"Point"}
}