{
  "type": "Feature",
  "properties": {
    "gn:admin1_code":"17.0",
    "gn:admin2_code":"828.0",
    "gn:asciiname":"Kivlegrendi",
    "gn:country_code":"NO",
    "gn:dem":441,
    "gn:feature_class":"P",
    "gn:feature_code":"PPL",
    "gn:name":"Kivlegrendi",
    "gn:population":0,
    "gn:timezone":"Europe/Oslo",
    "iso:country":"NO",
    "name:nor_x_preferred":[
        "Kivlegrendi"
    ],
    "wof:name":"Kivlegrendi",
    "wof:placetype":"locality"
},
  "geometry": {"coordinates":[8.58738,59.50322],"type":"Point"}
}