{
  "type": "Feature",
  "properties": {
    "gn:admin1_code":"8.0",
    "gn:admin2_code":"1576.0",
    "gn:asciiname":"Todalen",
    "gn:country_code":"NO",
    "gn:dem":20,
    "gn:feature_class":"P",
    "gn:feature_code":"PPL",
    "gn:name":"Todalen",
    "gn:population":0,
    "gn:timezone":"Europe/Oslo",
    "iso:country":"NO",
    "name:jav_x_preferred":[
        "Todalen"
    ],
    "name:msa_x_preferred":[
        "Todalen"
    ],
    "name:nor_x_preferred":[
        "Todalen"
    ],
    "name:nor_x_variant":[
        "Todal"
    ],
    "wof:name":"Todalen",
    "wof:placetype":"locality"
},
  "geometry": {"coordinates":[8.68752,63.2008],"type":"Point"}
}