{
  "type": "Feature",
  "properties": {
    "gn:admin1_code":"18",
    "gn:admin2_code":"1931",
    "gn:asciiname":"Lysnes",
    "gn:country_code":"NO",
    "gn:dem":-9999,
    "gn:feature_class":"P",
    "gn:feature_code":"PPLL",
    "gn:name":"Lysnes",
    "gn:population":0,
    "gn:timezone":"Europe/Oslo",
    "iso:country":"NO",
    "name:nor_x_preferred":[
        "Lysnes"
    ],
    "wof:name":"Lysnes",
    "wof:placetype":"locality"
},
  "geometry": {"coordinates":[17.96171,69.43199],"type":"Point"}
}