{
  "type": "Feature",
  "properties": {
    "gn:admin1_code":"9.0",
    "gn:admin2_code":"1833.0",
    "gn:asciiname":"Yttralenninga",
    "gn:country_code":"NO",
    "gn:dem":120,
    "gn:feature_class":"P",
    "gn:feature_code":"PPL",
    "gn:name":"Yttralenninga",
    "gn:population":0,
    "gn:timezone":"Europe/Oslo",
    "iso:country":"NO",
    "name:nor_x_preferred":[
        "Yttralenninga"
    ],
    "name:nor_x_variant":[
        "Ytterlendinga"
    ],
    "wof:name":"Yttralenninga",
    "wof:placetype":"locality"
},
  "geometry": {"coordinates":[14.12508,66.36454000000001],"type":"Point"}
}