{
  "type": "Feature",
  "properties": {
    "gn:admin1_code":"7",
    "gn:admin2_code":"1234.0",
    "gn:asciiname":"Kjerland",
    "gn:country_code":"NO",
    "gn:dem":588,
    "gn:feature_class":"P",
    "gn:feature_code":"PPL",
    "gn:name":"Kjerland",
    "gn:population":0,
    "gn:timezone":"Europe/Oslo",
    "iso:country":"NO",
    "wof:name":"Kjerland",
    "wof:placetype":"locality"
},
  "geometry": {"coordinates":[6.75,60.53333000000001],"type":"Point"}
}