{
  "type": "Feature",
  "properties": {
    "gn:admin1_code":"7",
    "gn:admin2_code":"1201",
    "gn:asciiname":"Elvenes",
    "gn:country_code":"NO",
    "gn:dem":70,
    "gn:feature_class":"P",
    "gn:feature_code":"PPLL",
    "gn:name":"Elvenes",
    "gn:population":0,
    "gn:timezone":"Europe/Oslo",
    "iso:country":"NO",
    "name:ceb_x_preferred":[
        "Elvenes"
    ],
    "name:deu_x_preferred":[
        "Elvenes"
    ],
    "name:nor_x_preferred":[
        "Elvenes"
    ],
    "wof:name":"Elvenes",
    "wof:placetype":"neighbourhood"
},
  "geometry": {"coordinates":[5.37037,60.30938],"type":"Point"}
}