{
  "type": "Feature",
  "properties": {
    "iso:country":"NO",
    "qs_pg:aaroncc":"NO",
    "qs_pg:name":"Brensholmen",
    "qs_pg:name_adm0":"Norge",
    "qs_pg:name_adm1":"Troms Fylke",
    "qs_pg:photos":263,
    "qs_pg:photos_1k":53,
    "qs_pg:photos_9k":1,
    "qs_pg:photos_9r":4,
    "qs_pg:photos_all":263,
    "qs_pg:photos_sr":5,
    "qs_pg:pop_sr":0,
    "qs_pg:qs_pg_placetype":"locality",
    "qs_pg:qs_pg_placetype_gp":"Town",
    "qs_pg:woe_adm0":23424910,
    "woe:adm0_id":23424910,
    "woe:name_adm0":"Norge",
    "woe:name_adm1":"Troms Fylke",
    "woe:placetype":"Town",
    "wof:name":"Brensholmen",
    "wof:placetype":"locality"
},
  "geometry": {"coordinates":[18.053154,69.60905200000001],"type":"Point"}
}