{
  "type": "Feature",
  "properties": {
    "gn:admin1_code":"7.0",
    "gn:admin2_code":"1235.0",
    "gn:asciiname":"Sakhaug",
    "gn:country_code":"NO",
    "gn:dem":346,
    "gn:feature_class":"P",
    "gn:feature_code":"PPL",
    "gn:name":"Sakhaug",
    "gn:population":0,
    "gn:timezone":"Europe/Oslo",
    "iso:country":"NO",
    "wof:name":"Sakhaug",
    "wof:placetype":"locality"
},
  "geometry": {"coordinates":[6.18333,60.63333000000001],"type":"Point"}
}