{
  "type": "Feature",
  "properties": {
    "gn:admin1_code":"7",
    "gn:admin2_code":"1238.0",
    "gn:asciiname":"Mo",
    "gn:country_code":"NO",
    "gn:dem":20,
    "gn:feature_class":"P",
    "gn:feature_code":"PPL",
    "gn:name":"Mo",
    "gn:population":0,
    "gn:timezone":"Europe/Oslo",
    "iso:country":"NO",
    "name:bar_x_preferred":[
        "Mo"
    ],
    "name:hun_x_preferred":[
        "Mo"
    ],
    "name:ind_x_preferred":[
        "Mo"
    ],
    "name:rus_x_preferred":[
        "Mo"
    ],
    "wof:name":"Mo",
    "wof:placetype":"locality"
},
  "geometry": {"coordinates":[6.13333,60.36666999999999],"type":"Point"}
}