{
  "type": "Feature",
  "properties": {
    "gn:admin1_code":"20",
    "gn:admin2_code":"729.0",
    "gn:asciiname":"Torkopp",
    "gn:cc2":"NO",
    "gn:country_code":"NO",
    "gn:dem":43,
    "gn:feature_class":"P",
    "gn:feature_code":"PPL",
    "gn:name":"T\u00f8rkopp",
    "gn:population":0,
    "gn:timezone":"Europe/Oslo",
    "iso:country":"NO",
    "name:und_x_variant":[
        "Torkop",
        "T\u00f8rkopp"
    ],
    "wof:name":"Torkopp",
    "wof:placetype":"locality"
},
  "geometry": {"coordinates":[10.39306,59.24528000000001],"type":"Point"}
}