{
  "type": "Feature",
  "properties": {
    "gn:admin1_code":"6.0",
    "gn:admin2_code":"428.0",
    "gn:asciiname":"Bjornbergsaetra",
    "gn:country_code":"NO",
    "gn:dem":620,
    "gn:feature_class":"P",
    "gn:feature_code":"PPL",
    "gn:name":"Bj\u00f8rnbergs\u00e6tra",
    "gn:population":0,
    "gn:timezone":"Europe/Oslo",
    "iso:country":"NO",
    "name:nor_x_preferred":[
        "Bj\u00f8rnbergs\u00e6tra"
    ],
    "name:nor_x_variant":[
        "Bj\u00f8rnbergss\u00e6tra"
    ],
    "wof:name":"Bjornbergsaetra",
    "wof:placetype":"locality"
},
  "geometry": {"coordinates":[12.66845,61.3465],"type":"Point"}
}