{
  "type": "Feature",
  "properties": {
    "gn:country":"NO",
    "iso:country":"NO",
    "name:ceb_x_preferred":[
        "Kloster"
    ],
    "name:dan_x_preferred":[
        "Kloster"
    ],
    "name:deu_x_preferred":[
        "Kloster"
    ],
    "name:ita_x_preferred":[
        "Kloster"
    ],
    "name:nld_x_preferred":[
        "Kloster"
    ],
    "name:pol_x_preferred":[
        "Kloster"
    ],
    "name:swe_x_preferred":[
        "Kloster"
    ],
    "qs_pg:aaroncc":"NO",
    "qs_pg:gn_country":"NO",
    "qs_pg:name":"Kloster",
    "qs_pg:name_adm0":"Norge",
    "qs_pg:name_adm1":"Hordaland Fylke",
    "qs_pg:photos":61,
    "qs_pg:photos_1k":12,
    "qs_pg:photos_9k":1,
    "qs_pg:photos_9r":2,
    "qs_pg:photos_all":61,
    "qs_pg:photos_sr":2,
    "qs_pg:pop_sr":0,
    "qs_pg:qs_pg_placetype":"locality",
    "qs_pg:qs_pg_placetype_gp":"Town",
    "qs_pg:woe_adm0":23424910,
    "woe:adm0_id":23424910,
    "woe:name_adm0":"Norge",
    "woe:name_adm1":"Hordaland Fylke",
    "woe:placetype":"Town",
    "wof:name":"Kloster",
    "wof:placetype":"locality"
},
  "geometry": {"coordinates":[5.654954,59.797369],"type":"Point"}
}