{
  "type": "Feature",
  "properties": {
    "gn:admin1_code":"14.0",
    "gn:admin2_code":"1133.0",
    "gn:asciiname":"Valheim",
    "gn:country_code":"NO",
    "gn:dem":156,
    "gn:feature_class":"P",
    "gn:feature_code":"PPL",
    "gn:name":"Valheim",
    "gn:population":0,
    "gn:timezone":"Europe/Oslo",
    "iso:country":"NO",
    "wof:name":"Valheim",
    "wof:placetype":"locality"
},
  "geometry": {"coordinates":[6.25,59.15],"type":"Point"}
}