{
  "type": "Feature",
  "properties": {
    "gn:admin1_code":"17",
    "gn:admin2_code":"814",
    "gn:asciiname":"Bratten",
    "gn:country_code":"NO",
    "gn:dem":54,
    "gn:feature_class":"P",
    "gn:feature_code":"PPLL",
    "gn:name":"Bratten",
    "gn:population":0,
    "gn:timezone":"Europe/Oslo",
    "iso:country":"NO",
    "name:nor_x_preferred":[
        "Bratten"
    ],
    "wof:name":"Bratten",
    "wof:placetype":"locality"
},
  "geometry": {"coordinates":[9.73929,59.00869],"type":"Point"}
}