{
  "type": "Feature",
  "properties": {
    "gn:admin1_code":"4.0",
    "gn:admin2_code":"620.0",
    "gn:asciiname":"Magnhildoyne",
    "gn:country_code":"NO",
    "gn:dem":735,
    "gn:feature_class":"P",
    "gn:feature_code":"PPL",
    "gn:name":"Magnhild\u00f8yne",
    "gn:population":0,
    "gn:timezone":"Europe/Oslo",
    "iso:country":"NO",
    "name:nor_x_preferred":[
        "Magnhild\u00f8yne"
    ],
    "wof:name":"Magnhildoyne",
    "wof:placetype":"locality"
},
  "geometry": {"coordinates":[8.24186,60.5443],"type":"Point"}
}