{
  "type": "Feature",
  "properties": {
    "gn:admin1_code":"19.0",
    "gn:admin2_code":"1002.0",
    "gn:asciiname":"Rodland",
    "gn:country_code":"NO",
    "gn:dem":88,
    "gn:feature_class":"P",
    "gn:feature_code":"PPL",
    "gn:name":"R\u00f8dland",
    "gn:population":0,
    "gn:timezone":"Europe/Oslo",
    "iso:country":"NO",
    "wof:name":"Rodland",
    "wof:placetype":"locality"
},
  "geometry": {"coordinates":[7.38333,58.05],"type":"Point"}
}