{
  "type": "Feature",
  "properties": {
    "gn:admin1_code":"7",
    "gn:admin2_code":"1246.0",
    "gn:asciiname":"Nord Bjoroy",
    "gn:country_code":"NO",
    "gn:dem":3,
    "gn:feature_class":"P",
    "gn:feature_code":"PPL",
    "gn:name":"Nord Bj\u00f8r\u00f8y",
    "gn:population":0,
    "gn:timezone":"Europe/Oslo",
    "iso:country":"NO",
    "wof:name":"Nord Bjoroy",
    "wof:placetype":"locality"
},
  "geometry": {"coordinates":[5.18333,60.31667],"type":"Point"}
}