{
  "type": "Feature",
  "properties": {
    "gn:admin1_code":"9",
    "gn:admin2_code":"1804.0",
    "gn:asciiname":"Kjoltan",
    "gn:country_code":"NO",
    "gn:dem":195,
    "gn:feature_class":"P",
    "gn:feature_code":"PPL",
    "gn:name":"Kjoltan",
    "gn:population":0,
    "gn:timezone":"Europe/Oslo",
    "iso:country":"NO",
    "wof:name":"Kjoltan",
    "wof:placetype":"locality"
},
  "geometry": {"coordinates":[14.98333,67.05],"type":"Point"}
}