{
  "type": "Feature",
  "properties": {
    "iso:country":"NO",
    "name:arz_x_preferred":[
        "\u0645\u0637\u0627\u0631 \u0644\u0627\u0643\u0633\u064a\u0644\u0641"
    ],
    "name:ceb_x_preferred":[
        "Lakselv Banak Airport"
    ],
    "name:dan_x_preferred":[
        "Lakselv Lufthavn"
    ],
    "name:deu_x_preferred":[
        "Flughafen Lakselv"
    ],
    "name:eng_x_preferred":[
        "Lakselv Airport"
    ],
    "name:eng_x_variant":[
        "LKL",
        "ENNA"
    ],
    "name:fas_x_preferred":[
        "\u0641\u0631\u0648\u062f\u06af\u0627\u0647 \u0644\u06a9\u0633\u0644\u0648 \u0628\u0627\u0646\u0627\u06a9"
    ],
    "name:fin_x_preferred":[
        "Lemmijoen lentoasema"
    ],
    "name:hun_x_preferred":[
        "Lakselvi rep\u00fcl\u0151t\u00e9r"
    ],
    "name:jpn_x_preferred":[
        "\u30e9\u30af\u30b9\u30a8\u30eb\u30d6\u7a7a\u6e2f"
    ],
    "name:msa_x_preferred":[
        "Lapangan Terbang Banak"
    ],
    "name:nld_x_preferred":[
        "Luchthaven Lakselv Banak"
    ],
    "name:nno_x_preferred":[
        "Lakselv lufthamn"
    ],
    "name:nob_x_preferred":[
        "Lakselv lufthavn"
    ],
    "name:nor_x_preferred":[
        "Lakselv lufthavn"
    ],
    "name:pol_x_preferred":[
        "Port lotniczy Lakselv"
    ],
    "name:spa_x_preferred":[
        "Aeropuerto de Lakselv-Banak"
    ],
    "name:swe_x_preferred":[
        "Lakselvs flygplats"
    ],
    "name:swe_x_variant":[
        "Lakselv flygplats"
    ],
    "name:tgk_x_preferred":[
        "\u0424\u0443\u0440\u0443\u0434\u0433\u043e\u04b3\u0438 \u043b\u043a\u0441\u043b\u0443 \u0431\u043e\u043d\u043e\u043a"
    ],
    "name:ukr_x_preferred":[
        "\u041b\u0430\u043a\u0441\u0435\u043b\u044c\u0432"
    ],
    "name:vie_x_preferred":[
        "S\u00e2n bay Lakselv"
    ],
    "oa:elevation_ft":"25",
    "oa:type":"medium_airport",
    "wd:wordcount":2548,
    "woe:hierarchy":{
        "country_id":23424910,
        "county_id":12592907,
        "planet_id":1,
        "state_id":2346388
    },
    "wof:name":"Lakselv Lufthavn Banak",
    "wof:placetype":"campus"
},
  "geometry": {"coordinates":[24.973889,70.066667],"type":"Point"}
}