{
  "type": "Feature",
  "properties": {
    "gn:admin1_code":"18",
    "gn:admin2_code":"1928.0",
    "gn:asciiname":"Ballesvika",
    "gn:country_code":"NO",
    "gn:dem":19,
    "gn:feature_class":"P",
    "gn:feature_code":"PPL",
    "gn:name":"Ballesvika",
    "gn:population":0,
    "gn:timezone":"Europe/Oslo",
    "iso:country":"NO",
    "wof:name":"Ballesvika",
    "wof:placetype":"locality"
},
  "geometry": {"coordinates":[17.11204,69.38195999999999],"type":"Point"}
}