{
  "type": "Feature",
  "properties": {
    "gn:admin1_code":"5.0",
    "gn:admin2_code":"2017.0",
    "gn:asciiname":"Oldervik",
    "gn:country_code":"NO",
    "gn:dem":60,
    "gn:feature_class":"P",
    "gn:feature_code":"PPL",
    "gn:name":"Oldervik",
    "gn:population":0,
    "gn:timezone":"Europe/Oslo",
    "iso:country":"NO",
    "name:nor_x_preferred":[
        "Oldervik"
    ],
    "wof:name":"Oldervik",
    "wof:placetype":"locality"
},
  "geometry": {"coordinates":[24.17606,70.52555],"type":"Point"}
}