{
  "type": "Feature",
  "properties": {
    "gn:admin1_code":"9",
    "gn:admin2_code":"1834",
    "gn:asciiname":"Sleneset",
    "gn:country_code":"NO",
    "gn:dem":-9999,
    "gn:feature_class":"P",
    "gn:feature_code":"PPLL",
    "gn:name":"Sleneset",
    "gn:population":0,
    "gn:timezone":"Europe/Oslo",
    "iso:country":"NO",
    "name:nor_x_preferred":[
        "Sleneset"
    ],
    "wof:name":"Sleneset",
    "wof:placetype":"locality"
},
  "geometry": {"coordinates":[12.60831,66.36365000000001],"type":"Point"}
}