{
  "type": "Feature",
  "properties": {
    "gn:admin1_code":"21",
    "gn:admin2_code":"5014.0",
    "gn:asciiname":"Bremneset",
    "gn:country_code":"NO",
    "gn:dem":20,
    "gn:feature_class":"P",
    "gn:feature_code":"PPL",
    "gn:name":"Bremneset",
    "gn:population":0,
    "gn:timezone":"Europe/Oslo",
    "iso:country":"NO",
    "name:nor_x_preferred":[
        "Bremneset"
    ],
    "name:nor_x_variant":[
        "Bremnes"
    ],
    "wof:name":"Bremneset",
    "wof:placetype":"locality"
},
  "geometry": {"coordinates":[8.64222,63.74034],"type":"Point"}
}