{
  "type": "Feature",
  "properties": {
    "gn:admin1_code":"19.0",
    "gn:admin2_code":"1018.0",
    "gn:asciiname":"Stolen",
    "gn:country_code":"NO",
    "gn:dem":9,
    "gn:feature_class":"P",
    "gn:feature_code":"PPL",
    "gn:name":"St\u00f8len",
    "gn:population":0,
    "gn:timezone":"Europe/Oslo",
    "iso:country":"NO",
    "name:ceb_x_preferred":[
        "Stolen"
    ],
    "name:deu_x_preferred":[
        "Stolen"
    ],
    "name:ita_x_preferred":[
        "Stolen"
    ],
    "name:nld_x_preferred":[
        "Stolen"
    ],
    "name:nor_x_preferred":[
        "St\u00f8len"
    ],
    "name:swe_x_preferred":[
        "Stolen"
    ],
    "name:tur_x_preferred":[
        "Stolen"
    ],
    "wof:name":"Stolen",
    "wof:placetype":"locality"
},
  "geometry": {"coordinates":[7.75188,58.07294],"type":"Point"}
}