{
  "type": "Feature",
  "properties": {
    "gn:admin1_code":"18.0",
    "gn:admin2_code":"1943.0",
    "gn:asciiname":"Burfjord",
    "gn:country_code":"NO",
    "gn:dem":119,
    "gn:feature_class":"P",
    "gn:feature_code":"PPLA2",
    "gn:name":"Burfjord",
    "gn:population":0,
    "gn:timezone":"Europe/Oslo",
    "iso:country":"NO",
    "name:ceb_x_preferred":[
        "Burfjord"
    ],
    "name:dan_x_preferred":[
        "Burfjord"
    ],
    "name:fra_x_preferred":[
        "Burfjord"
    ],
    "name:ita_x_preferred":[
        "Burfjord"
    ],
    "name:msa_x_preferred":[
        "Burfjord"
    ],
    "name:nno_x_preferred":[
        "Burfjord"
    ],
    "name:nor_x_preferred":[
        "Burfjord"
    ],
    "name:sme_x_preferred":[
        "Buvrovuotna"
    ],
    "name:spa_x_preferred":[
        "Burfjord"
    ],
    "wof:name":"Burfjord",
    "wof:placetype":"locality"
},
  "geometry": {"coordinates":[22.05205,69.93804],"type":"Point"}
}