{
  "type": "Feature",
  "properties": {
    "gn:admin1_code":"21.0",
    "gn:admin2_code":"5047.0",
    "gn:asciiname":"Vibstad",
    "gn:country_code":"NO",
    "gn:dem":40,
    "gn:feature_class":"P",
    "gn:feature_code":"PPL",
    "gn:name":"Vibstad",
    "gn:population":0,
    "gn:timezone":"Europe/Oslo",
    "iso:country":"NO",
    "name:nor_x_preferred":[
        "Vibstad"
    ],
    "wof:name":"Vibstad",
    "wof:placetype":"locality"
},
  "geometry": {"coordinates":[11.92715,64.47553000000001],"type":"Point"}
}