{
  "type": "Feature",
  "properties": {
    "gn:admin1_code":"6.0",
    "gn:admin2_code":"403.0",
    "gn:asciiname":"Storhamar",
    "gn:country_code":"NO",
    "gn:dem":123,
    "gn:feature_class":"P",
    "gn:feature_code":"PPL",
    "gn:name":"Storhamar",
    "gn:population":0,
    "gn:timezone":"Europe/Oslo",
    "iso:country":"NO",
    "name:nor_x_preferred":[
        "Storhamar"
    ],
    "wof:name":"Storhamar",
    "wof:placetype":"locality"
},
  "geometry": {"coordinates":[11.03333,60.78333000000001],"type":"Point"}
}