{
  "type": "Feature",
  "properties": {
    "gn:admin1_code":"21.0",
    "gn:admin2_code":"5011.0",
    "gn:asciiname":"Merkeneset",
    "gn:country_code":"NO",
    "gn:dem":10,
    "gn:feature_class":"P",
    "gn:feature_code":"PPL",
    "gn:name":"Merkeneset",
    "gn:population":0,
    "gn:timezone":"Europe/Oslo",
    "iso:country":"NO",
    "name:nor_x_preferred":[
        "Merkeneset"
    ],
    "wof:name":"Merkeneset",
    "wof:placetype":"locality"
},
  "geometry": {"coordinates":[9.11429,63.29232],"type":"Point"}
}