{
  "type": "Feature",
  "properties": {
    "gn:admin1_code":"7",
    "gn:admin2_code":"1260.0",
    "gn:asciiname":"Kvitstein",
    "gn:country_code":"NO",
    "gn:dem":160,
    "gn:feature_class":"P",
    "gn:feature_code":"PPL",
    "gn:name":"Kvitstein",
    "gn:population":0,
    "gn:timezone":"Europe/Oslo",
    "iso:country":"NO",
    "wof:name":"Kvitstein",
    "wof:placetype":"locality"
},
  "geometry": {"coordinates":[5.09667,60.60889],"type":"Point"}
}