{
  "type": "Feature",
  "properties": {
    "gn:admin1_code":"6.0",
    "gn:admin2_code":"415.0",
    "gn:asciiname":"Oysaetra",
    "gn:country_code":"NO",
    "gn:dem":563,
    "gn:feature_class":"P",
    "gn:feature_code":"PPL",
    "gn:name":"\u00d8ys\u00e6tra",
    "gn:population":0,
    "gn:timezone":"Europe/Oslo",
    "iso:country":"NO",
    "name:nor_x_preferred":[
        "\u00d8ys\u00e6tra"
    ],
    "wof:name":"Oysaetra",
    "wof:placetype":"locality"
},
  "geometry": {"coordinates":[11.32781,60.96726],"type":"Point"}
}