{
  "type": "Feature",
  "properties": {
    "gn:admin1_code":"14.0",
    "gn:admin2_code":"1141.0",
    "gn:asciiname":"Reilstad",
    "gn:country_code":"NO",
    "gn:dem":29,
    "gn:feature_class":"P",
    "gn:feature_code":"PPL",
    "gn:name":"Reilstad",
    "gn:population":0,
    "gn:timezone":"Europe/Oslo",
    "iso:country":"NO",
    "wof:name":"Reilstad",
    "wof:placetype":"locality"
},
  "geometry": {"coordinates":[5.83704,59.14749000000001],"type":"Point"}
}