{
  "type": "Feature",
  "properties": {
    "gn:admin1_code":"1",
    "gn:admin2_code":"238.0",
    "gn:asciiname":"Holtet",
    "gn:country_code":"NO",
    "gn:dem":250,
    "gn:feature_class":"P",
    "gn:feature_code":"PPL",
    "gn:name":"Holtet",
    "gn:population":0,
    "gn:timezone":"Europe/Oslo",
    "iso:country":"NO",
    "name:ceb_x_preferred":[
        "Holtet"
    ],
    "name:dan_x_preferred":[
        "Holtet"
    ],
    "name:deu_x_preferred":[
        "Holtet"
    ],
    "name:nor_x_preferred":[
        "Holtet"
    ],
    "name:swe_x_preferred":[
        "Vassbotten/Holtet"
    ],
    "wof:name":"Holtet",
    "wof:placetype":"locality"
},
  "geometry": {"coordinates":[11.03333,60.33333],"type":"Point"}
}