{
  "type": "Feature",
  "properties": {
    "gn:admin1_code":"18.0",
    "gn:admin2_code":"1926.0",
    "gn:asciiname":"Store Vinje",
    "gn:cc2":"NO",
    "gn:country_code":"NO",
    "gn:dem":183,
    "gn:feature_class":"P",
    "gn:feature_code":"PPL",
    "gn:name":"Store Vinje",
    "gn:population":0,
    "gn:timezone":"Europe/Oslo",
    "iso:country":"NO",
    "name:und_x_variant":[
        "Vinja",
        "Store Vinje"
    ],
    "wof:name":"Store Vinje",
    "wof:placetype":"locality"
},
  "geometry": {"coordinates":[17.38332999999999,69.01666999999999],"type":"Point"}
}