{
  "type": "Feature",
  "properties": {
    "gn:admin1_code":"4",
    "gn:admin2_code":"626",
    "gn:asciiname":"Hegg",
    "gn:country_code":"NO",
    "gn:dem":33,
    "gn:feature_class":"P",
    "gn:feature_code":"PPLL",
    "gn:name":"Hegg",
    "gn:population":0,
    "gn:timezone":"Europe/Oslo",
    "iso:country":"NO",
    "name:nor_x_preferred":[
        "Hegg"
    ],
    "name:nor_x_variant":[
        "Heggtoppen"
    ],
    "wof:name":"Hegg",
    "wof:placetype":"neighbourhood"
},
  "geometry": {"coordinates":[10.24304,59.78061999999999],"type":"Point"}
}