{
  "type": "Feature",
  "properties": {
    "gn:admin1_code":"9.0",
    "gn:admin2_code":"1870.0",
    "gn:asciiname":"Steiro",
    "gn:country_code":"NO",
    "gn:dem":7,
    "gn:feature_class":"P",
    "gn:feature_code":"PPL",
    "gn:name":"Steiro",
    "gn:population":0,
    "gn:timezone":"Europe/Oslo",
    "iso:country":"NO",
    "wof:name":"Steiro",
    "wof:placetype":"locality"
},
  "geometry": {"coordinates":[15.36335,68.66842],"type":"Point"}
}