{
  "type": "Feature",
  "properties": {
    "gn:admin1_code":"18.0",
    "gn:admin2_code":"1929.0",
    "gn:asciiname":"Nessan",
    "gn:country_code":"NO",
    "gn:dem":-9999,
    "gn:feature_class":"P",
    "gn:feature_code":"PPL",
    "gn:name":"Nessan",
    "gn:population":0,
    "gn:timezone":"Europe/Oslo",
    "iso:country":"NO",
    "name:nor_x_preferred":[
        "Nessan"
    ],
    "wof:name":"Nessan",
    "wof:placetype":"locality"
},
  "geometry": {"coordinates":[17.26405,69.41053000000001],"type":"Point"}
}