{
  "type": "Feature",
  "properties": {
    "gn:admin1_code":"6.0",
    "gn:admin2_code":"434.0",
    "gn:asciiname":"Elga",
    "gn:country_code":"NO",
    "gn:dem":700,
    "gn:feature_class":"P",
    "gn:feature_code":"PPL",
    "gn:name":"Elg\u00e0",
    "gn:population":0,
    "gn:timezone":"Europe/Oslo",
    "iso:country":"NO",
    "wof:name":"Elga",
    "wof:placetype":"locality"
},
  "geometry": {"coordinates":[11.9424,62.16721],"type":"Point"}
}