{
  "type": "Feature",
  "properties": {
    "gn:admin1_code":"9.0",
    "gn:admin2_code":"1804.0",
    "gn:asciiname":"Straum",
    "gn:cc2":"NO",
    "gn:country_code":"NO",
    "gn:dem":40,
    "gn:feature_class":"P",
    "gn:feature_code":"PPL",
    "gn:name":"Straum",
    "gn:population":0,
    "gn:timezone":"Europe/Oslo",
    "iso:country":"NO",
    "name:und_x_variant":[
        "Str\u00f6m",
        "Straum"
    ],
    "wof:name":"Straum",
    "wof:placetype":"locality"
},
  "geometry": {"coordinates":[14.58333,67.23333000000001],"type":"Point"}
}