{
  "type": "Feature",
  "properties": {
    "gn:admin1_code":"4",
    "gn:admin2_code":"633.0",
    "gn:asciiname":"Ljotegard",
    "gn:country_code":"NO",
    "gn:dem":768,
    "gn:feature_class":"P",
    "gn:feature_code":"PPL",
    "gn:name":"Ljotegard",
    "gn:population":0,
    "gn:timezone":"Europe/Oslo",
    "iso:country":"NO",
    "wof:name":"Ljotegard",
    "wof:placetype":"locality"
},
  "geometry": {"coordinates":[8.83333,60.26667],"type":"Point"}
}