{
  "type": "Feature",
  "properties": {
    "gn:admin1_code":"13",
    "gn:admin2_code":"119.0",
    "gn:asciiname":"Gaseby",
    "gn:cc2":"NO",
    "gn:country_code":"NO",
    "gn:dem":162,
    "gn:feature_class":"P",
    "gn:feature_code":"PPL",
    "gn:name":"G\u00e5seby",
    "gn:population":0,
    "gn:timezone":"Europe/Oslo",
    "iso:country":"NO",
    "name:und_x_variant":[
        "Gaaseby",
        "G\u00e5seby"
    ],
    "wof:name":"Gaseby",
    "wof:placetype":"locality"
},
  "geometry": {"coordinates":[11.63333,59.55],"type":"Point"}
}