{
  "type": "Feature",
  "properties": {
    "gn:admin1_code":"21",
    "gn:admin2_code":"5027.0",
    "gn:asciiname":"Kotsoy",
    "gn:country_code":"NO",
    "gn:dem":310,
    "gn:feature_class":"P",
    "gn:feature_code":"PPL",
    "gn:name":"Kots\u00f8y",
    "gn:population":0,
    "gn:timezone":"Europe/Oslo",
    "iso:country":"NO",
    "wof:name":"Kotsoy",
    "wof:placetype":"locality"
},
  "geometry": {"coordinates":[10.56268,62.97602],"type":"Point"}
}