{
  "type": "Feature",
  "properties": {
    "gn:admin1_code":"21",
    "gn:admin2_code":"5015.0",
    "gn:asciiname":"Beian",
    "gn:country_code":"NO",
    "gn:dem":-9999,
    "gn:feature_class":"P",
    "gn:feature_code":"PPL",
    "gn:name":"Beian",
    "gn:population":0,
    "gn:timezone":"Europe/Oslo",
    "iso:country":"NO",
    "wof:name":"Beian",
    "wof:placetype":"locality"
},
  "geometry": {"coordinates":[9.56953,63.65553000000001],"type":"Point"}
}