{
  "type": "Feature",
  "properties": {
    "gn:admin1_code":"4",
    "gn:admin2_code":"624.0",
    "gn:asciiname":"Grosland",
    "gn:country_code":"NO",
    "gn:dem":213,
    "gn:feature_class":"P",
    "gn:feature_code":"PPL",
    "gn:name":"Gr\u00f8sland",
    "gn:population":0,
    "gn:timezone":"Europe/Oslo",
    "iso:country":"NO",
    "wof:name":"Grosland",
    "wof:placetype":"locality"
},
  "geometry": {"coordinates":[9.81667,59.78333000000001],"type":"Point"}
}