{
  "type": "Feature",
  "properties": {
    "gn:admin1_code":"6",
    "gn:admin2_code":"438.0",
    "gn:asciiname":"Brandvalen",
    "gn:country_code":"NO",
    "gn:dem":800,
    "gn:feature_class":"P",
    "gn:feature_code":"PPL",
    "gn:name":"Brandv\u00e5len",
    "gn:population":0,
    "gn:timezone":"Europe/Oslo",
    "iso:country":"NO",
    "wof:name":"Brandvalen",
    "wof:placetype":"locality"
},
  "geometry": {"coordinates":[10.6251,62.16623000000001],"type":"Point"}
}