{
  "type": "Feature",
  "properties": {
    "gn:admin1_code":"2",
    "gn:admin2_code":"914.0",
    "gn:asciiname":"Skottevik",
    "gn:country_code":"NO",
    "gn:dem":-9999,
    "gn:feature_class":"P",
    "gn:feature_code":"PPL",
    "gn:name":"Skottevik",
    "gn:population":0,
    "gn:timezone":"Europe/Oslo",
    "iso:country":"NO",
    "wof:name":"Skottevik",
    "wof:placetype":"locality"
},
  "geometry": {"coordinates":[8.97139,58.58833000000001],"type":"Point"}
}