{
  "type": "Feature",
  "properties": {
    "gn:country":"NO",
    "iso:country":"NO",
    "qs_pg:aaroncc":"NO",
    "qs_pg:gn_country":"NO",
    "qs_pg:name":"H\u00f8yheimsvik",
    "qs_pg:name_adm0":"Norge",
    "qs_pg:name_adm1":"Sogn og Fjordane Fylke",
    "qs_pg:photos":84,
    "qs_pg:photos_1k":17,
    "qs_pg:photos_9k":1,
    "qs_pg:photos_9r":3,
    "qs_pg:photos_all":84,
    "qs_pg:photos_sr":3,
    "qs_pg:pop_sr":0,
    "qs_pg:qs_pg_placetype":"locality",
    "qs_pg:qs_pg_placetype_gp":"Town",
    "qs_pg:woe_adm0":23424910,
    "woe:adm0_id":23424910,
    "woe:name_adm0":"Norge",
    "woe:name_adm1":"Sogn og Fjordane Fylke",
    "woe:placetype":"Town",
    "wof:name":"H\u00f8yheimsvik",
    "wof:placetype":"locality"
},
  "geometry": {"coordinates":[7.395644,61.39446550000001],"type":"Point"}
}