{
  "type": "Feature",
  "properties": {
    "gn:admin1_code":"7",
    "gn:admin2_code":"1235.0",
    "gn:asciiname":"AEn",
    "gn:country_code":"NO",
    "gn:dem":78,
    "gn:feature_class":"P",
    "gn:feature_code":"PPL",
    "gn:name":"\u00c6n",
    "gn:population":0,
    "gn:timezone":"Europe/Oslo",
    "iso:country":"NO",
    "wof:name":"AEn",
    "wof:placetype":"locality"
},
  "geometry": {"coordinates":[6.45,60.66667],"type":"Point"}
}