{
  "type": "Feature",
  "properties": {
    "gn:admin1_code":"14",
    "gn:admin2_code":"1149.0",
    "gn:asciiname":"Falnes",
    "gn:country_code":"NO",
    "gn:dem":9,
    "gn:feature_class":"P",
    "gn:feature_code":"PPL",
    "gn:name":"Falnes",
    "gn:population":0,
    "gn:timezone":"Europe/Oslo",
    "iso:country":"NO",
    "wof:name":"Falnes",
    "wof:placetype":"locality"
},
  "geometry": {"coordinates":[5.28333,59.15],"type":"Point"}
}