{
  "type": "Feature",
  "properties": {
    "gn:admin1_code":"11",
    "gn:admin2_code":"502",
    "gn:asciiname":"Bybrua",
    "gn:country_code":"NO",
    "gn:dem":300,
    "gn:feature_class":"P",
    "gn:feature_code":"PPLL",
    "gn:name":"Bybrua",
    "gn:population":0,
    "gn:timezone":"Europe/Oslo",
    "iso:country":"NO",
    "name:nor_x_preferred":[
        "Bybrua"
    ],
    "wof:name":"Bybrua",
    "wof:placetype":"locality"
},
  "geometry": {"coordinates":[10.58073,60.80275],"type":"Point"}
}