{
  "type": "Feature",
  "properties": {
    "gn:admin1_code":"7",
    "gn:admin2_code":"1243.0",
    "gn:asciiname":"Askvik",
    "gn:country_code":"NO",
    "gn:dem":-9999,
    "gn:feature_class":"P",
    "gn:feature_code":"PPL",
    "gn:name":"Askvik",
    "gn:population":0,
    "gn:timezone":"Europe/Oslo",
    "iso:country":"NO",
    "wof:name":"Askvik",
    "wof:placetype":"neighbourhood"
},
  "geometry": {"coordinates":[5.38083,60.17722],"type":"Point"}
}