{
  "type": "Feature",
  "properties": {
    "gn:admin1_code":"18",
    "gn:admin2_code":"1933.0",
    "gn:asciiname":"Kjerrvika",
    "gn:cc2":"NO",
    "gn:country_code":"NO",
    "gn:dem":-9999,
    "gn:feature_class":"P",
    "gn:feature_code":"PPL",
    "gn:name":"Kjerrvika",
    "gn:population":0,
    "gn:timezone":"Europe/Oslo",
    "iso:country":"NO",
    "name:und_x_variant":[
        "Kj\u00e6rvik",
        "Kjerrvika"
    ],
    "wof:name":"Kjerrvika",
    "wof:placetype":"locality"
},
  "geometry": {"coordinates":[18.76667,69.34999999999999],"type":"Point"}
}