{
  "type": "Feature",
  "properties": {
    "gn:admin1_code":"7",
    "gn:admin2_code":"1235.0",
    "gn:asciiname":"Evanger",
    "gn:country_code":"NO",
    "gn:dem":120,
    "gn:feature_class":"P",
    "gn:feature_code":"PPL",
    "gn:name":"Evanger",
    "gn:population":0,
    "gn:timezone":"Europe/Oslo",
    "iso:country":"NO",
    "wof:name":"Evanger",
    "wof:placetype":"locality"
},
  "geometry": {"coordinates":[6.11216,60.64722],"type":"Point"}
}