{
  "type": "Feature",
  "properties": {
    "gn:admin1_code":"9.0",
    "gn:admin2_code":"1870.0",
    "gn:asciiname":"Storvik",
    "gn:country_code":"NO",
    "gn:dem":2,
    "gn:feature_class":"P",
    "gn:feature_code":"PPL",
    "gn:name":"Storvik",
    "gn:population":0,
    "gn:timezone":"Europe/Oslo",
    "iso:country":"NO",
    "wof:name":"Storvik",
    "wof:placetype":"locality"
},
  "geometry": {"coordinates":[15.06667,68.76666999999999],"type":"Point"}
}