{
  "type": "Feature",
  "properties": {
    "gn:admin1_code":"8",
    "gn:admin2_code":"1532",
    "gn:asciiname":"Nordstranda",
    "gn:country_code":"NO",
    "gn:dem":1,
    "gn:feature_class":"P",
    "gn:feature_code":"PPL",
    "gn:name":"Nordstranda",
    "gn:population":3700,
    "gn:timezone":"Europe/Oslo",
    "iso:country":"NO",
    "name:nor_x_preferred":[
        "Nordstranda"
    ],
    "wof:name":"Nordstranda",
    "wof:placetype":"locality",
    "wof:population":3700
},
  "geometry": {"coordinates":[6.13166,62.51384],"type":"Point"}
}