{
  "type": "Feature",
  "properties": {
    "gn:admin1_code":"11.0",
    "gn:admin2_code":"521.0",
    "gn:asciiname":"Brennlia",
    "gn:country_code":"NO",
    "gn:dem":880,
    "gn:feature_class":"P",
    "gn:feature_code":"PPL",
    "gn:name":"Brennlia",
    "gn:population":0,
    "gn:timezone":"Europe/Oslo",
    "iso:country":"NO",
    "name:nor_x_preferred":[
        "Brennlia"
    ],
    "wof:name":"Brennlia",
    "wof:placetype":"locality"
},
  "geometry": {"coordinates":[10.63607,61.30544],"type":"Point"}
}