{
  "type": "Feature",
  "properties": {
    "gn:admin1_code":"9.0",
    "gn:admin2_code":"1838.0",
    "gn:asciiname":"Rossnes",
    "gn:cc2":"NO",
    "gn:country_code":"NO",
    "gn:dem":1,
    "gn:feature_class":"P",
    "gn:feature_code":"PPL",
    "gn:name":"R\u00f8ssnes",
    "gn:population":0,
    "gn:timezone":"Europe/Oslo",
    "iso:country":"NO",
    "name:und_x_variant":[
        "R\u00f6snes",
        "R\u00f8ssnes i Salten",
        "R\u00f8ssnes"
    ],
    "wof:name":"Rossnes",
    "wof:placetype":"locality"
},
  "geometry": {"coordinates":[14.25,67.08333],"type":"Point"}
}