{
  "type": "Feature",
  "properties": {
    "gn:admin1_code":"20",
    "gn:admin2_code":"712",
    "gn:asciiname":"Rekkevik",
    "gn:country_code":"NO",
    "gn:dem":18,
    "gn:feature_class":"P",
    "gn:feature_code":"PPLL",
    "gn:name":"Rekkevik",
    "gn:population":0,
    "gn:timezone":"Europe/Oslo",
    "iso:country":"NO",
    "name:nor_x_preferred":[
        "Rekkevik"
    ],
    "wof:name":"Rekkevik",
    "wof:placetype":"neighbourhood"
},
  "geometry": {"coordinates":[10.07475,59.02848],"type":"Point"}
}