{
  "type": "Feature",
  "properties": {
    "gn:admin1_code":"11.0",
    "gn:admin2_code":"520.0",
    "gn:asciiname":"Smidesang",
    "gn:country_code":"NO",
    "gn:dem":380,
    "gn:feature_class":"P",
    "gn:feature_code":"PPL",
    "gn:name":"Smidesang",
    "gn:population":0,
    "gn:timezone":"Europe/Oslo",
    "iso:country":"NO",
    "wof:name":"Smidesang",
    "wof:placetype":"locality"
},
  "geometry": {"coordinates":[10.23333,61.41667],"type":"Point"}
}