{
  "type": "Feature",
  "properties": {
    "gn:admin1_code":"18.0",
    "gn:admin2_code":"1903.0",
    "gn:asciiname":"Slakstad",
    "gn:country_code":"NO",
    "gn:dem":1,
    "gn:feature_class":"P",
    "gn:feature_code":"PPL",
    "gn:name":"Slakstad",
    "gn:population":0,
    "gn:timezone":"Europe/Oslo",
    "iso:country":"NO",
    "name:nor_x_preferred":[
        "Slakstad"
    ],
    "wof:name":"Slakstad",
    "wof:placetype":"locality"
},
  "geometry": {"coordinates":[16.73812,68.95714],"type":"Point"}
}