{
  "type": "Feature",
  "properties": {
    "gn:admin1_code":"19.0",
    "gn:admin2_code":"1029.0",
    "gn:asciiname":"Skjollungsstad",
    "gn:country_code":"NO",
    "gn:dem":79,
    "gn:feature_class":"P",
    "gn:feature_code":"PPL",
    "gn:name":"Skj\u00f8llungsstad",
    "gn:population":0,
    "gn:timezone":"Europe/Oslo",
    "iso:country":"NO",
    "name:nor_x_preferred":[
        "Skj\u00f8llungsstad"
    ],
    "wof:name":"Skjollungsstad",
    "wof:placetype":"locality"
},
  "geometry": {"coordinates":[7.38811,58.06862],"type":"Point"}
}