{
  "type": "Feature",
  "properties": {
    "gn:admin1_code":"1.0",
    "gn:admin2_code":"236.0",
    "gn:asciiname":"Tyrigrava",
    "gn:country_code":"NO",
    "gn:dem":260,
    "gn:feature_class":"P",
    "gn:feature_code":"PPL",
    "gn:name":"Tyrigrava",
    "gn:population":0,
    "gn:timezone":"Europe/Oslo",
    "iso:country":"NO",
    "name:nor_x_preferred":[
        "Tyrigrava"
    ],
    "wof:name":"Tyrigrava",
    "wof:placetype":"locality"
},
  "geometry": {"coordinates":[11.71531,60.04269],"type":"Point"}
}