{
  "type": "Feature",
  "properties": {
    "gn:admin1_code":"21.0",
    "gn:admin2_code":"5054.0",
    "gn:asciiname":"Reinsgrenda",
    "gn:country_code":"NO",
    "gn:dem":132,
    "gn:feature_class":"P",
    "gn:feature_code":"PPL",
    "gn:name":"Reinsgrenda",
    "gn:population":0,
    "gn:timezone":"Europe/Oslo",
    "iso:country":"NO",
    "name:nor_x_preferred":[
        "Reinsgrenda"
    ],
    "wof:name":"Reinsgrenda",
    "wof:placetype":"locality"
},
  "geometry": {"coordinates":[9.92531,63.54891],"type":"Point"}
}