{
  "type": "Feature",
  "properties": {
    "gn:admin1_code":"15",
    "gn:admin2_code":"1411.0",
    "gn:asciiname":"Brosvik",
    "gn:country_code":"NO",
    "gn:dem":20,
    "gn:feature_class":"P",
    "gn:feature_code":"PPL",
    "gn:name":"Brosvik",
    "gn:population":0,
    "gn:timezone":"Europe/Oslo",
    "iso:country":"NO",
    "wof:name":"Brosvik",
    "wof:placetype":"locality"
},
  "geometry": {"coordinates":[5.13333,61.06667],"type":"Point"}
}