{
  "type": "Feature",
  "properties": {
    "gn:admin1_code":"9.0",
    "gn:admin2_code":"1874.0",
    "gn:asciiname":"Rostad",
    "gn:country_code":"NO",
    "gn:dem":140,
    "gn:feature_class":"P",
    "gn:feature_code":"PPL",
    "gn:name":"Rostad",
    "gn:population":0,
    "gn:timezone":"Europe/Oslo",
    "iso:country":"NO",
    "wof:name":"Rostad",
    "wof:placetype":"locality"
},
  "geometry": {"coordinates":[13.04634,67.9622],"type":"Point"}
}