{
  "type": "Feature",
  "properties": {
    "gn:admin1_code":"5.0",
    "gn:admin2_code":"2012.0",
    "gn:asciiname":"Tappeluft",
    "gn:country_code":"NO",
    "gn:dem":80,
    "gn:feature_class":"P",
    "gn:feature_code":"PPL",
    "gn:name":"Tappeluft",
    "gn:population":0,
    "gn:timezone":"Europe/Oslo",
    "iso:country":"NO",
    "name:nor_x_preferred":[
        "Tappeluft"
    ],
    "name:sme_x_preferred":[
        "Dappeluokta"
    ],
    "wof:name":"Tappeluft",
    "wof:placetype":"locality"
},
  "geometry": {"coordinates":[22.47472,70.08750000000001],"type":"Point"}
}