{
  "type": "Feature",
  "properties": {
    "gn:admin1_code":"11.0",
    "gn:admin2_code":"528.0",
    "gn:asciiname":"Rud",
    "gn:country_code":"NO",
    "gn:dem":360,
    "gn:feature_class":"P",
    "gn:feature_code":"PPL",
    "gn:name":"Rud",
    "gn:population":0,
    "gn:timezone":"Europe/Oslo",
    "iso:country":"NO",
    "name:aze_x_preferred":[
        "Rud"
    ],
    "name:nor_x_preferred":[
        "Rud"
    ],
    "name:rus_x_preferred":[
        "\u0420\u0443\u0434"
    ],
    "wof:name":"Rud",
    "wof:placetype":"locality"
},
  "geometry": {"coordinates":[10.73092,60.60544],"type":"Point"}
}