{
  "type": "Feature",
  "properties": {
    "gn:admin1_code":"11",
    "gn:admin2_code":"536",
    "gn:asciiname":"Vestrumsbygda",
    "gn:country_code":"NO",
    "gn:dem":490,
    "gn:feature_class":"P",
    "gn:feature_code":"PPL",
    "gn:name":"Vestrumsbygda",
    "gn:population":0,
    "gn:timezone":"Europe/Oslo",
    "iso:country":"NO",
    "wof:name":"Vestrumsbygda",
    "wof:placetype":"locality"
},
  "geometry": {"coordinates":[10.26559,60.80594],"type":"Point"}
}