{
  "type": "Feature",
  "properties": {
    "gn:admin1_code":"18.0",
    "gn:admin2_code":"1913.0",
    "gn:asciiname":"Elvebakken",
    "gn:country_code":"NO",
    "gn:dem":60,
    "gn:feature_class":"P",
    "gn:feature_code":"PPL",
    "gn:name":"Elvebakken",
    "gn:population":0,
    "gn:timezone":"Europe/Oslo",
    "iso:country":"NO",
    "name:nor_x_preferred":[
        "Elvebakken"
    ],
    "name:swe_x_preferred":[
        "Elvebakken"
    ],
    "wof:name":"Elvebakken",
    "wof:placetype":"locality"
},
  "geometry": {"coordinates":[16.92845,68.69682],"type":"Point"}
}