{
  "type": "Feature",
  "properties": {
    "gn:admin1_code":"9",
    "gn:admin2_code":"1813.0",
    "gn:asciiname":"Graven",
    "gn:country_code":"NO",
    "gn:dem":180,
    "gn:feature_class":"P",
    "gn:feature_code":"PPL",
    "gn:name":"Graven",
    "gn:population":0,
    "gn:timezone":"Europe/Oslo",
    "iso:country":"NO",
    "wof:name":"Graven",
    "wof:placetype":"locality"
},
  "geometry": {"coordinates":[12.63333,65.40000000000001],"type":"Point"}
}