{
  "type": "Feature",
  "properties": {
    "gn:admin1_code":"2",
    "gn:admin2_code":"919.0",
    "gn:asciiname":"Dale",
    "gn:country_code":"NO",
    "gn:dem":95,
    "gn:feature_class":"P",
    "gn:feature_code":"PPL",
    "gn:name":"Dale",
    "gn:population":0,
    "gn:timezone":"Europe/Oslo",
    "iso:country":"NO",
    "wof:name":"Dale",
    "wof:placetype":"locality"
},
  "geometry": {"coordinates":[8.63333,58.55],"type":"Point"}
}