{
  "type": "Feature",
  "properties": {
    "gn:admin1_code":"9",
    "gn:admin2_code":"1837.0",
    "gn:asciiname":"Eidsbukta",
    "gn:cc2":"NO",
    "gn:country_code":"NO",
    "gn:dem":-9999,
    "gn:feature_class":"P",
    "gn:feature_code":"PPL",
    "gn:name":"Eidsbukta",
    "gn:population":0,
    "gn:timezone":"Europe/Oslo",
    "iso:country":"NO",
    "name:und_x_variant":[
        "Eidbugten",
        "Eidbukt",
        "Eidsbukta"
    ],
    "wof:name":"Eidsbukta",
    "wof:placetype":"locality"
},
  "geometry": {"coordinates":[13.73333,66.83333],"type":"Point"}
}