{
  "type": "Feature",
  "properties": {
    "gn:admin1_code":"6.0",
    "gn:admin2_code":"428.0",
    "gn:asciiname":"Ostby",
    "gn:country_code":"NO",
    "gn:dem":476,
    "gn:feature_class":"P",
    "gn:feature_code":"PPLL",
    "gn:name":"\u00d8stby",
    "gn:population":0,
    "gn:timezone":"Europe/Oslo",
    "iso:country":"NO",
    "name:jav_x_preferred":[
        "\u00d8stby"
    ],
    "name:msa_x_preferred":[
        "\u00d8stby"
    ],
    "name:nld_x_preferred":[
        "\u00d8stby"
    ],
    "name:swe_x_preferred":[
        "\u00d8stby"
    ],
    "wof:name":"Ostby",
    "wof:placetype":"locality"
},
  "geometry": {"coordinates":[12.52688,61.25401],"type":"Point"}
}