{
  "type": "Feature",
  "properties": {
    "gn:admin1_code":"15",
    "gn:admin2_code":"1428.0",
    "gn:asciiname":"Hamna",
    "gn:country_code":"NO",
    "gn:dem":-9999,
    "gn:feature_class":"P",
    "gn:feature_code":"PPL",
    "gn:name":"Hamna",
    "gn:population":0,
    "gn:timezone":"Europe/Oslo",
    "iso:country":"NO",
    "wof:name":"Hamna",
    "wof:placetype":"locality"
},
  "geometry": {"coordinates":[4.73333,61.31667],"type":"Point"}
}