{
  "type": "Feature",
  "properties": {
    "gn:gn_country":"NO",
    "gn:gn_fcode":"PPL",
    "gn:gn_pop":204,
    "gn:population":204,
    "iso:country":"NO",
    "name:bul_x_preferred":[
        "\u0410\u043b\u043d\u0435\u0441"
    ],
    "name:ceb_x_preferred":[
        "Alnes"
    ],
    "name:eng_x_preferred":[
        "Alnes"
    ],
    "name:fas_x_preferred":[
        "\u0627\u0644\u0646\u0632"
    ],
    "name:fra_x_preferred":[
        "Alnes"
    ],
    "name:ita_x_preferred":[
        "Alnes"
    ],
    "name:jav_x_preferred":[
        "Alnes"
    ],
    "name:msa_x_preferred":[
        "Alnes"
    ],
    "name:nld_x_preferred":[
        "Alnes"
    ],
    "name:nob_x_preferred":[
        "Alnes"
    ],
    "name:ron_x_preferred":[
        "Alnes"
    ],
    "qs_pg:aaroncc":"NO",
    "qs_pg:gn_country":"NO",
    "qs_pg:gn_fcode":"PPL",
    "qs_pg:gn_pop":204,
    "qs_pg:name":"Alnes",
    "qs_pg:name_adm0":"Norge",
    "qs_pg:name_adm1":"M\u00f8re og Romsdal Fylke",
    "qs_pg:photos":208,
    "qs_pg:photos_1k":42,
    "qs_pg:photos_9k":1,
    "qs_pg:photos_9r":4,
    "qs_pg:photos_all":208,
    "qs_pg:photos_sr":4,
    "qs_pg:pop_sr":2,
    "qs_pg:qs_pg_placetype":"locality",
    "qs_pg:qs_pg_placetype_gp":"Town",
    "qs_pg:woe_adm0":23424910,
    "woe:adm0_id":23424910,
    "woe:name_adm0":"Norge",
    "woe:name_adm1":"M\u00f8re og Romsdal Fylke",
    "woe:placetype":"Town",
    "wof:name":"Alnes",
    "wof:placetype":"locality",
    "wof:population":204
},
  "geometry": {"coordinates":[5.96667,62.48333],"type":"Point"}
}