{
  "type": "Feature",
  "properties": {
    "gn:country":"NO",
    "iso:country":"NO",
    "name:ara_x_preferred":[
        "\u0628\u064a\u0648\u063a\u0646"
    ],
    "name:ast_x_preferred":[
        "Bjugn"
    ],
    "name:bpy_x_preferred":[
        "\u09ac\u099c\u09c1\u0997\u09a8"
    ],
    "name:cat_x_preferred":[
        "Bjugn"
    ],
    "name:ceb_x_preferred":[
        "Bjugn"
    ],
    "name:ces_x_preferred":[
        "Bjugn"
    ],
    "name:dan_x_preferred":[
        "Bjugn"
    ],
    "name:deu_x_preferred":[
        "Bjugn"
    ],
    "name:eng_x_preferred":[
        "Bjugn"
    ],
    "name:epo_x_preferred":[
        "Bjugn"
    ],
    "name:eus_x_preferred":[
        "Bjugn"
    ],
    "name:fin_x_preferred":[
        "Bjugn"
    ],
    "name:fra_x_preferred":[
        "Bjugn"
    ],
    "name:hye_x_preferred":[
        "\u0532\u0575\u0578\u0582\u0563\u0576"
    ],
    "name:ita_x_preferred":[
        "Bjugn"
    ],
    "name:lat_x_preferred":[
        "Bjugn"
    ],
    "name:lim_x_preferred":[
        "Bjugn"
    ],
    "name:msa_x_preferred":[
        "Bjugn"
    ],
    "name:nan_x_preferred":[
        "Bjugn"
    ],
    "name:nds_x_preferred":[
        "Kommun Bjugn"
    ],
    "name:nld_x_preferred":[
        "Bjugn"
    ],
    "name:nno_x_preferred":[
        "Bjugn"
    ],
    "name:nob_x_preferred":[
        "Bjugn"
    ],
    "name:pol_x_preferred":[
        "Bjugn"
    ],
    "name:por_x_preferred":[
        "Bjugn"
    ],
    "name:ron_x_preferred":[
        "Bjugn"
    ],
    "name:rus_x_preferred":[
        "\u0411\u044c\u044e\u0433\u043d"
    ],
    "name:slv_x_preferred":[
        "Bjugn"
    ],
    "name:sme_x_preferred":[
        "Bjugn"
    ],
    "name:spa_x_preferred":[
        "Bjugn"
    ],
    "name:sqi_x_preferred":[
        "Bjugn"
    ],
    "name:swa_x_preferred":[
        "Bjugn"
    ],
    "name:swe_x_preferred":[
        "Bjugn"
    ],
    "name:tur_x_preferred":[
        "Bjugn"
    ],
    "name:vie_x_preferred":[
        "Bjugn"
    ],
    "name:war_x_preferred":[
        "Bjugn"
    ],
    "name:zho_x_preferred":[
        "\u6bd4\u4e8e\u6069"
    ],
    "qs_pg:aaroncc":"NO",
    "qs_pg:gn_country":"NO",
    "qs_pg:name":"Bjugn",
    "qs_pg:name_adm0":"Norge",
    "qs_pg:name_adm1":"S\u00f8r-Tr\u00f8ndelag Fylke",
    "qs_pg:photos":74,
    "qs_pg:photos_1k":15,
    "qs_pg:photos_9k":1,
    "qs_pg:photos_9r":2,
    "qs_pg:photos_all":74,
    "qs_pg:photos_sr":2,
    "qs_pg:pop_sr":0,
    "qs_pg:qs_pg_placetype":"locality",
    "qs_pg:qs_pg_placetype_gp":"Town",
    "qs_pg:woe_adm0":23424910,
    "woe:adm0_id":23424910,
    "woe:name_adm0":"Norge",
    "woe:name_adm1":"S\u00f8r-Tr\u00f8ndelag Fylke",
    "woe:placetype":"Town",
    "wof:name":"Bjugn",
    "wof:placetype":"locality"
},
  "geometry": {"coordinates":[9.857482,63.725703],"type":"Point"}
}