{
  "type": "Feature",
  "properties": {
    "gn:admin1_code":"5.0",
    "gn:admin2_code":"2002.0",
    "gn:asciiname":"Kramvik",
    "gn:country_code":"NO",
    "gn:dem":-9999,
    "gn:feature_class":"P",
    "gn:feature_code":"PPL",
    "gn:name":"Kramvik",
    "gn:population":0,
    "gn:timezone":"Europe/Oslo",
    "iso:country":"NO",
    "name:eng_x_preferred":[
        "Kramvik"
    ],
    "name:rus_x_preferred":[
        "\u041a\u0440\u0430\u043c\u0432\u0438\u043a"
    ],
    "wof:name":"Kramvik",
    "wof:placetype":"locality"
},
  "geometry": {"coordinates":[30.85902,70.26652],"type":"Point"}
}