{
  "type": "Feature",
  "properties": {
    "gn:admin1_code":"19.0",
    "gn:admin2_code":"1003.0",
    "gn:asciiname":"Sondre Bjornestad",
    "gn:country_code":"NO",
    "gn:dem":90,
    "gn:feature_class":"P",
    "gn:feature_code":"PPL",
    "gn:name":"S\u00f8ndre Bj\u00f8rnestad",
    "gn:population":0,
    "gn:timezone":"Europe/Oslo",
    "iso:country":"NO",
    "name:nor_x_preferred":[
        "S\u00f8ndre Bj\u00f8rnestad"
    ],
    "wof:name":"Sondre Bjornestad",
    "wof:placetype":"locality"
},
  "geometry": {"coordinates":[6.88219,58.10947],"type":"Point"}
}