{
  "type": "Feature",
  "properties": {
    "gn:admin1_code":"5.0",
    "gn:admin2_code":"2019.0",
    "gn:asciiname":"Tunes",
    "gn:cc2":"NO",
    "gn:country_code":"NO",
    "gn:dem":-9999,
    "gn:feature_class":"P",
    "gn:feature_code":"PPL",
    "gn:name":"Tunes",
    "gn:population":0,
    "gn:timezone":"Europe/Oslo",
    "iso:country":"NO",
    "name:ara_x_preferred":[
        "\u062a\u0648\u0646\u0633"
    ],
    "name:ceb_x_preferred":[
        "Tunes"
    ],
    "name:deu_x_preferred":[
        "Tunes"
    ],
    "name:fas_x_preferred":[
        "\u062a\u0648\u0646\u0633"
    ],
    "name:fra_x_preferred":[
        "Tunes"
    ],
    "name:ita_x_preferred":[
        "Tunes"
    ],
    "name:nor_x_preferred":[
        "Tunes"
    ],
    "name:por_x_preferred":[
        "Tunes"
    ],
    "name:swe_x_preferred":[
        "Tunes"
    ],
    "name:tur_x_preferred":[
        "Tunes"
    ],
    "name:und_x_variant":[
        "Tuneset"
    ],
    "wof:name":"Tunes",
    "wof:placetype":"locality"
},
  "geometry": {"coordinates":[25.55,71.16667],"type":"Point"}
}