{
  "type": "Feature",
  "properties": {
    "gn:admin1_code":"15.0",
    "gn:admin2_code":"1421.0",
    "gn:asciiname":"Tero",
    "gn:country_code":"NO",
    "gn:dem":120,
    "gn:feature_class":"P",
    "gn:feature_code":"PPL",
    "gn:name":"Tero",
    "gn:population":0,
    "gn:timezone":"Europe/Oslo",
    "iso:country":"NO",
    "name:ceb_x_preferred":[
        "Tero"
    ],
    "name:jpn_x_preferred":[
        "\u30c6\u30ed"
    ],
    "name:spa_x_preferred":[
        "Tero"
    ],
    "name:swe_x_preferred":[
        "Tero"
    ],
    "wof:name":"Tero",
    "wof:placetype":"locality"
},
  "geometry": {"coordinates":[7.25,60.88333000000001],"type":"Point"}
}