{
  "type": "Feature",
  "properties": {
    "gn:admin1_code":"2.0",
    "gn:admin2_code":"906.0",
    "gn:asciiname":"Vage",
    "gn:cc2":"NO",
    "gn:country_code":"NO",
    "gn:dem":89,
    "gn:feature_class":"P",
    "gn:feature_code":"PPL",
    "gn:name":"V\u00e5ge",
    "gn:population":0,
    "gn:timezone":"Europe/Oslo",
    "iso:country":"NO",
    "name:und_x_variant":[
        "Vaaje",
        "V\u00e5ge"
    ],
    "wof:name":"Vage",
    "wof:placetype":"locality"
},
  "geometry": {"coordinates":[8.83333,58.56667],"type":"Point"}
}