{
  "type": "Feature",
  "properties": {
    "iso:country":"NO",
    "name:dan_x_preferred":[
        "Marienborg"
    ],
    "name:deu_x_preferred":[
        "Marienborg"
    ],
    "name:fra_x_preferred":[
        "Marienborg"
    ],
    "name:ita_x_preferred":[
        "Marienborg"
    ],
    "name:jpn_x_preferred":[
        "\u30de\u30ea\u30f3\u30dc\u30fc"
    ],
    "name:nor_x_preferred":[
        "Marienborg"
    ],
    "name:por_x_preferred":[
        "Marienborg"
    ],
    "name:swe_x_preferred":[
        "Marienborg"
    ],
    "name:unk_x_variant":[
        "Marienborg"
    ],
    "qs:gn_adm0_cc":"NO",
    "qs:gn_local":3133880,
    "qs:local_max":5709,
    "qs:local_sum":31956,
    "qs:localhoods":65,
    "qs:name":"Marienborg",
    "qs:name_adm0":"Norge",
    "qs:name_adm1":"S\u00f8r-Tr\u00f8ndelag Fylke",
    "qs:name_adm2":"Trondheim Kommune",
    "qs:name_local":"Trondheim",
    "qs:photo_max":30,
    "qs:photo_sum":213,
    "qs:placetype":"Suburb",
    "qs:quad_count":20,
    "qs:woe_adm0":23424910,
    "qs:woe_adm1":2346399,
    "qs:woe_adm2":12592932,
    "qs:woe_lau":0,
    "qs:woe_local":865157,
    "qs:woe_ver":"7.10.0",
    "wd:wordcount":529,
    "wof:lang":[
        "nor"
    ],
    "wof:name":"Marienborg",
    "wof:placetype":"neighbourhood"
},
  "geometry": {"coordinates":[10.381206,63.417802],"type":"Point"}
}