{
  "type": "Feature",
  "properties": {
    "gn:admin1_code":"9.0",
    "gn:admin2_code":"1845.0",
    "gn:asciiname":"Oyrnes",
    "gn:cc2":"NO",
    "gn:country_code":"NO",
    "gn:dem":-9999,
    "gn:feature_class":"P",
    "gn:feature_code":"PPL",
    "gn:name":"\u00d8yrnes",
    "gn:population":0,
    "gn:timezone":"Europe/Oslo",
    "iso:country":"NO",
    "name:und_x_variant":[
        "\u00d6rrnes",
        "\u00d8yrnes"
    ],
    "wof:name":"Oyrnes",
    "wof:placetype":"locality"
},
  "geometry": {"coordinates":[15.85,67.58333],"type":"Point"}
}