{
  "type": "Feature",
  "properties": {
    "gn:admin1_code":"17",
    "gn:admin2_code":"827.0",
    "gn:asciiname":"Flugun",
    "gn:country_code":"NO",
    "gn:dem":765,
    "gn:feature_class":"P",
    "gn:feature_code":"PPL",
    "gn:name":"Flugun",
    "gn:population":0,
    "gn:timezone":"Europe/Oslo",
    "iso:country":"NO",
    "wof:name":"Flugun",
    "wof:placetype":"locality"
},
  "geometry": {"coordinates":[8.85,59.75],"type":"Point"}
}