{
  "type": "Feature",
  "properties": {
    "gn:admin1_code":"18.0",
    "gn:admin2_code":"1924.0",
    "gn:asciiname":"Rosta",
    "gn:cc2":"NO",
    "gn:country_code":"NO",
    "gn:dem":170,
    "gn:feature_class":"P",
    "gn:feature_code":"PPL",
    "gn:name":"Rosta",
    "gn:population":0,
    "gn:timezone":"Europe/Oslo",
    "iso:country":"NO",
    "name:ita_x_preferred":[
        "Rosta"
    ],
    "name:und_x_variant":[
        "Ruosta"
    ],
    "wof:name":"Rosta",
    "wof:placetype":"locality"
},
  "geometry": {"coordinates":[19.66667,68.98333000000001],"type":"Point"}
}