{
  "type": "Feature",
  "properties": {
    "gn:admin1_code":"7.0",
    "gn:admin2_code":"1235.0",
    "gn:asciiname":"Rassdal",
    "gn:country_code":"NO",
    "gn:dem":430,
    "gn:feature_class":"P",
    "gn:feature_code":"PPL",
    "gn:name":"Rassdal",
    "gn:population":0,
    "gn:timezone":"Europe/Oslo",
    "iso:country":"NO",
    "wof:name":"Rassdal",
    "wof:placetype":"locality"
},
  "geometry": {"coordinates":[5.96667,60.61666999999999],"type":"Point"}
}