{
  "type": "Feature",
  "properties": {
    "gn:admin1_code":"11.0",
    "gn:admin2_code":"543.0",
    "gn:asciiname":"Vollen",
    "gn:cc2":"NO",
    "gn:country_code":"NO",
    "gn:dem":460,
    "gn:feature_class":"P",
    "gn:feature_code":"PPL",
    "gn:name":"Vollen",
    "gn:population":0,
    "gn:timezone":"Europe/Oslo",
    "iso:country":"NO",
    "name:ceb_x_preferred":[
        "Vollen"
    ],
    "name:nld_x_preferred":[
        "Vollen"
    ],
    "name:nor_x_preferred":[
        "Vollen"
    ],
    "name:spa_x_preferred":[
        "Vollen"
    ],
    "name:und_x_variant":[
        "Volden"
    ],
    "wof:name":"Vollen",
    "wof:placetype":"locality"
},
  "geometry": {"coordinates":[8.97517,61.09437],"type":"Point"}
}