{
  "type": "Feature",
  "properties": {
    "gn:country":"NO",
    "iso:country":"NO",
    "name:eng_x_preferred":[
        "Talgje"
    ],
    "name:fra_x_preferred":[
        "Talgje"
    ],
    "name:msa_x_preferred":[
        "Talgje"
    ],
    "name:nld_x_preferred":[
        "Talgje"
    ],
    "name:nno_x_preferred":[
        "Talgje"
    ],
    "name:nob_x_preferred":[
        "Talgje"
    ],
    "qs_pg:aaroncc":"NO",
    "qs_pg:gn_country":"NO",
    "qs_pg:name":"Talgje",
    "qs_pg:name_adm0":"Norge",
    "qs_pg:name_adm1":"Rogaland Fylke",
    "qs_pg:photos":47,
    "qs_pg:photos_1k":10,
    "qs_pg:photos_9k":1,
    "qs_pg:photos_9r":2,
    "qs_pg:photos_all":47,
    "qs_pg:photos_sr":2,
    "qs_pg:pop_sr":0,
    "qs_pg:qs_pg_placetype":"locality",
    "qs_pg:qs_pg_placetype_gp":"Town",
    "qs_pg:woe_adm0":23424910,
    "woe:adm0_id":23424910,
    "woe:name_adm0":"Norge",
    "woe:name_adm1":"Rogaland Fylke",
    "woe:placetype":"Town",
    "wof:name":"Talgje",
    "wof:placetype":"locality"
},
  "geometry": {"coordinates":[5.81314,59.115457],"type":"Point"}
}