{
  "type": "Feature",
  "properties": {
    "gn:admin1_code":"4.0",
    "gn:admin2_code":"626.0",
    "gn:asciiname":"Ogarden",
    "gn:cc2":"NO",
    "gn:country_code":"NO",
    "gn:dem":8,
    "gn:feature_class":"P",
    "gn:feature_code":"PPLL",
    "gn:name":"\u00d8g\u00e5rden",
    "gn:population":0,
    "gn:timezone":"Europe/Oslo",
    "iso:country":"NO",
    "name:und_x_variant":[
        "\u00d8deg\u00e5rd",
        "\u00d8g\u00e5rden"
    ],
    "wof:name":"Ogarden",
    "wof:placetype":"locality"
},
  "geometry": {"coordinates":[10.28028,59.76444],"type":"Point"}
}