{
  "type": "Feature",
  "properties": {
    "gn:admin1_code":"9.0",
    "gn:admin2_code":"1854.0",
    "gn:asciiname":"Porsoy",
    "gn:cc2":"NO",
    "gn:country_code":"NO",
    "gn:dem":1,
    "gn:feature_class":"P",
    "gn:feature_code":"PPL",
    "gn:name":"Pors\u00f8y",
    "gn:population":0,
    "gn:timezone":"Europe/Oslo",
    "iso:country":"NO",
    "name:und_x_variant":[
        "Pors\u00f6en",
        "Pors\u00f8y"
    ],
    "wof:name":"Porsoy",
    "wof:placetype":"locality"
},
  "geometry": {"coordinates":[16.61667000000001,68.41667],"type":"Point"}
}