{
  "type": "Feature",
  "properties": {
    "gn:admin1_code":"21.0",
    "gn:admin2_code":"5025.0",
    "gn:asciiname":"Sundet",
    "gn:country_code":"NO",
    "gn:dem":641,
    "gn:feature_class":"P",
    "gn:feature_code":"PPL",
    "gn:name":"Sundet",
    "gn:population":0,
    "gn:timezone":"Europe/Oslo",
    "iso:country":"NO",
    "name:nor_x_preferred":[
        "Sundet"
    ],
    "wof:name":"Sundet",
    "wof:placetype":"locality"
},
  "geometry": {"coordinates":[11.32588,62.58554],"type":"Point"}
}