{
  "type": "Feature",
  "properties": {
    "gn:country":"NO",
    "gn:fcode":"PPL",
    "gn:population":2599,
    "iso:country":"NO",
    "name:ceb_x_preferred":[
        "Sk\u00e5levik"
    ],
    "name:eng_x_preferred":[
        "Sk\u00e5levik"
    ],
    "name:fra_x_preferred":[
        "Sk\u00e5levik"
    ],
    "name:msa_x_preferred":[
        "Sk\u00e5levik"
    ],
    "name:nld_x_preferred":[
        "Sk\u00e5levik"
    ],
    "name:nno_x_preferred":[
        "Sk\u00e5levik"
    ],
    "name:nob_x_preferred":[
        "Sk\u00e5levik"
    ],
    "name:ron_x_preferred":[
        "Sk\u00e5levik"
    ],
    "name:spa_x_preferred":[
        "Sk\u00e5levik"
    ],
    "name:und_x_variant":[
        "Skaalevig"
    ],
    "qs_pg:aaroncc":"NO",
    "qs_pg:gn_country":"NO",
    "qs_pg:gn_fcode":"PPL",
    "qs_pg:gn_pop":2599,
    "qs_pg:name":"Ytre Sk\u00e5levik",
    "qs_pg:photos_9r":0,
    "qs_pg:photos_sr":0,
    "qs_pg:pop_sr":4,
    "qs_pg:qs_pg_placetype":"locality",
    "wof:name":"Ytre Sk\u00e5levik",
    "wof:placetype":"neighbourhood",
    "wof:population":2599
},
  "geometry": {"coordinates":[8.01667,58.08333],"type":"Point"}
}