{
  "type": "Feature",
  "properties": {
    "gn:admin1_code":"1.0",
    "gn:admin2_code":"236.0",
    "gn:asciiname":"Slutten",
    "gn:country_code":"NO",
    "gn:dem":180,
    "gn:feature_class":"P",
    "gn:feature_code":"PPL",
    "gn:name":"Slutten",
    "gn:population":0,
    "gn:timezone":"Europe/Oslo",
    "iso:country":"NO",
    "name:nor_x_preferred":[
        "Slutten"
    ],
    "wof:name":"Slutten",
    "wof:placetype":"locality"
},
  "geometry": {"coordinates":[11.53127,60.25456],"type":"Point"}
}