{
  "type": "Feature",
  "properties": {
    "gn:admin1_code":"9.0",
    "gn:admin2_code":"1850.0",
    "gn:asciiname":"Storjorda",
    "gn:country_code":"NO",
    "gn:dem":-9999,
    "gn:feature_class":"P",
    "gn:feature_code":"PPL",
    "gn:name":"Storjorda",
    "gn:population":0,
    "gn:timezone":"Europe/Oslo",
    "iso:country":"NO",
    "name:nor_x_preferred":[
        "Storjorda"
    ],
    "name:smj_x_preferred":[
        "Stuorgiedde"
    ],
    "wof:name":"Storjorda",
    "wof:placetype":"locality"
},
  "geometry": {"coordinates":[16.06857,68.20198000000001],"type":"Point"}
}