{
  "type": "Feature",
  "properties": {
    "gn:admin1_code":"6.0",
    "gn:admin2_code":"426.0",
    "gn:asciiname":"Svennebysaetra",
    "gn:country_code":"NO",
    "gn:dem":460,
    "gn:feature_class":"P",
    "gn:feature_code":"PPL",
    "gn:name":"Svennebys\u00e6tra",
    "gn:population":0,
    "gn:timezone":"Europe/Oslo",
    "iso:country":"NO",
    "name:nor_x_preferred":[
        "Svennebys\u00e6tra"
    ],
    "wof:name":"Svennebysaetra",
    "wof:placetype":"locality"
},
  "geometry": {"coordinates":[11.67985,60.62606],"type":"Point"}
}