{
  "type": "Feature",
  "properties": {
    "gn:admin1_code":"17",
    "gn:admin2_code":"827",
    "gn:asciiname":"Nord-bygdi",
    "gn:country_code":"NO",
    "gn:dem":466,
    "gn:feature_class":"P",
    "gn:feature_code":"PPL",
    "gn:name":"Nord-bygdi",
    "gn:population":0,
    "gn:timezone":"Europe/Oslo",
    "iso:country":"NO",
    "name:nor_x_preferred":[
        "Nord-bygdi"
    ],
    "wof:name":"Nord-bygdi",
    "wof:placetype":"locality"
},
  "geometry": {"coordinates":[8.60658,59.61204],"type":"Point"}
}