{
  "type": "Feature",
  "properties": {
    "gn:admin1_code":"6",
    "gn:admin2_code":"417.0",
    "gn:asciiname":"Foss",
    "gn:cc2":"NO",
    "gn:country_code":"NO",
    "gn:dem":260,
    "gn:feature_class":"P",
    "gn:feature_code":"PPL",
    "gn:name":"Foss",
    "gn:population":0,
    "gn:timezone":"Europe/Oslo",
    "iso:country":"NO",
    "name:ceb_x_preferred":[
        "Foss"
    ],
    "name:dan_x_preferred":[
        "Foss"
    ],
    "name:deu_x_preferred":[
        "Foss"
    ],
    "name:fin_x_preferred":[
        "Foss"
    ],
    "name:fra_x_preferred":[
        "Foss"
    ],
    "name:ita_x_preferred":[
        "Foss"
    ],
    "name:nds_x_preferred":[
        "Foss"
    ],
    "name:nld_x_preferred":[
        "Foss"
    ],
    "name:por_x_preferred":[
        "Foss"
    ],
    "name:swe_x_preferred":[
        "Foss"
    ],
    "name:und_x_variant":[
        "Fos"
    ],
    "wof:name":"Foss",
    "wof:placetype":"locality"
},
  "geometry": {"coordinates":[11.35,60.66667],"type":"Point"}
}