{
  "type": "Feature",
  "properties": {
    "gn:admin1_code":"18.0",
    "gn:admin2_code":"1938.0",
    "gn:asciiname":"Ravik",
    "gn:country_code":"NO",
    "gn:dem":60,
    "gn:feature_class":"P",
    "gn:feature_code":"PPL",
    "gn:name":"Ravik",
    "gn:population":0,
    "gn:timezone":"Europe/Oslo",
    "iso:country":"NO",
    "wof:name":"Ravik",
    "wof:placetype":"locality"
},
  "geometry": {"coordinates":[19.96667,69.83333],"type":"Point"}
}