{
  "type": "Feature",
  "properties": {
    "gn:admin1_code":"9.0",
    "gn:admin2_code":"1824.0",
    "gn:asciiname":"Stormoen",
    "gn:country_code":"NO",
    "gn:dem":140,
    "gn:feature_class":"P",
    "gn:feature_code":"PPL",
    "gn:name":"Stormoen",
    "gn:population":0,
    "gn:timezone":"Europe/Oslo",
    "iso:country":"NO",
    "wof:name":"Stormoen",
    "wof:placetype":"locality"
},
  "geometry": {"coordinates":[13.55,66.08333],"type":"Point"}
}