{
  "type": "Feature",
  "properties": {
    "gn:admin1_code":"14",
    "gn:admin2_code":"1130.0",
    "gn:asciiname":"Idsal",
    "gn:country_code":"NO",
    "gn:dem":35,
    "gn:feature_class":"P",
    "gn:feature_code":"PPL",
    "gn:name":"Idsal",
    "gn:population":0,
    "gn:timezone":"Europe/Oslo",
    "iso:country":"NO",
    "name:nno_x_preferred":[
        "Idsal"
    ],
    "name:nor_x_preferred":[
        "Idsal"
    ],
    "wof:name":"Idsal",
    "wof:placetype":"locality"
},
  "geometry": {"coordinates":[5.98333,58.98333],"type":"Point"}
}