{
  "type": "Feature",
  "properties": {
    "gn:admin1_code":"7",
    "gn:admin2_code":"1223.0",
    "gn:asciiname":"Hovland",
    "gn:country_code":"NO",
    "gn:dem":1,
    "gn:feature_class":"P",
    "gn:feature_code":"PPL",
    "gn:name":"Hovland",
    "gn:population":0,
    "gn:timezone":"Europe/Oslo",
    "iso:country":"NO",
    "name:deu_x_preferred":[
        "Hovland"
    ],
    "name:nor_x_preferred":[
        "Hovland"
    ],
    "name:rus_x_preferred":[
        "\u0425\u043e\u0432\u043b\u0430\u043d\u0434"
    ],
    "name:swe_x_preferred":[
        "Hovland"
    ],
    "wof:name":"Hovland",
    "wof:placetype":"locality"
},
  "geometry": {"coordinates":[5.69392,60.01336],"type":"Point"}
}