{
  "type": "Feature",
  "properties": {
    "gn:admin1_code":"5.0",
    "gn:admin2_code":"2028.0",
    "gn:asciiname":"Hamna",
    "gn:country_code":"NO",
    "gn:dem":33,
    "gn:feature_class":"P",
    "gn:feature_code":"PPL",
    "gn:name":"Hamna",
    "gn:population":0,
    "gn:timezone":"Europe/Oslo",
    "iso:country":"NO",
    "name:eng_x_preferred":[
        "Hamna"
    ],
    "name:rus_x_preferred":[
        "\u0425\u0430\u043c\u043d\u0430"
    ],
    "name:und_x_variant":[
        "Syltefjordbotn",
        "Hamna i Syltefjord",
        "Finnes"
    ],
    "wof:name":"Hamna",
    "wof:placetype":"locality"
},
  "geometry": {"coordinates":[30.0915,70.53601999999999],"type":"Point"}
}