{
  "type": "Feature",
  "properties": {
    "gn:admin1_code":"14.0",
    "gn:admin2_code":"1134.0",
    "gn:asciiname":"Roaldkvam",
    "gn:country_code":"NO",
    "gn:dem":78,
    "gn:feature_class":"P",
    "gn:feature_code":"PPL",
    "gn:name":"Roaldkvam",
    "gn:population":0,
    "gn:timezone":"Europe/Oslo",
    "iso:country":"NO",
    "wof:name":"Roaldkvam",
    "wof:placetype":"locality"
},
  "geometry": {"coordinates":[6.86667,59.65],"type":"Point"}
}