{
  "type": "Feature",
  "properties": {
    "iso:country":"NO",
    "name:bar_x_preferred":[
        "Bremanger"
    ],
    "name:bpy_x_preferred":[
        "\u09ac\u09cd\u09b0\u09c7\u09ae\u09be\u0999\u09cd\u0997\u09c7\u09b0"
    ],
    "name:cat_x_preferred":[
        "Bremanger"
    ],
    "name:ceb_x_preferred":[
        "Bremanger"
    ],
    "name:dan_x_preferred":[
        "Bremanger"
    ],
    "name:deu_x_preferred":[
        "Bremanger"
    ],
    "name:epo_x_preferred":[
        "Bremanger"
    ],
    "name:eus_x_preferred":[
        "Bremanger"
    ],
    "name:fin_x_preferred":[
        "Bremanger"
    ],
    "name:fra_x_preferred":[
        "Bremanger"
    ],
    "name:ita_x_preferred":[
        "Bremanger"
    ],
    "name:jav_x_preferred":[
        "Bremanger"
    ],
    "name:lat_x_preferred":[
        "V\u00e5gs\u00f8y"
    ],
    "name:lim_x_preferred":[
        "Bremanger"
    ],
    "name:msa_x_preferred":[
        "Bremanger"
    ],
    "name:nds_x_preferred":[
        "Kommun Bremanger"
    ],
    "name:nld_x_preferred":[
        "Bremanger"
    ],
    "name:nno_x_preferred":[
        "Bremanger kommune"
    ],
    "name:nor_x_preferred":[
        "Bremanger"
    ],
    "name:pol_x_preferred":[
        "Bremanger"
    ],
    "name:por_x_preferred":[
        "Bremanger"
    ],
    "name:ron_x_preferred":[
        "Bremanger"
    ],
    "name:rus_x_preferred":[
        "\u0411\u0440\u0435\u043c\u0430\u043d\u0433\u0435\u0440"
    ],
    "name:slv_x_preferred":[
        "Bremanger"
    ],
    "name:sme_x_preferred":[
        "Bremanger"
    ],
    "name:spa_x_preferred":[
        "Bremanger"
    ],
    "name:sqi_x_preferred":[
        "Bremanger"
    ],
    "name:swe_x_preferred":[
        "Bremangers kommun"
    ],
    "name:war_x_preferred":[
        "Bremanger"
    ],
    "name:zho_x_preferred":[
        "\u5e03\u96f7\u8292\u5384"
    ],
    "qs_pg:aaroncc":"NO",
    "qs_pg:name":"Bremanger",
    "qs_pg:name_adm0":"Norge",
    "qs_pg:name_adm1":"Sogn og Fjordane Fylke",
    "qs_pg:photos":109,
    "qs_pg:photos_1k":22,
    "qs_pg:photos_9k":1,
    "qs_pg:photos_9r":3,
    "qs_pg:photos_all":109,
    "qs_pg:photos_sr":3,
    "qs_pg:pop_sr":0,
    "qs_pg:qs_pg_placetype":"locality",
    "qs_pg:qs_pg_placetype_gp":"Town",
    "qs_pg:woe_adm0":23424910,
    "woe:adm0_id":23424910,
    "woe:name_adm0":"Norge",
    "woe:name_adm1":"Sogn og Fjordane Fylke",
    "woe:placetype":"Town",
    "wof:name":"Bremanger",
    "wof:placetype":"locality"
},
  "geometry": {"coordinates":[4.968395,61.840083],"type":"Point"}
}