{
  "type": "Feature",
  "properties": {
    "iso:country":"NO",
    "qs_pg:aaroncc":"NO",
    "qs_pg:name":"Bremanger",
    "qs_pg:name_adm0":"Norge",
    "qs_pg:name_adm1":"Sogn og Fjordane Fylke",
    "qs_pg:photos":109,
    "qs_pg:photos_1k":22,
    "qs_pg:photos_9k":1,
    "qs_pg:photos_9r":3,
    "qs_pg:photos_all":109,
    "qs_pg:photos_sr":3,
    "qs_pg:pop_sr":0,
    "qs_pg:qs_pg_placetype":"locality",
    "qs_pg:qs_pg_placetype_gp":"Town",
    "qs_pg:woe_adm0":23424910,
    "woe:adm0_id":23424910,
    "woe:name_adm0":"Norge",
    "woe:name_adm1":"Sogn og Fjordane Fylke",
    "woe:placetype":"Town",
    "wof:name":"Bremanger",
    "wof:placetype":"locality"
},
  "geometry": {"coordinates":[4.968395,61.840083],"type":"Point"}
}