{
  "type": "Feature",
  "properties": {
    "gn:admin1_code":"7",
    "gn:admin2_code":"1223.0",
    "gn:asciiname":"Haland",
    "gn:cc2":"NO",
    "gn:country_code":"NO",
    "gn:dem":114,
    "gn:feature_class":"P",
    "gn:feature_code":"PPL",
    "gn:name":"H\u00e5land",
    "gn:population":0,
    "gn:timezone":"Europe/Oslo",
    "iso:country":"NO",
    "name:und_x_variant":[
        "Haaland",
        "H\u00e5land"
    ],
    "wof:name":"Haland",
    "wof:placetype":"locality"
},
  "geometry": {"coordinates":[5.41667,59.98333],"type":"Point"}
}