{
  "type": "Feature",
  "properties": {
    "gn:admin1_code":"15.0",
    "gn:admin2_code":"1418.0",
    "gn:asciiname":"Tjugum",
    "gn:country_code":"NO",
    "gn:dem":1,
    "gn:feature_class":"P",
    "gn:feature_code":"PPL",
    "gn:name":"Tjugum",
    "gn:population":0,
    "gn:timezone":"Europe/Oslo",
    "iso:country":"NO",
    "wof:name":"Tjugum",
    "wof:placetype":"locality"
},
  "geometry": {"coordinates":[6.55,61.21666999999999],"type":"Point"}
}