{
  "type": "Feature",
  "properties": {
    "gn:admin1_code":"5.0",
    "gn:admin2_code":"2012.0",
    "gn:asciiname":"Russehamn",
    "gn:cc2":"NO",
    "gn:country_code":"NO",
    "gn:dem":160,
    "gn:feature_class":"P",
    "gn:feature_code":"PPL",
    "gn:name":"Russehamn",
    "gn:population":0,
    "gn:timezone":"Europe/Oslo",
    "iso:country":"NO",
    "name:und_x_variant":[
        "Russehavn",
        "Russehamn"
    ],
    "wof:name":"Russehamn",
    "wof:placetype":"locality"
},
  "geometry": {"coordinates":[22.83333,70.33333],"type":"Point"}
}