{
  "type": "Feature",
  "properties": {
    "gn:admin1_code":"1",
    "gn:admin2_code":"235.0",
    "gn:asciiname":"Furuset",
    "gn:country_code":"NO",
    "gn:dem":160,
    "gn:feature_class":"P",
    "gn:feature_code":"PPL",
    "gn:name":"Furuset",
    "gn:population":0,
    "gn:timezone":"Europe/Oslo",
    "iso:country":"NO",
    "name:nor_x_preferred":[
        "Furuset"
    ],
    "name:pol_x_preferred":[
        "Furuset"
    ],
    "wof:name":"Furuset",
    "wof:placetype":"locality"
},
  "geometry": {"coordinates":[11.28333,60.15],"type":"Point"}
}