{
  "type": "Feature",
  "properties": {
    "gn:admin1_code":"21",
    "gn:admin2_code":"5052.0",
    "gn:asciiname":"Frovik",
    "gn:cc2":"NO",
    "gn:country_code":"NO",
    "gn:dem":-9999,
    "gn:feature_class":"P",
    "gn:feature_code":"PPL",
    "gn:name":"Fr\u00f8vik",
    "gn:population":0,
    "gn:timezone":"Europe/Oslo",
    "iso:country":"NO",
    "name:und_x_variant":[
        "Froviken",
        "Fr\u00f8vik"
    ],
    "wof:name":"Frovik",
    "wof:placetype":"locality"
},
  "geometry": {"coordinates":[11.66667,65.06667],"type":"Point"}
}