{
  "type": "Feature",
  "properties": {
    "gn:admin1_code":"7.0",
    "gn:admin2_code":"1228.0",
    "gn:asciiname":"Sandvin",
    "gn:cc2":"NO",
    "gn:country_code":"NO",
    "gn:dem":780,
    "gn:feature_class":"P",
    "gn:feature_code":"PPL",
    "gn:name":"Sandvin",
    "gn:population":0,
    "gn:timezone":"Europe/Oslo",
    "iso:country":"NO",
    "name:und_x_variant":[
        "Sandven",
        "Sandvin"
    ],
    "wof:name":"Sandvin",
    "wof:placetype":"locality"
},
  "geometry": {"coordinates":[6.56667,60.01667],"type":"Point"}
}