{
  "type": "Feature",
  "properties": {
    "gn:admin1_code":"15.0",
    "gn:admin2_code":"1412.0",
    "gn:asciiname":"Tangenes",
    "gn:cc2":"NO",
    "gn:country_code":"NO",
    "gn:dem":-9999,
    "gn:feature_class":"P",
    "gn:feature_code":"PPL",
    "gn:name":"Tangenes",
    "gn:population":0,
    "gn:timezone":"Europe/Oslo",
    "iso:country":"NO",
    "name:und_x_variant":[
        "Tangenesv\u00e5g",
        "Tangenes"
    ],
    "wof:name":"Tangenes",
    "wof:placetype":"locality"
},
  "geometry": {"coordinates":[4.73333,61.08333],"type":"Point"}
}