{
  "type": "Feature",
  "properties": {
    "gn:admin1_code":"6",
    "gn:admin2_code":"430.0",
    "gn:asciiname":"Brenn",
    "gn:country_code":"NO",
    "gn:dem":720,
    "gn:feature_class":"P",
    "gn:feature_code":"PPL",
    "gn:name":"Brenn",
    "gn:population":0,
    "gn:timezone":"Europe/Oslo",
    "iso:country":"NO",
    "wof:name":"Brenn",
    "wof:placetype":"locality"
},
  "geometry": {"coordinates":[10.23333,61.85],"type":"Point"}
}