{
  "type": "Feature",
  "properties": {
    "gn:admin1_code":"9.0",
    "gn:admin2_code":"1850.0",
    "gn:asciiname":"Dimbarasvuodna",
    "gn:country_code":"NO",
    "gn:dem":240,
    "gn:feature_class":"P",
    "gn:feature_code":"PPL",
    "gn:name":"Dimbar\u00e1svuodna",
    "gn:population":0,
    "gn:timezone":"Europe/Oslo",
    "iso:country":"NO",
    "name:nor_x_preferred":[
        "T\u00f8mmer\u00e5sfjorden"
    ],
    "name:smj_x_preferred":[
        "Dimbar\u00e1svuodna"
    ],
    "wof:name":"Dimbarasvuodna",
    "wof:placetype":"locality"
},
  "geometry": {"coordinates":[16.47589,68.16446999999999],"type":"Point"}
}