{
  "type": "Feature",
  "properties": {
    "gn:admin1_code":"18.0",
    "gn:admin2_code":"1943.0",
    "gn:asciiname":"Seglvik",
    "gn:country_code":"NO",
    "gn:dem":100,
    "gn:feature_class":"P",
    "gn:feature_code":"PPL",
    "gn:name":"Seglvik",
    "gn:population":0,
    "gn:timezone":"Europe/Oslo",
    "iso:country":"NO",
    "wof:name":"Seglvik",
    "wof:placetype":"locality"
},
  "geometry": {"coordinates":[21.21672,70.20621],"type":"Point"}
}