{
  "type": "Feature",
  "properties": {
    "gn:admin1_code":"2.0",
    "gn:admin2_code":"929.0",
    "gn:asciiname":"Oland",
    "gn:country_code":"NO",
    "gn:dem":236,
    "gn:feature_class":"P",
    "gn:feature_code":"PPL",
    "gn:name":"Oland",
    "gn:population":0,
    "gn:timezone":"Europe/Oslo",
    "iso:country":"NO",
    "wof:name":"Oland",
    "wof:placetype":"locality"
},
  "geometry": {"coordinates":[8.36667,58.83333],"type":"Point"}
}