{
  "type": "Feature",
  "properties": {
    "gn:admin1_code":"21.0",
    "gn:admin2_code":"5004.0",
    "gn:asciiname":"Retlo",
    "gn:country_code":"NO",
    "gn:dem":40,
    "gn:feature_class":"P",
    "gn:feature_code":"PPL",
    "gn:name":"Retlo",
    "gn:population":0,
    "gn:timezone":"Europe/Oslo",
    "iso:country":"NO",
    "name:nor_x_preferred":[
        "Retlo"
    ],
    "wof:name":"Retlo",
    "wof:placetype":"locality"
},
  "geometry": {"coordinates":[11.64481,64.10099],"type":"Point"}
}