{
  "type": "Feature",
  "properties": {
    "gn:admin1_code":"19",
    "gn:admin2_code":"1003.0",
    "gn:asciiname":"Birkjenes",
    "gn:cc2":"NO",
    "gn:country_code":"NO",
    "gn:dem":15,
    "gn:feature_class":"P",
    "gn:feature_code":"PPL",
    "gn:name":"Birkjenes",
    "gn:population":0,
    "gn:timezone":"Europe/Oslo",
    "iso:country":"NO",
    "name:und_x_variant":[
        "Birkenes",
        "Birkjenes"
    ],
    "wof:name":"Birkjenes",
    "wof:placetype":"locality"
},
  "geometry": {"coordinates":[6.86667,58.08333],"type":"Point"}
}