{
  "type": "Feature",
  "properties": {
    "gn:admin1_code":"7.0",
    "gn:admin2_code":"1244.0",
    "gn:asciiname":"Rostoy",
    "gn:country_code":"NO",
    "gn:dem":3,
    "gn:feature_class":"P",
    "gn:feature_code":"PPL",
    "gn:name":"Rost\u00f8y",
    "gn:population":0,
    "gn:timezone":"Europe/Oslo",
    "iso:country":"NO",
    "name:und_x_variant":[
        "Rostoysund",
        "Rostog",
        "Rost\u00f8y"
    ],
    "wof:name":"Rostoy",
    "wof:placetype":"locality"
},
  "geometry": {"coordinates":[5.2051,60.08006999999999],"type":"Point"}
}