{
  "type": "Feature",
  "properties": {
    "gn:admin1_code":"8",
    "gn:admin2_code":"1502.0",
    "gn:asciiname":"Horsgard",
    "gn:cc2":"NO",
    "gn:country_code":"NO",
    "gn:dem":180,
    "gn:feature_class":"P",
    "gn:feature_code":"PPL",
    "gn:name":"Horsgard",
    "gn:population":0,
    "gn:timezone":"Europe/Oslo",
    "iso:country":"NO",
    "name:und_x_variant":[
        "Horsgaard",
        "Horsgora",
        "Horsgaardreiten",
        "Horsgard"
    ],
    "wof:name":"Horsgard",
    "wof:placetype":"locality"
},
  "geometry": {"coordinates":[7.63333,62.71666999999999],"type":"Point"}
}