{
  "type": "Feature",
  "properties": {
    "gn:admin1_code":"17.0",
    "gn:admin2_code":"829.0",
    "gn:asciiname":"Skarprud",
    "gn:cc2":"NO",
    "gn:country_code":"NO",
    "gn:dem":93,
    "gn:feature_class":"P",
    "gn:feature_code":"PPL",
    "gn:name":"Skarprud",
    "gn:population":0,
    "gn:timezone":"Europe/Oslo",
    "iso:country":"NO",
    "name:und_x_variant":[
        "Skaperud",
        "Skarperud",
        "Skarprud"
    ],
    "wof:name":"Skarprud",
    "wof:placetype":"locality"
},
  "geometry": {"coordinates":[8.46667,59.38333000000001],"type":"Point"}
}