{
  "type": "Feature",
  "properties": {
    "gn:admin1_code":"21.0",
    "gn:admin2_code":"5035.0",
    "gn:asciiname":"Palestina",
    "gn:country_code":"NO",
    "gn:dem":20,
    "gn:feature_class":"P",
    "gn:feature_code":"PPL",
    "gn:name":"Palestina",
    "gn:population":0,
    "gn:timezone":"Europe/Oslo",
    "iso:country":"NO",
    "name:nor_x_preferred":[
        "Palestina"
    ],
    "wof:name":"Palestina",
    "wof:placetype":"locality"
},
  "geometry": {"coordinates":[11.09122,63.45928000000001],"type":"Point"}
}