{
  "type": "Feature",
  "properties": {
    "gn:admin1_code":"9",
    "gn:admin2_code":"1833.0",
    "gn:asciiname":"Dunderland",
    "gn:country_code":"NO",
    "gn:dem":260,
    "gn:feature_class":"P",
    "gn:feature_code":"PPL",
    "gn:name":"Dunderland",
    "gn:population":0,
    "gn:timezone":"Europe/Oslo",
    "iso:country":"NO",
    "wof:name":"Dunderland",
    "wof:placetype":"locality"
},
  "geometry": {"coordinates":[14.83894,66.44561999999999],"type":"Point"}
}