{
  "type": "Feature",
  "properties": {
    "gn:admin1_code":"17.0",
    "gn:admin2_code":"834.0",
    "gn:asciiname":"Va",
    "gn:country_code":"NO",
    "gn:dem":686,
    "gn:feature_class":"P",
    "gn:feature_code":"PPL",
    "gn:name":"V\u00e5",
    "gn:population":0,
    "gn:timezone":"Europe/Oslo",
    "iso:country":"NO",
    "wof:name":"Va",
    "wof:placetype":"locality"
},
  "geometry": {"coordinates":[7.81667,59.75],"type":"Point"}
}