{
  "type": "Feature",
  "properties": {
    "gn:admin1_code":"6.0",
    "gn:admin2_code":"429.0",
    "gn:asciiname":"Nordsaetra",
    "gn:country_code":"NO",
    "gn:dem":860,
    "gn:feature_class":"P",
    "gn:feature_code":"PPL",
    "gn:name":"Nords\u00e6tra",
    "gn:population":0,
    "gn:timezone":"Europe/Oslo",
    "iso:country":"NO",
    "name:nor_x_preferred":[
        "Nords\u00e6tra"
    ],
    "wof:name":"Nordsaetra",
    "wof:placetype":"locality"
},
  "geometry": {"coordinates":[11.45104,61.38488],"type":"Point"}
}