{
  "type": "Feature",
  "properties": {
    "gn:admin1_code":"21.0",
    "gn:admin2_code":"5035.0",
    "gn:asciiname":"Bjorgan",
    "gn:country_code":"NO",
    "gn:dem":20,
    "gn:feature_class":"P",
    "gn:feature_code":"PPL",
    "gn:name":"Bj\u00f8rgan",
    "gn:population":0,
    "gn:timezone":"Europe/Oslo",
    "iso:country":"NO",
    "name:nor_x_preferred":[
        "Bj\u00f8rgan"
    ],
    "wof:name":"Bjorgan",
    "wof:placetype":"locality"
},
  "geometry": {"coordinates":[10.92493,63.43415],"type":"Point"}
}