{
  "type": "Feature",
  "properties": {
    "gn:admin1_code":"11.0",
    "gn:admin2_code":"538.0",
    "gn:asciiname":"Sluguasaetrene",
    "gn:country_code":"NO",
    "gn:dem":840,
    "gn:feature_class":"P",
    "gn:feature_code":"PPL",
    "gn:name":"Sluguas\u00e6trene",
    "gn:population":0,
    "gn:timezone":"Europe/Oslo",
    "iso:country":"NO",
    "name:nor_x_preferred":[
        "Sluguas\u00e6trene"
    ],
    "wof:name":"Sluguasaetrene",
    "wof:placetype":"locality"
},
  "geometry": {"coordinates":[9.82919,61.12956],"type":"Point"}
}