{
  "type": "Feature",
  "properties": {
    "gn:admin1_code":"8.0",
    "gn:admin2_code":"1551.0",
    "gn:asciiname":"Visnes",
    "gn:country_code":"NO",
    "gn:dem":15,
    "gn:feature_class":"P",
    "gn:feature_code":"PPL",
    "gn:name":"Visnes",
    "gn:population":0,
    "gn:timezone":"Europe/Oslo",
    "iso:country":"NO",
    "name:jav_x_preferred":[
        "Visnes"
    ],
    "name:msa_x_preferred":[
        "Visnes"
    ],
    "name:nor_x_preferred":[
        "Visnes"
    ],
    "wof:name":"Visnes",
    "wof:placetype":"locality"
},
  "geometry": {"coordinates":[7.4018,62.95409],"type":"Point"}
}