{
  "type": "Feature",
  "properties": {
    "gn:admin1_code":"19",
    "gn:admin2_code":"1003.0",
    "gn:asciiname":"Lindland",
    "gn:country_code":"NO",
    "gn:dem":207,
    "gn:feature_class":"P",
    "gn:feature_code":"PPL",
    "gn:name":"Lindland",
    "gn:population":0,
    "gn:timezone":"Europe/Oslo",
    "iso:country":"NO",
    "wof:name":"Lindland",
    "wof:placetype":"locality"
},
  "geometry": {"coordinates":[6.76667,58.11666999999999],"type":"Point"}
}