{
  "type": "Feature",
  "properties": {
    "gn:admin1_code":"19.0",
    "gn:admin2_code":"1001.0",
    "gn:asciiname":"Kuholmen",
    "gn:country_code":"NO",
    "gn:dem":12,
    "gn:feature_class":"P",
    "gn:feature_code":"PPL",
    "gn:name":"Kuholmen",
    "gn:population":0,
    "gn:timezone":"Europe/Oslo",
    "iso:country":"NO",
    "name:nor_x_preferred":[
        "Kuholmen"
    ],
    "wof:name":"Kuholmen",
    "wof:placetype":"locality"
},
  "geometry": {"coordinates":[8.0238,58.14414],"type":"Point"}
}