{
  "type": "Feature",
  "properties": {
    "gn:admin1_code":"4",
    "gn:admin2_code":"620.0",
    "gn:asciiname":"Myro",
    "gn:country_code":"NO",
    "gn:dem":960,
    "gn:feature_class":"P",
    "gn:feature_code":"PPL",
    "gn:name":"Myro",
    "gn:population":0,
    "gn:timezone":"Europe/Oslo",
    "iso:country":"NO",
    "wof:name":"Myro",
    "wof:placetype":"locality"
},
  "geometry": {"coordinates":[8.31667,60.61666999999999],"type":"Point"}
}