{
  "type": "Feature",
  "properties": {
    "gn:admin1_code":"15.0",
    "gn:admin2_code":"1438.0",
    "gn:asciiname":"Rugsund",
    "gn:country_code":"NO",
    "gn:dem":80,
    "gn:feature_class":"P",
    "gn:feature_code":"PPL",
    "gn:name":"Rugsund",
    "gn:population":0,
    "gn:timezone":"Europe/Oslo",
    "iso:country":"NO",
    "name:ceb_x_preferred":[
        "Rugsundet"
    ],
    "name:msa_x_preferred":[
        "Rugsund"
    ],
    "name:nor_x_preferred":[
        "Rugsund"
    ],
    "name:pol_x_preferred":[
        "Rugsund"
    ],
    "wof:name":"Rugsund",
    "wof:placetype":"locality"
},
  "geometry": {"coordinates":[5.33333,61.88333000000001],"type":"Point"}
}