{
  "type": "Feature",
  "properties": {
    "gn:admin1_code":"6",
    "gn:admin2_code":"432.0",
    "gn:asciiname":"Kvernnes",
    "gn:country_code":"NO",
    "gn:dem":320,
    "gn:feature_class":"P",
    "gn:feature_code":"PPL",
    "gn:name":"Kvernnes",
    "gn:population":0,
    "gn:timezone":"Europe/Oslo",
    "iso:country":"NO",
    "wof:name":"Kvernnes",
    "wof:placetype":"locality"
},
  "geometry": {"coordinates":[11.21667,61.73333],"type":"Point"}
}