{
  "type": "Feature",
  "properties": {
    "gn:admin1_code":"7",
    "gn:admin2_code":"1243.0",
    "gn:asciiname":"Lunde",
    "gn:country_code":"NO",
    "gn:dem":1,
    "gn:feature_class":"P",
    "gn:feature_code":"PPL",
    "gn:name":"Lunde",
    "gn:population":0,
    "gn:timezone":"Europe/Oslo",
    "iso:country":"NO",
    "name:ceb_x_preferred":[
        "Lunde"
    ],
    "name:dan_x_preferred":[
        "Lunde"
    ],
    "name:deu_x_preferred":[
        "Lunde"
    ],
    "name:fra_x_preferred":[
        "Lunde"
    ],
    "name:nld_x_preferred":[
        "Lunde"
    ],
    "name:nno_x_preferred":[
        "Lunde"
    ],
    "name:nor_x_preferred":[
        "Lunde"
    ],
    "name:rus_x_preferred":[
        "\u041b\u0443\u043d\u0434\u0435"
    ],
    "name:swe_x_preferred":[
        "Lunde"
    ],
    "wof:name":"Lunde",
    "wof:placetype":"neighbourhood"
},
  "geometry": {"coordinates":[5.45,60.16667],"type":"Point"}
}