{
  "type": "Feature",
  "properties": {
    "gn:admin1_code":"7",
    "gn:admin2_code":"1234.0",
    "gn:asciiname":"Lussand",
    "gn:country_code":"NO",
    "gn:dem":540,
    "gn:feature_class":"P",
    "gn:feature_code":"PPL",
    "gn:name":"Lussand",
    "gn:population":0,
    "gn:timezone":"Europe/Oslo",
    "iso:country":"NO",
    "wof:name":"Lussand",
    "wof:placetype":"locality"
},
  "geometry": {"coordinates":[6.55,60.46666999999999],"type":"Point"}
}