{
  "type": "Feature",
  "properties": {
    "gn:admin1_code":"21",
    "gn:admin2_code":"5051.0",
    "gn:asciiname":"Gravika",
    "gn:cc2":"NO",
    "gn:country_code":"NO",
    "gn:dem":100,
    "gn:feature_class":"P",
    "gn:feature_code":"PPL",
    "gn:name":"Gravika",
    "gn:population":0,
    "gn:timezone":"Europe/Oslo",
    "iso:country":"NO",
    "name:jav_x_preferred":[
        "Gravvik"
    ],
    "name:msa_x_preferred":[
        "Gravvik"
    ],
    "name:nor_x_preferred":[
        "Gravvik"
    ],
    "name:und_x_variant":[
        "Gravvika"
    ],
    "wof:name":"Gravika",
    "wof:placetype":"locality"
},
  "geometry": {"coordinates":[11.7712,64.98953],"type":"Point"}
}