{
  "type": "Feature",
  "properties": {
    "gn:admin1_code":"13.0",
    "gn:admin2_code":"128.0",
    "gn:asciiname":"Skantebygda",
    "gn:cc2":"NO",
    "gn:country_code":"NO",
    "gn:dem":120,
    "gn:feature_class":"P",
    "gn:feature_code":"PPL",
    "gn:name":"Skantebygda",
    "gn:population":0,
    "gn:timezone":"Europe/Oslo",
    "iso:country":"NO",
    "name:jav_x_preferred":[
        "Skantebygda"
    ],
    "name:msa_x_preferred":[
        "Skantebygda"
    ],
    "name:und_x_variant":[
        "Skantebygden",
        "Skantebygda"
    ],
    "wof:name":"Skantebygda",
    "wof:placetype":"locality"
},
  "geometry": {"coordinates":[11.24105,59.39616],"type":"Point"}
}