{
  "type": "Feature",
  "properties": {
    "gn:admin1_code":"21.0",
    "gn:admin2_code":"5005.0",
    "gn:asciiname":"Spillum",
    "gn:cc2":"NO",
    "gn:country_code":"NO",
    "gn:dem":40,
    "gn:feature_class":"P",
    "gn:feature_code":"PPL",
    "gn:name":"Spillum",
    "gn:population":0,
    "gn:timezone":"Europe/Oslo",
    "iso:country":"NO",
    "name:und_x_variant":[
        "Spill\u00e5m",
        "Spillum i Namdalen",
        "Spillum"
    ],
    "wof:name":"Spillum",
    "wof:placetype":"locality"
},
  "geometry": {"coordinates":[11.52126,64.44541],"type":"Point"}
}