{
  "type": "Feature",
  "properties": {
    "gn:admin1_code":"18",
    "gn:admin2_code":"1931",
    "gn:asciiname":"Husoy",
    "gn:country_code":"NO",
    "gn:dem":-9999,
    "gn:feature_class":"P",
    "gn:feature_code":"PPL",
    "gn:name":"Hus\u00f8y",
    "gn:population":0,
    "gn:timezone":"Europe/Oslo",
    "iso:country":"NO",
    "name:nor_x_preferred":[
        "Hus\u00f8y"
    ],
    "wof:name":"Husoy",
    "wof:placetype":"locality"
},
  "geometry": {"coordinates":[17.66368,69.54411],"type":"Point"}
}