{
  "type": "Feature",
  "properties": {
    "gn:admin1_code":"21",
    "gn:admin2_code":"5029.0",
    "gn:asciiname":"Myrin",
    "gn:country_code":"NO",
    "gn:dem":69,
    "gn:feature_class":"P",
    "gn:feature_code":"PPL",
    "gn:name":"Myrin",
    "gn:population":0,
    "gn:timezone":"Europe/Oslo",
    "iso:country":"NO",
    "name:nor_x_preferred":[
        "Myrin"
    ],
    "wof:name":"Myrin",
    "wof:placetype":"locality"
},
  "geometry": {"coordinates":[10.01667,63.26667],"type":"Point"}
}