{
  "type": "Feature",
  "properties": {
    "gn:country":"NO",
    "gn:fcode":"PPL",
    "gn:population":450,
    "iso:country":"NO",
    "name:ceb_x_preferred":[
        "Nordv\u00e5gen"
    ],
    "name:deu_x_preferred":[
        "Nordv\u00e5gen"
    ],
    "name:eng_x_preferred":[
        "Nordv\u00e5gen"
    ],
    "name:fra_x_preferred":[
        "Nordv\u00e5gen"
    ],
    "name:jav_x_preferred":[
        "Nordv\u00e5gen"
    ],
    "name:msa_x_preferred":[
        "Nordv\u00e5gen"
    ],
    "name:nld_x_preferred":[
        "Nordv\u00e5gen"
    ],
    "name:nno_x_preferred":[
        "Nordv\u00e5gen"
    ],
    "name:nob_x_preferred":[
        "Nordv\u00e5gen"
    ],
    "name:ron_x_preferred":[
        "Nordv\u00e5gen"
    ],
    "name:spa_x_preferred":[
        "Nordv\u00e5gen"
    ],
    "name:swe_x_preferred":[
        "Nordv\u00e5gen"
    ],
    "name:und_x_variant":[
        "Nordvaagen"
    ],
    "qs_pg:aaroncc":"NO",
    "qs_pg:gn_country":"NO",
    "qs_pg:gn_fcode":"PPL",
    "qs_pg:gn_pop":450,
    "qs_pg:name":"Nordv\u00e5gen",
    "qs_pg:name_adm0":"Norge",
    "qs_pg:name_adm1":"Finnmark Fylke",
    "qs_pg:photos":50,
    "qs_pg:photos_1k":10,
    "qs_pg:photos_9k":1,
    "qs_pg:photos_9r":2,
    "qs_pg:photos_all":50,
    "qs_pg:photos_sr":2,
    "qs_pg:pop_sr":2,
    "qs_pg:qs_pg_placetype":"locality",
    "qs_pg:qs_pg_placetype_gp":"Town",
    "qs_pg:woe_adm0":23424910,
    "woe:adm0_id":23424910,
    "woe:name_adm0":"Norge",
    "woe:name_adm1":"Finnmark Fylke",
    "woe:placetype":"Town",
    "wof:name":"Nordv\u00e5gen",
    "wof:placetype":"locality",
    "wof:population":450
},
  "geometry": {"coordinates":[26.03333,70.98333],"type":"Point"}
}