{
  "type": "Feature",
  "properties": {
    "gn:admin1_code":"8.0",
    "gn:admin2_code":"1539.0",
    "gn:asciiname":"Indre Siem",
    "gn:country_code":"NO",
    "gn:dem":140,
    "gn:feature_class":"P",
    "gn:feature_code":"PPL",
    "gn:name":"Indre Siem",
    "gn:population":0,
    "gn:timezone":"Europe/Oslo",
    "iso:country":"NO",
    "name:nor_x_preferred":[
        "Indre Siem"
    ],
    "wof:name":"Indre Siem",
    "wof:placetype":"locality"
},
  "geometry": {"coordinates":[7.56236,62.57988],"type":"Point"}
}