{
  "type": "Feature",
  "properties": {
    "gn:admin1_code":"15",
    "gn:admin2_code":"1432.0",
    "gn:asciiname":"Hjelle",
    "gn:country_code":"NO",
    "gn:dem":90,
    "gn:feature_class":"P",
    "gn:feature_code":"PPL",
    "gn:name":"Hjelle",
    "gn:population":0,
    "gn:timezone":"Europe/Oslo",
    "iso:country":"NO",
    "wof:name":"Hjelle",
    "wof:placetype":"locality"
},
  "geometry": {"coordinates":[5.91667,61.46666999999999],"type":"Point"}
}