{
  "type": "Feature",
  "properties": {
    "gn:country":"NO",
    "gn:fcode":"PPLA2",
    "gn:population":365,
    "iso:country":"NO",
    "name:cat_x_preferred":[
        "Vik"
    ],
    "name:ceb_x_preferred":[
        "Vik"
    ],
    "name:eng_x_preferred":[
        "Vik"
    ],
    "name:fra_x_preferred":[
        "Vik"
    ],
    "name:ita_x_preferred":[
        "Vik"
    ],
    "name:jav_x_preferred":[
        "Vik"
    ],
    "name:msa_x_preferred":[
        "Vik"
    ],
    "name:nld_x_preferred":[
        "Vik"
    ],
    "name:nno_x_preferred":[
        "Vik p\u00e5 Helgeland"
    ],
    "name:nob_x_preferred":[
        "Vik"
    ],
    "name:ron_x_preferred":[
        "Vik"
    ],
    "name:rus_x_preferred":[
        "\u0412\u0438\u043a"
    ],
    "name:spa_x_preferred":[
        "Vik"
    ],
    "name:swe_x_preferred":[
        "Vik"
    ],
    "name:und_x_variant":[
        "Vik i Helgeland"
    ],
    "qs_pg:aaroncc":"NO",
    "qs_pg:gn_country":"NO",
    "qs_pg:gn_fcode":"PPLA2",
    "qs_pg:gn_pop":365,
    "qs_pg:name":"Vik",
    "qs_pg:photos_9r":0,
    "qs_pg:photos_sr":0,
    "qs_pg:pop_sr":2,
    "qs_pg:qs_pg_placetype":"locality",
    "wof:name":"Vik",
    "wof:placetype":"locality",
    "wof:population":365
},
  "geometry": {"coordinates":[12.16734,65.31254],"type":"Point"}
}