{
  "type": "Feature",
  "properties": {
    "gn:admin1_code":"7.0",
    "gn:admin2_code":"1247.0",
    "gn:asciiname":"Tveit",
    "gn:country_code":"NO",
    "gn:dem":100,
    "gn:feature_class":"P",
    "gn:feature_code":"PPL",
    "gn:name":"Tveit",
    "gn:population":0,
    "gn:timezone":"Europe/Oslo",
    "iso:country":"NO",
    "name:ceb_x_preferred":[
        "Tveit"
    ],
    "name:dan_x_preferred":[
        "Tveit"
    ],
    "name:deu_x_preferred":[
        "Tveit"
    ],
    "name:msa_x_preferred":[
        "Tveit"
    ],
    "name:nld_x_preferred":[
        "Tveit"
    ],
    "name:nor_x_preferred":[
        "Tveit"
    ],
    "name:ron_x_preferred":[
        "Tveit"
    ],
    "name:spa_x_preferred":[
        "Tveit"
    ],
    "wof:name":"Tveit",
    "wof:placetype":"locality"
},
  "geometry": {"coordinates":[5.15,60.46666999999999],"type":"Point"}
}