{
  "type": "Feature",
  "properties": {
    "gn:admin1_code":"1.0",
    "gn:admin2_code":"237.0",
    "gn:asciiname":"Sorbakken",
    "gn:country_code":"NO",
    "gn:dem":392,
    "gn:feature_class":"P",
    "gn:feature_code":"PPL",
    "gn:name":"S\u00f8rbakken",
    "gn:population":0,
    "gn:timezone":"Europe/Oslo",
    "iso:country":"NO",
    "wof:name":"Sorbakken",
    "wof:placetype":"locality"
},
  "geometry": {"coordinates":[11.15,60.53333000000001],"type":"Point"}
}