{
  "type": "Feature",
  "properties": {
    "gn:admin1_code":"21.0",
    "gn:admin2_code":"5014.0",
    "gn:asciiname":"Rabben",
    "gn:country_code":"NO",
    "gn:dem":1,
    "gn:feature_class":"P",
    "gn:feature_code":"PPL",
    "gn:name":"Rabben",
    "gn:population":0,
    "gn:timezone":"Europe/Oslo",
    "iso:country":"NO",
    "name:nor_x_preferred":[
        "Rabben"
    ],
    "wof:name":"Rabben",
    "wof:placetype":"locality"
},
  "geometry": {"coordinates":[8.83976,63.72106],"type":"Point"}
}