{
  "type": "Feature",
  "properties": {
    "gn:admin1_code":"15.0",
    "gn:admin2_code":"1411.0",
    "gn:asciiname":"Risnes",
    "gn:cc2":"NO",
    "gn:country_code":"NO",
    "gn:dem":120,
    "gn:feature_class":"P",
    "gn:feature_code":"PPL",
    "gn:name":"Risnes",
    "gn:population":0,
    "gn:timezone":"Europe/Oslo",
    "iso:country":"NO",
    "name:und_x_variant":[
        "Risen\u00e6s",
        "Risenes",
        "Risnes"
    ],
    "wof:name":"Risnes",
    "wof:placetype":"locality"
},
  "geometry": {"coordinates":[5.05,61.05],"type":"Point"}
}