{
  "type": "Feature",
  "properties": {
    "gn:admin1_code":"9",
    "gn:admin2_code":"1866.0",
    "gn:asciiname":"Kjorstad",
    "gn:country_code":"NO",
    "gn:dem":-9999,
    "gn:feature_class":"P",
    "gn:feature_code":"PPL",
    "gn:name":"Kj\u00f8rstad",
    "gn:population":0,
    "gn:timezone":"Europe/Oslo",
    "iso:country":"NO",
    "wof:name":"Kjorstad",
    "wof:placetype":"locality"
},
  "geometry": {"coordinates":[14.93333,68.66667],"type":"Point"}
}