{
  "type": "Feature",
  "properties": {
    "gn:admin1_code":"7",
    "gn:admin2_code":"1201",
    "gn:asciiname":"Ortuflaten",
    "gn:country_code":"NO",
    "gn:dem":140,
    "gn:feature_class":"P",
    "gn:feature_code":"PPLL",
    "gn:name":"Ortuflaten",
    "gn:population":0,
    "gn:timezone":"Europe/Oslo",
    "iso:country":"NO",
    "name:nor_x_preferred":[
        "Ortuflaten"
    ],
    "wof:name":"Ortuflaten",
    "wof:placetype":"locality"
},
  "geometry": {"coordinates":[5.2982,60.34316999999999],"type":"Point"}
}