{
  "type": "Feature",
  "properties": {
    "gn:admin1_code":"1.0",
    "gn:admin2_code":"237.0",
    "gn:asciiname":"Dolihagen",
    "gn:country_code":"NO",
    "gn:dem":140,
    "gn:feature_class":"P",
    "gn:feature_code":"PPL",
    "gn:name":"D\u00f8lihagen",
    "gn:population":0,
    "gn:timezone":"Europe/Oslo",
    "iso:country":"NO",
    "name:nor_x_preferred":[
        "D\u00f8lihagen"
    ],
    "wof:name":"Dolihagen",
    "wof:placetype":"locality"
},
  "geometry": {"coordinates":[11.29399,60.28147],"type":"Point"}
}