{
  "type": "Feature",
  "properties": {
    "gn:admin1_code":"9",
    "gn:admin2_code":"1836.0",
    "gn:asciiname":"Jaegtvik",
    "gn:country_code":"NO",
    "gn:dem":3,
    "gn:feature_class":"P",
    "gn:feature_code":"PPL",
    "gn:name":"J\u00e6gtvik",
    "gn:population":0,
    "gn:timezone":"Europe/Oslo",
    "iso:country":"NO",
    "wof:name":"Jaegtvik",
    "wof:placetype":"locality"
},
  "geometry": {"coordinates":[13.28333,66.61667],"type":"Point"}
}