{
  "type": "Feature",
  "properties": {
    "gn:admin1_code":"1",
    "gn:admin2_code":"220",
    "gn:asciiname":"Risenga",
    "gn:country_code":"NO",
    "gn:dem":132,
    "gn:feature_class":"P",
    "gn:feature_code":"PPLL",
    "gn:name":"Risenga",
    "gn:population":0,
    "gn:timezone":"Europe/Oslo",
    "iso:country":"NO",
    "name:nor_x_preferred":[
        "Risenga"
    ],
    "wof:name":"Risenga",
    "wof:placetype":"locality"
},
  "geometry": {"coordinates":[10.43796,59.82633000000001],"type":"Point"}
}