{
  "type": "Feature",
  "properties": {
    "gn:admin1_code":"9.0",
    "gn:admin2_code":"1867.0",
    "gn:asciiname":"Sund",
    "gn:country_code":"NO",
    "gn:dem":20,
    "gn:feature_class":"P",
    "gn:feature_code":"PPL",
    "gn:name":"Sund",
    "gn:population":0,
    "gn:timezone":"Europe/Oslo",
    "iso:country":"NO",
    "wof:name":"Sund",
    "wof:placetype":"locality"
},
  "geometry": {"coordinates":[14.62915,68.74273000000001],"type":"Point"}
}