{
  "type": "Feature",
  "properties": {
    "gn:admin1_code":"9",
    "gn:admin2_code":"1860.0",
    "gn:asciiname":"Hagvagen",
    "gn:cc2":"NO",
    "gn:country_code":"NO",
    "gn:dem":10,
    "gn:feature_class":"P",
    "gn:feature_code":"PPL",
    "gn:name":"Hagv\u00e5gen",
    "gn:population":0,
    "gn:timezone":"Europe/Oslo",
    "iso:country":"NO",
    "name:und_x_variant":[
        "Hagevaag",
        "Haggv\u00e5g"
    ],
    "wof:name":"Hagvagen",
    "wof:placetype":"locality"
},
  "geometry": {"coordinates":[13.78145,68.25608000000001],"type":"Point"}
}