{
  "type": "Feature",
  "properties": {
    "iso:country":"NO",
    "name:ara_x_preferred":[
        "\u062a\u064a\u062f\u0627\u0644"
    ],
    "name:ast_x_preferred":[
        "Tydal"
    ],
    "name:bar_x_preferred":[
        "Tydal"
    ],
    "name:bpy_x_preferred":[
        "\u099f\u09be\u09af\u09bc\u09a1\u09be\u09b2"
    ],
    "name:bul_x_preferred":[
        "\u0422\u0439\u0434\u0430\u043b"
    ],
    "name:cat_x_preferred":[
        "Tydal"
    ],
    "name:ceb_x_preferred":[
        "Tydal"
    ],
    "name:dan_x_preferred":[
        "Tydal"
    ],
    "name:deu_x_preferred":[
        "Tydal"
    ],
    "name:eng_x_preferred":[
        "Tydal"
    ],
    "name:epo_x_preferred":[
        "Tydal"
    ],
    "name:eus_x_preferred":[
        "Tydal"
    ],
    "name:fin_x_preferred":[
        "Tydal"
    ],
    "name:fra_x_preferred":[
        "Tydal"
    ],
    "name:ita_x_preferred":[
        "Tydal"
    ],
    "name:lat_x_preferred":[
        "Tydal"
    ],
    "name:lim_x_preferred":[
        "Tydal"
    ],
    "name:msa_x_preferred":[
        "Tydal"
    ],
    "name:nan_x_preferred":[
        "Tydal"
    ],
    "name:nds_x_preferred":[
        "Kommun Tydal"
    ],
    "name:nld_x_preferred":[
        "Tydal"
    ],
    "name:nno_x_preferred":[
        "Tydal"
    ],
    "name:nob_x_preferred":[
        "Tydal"
    ],
    "name:pol_x_preferred":[
        "Tydal"
    ],
    "name:por_x_preferred":[
        "Tydal"
    ],
    "name:ron_x_preferred":[
        "Tydal"
    ],
    "name:rus_x_preferred":[
        "\u0422\u044e\u0434\u0430\u043b"
    ],
    "name:sme_x_preferred":[
        "Tydal"
    ],
    "name:spa_x_preferred":[
        "Tydal"
    ],
    "name:sqi_x_preferred":[
        "Tydal"
    ],
    "name:swa_x_preferred":[
        "Tydal"
    ],
    "name:swe_x_preferred":[
        "Tydal"
    ],
    "name:vie_x_preferred":[
        "Tydal"
    ],
    "name:war_x_preferred":[
        "Tydal"
    ],
    "name:zho_x_preferred":[
        "\u8482\u9054\u723e"
    ],
    "qs_pg:aaroncc":"NO",
    "qs_pg:name":"Tydal",
    "qs_pg:name_adm0":"Norge",
    "qs_pg:name_adm1":"S\u00f8r-Tr\u00f8ndelag Fylke",
    "qs_pg:photos":103,
    "qs_pg:photos_1k":21,
    "qs_pg:photos_9k":1,
    "qs_pg:photos_9r":3,
    "qs_pg:photos_all":103,
    "qs_pg:photos_sr":3,
    "qs_pg:pop_sr":0,
    "qs_pg:qs_pg_placetype":"locality",
    "qs_pg:qs_pg_placetype_gp":"Town",
    "qs_pg:woe_adm0":23424910,
    "woe:adm0_id":23424910,
    "woe:name_adm0":"Norge",
    "woe:name_adm1":"S\u00f8r-Tr\u00f8ndelag Fylke",
    "woe:placetype":"Town",
    "wof:name":"Tydal",
    "wof:placetype":"locality"
},
  "geometry": {"coordinates":[11.65306,63.049358],"type":"Point"}
}