{
  "type": "Feature",
  "properties": {
    "gn:admin1_code":"9",
    "gn:admin2_code":"1824.0",
    "gn:asciiname":"Alsgard",
    "gn:cc2":"NO",
    "gn:country_code":"NO",
    "gn:dem":360,
    "gn:feature_class":"P",
    "gn:feature_code":"PPL",
    "gn:name":"Alsgard",
    "gn:population":0,
    "gn:timezone":"Europe/Oslo",
    "iso:country":"NO",
    "name:und_x_variant":[
        "Alsgaarden",
        "Alsgard"
    ],
    "wof:name":"Alsgard",
    "wof:placetype":"locality"
},
  "geometry": {"coordinates":[13.31667,65.76666999999999],"type":"Point"}
}