{
  "type": "Feature",
  "properties": {
    "gn:admin1_code":"7.0",
    "gn:admin2_code":"1244.0",
    "gn:asciiname":"Vage",
    "gn:country_code":"NO",
    "gn:dem":18,
    "gn:feature_class":"P",
    "gn:feature_code":"PPL",
    "gn:name":"V\u00e5ge",
    "gn:population":0,
    "gn:timezone":"Europe/Oslo",
    "iso:country":"NO",
    "name:ceb_x_preferred":[
        "V\u00e5ge"
    ],
    "name:jav_x_preferred":[
        "V\u00e5ge"
    ],
    "name:msa_x_preferred":[
        "V\u00e5ge"
    ],
    "name:spa_x_preferred":[
        "V\u00e5ge"
    ],
    "name:swe_x_preferred":[
        "V\u00e5ge"
    ],
    "wof:name":"Vage",
    "wof:placetype":"locality"
},
  "geometry": {"coordinates":[5.07889,59.98556],"type":"Point"}
}