{
  "type": "Feature",
  "properties": {
    "gn:admin1_code":"18.0",
    "gn:admin2_code":"1923.0",
    "gn:asciiname":"Seljeskog",
    "gn:country_code":"NO",
    "gn:dem":171,
    "gn:feature_class":"P",
    "gn:feature_code":"PPL",
    "gn:name":"Seljeskog",
    "gn:population":0,
    "gn:timezone":"Europe/Oslo",
    "iso:country":"NO",
    "name:fra_x_preferred":[
        "Seljeskogen"
    ],
    "name:msa_x_preferred":[
        "Seljeskogen"
    ],
    "name:spa_x_preferred":[
        "Seljeskog"
    ],
    "wof:name":"Seljeskog",
    "wof:placetype":"locality"
},
  "geometry": {"coordinates":[17.86336,68.90524000000001],"type":"Point"}
}