{
  "type": "Feature",
  "properties": {
    "gn:admin1_code":"19.0",
    "gn:admin2_code":"1004.0",
    "gn:asciiname":"Ovre Fjellsa",
    "gn:cc2":"NO",
    "gn:country_code":"NO",
    "gn:dem":48,
    "gn:feature_class":"P",
    "gn:feature_code":"PPL",
    "gn:name":"\u00d8vre Fjells\u00e5",
    "gn:population":0,
    "gn:timezone":"Europe/Oslo",
    "iso:country":"NO",
    "name:und_x_variant":[
        "\u00d6vre Fjeldsaa",
        "\u00d8vre Fjells\u00e5"
    ],
    "wof:name":"Ovre Fjellsa",
    "wof:placetype":"locality"
},
  "geometry": {"coordinates":[6.56667,58.33333],"type":"Point"}
}