{
  "type": "Feature",
  "properties": {
    "gn:admin1_code":"4.0",
    "gn:admin2_code":"626.0",
    "gn:asciiname":"Kanada",
    "gn:country_code":"NO",
    "gn:dem":182,
    "gn:feature_class":"P",
    "gn:feature_code":"PPL",
    "gn:name":"Kanada",
    "gn:population":0,
    "gn:timezone":"Europe/Oslo",
    "iso:country":"NO",
    "name:bel_x_preferred":[
        "\u041a\u0430\u043d\u0430\u0434\u0430"
    ],
    "name:bul_x_preferred":[
        "\u041a\u0430\u043d\u0430\u0434\u0430"
    ],
    "name:ces_x_preferred":[
        "Kanada"
    ],
    "name:deu_x_preferred":[
        "Kanada"
    ],
    "name:ita_x_preferred":[
        "Kanada"
    ],
    "name:msa_x_preferred":[
        "Kanada"
    ],
    "name:nds_x_preferred":[
        "Kanada"
    ],
    "name:nor_x_preferred":[
        "Kanada"
    ],
    "name:pol_x_preferred":[
        "Kanada"
    ],
    "name:rus_x_preferred":[
        "\u041a\u0430\u043d\u0430\u0434\u0430"
    ],
    "name:ukr_x_preferred":[
        "\u041a\u0430\u043d\u0430\u0434\u0430"
    ],
    "wof:name":"Kanada",
    "wof:placetype":"locality"
},
  "geometry": {"coordinates":[10.23006,59.88857],"type":"Point"}
}