{
  "type": "Feature",
  "properties": {
    "gn:country":"NO",
    "iso:country":"NO",
    "qs_pg:aaroncc":"NO",
    "qs_pg:gn_country":"NO",
    "qs_pg:name":"Vestre Sand\u00f8ya",
    "qs_pg:name_adm0":"Norge",
    "qs_pg:name_adm1":"Aust-Agder Fylke",
    "qs_pg:photos":17,
    "qs_pg:photos_1k":3,
    "qs_pg:photos_9k":1,
    "qs_pg:photos_9r":1,
    "qs_pg:photos_all":17,
    "qs_pg:photos_sr":1,
    "qs_pg:pop_sr":0,
    "qs_pg:qs_pg_placetype":"locality",
    "qs_pg:qs_pg_placetype_gp":"Town",
    "qs_pg:woe_adm0":23424910,
    "woe:adm0_id":23424910,
    "woe:name_adm0":"Norge",
    "woe:name_adm1":"Aust-Agder Fylke",
    "woe:placetype":"Town",
    "wof:name":"Vestre Sand\u00f8ya",
    "wof:placetype":"locality"
},
  "geometry": {"coordinates":[9.064235,58.590445],"type":"Point"}
}