{
  "type": "Feature",
  "properties": {
    "gn:admin1_code":"5.0",
    "gn:admin2_code":"2021.0",
    "gn:asciiname":"Raidenjarga",
    "gn:country_code":"NO",
    "gn:dem":137,
    "gn:feature_class":"P",
    "gn:feature_code":"PPL",
    "gn:name":"R\u00e1idenj\u00e1rga",
    "gn:population":0,
    "gn:timezone":"Europe/Oslo",
    "iso:country":"NO",
    "name:sme_x_preferred":[
        "R\u00e1idenj\u00e1rga"
    ],
    "wof:name":"Raidenjarga",
    "wof:placetype":"locality"
},
  "geometry": {"coordinates":[25.80367,69.429],"type":"Point"}
}