{
  "type": "Feature",
  "properties": {
    "gn:admin1_code":"21.0",
    "gn:admin2_code":"5021.0",
    "gn:asciiname":"Snove",
    "gn:country_code":"NO",
    "gn:dem":500,
    "gn:feature_class":"P",
    "gn:feature_code":"PPL",
    "gn:name":"Sn\u00f8ve",
    "gn:population":0,
    "gn:timezone":"Europe/Oslo",
    "iso:country":"NO",
    "name:nor_x_preferred":[
        "Sn\u00f8ve"
    ],
    "wof:name":"Snove",
    "wof:placetype":"locality"
},
  "geometry": {"coordinates":[9.62603,62.57093],"type":"Point"}
}