{
  "type": "Feature",
  "properties": {
    "gn:admin1_code":"17",
    "gn:admin2_code":"833",
    "gn:asciiname":"Aslandmoen",
    "gn:country_code":"NO",
    "gn:dem":84,
    "gn:feature_class":"P",
    "gn:feature_code":"PPLL",
    "gn:name":"\u00c5slandmoen",
    "gn:population":0,
    "gn:timezone":"Europe/Oslo",
    "iso:country":"NO",
    "name:nor_x_preferred":[
        "\u00c5slandmoen"
    ],
    "wof:name":"Aslandmoen",
    "wof:placetype":"neighbourhood"
},
  "geometry": {"coordinates":[7.98492,59.44566],"type":"Point"}
}