{
  "type": "Feature",
  "properties": {
    "gn:admin1_code":"21",
    "gn:admin2_code":"5045.0",
    "gn:asciiname":"Aunfoss",
    "gn:country_code":"NO",
    "gn:dem":120,
    "gn:feature_class":"P",
    "gn:feature_code":"PPL",
    "gn:name":"Aunfoss",
    "gn:population":0,
    "gn:timezone":"Europe/Oslo",
    "iso:country":"NO",
    "name:nor_x_preferred":[
        "Aunfoss"
    ],
    "wof:name":"Aunfoss",
    "wof:placetype":"locality"
},
  "geometry": {"coordinates":[12.56667,64.61667],"type":"Point"}
}