{
  "type": "Feature",
  "properties": {
    "gn:country":"NO",
    "gn:fcode":"PPL",
    "gn:population":0,
    "iso:country":"NO",
    "name:bar_x_preferred":[
        "R\u00e5de"
    ],
    "name:bpy_x_preferred":[
        "\u09b0\u09be\u09a1\u09c7"
    ],
    "name:cat_x_preferred":[
        "R\u00e5de"
    ],
    "name:ceb_x_preferred":[
        "R\u00e5de"
    ],
    "name:dan_x_preferred":[
        "R\u00e5de"
    ],
    "name:deu_x_preferred":[
        "R\u00e5de"
    ],
    "name:epo_x_preferred":[
        "R\u00e5de"
    ],
    "name:est_x_preferred":[
        "R\u00e5de vald"
    ],
    "name:eus_x_preferred":[
        "R\u00e5de"
    ],
    "name:fin_x_preferred":[
        "R\u00e5de"
    ],
    "name:fra_x_preferred":[
        "R\u00e5de"
    ],
    "name:ind_x_preferred":[
        "R\u00e5de"
    ],
    "name:ita_x_preferred":[
        "R\u00e5de"
    ],
    "name:jav_x_preferred":[
        "R\u00e5de"
    ],
    "name:lat_x_preferred":[
        "R\u00e5de"
    ],
    "name:lim_x_preferred":[
        "R\u00e5de"
    ],
    "name:msa_x_preferred":[
        "R\u00e5de"
    ],
    "name:nds_x_preferred":[
        "Kommun R\u00e5de"
    ],
    "name:nld_x_preferred":[
        "R\u00e5de"
    ],
    "name:nno_x_preferred":[
        "R\u00e5de kommune"
    ],
    "name:nor_x_preferred":[
        "Karlshus"
    ],
    "name:nor_x_variant":[
        "R\u00e5de"
    ],
    "name:pol_x_preferred":[
        "R\u00e5de"
    ],
    "name:por_x_preferred":[
        "R\u00e5de"
    ],
    "name:ron_x_preferred":[
        "R\u00e5de"
    ],
    "name:rus_x_preferred":[
        "\u0420\u043e\u0434\u0435"
    ],
    "name:sme_x_preferred":[
        "R\u00e5de"
    ],
    "name:spa_x_preferred":[
        "R\u00e5de"
    ],
    "name:sqi_x_preferred":[
        "R\u00e5de"
    ],
    "name:swe_x_preferred":[
        "R\u00e5de kommun"
    ],
    "name:und_x_variant":[
        "Raade"
    ],
    "name:vie_x_preferred":[
        "R\u00e5de"
    ],
    "name:war_x_preferred":[
        "R\u00e5de"
    ],
    "name:zho_x_preferred":[
        "\u7f85\u5fb7"
    ],
    "qs_pg:aaroncc":"NO",
    "qs_pg:gn_country":"NO",
    "qs_pg:gn_fcode":"PPL",
    "qs_pg:gn_pop":0,
    "qs_pg:name":"R\u00e5de",
    "qs_pg:name_adm0":"Norge",
    "qs_pg:name_adm1":"\u00d8stfold Fylke",
    "qs_pg:photos":245,
    "qs_pg:photos_1k":50,
    "qs_pg:photos_9k":1,
    "qs_pg:photos_9r":4,
    "qs_pg:photos_all":245,
    "qs_pg:photos_sr":4,
    "qs_pg:pop_sr":0,
    "qs_pg:qs_pg_placetype":"locality",
    "qs_pg:qs_pg_placetype_gp":"Town",
    "qs_pg:woe_adm0":23424910,
    "woe:adm0_id":23424910,
    "woe:name_adm0":"Norge",
    "woe:name_adm1":"\u00d8stfold Fylke",
    "woe:placetype":"Town",
    "wof:name":"R\u00e5de",
    "wof:placetype":"locality"
},
  "geometry": {"coordinates":[10.85,59.35],"type":"Point"}
}