{
  "type": "Feature",
  "properties": {
    "gn:admin1_code":"7",
    "gn:admin2_code":"1211.0",
    "gn:asciiname":"Litledalen",
    "gn:cc2":"NO",
    "gn:country_code":"NO",
    "gn:dem":132,
    "gn:feature_class":"P",
    "gn:feature_code":"PPL",
    "gn:name":"Litledalen",
    "gn:population":0,
    "gn:timezone":"Europe/Oslo",
    "iso:country":"NO",
    "name:und_x_variant":[
        "Litledal",
        "Litledalen"
    ],
    "wof:name":"Litledalen",
    "wof:placetype":"locality"
},
  "geometry": {"coordinates":[6.06667,59.66667],"type":"Point"}
}