{
  "type": "Feature",
  "properties": {
    "gn:admin1_code":"6.0",
    "gn:admin2_code":"425.0",
    "gn:asciiname":"Sagmoroa",
    "gn:country_code":"NO",
    "gn:dem":199,
    "gn:feature_class":"P",
    "gn:feature_code":"PPL",
    "gn:name":"Sagmoroa",
    "gn:population":0,
    "gn:timezone":"Europe/Oslo",
    "iso:country":"NO",
    "name:nor_x_preferred":[
        "Sagmoroa"
    ],
    "wof:name":"Sagmoroa",
    "wof:placetype":"locality"
},
  "geometry": {"coordinates":[12.18228,60.67281],"type":"Point"}
}