{
  "type": "Feature",
  "properties": {
    "gn:admin1_code":"21",
    "gn:admin2_code":"5049.0",
    "gn:asciiname":"Dale",
    "gn:country_code":"NO",
    "gn:dem":140,
    "gn:feature_class":"P",
    "gn:feature_code":"PPL",
    "gn:name":"Dale",
    "gn:population":0,
    "gn:timezone":"Europe/Oslo",
    "iso:country":"NO",
    "name:nor_x_preferred":[
        "Dale"
    ],
    "wof:name":"Dale",
    "wof:placetype":"locality"
},
  "geometry": {"coordinates":[10.98333,64.45],"type":"Point"}
}