{
  "type": "Feature",
  "properties": {
    "gn:admin1_code":"21",
    "gn:admin2_code":"5049.0",
    "gn:asciiname":"Dale",
    "gn:country_code":"NO",
    "gn:dem":140,
    "gn:feature_class":"P",
    "gn:feature_code":"PPL",
    "gn:name":"Dale",
    "gn:population":0,
    "gn:timezone":"Europe/Oslo",
    "iso:country":"NO",
    "name:cat_x_preferred":[
        "Dale"
    ],
    "name:ceb_x_preferred":[
        "Dale"
    ],
    "name:ces_x_preferred":[
        "Dale"
    ],
    "name:cor_x_preferred":[
        "Dale"
    ],
    "name:dan_x_preferred":[
        "Dale"
    ],
    "name:deu_x_preferred":[
        "Dale"
    ],
    "name:fin_x_preferred":[
        "Dale"
    ],
    "name:fra_x_preferred":[
        "Dale"
    ],
    "name:ita_x_preferred":[
        "Dale"
    ],
    "name:jpn_x_preferred":[
        "\u30c7\u30a4\u30eb"
    ],
    "name:nds_x_preferred":[
        "Dale"
    ],
    "name:nld_x_preferred":[
        "Dale"
    ],
    "name:nno_x_preferred":[
        "Dale"
    ],
    "name:nor_x_preferred":[
        "Dale"
    ],
    "name:pol_x_preferred":[
        "Dale"
    ],
    "name:por_x_preferred":[
        "Dale"
    ],
    "name:rus_x_preferred":[
        "\u0414\u0435\u0439\u043b"
    ],
    "name:spa_x_preferred":[
        "Dale"
    ],
    "name:srp_x_preferred":[
        "\u0414\u0435\u0458\u043b"
    ],
    "name:swe_x_preferred":[
        "Dale"
    ],
    "name:ukr_x_preferred":[
        "\u0414\u0435\u0439\u043b"
    ],
    "wof:name":"Dale",
    "wof:placetype":"locality"
},
  "geometry": {"coordinates":[10.98333,64.45],"type":"Point"}
}