{
  "type": "Feature",
  "properties": {
    "gn:admin1_code":"17",
    "gn:admin2_code":"819.0",
    "gn:asciiname":"Hjontvet",
    "gn:country_code":"NO",
    "gn:dem":186,
    "gn:feature_class":"P",
    "gn:feature_code":"PPL",
    "gn:name":"Hj\u00f8ntvet",
    "gn:population":0,
    "gn:timezone":"Europe/Oslo",
    "iso:country":"NO",
    "wof:name":"Hjontvet",
    "wof:placetype":"locality"
},
  "geometry": {"coordinates":[9.33333,59.25],"type":"Point"}
}