{
  "type": "Feature",
  "properties": {
    "gn:admin1_code":"5",
    "gn:admin2_code":"2030",
    "gn:asciiname":"Hessenki",
    "gn:country_code":"NO",
    "gn:dem":60,
    "gn:feature_class":"P",
    "gn:feature_code":"PPLL",
    "gn:name":"Hessenki",
    "gn:population":0,
    "gn:timezone":"Europe/Oslo",
    "iso:country":"NO",
    "name:cat_x_preferred":[
        "Hesseng"
    ],
    "name:fkv_x_preferred":[
        "Hessenki"
    ],
    "name:fra_x_preferred":[
        "Hesseng"
    ],
    "name:jav_x_preferred":[
        "Hesseng"
    ],
    "name:msa_x_preferred":[
        "Hesseng"
    ],
    "name:nld_x_preferred":[
        "Hesseng"
    ],
    "name:nno_x_preferred":[
        "Hesseng"
    ],
    "name:nor_x_preferred":[
        "Hesseng"
    ],
    "name:ron_x_preferred":[
        "Hesseng"
    ],
    "name:rus_x_preferred":[
        "\u0425\u0435\u0441\u0441\u0435\u043d\u0433"
    ],
    "name:spa_x_preferred":[
        "Hesseng"
    ],
    "name:swe_x_preferred":[
        "Hesseng"
    ],
    "wof:name":"Hessenki",
    "wof:placetype":"locality"
},
  "geometry": {"coordinates":[29.98817,69.68753000000001],"type":"Point"}
}