{
  "type": "Feature",
  "properties": {
    "gn:admin1_code":"5.0",
    "gn:admin2_code":"2030.0",
    "gn:asciiname":"Neiden,ovre",
    "gn:country_code":"NO",
    "gn:dem":57,
    "gn:feature_class":"P",
    "gn:feature_code":"PPL",
    "gn:name":"Neiden,\u00f8vre",
    "gn:population":0,
    "gn:timezone":"Europe/Oslo",
    "iso:country":"NO",
    "name:fkv_x_preferred":[
        "Yli-N\u00e4\u00e4t\u00e4m\u00f6"
    ],
    "name:nor_x_preferred":[
        "Neiden,\u00f8vre"
    ],
    "name:nor_x_variant":[
        "\u00d8vre Neiden",
        "Veines"
    ],
    "name:sme_x_preferred":[
        "P\u00e5\u014bjjel-Njaudd\u00e1m"
    ],
    "name:sme_x_variant":[
        "Baddjenjavdan",
        "Badjenj\u00e1vd\u00e1n"
    ],
    "wof:name":"Neiden,ovre",
    "wof:placetype":"locality"
},
  "geometry": {"coordinates":[29.25099,69.70140000000001],"type":"Point"}
}