{
  "type": "Feature",
  "properties": {
    "gn:admin1_code":"8.0",
    "gn:admin2_code":"1515.0",
    "gn:asciiname":"Myrvag",
    "gn:country_code":"NO",
    "gn:dem":22,
    "gn:feature_class":"P",
    "gn:feature_code":"PPL",
    "gn:name":"Myrv\u00e5g",
    "gn:population":0,
    "gn:timezone":"Europe/Oslo",
    "iso:country":"NO",
    "name:nor_x_preferred":[
        "Myrv\u00e5g"
    ],
    "wof:name":"Myrvag",
    "wof:placetype":"locality"
},
  "geometry": {"coordinates":[5.79763,62.2784],"type":"Point"}
}