{
  "type": "Feature",
  "properties": {
    "iso:country":"NO",
    "name:eng_x_preferred":[
        "Varteig"
    ],
    "name:fra_x_preferred":[
        "Varteig"
    ],
    "name:jav_x_preferred":[
        "Varteig"
    ],
    "name:msa_x_preferred":[
        "Varteig"
    ],
    "name:nld_x_preferred":[
        "Varteig"
    ],
    "name:nob_x_preferred":[
        "Varteig"
    ],
    "name:rus_x_preferred":[
        "\u0412\u0430\u0440\u0442\u0435\u0439\u0433"
    ],
    "qs_pg:aaroncc":"NO",
    "qs_pg:name":"Varteig",
    "qs_pg:name_adm0":"Norge",
    "qs_pg:name_adm1":"\u00d8stfold Fylke",
    "qs_pg:photos":9,
    "qs_pg:photos_1k":2,
    "qs_pg:photos_9k":1,
    "qs_pg:photos_9r":1,
    "qs_pg:photos_all":9,
    "qs_pg:photos_sr":1,
    "qs_pg:pop_sr":0,
    "qs_pg:qs_pg_placetype":"locality",
    "qs_pg:qs_pg_placetype_gp":"Town",
    "qs_pg:woe_adm0":23424910,
    "woe:adm0_id":23424910,
    "woe:name_adm0":"Norge",
    "woe:name_adm1":"\u00d8stfold Fylke",
    "woe:placetype":"Town",
    "wof:name":"Varteig",
    "wof:placetype":"locality"
},
  "geometry": {"coordinates":[11.184382,59.356733],"type":"Point"}
}