{
  "type": "Feature",
  "properties": {
    "gn:admin1_code":"5.0",
    "gn:admin2_code":"2021.0",
    "gn:asciiname":"Vullosnjarga",
    "gn:country_code":"NO",
    "gn:dem":140,
    "gn:feature_class":"P",
    "gn:feature_code":"PPL",
    "gn:name":"Vullo\u0161nj\u00e1rga",
    "gn:population":0,
    "gn:timezone":"Europe/Oslo",
    "iso:country":"NO",
    "name:sme_x_preferred":[
        "Vullo\u0161nj\u00e1rga"
    ],
    "wof:name":"Vullosnjarga",
    "wof:placetype":"locality"
},
  "geometry": {"coordinates":[25.48074,69.46225],"type":"Point"}
}