{
  "type": "Feature",
  "properties": {
    "gn:admin1_code":"20",
    "gn:admin2_code":"711",
    "gn:asciiname":"Blindsand",
    "gn:country_code":"NO",
    "gn:dem":11,
    "gn:feature_class":"P",
    "gn:feature_code":"PPLL",
    "gn:name":"Blindsand",
    "gn:population":0,
    "gn:timezone":"Europe/Oslo",
    "iso:country":"NO",
    "name:nor_x_preferred":[
        "Blindsand"
    ],
    "wof:name":"Blindsand",
    "wof:placetype":"locality"
},
  "geometry": {"coordinates":[10.38258,59.53856],"type":"Point"}
}