{
  "type": "Feature",
  "properties": {
    "gn:admin1_code":"6",
    "gn:admin2_code":"417.0",
    "gn:asciiname":"Horne",
    "gn:country_code":"NO",
    "gn:dem":150,
    "gn:feature_class":"P",
    "gn:feature_code":"PPL",
    "gn:name":"Horne",
    "gn:population":0,
    "gn:timezone":"Europe/Oslo",
    "iso:country":"NO",
    "name:ceb_x_preferred":[
        "Horne"
    ],
    "name:dan_x_preferred":[
        "Horne"
    ],
    "name:deu_x_preferred":[
        "Horne"
    ],
    "name:fra_x_preferred":[
        "Horne"
    ],
    "name:ita_x_preferred":[
        "Horne"
    ],
    "name:nds_x_preferred":[
        "Horne"
    ],
    "name:nld_x_preferred":[
        "Horne"
    ],
    "name:swe_x_preferred":[
        "Horne"
    ],
    "wof:name":"Horne",
    "wof:placetype":"locality"
},
  "geometry": {"coordinates":[11.21667,60.76667],"type":"Point"}
}