{
  "type": "Feature",
  "properties": {
    "gn:population":960,
    "iso:country":"NO",
    "name:ast_x_preferred":[
        "Sveio"
    ],
    "name:bpy_x_preferred":[
        "\u09b8\u09ad\u09c7\u0987\u0993"
    ],
    "name:cat_x_preferred":[
        "Sveio"
    ],
    "name:ceb_x_preferred":[
        "Sveio"
    ],
    "name:dan_x_preferred":[
        "Sveio"
    ],
    "name:deu_x_preferred":[
        "Sveio"
    ],
    "name:eng_x_preferred":[
        "Sveio"
    ],
    "name:epo_x_preferred":[
        "Sveio"
    ],
    "name:eus_x_preferred":[
        "Sveio"
    ],
    "name:fin_x_preferred":[
        "Sveio"
    ],
    "name:fra_x_preferred":[
        "Sveio"
    ],
    "name:ita_x_preferred":[
        "Sveio"
    ],
    "name:jav_x_preferred":[
        "Sveio"
    ],
    "name:lat_x_preferred":[
        "Sveio"
    ],
    "name:lim_x_preferred":[
        "Sveio"
    ],
    "name:msa_x_preferred":[
        "Sveio"
    ],
    "name:nan_x_preferred":[
        "Sveio"
    ],
    "name:nds_x_preferred":[
        "Kommun Sveio"
    ],
    "name:nld_x_preferred":[
        "Sveio"
    ],
    "name:nno_x_preferred":[
        "Sveio kommune"
    ],
    "name:nno_x_variant":[
        "Sveio"
    ],
    "name:nob_x_preferred":[
        "Sveio"
    ],
    "name:nor_x_preferred":[
        "Sveio"
    ],
    "name:nor_x_variant":[
        "Sveios"
    ],
    "name:oci_x_preferred":[
        "Sveio"
    ],
    "name:pol_x_preferred":[
        "Sveio"
    ],
    "name:por_x_preferred":[
        "Sveio"
    ],
    "name:ron_x_preferred":[
        "Sveio"
    ],
    "name:rus_x_preferred":[
        "\u0421\u0432\u0435\u0439\u0443"
    ],
    "name:slv_x_preferred":[
        "Sveio"
    ],
    "name:sme_x_preferred":[
        "Sveio"
    ],
    "name:spa_x_preferred":[
        "Sveio"
    ],
    "name:sqi_x_preferred":[
        "Sveio"
    ],
    "name:swa_x_preferred":[
        "Sveio"
    ],
    "name:swe_x_preferred":[
        "Sveio kommun"
    ],
    "name:swe_x_variant":[
        "Sveio"
    ],
    "name:vie_x_preferred":[
        "Sveio"
    ],
    "name:war_x_preferred":[
        "Sveio"
    ],
    "name:zho_min_nan_x_preferred":[
        "Sveio"
    ],
    "name:zho_x_preferred":[
        "\u65af\u97cb\u5967"
    ],
    "qs:a0":"Norge",
    "qs:a1":"*Hordaland",
    "qs:a1r":"0",
    "qs:adm0":"Norge",
    "qs:la_lc":"*",
    "qs:level":"locality",
    "qs:loc":"Sveio",
    "qs:loc_alt":"Sveio",
    "qs:pop":0,
    "qs:type":"buffered point",
    "wd:wordcount":829,
    "wof:lang":[
        "nor"
    ],
    "wof:name":"Sveio",
    "wof:placetype":"locality",
    "wof:population":960
},
  "geometry": {"coordinates":[5.338089,59.541202],"type":"Point"}
}