{
  "type": "Feature",
  "properties": {
    "gn:admin1_code":"15",
    "gn:admin2_code":"1417.0",
    "gn:asciiname":"Fjaerestad",
    "gn:country_code":"NO",
    "gn:dem":436,
    "gn:feature_class":"P",
    "gn:feature_code":"PPL",
    "gn:name":"Fj\u00e6restad",
    "gn:population":0,
    "gn:timezone":"Europe/Oslo",
    "iso:country":"NO",
    "wof:name":"Fjaerestad",
    "wof:placetype":"locality"
},
  "geometry": {"coordinates":[6.53333,61.05],"type":"Point"}
}