{
  "type": "Feature",
  "properties": {
    "gn:admin1_code":"19",
    "gn:admin2_code":"1017.0",
    "gn:asciiname":"Djubesland",
    "gn:cc2":"NO",
    "gn:country_code":"NO",
    "gn:dem":301,
    "gn:feature_class":"P",
    "gn:feature_code":"PPL",
    "gn:name":"Djubesland",
    "gn:population":0,
    "gn:timezone":"Europe/Oslo",
    "iso:country":"NO",
    "name:und_x_variant":[
        "Diubesland"
    ],
    "wof:name":"Djubesland",
    "wof:placetype":"locality"
},
  "geometry": {"coordinates":[7.62277,58.29977],"type":"Point"}
}