{
  "type": "Feature",
  "properties": {
    "gn:gn_country":"NO",
    "gn:gn_fcode":"PPL",
    "gn:gn_pop":304,
    "gn:population":304,
    "iso:country":"NO",
    "name:eng_x_preferred":[
        "Utg\u00e5rd"
    ],
    "name:fra_x_preferred":[
        "Utg\u00e5rd"
    ],
    "name:jav_x_preferred":[
        "Utg\u00e5rd"
    ],
    "name:msa_x_preferred":[
        "Utg\u00e5rd"
    ],
    "name:nld_x_preferred":[
        "Utg\u00e5rd"
    ],
    "name:nno_x_preferred":[
        "Utg\u00e5rd"
    ],
    "name:nob_x_preferred":[
        "Utg\u00e5rd"
    ],
    "name:ron_x_preferred":[
        "Utg\u00e5rd"
    ],
    "name:spa_x_preferred":[
        "Utg\u00e5rd"
    ],
    "name:unk_x_variant":[
        "Utgaard"
    ],
    "qs_pg:aaroncc":"NO",
    "qs_pg:gn_country":"NO",
    "qs_pg:gn_fcode":"PPL",
    "qs_pg:gn_pop":304,
    "qs_pg:name":"Utg\u00e5rd",
    "qs_pg:name_adm0":"Norge",
    "qs_pg:name_adm1":"\u00d8stfold Fylke",
    "qs_pg:photos_9k":1,
    "qs_pg:photos_9r":3,
    "qs_pg:photos_all":86,
    "qs_pg:photos_sr":0,
    "qs_pg:pop_sr":2,
    "qs_pg:qs_pg_placetype":"locality",
    "qs_pg:qs_pg_placetype_gp":"Town",
    "qs_pg:woe_adm0":23424910,
    "woe:adm0_id":23424910,
    "woe:name_adm0":"Norge",
    "woe:name_adm1":"\u00d8stfold Fylke",
    "woe:placetype":"Town",
    "wof:name":"Utg\u00e5rd",
    "wof:placetype":"locality",
    "wof:population":304
},
  "geometry": {"coordinates":[10.86667,59.08333],"type":"Point"}
}