{
  "type": "Feature",
  "properties": {
    "gn:admin1_code":"9.0",
    "gn:admin2_code":"1849.0",
    "gn:asciiname":"Uteid",
    "gn:country_code":"NO",
    "gn:dem":100,
    "gn:feature_class":"P",
    "gn:feature_code":"PPL",
    "gn:name":"Uteid",
    "gn:population":0,
    "gn:timezone":"Europe/Oslo",
    "iso:country":"NO",
    "wof:name":"Uteid",
    "wof:placetype":"locality"
},
  "geometry": {"coordinates":[15.59306,68.08360999999999],"type":"Point"}
}