{
  "type": "Feature",
  "properties": {
    "gn:admin1_code":"9",
    "gn:admin2_code":"1833.0",
    "gn:asciiname":"Bjornbaervika",
    "gn:cc2":"NO",
    "gn:country_code":"NO",
    "gn:dem":300,
    "gn:feature_class":"P",
    "gn:feature_code":"PPL",
    "gn:name":"Bj\u00f8rnb\u00e6rvika",
    "gn:population":0,
    "gn:timezone":"Europe/Oslo",
    "iso:country":"NO",
    "name:und_x_variant":[
        "Bj\u00f6rnb\u00e6rviken",
        "Bj\u00f8rnb\u00e6rvika"
    ],
    "wof:name":"Bjornbaervika",
    "wof:placetype":"neighbourhood"
},
  "geometry": {"coordinates":[14.05,66.28333000000001],"type":"Point"}
}