{
  "type": "Feature",
  "properties": {
    "gn:country":"NO",
    "gn:fcode":"PPLA2",
    "gn:population":0,
    "iso:country":"NO",
    "name:ara_x_preferred":[
        "\u0643\u0641\u0627\u0644\u0633\u0648\u0646\u062f"
    ],
    "name:bar_x_preferred":[
        "Kvalsund"
    ],
    "name:bpy_x_preferred":[
        "\u0995\u09ad\u09be\u09b2\u09b8\u09c1\u09a8\u09cd\u09a1"
    ],
    "name:cat_x_preferred":[
        "Kvalsund"
    ],
    "name:ceb_x_preferred":[
        "Kvalsund"
    ],
    "name:dan_x_preferred":[
        "Kvalsund"
    ],
    "name:deu_x_preferred":[
        "Kvalsund"
    ],
    "name:epo_x_preferred":[
        "Kvalsund"
    ],
    "name:est_x_preferred":[
        "Kvalsundi vald"
    ],
    "name:eus_x_preferred":[
        "Kvalsund"
    ],
    "name:fas_x_preferred":[
        "\u06a9\u0648\u0627\u0644\u0633\u0648\u0646\u062f"
    ],
    "name:fin_x_preferred":[
        "Kvalsund"
    ],
    "name:fra_x_preferred":[
        "Kvalsund"
    ],
    "name:hye_x_preferred":[
        "\u053f\u057e\u0561\u056c\u057d\u0578\u0582\u0576"
    ],
    "name:ita_x_preferred":[
        "Kvalsund"
    ],
    "name:jav_x_preferred":[
        "Kvalsund"
    ],
    "name:lat_x_preferred":[
        "Kvalsund"
    ],
    "name:lim_x_preferred":[
        "Kvalsund"
    ],
    "name:msa_x_preferred":[
        "Kvalsund"
    ],
    "name:nds_x_preferred":[
        "Kommun Kvalsund"
    ],
    "name:nld_x_preferred":[
        "Kvalsund"
    ],
    "name:nno_x_preferred":[
        "Kvalsund"
    ],
    "name:nno_x_variant":[
        "Kvalsund kommune"
    ],
    "name:nor_x_preferred":[
        "Kvalsund"
    ],
    "name:pol_x_preferred":[
        "Kvalsund"
    ],
    "name:por_x_preferred":[
        "Kvalsund"
    ],
    "name:ron_x_preferred":[
        "Kvalsund"
    ],
    "name:rus_x_preferred":[
        "\u041a\u0432\u0430\u043b\u0441\u0443\u043d\u043d"
    ],
    "name:slv_x_preferred":[
        "Kvalsund"
    ],
    "name:sme_x_preferred":[
        "R\u00e1hkker\u00e1vju"
    ],
    "name:sme_x_variant":[
        "Rakkeravjo",
        "F\u00e1lesnuorri"
    ],
    "name:spa_x_preferred":[
        "Kvalsund"
    ],
    "name:sqi_x_preferred":[
        "Kvalsund"
    ],
    "name:swe_x_preferred":[
        "Kvalsunds kommun"
    ],
    "name:vie_x_preferred":[
        "Kvalsund"
    ],
    "name:war_x_preferred":[
        "Kvalsund"
    ],
    "name:zho_x_preferred":[
        "\u514b\u74e6\u723e\u677e"
    ],
    "qs_pg:aaroncc":"NO",
    "qs_pg:gn_country":"NO",
    "qs_pg:gn_fcode":"PPLA2",
    "qs_pg:gn_pop":0,
    "qs_pg:name":"Kvalsund",
    "qs_pg:photos_9r":0,
    "qs_pg:photos_sr":0,
    "qs_pg:pop_sr":0,
    "qs_pg:qs_pg_placetype":"locality",
    "wof:name":"Kvalsund",
    "wof:placetype":"locality"
},
  "geometry": {"coordinates":[23.97974,70.50270999999999],"type":"Point"}
}