{
  "type": "Feature",
  "properties": {
    "gn:gn_country":"NO",
    "gn:gn_fcode":"PPLA2",
    "gn:gn_pop":0,
    "iso:country":"NO",
    "name:bpy_x_preferred":[
        "\u0995\u09ad\u09be\u09b2\u09b8\u09c1\u09a8\u09cd\u09a1"
    ],
    "name:est_x_preferred":[
        "Kvalsundi vald"
    ],
    "name:nds_x_preferred":[
        "Kommun Kvalsund"
    ],
    "name:nno_x_preferred":[
        "Kvalsund"
    ],
    "name:nor_x_preferred":[
        "Kvalsund"
    ],
    "name:rus_x_preferred":[
        "\u041a\u0432\u0430\u043b\u0441\u0443\u043d\u043d"
    ],
    "name:sme_x_preferred":[
        "R\u00e1hkker\u00e1vju"
    ],
    "name:sme_x_variant":[
        "Rakkeravjo",
        "F\u00e1lesnuorri"
    ],
    "name:swe_x_preferred":[
        "Kvalsunds kommun"
    ],
    "name:zho_x_preferred":[
        "\u514b\u74e6\u723e\u677e"
    ],
    "qs_pg:aaroncc":"NO",
    "qs_pg:gn_country":"NO",
    "qs_pg:gn_fcode":"PPLA2",
    "qs_pg:gn_pop":0,
    "qs_pg:name":"Kvalsund",
    "qs_pg:photos_9r":0,
    "qs_pg:photos_sr":0,
    "qs_pg:pop_sr":0,
    "qs_pg:qs_pg_placetype":"locality",
    "wof:name":"Kvalsund",
    "wof:placetype":"locality"
},
  "geometry": {"coordinates":[23.97974,70.50270999999999],"type":"Point"}
}