{
  "type": "Feature",
  "properties": {
    "gn:admin1_code":"8",
    "gn:admin2_code":"1548.0",
    "gn:asciiname":"Gjerdet",
    "gn:country_code":"NO",
    "gn:dem":20,
    "gn:feature_class":"P",
    "gn:feature_code":"PPL",
    "gn:name":"Gjerdet",
    "gn:population":0,
    "gn:timezone":"Europe/Oslo",
    "iso:country":"NO",
    "wof:name":"Gjerdet",
    "wof:placetype":"locality"
},
  "geometry": {"coordinates":[7.01667,62.95],"type":"Point"}
}