{
  "type": "Feature",
  "properties": {
    "gn:admin1_code":"11.0",
    "gn:admin2_code":"528.0",
    "gn:asciiname":"Gransmarka",
    "gn:country_code":"NO",
    "gn:dem":400,
    "gn:feature_class":"P",
    "gn:feature_code":"PPL",
    "gn:name":"Gransmarka",
    "gn:population":0,
    "gn:timezone":"Europe/Oslo",
    "iso:country":"NO",
    "name:nor_x_preferred":[
        "Gransmarka"
    ],
    "wof:name":"Gransmarka",
    "wof:placetype":"locality"
},
  "geometry": {"coordinates":[10.8058,60.63486],"type":"Point"}
}