{
  "type": "Feature",
  "properties": {
    "gn:admin1_code":"7",
    "gn:admin2_code":"1251.0",
    "gn:asciiname":"Eikefet",
    "gn:country_code":"NO",
    "gn:dem":440,
    "gn:feature_class":"P",
    "gn:feature_code":"PPL",
    "gn:name":"Eikefet",
    "gn:population":0,
    "gn:timezone":"Europe/Oslo",
    "iso:country":"NO",
    "wof:name":"Eikefet",
    "wof:placetype":"locality"
},
  "geometry": {"coordinates":[5.81667,60.75],"type":"Point"}
}