{
  "type": "Feature",
  "properties": {
    "gn:admin1_code":"8.0",
    "gn:admin2_code":"1560.0",
    "gn:asciiname":"Vagbo",
    "gn:cc2":"NO",
    "gn:country_code":"NO",
    "gn:dem":30,
    "gn:feature_class":"P",
    "gn:feature_code":"PPL",
    "gn:name":"V\u00e5gb\u00f8",
    "gn:population":0,
    "gn:timezone":"Europe/Oslo",
    "iso:country":"NO",
    "name:und_x_variant":[
        "Vaagb\u00f6",
        "V\u00e5gb\u00f8"
    ],
    "wof:name":"Vagbo",
    "wof:placetype":"locality"
},
  "geometry": {"coordinates":[8.28,62.92389],"type":"Point"}
}