{
  "type": "Feature",
  "properties": {
    "gn:admin1_code":"8.0",
    "gn:admin2_code":"1523.0",
    "gn:asciiname":"Vestre",
    "gn:country_code":"NO",
    "gn:dem":100,
    "gn:feature_class":"P",
    "gn:feature_code":"PPL",
    "gn:name":"Vestre",
    "gn:population":0,
    "gn:timezone":"Europe/Oslo",
    "iso:country":"NO",
    "name:nor_x_preferred":[
        "Vestre"
    ],
    "wof:name":"Vestre",
    "wof:placetype":"locality"
},
  "geometry": {"coordinates":[6.87313,62.46137],"type":"Point"}
}