{
  "type": "Feature",
  "properties": {
    "gn:admin1_code":"9.0",
    "gn:admin2_code":"1824.0",
    "gn:asciiname":"Softing",
    "gn:country_code":"NO",
    "gn:dem":40,
    "gn:feature_class":"P",
    "gn:feature_code":"PPL",
    "gn:name":"S\u00f8fting",
    "gn:population":0,
    "gn:timezone":"Europe/Oslo",
    "iso:country":"NO",
    "wof:name":"Softing",
    "wof:placetype":"locality"
},
  "geometry": {"coordinates":[13.17226,65.90817],"type":"Point"}
}