{
  "type": "Feature",
  "properties": {
    "gn:admin1_code":"15.0",
    "gn:admin2_code":"1431.0",
    "gn:asciiname":"Stranda",
    "gn:country_code":"NO",
    "gn:dem":207,
    "gn:feature_class":"P",
    "gn:feature_code":"PPL",
    "gn:name":"Stranda",
    "gn:population":0,
    "gn:timezone":"Europe/Oslo",
    "iso:country":"NO",
    "name:bpy_x_preferred":[
        "\u09b8\u09cd\u099f\u09cd\u09b0\u09be\u09a8\u09cd\u09a1\u09be"
    ],
    "name:cat_x_preferred":[
        "Stranda"
    ],
    "name:ceb_x_preferred":[
        "Stranda"
    ],
    "name:dan_x_preferred":[
        "Stranda"
    ],
    "name:deu_x_preferred":[
        "Stranda"
    ],
    "name:epo_x_preferred":[
        "Stranda"
    ],
    "name:eus_x_preferred":[
        "Stranda"
    ],
    "name:fas_x_preferred":[
        "\u0627\u0633\u062a\u0631\u0627\u0646\u062f\u0627"
    ],
    "name:fin_x_preferred":[
        "Stranda"
    ],
    "name:fra_x_preferred":[
        "Stranda"
    ],
    "name:ita_x_preferred":[
        "Stranda"
    ],
    "name:jav_x_preferred":[
        "Stranda"
    ],
    "name:lat_x_preferred":[
        "Stranda"
    ],
    "name:lim_x_preferred":[
        "Stranda"
    ],
    "name:msa_x_preferred":[
        "Stranda"
    ],
    "name:nds_x_preferred":[
        "Kommun Stranda"
    ],
    "name:nld_x_preferred":[
        "Stranda"
    ],
    "name:nno_x_preferred":[
        "Stranda kommune"
    ],
    "name:nor_x_preferred":[
        "Stranda"
    ],
    "name:pol_x_preferred":[
        "Stranda"
    ],
    "name:por_x_preferred":[
        "Stranda"
    ],
    "name:ron_x_preferred":[
        "Stranda"
    ],
    "name:rus_x_preferred":[
        "\u0421\u0442\u0440\u0430\u043d\u0434\u0430"
    ],
    "name:slv_x_preferred":[
        "Stranda"
    ],
    "name:sme_x_preferred":[
        "Stranda"
    ],
    "name:spa_x_preferred":[
        "Stranda"
    ],
    "name:sqi_x_preferred":[
        "Stranda"
    ],
    "name:swe_x_preferred":[
        "Stranda kommun"
    ],
    "name:vie_x_preferred":[
        "Stranda"
    ],
    "name:war_x_preferred":[
        "Stranda"
    ],
    "name:zho_x_preferred":[
        "\u65af\u7279\u862d\u9054"
    ],
    "wof:name":"Stranda",
    "wof:placetype":"locality"
},
  "geometry": {"coordinates":[6.22068,61.52876],"type":"Point"}
}