{
  "type": "Feature",
  "properties": {
    "gn:admin1_code":"15.0",
    "gn:admin2_code":"1431.0",
    "gn:asciiname":"Stranda",
    "gn:country_code":"NO",
    "gn:dem":207,
    "gn:feature_class":"P",
    "gn:feature_code":"PPL",
    "gn:name":"Stranda",
    "gn:population":0,
    "gn:timezone":"Europe/Oslo",
    "iso:country":"NO",
    "name:nor_x_preferred":[
        "Stranda"
    ],
    "wof:name":"Stranda",
    "wof:placetype":"locality"
},
  "geometry": {"coordinates":[6.22068,61.52876],"type":"Point"}
}