{
  "type": "Feature",
  "properties": {
    "gn:admin1_code":"4.0",
    "gn:admin2_code":"626.0",
    "gn:asciiname":"Royne",
    "gn:cc2":"NO",
    "gn:country_code":"NO",
    "gn:dem":348,
    "gn:feature_class":"P",
    "gn:feature_code":"PPL",
    "gn:name":"R\u00f8yne",
    "gn:population":0,
    "gn:timezone":"Europe/Oslo",
    "iso:country":"NO",
    "name:und_x_variant":[
        "R\u00f6ine",
        "R\u00f8yne"
    ],
    "wof:name":"Royne",
    "wof:placetype":"locality"
},
  "geometry": {"coordinates":[10.26667,59.93333000000001],"type":"Point"}
}