{
  "type": "Feature",
  "properties": {
    "gn:admin1_code":"18",
    "gn:admin2_code":"1902.0",
    "gn:asciiname":"Hakoy",
    "gn:country_code":"NO",
    "gn:dem":-9999,
    "gn:feature_class":"P",
    "gn:feature_code":"PPL",
    "gn:name":"H\u00e5k\u00f8y",
    "gn:population":0,
    "gn:timezone":"Europe/Oslo",
    "iso:country":"NO",
    "wof:name":"Hakoy",
    "wof:placetype":"locality"
},
  "geometry": {"coordinates":[18.83333,69.65000000000001],"type":"Point"}
}