{
  "type": "Feature",
  "properties": {
    "gn:admin1_code":"21",
    "gn:admin2_code":"5014.0",
    "gn:asciiname":"Dragsnes",
    "gn:country_code":"NO",
    "gn:dem":-9999,
    "gn:feature_class":"P",
    "gn:feature_code":"PPL",
    "gn:name":"Dragsnes",
    "gn:population":0,
    "gn:timezone":"Europe/Oslo",
    "iso:country":"NO",
    "name:nor_x_preferred":[
        "Dragsnes"
    ],
    "wof:name":"Dragsnes",
    "wof:placetype":"locality"
},
  "geometry": {"coordinates":[8.75,63.78333000000001],"type":"Point"}
}