{
  "type": "Feature",
  "properties": {
    "gn:admin1_code":"21.0",
    "gn:admin2_code":"5054.0",
    "gn:asciiname":"Hindrem",
    "gn:country_code":"NO",
    "gn:dem":20,
    "gn:feature_class":"P",
    "gn:feature_code":"PPL",
    "gn:name":"Hindrem",
    "gn:population":0,
    "gn:timezone":"Europe/Oslo",
    "iso:country":"NO",
    "name:nor_x_preferred":[
        "Hindrem"
    ],
    "wof:name":"Hindrem",
    "wof:placetype":"locality"
},
  "geometry": {"coordinates":[10.41595,63.58955],"type":"Point"}
}