{
  "type": "Feature",
  "properties": {
    "gn:admin1_code":"19.0",
    "gn:admin2_code":"1029.0",
    "gn:asciiname":"Snig",
    "gn:country_code":"NO",
    "gn:dem":3,
    "gn:feature_class":"P",
    "gn:feature_code":"PPLL",
    "gn:name":"Snig",
    "gn:population":0,
    "gn:timezone":"Europe/Oslo",
    "iso:country":"NO",
    "wof:name":"Snig",
    "wof:placetype":"locality"
},
  "geometry": {"coordinates":[7.27071,58.05348000000001],"type":"Point"}
}