{
  "type": "Feature",
  "properties": {
    "gn:admin1_code":"8.0",
    "gn:admin2_code":"1573.0",
    "gn:asciiname":"Bellabakkan",
    "gn:country_code":"NO",
    "gn:dem":-9999,
    "gn:feature_class":"P",
    "gn:feature_code":"PPL",
    "gn:name":"Bellabakkan",
    "gn:population":0,
    "gn:timezone":"Europe/Oslo",
    "iso:country":"NO",
    "name:nor_x_preferred":[
        "Bellabakkan"
    ],
    "wof:name":"Bellabakkan",
    "wof:placetype":"locality"
},
  "geometry": {"coordinates":[7.95386,63.51843],"type":"Point"}
}