{
  "type": "Feature",
  "properties": {
    "gn:gn_country":"NO",
    "gn:gn_fcode":"PPL",
    "gn:gn_pop":457,
    "gn:population":457,
    "iso:country":"NO",
    "name:eng_x_preferred":[
        "Heradsbygd"
    ],
    "name:fra_x_preferred":[
        "Heradsbygd"
    ],
    "name:jav_x_preferred":[
        "Heradsbygd"
    ],
    "name:msa_x_preferred":[
        "Heradsbygd"
    ],
    "name:nld_x_preferred":[
        "Heradsbygd"
    ],
    "name:nno_x_preferred":[
        "Heradsbygd"
    ],
    "name:nob_x_preferred":[
        "Heradsbygd"
    ],
    "name:nor_x_preferred":[
        "Heradsbygd"
    ],
    "name:nor_x_variant":[
        "Heradsbygda"
    ],
    "name:ron_x_preferred":[
        "Heradsbygd"
    ],
    "qs_pg:aaroncc":"NO",
    "qs_pg:gn_country":"NO",
    "qs_pg:gn_fcode":"PPL",
    "qs_pg:gn_pop":457,
    "qs_pg:name":"Heradsbygd",
    "qs_pg:name_adm0":"Norge",
    "qs_pg:name_adm1":"Hedmark Fylke",
    "qs_pg:photos":80,
    "qs_pg:photos_1k":16,
    "qs_pg:photos_9k":1,
    "qs_pg:photos_9r":3,
    "qs_pg:photos_all":80,
    "qs_pg:photos_sr":3,
    "qs_pg:pop_sr":2,
    "qs_pg:qs_pg_placetype":"locality",
    "qs_pg:qs_pg_placetype_gp":"Town",
    "qs_pg:woe_adm0":23424910,
    "woe:adm0_id":23424910,
    "woe:name_adm0":"Norge",
    "woe:name_adm1":"Hedmark Fylke",
    "woe:placetype":"Town",
    "wof:name":"Heradsbygd",
    "wof:placetype":"locality",
    "wof:population":457
},
  "geometry": {"coordinates":[11.63333,60.81667],"type":"Point"}
}