{
  "type": "Feature",
  "properties": {
    "gn:admin1_code":"7",
    "gn:admin2_code":"1266.0",
    "gn:asciiname":"Duesund",
    "gn:country_code":"NO",
    "gn:dem":-9999,
    "gn:feature_class":"P",
    "gn:feature_code":"PPL",
    "gn:name":"Duesund",
    "gn:population":0,
    "gn:timezone":"Europe/Oslo",
    "iso:country":"NO",
    "wof:name":"Duesund",
    "wof:placetype":"locality"
},
  "geometry": {"coordinates":[5.30611,60.81528],"type":"Point"}
}