{
  "type": "Feature",
  "properties": {
    "gn:admin1_code":"21.0",
    "gn:admin2_code":"5035.0",
    "gn:asciiname":"Lundan",
    "gn:country_code":"NO",
    "gn:dem":160,
    "gn:feature_class":"P",
    "gn:feature_code":"PPL",
    "gn:name":"Lundan",
    "gn:population":0,
    "gn:timezone":"Europe/Oslo",
    "iso:country":"NO",
    "name:nor_x_preferred":[
        "Lundan"
    ],
    "wof:name":"Lundan",
    "wof:placetype":"locality"
},
  "geometry": {"coordinates":[11.00053,63.5077],"type":"Point"}
}