{
  "type": "Feature",
  "properties": {
    "gn:admin1_code":"1.0",
    "gn:admin2_code":"228.0",
    "gn:asciiname":"Borgen",
    "gn:country_code":"NO",
    "gn:dem":113,
    "gn:feature_class":"P",
    "gn:feature_code":"PPL",
    "gn:name":"Borgen",
    "gn:population":0,
    "gn:timezone":"Europe/Oslo",
    "iso:country":"NO",
    "name:nor_x_preferred":[
        "Borgen"
    ],
    "wof:name":"Borgen",
    "wof:placetype":"locality"
},
  "geometry": {"coordinates":[11.05642,59.94331],"type":"Point"}
}