{
  "type": "Feature",
  "properties": {
    "gn:admin1_code":"1.0",
    "gn:admin2_code":"228.0",
    "gn:asciiname":"Borgen",
    "gn:country_code":"NO",
    "gn:dem":113,
    "gn:feature_class":"P",
    "gn:feature_code":"PPL",
    "gn:name":"Borgen",
    "gn:population":0,
    "gn:timezone":"Europe/Oslo",
    "iso:country":"NO",
    "name:ceb_x_preferred":[
        "Borgen"
    ],
    "name:ces_x_preferred":[
        "Borgen"
    ],
    "name:dan_x_preferred":[
        "Borgen"
    ],
    "name:deu_x_preferred":[
        "Borgen"
    ],
    "name:fra_x_preferred":[
        "Borgen"
    ],
    "name:ita_x_preferred":[
        "Borgen"
    ],
    "name:nld_x_preferred":[
        "Borgen"
    ],
    "name:nno_x_preferred":[
        "Borgen"
    ],
    "name:nor_x_preferred":[
        "Borgen"
    ],
    "name:por_x_preferred":[
        "Borgen"
    ],
    "name:rus_x_preferred":[
        "\u0411\u043e\u0440\u0433\u0435\u043d"
    ],
    "name:spa_x_preferred":[
        "Borgen"
    ],
    "name:swe_x_preferred":[
        "Borgen"
    ],
    "wof:name":"Borgen",
    "wof:placetype":"locality"
},
  "geometry": {"coordinates":[11.05642,59.94331],"type":"Point"}
}