{
  "type": "Feature",
  "properties": {
    "gn:admin1_code":"19",
    "gn:admin2_code":"1002",
    "gn:asciiname":"Nedre Malmo",
    "gn:country_code":"NO",
    "gn:dem":4,
    "gn:feature_class":"P",
    "gn:feature_code":"PPLL",
    "gn:name":"Nedre Malm\u00f8",
    "gn:population":0,
    "gn:timezone":"Europe/Oslo",
    "iso:country":"NO",
    "name:nor_x_preferred":[
        "Nedre Malm\u00f8"
    ],
    "wof:name":"Nedre Malmo",
    "wof:placetype":"neighbourhood"
},
  "geometry": {"coordinates":[7.45844,58.02494],"type":"Point"}
}