{
  "type": "Feature",
  "properties": {
    "gn:admin1_code":"21",
    "gn:admin2_code":"5038.0",
    "gn:asciiname":"Lund",
    "gn:country_code":"NO",
    "gn:dem":120,
    "gn:feature_class":"P",
    "gn:feature_code":"PPL",
    "gn:name":"Lund",
    "gn:population":0,
    "gn:timezone":"Europe/Oslo",
    "iso:country":"NO",
    "name:nor_x_preferred":[
        "Lund"
    ],
    "wof:name":"Lund",
    "wof:placetype":"locality"
},
  "geometry": {"coordinates":[11.65932,63.83886999999999],"type":"Point"}
}