{
  "type": "Feature",
  "properties": {
    "iso:country":"NO",
    "name:ara_x_preferred":[
        "\u0631\u0627\u0645"
    ],
    "name:bar_x_preferred":[
        "Rom"
    ],
    "name:bre_x_preferred":[
        "Rom"
    ],
    "name:cat_x_preferred":[
        "Rom"
    ],
    "name:ceb_x_preferred":[
        "Rom"
    ],
    "name:ces_x_preferred":[
        "Rom"
    ],
    "name:dan_x_preferred":[
        "Rom"
    ],
    "name:deu_x_preferred":[
        "Rom"
    ],
    "name:eus_x_preferred":[
        "Rom"
    ],
    "name:fas_x_preferred":[
        "\u0631\u0627\u0645"
    ],
    "name:fra_x_preferred":[
        "Rom"
    ],
    "name:heb_x_preferred":[
        "\u05e8\u05d5\u05dd"
    ],
    "name:ind_x_preferred":[
        "Rom"
    ],
    "name:krc_x_preferred":[
        "\u0420\u0438\u043c"
    ],
    "name:ltz_x_preferred":[
        "Rom"
    ],
    "name:mkd_x_preferred":[
        "\u0420\u043e\u043c"
    ],
    "name:msa_x_preferred":[
        "Rom"
    ],
    "name:nld_x_preferred":[
        "Rom"
    ],
    "name:nno_x_preferred":[
        "Rom"
    ],
    "name:nor_x_preferred":[
        "Rom"
    ],
    "name:oci_x_preferred":[
        "R\u00f2m"
    ],
    "name:oss_x_preferred":[
        "\u0420\u043e\u043c"
    ],
    "name:pol_x_preferred":[
        "Rom"
    ],
    "name:por_x_preferred":[
        "ROM"
    ],
    "name:ron_x_preferred":[
        "Rom"
    ],
    "name:rus_x_preferred":[
        "\u0420\u043e\u043c"
    ],
    "name:slk_x_preferred":[
        "Rom"
    ],
    "name:spa_x_preferred":[
        "Rom"
    ],
    "name:srp_x_preferred":[
        "\u0420\u043e\u043c"
    ],
    "name:swe_x_preferred":[
        "Rom"
    ],
    "name:tur_x_preferred":[
        "Rom"
    ],
    "name:ukr_x_preferred":[
        "\u0420\u043e\u043c"
    ],
    "name:uzb_x_preferred":[
        "Rom"
    ],
    "qs_pg:aaroncc":"NO",
    "qs_pg:name":"Rom",
    "qs_pg:name_adm0":"Norge",
    "qs_pg:name_adm1":"Vest-Agder Fylke",
    "qs_pg:photos":9,
    "qs_pg:photos_1k":2,
    "qs_pg:photos_9k":1,
    "qs_pg:photos_9r":1,
    "qs_pg:photos_all":9,
    "qs_pg:photos_sr":1,
    "qs_pg:pop_sr":0,
    "qs_pg:qs_pg_placetype":"locality",
    "qs_pg:qs_pg_placetype_gp":"Town",
    "qs_pg:woe_adm0":23424910,
    "woe:adm0_id":23424910,
    "woe:name_adm0":"Norge",
    "woe:name_adm1":"Vest-Agder Fylke",
    "woe:placetype":"Town",
    "wof:name":"Rom",
    "wof:placetype":"neighbourhood"
},
  "geometry": {"coordinates":[7.094689,58.152583],"type":"Point"}
}