{
  "type": "Feature",
  "properties": {
    "gn:country":"NO",
    "gn:fcode":"PPL",
    "gn:population":499,
    "iso:country":"NO",
    "name:ceb_x_preferred":[
        "Kleive"
    ],
    "name:eng_x_preferred":[
        "Kleive"
    ],
    "name:fra_x_preferred":[
        "Kleive"
    ],
    "name:jav_x_preferred":[
        "Kleive"
    ],
    "name:msa_x_preferred":[
        "Kleive"
    ],
    "name:nld_x_preferred":[
        "Kleive"
    ],
    "name:nno_x_preferred":[
        "Kleive"
    ],
    "name:nob_x_preferred":[
        "Kleive"
    ],
    "name:ron_x_preferred":[
        "Kleive"
    ],
    "name:spa_x_preferred":[
        "Kleive"
    ],
    "name:und_x_variant":[
        "Kleve"
    ],
    "qs_pg:aaroncc":"NO",
    "qs_pg:gn_country":"NO",
    "qs_pg:gn_fcode":"PPL",
    "qs_pg:gn_pop":499,
    "qs_pg:name":"Kleive",
    "qs_pg:photos_9r":0,
    "qs_pg:photos_sr":0,
    "qs_pg:pop_sr":2,
    "qs_pg:qs_pg_placetype":"locality",
    "wof:name":"Kleive",
    "wof:placetype":"locality",
    "wof:population":499
},
  "geometry": {"coordinates":[7.66667,62.81667],"type":"Point"}
}