{
  "type": "Feature",
  "properties": {
    "gn:admin1_code":"2",
    "gn:admin2_code":"911.0",
    "gn:asciiname":"Fone",
    "gn:country_code":"NO",
    "gn:dem":53,
    "gn:feature_class":"P",
    "gn:feature_code":"PPL",
    "gn:name":"Fone",
    "gn:population":0,
    "gn:timezone":"Europe/Oslo",
    "iso:country":"NO",
    "name:por_x_preferred":[
        "Fone"
    ],
    "wof:name":"Fone",
    "wof:placetype":"locality"
},
  "geometry": {"coordinates":[9.08333,58.85],"type":"Point"}
}