{
  "type": "Feature",
  "properties": {
    "gn:admin1_code":"21",
    "gn:admin2_code":"5022.0",
    "gn:asciiname":"Buan",
    "gn:country_code":"NO",
    "gn:dem":460,
    "gn:feature_class":"P",
    "gn:feature_code":"PPL",
    "gn:name":"Buan",
    "gn:population":0,
    "gn:timezone":"Europe/Oslo",
    "iso:country":"NO",
    "name:nor_x_preferred":[
        "Buan"
    ],
    "wof:name":"Buan",
    "wof:placetype":"locality"
},
  "geometry": {"coordinates":[10.05,62.86666999999999],"type":"Point"}
}