{
  "type": "Feature",
  "properties": {
    "gn:admin1_code":"18",
    "gn:admin2_code":"1913.0",
    "gn:asciiname":"Grov",
    "gn:cc2":"NO",
    "gn:country_code":"NO",
    "gn:dem":60,
    "gn:feature_class":"P",
    "gn:feature_code":"PPL",
    "gn:name":"Grov",
    "gn:population":0,
    "gn:timezone":"Europe/Oslo",
    "iso:country":"NO",
    "name:ceb_x_preferred":[
        "Grov"
    ],
    "name:fra_x_preferred":[
        "Grov"
    ],
    "name:msa_x_preferred":[
        "Grov"
    ],
    "name:nld_x_preferred":[
        "Grov"
    ],
    "name:nno_x_preferred":[
        "Grov"
    ],
    "name:nor_x_preferred":[
        "Grov"
    ],
    "name:nor_x_variant":[
        "Grovfjord"
    ],
    "name:ron_x_preferred":[
        "Grov"
    ],
    "name:sme_x_preferred":[
        "Roahpa"
    ],
    "wof:name":"Grov",
    "wof:placetype":"locality"
},
  "geometry": {"coordinates":[17.12079,68.67644],"type":"Point"}
}