{
  "type": "Feature",
  "properties": {
    "gn:admin1_code":"6",
    "gn:admin2_code":"423.0",
    "gn:asciiname":"Holt",
    "gn:country_code":"NO",
    "gn:dem":212,
    "gn:feature_class":"P",
    "gn:feature_code":"PPL",
    "gn:name":"Holt",
    "gn:population":0,
    "gn:timezone":"Europe/Oslo",
    "iso:country":"NO",
    "wof:name":"Holt",
    "wof:placetype":"locality"
},
  "geometry": {"coordinates":[11.96667,60.48333],"type":"Point"}
}