{
  "type": "Feature",
  "properties": {
    "gn:admin1_code":"9.0",
    "gn:admin2_code":"1865.0",
    "gn:asciiname":"Straumnes",
    "gn:cc2":"NO",
    "gn:country_code":"NO",
    "gn:dem":2,
    "gn:feature_class":"P",
    "gn:feature_code":"PPL",
    "gn:name":"Straumnes",
    "gn:population":0,
    "gn:timezone":"Europe/Oslo",
    "iso:country":"NO",
    "name:und_x_variant":[
        "Str\u00f6mnes",
        "Straumnes"
    ],
    "wof:name":"Straumnes",
    "wof:placetype":"locality"
},
  "geometry": {"coordinates":[14.46627,68.39319],"type":"Point"}
}