{
  "type": "Feature",
  "properties": {
    "gn:admin1_code":"5.0",
    "gn:admin2_code":"2030.0",
    "gn:asciiname":"Elvenes",
    "gn:country_code":"NO",
    "gn:dem":1,
    "gn:feature_class":"P",
    "gn:feature_code":"PPL",
    "gn:name":"Elvenes",
    "gn:population":0,
    "gn:timezone":"Europe/Oslo",
    "iso:country":"NO",
    "name:cat_x_preferred":[
        "Elvenes"
    ],
    "name:eng_x_preferred":[
        "Elvenes"
    ],
    "name:jav_x_preferred":[
        "Elvenes"
    ],
    "name:msa_x_preferred":[
        "Elvenes"
    ],
    "name:nno_x_preferred":[
        "Elvenes"
    ],
    "name:nor_x_preferred":[
        "Elvenes"
    ],
    "name:nor_x_variant":[
        "Elvnes"
    ],
    "name:rus_x_preferred":[
        "\u042d\u043b\u044c\u0432\u0435\u043d\u0435\u0441"
    ],
    "name:swe_x_preferred":[
        "Elvenes"
    ],
    "wof:name":"Elvenes",
    "wof:placetype":"locality"
},
  "geometry": {"coordinates":[30.10499,69.67931],"type":"Point"}
}