{
  "type": "Feature",
  "properties": {
    "iso:country":"NO",
    "name:nor_x_preferred":[
        "Tellevik"
    ],
    "qs:gn_adm0_cc":"NO",
    "qs:gn_fcode":"PPL",
    "qs:gn_local":3151863,
    "qs:gn_nam_loc":"Hordvik, Bergen, Hordaland Fylke, NO",
    "qs:gn_namadm1":"15",
    "qs:gn_name":"Hellevik",
    "qs:local_max":715,
    "qs:local_sum":956,
    "qs:localhoods":3,
    "qs:name":"Tellevik",
    "qs:name_adm0":"Norge",
    "qs:name_adm1":"Hordaland Fylke",
    "qs:name_adm2":"Bergen Kommune",
    "qs:name_local":"Hordvik",
    "qs:photo_max":236,
    "qs:photo_sum":715,
    "qs:placetype":"Suburb",
    "qs:quad_count":41,
    "qs:woe_adm0":23424910,
    "qs:woe_adm1":2346390,
    "qs:woe_adm2":12592658,
    "qs:woe_lau":0,
    "qs:woe_local":860013,
    "qs:woe_ver":"7.10.0",
    "wof:lang":[
        "nor"
    ],
    "wof:name":"Tellevik",
    "wof:placetype":"neighbourhood"
},
  "geometry": {"coordinates":[5.255019,60.516273],"type":"Point"}
}