{
  "type": "Feature",
  "properties": {
    "gn:admin1_code":"11.0",
    "gn:admin2_code":"520.0",
    "gn:asciiname":"Oppsal",
    "gn:cc2":"NO",
    "gn:country_code":"NO",
    "gn:dem":470,
    "gn:feature_class":"P",
    "gn:feature_code":"PPL",
    "gn:name":"Oppsal",
    "gn:population":0,
    "gn:timezone":"Europe/Oslo",
    "iso:country":"NO",
    "name:nor_x_preferred":[
        "Oppsal"
    ],
    "name:und_x_variant":[
        "Opsal"
    ],
    "wof:name":"Oppsal",
    "wof:placetype":"locality"
},
  "geometry": {"coordinates":[10.23333,61.43333000000001],"type":"Point"}
}