{
  "type": "Feature",
  "properties": {
    "gn:admin1_code":"18.0",
    "gn:admin2_code":"1942.0",
    "gn:asciiname":"Storneshamn",
    "gn:cc2":"NO",
    "gn:country_code":"NO",
    "gn:dem":-9999,
    "gn:feature_class":"P",
    "gn:feature_code":"PPL",
    "gn:name":"Storneshamn",
    "gn:population":0,
    "gn:timezone":"Europe/Oslo",
    "iso:country":"NO",
    "name:und_x_variant":[
        "Stornes",
        "Storneshamn"
    ],
    "wof:name":"Storneshamn",
    "wof:placetype":"locality"
},
  "geometry": {"coordinates":[21.05,69.90000000000001],"type":"Point"}
}