{
  "type": "Feature",
  "properties": {
    "gn:admin1_code":"18.0",
    "gn:admin2_code":"1926.0",
    "gn:asciiname":"Finnfjellet",
    "gn:country_code":"NO",
    "gn:dem":194,
    "gn:feature_class":"P",
    "gn:feature_code":"PPL",
    "gn:name":"Finnfjellet",
    "gn:population":0,
    "gn:timezone":"Europe/Oslo",
    "iso:country":"NO",
    "name:nor_x_preferred":[
        "Finnfjellet"
    ],
    "wof:name":"Finnfjellet",
    "wof:placetype":"locality"
},
  "geometry": {"coordinates":[17.7532,69.07965],"type":"Point"}
}