{
  "type": "Feature",
  "properties": {
    "gn:admin1_code":"6.0",
    "gn:admin2_code":"428.0",
    "gn:asciiname":"Vestad",
    "gn:cc2":"NO",
    "gn:country_code":"NO",
    "gn:dem":520,
    "gn:feature_class":"P",
    "gn:feature_code":"PPL",
    "gn:name":"Vestad",
    "gn:population":0,
    "gn:timezone":"Europe/Oslo",
    "iso:country":"NO",
    "name:und_x_variant":[
        "V\u00e6stad",
        "Vestad"
    ],
    "wof:name":"Vestad",
    "wof:placetype":"locality"
},
  "geometry": {"coordinates":[12.26667,61.31667],"type":"Point"}
}