{
  "type": "Feature",
  "properties": {
    "gn:admin1_code":"17.0",
    "gn:admin2_code":"833.0",
    "gn:asciiname":"Hatveit",
    "gn:country_code":"NO",
    "gn:dem":625,
    "gn:feature_class":"P",
    "gn:feature_code":"PPL",
    "gn:name":"H\u00e5tveit",
    "gn:population":0,
    "gn:timezone":"Europe/Oslo",
    "iso:country":"NO",
    "name:nor_x_preferred":[
        "H\u00e5tveit"
    ],
    "wof:name":"Hatveit",
    "wof:placetype":"locality"
},
  "geometry": {"coordinates":[7.86409,59.48891],"type":"Point"}
}