{
  "type": "Feature",
  "properties": {
    "gn:admin1_code":"9",
    "gn:admin2_code":"1849.0",
    "gn:asciiname":"Oppeid",
    "gn:country_code":"NO",
    "gn:dem":80,
    "gn:feature_class":"P",
    "gn:feature_code":"PPLA2",
    "gn:name":"Oppeid",
    "gn:population":0,
    "gn:timezone":"Europe/Oslo",
    "iso:country":"NO",
    "name:ceb_x_preferred":[
        "Oppeid"
    ],
    "name:fra_x_preferred":[
        "Oppeid"
    ],
    "name:ita_x_preferred":[
        "Oppeid"
    ],
    "name:jav_x_preferred":[
        "Oppeid"
    ],
    "name:msa_x_preferred":[
        "Oppeid"
    ],
    "name:nld_x_preferred":[
        "Oppeid"
    ],
    "name:nno_x_preferred":[
        "Oppeid"
    ],
    "name:nor_x_preferred":[
        "Oppeid"
    ],
    "name:ron_x_preferred":[
        "Oppeid"
    ],
    "name:rus_x_preferred":[
        "\u041e\u043f\u043f\u0435\u0439\u0434"
    ],
    "name:spa_x_preferred":[
        "Oppeid"
    ],
    "wof:name":"Oppeid",
    "wof:placetype":"locality"
},
  "geometry": {"coordinates":[15.60942,68.08521999999999],"type":"Point"}
}