{
  "type": "Feature",
  "properties": {
    "gn:admin1_code":"20.0",
    "gn:admin2_code":"712.0",
    "gn:asciiname":"Rimstad",
    "gn:country_code":"NO",
    "gn:dem":41,
    "gn:feature_class":"P",
    "gn:feature_code":"PPL",
    "gn:name":"Rimstad",
    "gn:population":0,
    "gn:timezone":"Europe/Oslo",
    "iso:country":"NO",
    "wof:name":"Rimstad",
    "wof:placetype":"locality"
},
  "geometry": {"coordinates":[9.95,59.25],"type":"Point"}
}