{
  "type": "Feature",
  "properties": {
    "gn:admin1_code":"9",
    "gn:admin2_code":"1828.0",
    "gn:asciiname":"Einmoen",
    "gn:country_code":"NO",
    "gn:dem":120,
    "gn:feature_class":"P",
    "gn:feature_code":"PPL",
    "gn:name":"Einmoen",
    "gn:population":0,
    "gn:timezone":"Europe/Oslo",
    "iso:country":"NO",
    "wof:name":"Einmoen",
    "wof:placetype":"locality"
},
  "geometry": {"coordinates":[13.21667,66.26666999999999],"type":"Point"}
}