{
  "type": "Feature",
  "properties": {
    "gn:admin1_code":"11.0",
    "gn:admin2_code":"501.0",
    "gn:asciiname":"Veslesetra",
    "gn:country_code":"NO",
    "gn:dem":440,
    "gn:feature_class":"P",
    "gn:feature_code":"PPL",
    "gn:name":"Veslesetra",
    "gn:population":0,
    "gn:timezone":"Europe/Oslo",
    "iso:country":"NO",
    "name:nor_x_preferred":[
        "Veslesetra"
    ],
    "wof:name":"Veslesetra",
    "wof:placetype":"locality"
},
  "geometry": {"coordinates":[10.30561,61.07227],"type":"Point"}
}