{
  "type": "Feature",
  "properties": {
    "gn:admin1_code":"18",
    "gn:admin2_code":"1922.0",
    "gn:asciiname":"Bardujord",
    "gn:cc2":"NO",
    "gn:country_code":"NO",
    "gn:dem":79,
    "gn:feature_class":"P",
    "gn:feature_code":"PPL",
    "gn:name":"Bardujord",
    "gn:population":0,
    "gn:timezone":"Europe/Oslo",
    "iso:country":"NO",
    "name:und_x_variant":[
        "Bardujorda"
    ],
    "wof:name":"Bardujord",
    "wof:placetype":"locality"
},
  "geometry": {"coordinates":[18.53138,68.80547],"type":"Point"}
}