{
  "type": "Feature",
  "properties": {
    "gn:admin1_code":"9",
    "gn:admin2_code":"1870.0",
    "gn:asciiname":"Grytting",
    "gn:country_code":"NO",
    "gn:dem":1,
    "gn:feature_class":"P",
    "gn:feature_code":"PPL",
    "gn:name":"Grytting",
    "gn:population":0,
    "gn:timezone":"Europe/Oslo",
    "iso:country":"NO",
    "name:fra_x_preferred":[
        "Grytting"
    ],
    "name:jav_x_preferred":[
        "Grytting"
    ],
    "name:msa_x_preferred":[
        "Grytting"
    ],
    "name:nor_x_preferred":[
        "Grytting"
    ],
    "wof:name":"Grytting",
    "wof:placetype":"locality"
},
  "geometry": {"coordinates":[15.03333,68.71666999999999],"type":"Point"}
}