{
  "type": "Feature",
  "properties": {
    "gn:admin1_code":"4.0",
    "gn:admin2_code":"620.0",
    "gn:asciiname":"Kvisla",
    "gn:country_code":"NO",
    "gn:dem":647,
    "gn:feature_class":"P",
    "gn:feature_code":"PPL",
    "gn:name":"Kvisla",
    "gn:population":0,
    "gn:timezone":"Europe/Oslo",
    "iso:country":"NO",
    "name:jav_x_preferred":[
        "Kvisla"
    ],
    "name:msa_x_preferred":[
        "Kvisla"
    ],
    "name:nor_x_preferred":[
        "Kvisla"
    ],
    "wof:name":"Kvisla",
    "wof:placetype":"locality"
},
  "geometry": {"coordinates":[8.31099,60.58197],"type":"Point"}
}