{
  "type": "Feature",
  "properties": {
    "gn:admin1_code":"18.0",
    "gn:admin2_code":"1902.0",
    "gn:asciiname":"Tomasbakken",
    "gn:cc2":"NO",
    "gn:country_code":"NO",
    "gn:dem":178,
    "gn:feature_class":"P",
    "gn:feature_code":"PPL",
    "gn:name":"Tomasbakken",
    "gn:population":0,
    "gn:timezone":"Europe/Oslo",
    "iso:country":"NO",
    "name:und_x_variant":[
        "Tomasbakk",
        "Tomasbakken"
    ],
    "wof:name":"Tomasbakken",
    "wof:placetype":"locality"
},
  "geometry": {"coordinates":[19.21667,69.56667],"type":"Point"}
}