{
  "type": "Feature",
  "properties": {
    "gn:admin1_code":"15.0",
    "gn:admin2_code":"1418.0",
    "gn:asciiname":"Farnes",
    "gn:country_code":"NO",
    "gn:dem":1,
    "gn:feature_class":"P",
    "gn:feature_code":"PPL",
    "gn:name":"Farnes",
    "gn:population":0,
    "gn:timezone":"Europe/Oslo",
    "iso:country":"NO",
    "name:nor_x_preferred":[
        "Farnes"
    ],
    "wof:name":"Farnes",
    "wof:placetype":"locality"
},
  "geometry": {"coordinates":[6.54152,61.25671],"type":"Point"}
}