{
  "type": "Feature",
  "properties": {
    "gn:admin1_code":"21",
    "gn:admin2_code":"5045.0",
    "gn:asciiname":"Homo",
    "gn:cc2":"NO",
    "gn:country_code":"NO",
    "gn:dem":67,
    "gn:feature_class":"P",
    "gn:feature_code":"PPL",
    "gn:name":"Homo",
    "gn:population":0,
    "gn:timezone":"Europe/Oslo",
    "iso:country":"NO",
    "name:und_x_variant":[
        "Joma",
        "Homo"
    ],
    "wof:name":"Homo",
    "wof:placetype":"locality"
},
  "geometry": {"coordinates":[12.32642,64.44181999999999],"type":"Point"}
}