{
  "type": "Feature",
  "properties": {
    "gn:admin1_code":"9.0",
    "gn:admin2_code":"1804.0",
    "gn:asciiname":"Os",
    "gn:country_code":"NO",
    "gn:dem":20,
    "gn:feature_class":"P",
    "gn:feature_code":"PPL",
    "gn:name":"Os",
    "gn:population":0,
    "gn:timezone":"Europe/Oslo",
    "iso:country":"NO",
    "wof:name":"Os",
    "wof:placetype":"locality"
},
  "geometry": {"coordinates":[14.8343,67.53834000000001],"type":"Point"}
}