{
  "type": "Feature",
  "properties": {
    "gn:admin1_code":"21.0",
    "gn:admin2_code":"5028.0",
    "gn:asciiname":"Vollagrenda",
    "gn:country_code":"NO",
    "gn:dem":180,
    "gn:feature_class":"P",
    "gn:feature_code":"PPL",
    "gn:name":"Vollagrenda",
    "gn:population":0,
    "gn:timezone":"Europe/Oslo",
    "iso:country":"NO",
    "name:nor_x_preferred":[
        "Vollagrenda"
    ],
    "wof:name":"Vollagrenda",
    "wof:placetype":"locality"
},
  "geometry": {"coordinates":[10.24186,63.09953],"type":"Point"}
}