{
  "type": "Feature",
  "properties": {
    "gn:admin1_code":"5.0",
    "gn:admin2_code":"2002.0",
    "gn:asciiname":"Smelror",
    "gn:cc2":"NO",
    "gn:country_code":"NO",
    "gn:dem":8,
    "gn:feature_class":"P",
    "gn:feature_code":"PPL",
    "gn:name":"Smelror",
    "gn:population":0,
    "gn:timezone":"Europe/Oslo",
    "iso:country":"NO",
    "name:eng_x_preferred":[
        "Ytre Smellror"
    ],
    "name:rus_x_preferred":[
        "\u0421\u043c\u0435\u043b\u044c\u0440\u043e\u0440\u0435\u043d"
    ],
    "name:und_x_variant":[
        "Smellror",
        "Smelroren",
        "Ytre Smellror"
    ],
    "wof:name":"Smelror",
    "wof:placetype":"locality"
},
  "geometry": {"coordinates":[31.02043,70.38535],"type":"Point"}
}