{
  "type": "Feature",
  "properties": {
    "gn:admin1_code":"17",
    "gn:admin2_code":"827",
    "gn:asciiname":"Bjar",
    "gn:country_code":"NO",
    "gn:dem":475,
    "gn:feature_class":"P",
    "gn:feature_code":"PPLL",
    "gn:name":"Bj\u00e5r",
    "gn:population":0,
    "gn:timezone":"Europe/Oslo",
    "iso:country":"NO",
    "name:nor_x_preferred":[
        "Bj\u00e5r"
    ],
    "wof:name":"Bjar",
    "wof:placetype":"locality"
},
  "geometry": {"coordinates":[8.79708,59.75212],"type":"Point"}
}