{
  "type": "Feature",
  "properties": {
    "gn:admin1_code":"17.0",
    "gn:admin2_code":"815.0",
    "gn:asciiname":"Vadfoss",
    "gn:country_code":"NO",
    "gn:dem":32,
    "gn:feature_class":"P",
    "gn:feature_code":"PPL",
    "gn:name":"Vadfoss",
    "gn:population":0,
    "gn:timezone":"Europe/Oslo",
    "iso:country":"NO",
    "wof:name":"Vadfoss",
    "wof:placetype":"locality"
},
  "geometry": {"coordinates":[9.34496,58.89187],"type":"Point"}
}