{
  "type": "Feature",
  "properties": {
    "gn:admin1_code":"7",
    "gn:admin2_code":"1264.0",
    "gn:asciiname":"Litlas",
    "gn:cc2":"NO",
    "gn:country_code":"NO",
    "gn:dem":80,
    "gn:feature_class":"P",
    "gn:feature_code":"PPLL",
    "gn:name":"Litl\u00e5s",
    "gn:population":0,
    "gn:timezone":"Europe/Oslo",
    "iso:country":"NO",
    "name:und_x_variant":[
        "Aase",
        "Litl\u00e5s"
    ],
    "wof:name":"Litlas",
    "wof:placetype":"locality"
},
  "geometry": {"coordinates":[5.01944,60.795],"type":"Point"}
}