{
  "type": "Feature",
  "properties": {
    "gn:admin1_code":"11.0",
    "gn:admin2_code":"501.0",
    "gn:asciiname":"Gammeldossaetra",
    "gn:country_code":"NO",
    "gn:dem":580,
    "gn:feature_class":"P",
    "gn:feature_code":"PPL",
    "gn:name":"Gammeld\u00f8ss\u00e6tra",
    "gn:population":0,
    "gn:timezone":"Europe/Oslo",
    "iso:country":"NO",
    "name:nor_x_preferred":[
        "Gammeld\u00f8ss\u00e6tra"
    ],
    "wof:name":"Gammeldossaetra",
    "wof:placetype":"locality"
},
  "geometry": {"coordinates":[10.29902,61.06222],"type":"Point"}
}