{
  "type": "Feature",
  "properties": {
    "gn:admin1_code":"4.0",
    "gn:admin2_code":"616.0",
    "gn:asciiname":"Volelii",
    "gn:country_code":"NO",
    "gn:dem":857,
    "gn:feature_class":"P",
    "gn:feature_code":"PPL",
    "gn:name":"Volelii",
    "gn:population":0,
    "gn:timezone":"Europe/Oslo",
    "iso:country":"NO",
    "name:nor_x_preferred":[
        "Volelii"
    ],
    "name:nor_x_variant":[
        "Volelie"
    ],
    "wof:name":"Volelii",
    "wof:placetype":"locality"
},
  "geometry": {"coordinates":[8.87845,60.53944],"type":"Point"}
}