{
  "type": "Feature",
  "properties": {
    "gn:admin1_code":"6.0",
    "gn:admin2_code":"423.0",
    "gn:asciiname":"Toverud",
    "gn:country_code":"NO",
    "gn:dem":160,
    "gn:feature_class":"P",
    "gn:feature_code":"PPL",
    "gn:name":"Toverud",
    "gn:population":0,
    "gn:timezone":"Europe/Oslo",
    "iso:country":"NO",
    "wof:name":"Toverud",
    "wof:placetype":"locality"
},
  "geometry": {"coordinates":[12.06667,60.53333000000001],"type":"Point"}
}