{
  "type": "Feature",
  "properties": {
    "gn:country":"NO",
    "iso:country":"NO",
    "name:bul_x_preferred":[
        "\u0425\u0432\u0430\u0441\u0435\u0440"
    ],
    "name:ceb_x_preferred":[
        "Hvasser"
    ],
    "name:dan_x_preferred":[
        "Hvasser"
    ],
    "name:eng_x_preferred":[
        "Hvasser"
    ],
    "name:fra_x_preferred":[
        "Hvasser"
    ],
    "name:msa_x_preferred":[
        "Hvasser"
    ],
    "name:nld_x_preferred":[
        "Hvasser"
    ],
    "name:nno_x_preferred":[
        "Hvasser"
    ],
    "name:nob_x_preferred":[
        "Hvasser"
    ],
    "name:rus_x_preferred":[
        "\u0412\u0430\u0441\u0441\u0435\u0440"
    ],
    "name:spa_x_preferred":[
        "Hvasser"
    ],
    "qs_pg:aaroncc":"NO",
    "qs_pg:gn_country":"NO",
    "qs_pg:name":"Hvasser",
    "qs_pg:name_adm0":"Norge",
    "qs_pg:name_adm1":"Vestfold Fylke",
    "qs_pg:photos":572,
    "qs_pg:photos_1k":116,
    "qs_pg:photos_9k":3,
    "qs_pg:photos_9r":5,
    "qs_pg:photos_all":572,
    "qs_pg:photos_sr":8,
    "qs_pg:pop_sr":0,
    "qs_pg:qs_pg_placetype":"locality",
    "qs_pg:qs_pg_placetype_gp":"Town",
    "qs_pg:woe_adm0":23424910,
    "woe:adm0_id":23424910,
    "woe:name_adm0":"Norge",
    "woe:name_adm1":"Vestfold Fylke",
    "woe:placetype":"Town",
    "wof:name":"Hvasser",
    "wof:placetype":"locality"
},
  "geometry": {"coordinates":[10.412204,59.070489],"type":"Point"}
}