{
  "type": "Feature",
  "properties": {
    "gn:admin1_code":"9",
    "gn:admin2_code":"1870.0",
    "gn:asciiname":"Bo",
    "gn:country_code":"NO",
    "gn:dem":1,
    "gn:feature_class":"P",
    "gn:feature_code":"PPL",
    "gn:name":"B\u00f8",
    "gn:population":0,
    "gn:timezone":"Europe/Oslo",
    "iso:country":"NO",
    "name:fas_x_preferred":[
        "\u0628\u0648"
    ],
    "name:fra_x_preferred":[
        "B\u00f8"
    ],
    "name:hun_x_preferred":[
        "Bo"
    ],
    "name:jav_x_preferred":[
        "B\u00f8"
    ],
    "name:msa_x_preferred":[
        "B\u00f8"
    ],
    "wof:name":"Bo",
    "wof:placetype":"locality"
},
  "geometry": {"coordinates":[15.31935,68.65606],"type":"Point"}
}