{
  "type": "Feature",
  "properties": {
    "gn:admin1_code":"4.0",
    "gn:admin2_code":"616.0",
    "gn:asciiname":"Rukke",
    "gn:country_code":"NO",
    "gn:dem":840,
    "gn:feature_class":"P",
    "gn:feature_code":"PPL",
    "gn:name":"Rukke",
    "gn:population":0,
    "gn:timezone":"Europe/Oslo",
    "iso:country":"NO",
    "wof:name":"Rukke",
    "wof:placetype":"locality"
},
  "geometry": {"coordinates":[8.91667,60.51667],"type":"Point"}
}