{
  "type": "Feature",
  "properties": {
    "gn:admin1_code":"6.0",
    "gn:admin2_code":"428.0",
    "gn:asciiname":"Grensen",
    "gn:country_code":"NO",
    "gn:dem":304,
    "gn:feature_class":"P",
    "gn:feature_code":"PPL",
    "gn:name":"Grensen",
    "gn:population":0,
    "gn:timezone":"Europe/Stockholm",
    "iso:country":"NO",
    "name:nor_x_preferred":[
        "Grensen"
    ],
    "wof:name":"Grensen",
    "wof:placetype":"locality"
},
  "geometry": {"coordinates":[12.59629,61.04755],"type":"Point"}
}