{
  "type": "Feature",
  "properties": {
    "gn:admin1_code":"5.0",
    "gn:admin2_code":"2021.0",
    "gn:asciiname":"Haldenjarga",
    "gn:country_code":"NO",
    "gn:dem":140,
    "gn:feature_class":"P",
    "gn:feature_code":"PPL",
    "gn:name":"H\u00e1ldenj\u00e1rga",
    "gn:population":0,
    "gn:timezone":"Europe/Oslo",
    "iso:country":"NO",
    "name:sme_x_preferred":[
        "H\u00e1ldenj\u00e1rga"
    ],
    "wof:name":"Haldenjarga",
    "wof:placetype":"locality"
},
  "geometry": {"coordinates":[25.34358,69.44598000000001],"type":"Point"}
}