{
  "type": "Feature",
  "properties": {
    "gn:admin1_code":"4.0",
    "gn:admin2_code":"618.0",
    "gn:asciiname":"Ulsakstolane",
    "gn:country_code":"NO",
    "gn:dem":880,
    "gn:feature_class":"P",
    "gn:feature_code":"PPL",
    "gn:name":"Uls\u00e5kst\u00f8lane",
    "gn:population":0,
    "gn:timezone":"Europe/Oslo",
    "iso:country":"NO",
    "name:nor_x_preferred":[
        "Uls\u00e5kst\u00f8lane"
    ],
    "wof:name":"Ulsakstolane",
    "wof:placetype":"locality"
},
  "geometry": {"coordinates":[8.70422,60.86861999999999],"type":"Point"}
}