{
  "type": "Feature",
  "properties": {
    "gn:admin1_code":"9",
    "gn:admin2_code":"1833.0",
    "gn:asciiname":"Flostrand",
    "gn:country_code":"NO",
    "gn:dem":10,
    "gn:feature_class":"P",
    "gn:feature_code":"PPL",
    "gn:name":"Flostrand",
    "gn:population":0,
    "gn:timezone":"Europe/Oslo",
    "iso:country":"NO",
    "wof:name":"Flostrand",
    "wof:placetype":"locality"
},
  "geometry": {"coordinates":[13.36858,66.33628],"type":"Point"}
}