{
  "type": "Feature",
  "properties": {
    "gn:admin1_code":"14",
    "gn:admin2_code":"1124",
    "gn:asciiname":"Batstad",
    "gn:country_code":"NO",
    "gn:dem":8,
    "gn:feature_class":"P",
    "gn:feature_code":"PPLL",
    "gn:name":"B\u00e5tstad",
    "gn:population":0,
    "gn:timezone":"Europe/Oslo",
    "iso:country":"NO",
    "name:nor_x_preferred":[
        "B\u00e5tstad"
    ],
    "wof:name":"Batstad",
    "wof:placetype":"neighbourhood"
},
  "geometry": {"coordinates":[5.60682,58.93213000000001],"type":"Point"}
}