{
  "type": "Feature",
  "properties": {
    "gn:admin1_code":"21.0",
    "gn:admin2_code":"5041.0",
    "gn:asciiname":"Vegset",
    "gn:country_code":"NO",
    "gn:dem":280,
    "gn:feature_class":"P",
    "gn:feature_code":"PPL",
    "gn:name":"Vegset",
    "gn:population":0,
    "gn:timezone":"Europe/Oslo",
    "iso:country":"NO",
    "name:nor_x_preferred":[
        "Vegset"
    ],
    "wof:name":"Vegset",
    "wof:placetype":"locality"
},
  "geometry": {"coordinates":[12.25,64.26666999999999],"type":"Point"}
}