{
  "type": "Feature",
  "properties": {
    "gn:admin1_code":"7",
    "gn:admin2_code":"1242",
    "gn:asciiname":"Haga",
    "gn:country":"NO",
    "gn:country_code":"NO",
    "gn:dem":160,
    "gn:fcode":"PPL",
    "gn:feature_class":"P",
    "gn:feature_code":"PPLL",
    "gn:name":"Haga",
    "gn:population":900,
    "gn:timezone":"Europe/Oslo",
    "iso:country":"NO",
    "name:ceb_x_preferred":[
        "Haga"
    ],
    "name:dan_x_preferred":[
        "Haga"
    ],
    "name:deu_x_preferred":[
        "Haga"
    ],
    "name:eng_x_preferred":[
        "Haga"
    ],
    "name:fin_x_preferred":[
        "Haga"
    ],
    "name:fra_x_preferred":[
        "Haga"
    ],
    "name:nld_x_preferred":[
        "Haga"
    ],
    "name:nno_x_preferred":[
        "Haga i Samnanger"
    ],
    "name:nob_x_preferred":[
        "Haga"
    ],
    "name:nor_x_preferred":[
        "Haga"
    ],
    "name:por_x_preferred":[
        "Haga"
    ],
    "name:ron_x_preferred":[
        "Haga"
    ],
    "name:rus_x_preferred":[
        "\u0425\u0430\u0433\u0430"
    ],
    "name:swe_x_preferred":[
        "Haga"
    ],
    "qs_pg:aaroncc":"NO",
    "qs_pg:gn_country":"NO",
    "qs_pg:gn_fcode":"PPL",
    "qs_pg:gn_pop":900,
    "qs_pg:name":"Haga",
    "qs_pg:name_adm0":"Norge",
    "qs_pg:name_adm1":"Hordaland Fylke",
    "qs_pg:photos_9k":1,
    "qs_pg:photos_9r":1,
    "qs_pg:photos_all":15,
    "qs_pg:photos_sr":0,
    "qs_pg:pop_sr":2,
    "qs_pg:qs_pg_placetype":"locality",
    "qs_pg:qs_pg_placetype_gp":"Town",
    "qs_pg:woe_adm0":23424910,
    "woe:adm0_id":23424910,
    "woe:name_adm0":"Norge",
    "woe:name_adm1":"Hordaland Fylke",
    "woe:placetype":"Town",
    "wof:name":"Haga",
    "wof:placetype":"locality",
    "wof:population":900
},
  "geometry": {"coordinates":[5.77056,60.38778],"type":"Point"}
}