{
  "type": "Feature",
  "properties": {
    "gn:admin1_code":"19.0",
    "gn:admin2_code":"1018.0",
    "gn:asciiname":"Repstad",
    "gn:country_code":"NO",
    "gn:dem":41,
    "gn:feature_class":"P",
    "gn:feature_code":"PPL",
    "gn:name":"Repstad",
    "gn:population":0,
    "gn:timezone":"Europe/Oslo",
    "iso:country":"NO",
    "wof:name":"Repstad",
    "wof:placetype":"locality"
},
  "geometry": {"coordinates":[7.75,58.11666999999999],"type":"Point"}
}