{
  "type": "Feature",
  "properties": {
    "gn:admin1_code":"5.0",
    "gn:admin2_code":"2015.0",
    "gn:asciiname":"Breivikbotn",
    "gn:country_code":"NO",
    "gn:dem":40,
    "gn:feature_class":"P",
    "gn:feature_code":"PPLA2",
    "gn:name":"Breivikbotn",
    "gn:population":0,
    "gn:timezone":"Europe/Oslo",
    "iso:country":"NO",
    "name:nor_x_preferred":[
        "Breidvikbotn"
    ],
    "name:nor_x_variant":[
        "Breivikbotn"
    ],
    "wof:name":"Breivikbotn",
    "wof:placetype":"locality"
},
  "geometry": {"coordinates":[22.28712,70.58877],"type":"Point"}
}