{
  "type": "Feature",
  "properties": {
    "gn:country":"NO",
    "gn:fcode":"PPL",
    "gn:population":0,
    "iso:country":"NO",
    "name:eng_x_preferred":[
        "Tran\u00f8y"
    ],
    "name:fra_x_preferred":[
        "Tran\u00f8ya"
    ],
    "name:jav_x_preferred":[
        "Tran\u00f8y"
    ],
    "name:msa_x_preferred":[
        "Tran\u00f8y"
    ],
    "name:nld_x_preferred":[
        "Tran\u00f8y"
    ],
    "name:nob_x_preferred":[
        "Tran\u00f8y"
    ],
    "qs_pg:aaroncc":"NO",
    "qs_pg:gn_country":"NO",
    "qs_pg:gn_fcode":"PPL",
    "qs_pg:gn_pop":0,
    "qs_pg:name":"Tran\u00f8y",
    "qs_pg:name_adm0":"Norge",
    "qs_pg:name_adm1":"Nordland Fylke",
    "qs_pg:photos":148,
    "qs_pg:photos_1k":30,
    "qs_pg:photos_9k":1,
    "qs_pg:photos_9r":3,
    "qs_pg:photos_all":148,
    "qs_pg:photos_sr":3,
    "qs_pg:pop_sr":3,
    "qs_pg:qs_pg_placetype":"locality",
    "qs_pg:qs_pg_placetype_gp":"Town",
    "qs_pg:woe_adm0":23424910,
    "woe:adm0_id":23424910,
    "woe:name_adm0":"Norge",
    "woe:name_adm1":"Nordland Fylke",
    "woe:placetype":"Town",
    "wof:name":"Tran\u00f8y",
    "wof:placetype":"locality"
},
  "geometry": {"coordinates":[15.65833,68.18444],"type":"Point"}
}