{
  "type": "Feature",
  "properties": {
    "gn:admin1_code":"5.0",
    "gn:admin2_code":"2004.0",
    "gn:asciiname":"Eidvageid",
    "gn:country_code":"NO",
    "gn:dem":1,
    "gn:feature_class":"P",
    "gn:feature_code":"PPL",
    "gn:name":"Eidv\u00e5geid",
    "gn:population":0,
    "gn:timezone":"Europe/Oslo",
    "iso:country":"NO",
    "name:nor_x_preferred":[
        "Eidv\u00e5geid"
    ],
    "name:nor_x_variant":[
        "Eidv\u00e5geidet"
    ],
    "name:sme_x_preferred":[
        "Roavvi"
    ],
    "wof:name":"Eidvageid",
    "wof:placetype":"locality"
},
  "geometry": {"coordinates":[23.53661,70.53955000000001],"type":"Point"}
}