{
  "type": "Feature",
  "properties": {
    "gn:admin1_code":"7.0",
    "gn:admin2_code":"1221.0",
    "gn:asciiname":"Sor-Huglo",
    "gn:country_code":"NO",
    "gn:dem":9,
    "gn:feature_class":"P",
    "gn:feature_code":"PPL",
    "gn:name":"S\u00f8r-Huglo",
    "gn:population":0,
    "gn:timezone":"Europe/Oslo",
    "iso:country":"NO",
    "wof:name":"Sor-Huglo",
    "wof:placetype":"locality"
},
  "geometry": {"coordinates":[5.57218,59.83316],"type":"Point"}
}