{
  "type": "Feature",
  "properties": {
    "gn:admin1_code":"15.0",
    "gn:admin2_code":"1428.0",
    "gn:asciiname":"Ytre-Vardal",
    "gn:country_code":"NO",
    "gn:dem":3,
    "gn:feature_class":"P",
    "gn:feature_code":"PPL",
    "gn:name":"Ytre-V\u00e5rdal",
    "gn:population":0,
    "gn:timezone":"Europe/Oslo",
    "iso:country":"NO",
    "wof:name":"Ytre-Vardal",
    "wof:placetype":"locality"
},
  "geometry": {"coordinates":[5.15865,61.33713],"type":"Point"}
}