{
  "type": "Feature",
  "properties": {
    "gn:admin1_code":"13",
    "gn:admin2_code":"106",
    "gn:asciiname":"Skiviken",
    "gn:country_code":"NO",
    "gn:dem":25,
    "gn:feature_class":"P",
    "gn:feature_code":"PPL",
    "gn:name":"Skiviken",
    "gn:population":0,
    "gn:timezone":"Europe/Oslo",
    "iso:country":"NO",
    "name:jav_x_preferred":[
        "Skj\u00e6rvika"
    ],
    "name:msa_x_preferred":[
        "Skj\u00e6rvika"
    ],
    "name:nld_x_preferred":[
        "Skivika"
    ],
    "name:nno_x_preferred":[
        "Skivika"
    ],
    "name:nor_x_preferred":[
        "Skiviken"
    ],
    "name:nor_x_variant":[
        "Skivika",
        "Skj\u00e6rvika"
    ],
    "name:ron_x_preferred":[
        "Skivika"
    ],
    "name:spa_x_preferred":[
        "Skivika"
    ],
    "name:swe_x_preferred":[
        "Skivika"
    ],
    "wof:name":"Skiviken",
    "wof:placetype":"locality"
},
  "geometry": {"coordinates":[11.0741,59.21523000000001],"type":"Point"}
}