{
  "type": "Feature",
  "properties": {
    "gn:admin1_code":"14",
    "gn:admin2_code":"1119.0",
    "gn:asciiname":"Brattland",
    "gn:cc2":"NO",
    "gn:country_code":"NO",
    "gn:dem":13,
    "gn:feature_class":"P",
    "gn:feature_code":"PPL",
    "gn:name":"Brattland",
    "gn:population":0,
    "gn:timezone":"Europe/Oslo",
    "iso:country":"NO",
    "name:und_x_variant":[
        "Bratlend",
        "Brattlend",
        "Brattland"
    ],
    "wof:name":"Brattland",
    "wof:placetype":"locality"
},
  "geometry": {"coordinates":[5.61667,58.61666999999999],"type":"Point"}
}