{
  "type": "Feature",
  "properties": {
    "gn:admin1_code":"7",
    "gn:admin2_code":"1244.0",
    "gn:asciiname":"Bjelland",
    "gn:country_code":"NO",
    "gn:dem":20,
    "gn:feature_class":"P",
    "gn:feature_code":"PPL",
    "gn:name":"Bjelland",
    "gn:population":0,
    "gn:timezone":"Europe/Oslo",
    "iso:country":"NO",
    "name:msa_x_preferred":[
        "Bjelland"
    ],
    "name:nld_x_preferred":[
        "Bjelland"
    ],
    "wof:name":"Bjelland",
    "wof:placetype":"locality"
},
  "geometry": {"coordinates":[5.26667,60.08333],"type":"Point"}
}