{
  "type": "Feature",
  "properties": {
    "gn:admin1_code":"7",
    "gn:admin2_code":"1256",
    "gn:asciiname":"Flatoy",
    "gn:country_code":"NO",
    "gn:dem":3,
    "gn:feature_class":"P",
    "gn:feature_code":"PPLL",
    "gn:name":"Flat\u00f8y",
    "gn:population":0,
    "gn:timezone":"Europe/Oslo",
    "iso:country":"NO",
    "name:nor_x_preferred":[
        "Flat\u00f8y"
    ],
    "wof:name":"Flatoy",
    "wof:placetype":"locality"
},
  "geometry": {"coordinates":[5.25948,60.53459],"type":"Point"}
}