{
  "type": "Feature",
  "properties": {
    "gn:admin1_code":"21",
    "gn:admin2_code":"5004.0",
    "gn:asciiname":"Froset",
    "gn:country_code":"NO",
    "gn:dem":100,
    "gn:feature_class":"P",
    "gn:feature_code":"PPL",
    "gn:name":"Fr\u00f8set",
    "gn:population":0,
    "gn:timezone":"Europe/Oslo",
    "iso:country":"NO",
    "name:nor_x_preferred":[
        "Fr\u00f8set"
    ],
    "wof:name":"Froset",
    "wof:placetype":"locality"
},
  "geometry": {"coordinates":[11.43333,63.98333],"type":"Point"}
}