{
  "type": "Feature",
  "properties": {
    "gn:admin1_code":"1.0",
    "gn:admin2_code":"237.0",
    "gn:asciiname":"Vestby",
    "gn:country_code":"NO",
    "gn:dem":180,
    "gn:feature_class":"P",
    "gn:feature_code":"PPL",
    "gn:name":"Vestby",
    "gn:population":0,
    "gn:timezone":"Europe/Oslo",
    "iso:country":"NO",
    "name:ara_x_preferred":[
        "\u0641\u064a\u0633\u062a\u0628\u064a"
    ],
    "name:bpy_x_preferred":[
        "\u09ac\u09c7\u09b8\u09cd\u099f\u09ac\u09be\u0987"
    ],
    "name:cat_x_preferred":[
        "Vestby"
    ],
    "name:ceb_x_preferred":[
        "Vestby"
    ],
    "name:dan_x_preferred":[
        "Vestby"
    ],
    "name:deu_x_preferred":[
        "Vestby"
    ],
    "name:epo_x_preferred":[
        "Vestby"
    ],
    "name:eus_x_preferred":[
        "Vestby"
    ],
    "name:fin_x_preferred":[
        "Vestby"
    ],
    "name:fra_x_preferred":[
        "Vestby"
    ],
    "name:glg_x_preferred":[
        "Vestby"
    ],
    "name:hye_x_preferred":[
        "\u054e\u0565\u057d\u0569\u0562\u0575\u0578\u0582"
    ],
    "name:ita_x_preferred":[
        "Vestby"
    ],
    "name:jav_x_preferred":[
        "Vestby"
    ],
    "name:lat_x_preferred":[
        "Vestby"
    ],
    "name:lim_x_preferred":[
        "Vestby"
    ],
    "name:msa_x_preferred":[
        "Vestby"
    ],
    "name:nds_x_preferred":[
        "Kommun Vestby"
    ],
    "name:nld_x_preferred":[
        "Vestby"
    ],
    "name:nno_x_preferred":[
        "Vestby kommune"
    ],
    "name:nor_x_preferred":[
        "Vestby"
    ],
    "name:pol_x_preferred":[
        "Vestby"
    ],
    "name:por_x_preferred":[
        "Vestby"
    ],
    "name:ron_x_preferred":[
        "Vestby"
    ],
    "name:rus_x_preferred":[
        "\u0412\u0435\u0441\u0442\u0431\u044e"
    ],
    "name:slv_x_preferred":[
        "Vestby"
    ],
    "name:sme_x_preferred":[
        "Vestby"
    ],
    "name:spa_x_preferred":[
        "Vestby"
    ],
    "name:sqi_x_preferred":[
        "Vestby"
    ],
    "name:swe_x_preferred":[
        "Vestby kommun"
    ],
    "name:vie_x_preferred":[
        "Vestby"
    ],
    "name:war_x_preferred":[
        "Vestby"
    ],
    "name:zho_x_preferred":[
        "\u97cb\u65af\u7279\u6bd4"
    ],
    "wof:name":"Vestby",
    "wof:placetype":"locality"
},
  "geometry": {"coordinates":[11.18333,60.25],"type":"Point"}
}