{
  "type": "Feature",
  "properties": {
    "gn:admin1_code":"21",
    "gn:admin2_code":"5001.0",
    "gn:asciiname":"Kystad",
    "gn:country_code":"NO",
    "gn:dem":180,
    "gn:feature_class":"P",
    "gn:feature_code":"PPL",
    "gn:name":"Kystad",
    "gn:population":0,
    "gn:timezone":"Europe/Oslo",
    "iso:country":"NO",
    "name:nor_x_preferred":[
        "Kystad"
    ],
    "wof:name":"Kystad",
    "wof:placetype":"locality"
},
  "geometry": {"coordinates":[10.33333,63.38333000000001],"type":"Point"}
}