{
  "type": "Feature",
  "properties": {
    "gn:admin1_code":"2.0",
    "gn:admin2_code":"919.0",
    "gn:asciiname":"Roed",
    "gn:country_code":"NO",
    "gn:dem":82,
    "gn:feature_class":"P",
    "gn:feature_code":"PPL",
    "gn:name":"R\u00f8ed",
    "gn:population":0,
    "gn:timezone":"Europe/Oslo",
    "iso:country":"NO",
    "name:nor_x_preferred":[
        "R\u00f8ed"
    ],
    "wof:name":"Roed",
    "wof:placetype":"locality"
},
  "geometry": {"coordinates":[8.65051,58.50754000000001],"type":"Point"}
}