{
  "type": "Feature",
  "properties": {
    "gn:admin1_code":"6",
    "gn:admin2_code":"425.0",
    "gn:asciiname":"Flissundet",
    "gn:cc2":"NO",
    "gn:country_code":"NO",
    "gn:dem":200,
    "gn:feature_class":"P",
    "gn:feature_code":"PPL",
    "gn:name":"Flissundet",
    "gn:population":0,
    "gn:timezone":"Europe/Oslo",
    "iso:country":"NO",
    "name:und_x_variant":[
        "Flissund",
        "Flissundet"
    ],
    "wof:name":"Flissundet",
    "wof:placetype":"locality"
},
  "geometry": {"coordinates":[12.03333,60.61666999999999],"type":"Point"}
}