{
  "type": "Feature",
  "properties": {
    "gn:country":"NO",
    "gn:fcode":"PPL",
    "gn:population":371,
    "iso:country":"NO",
    "name:ceb_x_preferred":[
        "Her\u00f8ysund"
    ],
    "name:eng_x_preferred":[
        "Her\u00f8ysund"
    ],
    "name:fra_x_preferred":[
        "Her\u00f8ysund"
    ],
    "name:nld_x_preferred":[
        "Her\u00f8ysund"
    ],
    "name:nno_x_preferred":[
        "Her\u00f8ysund"
    ],
    "name:nob_x_preferred":[
        "Her\u00f8ysund"
    ],
    "name:ron_x_preferred":[
        "Her\u00f8ysund"
    ],
    "name:spa_x_preferred":[
        "Her\u00f8ysund"
    ],
    "name:und_x_variant":[
        "Her\u00f8ysundet"
    ],
    "qs_pg:aaroncc":"NO",
    "qs_pg:gn_country":"NO",
    "qs_pg:gn_fcode":"PPL",
    "qs_pg:gn_pop":371,
    "qs_pg:name":"Her\u00f8ysund",
    "qs_pg:photos_9r":0,
    "qs_pg:photos_sr":0,
    "qs_pg:pop_sr":2,
    "qs_pg:qs_pg_placetype":"locality",
    "wof:name":"Her\u00f8ysund",
    "wof:placetype":"locality",
    "wof:population":371
},
  "geometry": {"coordinates":[5.78944,59.91722],"type":"Point"}
}