{
  "type": "Feature",
  "properties": {
    "gn:admin1_code":"5.0",
    "gn:admin2_code":"2025.0",
    "gn:asciiname":"Tana bru",
    "gn:country_code":"NO",
    "gn:dem":12,
    "gn:feature_class":"P",
    "gn:feature_code":"PPLA2",
    "gn:name":"Tana bru",
    "gn:population":0,
    "gn:timezone":"Europe/Oslo",
    "iso:country":"NO",
    "wof:name":"Tana bru",
    "wof:placetype":"locality"
},
  "geometry": {"coordinates":[28.19039,70.19909],"type":"Point"}
}