{
  "type": "Feature",
  "properties": {
    "gn:admin1_code":"18",
    "gn:admin2_code":"1919.0",
    "gn:asciiname":"Foldvika",
    "gn:cc2":"NO",
    "gn:country_code":"NO",
    "gn:dem":1,
    "gn:feature_class":"P",
    "gn:feature_code":"PPL",
    "gn:name":"Foldvika",
    "gn:population":0,
    "gn:timezone":"Europe/Oslo",
    "iso:country":"NO",
    "name:und_x_variant":[
        "Foldvik",
        "Foldvika"
    ],
    "wof:name":"Foldvika",
    "wof:placetype":"locality"
},
  "geometry": {"coordinates":[17.42513,68.69270999999999],"type":"Point"}
}