{
  "type": "Feature",
  "properties": {
    "gn:admin1_code":"21.0",
    "gn:admin2_code":"5041.0",
    "gn:asciiname":"Overbygda",
    "gn:cc2":"NO",
    "gn:country_code":"NO",
    "gn:dem":84,
    "gn:feature_class":"P",
    "gn:feature_code":"PPL",
    "gn:name":"\u00d8verbygda",
    "gn:population":0,
    "gn:timezone":"Europe/Oslo",
    "iso:country":"NO",
    "name:und_x_variant":[
        "Overbygden",
        "\u00d8verbygda"
    ],
    "wof:name":"Overbygda",
    "wof:placetype":"locality"
},
  "geometry": {"coordinates":[12.46667,64.25],"type":"Point"}
}