{
  "type": "Feature",
  "properties": {
    "gn:admin1_code":"19",
    "gn:admin2_code":"1018.0",
    "gn:asciiname":"Fuglevik",
    "gn:cc2":"NO",
    "gn:country_code":"NO",
    "gn:dem":18,
    "gn:feature_class":"P",
    "gn:feature_code":"PPL",
    "gn:name":"Fuglevik",
    "gn:population":0,
    "gn:timezone":"Europe/Oslo",
    "iso:country":"NO",
    "name:jav_x_preferred":[
        "Fuglevik"
    ],
    "name:msa_x_preferred":[
        "Fuglevik"
    ],
    "name:nld_x_preferred":[
        "Fuglevik"
    ],
    "name:nno_x_preferred":[
        "Fuglevik"
    ],
    "name:nor_x_preferred":[
        "Fuglevik"
    ],
    "name:ron_x_preferred":[
        "Fuglevik"
    ],
    "name:spa_x_preferred":[
        "Fuglevik"
    ],
    "name:swe_x_preferred":[
        "Fuglevik"
    ],
    "name:und_x_variant":[
        "Fuvig"
    ],
    "wof:name":"Fuglevik",
    "wof:placetype":"locality"
},
  "geometry": {"coordinates":[7.66667,58.03333000000001],"type":"Point"}
}