{
  "type": "Feature",
  "properties": {
    "gn:admin1_code":"4.0",
    "gn:admin2_code":"623.0",
    "gn:asciiname":"Skredsvik",
    "gn:country_code":"NO",
    "gn:dem":91,
    "gn:feature_class":"P",
    "gn:feature_code":"PPL",
    "gn:name":"Skredsvik",
    "gn:population":0,
    "gn:timezone":"Europe/Oslo",
    "iso:country":"NO",
    "wof:name":"Skredsvik",
    "wof:placetype":"locality"
},
  "geometry": {"coordinates":[9.95,59.91667],"type":"Point"}
}