{
  "type": "Feature",
  "properties": {
    "gn:admin1_code":"11.0",
    "gn:admin2_code":"515.0",
    "gn:asciiname":"Nedre Bringen",
    "gn:country_code":"NO",
    "gn:dem":760,
    "gn:feature_class":"P",
    "gn:feature_code":"PPL",
    "gn:name":"Nedre Bringen",
    "gn:population":0,
    "gn:timezone":"Europe/Oslo",
    "iso:country":"NO",
    "name:nor_x_preferred":[
        "Nedre Bringen"
    ],
    "wof:name":"Nedre Bringen",
    "wof:placetype":"locality"
},
  "geometry": {"coordinates":[9.18519,61.79821],"type":"Point"}
}