{
  "type": "Feature",
  "properties": {
    "gn:admin1_code":"17.0",
    "gn:admin2_code":"807.0",
    "gn:asciiname":"Busnesgrenda",
    "gn:country_code":"NO",
    "gn:dem":275,
    "gn:feature_class":"P",
    "gn:feature_code":"PPL",
    "gn:name":"Busnesgrenda",
    "gn:population":0,
    "gn:timezone":"Europe/Oslo",
    "iso:country":"NO",
    "wof:name":"Busnesgrenda",
    "wof:placetype":"locality"
},
  "geometry": {"coordinates":[8.98599,59.81641],"type":"Point"}
}