{
  "type": "Feature",
  "properties": {
    "gn:admin1_code":"8",
    "gn:admin2_code":"1504.0",
    "gn:asciiname":"Breidvik",
    "gn:cc2":"NO",
    "gn:country_code":"NO",
    "gn:dem":-9999,
    "gn:feature_class":"P",
    "gn:feature_code":"PPL",
    "gn:name":"Breidvik",
    "gn:population":0,
    "gn:timezone":"Europe/Oslo",
    "iso:country":"NO",
    "name:und_x_variant":[
        "Brejvik",
        "Bredvik",
        "Breidvik"
    ],
    "wof:name":"Breidvik",
    "wof:placetype":"neighbourhood"
},
  "geometry": {"coordinates":[6.35568,62.44938000000001],"type":"Point"}
}