{
  "type": "Feature",
  "properties": {
    "gn:admin1_code":"7",
    "gn:admin2_code":"1260.0",
    "gn:asciiname":"Kvaleim",
    "gn:country_code":"NO",
    "gn:dem":6,
    "gn:feature_class":"P",
    "gn:feature_code":"PPLL",
    "gn:name":"Kvaleim",
    "gn:population":0,
    "gn:timezone":"Europe/Oslo",
    "iso:country":"NO",
    "wof:name":"Kvaleim",
    "wof:placetype":"locality"
},
  "geometry": {"coordinates":[4.93694,60.68806],"type":"Point"}
}