{
  "type": "Feature",
  "properties": {
    "gn:country":"NO",
    "gn:fcode":"PPL",
    "gn:population":0,
    "iso:country":"NO",
    "name:nld_x_preferred":[
        "Rolvs\u00f8y"
    ],
    "name:nor_x_preferred":[
        "Rolvs\u00f8y"
    ],
    "qs_pg:aaroncc":"NO",
    "qs_pg:gn_country":"NO",
    "qs_pg:gn_fcode":"PPL",
    "qs_pg:gn_pop":0,
    "qs_pg:name":"Rolvs\u00f8y",
    "qs_pg:name_adm0":"Norge",
    "qs_pg:name_adm1":"\u00d8stfold Fylke",
    "qs_pg:photos":53,
    "qs_pg:photos_1k":11,
    "qs_pg:photos_9k":1,
    "qs_pg:photos_9r":2,
    "qs_pg:photos_all":53,
    "qs_pg:photos_sr":2,
    "qs_pg:pop_sr":0,
    "qs_pg:qs_pg_placetype":"locality",
    "qs_pg:qs_pg_placetype_gp":"Town",
    "qs_pg:woe_adm0":23424910,
    "woe:adm0_id":23424910,
    "woe:name_adm0":"Norge",
    "woe:name_adm1":"\u00d8stfold Fylke",
    "woe:placetype":"Town",
    "wof:name":"Rolvs\u00f8y",
    "wof:placetype":"neighbourhood"
},
  "geometry": {"coordinates":[11.01667,59.26667],"type":"Point"}
}