{
  "type": "Feature",
  "properties": {
    "gn:admin1_code":"6",
    "gn:admin2_code":"402.0",
    "gn:asciiname":"Gjermshus",
    "gn:country_code":"NO",
    "gn:dem":260,
    "gn:feature_class":"P",
    "gn:feature_code":"PPL",
    "gn:name":"Gjermshus",
    "gn:population":0,
    "gn:timezone":"Europe/Oslo",
    "iso:country":"NO",
    "wof:name":"Gjermshus",
    "wof:placetype":"locality"
},
  "geometry": {"coordinates":[12.09376,60.13735],"type":"Point"}
}