{
  "type": "Feature",
  "properties": {
    "gn:admin1_code":"18",
    "gn:admin2_code":"1927.0",
    "gn:asciiname":"Molnevika",
    "gn:country_code":"NO",
    "gn:dem":101,
    "gn:feature_class":"P",
    "gn:feature_code":"PPL",
    "gn:name":"M\u00f8lnevika",
    "gn:population":0,
    "gn:timezone":"Europe/Oslo",
    "iso:country":"NO",
    "wof:name":"Molnevika",
    "wof:placetype":"locality"
},
  "geometry": {"coordinates":[17.61194,69.1525],"type":"Point"}
}