{
  "type": "Feature",
  "properties": {
    "gn:admin1_code":"4",
    "gn:admin2_code":"615.0",
    "gn:asciiname":"Kolsrud",
    "gn:country_code":"NO",
    "gn:dem":310,
    "gn:feature_class":"P",
    "gn:feature_code":"PPL",
    "gn:name":"Kolsrud",
    "gn:population":0,
    "gn:timezone":"Europe/Oslo",
    "iso:country":"NO",
    "name:nor_x_preferred":[
        "Kolsrud"
    ],
    "name:swe_x_preferred":[
        "Kolsrud"
    ],
    "wof:name":"Kolsrud",
    "wof:placetype":"locality"
},
  "geometry": {"coordinates":[9.31667,60.45],"type":"Point"}
}