{
  "type": "Feature",
  "properties": {
    "gn:admin1_code":"1.0",
    "gn:admin2_code":"231.0",
    "gn:asciiname":"Nybraten",
    "gn:country_code":"NO",
    "gn:dem":198,
    "gn:feature_class":"P",
    "gn:feature_code":"PPL",
    "gn:name":"Nybr\u00e5ten",
    "gn:population":0,
    "gn:timezone":"Europe/Oslo",
    "iso:country":"NO",
    "name:nor_x_preferred":[
        "Nybr\u00e5ten"
    ],
    "wof:name":"Nybraten",
    "wof:placetype":"locality"
},
  "geometry": {"coordinates":[11.13102,59.98619],"type":"Point"}
}