{
  "type": "Feature",
  "properties": {
    "gn:admin1_code":"6.0",
    "gn:admin2_code":"437.0",
    "gn:asciiname":"Stromsasgrenda",
    "gn:cc2":"NO",
    "gn:country_code":"NO",
    "gn:dem":640,
    "gn:feature_class":"P",
    "gn:feature_code":"PPL",
    "gn:name":"Str\u00f8ms\u00e5sgrenda",
    "gn:population":0,
    "gn:timezone":"Europe/Oslo",
    "iso:country":"NO",
    "name:und_x_variant":[
        "Str\u00f6msaas",
        "Str\u00f8ms\u00e5s"
    ],
    "wof:name":"Stromsasgrenda",
    "wof:placetype":"locality"
},
  "geometry": {"coordinates":[10.5954,62.22094],"type":"Point"}
}