{
  "type": "Feature",
  "properties": {
    "gn:admin1_code":"5.0",
    "gn:admin2_code":"2021.0",
    "gn:asciiname":"Ajonjarga",
    "gn:country_code":"NO",
    "gn:dem":140,
    "gn:feature_class":"P",
    "gn:feature_code":"PPL",
    "gn:name":"\u00c1jonj\u00e1rga",
    "gn:population":0,
    "gn:timezone":"Europe/Oslo",
    "iso:country":"NO",
    "name:sme_x_preferred":[
        "\u00c1jonj\u00e1rga"
    ],
    "wof:name":"Ajonjarga",
    "wof:placetype":"locality"
},
  "geometry": {"coordinates":[25.60588,69.45269999999999],"type":"Point"}
}