{
  "type": "Feature",
  "properties": {
    "gn:admin1_code":"7.0",
    "gn:admin2_code":"1235.0",
    "gn:asciiname":"Tysso",
    "gn:cc2":"NO",
    "gn:country_code":"NO",
    "gn:dem":84,
    "gn:feature_class":"P",
    "gn:feature_code":"PPL",
    "gn:name":"Tysso",
    "gn:population":0,
    "gn:timezone":"Europe/Oslo",
    "iso:country":"NO",
    "name:und_x_variant":[
        "Tyssen",
        "Tysso"
    ],
    "wof:name":"Tysso",
    "wof:placetype":"locality"
},
  "geometry": {"coordinates":[5.88333,60.63333000000001],"type":"Point"}
}