{
  "type": "Feature",
  "properties": {
    "gn:admin1_code":"7",
    "gn:admin2_code":"1231.0",
    "gn:asciiname":"Espe",
    "gn:cc2":"NO",
    "gn:country_code":"NO",
    "gn:dem":860,
    "gn:feature_class":"P",
    "gn:feature_code":"PPL",
    "gn:name":"Espe",
    "gn:population":0,
    "gn:timezone":"Europe/Oslo",
    "iso:country":"NO",
    "name:ceb_x_preferred":[
        "Espe"
    ],
    "name:dan_x_preferred":[
        "Espe"
    ],
    "name:deu_x_preferred":[
        "Espe"
    ],
    "name:nld_x_preferred":[
        "Espe"
    ],
    "name:swe_x_preferred":[
        "Espe"
    ],
    "name:und_x_variant":[
        "Espa"
    ],
    "wof:name":"Espe",
    "wof:placetype":"locality"
},
  "geometry": {"coordinates":[6.61667,60.21666999999999],"type":"Point"}
}