{
  "type": "Feature",
  "properties": {
    "iso:country":"NO",
    "name:nor_x_preferred":[
        "Asvang"
    ],
    "qs:gn_adm0_cc":"NO",
    "qs:gn_local":3133880,
    "qs:local_max":5709,
    "qs:local_sum":31956,
    "qs:localhoods":65,
    "qs:name":"Asvang",
    "qs:name_adm0":"Norge",
    "qs:name_adm1":"S\u00f8r-Tr\u00f8ndelag Fylke",
    "qs:name_adm2":"Trondheim Kommune",
    "qs:name_local":"Trondheim",
    "qs:photo_max":14,
    "qs:photo_sum":39,
    "qs:placetype":"Suburb",
    "qs:quad_count":9,
    "qs:woe_adm0":23424910,
    "qs:woe_adm1":2346399,
    "qs:woe_adm2":12592932,
    "qs:woe_lau":0,
    "qs:woe_local":865157,
    "qs:woe_ver":"7.10.0",
    "wof:lang":[
        "nor"
    ],
    "wof:name":"Asvang",
    "wof:placetype":"neighbourhood"
},
  "geometry": {"coordinates":[10.449539,63.411228],"type":"Point"}
}