{
  "type": "Feature",
  "properties": {
    "gn:admin1_code":"8.0",
    "gn:admin2_code":"1520.0",
    "gn:asciiname":"Vartdal",
    "gn:cc2":"NO",
    "gn:country_code":"NO",
    "gn:dem":1,
    "gn:feature_class":"P",
    "gn:feature_code":"PPL",
    "gn:name":"Vartdal",
    "gn:population":0,
    "gn:timezone":"Europe/Oslo",
    "iso:country":"NO",
    "name:fas_x_preferred":[
        "\u0648\u0631\u062a\u062f\u0644"
    ],
    "name:nno_x_preferred":[
        "Vartdal kommune"
    ],
    "name:nor_x_preferred":[
        "Vartdal"
    ],
    "name:nor_x_variant":[
        "S\u00f8re Vartdal"
    ],
    "name:und_x_variant":[
        "Vartdal S\u00f8re"
    ],
    "wof:name":"Vartdal",
    "wof:placetype":"locality"
},
  "geometry": {"coordinates":[6.0822,62.30047],"type":"Point"}
}