{
  "type": "Feature",
  "properties": {
    "gn:admin1_code":"17",
    "gn:admin2_code":"821.0",
    "gn:asciiname":"Li",
    "gn:country_code":"NO",
    "gn:dem":147,
    "gn:feature_class":"P",
    "gn:feature_code":"PPL",
    "gn:name":"Li",
    "gn:population":0,
    "gn:timezone":"Europe/Oslo",
    "iso:country":"NO",
    "name:bos_x_preferred":[
        "Li"
    ],
    "name:hun_x_preferred":[
        "Li"
    ],
    "name:hye_x_preferred":[
        "\u053c\u056b"
    ],
    "name:rus_x_preferred":[
        "Li"
    ],
    "name:tha_x_preferred":[
        "\u0e25\u0e35\u0e49"
    ],
    "name:ukr_x_preferred":[
        "Li"
    ],
    "name:zho_x_preferred":[
        "Li"
    ],
    "wof:name":"Li",
    "wof:placetype":"locality"
},
  "geometry": {"coordinates":[9.01667,59.43333000000001],"type":"Point"}
}