{
  "type": "Feature",
  "properties": {
    "gn:admin1_code":"7",
    "gn:admin2_code":"1253.0",
    "gn:asciiname":"Lotveit",
    "gn:country_code":"NO",
    "gn:dem":154,
    "gn:feature_class":"P",
    "gn:feature_code":"PPL",
    "gn:name":"L\u00f8tveit",
    "gn:population":0,
    "gn:timezone":"Europe/Oslo",
    "iso:country":"NO",
    "wof:name":"Lotveit",
    "wof:placetype":"locality"
},
  "geometry": {"coordinates":[5.58333,60.58333],"type":"Point"}
}