{
  "type": "Feature",
  "properties": {
    "gn:admin1_code":"9",
    "gn:admin2_code":"1820.0",
    "gn:asciiname":"Myklebostad",
    "gn:country_code":"NO",
    "gn:dem":-9999,
    "gn:feature_class":"P",
    "gn:feature_code":"PPL",
    "gn:name":"Myklebostad",
    "gn:population":0,
    "gn:timezone":"Europe/Oslo",
    "iso:country":"NO",
    "wof:name":"Myklebostad",
    "wof:placetype":"locality"
},
  "geometry": {"coordinates":[12.46667,65.76666999999999],"type":"Point"}
}