{
  "type": "Feature",
  "properties": {
    "gn:admin1_code":"7.0",
    "gn:admin2_code":"1224.0",
    "gn:asciiname":"Skjelnes",
    "gn:country_code":"NO",
    "gn:dem":20,
    "gn:feature_class":"P",
    "gn:feature_code":"PPL",
    "gn:name":"Skjelnes",
    "gn:population":0,
    "gn:timezone":"Europe/Oslo",
    "iso:country":"NO",
    "wof:name":"Skjelnes",
    "wof:placetype":"locality"
},
  "geometry": {"coordinates":[5.98333,60.08333],"type":"Point"}
}