{
  "type": "Feature",
  "properties": {
    "gn:admin1_code":"6.0",
    "gn:admin2_code":"403.0",
    "gn:asciiname":"Bringbusaetra",
    "gn:country_code":"NO",
    "gn:dem":540,
    "gn:feature_class":"P",
    "gn:feature_code":"PPL",
    "gn:name":"Bringbus\u00e6tra",
    "gn:population":0,
    "gn:timezone":"Europe/Oslo",
    "iso:country":"NO",
    "name:nor_x_preferred":[
        "Bringbus\u00e6tra"
    ],
    "wof:name":"Bringbusaetra",
    "wof:placetype":"locality"
},
  "geometry": {"coordinates":[11.05715,61.10456],"type":"Point"}
}