{
  "type": "Feature",
  "properties": {
    "gn:admin1_code":"6.0",
    "gn:admin2_code":"428.0",
    "gn:asciiname":"Storsvea",
    "gn:country_code":"NO",
    "gn:dem":560,
    "gn:feature_class":"P",
    "gn:feature_code":"PPL",
    "gn:name":"Storsvea",
    "gn:population":0,
    "gn:timezone":"Europe/Oslo",
    "iso:country":"NO",
    "wof:name":"Storsvea",
    "wof:placetype":"locality"
},
  "geometry": {"coordinates":[12.1046,61.09114],"type":"Point"}
}