{
  "type": "Feature",
  "properties": {
    "gn:admin1_code":"5.0",
    "gn:admin2_code":"2003.0",
    "gn:asciiname":"Kiby",
    "gn:country_code":"NO",
    "gn:dem":-9999,
    "gn:feature_class":"P",
    "gn:feature_code":"PPLL",
    "gn:name":"Kiby",
    "gn:population":0,
    "gn:timezone":"Europe/Oslo",
    "iso:country":"NO",
    "name:jav_x_preferred":[
        "Kiby"
    ],
    "name:msa_x_preferred":[
        "Kiby"
    ],
    "name:nor_x_preferred":[
        "Kiby"
    ],
    "name:swe_x_preferred":[
        "Kiby"
    ],
    "wof:name":"Kiby",
    "wof:placetype":"locality"
},
  "geometry": {"coordinates":[29.85667,70.06249],"type":"Point"}
}