{
  "type": "Feature",
  "properties": {
    "gn:admin1_code":"4.0",
    "gn:admin2_code":"616.0",
    "gn:asciiname":"Gronhovd",
    "gn:country_code":"NO",
    "gn:dem":929,
    "gn:feature_class":"P",
    "gn:feature_code":"PPL",
    "gn:name":"Gr\u00f8nhovd",
    "gn:population":0,
    "gn:timezone":"Europe/Oslo",
    "iso:country":"NO",
    "name:nor_x_preferred":[
        "Gr\u00f8nhovd"
    ],
    "wof:name":"Gronhovd",
    "wof:placetype":"locality"
},
  "geometry": {"coordinates":[8.76297,60.53255],"type":"Point"}
}