{
  "type": "Feature",
  "properties": {
    "gn:country":"NO",
    "gn:fcode":"PPL",
    "gn:population":0,
    "iso:country":"NO",
    "name:afr_x_preferred":[
        "Barmen"
    ],
    "name:cat_x_preferred":[
        "Barmen"
    ],
    "name:deu_x_preferred":[
        "Barmen"
    ],
    "name:epo_x_preferred":[
        "Barmen"
    ],
    "name:fra_x_preferred":[
        "Barmen"
    ],
    "name:hun_x_preferred":[
        "Barmen"
    ],
    "name:ksh_x_preferred":[
        "Barmen"
    ],
    "name:rus_x_preferred":[
        "\u0411\u0430\u0440\u043c\u0435\u043d"
    ],
    "name:sco_x_preferred":[
        "Barmen"
    ],
    "qs_pg:aaroncc":"NO",
    "qs_pg:gn_country":"NO",
    "qs_pg:gn_fcode":"PPL",
    "qs_pg:gn_pop":0,
    "qs_pg:name":"Barmen",
    "qs_pg:name_adm0":"Norge",
    "qs_pg:name_adm1":"Sogn og Fjordane Fylke",
    "qs_pg:photos":47,
    "qs_pg:photos_1k":10,
    "qs_pg:photos_9k":1,
    "qs_pg:photos_9r":2,
    "qs_pg:photos_all":47,
    "qs_pg:photos_sr":2,
    "qs_pg:pop_sr":0,
    "qs_pg:qs_pg_placetype":"locality",
    "qs_pg:qs_pg_placetype_gp":"Town",
    "qs_pg:woe_adm0":23424910,
    "woe:adm0_id":23424910,
    "woe:name_adm0":"Norge",
    "woe:name_adm1":"Sogn og Fjordane Fylke",
    "woe:placetype":"Town",
    "wof:name":"Barmen",
    "wof:placetype":"locality"
},
  "geometry": {"coordinates":[5.29,61.99917],"type":"Point"}
}