{
  "type": "Feature",
  "properties": {
    "gn:admin1_code":"21",
    "gn:admin2_code":"5032.0",
    "gn:asciiname":"Grottem",
    "gn:country_code":"NO",
    "gn:dem":157,
    "gn:feature_class":"P",
    "gn:feature_code":"PPL",
    "gn:name":"Gr\u00f8ttem",
    "gn:population":0,
    "gn:timezone":"Europe/Oslo",
    "iso:country":"NO",
    "wof:name":"Grottem",
    "wof:placetype":"locality"
},
  "geometry": {"coordinates":[10.96006,63.25552],"type":"Point"}
}