{
  "type": "Feature",
  "properties": {
    "gn:admin1_code":"21.0",
    "gn:admin2_code":"5020.0",
    "gn:asciiname":"Nausthaugan",
    "gn:country_code":"NO",
    "gn:dem":140,
    "gn:feature_class":"P",
    "gn:feature_code":"PPL",
    "gn:name":"Nausthaugan",
    "gn:population":0,
    "gn:timezone":"Europe/Oslo",
    "iso:country":"NO",
    "name:nor_x_preferred":[
        "Nausthaugan"
    ],
    "wof:name":"Nausthaugan",
    "wof:placetype":"locality"
},
  "geometry": {"coordinates":[10.47523,64.33410000000001],"type":"Point"}
}