{
  "type": "Feature",
  "properties": {
    "gn:admin1_code":"13",
    "gn:admin2_code":"106",
    "gn:asciiname":"Viker",
    "gn:country_code":"NO",
    "gn:dem":15,
    "gn:feature_class":"P",
    "gn:feature_code":"PPLL",
    "gn:name":"Viker",
    "gn:population":0,
    "gn:timezone":"Europe/Oslo",
    "iso:country":"NO",
    "name:nor_x_preferred":[
        "Viker"
    ],
    "wof:name":"Viker",
    "wof:placetype":"locality"
},
  "geometry": {"coordinates":[10.87529,59.18865],"type":"Point"}
}