{
  "type": "Feature",
  "properties": {
    "gn:admin1_code":"18.0",
    "gn:admin2_code":"1902.0",
    "gn:asciiname":"Skittenelv",
    "gn:cc2":"NO",
    "gn:country_code":"NO",
    "gn:dem":-9999,
    "gn:feature_class":"P",
    "gn:feature_code":"PPL",
    "gn:name":"Skittenelv",
    "gn:population":0,
    "gn:timezone":"Europe/Oslo",
    "iso:country":"NO",
    "name:und_x_variant":[
        "Skitenelv",
        "Skitnelv"
    ],
    "wof:name":"Skittenelv",
    "wof:placetype":"locality"
},
  "geometry": {"coordinates":[19.39699,69.77670000000001],"type":"Point"}
}