{
  "type": "Feature",
  "properties": {
    "gn:admin1_code":"8.0",
    "gn:admin2_code":"1504.0",
    "gn:asciiname":"Skuggen",
    "gn:country_code":"NO",
    "gn:dem":-9999,
    "gn:feature_class":"P",
    "gn:feature_code":"PPL",
    "gn:name":"Skuggen",
    "gn:population":0,
    "gn:timezone":"Europe/Oslo",
    "iso:country":"NO",
    "name:nor_x_preferred":[
        "Skuggen"
    ],
    "wof:name":"Skuggen",
    "wof:placetype":"locality"
},
  "geometry": {"coordinates":[6.24737,62.46876999999999],"type":"Point"}
}