{
  "type": "Feature",
  "properties": {
    "gn:admin1_code":"19.0",
    "gn:admin2_code":"1026.0",
    "gn:asciiname":"Kyrkjebygda",
    "gn:country_code":"NO",
    "gn:dem":262,
    "gn:feature_class":"P",
    "gn:feature_code":"PPLA2",
    "gn:name":"Kyrkjebygda",
    "gn:population":0,
    "gn:timezone":"Europe/Oslo",
    "iso:country":"NO",
    "wof:name":"Kyrkjebygda",
    "wof:placetype":"locality"
},
  "geometry": {"coordinates":[7.41391,58.61523],"type":"Point"}
}