{
  "type": "Feature",
  "properties": {
    "gn:admin1_code":"6.0",
    "gn:admin2_code":"425.0",
    "gn:asciiname":"Snalroa",
    "gn:country_code":"NO",
    "gn:dem":158,
    "gn:feature_class":"P",
    "gn:feature_code":"PPL",
    "gn:name":"Sn\u00e5lroa",
    "gn:population":0,
    "gn:timezone":"Europe/Oslo",
    "iso:country":"NO",
    "name:nor_x_preferred":[
        "Sn\u00e5lroa"
    ],
    "wof:name":"Snalroa",
    "wof:placetype":"locality"
},
  "geometry": {"coordinates":[11.97054,60.58985],"type":"Point"}
}