{
  "type": "Feature",
  "properties": {
    "gn:admin1_code":"18",
    "gn:admin2_code":"1931.0",
    "gn:asciiname":"Botnhamn",
    "gn:country_code":"NO",
    "gn:dem":-9999,
    "gn:feature_class":"P",
    "gn:feature_code":"PPL",
    "gn:name":"Botnhamn",
    "gn:population":0,
    "gn:timezone":"Europe/Oslo",
    "iso:country":"NO",
    "name:fra_x_preferred":[
        "Botnhamn"
    ],
    "name:msa_x_preferred":[
        "Botnhamn"
    ],
    "name:nno_x_preferred":[
        "Botnhamn"
    ],
    "name:nor_x_preferred":[
        "Botnhamn"
    ],
    "name:spa_x_preferred":[
        "Botnhamn"
    ],
    "wof:name":"Botnhamn",
    "wof:placetype":"locality"
},
  "geometry": {"coordinates":[17.90273999999999,69.50745999999999],"type":"Point"}
}