{
  "type": "Feature",
  "properties": {
    "gn:admin1_code":"7.0",
    "gn:admin2_code":"1241.0",
    "gn:asciiname":"Sanddal",
    "gn:country_code":"NO",
    "gn:dem":238,
    "gn:feature_class":"P",
    "gn:feature_code":"PPL",
    "gn:name":"Sanddal",
    "gn:population":0,
    "gn:timezone":"Europe/Oslo",
    "iso:country":"NO",
    "wof:name":"Sanddal",
    "wof:placetype":"locality"
},
  "geometry": {"coordinates":[5.76667,60.18333000000001],"type":"Point"}
}