{
  "type": "Feature",
  "properties": {
    "gn:admin1_code":"1.0",
    "gn:admin2_code":"217.0",
    "gn:asciiname":"Ryberg",
    "gn:country_code":"NO",
    "gn:dem":156,
    "gn:feature_class":"P",
    "gn:feature_code":"PPL",
    "gn:name":"Ryberg",
    "gn:population":0,
    "gn:timezone":"Europe/Oslo",
    "iso:country":"NO",
    "name:nor_x_preferred":[
        "Ryberg"
    ],
    "wof:name":"Ryberg",
    "wof:placetype":"locality"
},
  "geometry": {"coordinates":[10.8256,59.76968000000001],"type":"Point"}
}