{
  "type": "Feature",
  "properties": {
    "gn:admin1_code":"11",
    "gn:admin2_code":"520.0",
    "gn:asciiname":"Nordrom",
    "gn:cc2":"NO",
    "gn:country_code":"NO",
    "gn:dem":260,
    "gn:feature_class":"P",
    "gn:feature_code":"PPL",
    "gn:name":"Nordrom",
    "gn:population":0,
    "gn:timezone":"Europe/Oslo",
    "iso:country":"NO",
    "name:und_x_variant":[
        "Nordrum",
        "Nordrom"
    ],
    "wof:name":"Nordrom",
    "wof:placetype":"locality"
},
  "geometry": {"coordinates":[10.08333,61.55],"type":"Point"}
}