{
  "type": "Feature",
  "properties": {
    "gn:admin1_code":"19.0",
    "gn:admin2_code":"1032.0",
    "gn:asciiname":"Eikjeland",
    "gn:country_code":"NO",
    "gn:dem":192,
    "gn:feature_class":"P",
    "gn:feature_code":"PPL",
    "gn:name":"Eikjeland",
    "gn:population":0,
    "gn:timezone":"Europe/Oslo",
    "iso:country":"NO",
    "name:nor_x_preferred":[
        "Eikjeland"
    ],
    "wof:name":"Eikjeland",
    "wof:placetype":"locality"
},
  "geometry": {"coordinates":[7.03398,58.2037],"type":"Point"}
}