{
  "type": "Feature",
  "properties": {
    "gn:admin1_code":"7",
    "gn:admin2_code":"1219.0",
    "gn:asciiname":"Kuleseid",
    "gn:cc2":"NO",
    "gn:country_code":"NO",
    "gn:dem":9,
    "gn:feature_class":"P",
    "gn:feature_code":"PPL",
    "gn:name":"Kuleseid",
    "gn:population":0,
    "gn:timezone":"Europe/Oslo",
    "iso:country":"NO",
    "name:nor_x_preferred":[
        "Kulleseidkanalen"
    ],
    "name:und_x_variant":[
        "Kulleseid"
    ],
    "wof:name":"Kuleseid",
    "wof:placetype":"locality"
},
  "geometry": {"coordinates":[5.23267,59.73988000000001],"type":"Point"}
}