{
  "type": "Feature",
  "properties": {
    "gn:admin1_code":"9.0",
    "gn:admin2_code":"1856.0",
    "gn:asciiname":"Rost",
    "gn:country_code":"NO",
    "gn:dem":-9999,
    "gn:feature_class":"P",
    "gn:feature_code":"PPLA2",
    "gn:name":"R\u00f8st",
    "gn:population":0,
    "gn:timezone":"Europe/Oslo",
    "iso:country":"NO",
    "wof:name":"Rost",
    "wof:placetype":"locality"
},
  "geometry": {"coordinates":[12.1176,67.51754],"type":"Point"}
}