{
  "type": "Feature",
  "properties": {
    "gn:admin1_code":"9.0",
    "gn:admin2_code":"1860.0",
    "gn:asciiname":"Reine",
    "gn:country_code":"NO",
    "gn:dem":2,
    "gn:feature_class":"P",
    "gn:feature_code":"PPL",
    "gn:name":"Reine",
    "gn:population":0,
    "gn:timezone":"Europe/Oslo",
    "iso:country":"NO",
    "name:afr_x_preferred":[
        "Reine"
    ],
    "name:cat_x_preferred":[
        "Reine"
    ],
    "name:ceb_x_preferred":[
        "Reine"
    ],
    "name:ces_x_preferred":[
        "Reine"
    ],
    "name:dan_x_preferred":[
        "Reine"
    ],
    "name:deu_x_preferred":[
        "Reine"
    ],
    "name:fas_x_preferred":[
        "\u0631\u0626\u06cc\u0646"
    ],
    "name:fin_x_preferred":[
        "Reine"
    ],
    "name:fra_x_preferred":[
        "Reine"
    ],
    "name:hye_x_preferred":[
        "\u054c\u0565\u0575\u0576\u0565"
    ],
    "name:ind_x_preferred":[
        "Reine"
    ],
    "name:ita_x_preferred":[
        "Reine"
    ],
    "name:jav_x_preferred":[
        "Reine"
    ],
    "name:jpn_x_preferred":[
        "\u30ec\u30fc\u30cc"
    ],
    "name:mkd_x_preferred":[
        "\u0420\u0435\u0458\u043d\u0435"
    ],
    "name:msa_x_preferred":[
        "Reine"
    ],
    "name:nld_x_preferred":[
        "Reine"
    ],
    "name:nno_x_preferred":[
        "Reine"
    ],
    "name:nor_x_preferred":[
        "Reine"
    ],
    "name:oss_x_preferred":[
        "\u0420\u0435\u0439\u043d\u0435"
    ],
    "name:pol_x_preferred":[
        "Reine"
    ],
    "name:ron_x_preferred":[
        "Reine"
    ],
    "name:rus_x_preferred":[
        "\u0420\u0435\u0439\u043d\u0435"
    ],
    "name:spa_x_preferred":[
        "Reine"
    ],
    "name:swe_x_preferred":[
        "Reine"
    ],
    "name:tur_x_preferred":[
        "Reine"
    ],
    "name:ukr_x_preferred":[
        "\u0420\u0435\u0439\u043d\u0435"
    ],
    "wof:name":"Reine",
    "wof:placetype":"locality"
},
  "geometry": {"coordinates":[13.51667,68.08333],"type":"Point"}
}