{
  "type": "Feature",
  "properties": {
    "iso:country":"NO",
    "name:alb_x_preferred":[
        "B\u00f8mlo"
    ],
    "name:baq_x_preferred":[
        "B\u00f8mlo"
    ],
    "name:bar_x_preferred":[
        "B\u00f8mlo"
    ],
    "name:bpy_x_preferred":[
        "\u09ac\u09be\u09ae\u09b2\u09cb"
    ],
    "name:cat_x_preferred":[
        "B\u00f8mlo"
    ],
    "name:chi_x_preferred":[
        "\u4f2f\u59c6\u76e7"
    ],
    "name:dan_x_preferred":[
        "B\u00f8mlo"
    ],
    "name:dut_x_preferred":[
        "B\u00f8mlo"
    ],
    "name:eng_x_preferred":[
        "B\u00f8mlo"
    ],
    "name:epo_x_preferred":[
        "B\u00f8mlo"
    ],
    "name:fin_x_preferred":[
        "B\u00f8mlo"
    ],
    "name:fre_x_preferred":[
        "B\u00f8mlo"
    ],
    "name:ger_x_preferred":[
        "B\u00f8mlo"
    ],
    "name:gre_x_preferred":[
        "\u039c\u03c0\u03ad\u03bc\u03bb\u03bf"
    ],
    "name:ind_x_preferred":[
        "B\u00f8mlo"
    ],
    "name:ita_x_preferred":[
        "B\u00f8mlo"
    ],
    "name:jav_x_preferred":[
        "B\u00f8mlo"
    ],
    "name:lat_x_preferred":[
        "B\u00f8mlo"
    ],
    "name:lim_x_preferred":[
        "B\u00f8mlo"
    ],
    "name:may_x_preferred":[
        "B\u00f8mlo"
    ],
    "name:nan_x_preferred":[
        "B\u00f8mlo"
    ],
    "name:nds_x_preferred":[
        "Kommun B\u00f8mlo"
    ],
    "name:nno_x_preferred":[
        "B\u00f8mlo"
    ],
    "name:nob_x_preferred":[
        "B\u00f8mlo"
    ],
    "name:oci_x_preferred":[
        "B\u00f8mlo"
    ],
    "name:pol_x_preferred":[
        "B\u00f8mlo"
    ],
    "name:por_x_preferred":[
        "B\u00f8mlo"
    ],
    "name:rum_x_preferred":[
        "B\u00f8mlo"
    ],
    "name:rus_x_preferred":[
        "\u0411\u0451\u043c\u043b\u0443"
    ],
    "name:slv_x_preferred":[
        "B\u00f8mlo"
    ],
    "name:sme_x_preferred":[
        "B\u00f8mlo"
    ],
    "name:spa_x_preferred":[
        "B\u00f8mlo"
    ],
    "name:swa_x_preferred":[
        "B\u00f8mlo"
    ],
    "name:swe_x_preferred":[
        "B\u00f8mlo"
    ],
    "name:tur_x_preferred":[
        "B\u00f8mlo"
    ],
    "name:vie_x_preferred":[
        "B\u00f8mlo"
    ],
    "name:war_x_preferred":[
        "B\u00f8mlo"
    ],
    "qs_pg:aaroncc":"NO",
    "qs_pg:name":"B\u00f8mlo",
    "qs_pg:name_adm0":"Norge",
    "qs_pg:name_adm1":"Hordaland Fylke",
    "qs_pg:photos":49,
    "qs_pg:photos_1k":10,
    "qs_pg:photos_9k":1,
    "qs_pg:photos_9r":2,
    "qs_pg:photos_all":49,
    "qs_pg:photos_sr":2,
    "qs_pg:pop_sr":0,
    "qs_pg:qs_pg_placetype":"locality",
    "qs_pg:qs_pg_placetype_gp":"Town",
    "qs_pg:woe_adm0":23424910,
    "woe:adm0_id":23424910,
    "woe:name_adm0":"Norge",
    "woe:name_adm1":"Hordaland Fylke",
    "woe:placetype":"Town",
    "wof:name":"B\u00f8mlo",
    "wof:placetype":"locality"
},
  "geometry": {"coordinates":[5.18822,59.797439],"type":"Point"}
}