{
  "type": "Feature",
  "properties": {
    "gn:admin1_code":"5.0",
    "gn:admin2_code":"2018.0",
    "gn:asciiname":"Eidnes",
    "gn:country_code":"NO",
    "gn:dem":-9999,
    "gn:feature_class":"P",
    "gn:feature_code":"PPL",
    "gn:name":"Eidnes",
    "gn:population":0,
    "gn:timezone":"Europe/Oslo",
    "iso:country":"NO",
    "wof:name":"Eidnes",
    "wof:placetype":"locality"
},
  "geometry": {"coordinates":[24.06667,71.03333000000001],"type":"Point"}
}