{
  "type": "Feature",
  "properties": {
    "gn:admin1_code":"21.0",
    "gn:admin2_code":"5012.0",
    "gn:asciiname":"Skorilla",
    "gn:cc2":"NO",
    "gn:country_code":"NO",
    "gn:dem":-9999,
    "gn:feature_class":"P",
    "gn:feature_code":"PPL",
    "gn:name":"Skorilla",
    "gn:population":0,
    "gn:timezone":"Europe/Oslo",
    "iso:country":"NO",
    "name:und_x_variant":[
        "Skorill",
        "Skorild",
        "Skorilla"
    ],
    "wof:name":"Skorilla",
    "wof:placetype":"locality"
},
  "geometry": {"coordinates":[9.38333,63.38333000000001],"type":"Point"}
}