{
  "type": "Feature",
  "properties": {
    "gn:admin1_code":"19.0",
    "gn:admin2_code":"1001.0",
    "gn:asciiname":"Bjorkevollen",
    "gn:country_code":"NO",
    "gn:dem":23,
    "gn:feature_class":"P",
    "gn:feature_code":"PPL",
    "gn:name":"Bj\u00f8rkevollen",
    "gn:population":0,
    "gn:timezone":"Europe/Oslo",
    "iso:country":"NO",
    "name:nor_x_preferred":[
        "Bj\u00f8rkevollen"
    ],
    "wof:name":"Bjorkevollen",
    "wof:placetype":"locality"
},
  "geometry": {"coordinates":[8.11732,58.21682],"type":"Point"}
}