{
  "type": "Feature",
  "properties": {
    "gn:admin1_code":"11.0",
    "gn:admin2_code":"543.0",
    "gn:asciiname":"Nordre Nosen",
    "gn:country_code":"NO",
    "gn:dem":933,
    "gn:feature_class":"P",
    "gn:feature_code":"PPL",
    "gn:name":"N\u00f8rdre N\u00f8sen",
    "gn:population":0,
    "gn:timezone":"Europe/Oslo",
    "iso:country":"NO",
    "name:nor_x_preferred":[
        "N\u00f8rdre N\u00f8sen"
    ],
    "name:nor_x_variant":[
        "Nosast\u00f8len"
    ],
    "wof:name":"Nordre Nosen",
    "wof:placetype":"locality"
},
  "geometry": {"coordinates":[8.75762,61.03001],"type":"Point"}
}