{
  "type": "Feature",
  "properties": {
    "gn:admin1_code":"7",
    "gn:admin2_code":"1201.0",
    "gn:asciiname":"Gjerdingen",
    "gn:cc2":"NO",
    "gn:country_code":"NO",
    "gn:dem":-9999,
    "gn:feature_class":"P",
    "gn:feature_code":"PPLL",
    "gn:name":"Gjerdingen",
    "gn:population":0,
    "gn:timezone":"Europe/Oslo",
    "iso:country":"NO",
    "name:und_x_variant":[
        "Gjerdingsnes",
        "Gjerdingen"
    ],
    "wof:name":"Gjerdingen",
    "wof:placetype":"neighbourhood"
},
  "geometry": {"coordinates":[5.20556,60.38556],"type":"Point"}
}