{
  "type": "Feature",
  "properties": {
    "gn:admin1_code":"7.0",
    "gn:admin2_code":"1201.0",
    "gn:asciiname":"Dolvik",
    "gn:country_code":"NO",
    "gn:dem":60,
    "gn:feature_class":"P",
    "gn:feature_code":"PPLL",
    "gn:name":"Dolvik",
    "gn:population":0,
    "gn:timezone":"Europe/Oslo",
    "iso:country":"NO",
    "wof:name":"Dolvik",
    "wof:placetype":"neighbourhood"
},
  "geometry": {"coordinates":[5.26674,60.31024],"type":"Point"}
}