{
  "type": "Feature",
  "properties": {
    "gn:admin1_code":"15.0",
    "gn:admin2_code":"1426.0",
    "gn:asciiname":"Skjervo",
    "gn:country_code":"NO",
    "gn:dem":440,
    "gn:feature_class":"P",
    "gn:feature_code":"PPL",
    "gn:name":"Skjervo",
    "gn:population":0,
    "gn:timezone":"Europe/Oslo",
    "iso:country":"NO",
    "wof:name":"Skjervo",
    "wof:placetype":"locality"
},
  "geometry": {"coordinates":[7.16667,61.31667],"type":"Point"}
}