{
  "type": "Feature",
  "properties": {
    "gn:admin1_code":"5.0",
    "gn:admin2_code":"2020.0",
    "gn:asciiname":"Goarahat",
    "gn:country_code":"NO",
    "gn:dem":-9999,
    "gn:feature_class":"P",
    "gn:feature_code":"PPL",
    "gn:name":"Goarahat",
    "gn:population":0,
    "gn:timezone":"Europe/Oslo",
    "iso:country":"NO",
    "name:fkv_x_preferred":[
        "Kuoratakka"
    ],
    "name:nor_x_preferred":[
        "G\u00e5radak"
    ],
    "name:sme_x_preferred":[
        "Goarahat"
    ],
    "name:und_x_variant":[
        "Ytre Gaaradak",
        "Ytre G\u00e5radak"
    ],
    "wof:name":"Goarahat",
    "wof:placetype":"locality"
},
  "geometry": {"coordinates":[25.02715,70.26276],"type":"Point"}
}