{
  "type": "Feature",
  "properties": {
    "gn:admin1_code":"7.0",
    "gn:admin2_code":"1201.0",
    "gn:asciiname":"Radal",
    "gn:country_code":"NO",
    "gn:dem":40,
    "gn:feature_class":"P",
    "gn:feature_code":"PPL",
    "gn:name":"R\u00e5dal",
    "gn:population":0,
    "gn:timezone":"Europe/Oslo",
    "iso:country":"NO",
    "wof:name":"Radal",
    "wof:placetype":"locality"
},
  "geometry": {"coordinates":[5.34554,60.31063],"type":"Point"}
}