{
  "type": "Feature",
  "properties": {
    "gn:admin1_code":"21.0",
    "gn:admin2_code":"5027.0",
    "gn:asciiname":"Soknes",
    "gn:country_code":"NO",
    "gn:dem":81,
    "gn:feature_class":"P",
    "gn:feature_code":"PPL",
    "gn:name":"Soknes",
    "gn:population":0,
    "gn:timezone":"Europe/Oslo",
    "iso:country":"NO",
    "name:nor_x_preferred":[
        "Soknes"
    ],
    "wof:name":"Soknes",
    "wof:placetype":"neighbourhood"
},
  "geometry": {"coordinates":[10.28333,63.03333000000001],"type":"Point"}
}