{
  "type": "Feature",
  "properties": {
    "gn:admin1_code":"9.0",
    "gn:admin2_code":"1827.0",
    "gn:asciiname":"Vag",
    "gn:cc2":"NO",
    "gn:country_code":"NO",
    "gn:dem":10,
    "gn:feature_class":"P",
    "gn:feature_code":"PPL",
    "gn:name":"V\u00e5g",
    "gn:population":0,
    "gn:timezone":"Europe/Oslo",
    "iso:country":"NO",
    "name:und_x_variant":[
        "Vaag",
        "V\u00e5g"
    ],
    "wof:name":"Vag",
    "wof:placetype":"locality"
},
  "geometry": {"coordinates":[12.55537,66.13659],"type":"Point"}
}