{
  "type": "Feature",
  "properties": {
    "gn:admin1_code":"9",
    "gn:admin2_code":"1848.0",
    "gn:asciiname":"Leirvik",
    "gn:country_code":"NO",
    "gn:dem":15,
    "gn:feature_class":"P",
    "gn:feature_code":"PPL",
    "gn:name":"Leirvik",
    "gn:population":0,
    "gn:timezone":"Europe/Oslo",
    "iso:country":"NO",
    "name:ara_x_preferred":[
        "\u0644\u0627\u064a\u0631\u0641\u064a\u0643"
    ],
    "name:bul_x_preferred":[
        "\u041b\u0430\u0439\u0440\u0432\u0438\u043a"
    ],
    "name:ceb_x_preferred":[
        "Leirvik"
    ],
    "name:deu_x_preferred":[
        "Leirvik"
    ],
    "name:fas_x_preferred":[
        "\u0644\u06cc\u0631\u0648\u06cc\u06a9"
    ],
    "name:fin_x_preferred":[
        "Leirvik"
    ],
    "name:fra_x_preferred":[
        "Leirvik"
    ],
    "name:isl_x_preferred":[
        "Leirv\u00edk"
    ],
    "name:ita_x_preferred":[
        "Leirvik"
    ],
    "name:nld_x_preferred":[
        "Leirvik"
    ],
    "name:nno_x_preferred":[
        "Leirvik"
    ],
    "name:nor_x_preferred":[
        "Leirvik"
    ],
    "name:ron_x_preferred":[
        "Leirvik"
    ],
    "name:srp_x_preferred":[
        "\u041b\u0435\u0458\u0440\u0432\u0438\u043a"
    ],
    "name:swe_x_preferred":[
        "Leirvik"
    ],
    "name:zho_x_preferred":[
        "\u83b1\u5c14\u7ef4\u514b"
    ],
    "wof:name":"Leirvik",
    "wof:placetype":"locality"
},
  "geometry": {"coordinates":[15.195,67.88889],"type":"Point"}
}