{
  "type": "Feature",
  "properties": {
    "gn:admin1_code":"9",
    "gn:admin2_code":"1848.0",
    "gn:asciiname":"Leirvik",
    "gn:country_code":"NO",
    "gn:dem":15,
    "gn:feature_class":"P",
    "gn:feature_code":"PPL",
    "gn:name":"Leirvik",
    "gn:population":0,
    "gn:timezone":"Europe/Oslo",
    "iso:country":"NO",
    "wof:name":"Leirvik",
    "wof:placetype":"locality"
},
  "geometry": {"coordinates":[15.195,67.88889],"type":"Point"}
}