{
  "type": "Feature",
  "properties": {
    "gn:admin1_code":"11",
    "gn:admin2_code":"542.0",
    "gn:asciiname":"Hove",
    "gn:country_code":"NO",
    "gn:dem":440,
    "gn:feature_class":"P",
    "gn:feature_code":"PPL",
    "gn:name":"Hove",
    "gn:population":0,
    "gn:timezone":"Europe/Oslo",
    "iso:country":"NO",
    "wof:name":"Hove",
    "wof:placetype":"locality"
},
  "geometry": {"coordinates":[9.33333,60.91667],"type":"Point"}
}