{
  "type": "Feature",
  "properties": {
    "gn:admin1_code":"8.0",
    "gn:admin2_code":"1543.0",
    "gn:asciiname":"Toven",
    "gn:country_code":"NO",
    "gn:dem":108,
    "gn:feature_class":"P",
    "gn:feature_code":"PPL",
    "gn:name":"Toven",
    "gn:population":0,
    "gn:timezone":"Europe/Oslo",
    "iso:country":"NO",
    "wof:name":"Toven",
    "wof:placetype":"locality"
},
  "geometry": {"coordinates":[8.12167,62.79611],"type":"Point"}
}