{
  "type": "Feature",
  "properties": {
    "gn:country":"NO",
    "gn:fcode":"PPL",
    "gn:population":0,
    "iso:country":"NO",
    "name:pan_x_preferred":[
        "\u0a2c\u0a4c\u0a02\u0a26\u0a32"
    ],
    "qs_pg:aaroncc":"NO",
    "qs_pg:gn_country":"NO",
    "qs_pg:gn_fcode":"PPL",
    "qs_pg:gn_pop":0,
    "qs_pg:name":"Bondal",
    "qs_pg:name_adm0":"Norge",
    "qs_pg:name_adm1":"Telemark Fylke",
    "qs_pg:photos":189,
    "qs_pg:photos_1k":38,
    "qs_pg:photos_9k":1,
    "qs_pg:photos_9r":4,
    "qs_pg:photos_all":189,
    "qs_pg:photos_sr":4,
    "qs_pg:pop_sr":0,
    "qs_pg:qs_pg_placetype":"locality",
    "qs_pg:qs_pg_placetype_gp":"Town",
    "qs_pg:woe_adm0":23424910,
    "woe:adm0_id":23424910,
    "woe:name_adm0":"Norge",
    "woe:name_adm1":"Telemark Fylke",
    "woe:placetype":"Town",
    "wof:name":"Bondal",
    "wof:placetype":"locality"
},
  "geometry": {"coordinates":[8.61667,59.81667],"type":"Point"}
}