{
  "type": "Feature",
  "properties": {
    "gn:admin1_code":"21",
    "gn:admin2_code":"5001",
    "gn:asciiname":"Risvollen",
    "gn:country_code":"NO",
    "gn:dem":120,
    "gn:feature_class":"P",
    "gn:feature_code":"PPLL",
    "gn:name":"Risvollen",
    "gn:population":0,
    "gn:timezone":"Europe/Oslo",
    "iso:country":"NO",
    "name:nor_x_preferred":[
        "Risvollen"
    ],
    "name:nor_x_variant":[
        "Risvollan"
    ],
    "wof:name":"Risvollen",
    "wof:placetype":"neighbourhood"
},
  "geometry": {"coordinates":[10.4268,63.39552],"type":"Point"}
}