{
  "type": "Feature",
  "properties": {
    "gn:admin1_code":"8.0",
    "gn:admin2_code":"1560.0",
    "gn:asciiname":"Skard",
    "gn:country_code":"NO",
    "gn:dem":120,
    "gn:feature_class":"P",
    "gn:feature_code":"PPL",
    "gn:name":"Skard",
    "gn:population":0,
    "gn:timezone":"Europe/Oslo",
    "iso:country":"NO",
    "name:nor_x_preferred":[
        "Skard"
    ],
    "name:nor_x_variant":[
        "Skar"
    ],
    "wof:name":"Skard",
    "wof:placetype":"locality"
},
  "geometry": {"coordinates":[8.30487,62.83088000000001],"type":"Point"}
}