{
  "type": "Feature",
  "properties": {
    "gn:gn_country":"NO",
    "gn:gn_fcode":"PPLA2",
    "gn:gn_pop":685,
    "gn:population":685,
    "iso:country":"NO",
    "name:dut_x_preferred":[
        "Sistranda"
    ],
    "name:eng_x_preferred":[
        "Sistranda"
    ],
    "name:fin_x_preferred":[
        "Sistranda"
    ],
    "name:fre_x_preferred":[
        "Sistranda"
    ],
    "name:may_x_preferred":[
        "Sistranda"
    ],
    "name:nno_x_preferred":[
        "Sistranda"
    ],
    "name:nob_x_preferred":[
        "Sistranda"
    ],
    "name:rum_x_preferred":[
        "Sistranda"
    ],
    "name:unk_x_variant":[
        "Sistranden"
    ],
    "qs_pg:aaroncc":"NO",
    "qs_pg:gn_country":"NO",
    "qs_pg:gn_fcode":"PPLA2",
    "qs_pg:gn_pop":685,
    "qs_pg:name":"Sistranda",
    "qs_pg:name_adm0":"Norge",
    "qs_pg:name_adm1":"S\u00f8r-Tr\u00f8ndelag Fylke",
    "qs_pg:photos_9k":1,
    "qs_pg:photos_9r":1,
    "qs_pg:photos_all":3,
    "qs_pg:photos_sr":0,
    "qs_pg:pop_sr":2,
    "qs_pg:qs_pg_placetype":"locality",
    "qs_pg:qs_pg_placetype_gp":"Town",
    "qs_pg:woe_adm0":23424910,
    "woe:adm0_id":23424910,
    "woe:name_adm0":"Norge",
    "woe:name_adm1":"S\u00f8r-Tr\u00f8ndelag Fylke",
    "woe:placetype":"Town",
    "wof:name":"Sistranda",
    "wof:placetype":"locality",
    "wof:population":685
},
  "geometry": {"coordinates":[8.83402,63.72555],"type":"Point"}
}