{
  "type": "Feature",
  "properties": {
    "gn:admin1_code":"18.0",
    "gn:admin2_code":"1902.0",
    "gn:asciiname":"Hamn",
    "gn:country_code":"NO",
    "gn:dem":54,
    "gn:feature_class":"P",
    "gn:feature_code":"PPL",
    "gn:name":"Hamn",
    "gn:population":0,
    "gn:timezone":"Europe/Oslo",
    "iso:country":"NO",
    "name:nor_x_preferred":[
        "Hamn"
    ],
    "wof:name":"Hamn",
    "wof:placetype":"locality"
},
  "geometry": {"coordinates":[18.70354,69.56216999999999],"type":"Point"}
}