{
  "type": "Feature",
  "properties": {
    "gn:admin1_code":"18.0",
    "gn:admin2_code":"1927.0",
    "gn:asciiname":"Rodsand",
    "gn:cc2":"NO",
    "gn:country_code":"NO",
    "gn:dem":3,
    "gn:feature_class":"P",
    "gn:feature_code":"PPL",
    "gn:name":"R\u00f8dsand",
    "gn:population":0,
    "gn:timezone":"Europe/Oslo",
    "iso:country":"NO",
    "name:und_x_variant":[
        "R\u00f8dsand i Senja",
        "Rausand",
        "R\u00f8dsand"
    ],
    "wof:name":"Rodsand",
    "wof:placetype":"locality"
},
  "geometry": {"coordinates":[17.02734,69.13399],"type":"Point"}
}