{
  "type": "Feature",
  "properties": {
    "gn:admin1_code":"18.0",
    "gn:admin2_code":"1903.0",
    "gn:asciiname":"Rogla",
    "gn:cc2":"NO",
    "gn:country_code":"NO",
    "gn:dem":20,
    "gn:feature_class":"P",
    "gn:feature_code":"PPL",
    "gn:name":"Rogla",
    "gn:population":0,
    "gn:timezone":"Europe/Oslo",
    "iso:country":"NO",
    "name:und_x_variant":[
        "R\u00f6glen",
        "Rogla"
    ],
    "wof:name":"Rogla",
    "wof:placetype":"locality"
},
  "geometry": {"coordinates":[16.65,68.73333000000001],"type":"Point"}
}