{
  "type": "Feature",
  "properties": {
    "gn:admin1_code":"6.0",
    "gn:admin2_code":"438.0",
    "gn:asciiname":"Baugen",
    "gn:country_code":"NO",
    "gn:dem":480,
    "gn:feature_class":"P",
    "gn:feature_code":"PPL",
    "gn:name":"Baugen",
    "gn:population":0,
    "gn:timezone":"Europe/Oslo",
    "iso:country":"NO",
    "name:nor_x_preferred":[
        "Baugen"
    ],
    "name:nor_x_variant":[
        "Vestatil"
    ],
    "wof:name":"Baugen",
    "wof:placetype":"locality"
},
  "geometry": {"coordinates":[10.62395,62.09271999999999],"type":"Point"}
}