{
  "type": "Feature",
  "properties": {
    "gn:admin1_code":"6.0",
    "gn:admin2_code":"420.0",
    "gn:asciiname":"Hesbol",
    "gn:country_code":"NO",
    "gn:dem":178,
    "gn:feature_class":"P",
    "gn:feature_code":"PPL",
    "gn:name":"Hesb\u00f8l",
    "gn:population":0,
    "gn:timezone":"Europe/Oslo",
    "iso:country":"NO",
    "name:nor_x_preferred":[
        "Hesb\u00f8l"
    ],
    "wof:name":"Hesbol",
    "wof:placetype":"locality"
},
  "geometry": {"coordinates":[12.12762,60.00381],"type":"Point"}
}