{
  "type": "Feature",
  "properties": {
    "gn:admin1_code":"9",
    "gn:admin2_code":"1818.0",
    "gn:asciiname":"Gaasvaer",
    "gn:country_code":"NO",
    "gn:dem":-9999,
    "gn:feature_class":"P",
    "gn:feature_code":"PPL",
    "gn:name":"Gaasvaer",
    "gn:population":0,
    "gn:timezone":"Europe/Oslo",
    "iso:country":"NO",
    "name:nor_x_preferred":[
        "G\u00e5sv\u00e6r"
    ],
    "name:und_x_variant":[
        "G\u00e5sv\u00e6r i Helgeland",
        "G\u00e5sv\u00e6r"
    ],
    "wof:name":"Gaasvaer",
    "wof:placetype":"locality"
},
  "geometry": {"coordinates":[12.05,66.05],"type":"Point"}
}