{
  "type": "Feature",
  "properties": {
    "gn:admin1_code":"9.0",
    "gn:admin2_code":"1867.0",
    "gn:asciiname":"Gasland",
    "gn:country_code":"NO",
    "gn:dem":35,
    "gn:feature_class":"P",
    "gn:feature_code":"PPL",
    "gn:name":"G\u00e5sland",
    "gn:population":0,
    "gn:timezone":"Europe/Oslo",
    "iso:country":"NO",
    "name:nor_x_preferred":[
        "G\u00e5sland"
    ],
    "wof:name":"Gasland",
    "wof:placetype":"locality"
},
  "geometry": {"coordinates":[14.62438,68.70039],"type":"Point"}
}