{
  "type": "Feature",
  "properties": {
    "gn:admin1_code":"9.0",
    "gn:admin2_code":"1867.0",
    "gn:asciiname":"Gasland",
    "gn:country_code":"NO",
    "gn:dem":35,
    "gn:feature_class":"P",
    "gn:feature_code":"PPL",
    "gn:name":"G\u00e5sland",
    "gn:population":0,
    "gn:timezone":"Europe/Oslo",
    "iso:country":"NO",
    "name:bul_x_preferred":[
        "\u0413\u0430\u0437\u043e\u0432\u0430 \u0441\u0442\u0440\u0430\u043d\u0430"
    ],
    "name:deu_x_preferred":[
        "Gasland"
    ],
    "name:fra_x_preferred":[
        "Gasland"
    ],
    "name:hye_x_preferred":[
        "\u0533\u0561\u0566\u056b \u0565\u0580\u056f\u056b\u0580"
    ],
    "name:ita_x_preferred":[
        "Gasland"
    ],
    "name:jpn_x_preferred":[
        "\u30ac\u30b9\u30e9\u30f3\u30c9"
    ],
    "name:nld_x_preferred":[
        "Gasland"
    ],
    "name:nor_x_preferred":[
        "G\u00e5sland"
    ],
    "name:nor_x_variant":[
        "Gasland"
    ],
    "name:por_x_preferred":[
        "Gasland"
    ],
    "name:rus_x_preferred":[
        "\u0413\u0430\u0437\u043e\u0432\u0430\u044f \u0441\u0442\u0440\u0430\u043d\u0430"
    ],
    "name:spa_x_preferred":[
        "Gasland"
    ],
    "name:swe_x_preferred":[
        "Gasland"
    ],
    "wof:name":"Gasland",
    "wof:placetype":"locality"
},
  "geometry": {"coordinates":[14.62438,68.70039],"type":"Point"}
}