{
  "type": "Feature",
  "properties": {
    "gn:country":"NO",
    "gn:fcode":"PPLA2",
    "gn:population":0,
    "iso:country":"NO",
    "name:bpy_x_preferred":[
        "\u09ab\u09cb\u09b0\u09b8\u09be\u09a8\u09cd\u09a1"
    ],
    "name:cat_x_preferred":[
        "Forsand"
    ],
    "name:ceb_x_preferred":[
        "Forsand"
    ],
    "name:ces_x_preferred":[
        "Forsand"
    ],
    "name:dan_x_preferred":[
        "Forsand"
    ],
    "name:deu_x_preferred":[
        "Forsand"
    ],
    "name:epo_x_preferred":[
        "Forsand"
    ],
    "name:eus_x_preferred":[
        "Forsand"
    ],
    "name:fin_x_preferred":[
        "Forsand"
    ],
    "name:fra_x_preferred":[
        "Forsand"
    ],
    "name:hun_x_preferred":[
        "Forsand"
    ],
    "name:hye_x_preferred":[
        "\u0556\u0578\u0580\u057d\u0561\u0576"
    ],
    "name:ita_x_preferred":[
        "Forsand"
    ],
    "name:jav_x_preferred":[
        "Forsand"
    ],
    "name:lat_x_preferred":[
        "Forsand"
    ],
    "name:lim_x_preferred":[
        "Forsand"
    ],
    "name:msa_x_preferred":[
        "Forsand"
    ],
    "name:nds_x_preferred":[
        "Kommun Forsand"
    ],
    "name:nld_x_preferred":[
        "Forsand"
    ],
    "name:nno_x_preferred":[
        "Forsand kommune"
    ],
    "name:nor_x_preferred":[
        "Forsand"
    ],
    "name:pol_x_preferred":[
        "Forsand"
    ],
    "name:por_x_preferred":[
        "Forsand"
    ],
    "name:ron_x_preferred":[
        "Forsand"
    ],
    "name:rus_x_preferred":[
        "\u0424\u043e\u0440\u0441\u0430\u043d\u043d"
    ],
    "name:slv_x_preferred":[
        "Forsand"
    ],
    "name:sme_x_preferred":[
        "Forsand"
    ],
    "name:spa_x_preferred":[
        "Forsand"
    ],
    "name:sqi_x_preferred":[
        "Forsand"
    ],
    "name:swe_x_preferred":[
        "Forsands kommun"
    ],
    "name:vie_x_preferred":[
        "Forsand"
    ],
    "name:war_x_preferred":[
        "Forsand"
    ],
    "qs_pg:aaroncc":"NO",
    "qs_pg:gn_country":"NO",
    "qs_pg:gn_fcode":"PPLA2",
    "qs_pg:gn_pop":0,
    "qs_pg:name":"Forsand",
    "qs_pg:name_adm0":"Norge",
    "qs_pg:name_adm1":"Rogaland Fylke",
    "qs_pg:photos":205,
    "qs_pg:photos_1k":42,
    "qs_pg:photos_9k":1,
    "qs_pg:photos_9r":4,
    "qs_pg:photos_all":205,
    "qs_pg:photos_sr":4,
    "qs_pg:pop_sr":0,
    "qs_pg:qs_pg_placetype":"locality",
    "qs_pg:qs_pg_placetype_gp":"Town",
    "qs_pg:woe_adm0":23424910,
    "woe:adm0_id":23424910,
    "woe:name_adm0":"Norge",
    "woe:name_adm1":"Rogaland Fylke",
    "woe:placetype":"Town",
    "wof:name":"Forsand",
    "wof:placetype":"locality"
},
  "geometry": {"coordinates":[6.1048,58.9033],"type":"Point"}
}