{
  "type": "Feature",
  "properties": {
    "gn:gn_country":"NO",
    "gn:gn_fcode":"PPLA2",
    "gn:gn_pop":0,
    "iso:country":"NO",
    "qs_pg:aaroncc":"NO",
    "qs_pg:gn_country":"NO",
    "qs_pg:gn_fcode":"PPLA2",
    "qs_pg:gn_pop":0,
    "qs_pg:name":"Forsand",
    "qs_pg:name_adm0":"Norge",
    "qs_pg:name_adm1":"Rogaland Fylke",
    "qs_pg:photos":205,
    "qs_pg:photos_1k":42,
    "qs_pg:photos_9k":1,
    "qs_pg:photos_9r":4,
    "qs_pg:photos_all":205,
    "qs_pg:photos_sr":4,
    "qs_pg:pop_sr":0,
    "qs_pg:qs_pg_placetype":"locality",
    "qs_pg:qs_pg_placetype_gp":"Town",
    "qs_pg:woe_adm0":23424910,
    "woe:adm0_id":23424910,
    "woe:name_adm0":"Norge",
    "woe:name_adm1":"Rogaland Fylke",
    "woe:placetype":"Town",
    "wof:name":"Forsand",
    "wof:placetype":"locality"
},
  "geometry": {"coordinates":[6.1048,58.9033],"type":"Point"}
}