{
  "type": "Feature",
  "properties": {
    "iso:country":"NO",
    "name:nno_x_preferred":[
        "Hovin"
    ],
    "name:nor_x_preferred":[
        "Hovin"
    ],
    "qs_pg:aaroncc":"NO",
    "qs_pg:name":"Hovin",
    "qs_pg:name_adm0":"Norge",
    "qs_pg:name_adm1":"Telemark Fylke",
    "qs_pg:photos":46,
    "qs_pg:photos_1k":9,
    "qs_pg:photos_9k":1,
    "qs_pg:photos_9r":2,
    "qs_pg:photos_all":46,
    "qs_pg:photos_sr":2,
    "qs_pg:pop_sr":0,
    "qs_pg:qs_pg_placetype":"locality",
    "qs_pg:qs_pg_placetype_gp":"Town",
    "qs_pg:woe_adm0":23424910,
    "woe:adm0_id":23424910,
    "woe:name_adm0":"Norge",
    "woe:name_adm1":"Telemark Fylke",
    "woe:placetype":"Town",
    "wof:name":"Hovin",
    "wof:placetype":"locality"
},
  "geometry": {"coordinates":[8.923301,59.904865],"type":"Point"}
}