{
  "type": "Feature",
  "properties": {
    "gn:admin1_code":"19.0",
    "gn:admin2_code":"1027.0",
    "gn:asciiname":"Vaulemo",
    "gn:country_code":"NO",
    "gn:dem":66,
    "gn:feature_class":"P",
    "gn:feature_code":"PPL",
    "gn:name":"Vaulemo",
    "gn:population":0,
    "gn:timezone":"Europe/Oslo",
    "iso:country":"NO",
    "wof:name":"Vaulemo",
    "wof:placetype":"locality"
},
  "geometry": {"coordinates":[7.35,58.25],"type":"Point"}
}