{
  "type": "Feature",
  "properties": {
    "gn:country":"NO",
    "gn:fcode":"PPL",
    "gn:population":349,
    "iso:country":"NO",
    "name:bos_x_preferred":[
        "Li"
    ],
    "name:hun_x_preferred":[
        "Li"
    ],
    "name:hye_x_preferred":[
        "\u053c\u056b"
    ],
    "name:rus_x_preferred":[
        "Li"
    ],
    "name:tha_x_preferred":[
        "\u0e25\u0e35\u0e49"
    ],
    "name:ukr_x_preferred":[
        "Li"
    ],
    "name:zho_x_preferred":[
        "Li"
    ],
    "qs_pg:aaroncc":"NO",
    "qs_pg:gn_country":"NO",
    "qs_pg:gn_fcode":"PPL",
    "qs_pg:gn_pop":349,
    "qs_pg:name":"Li",
    "qs_pg:name_adm0":"Norge",
    "qs_pg:name_adm1":"Hordaland Fylke",
    "qs_pg:photos":86,
    "qs_pg:photos_1k":17,
    "qs_pg:photos_9k":1,
    "qs_pg:photos_9r":3,
    "qs_pg:photos_all":86,
    "qs_pg:photos_sr":3,
    "qs_pg:pop_sr":2,
    "qs_pg:qs_pg_placetype":"locality",
    "qs_pg:qs_pg_placetype_gp":"Town",
    "qs_pg:woe_adm0":23424910,
    "woe:adm0_id":23424910,
    "woe:name_adm0":"Norge",
    "woe:name_adm1":"Hordaland Fylke",
    "woe:placetype":"Town",
    "wof:name":"Li",
    "wof:placetype":"locality",
    "wof:population":349
},
  "geometry": {"coordinates":[5.12833,60.30528],"type":"Point"}
}