{
  "type": "Feature",
  "properties": {
    "gn:admin1_code":"21.0",
    "gn:admin2_code":"5037.0",
    "gn:asciiname":"Eidet",
    "gn:country_code":"NO",
    "gn:dem":60,
    "gn:feature_class":"P",
    "gn:feature_code":"PPL",
    "gn:name":"Eidet",
    "gn:population":0,
    "gn:timezone":"Europe/Oslo",
    "iso:country":"NO",
    "name:nor_x_preferred":[
        "Eidet"
    ],
    "wof:name":"Eidet",
    "wof:placetype":"locality"
},
  "geometry": {"coordinates":[11.15144,63.80318000000001],"type":"Point"}
}