{
  "type": "Feature",
  "properties": {
    "gn:admin1_code":"11.0",
    "gn:admin2_code":"542.0",
    "gn:asciiname":"Abjorsheimasen",
    "gn:country_code":"NO",
    "gn:dem":820,
    "gn:feature_class":"P",
    "gn:feature_code":"PPL",
    "gn:name":"\u00c5bj\u00f8rsheim\u00e5sen",
    "gn:population":0,
    "gn:timezone":"Europe/Oslo",
    "iso:country":"NO",
    "name:nor_x_preferred":[
        "\u00c5bj\u00f8rsheim\u00e5sen"
    ],
    "wof:name":"Abjorsheimasen",
    "wof:placetype":"locality"
},
  "geometry": {"coordinates":[9.25013,60.92604],"type":"Point"}
}