{
  "type": "Feature",
  "properties": {
    "gn:admin1_code":"21",
    "gn:admin2_code":"5038.0",
    "gn:asciiname":"Adalsvollen",
    "gn:country_code":"NO",
    "gn:dem":393,
    "gn:feature_class":"P",
    "gn:feature_code":"PPL",
    "gn:name":"\u00c5dalsvollen",
    "gn:population":0,
    "gn:timezone":"Europe/Oslo",
    "iso:country":"NO",
    "name:nor_x_preferred":[
        "\u00c5dalsvollen"
    ],
    "wof:name":"Adalsvollen",
    "wof:placetype":"locality"
},
  "geometry": {"coordinates":[12.06667,63.66667],"type":"Point"}
}