{
  "type": "Feature",
  "properties": {
    "gn:admin1_code":"1.0",
    "gn:admin2_code":"226.0",
    "gn:asciiname":"Furulund",
    "gn:country_code":"NO",
    "gn:dem":140,
    "gn:feature_class":"P",
    "gn:feature_code":"PPL",
    "gn:name":"Furulund",
    "gn:population":0,
    "gn:timezone":"Europe/Oslo",
    "iso:country":"NO",
    "name:deu_x_preferred":[
        "Furulund"
    ],
    "name:fin_x_preferred":[
        "Furulund"
    ],
    "name:hun_x_preferred":[
        "Furulund"
    ],
    "name:ita_x_preferred":[
        "Furulund"
    ],
    "name:nld_x_preferred":[
        "Furulund"
    ],
    "name:nno_x_preferred":[
        "Furulund"
    ],
    "name:nor_x_preferred":[
        "Furulund"
    ],
    "name:swe_x_preferred":[
        "Furulund"
    ],
    "wof:name":"Furulund",
    "wof:placetype":"locality"
},
  "geometry": {"coordinates":[11.07812,60.03109],"type":"Point"}
}