{
  "type": "Feature",
  "properties": {
    "gn:admin1_code":"21",
    "gn:admin2_code":"5027.0",
    "gn:asciiname":"Almas",
    "gn:cc2":"NO",
    "gn:country_code":"NO",
    "gn:dem":300,
    "gn:feature_class":"P",
    "gn:feature_code":"PPL",
    "gn:name":"Alm\u00e5s",
    "gn:population":0,
    "gn:timezone":"Europe/Oslo",
    "iso:country":"NO",
    "name:und_x_variant":[
        "Almaas",
        "Alm\u00e5s"
    ],
    "wof:name":"Almas",
    "wof:placetype":"locality"
},
  "geometry": {"coordinates":[10.88333,62.98333],"type":"Point"}
}