{
  "type": "Feature",
  "properties": {
    "gn:admin1_code":"21",
    "gn:admin2_code":"5027.0",
    "gn:asciiname":"Almas",
    "gn:cc2":"NO",
    "gn:country_code":"NO",
    "gn:dem":300,
    "gn:feature_class":"P",
    "gn:feature_code":"PPL",
    "gn:name":"Alm\u00e5s",
    "gn:population":0,
    "gn:timezone":"Europe/Oslo",
    "iso:country":"NO",
    "name:ceb_x_preferred":[
        "Almas"
    ],
    "name:deu_x_preferred":[
        "Almas"
    ],
    "name:epo_x_preferred":[
        "Almas"
    ],
    "name:ita_x_preferred":[
        "Almas"
    ],
    "name:kaz_x_preferred":[
        "\u0410\u043b\u043c\u0430\u0441"
    ],
    "name:nld_x_preferred":[
        "Almas"
    ],
    "name:por_x_preferred":[
        "Almas"
    ],
    "name:rus_x_preferred":[
        "\u0410\u043b\u043c\u0430\u0441"
    ],
    "name:spa_x_preferred":[
        "Almas"
    ],
    "name:swe_x_preferred":[
        "Almas"
    ],
    "name:tur_x_preferred":[
        "Almas"
    ],
    "name:und_x_variant":[
        "Almaas",
        "Alm\u00e5s"
    ],
    "name:vie_x_preferred":[
        "Almas"
    ],
    "wof:name":"Almas",
    "wof:placetype":"locality"
},
  "geometry": {"coordinates":[10.88333,62.98333],"type":"Point"}
}