{
  "type": "Feature",
  "properties": {
    "gn:admin1_code":"19.0",
    "gn:admin2_code":"1037.0",
    "gn:asciiname":"Hamre",
    "gn:country_code":"NO",
    "gn:dem":188,
    "gn:feature_class":"P",
    "gn:feature_code":"PPL",
    "gn:name":"Hamre",
    "gn:population":0,
    "gn:timezone":"Europe/Oslo",
    "iso:country":"NO",
    "name:deu_x_preferred":[
        "Hamre"
    ],
    "name:nor_x_preferred":[
        "Hamre"
    ],
    "name:rus_x_preferred":[
        "\u0425\u0430\u043c\u0440\u0435"
    ],
    "name:swe_x_preferred":[
        "Hamre"
    ],
    "wof:name":"Hamre",
    "wof:placetype":"locality"
},
  "geometry": {"coordinates":[6.98056,58.33379],"type":"Point"}
}