{
  "type": "Feature",
  "properties": {
    "iso:country":"NO",
    "qs_pg:aaroncc":"NO",
    "qs_pg:name":"Sund I Lofoten",
    "qs_pg:name_adm0":"Norge",
    "qs_pg:name_adm1":"Nordland Fylke",
    "qs_pg:photos":139,
    "qs_pg:photos_1k":28,
    "qs_pg:photos_9k":1,
    "qs_pg:photos_9r":3,
    "qs_pg:photos_all":139,
    "qs_pg:photos_sr":3,
    "qs_pg:pop_sr":0,
    "qs_pg:qs_pg_placetype":"locality",
    "qs_pg:qs_pg_placetype_gp":"Town",
    "qs_pg:woe_adm0":23424910,
    "woe:adm0_id":23424910,
    "woe:name_adm0":"Norge",
    "woe:name_adm1":"Nordland Fylke",
    "woe:placetype":"Town",
    "wof:name":"Sund I Lofoten",
    "wof:placetype":"locality"
},
  "geometry": {"coordinates":[13.189773,68.018681],"type":"Point"}
}