{
  "type": "Feature",
  "properties": {
    "gn:admin1_code":"21.0",
    "gn:admin2_code":"5005.0",
    "gn:asciiname":"Selnes",
    "gn:cc2":"NO",
    "gn:country_code":"NO",
    "gn:dem":30,
    "gn:feature_class":"P",
    "gn:feature_code":"PPL",
    "gn:name":"Selnes",
    "gn:population":0,
    "gn:timezone":"Europe/Oslo",
    "iso:country":"NO",
    "name:ceb_x_preferred":[
        "Selnes"
    ],
    "name:swe_x_preferred":[
        "Selnes"
    ],
    "name:und_x_variant":[
        "Selnesviken"
    ],
    "wof:name":"Selnes",
    "wof:placetype":"locality"
},
  "geometry": {"coordinates":[11.42026,64.42737],"type":"Point"}
}