{
  "type": "Feature",
  "properties": {
    "gn:admin1_code":"7",
    "gn:admin2_code":"1263.0",
    "gn:asciiname":"Hodno",
    "gn:cc2":"NO",
    "gn:country_code":"NO",
    "gn:dem":170,
    "gn:feature_class":"P",
    "gn:feature_code":"PPL",
    "gn:name":"Hodno",
    "gn:population":0,
    "gn:timezone":"Europe/Oslo",
    "iso:country":"NO",
    "name:und_x_variant":[
        "Hodne",
        "Horno",
        "Hodno"
    ],
    "wof:name":"Hodno",
    "wof:placetype":"locality"
},
  "geometry": {"coordinates":[5.3175,60.71083],"type":"Point"}
}