{
  "type": "Feature",
  "properties": {
    "gn:admin1_code":"8",
    "gn:admin2_code":"1576.0",
    "gn:asciiname":"Gullstein",
    "gn:cc2":"NO",
    "gn:country_code":"NO",
    "gn:dem":-9999,
    "gn:feature_class":"P",
    "gn:feature_code":"PPL",
    "gn:name":"Gullstein",
    "gn:population":0,
    "gn:timezone":"Europe/Oslo",
    "iso:country":"NO",
    "name:jav_x_preferred":[
        "Gullstein"
    ],
    "name:msa_x_preferred":[
        "Gullstein"
    ],
    "name:nno_x_preferred":[
        "Gullstein"
    ],
    "name:nor_x_preferred":[
        "Gullstein"
    ],
    "name:und_x_variant":[
        "Guldsten",
        "Gullstein"
    ],
    "wof:name":"Gullstein",
    "wof:placetype":"locality"
},
  "geometry": {"coordinates":[8.15,63.21666999999999],"type":"Point"}
}