{
  "type": "Feature",
  "properties": {
    "gn:admin1_code":"7",
    "gn:admin2_code":"1247.0",
    "gn:asciiname":"Austdalen",
    "gn:cc2":"NO",
    "gn:country_code":"NO",
    "gn:dem":20,
    "gn:feature_class":"P",
    "gn:feature_code":"PPLL",
    "gn:name":"Austdalen",
    "gn:population":0,
    "gn:timezone":"Europe/Oslo",
    "iso:country":"NO",
    "name:und_x_variant":[
        "Austadal",
        "Austdalen"
    ],
    "wof:name":"Austdalen",
    "wof:placetype":"neighbourhood"
},
  "geometry": {"coordinates":[5.23194,60.43306],"type":"Point"}
}