{
  "type": "Feature",
  "properties": {
    "gn:admin1_code":"6",
    "gn:admin2_code":"402.0",
    "gn:asciiname":"Hynni",
    "gn:country_code":"NO",
    "gn:dem":180,
    "gn:feature_class":"P",
    "gn:feature_code":"PPL",
    "gn:name":"Hynni",
    "gn:population":0,
    "gn:timezone":"Europe/Oslo",
    "iso:country":"NO",
    "wof:name":"Hynni",
    "wof:placetype":"locality"
},
  "geometry": {"coordinates":[11.98333,60.33333],"type":"Point"}
}