{
  "type": "Feature",
  "properties": {
    "gn:country":"NO",
    "iso:country":"NO",
    "name:bjn_x_preferred":[
        "Bjark\u00f8y"
    ],
    "name:bpy_x_preferred":[
        "\u09ac\u099c\u09be\u09b0\u0995\u09be\u09af\u09bc"
    ],
    "name:cat_x_preferred":[
        "Bjark\u00f8y"
    ],
    "name:cym_x_preferred":[
        "Bjark\u00f8y"
    ],
    "name:dan_x_preferred":[
        "Bjark\u00f8y"
    ],
    "name:deu_x_preferred":[
        "Bjark\u00f8y"
    ],
    "name:eng_x_preferred":[
        "Bjark\u00f8y"
    ],
    "name:epo_x_preferred":[
        "Bjark\u00f8y"
    ],
    "name:eus_x_preferred":[
        "Bjark\u00f8y"
    ],
    "name:fin_x_preferred":[
        "Bjark\u00f8y"
    ],
    "name:fra_x_preferred":[
        "Bjark\u00f8y"
    ],
    "name:gle_x_preferred":[
        "Bjark\u00f8y"
    ],
    "name:hye_x_preferred":[
        "\u0532\u0575\u0561\u0580\u056f\u056b\u0578"
    ],
    "name:ind_x_preferred":[
        "Bjark\u00f8y"
    ],
    "name:ita_x_preferred":[
        "Bjark\u00f8y"
    ],
    "name:lat_x_preferred":[
        "Bjark\u00f8y"
    ],
    "name:lim_x_preferred":[
        "Bjark\u00f8y"
    ],
    "name:nan_x_preferred":[
        "Bjark\u00f8y"
    ],
    "name:nds_x_preferred":[
        "Kommun Bjark\u00f8y"
    ],
    "name:nld_x_preferred":[
        "Bjark\u00f8y"
    ],
    "name:nno_x_preferred":[
        "Bjark\u00f8y kommune"
    ],
    "name:nob_x_preferred":[
        "Bjark\u00f8y"
    ],
    "name:oci_x_preferred":[
        "Bjark\u00f8y"
    ],
    "name:pol_x_preferred":[
        "Bjark\u00f8y"
    ],
    "name:por_x_preferred":[
        "Bjark\u00f8y"
    ],
    "name:ron_x_preferred":[
        "Bjark\u00f8y"
    ],
    "name:rus_x_preferred":[
        "\u0411\u044c\u044f\u0440\u043a\u0451\u0439"
    ],
    "name:slv_x_preferred":[
        "Bjark\u00f8y"
    ],
    "name:sme_x_preferred":[
        "Bjarkeddjo"
    ],
    "name:spa_x_preferred":[
        "Bjark\u00f8y"
    ],
    "name:sqi_x_preferred":[
        "Bjark\u00f8y"
    ],
    "name:swe_x_preferred":[
        "Bjark\u00f8y kommun"
    ],
    "name:swe_x_variant":[
        "Bjark\u00f8y"
    ],
    "name:vie_x_preferred":[
        "Bjark\u00f8y"
    ],
    "name:war_x_preferred":[
        "Bjark\u00f8y"
    ],
    "qs_pg:aaroncc":"NO",
    "qs_pg:gn_country":"NO",
    "qs_pg:name":"Bjark\u00f8y",
    "qs_pg:name_adm0":"Norge",
    "qs_pg:name_adm1":"Troms Fylke",
    "qs_pg:photos":65,
    "qs_pg:photos_1k":13,
    "qs_pg:photos_9k":1,
    "qs_pg:photos_9r":2,
    "qs_pg:photos_all":65,
    "qs_pg:photos_sr":2,
    "qs_pg:pop_sr":0,
    "qs_pg:qs_pg_placetype":"locality",
    "qs_pg:qs_pg_placetype_gp":"Town",
    "qs_pg:woe_adm0":23424910,
    "woe:adm0_id":23424910,
    "woe:name_adm0":"Norge",
    "woe:name_adm1":"Troms Fylke",
    "woe:placetype":"Town",
    "wof:name":"Bjark\u00f8y",
    "wof:placetype":"locality"
},
  "geometry": {"coordinates":[16.536899,68.997309],"type":"Point"}
}