{
  "type": "Feature",
  "properties": {
    "gn:admin1_code":"6.0",
    "gn:admin2_code":"439.0",
    "gn:asciiname":"Sogardan",
    "gn:country_code":"NO",
    "gn:dem":820,
    "gn:feature_class":"P",
    "gn:feature_code":"PPL",
    "gn:name":"S\u00f8gardan",
    "gn:population":0,
    "gn:timezone":"Europe/Oslo",
    "iso:country":"NO",
    "name:nor_x_preferred":[
        "S\u00f8gardan"
    ],
    "name:nor_x_variant":[
        "S\u00f8rgardan"
    ],
    "wof:name":"Sogardan",
    "wof:placetype":"locality"
},
  "geometry": {"coordinates":[9.83371,62.17084000000001],"type":"Point"}
}