{
  "type": "Feature",
  "properties": {
    "gn:admin1_code":"6.0",
    "gn:admin2_code":"425.0",
    "gn:asciiname":"Vermundsjoen",
    "gn:country_code":"NO",
    "gn:dem":215,
    "gn:feature_class":"P",
    "gn:feature_code":"PPL",
    "gn:name":"Vermundsj\u00f8en",
    "gn:population":0,
    "gn:timezone":"Europe/Oslo",
    "iso:country":"NO",
    "name:nor_x_preferred":[
        "Vermundsj\u00f8en"
    ],
    "wof:name":"Vermundsjoen",
    "wof:placetype":"locality"
},
  "geometry": {"coordinates":[12.37047,60.70659000000001],"type":"Point"}
}