{
  "type": "Feature",
  "properties": {
    "gn:admin1_code":"19",
    "gn:admin2_code":"1003.0",
    "gn:asciiname":"Eikvag",
    "gn:cc2":"NO",
    "gn:country_code":"NO",
    "gn:dem":26,
    "gn:feature_class":"P",
    "gn:feature_code":"PPL",
    "gn:name":"Eikv\u00e5g",
    "gn:population":0,
    "gn:timezone":"Europe/Oslo",
    "iso:country":"NO",
    "name:und_x_variant":[
        "Figvaag",
        "Figv\u00e5g"
    ],
    "wof:name":"Eikvag",
    "wof:placetype":"locality"
},
  "geometry": {"coordinates":[6.81151,58.07073000000001],"type":"Point"}
}