{
  "type": "Feature",
  "properties": {
    "gn:admin1_code":"14",
    "gn:admin2_code":"1120",
    "gn:asciiname":"Haugabakka",
    "gn:country_code":"NO",
    "gn:dem":75,
    "gn:feature_class":"P",
    "gn:feature_code":"PPLL",
    "gn:name":"Haugabakka",
    "gn:population":0,
    "gn:timezone":"Europe/Oslo",
    "iso:country":"NO",
    "name:nor_x_preferred":[
        "Haugabakka"
    ],
    "wof:name":"Haugabakka",
    "wof:placetype":"locality"
},
  "geometry": {"coordinates":[5.6229,58.7699],"type":"Point"}
}