{
  "type": "Feature",
  "properties": {
    "gn:admin1_code":"18",
    "gn:admin2_code":"1903.0",
    "gn:asciiname":"Fauskevag",
    "gn:cc2":"NO",
    "gn:country_code":"NO",
    "gn:dem":1,
    "gn:feature_class":"P",
    "gn:feature_code":"PPL",
    "gn:name":"Fauskev\u00e5g",
    "gn:population":0,
    "gn:timezone":"Europe/Oslo",
    "iso:country":"NO",
    "name:fra_x_preferred":[
        "Fauskev\u00e5g"
    ],
    "name:msa_x_preferred":[
        "Fauskev\u00e5g"
    ],
    "name:nor_x_preferred":[
        "Fauskev\u00e5g"
    ],
    "name:nor_x_variant":[
        "Store Fauskev\u00e5g"
    ],
    "name:und_x_variant":[
        "Fauskevaag"
    ],
    "wof:name":"Fauskevag",
    "wof:placetype":"locality"
},
  "geometry": {"coordinates":[16.57536,68.66568000000001],"type":"Point"}
}