{
  "type": "Feature",
  "properties": {
    "gn:admin1_code":"6.0",
    "gn:admin2_code":"432.0",
    "gn:asciiname":"Vestaberget",
    "gn:country_code":"NO",
    "gn:dem":320,
    "gn:feature_class":"P",
    "gn:feature_code":"PPL",
    "gn:name":"Vestaberget",
    "gn:population":0,
    "gn:timezone":"Europe/Oslo",
    "iso:country":"NO",
    "name:nor_x_preferred":[
        "Vestaberget"
    ],
    "wof:name":"Vestaberget",
    "wof:placetype":"locality"
},
  "geometry": {"coordinates":[11.07118,61.8801],"type":"Point"}
}