{
  "type": "Feature",
  "properties": {
    "gn:admin1_code":"17.0",
    "gn:admin2_code":"828.0",
    "gn:asciiname":"Svartdal",
    "gn:country_code":"NO",
    "gn:dem":476,
    "gn:feature_class":"P",
    "gn:feature_code":"PPL",
    "gn:name":"Svartdal",
    "gn:population":0,
    "gn:timezone":"Europe/Oslo",
    "iso:country":"NO",
    "wof:name":"Svartdal",
    "wof:placetype":"locality"
},
  "geometry": {"coordinates":[8.56667,59.58333],"type":"Point"}
}