{
  "type": "Feature",
  "properties": {
    "gn:admin1_code":"6",
    "gn:admin2_code":"403.0",
    "gn:asciiname":"Blaestad",
    "gn:country_code":"NO",
    "gn:dem":217,
    "gn:feature_class":"P",
    "gn:feature_code":"PPL",
    "gn:name":"Bl\u00e6stad",
    "gn:population":0,
    "gn:timezone":"Europe/Oslo",
    "iso:country":"NO",
    "wof:name":"Blaestad",
    "wof:placetype":"locality"
},
  "geometry": {"coordinates":[11.15,60.81667],"type":"Point"}
}