{
  "type": "Feature",
  "properties": {
    "gn:gn_country":"NO",
    "iso:country":"NO",
    "name:dan_x_preferred":[
        "V\u00e5gsbygd"
    ],
    "name:eng_x_preferred":[
        "V\u00e5gsbygd"
    ],
    "name:nld_x_preferred":[
        "V\u00e5gsbygd"
    ],
    "name:nob_x_preferred":[
        "V\u00e5gsbygd"
    ],
    "name:spa_x_preferred":[
        "V\u00e5gsbygd"
    ],
    "qs_pg:aaroncc":"NO",
    "qs_pg:gn_country":"NO",
    "qs_pg:name":"V\u00e5gsbygda",
    "qs_pg:name_adm0":"Norge",
    "qs_pg:name_adm1":"Vest-Agder Fylke",
    "qs_pg:photos":52,
    "qs_pg:photos_1k":11,
    "qs_pg:photos_9k":1,
    "qs_pg:photos_9r":2,
    "qs_pg:photos_all":52,
    "qs_pg:photos_sr":2,
    "qs_pg:pop_sr":0,
    "qs_pg:qs_pg_placetype":"locality",
    "qs_pg:qs_pg_placetype_gp":"Town",
    "qs_pg:woe_adm0":23424910,
    "woe:adm0_id":23424910,
    "woe:name_adm0":"Norge",
    "woe:name_adm1":"Vest-Agder Fylke",
    "woe:placetype":"Town",
    "wof:name":"V\u00e5gsbygda",
    "wof:placetype":"locality"
},
  "geometry": {"coordinates":[7.958736,58.1213755],"type":"Point"}
}