{
  "type": "Feature",
  "properties": {
    "iso:country":"NO",
    "qs_pg:aaroncc":"NO",
    "qs_pg:name":"Storjord I Tysfjord",
    "qs_pg:name_adm0":"Norge",
    "qs_pg:name_adm1":"Nordland Fylke",
    "qs_pg:photos":206,
    "qs_pg:photos_1k":42,
    "qs_pg:photos_9k":1,
    "qs_pg:photos_9r":4,
    "qs_pg:photos_all":206,
    "qs_pg:photos_sr":4,
    "qs_pg:pop_sr":0,
    "qs_pg:qs_pg_placetype":"locality",
    "qs_pg:qs_pg_placetype_gp":"Town",
    "qs_pg:woe_adm0":23424910,
    "woe:adm0_id":23424910,
    "woe:name_adm0":"Norge",
    "woe:name_adm1":"Nordland Fylke",
    "woe:placetype":"Town",
    "wof:name":"Storjord I Tysfjord",
    "wof:placetype":"locality"
},
  "geometry": {"coordinates":[16.060552,68.199431],"type":"Point"}
}