{
  "type": "Feature",
  "properties": {
    "gn:admin1_code":"17",
    "gn:admin2_code":"815.0",
    "gn:asciiname":"Jomfruland",
    "gn:country_code":"NO",
    "gn:dem":-9999,
    "gn:feature_class":"P",
    "gn:feature_code":"PPL",
    "gn:name":"Jomfruland",
    "gn:population":0,
    "gn:timezone":"Europe/Oslo",
    "iso:country":"NO",
    "name:ceb_x_preferred":[
        "Jomfruland"
    ],
    "name:dan_x_preferred":[
        "Jomfruland"
    ],
    "name:deu_x_preferred":[
        "Jomfruland"
    ],
    "name:msa_x_preferred":[
        "Jomfruland"
    ],
    "name:nno_x_preferred":[
        "Jomfruland"
    ],
    "name:nor_x_preferred":[
        "Jomfruland"
    ],
    "wof:name":"Jomfruland",
    "wof:placetype":"locality"
},
  "geometry": {"coordinates":[9.58333,58.86666999999999],"type":"Point"}
}