{
  "type": "Feature",
  "properties": {
    "gn:admin1_code":"14",
    "gn:admin2_code":"1122.0",
    "gn:asciiname":"Haland",
    "gn:country_code":"NO",
    "gn:dem":255,
    "gn:feature_class":"P",
    "gn:feature_code":"PPL",
    "gn:name":"H\u00e5land",
    "gn:population":0,
    "gn:timezone":"Europe/Oslo",
    "iso:country":"NO",
    "wof:name":"Haland",
    "wof:placetype":"locality"
},
  "geometry": {"coordinates":[6.35,58.85],"type":"Point"}
}