{
  "type": "Feature",
  "properties": {
    "iso:country":"NO",
    "qs_pg:aaroncc":"NO",
    "qs_pg:name":"Steinmoen",
    "qs_pg:name_adm0":"Norge",
    "qs_pg:name_adm1":"Oppland Fylke",
    "qs_pg:photos":8,
    "qs_pg:photos_1k":2,
    "qs_pg:photos_9k":1,
    "qs_pg:photos_9r":1,
    "qs_pg:photos_all":8,
    "qs_pg:photos_sr":1,
    "qs_pg:pop_sr":0,
    "qs_pg:qs_pg_placetype":"locality",
    "qs_pg:qs_pg_placetype_gp":"Town",
    "qs_pg:woe_adm0":23424910,
    "woe:adm0_id":23424910,
    "woe:name_adm0":"Norge",
    "woe:name_adm1":"Oppland Fylke",
    "woe:placetype":"Town",
    "wof:name":"Steinmoen",
    "wof:placetype":"locality"
},
  "geometry": {"coordinates":[10.681591,60.9093545],"type":"Point"}
}