{
  "type": "Feature",
  "properties": {
    "gn:admin1_code":"21.0",
    "gn:admin2_code":"5028.0",
    "gn:asciiname":"Gimsan",
    "gn:country_code":"NO",
    "gn:dem":40,
    "gn:feature_class":"P",
    "gn:feature_code":"PPL",
    "gn:name":"Gimsan",
    "gn:population":0,
    "gn:timezone":"Europe/Oslo",
    "iso:country":"NO",
    "name:nor_x_preferred":[
        "Gimsan"
    ],
    "wof:name":"Gimsan",
    "wof:placetype":"locality"
},
  "geometry": {"coordinates":[10.25809,63.28069],"type":"Point"}
}