{
  "type": "Feature",
  "properties": {
    "iso:country":"NO",
    "qs_pg:aaroncc":"NO",
    "qs_pg:name":"S\u00f8stugrenda",
    "qs_pg:name_adm0":"Norge",
    "qs_pg:name_adm1":"Hedmark Fylke",
    "qs_pg:photos":6,
    "qs_pg:photos_1k":1,
    "qs_pg:photos_9k":1,
    "qs_pg:photos_9r":1,
    "qs_pg:photos_all":6,
    "qs_pg:photos_sr":1,
    "qs_pg:pop_sr":0,
    "qs_pg:qs_pg_placetype":"locality",
    "qs_pg:qs_pg_placetype_gp":"Town",
    "qs_pg:woe_adm0":23424910,
    "woe:adm0_id":23424910,
    "woe:name_adm0":"Norge",
    "woe:name_adm1":"Hedmark Fylke",
    "woe:placetype":"Town",
    "wof:name":"S\u00f8stugrenda",
    "wof:placetype":"locality"
},
  "geometry": {"coordinates":[11.524379,60.909018],"type":"Point"}
}