{
  "type": "Feature",
  "properties": {
    "gn:admin1_code":"18.0",
    "gn:admin2_code":"1940.0",
    "gn:asciiname":"Stornes",
    "gn:country_code":"NO",
    "gn:dem":27,
    "gn:feature_class":"P",
    "gn:feature_code":"PPL",
    "gn:name":"Stornes",
    "gn:population":0,
    "gn:timezone":"Europe/Oslo",
    "iso:country":"NO",
    "name:nor_x_preferred":[
        "Stornes"
    ],
    "wof:name":"Stornes",
    "wof:placetype":"locality"
},
  "geometry": {"coordinates":[20.84669,69.48886999999999],"type":"Point"}
}