{
  "type": "Feature",
  "properties": {
    "iso:country":"NO",
    "qs_pg:aaroncc":"NO",
    "qs_pg:name":"Tuss\u00f8y",
    "qs_pg:name_adm0":"Norge",
    "qs_pg:name_adm1":"Troms Fylke",
    "qs_pg:photos":49,
    "qs_pg:photos_1k":10,
    "qs_pg:photos_9k":1,
    "qs_pg:photos_9r":2,
    "qs_pg:photos_all":49,
    "qs_pg:photos_sr":2,
    "qs_pg:pop_sr":0,
    "qs_pg:qs_pg_placetype":"locality",
    "qs_pg:qs_pg_placetype_gp":"Town",
    "qs_pg:woe_adm0":23424910,
    "woe:adm0_id":23424910,
    "woe:name_adm0":"Norge",
    "woe:name_adm1":"Troms Fylke",
    "woe:placetype":"Town",
    "wof:name":"Tuss\u00f8y",
    "wof:placetype":"locality"
},
  "geometry": {"coordinates":[18.128128,69.62538000000001],"type":"Point"}
}