{
  "type": "Feature",
  "properties": {
    "gn:admin1_code":"7",
    "gn:admin2_code":"1263.0",
    "gn:asciiname":"Kvalvagen",
    "gn:country_code":"NO",
    "gn:dem":30,
    "gn:feature_class":"P",
    "gn:feature_code":"PPL",
    "gn:name":"Kvalv\u00e5gen",
    "gn:population":0,
    "gn:timezone":"Europe/Oslo",
    "iso:country":"NO",
    "wof:name":"Kvalvagen",
    "wof:placetype":"locality"
},
  "geometry": {"coordinates":[5.16925,60.69877],"type":"Point"}
}