{
  "type": "Feature",
  "properties": {
    "gn:admin1_code":"11.0",
    "gn:admin2_code":"536.0",
    "gn:asciiname":"Trevatn",
    "gn:country_code":"NO",
    "gn:dem":420,
    "gn:feature_class":"P",
    "gn:feature_code":"PPL",
    "gn:name":"Trevatn",
    "gn:population":0,
    "gn:timezone":"Europe/Oslo",
    "iso:country":"NO",
    "name:nor_x_preferred":[
        "Trevatn"
    ],
    "wof:name":"Trevatn",
    "wof:placetype":"locality"
},
  "geometry": {"coordinates":[10.51245,60.6268],"type":"Point"}
}