{
  "type": "Feature",
  "properties": {
    "gn:admin1_code":"17",
    "gn:admin2_code":"826.0",
    "gn:asciiname":"Einung",
    "gn:country_code":"NO",
    "gn:dem":724,
    "gn:feature_class":"P",
    "gn:feature_code":"PPL",
    "gn:name":"Einung",
    "gn:population":0,
    "gn:timezone":"Europe/Oslo",
    "iso:country":"NO",
    "wof:name":"Einung",
    "wof:placetype":"locality"
},
  "geometry": {"coordinates":[8.76667,59.91667],"type":"Point"}
}