{
  "type": "Feature",
  "properties": {
    "gn:admin1_code":"19",
    "gn:admin2_code":"1017",
    "gn:asciiname":"Hortemo",
    "gn:country_code":"NO",
    "gn:dem":22,
    "gn:feature_class":"P",
    "gn:feature_code":"PPLL",
    "gn:name":"Hortemo",
    "gn:population":0,
    "gn:timezone":"Europe/Oslo",
    "iso:country":"NO",
    "name:nor_x_preferred":[
        "Hortemo"
    ],
    "wof:name":"Hortemo",
    "wof:placetype":"locality"
},
  "geometry": {"coordinates":[7.82756,58.17276999999999],"type":"Point"}
}