{
  "type": "Feature",
  "properties": {
    "gn:admin1_code":"4",
    "gn:admin2_code":"624",
    "gn:asciiname":"Skotselv",
    "gn:country_code":"NO",
    "gn:dem":40,
    "gn:feature_class":"P",
    "gn:feature_code":"PPL",
    "gn:name":"Skotselv",
    "gn:population":0,
    "gn:timezone":"Europe/Oslo",
    "iso:country":"NO",
    "name:jav_x_preferred":[
        "Skotselv"
    ],
    "name:msa_x_preferred":[
        "Skotselv"
    ],
    "name:nld_x_preferred":[
        "Skotselv"
    ],
    "name:nno_x_preferred":[
        "Skotselv"
    ],
    "name:nor_x_preferred":[
        "Skotselv"
    ],
    "name:ron_x_preferred":[
        "Skotselv"
    ],
    "name:spa_x_preferred":[
        "Skotselv"
    ],
    "wof:name":"Skotselv",
    "wof:placetype":"locality"
},
  "geometry": {"coordinates":[9.88406,59.84503],"type":"Point"}
}