{
  "type": "Feature",
  "properties": {
    "gn:admin1_code":"18.0",
    "gn:admin2_code":"1941.0",
    "gn:asciiname":"Arnoyhamn",
    "gn:country_code":"NO",
    "gn:dem":1,
    "gn:feature_class":"P",
    "gn:feature_code":"PPL",
    "gn:name":"Arn\u00f8yhamn",
    "gn:population":0,
    "gn:timezone":"Europe/Oslo",
    "iso:country":"NO",
    "name:fra_x_preferred":[
        "Arn\u00f8yhamn"
    ],
    "name:msa_x_preferred":[
        "Arn\u00f8yhamn"
    ],
    "name:nno_x_preferred":[
        "Arn\u00f8yhamn"
    ],
    "name:nor_x_preferred":[
        "Arn\u00f8yhamn"
    ],
    "name:spa_x_preferred":[
        "Arn\u00f8yhamn"
    ],
    "wof:name":"Arnoyhamn",
    "wof:placetype":"locality"
},
  "geometry": {"coordinates":[20.63242,70.05271999999999],"type":"Point"}
}