{
  "type": "Feature",
  "properties": {
    "iso:country":"NO",
    "name:ceb_x_preferred":[
        "Sofiemyr"
    ],
    "name:eng_x_preferred":[
        "Sofiemyr"
    ],
    "name:fra_x_preferred":[
        "Sofiemyr"
    ],
    "name:jav_x_preferred":[
        "Sofiemyr"
    ],
    "name:msa_x_preferred":[
        "Sofiemyr"
    ],
    "name:nld_x_preferred":[
        "Sofiemyr"
    ],
    "name:nob_x_preferred":[
        "Sofiemyr"
    ],
    "qs_pg:aaroncc":"NO",
    "qs_pg:name":"Sofiemyr",
    "qs_pg:name_adm0":"Norge",
    "qs_pg:name_adm1":"Akershus Fylke",
    "qs_pg:photos":153,
    "qs_pg:photos_1k":31,
    "qs_pg:photos_9k":1,
    "qs_pg:photos_9r":4,
    "qs_pg:photos_all":153,
    "qs_pg:photos_sr":4,
    "qs_pg:pop_sr":0,
    "qs_pg:qs_pg_placetype":"locality",
    "qs_pg:qs_pg_placetype_gp":"Town",
    "qs_pg:woe_adm0":23424910,
    "woe:adm0_id":23424910,
    "woe:name_adm0":"Norge",
    "woe:name_adm1":"Akershus Fylke",
    "woe:placetype":"Town",
    "wof:name":"Sofiemyr",
    "wof:placetype":"locality"
},
  "geometry": {"coordinates":[10.817756,59.8015],"type":"Point"}
}