{
  "type": "Feature",
  "properties": {
    "gn:admin1_code":"7",
    "gn:admin2_code":"1219",
    "gn:asciiname":"Totlandssjoen",
    "gn:country_code":"NO",
    "gn:dem":1,
    "gn:feature_class":"P",
    "gn:feature_code":"PPLL",
    "gn:name":"Totlandssj\u00f8en",
    "gn:population":0,
    "gn:timezone":"Europe/Oslo",
    "iso:country":"NO",
    "name:nor_x_preferred":[
        "Totlandssj\u00f8en"
    ],
    "wof:name":"Totlandssjoen",
    "wof:placetype":"locality"
},
  "geometry": {"coordinates":[5.34136,59.69456],"type":"Point"}
}