{
  "type": "Feature",
  "properties": {
    "gn:admin1_code":"7",
    "gn:admin2_code":"1224.0",
    "gn:asciiname":"Kaldestad",
    "gn:country_code":"NO",
    "gn:dem":22,
    "gn:feature_class":"P",
    "gn:feature_code":"PPL",
    "gn:name":"Kaldestad",
    "gn:population":0,
    "gn:timezone":"Europe/Oslo",
    "iso:country":"NO",
    "wof:name":"Kaldestad",
    "wof:placetype":"neighbourhood"
},
  "geometry": {"coordinates":[5.73833,59.86],"type":"Point"}
}