{
  "type": "Feature",
  "properties": {
    "gn:admin1_code":"17",
    "gn:admin2_code":"830.0",
    "gn:asciiname":"Fossli",
    "gn:country_code":"NO",
    "gn:dem":221,
    "gn:feature_class":"P",
    "gn:feature_code":"PPL",
    "gn:name":"Fossli",
    "gn:population":0,
    "gn:timezone":"Europe/Oslo",
    "iso:country":"NO",
    "wof:name":"Fossli",
    "wof:placetype":"locality"
},
  "geometry": {"coordinates":[8.51667,58.96666999999999],"type":"Point"}
}