{
  "type": "Feature",
  "properties": {
    "gn:admin1_code":"19.0",
    "gn:admin2_code":"1003.0",
    "gn:asciiname":"Kjorkleiv",
    "gn:country_code":"NO",
    "gn:dem":177,
    "gn:feature_class":"P",
    "gn:feature_code":"PPL",
    "gn:name":"Kj\u00f8rkleiv",
    "gn:population":0,
    "gn:timezone":"Europe/Oslo",
    "iso:country":"NO",
    "name:nor_x_preferred":[
        "Kj\u00f8rkleiv"
    ],
    "wof:name":"Kjorkleiv",
    "wof:placetype":"locality"
},
  "geometry": {"coordinates":[6.73527,58.19512],"type":"Point"}
}