{
  "type": "Feature",
  "properties": {
    "gn:admin1_code":"7",
    "gn:admin2_code":"1245.0",
    "gn:asciiname":"Berge",
    "gn:country_code":"NO",
    "gn:dem":100,
    "gn:feature_class":"P",
    "gn:feature_code":"PPL",
    "gn:name":"Berge",
    "gn:population":0,
    "gn:timezone":"Europe/Oslo",
    "iso:country":"NO",
    "wof:name":"Berge",
    "wof:placetype":"locality"
},
  "geometry": {"coordinates":[5.08333,60.21666999999999],"type":"Point"}
}