{
  "type": "Feature",
  "properties": {
    "gn:admin1_code":"7",
    "gn:admin2_code":"1232.0",
    "gn:asciiname":"Katlo",
    "gn:country_code":"NO",
    "gn:dem":75,
    "gn:feature_class":"P",
    "gn:feature_code":"PPL",
    "gn:name":"Katlo",
    "gn:population":0,
    "gn:timezone":"Europe/Oslo",
    "iso:country":"NO",
    "wof:name":"Katlo",
    "wof:placetype":"locality"
},
  "geometry": {"coordinates":[7.13333,60.41667],"type":"Point"}
}