{
  "type": "Feature",
  "properties": {
    "gn:admin1_code":"21",
    "gn:admin2_code":"5027.0",
    "gn:asciiname":"Bordal",
    "gn:country_code":"NO",
    "gn:dem":310,
    "gn:feature_class":"P",
    "gn:feature_code":"PPL",
    "gn:name":"Bordal",
    "gn:population":0,
    "gn:timezone":"Europe/Oslo",
    "iso:country":"NO",
    "name:nor_x_preferred":[
        "Bordal"
    ],
    "wof:name":"Bordal",
    "wof:placetype":"locality"
},
  "geometry": {"coordinates":[10.16667,62.96666999999999],"type":"Point"}
}