{
  "type": "Feature",
  "properties": {
    "gn:country":"NO",
    "gn:fcode":"PPL",
    "gn:population":0,
    "iso:country":"NO",
    "name:ara_x_preferred":[
        "\u0623\u064a\u062f\u0633\u0628\u0631\u063a"
    ],
    "name:ast_x_preferred":[
        "Eidsberg"
    ],
    "name:aze_x_preferred":[
        "Eydsberq"
    ],
    "name:bar_x_preferred":[
        "Eidsberg"
    ],
    "name:bpy_x_preferred":[
        "\u098f\u09a1\u09bf\u09b8\u09ac\u09be\u09b0\u09cd\u0997"
    ],
    "name:bul_x_preferred":[
        "\u0415\u0438\u0434\u0441\u0431\u0435\u0440\u0433"
    ],
    "name:cat_x_preferred":[
        "Eidsberg"
    ],
    "name:ceb_x_preferred":[
        "Eidsberg"
    ],
    "name:dan_x_preferred":[
        "Eidsberg"
    ],
    "name:deu_x_preferred":[
        "Eidsberg"
    ],
    "name:eng_x_preferred":[
        "Eidsberg"
    ],
    "name:epo_x_preferred":[
        "Eidsberg"
    ],
    "name:est_x_preferred":[
        "Eidsbergi vald"
    ],
    "name:eus_x_preferred":[
        "Eidsberg"
    ],
    "name:fin_x_preferred":[
        "Eidsberg"
    ],
    "name:fra_x_preferred":[
        "Eidsberg"
    ],
    "name:ita_x_preferred":[
        "Eidsberg"
    ],
    "name:jav_x_preferred":[
        "Eidsberg"
    ],
    "name:lat_x_preferred":[
        "Eidsberg"
    ],
    "name:lim_x_preferred":[
        "Eidsberg"
    ],
    "name:lit_x_preferred":[
        "Eidsbergas"
    ],
    "name:msa_x_preferred":[
        "Eidsberg"
    ],
    "name:nan_x_preferred":[
        "Eidsberg"
    ],
    "name:nds_x_preferred":[
        "Kommun Eidsberg"
    ],
    "name:nld_x_preferred":[
        "Eidsberg"
    ],
    "name:nno_x_preferred":[
        "Eidsberg"
    ],
    "name:nob_x_preferred":[
        "Eidsberg"
    ],
    "name:oci_x_preferred":[
        "Eidsberg"
    ],
    "name:pol_x_preferred":[
        "Eidsberg"
    ],
    "name:por_x_preferred":[
        "Eidsberg"
    ],
    "name:ron_x_preferred":[
        "Eidsberg"
    ],
    "name:rus_x_preferred":[
        "\u042d\u0439\u0434\u0441\u0431\u0435\u0440\u0433"
    ],
    "name:sme_x_preferred":[
        "Eidsberg"
    ],
    "name:spa_x_preferred":[
        "Eidsberg"
    ],
    "name:sqi_x_preferred":[
        "Eidsberg"
    ],
    "name:swa_x_preferred":[
        "Eidsberg"
    ],
    "name:swe_x_preferred":[
        "Eidsbergs kommun"
    ],
    "name:vie_x_preferred":[
        "Eidsberg"
    ],
    "name:war_x_preferred":[
        "Eidsberg"
    ],
    "name:zho_x_preferred":[
        "\u57c3\u5fb7\u65af\u8c9d\u683c"
    ],
    "qs_pg:aaroncc":"NO",
    "qs_pg:gn_country":"NO",
    "qs_pg:gn_fcode":"PPL",
    "qs_pg:gn_pop":0,
    "qs_pg:name":"Eidsberg",
    "qs_pg:name_adm0":"Norge",
    "qs_pg:name_adm1":"\u00d8stfold Fylke",
    "qs_pg:photos_9k":1,
    "qs_pg:photos_9r":1,
    "qs_pg:photos_all":1,
    "qs_pg:photos_sr":0,
    "qs_pg:pop_sr":0,
    "qs_pg:qs_pg_placetype":"locality",
    "qs_pg:qs_pg_placetype_gp":"Town",
    "qs_pg:woe_adm0":23424910,
    "woe:adm0_id":23424910,
    "woe:name_adm0":"Norge",
    "woe:name_adm1":"\u00d8stfold Fylke",
    "woe:placetype":"Town",
    "wof:name":"Eidsberg",
    "wof:placetype":"locality"
},
  "geometry": {"coordinates":[11.26667,59.51667],"type":"Point"}
}