{
  "type": "Feature",
  "properties": {
    "gn:admin1_code":"11.0",
    "gn:admin2_code":"521.0",
    "gn:asciiname":"Hundersaetra",
    "gn:country_code":"NO",
    "gn:dem":940,
    "gn:feature_class":"P",
    "gn:feature_code":"PPL",
    "gn:name":"Hunders\u00e6tra",
    "gn:population":0,
    "gn:timezone":"Europe/Oslo",
    "iso:country":"NO",
    "name:nor_x_preferred":[
        "Hunders\u00e6tra"
    ],
    "wof:name":"Hundersaetra",
    "wof:placetype":"locality"
},
  "geometry": {"coordinates":[10.54797,61.22386],"type":"Point"}
}