{
  "type": "Feature",
  "properties": {
    "gn:admin1_code":"1.0",
    "gn:admin2_code":"214.0",
    "gn:asciiname":"Solhaug",
    "gn:country_code":"NO",
    "gn:dem":161,
    "gn:feature_class":"P",
    "gn:feature_code":"PPL",
    "gn:name":"Solhaug",
    "gn:population":0,
    "gn:timezone":"Europe/Oslo",
    "iso:country":"NO",
    "name:nor_x_preferred":[
        "Solhaug"
    ],
    "wof:name":"Solhaug",
    "wof:placetype":"locality"
},
  "geometry": {"coordinates":[10.80503,59.71925],"type":"Point"}
}