{
  "type": "Feature",
  "properties": {
    "gn:admin1_code":"9.0",
    "gn:admin2_code":"1865.0",
    "gn:asciiname":"Saupstad",
    "gn:country_code":"NO",
    "gn:dem":1,
    "gn:feature_class":"P",
    "gn:feature_code":"PPL",
    "gn:name":"Saupstad",
    "gn:population":0,
    "gn:timezone":"Europe/Oslo",
    "iso:country":"NO",
    "wof:name":"Saupstad",
    "wof:placetype":"locality"
},
  "geometry": {"coordinates":[14.16667,68.33333],"type":"Point"}
}