{
  "type": "Feature",
  "properties": {
    "gn:admin1_code":"5.0",
    "gn:admin2_code":"2020.0",
    "gn:asciiname":"Brennelv,ovre",
    "gn:country_code":"NO",
    "gn:dem":21,
    "gn:feature_class":"P",
    "gn:feature_code":"PPL",
    "gn:name":"Brennelv,\u00f8vre",
    "gn:population":0,
    "gn:timezone":"Europe/Oslo",
    "iso:country":"NO",
    "name:fkv_x_preferred":[
        "Yli-Palo"
    ],
    "name:nor_x_preferred":[
        "Brennelv,\u00f8vre"
    ],
    "name:nor_x_variant":[
        "\u00d8vre Brennelv"
    ],
    "wof:name":"Brennelv,ovre",
    "wof:placetype":"locality"
},
  "geometry": {"coordinates":[25.06757,70.05069],"type":"Point"}
}