{
  "type": "Feature",
  "properties": {
    "gn:admin1_code":"9.0",
    "gn:admin2_code":"1841.0",
    "gn:asciiname":"Stokkland",
    "gn:country_code":"NO",
    "gn:dem":9,
    "gn:feature_class":"P",
    "gn:feature_code":"PPL",
    "gn:name":"Stokkland",
    "gn:population":0,
    "gn:timezone":"Europe/Oslo",
    "iso:country":"NO",
    "wof:name":"Stokkland",
    "wof:placetype":"locality"
},
  "geometry": {"coordinates":[15.15541,67.28713],"type":"Point"}
}