{
  "type": "Feature",
  "properties": {
    "gn:admin1_code":"13",
    "gn:admin2_code":"127.0",
    "gn:asciiname":"Langli",
    "gn:cc2":"NO",
    "gn:country_code":"NO",
    "gn:dem":121,
    "gn:feature_class":"P",
    "gn:feature_code":"PPL",
    "gn:name":"Langli",
    "gn:population":0,
    "gn:timezone":"Europe/Oslo",
    "iso:country":"NO",
    "name:und_x_variant":[
        "Langeli",
        "Langli"
    ],
    "wof:name":"Langli",
    "wof:placetype":"locality"
},
  "geometry": {"coordinates":[11.13333,59.53333000000001],"type":"Point"}
}