{
  "type": "Feature",
  "properties": {
    "gn:admin1_code":"17.0",
    "gn:admin2_code":"834.0",
    "gn:asciiname":"Skalestrondi",
    "gn:country_code":"NO",
    "gn:dem":712,
    "gn:feature_class":"P",
    "gn:feature_code":"PPL",
    "gn:name":"Sk\u00e5lestrondi",
    "gn:population":0,
    "gn:timezone":"Europe/Oslo",
    "iso:country":"NO",
    "name:nor_x_preferred":[
        "Sk\u00e5lestrondi"
    ],
    "wof:name":"Skalestrondi",
    "wof:placetype":"locality"
},
  "geometry": {"coordinates":[8.03801,59.66273],"type":"Point"}
}