{
  "type": "Feature",
  "properties": {
    "iso:country":"NO",
    "qs_pg:aaroncc":"NO",
    "qs_pg:name":"Moskushamn",
    "qs_pg:name_adm0":"Svalbard",
    "qs_pg:name_adm1":"Svalbard",
    "qs_pg:photos":190,
    "qs_pg:photos_1k":39,
    "qs_pg:photos_9k":1,
    "qs_pg:photos_9r":4,
    "qs_pg:photos_all":190,
    "qs_pg:photos_sr":4,
    "qs_pg:pop_sr":0,
    "qs_pg:qs_pg_placetype":"locality",
    "qs_pg:qs_pg_placetype_gp":"Town",
    "qs_pg:woe_adm0":28289413,
    "woe:adm0_id":28289413,
    "woe:name_adm0":"Svalbard",
    "woe:name_adm1":"Svalbard",
    "woe:placetype":"Town",
    "wof:name":"Moskushamn",
    "wof:placetype":"locality"
},
  "geometry": {"coordinates":[15.7266775,78.250119],"type":"Point"}
}