{
  "type": "Feature",
  "properties": {
    "gn:admin1_code":"18.0",
    "gn:admin2_code":"1913.0",
    "gn:asciiname":"Forneset",
    "gn:country_code":"NO",
    "gn:dem":-9999,
    "gn:feature_class":"P",
    "gn:feature_code":"PPL",
    "gn:name":"Forneset",
    "gn:population":0,
    "gn:timezone":"Europe/Oslo",
    "iso:country":"NO",
    "name:nor_x_preferred":[
        "Forneset"
    ],
    "wof:name":"Forneset",
    "wof:placetype":"locality"
},
  "geometry": {"coordinates":[17.04293,68.71281999999999],"type":"Point"}
}