{
  "type": "Feature",
  "properties": {
    "gn:admin1_code":"21",
    "gn:admin2_code":"5001",
    "gn:asciiname":"Lundasen",
    "gn:country_code":"NO",
    "gn:dem":170,
    "gn:feature_class":"P",
    "gn:feature_code":"PPLL",
    "gn:name":"Lund\u00e5sen",
    "gn:population":0,
    "gn:timezone":"Europe/Oslo",
    "iso:country":"NO",
    "name:nor_x_preferred":[
        "Lund\u00e5sen"
    ],
    "wof:name":"Lundasen",
    "wof:placetype":"neighbourhood"
},
  "geometry": {"coordinates":[10.32683,63.35217],"type":"Point"}
}