{
  "type": "Feature",
  "properties": {
    "gn:admin1_code":"15",
    "gn:admin2_code":"1441.0",
    "gn:asciiname":"Hove",
    "gn:country_code":"NO",
    "gn:dem":-9999,
    "gn:feature_class":"P",
    "gn:feature_code":"PPL",
    "gn:name":"Hove",
    "gn:population":0,
    "gn:timezone":"Europe/Oslo",
    "iso:country":"NO",
    "wof:name":"Hove",
    "wof:placetype":"locality"
},
  "geometry": {"coordinates":[5.33333,62.05],"type":"Point"}
}