{
  "type": "Feature",
  "properties": {
    "gn:admin1_code":"15",
    "gn:admin2_code":"1441.0",
    "gn:asciiname":"Hove",
    "gn:country_code":"NO",
    "gn:dem":-9999,
    "gn:feature_class":"P",
    "gn:feature_code":"PPL",
    "gn:name":"Hove",
    "gn:population":0,
    "gn:timezone":"Europe/Oslo",
    "iso:country":"NO",
    "name:azb_x_preferred":[
        "\u0647\u0648\u0648"
    ],
    "name:bar_x_preferred":[
        "Hove"
    ],
    "name:ceb_x_preferred":[
        "Hove"
    ],
    "name:ces_x_preferred":[
        "Hove"
    ],
    "name:deu_x_preferred":[
        "Hove"
    ],
    "name:epo_x_preferred":[
        "Hove"
    ],
    "name:est_x_preferred":[
        "Hove"
    ],
    "name:fas_x_preferred":[
        "\u0647\u0648\u0648"
    ],
    "name:fra_x_preferred":[
        "Hove"
    ],
    "name:hin_x_preferred":[
        "\u0939\u094b\u0935"
    ],
    "name:ita_x_preferred":[
        "Hove"
    ],
    "name:nld_x_preferred":[
        "Hove"
    ],
    "name:pol_x_preferred":[
        "Hove"
    ],
    "name:por_x_preferred":[
        "Hove"
    ],
    "name:ron_x_preferred":[
        "Hove"
    ],
    "name:rus_x_preferred":[
        "\u0425\u043e\u0432"
    ],
    "name:spa_x_preferred":[
        "Hove"
    ],
    "name:srp_x_preferred":[
        "\u0425\u043e\u0443\u0432"
    ],
    "name:swe_x_preferred":[
        "Hove"
    ],
    "name:urd_x_preferred":[
        "\u06c1\u0648\u0648"
    ],
    "name:war_x_preferred":[
        "Hove"
    ],
    "name:zho_x_preferred":[
        "\u970d\u592b"
    ],
    "wof:name":"Hove",
    "wof:placetype":"locality"
},
  "geometry": {"coordinates":[5.33333,62.05],"type":"Point"}
}