{
  "type": "Feature",
  "properties": {
    "gn:country":"NO",
    "gn:fcode":"PPLA2",
    "gn:population":0,
    "iso:country":"NO",
    "name:ceb_x_preferred":[
        "Valder\u00f8ya"
    ],
    "name:deu_x_preferred":[
        "Valder\u00f8ya"
    ],
    "name:nno_x_preferred":[
        "Valder\u00f8ya"
    ],
    "name:nor_x_preferred":[
        "Valder\u00f8y"
    ],
    "name:spa_x_preferred":[
        "Valder\u00f8y"
    ],
    "qs_pg:aaroncc":"NO",
    "qs_pg:gn_country":"NO",
    "qs_pg:gn_fcode":"PPLA2",
    "qs_pg:gn_pop":0,
    "qs_pg:name":"Valder\u00f8y",
    "qs_pg:photos_9r":0,
    "qs_pg:photos_sr":0,
    "qs_pg:pop_sr":0,
    "qs_pg:qs_pg_placetype":"locality",
    "wof:name":"Valder\u00f8y",
    "wof:placetype":"locality"
},
  "geometry": {"coordinates":[6.13472,62.5007],"type":"Point"}
}