{
  "type": "Feature",
  "properties": {
    "gn:admin1_code":"18.0",
    "gn:admin2_code":"1917.0",
    "gn:asciiname":"Straumen",
    "gn:country_code":"NO",
    "gn:dem":44,
    "gn:feature_class":"P",
    "gn:feature_code":"PPL",
    "gn:name":"Straumen",
    "gn:population":0,
    "gn:timezone":"Europe/Oslo",
    "iso:country":"NO",
    "wof:name":"Straumen",
    "wof:placetype":"locality"
},
  "geometry": {"coordinates":[17.19501,68.91276999999999],"type":"Point"}
}