{
  "type": "Feature",
  "properties": {
    "gn:admin1_code":"18.0",
    "gn:admin2_code":"1917.0",
    "gn:asciiname":"Straumen",
    "gn:country_code":"NO",
    "gn:dem":44,
    "gn:feature_class":"P",
    "gn:feature_code":"PPL",
    "gn:name":"Straumen",
    "gn:population":0,
    "gn:timezone":"Europe/Oslo",
    "iso:country":"NO",
    "name:ceb_x_preferred":[
        "Straumen"
    ],
    "name:deu_x_preferred":[
        "Straumen"
    ],
    "name:ita_x_preferred":[
        "Straumen"
    ],
    "name:nld_x_preferred":[
        "Straumen"
    ],
    "name:nno_x_preferred":[
        "Straumen"
    ],
    "name:nor_x_preferred":[
        "Straumen"
    ],
    "name:ron_x_preferred":[
        "Straumen"
    ],
    "name:spa_x_preferred":[
        "Straumen"
    ],
    "wof:name":"Straumen",
    "wof:placetype":"locality"
},
  "geometry": {"coordinates":[17.19501,68.91276999999999],"type":"Point"}
}