{
  "type": "Feature",
  "properties": {
    "gn:admin1_code":"7",
    "gn:admin2_code":"1256.0",
    "gn:asciiname":"Vollo",
    "gn:country_code":"NO",
    "gn:dem":60,
    "gn:feature_class":"P",
    "gn:feature_code":"PPLL",
    "gn:name":"Vollo",
    "gn:population":0,
    "gn:timezone":"Europe/Oslo",
    "iso:country":"NO",
    "wof:name":"Vollo",
    "wof:placetype":"locality"
},
  "geometry": {"coordinates":[5.14556,60.54417],"type":"Point"}
}