{
  "type": "Feature",
  "properties": {
    "gn:gn_country":"NO",
    "gn:gn_fcode":"PPL",
    "gn:gn_pop":0,
    "iso:country":"NO",
    "name:eng_x_preferred":[
        "Laupstad"
    ],
    "name:fra_x_preferred":[
        "Laupstad"
    ],
    "name:jav_x_preferred":[
        "Laupstad"
    ],
    "name:msa_x_preferred":[
        "Laupstad"
    ],
    "name:nld_x_preferred":[
        "Laupstad"
    ],
    "name:nob_x_preferred":[
        "Laupstad"
    ],
    "qs_pg:aaroncc":"NO",
    "qs_pg:gn_country":"NO",
    "qs_pg:gn_fcode":"PPL",
    "qs_pg:gn_pop":0,
    "qs_pg:name":"Laupstad",
    "qs_pg:name_adm0":"Norge",
    "qs_pg:name_adm1":"Nordland Fylke",
    "qs_pg:photos":535,
    "qs_pg:photos_1k":108,
    "qs_pg:photos_9k":2,
    "qs_pg:photos_9r":5,
    "qs_pg:photos_all":535,
    "qs_pg:photos_sr":7,
    "qs_pg:pop_sr":0,
    "qs_pg:qs_pg_placetype":"locality",
    "qs_pg:qs_pg_placetype_gp":"Town",
    "qs_pg:woe_adm0":23424910,
    "woe:adm0_id":23424910,
    "woe:name_adm0":"Norge",
    "woe:name_adm1":"Nordland Fylke",
    "woe:placetype":"Town",
    "wof:name":"Laupstad",
    "wof:placetype":"locality"
},
  "geometry": {"coordinates":[14.73333,68.34999999999999],"type":"Point"}
}