{
  "type": "Feature",
  "properties": {
    "gn:admin1_code":"4",
    "gn:admin2_code":"604",
    "gn:asciiname":"Kongsgardmoen",
    "gn:country_code":"NO",
    "gn:dem":176,
    "gn:feature_class":"P",
    "gn:feature_code":"PPLL",
    "gn:name":"Kongsg\u00e5rdmoen",
    "gn:population":0,
    "gn:timezone":"Europe/Oslo",
    "iso:country":"NO",
    "name:nor_x_preferred":[
        "Kongsg\u00e5rdmoen"
    ],
    "wof:name":"Kongsgardmoen",
    "wof:placetype":"neighbourhood"
},
  "geometry": {"coordinates":[9.64105,59.63314],"type":"Point"}
}