{
  "type": "Feature",
  "properties": {
    "gn:admin1_code":"7.0",
    "gn:admin2_code":"1264.0",
    "gn:asciiname":"Rongevaer",
    "gn:cc2":"NO",
    "gn:country_code":"NO",
    "gn:dem":-9999,
    "gn:feature_class":"P",
    "gn:feature_code":"PPL",
    "gn:name":"Rongev\u00e6r",
    "gn:population":0,
    "gn:timezone":"Europe/Oslo",
    "iso:country":"NO",
    "name:und_x_variant":[
        "Rognev\u00e6r",
        "Rongev\u00e6r"
    ],
    "wof:name":"Rongevaer",
    "wof:placetype":"locality"
},
  "geometry": {"coordinates":[4.78333,60.81667],"type":"Point"}
}