{
  "type": "Feature",
  "properties": {
    "gn:gn_country":"NO",
    "gn:gn_fcode":"PPL",
    "gn:gn_pop":384,
    "gn:population":384,
    "iso:country":"NO",
    "name:eng_x_preferred":[
        "Brusand"
    ],
    "name:fra_x_preferred":[
        "Brusand"
    ],
    "name:jav_x_preferred":[
        "Brusand"
    ],
    "name:msa_x_preferred":[
        "Brusand"
    ],
    "name:nld_x_preferred":[
        "Brusand"
    ],
    "name:nno_x_preferred":[
        "Brusand"
    ],
    "name:nob_x_preferred":[
        "Brusand"
    ],
    "name:ron_x_preferred":[
        "Brusand"
    ],
    "qs_pg:aaroncc":"NO",
    "qs_pg:gn_country":"NO",
    "qs_pg:gn_fcode":"PPL",
    "qs_pg:gn_pop":384,
    "qs_pg:name":"Brusand",
    "qs_pg:name_adm0":"Norge",
    "qs_pg:name_adm1":"Rogaland Fylke",
    "qs_pg:photos":114,
    "qs_pg:photos_1k":23,
    "qs_pg:photos_9k":1,
    "qs_pg:photos_9r":3,
    "qs_pg:photos_all":114,
    "qs_pg:photos_sr":3,
    "qs_pg:pop_sr":2,
    "qs_pg:qs_pg_placetype":"locality",
    "qs_pg:qs_pg_placetype_gp":"Town",
    "qs_pg:woe_adm0":23424910,
    "woe:adm0_id":23424910,
    "woe:name_adm0":"Norge",
    "woe:name_adm1":"Rogaland Fylke",
    "woe:placetype":"Town",
    "wof:name":"Brusand",
    "wof:placetype":"locality",
    "wof:population":384
},
  "geometry": {"coordinates":[5.76667,58.53333],"type":"Point"}
}