{
  "type": "Feature",
  "properties": {
    "gn:admin1_code":"5.0",
    "gn:admin2_code":"2017.0",
    "gn:asciiname":"Oldervik",
    "gn:country_code":"NO",
    "gn:dem":107,
    "gn:feature_class":"P",
    "gn:feature_code":"PPL",
    "gn:name":"Oldervik",
    "gn:population":0,
    "gn:timezone":"Europe/Oslo",
    "iso:country":"NO",
    "wof:name":"Oldervik",
    "wof:placetype":"locality"
},
  "geometry": {"coordinates":[23.68139,70.42055999999999],"type":"Point"}
}