{
  "type": "Feature",
  "properties": {
    "gn:admin1_code":"21.0",
    "gn:admin2_code":"5016.0",
    "gn:asciiname":"Stordalsbugen",
    "gn:cc2":"NO",
    "gn:country_code":"NO",
    "gn:dem":10,
    "gn:feature_class":"P",
    "gn:feature_code":"PPL",
    "gn:name":"St\u00f8rdalsbugen",
    "gn:population":0,
    "gn:timezone":"Europe/Oslo",
    "iso:country":"NO",
    "name:und_x_variant":[
        "St\u00f6rdals\u00f6ren",
        "St\u00f8rdalsbugen"
    ],
    "wof:name":"Stordalsbugen",
    "wof:placetype":"locality"
},
  "geometry": {"coordinates":[9.78333,63.56667],"type":"Point"}
}