{
  "type": "Feature",
  "properties": {
    "gn:admin1_code":"14",
    "gn:admin2_code":"1149.0",
    "gn:asciiname":"Fosen",
    "gn:country_code":"NO",
    "gn:dem":-9999,
    "gn:feature_class":"P",
    "gn:feature_code":"PPL",
    "gn:name":"Fosen",
    "gn:population":0,
    "gn:timezone":"Europe/Oslo",
    "iso:country":"NO",
    "name:azb_x_preferred":[
        "\u0641\u0627\u0633\u0646"
    ],
    "name:bar_x_preferred":[
        "Fosen"
    ],
    "name:cat_x_preferred":[
        "Fosen"
    ],
    "name:dan_x_preferred":[
        "Fosen"
    ],
    "name:deu_x_preferred":[
        "Fosen"
    ],
    "name:fra_x_preferred":[
        "Fosen"
    ],
    "name:nno_x_preferred":[
        "Fosen"
    ],
    "name:nor_x_preferred":[
        "Fosen"
    ],
    "name:pnb_x_preferred":[
        "\u0641\u0648\u0633\u0646\u0627"
    ],
    "name:sme_x_preferred":[
        "Fosen"
    ],
    "wof:name":"Fosen",
    "wof:placetype":"locality"
},
  "geometry": {"coordinates":[5.38333,59.31667],"type":"Point"}
}