{
  "type": "Feature",
  "properties": {
    "gn:admin1_code":"14",
    "gn:admin2_code":"1149.0",
    "gn:asciiname":"Fosen",
    "gn:country_code":"NO",
    "gn:dem":-9999,
    "gn:feature_class":"P",
    "gn:feature_code":"PPL",
    "gn:name":"Fosen",
    "gn:population":0,
    "gn:timezone":"Europe/Oslo",
    "iso:country":"NO",
    "wof:name":"Fosen",
    "wof:placetype":"locality"
},
  "geometry": {"coordinates":[5.38333,59.31667],"type":"Point"}
}