{
  "type": "Feature",
  "properties": {
    "gn:admin1_code":"18.0",
    "gn:admin2_code":"1931.0",
    "gn:asciiname":"Rossfjord",
    "gn:cc2":"NO",
    "gn:country_code":"NO",
    "gn:dem":1,
    "gn:feature_class":"P",
    "gn:feature_code":"PPL",
    "gn:name":"Rossfjord",
    "gn:population":0,
    "gn:timezone":"Europe/Oslo",
    "iso:country":"NO",
    "name:und_x_variant":[
        "Rogsfjord",
        "Rossfjord"
    ],
    "wof:name":"Rossfjord",
    "wof:placetype":"locality"
},
  "geometry": {"coordinates":[18.38538,69.39435],"type":"Point"}
}