{
  "type": "Feature",
  "properties": {
    "gn:admin1_code":"21",
    "gn:admin2_code":"5027.0",
    "gn:asciiname":"Fredheim",
    "gn:country_code":"NO",
    "gn:dem":82,
    "gn:feature_class":"P",
    "gn:feature_code":"PPLL",
    "gn:name":"Fredheim",
    "gn:population":0,
    "gn:timezone":"Europe/Oslo",
    "iso:country":"NO",
    "wof:name":"Fredheim",
    "wof:placetype":"locality"
},
  "geometry": {"coordinates":[10.28371,63.04101],"type":"Point"}
}