{
  "type": "Feature",
  "properties": {
    "gn:admin1_code":"13",
    "gn:admin2_code":"105",
    "gn:asciiname":"Bede",
    "gn:country_code":"NO",
    "gn:dem":37,
    "gn:feature_class":"P",
    "gn:feature_code":"PPLL",
    "gn:name":"Bede",
    "gn:population":0,
    "gn:timezone":"Europe/Oslo",
    "iso:country":"NO",
    "name:nor_x_preferred":[
        "Bede"
    ],
    "name:nor_x_variant":[
        "Navestad"
    ],
    "wof:name":"Bede",
    "wof:placetype":"locality"
},
  "geometry": {"coordinates":[11.13066,59.2606],"type":"Point"}
}