{
  "type": "Feature",
  "properties": {
    "gn:admin1_code":"17",
    "gn:admin2_code":"805.0",
    "gn:asciiname":"Eidanger",
    "gn:country_code":"NO",
    "gn:dem":39,
    "gn:feature_class":"P",
    "gn:feature_code":"PPL",
    "gn:name":"Eidanger",
    "gn:population":0,
    "gn:timezone":"Europe/Oslo",
    "iso:country":"NO",
    "name:msa_x_preferred":[
        "Eidanger"
    ],
    "name:nno_x_preferred":[
        "Eidanger"
    ],
    "name:nor_x_preferred":[
        "Eidanger"
    ],
    "name:por_x_preferred":[
        "Eidanger"
    ],
    "wof:name":"Eidanger",
    "wof:placetype":"locality"
},
  "geometry": {"coordinates":[9.71852,59.1174],"type":"Point"}
}