{
  "type": "Feature",
  "properties": {
    "gn:admin1_code":"21.0",
    "gn:admin2_code":"5019.0",
    "gn:asciiname":"Vorpstranda",
    "gn:cc2":"NO",
    "gn:country_code":"NO",
    "gn:dem":287,
    "gn:feature_class":"P",
    "gn:feature_code":"PPL",
    "gn:name":"Vorpstranda",
    "gn:population":0,
    "gn:timezone":"Europe/Oslo",
    "iso:country":"NO",
    "name:und_x_variant":[
        "Vorpstranden",
        "Vorpstranda"
    ],
    "wof:name":"Vorpstranda",
    "wof:placetype":"locality"
},
  "geometry": {"coordinates":[10.21667,64.11667],"type":"Point"}
}