{
  "type": "Feature",
  "properties": {
    "gn:admin1_code":"9",
    "gn:admin2_code":"1822.0",
    "gn:asciiname":"Litle Fagervika",
    "gn:cc2":"NO",
    "gn:country_code":"NO",
    "gn:dem":440,
    "gn:feature_class":"P",
    "gn:feature_code":"PPL",
    "gn:name":"Litle Fagervika",
    "gn:population":0,
    "gn:timezone":"Europe/Oslo",
    "iso:country":"NO",
    "name:und_x_variant":[
        "Fagervika",
        "Fagervik",
        "Fagerviken",
        "Litle Fagervika"
    ],
    "wof:name":"Litle Fagervika",
    "wof:placetype":"locality"
},
  "geometry": {"coordinates":[12.78333,66.09999999999999],"type":"Point"}
}