{
  "type": "Feature",
  "properties": {
    "gn:admin1_code":"9.0",
    "gn:admin2_code":"1832.0",
    "gn:asciiname":"Valamoen",
    "gn:cc2":"NO",
    "gn:country_code":"NO",
    "gn:dem":40,
    "gn:feature_class":"P",
    "gn:feature_code":"PPL",
    "gn:name":"Val\u00e5moen",
    "gn:population":0,
    "gn:timezone":"Europe/Oslo",
    "iso:country":"NO",
    "name:und_x_variant":[
        "Valaamoen",
        "Val\u00e5moen"
    ],
    "wof:name":"Valamoen",
    "wof:placetype":"locality"
},
  "geometry": {"coordinates":[13.8077,66.08709],"type":"Point"}
}