{
  "type": "Feature",
  "properties": {
    "gn:admin1_code":"9.0",
    "gn:admin2_code":"1865.0",
    "gn:asciiname":"Svolvaer (Lofoten)",
    "gn:country_code":"NO",
    "gn:dem":3,
    "gn:feature_class":"P",
    "gn:feature_code":"PPL",
    "gn:name":"Svolv\u00e6r (Lofoten)",
    "gn:population":0,
    "gn:timezone":"Europe/Oslo",
    "iso:country":"NO",
    "wof:name":"Svolvaer (Lofoten)",
    "wof:placetype":"neighbourhood"
},
  "geometry": {"coordinates":[14.56615,68.23568],"type":"Point"}
}