{
  "type": "Feature",
  "properties": {
    "gn:admin1_code":"15",
    "gn:admin2_code":"1428.0",
    "gn:asciiname":"Hegrenes",
    "gn:country_code":"NO",
    "gn:dem":120,
    "gn:feature_class":"P",
    "gn:feature_code":"PPL",
    "gn:name":"Hegrenes",
    "gn:population":0,
    "gn:timezone":"Europe/Oslo",
    "iso:country":"NO",
    "wof:name":"Hegrenes",
    "wof:placetype":"locality"
},
  "geometry": {"coordinates":[5.35,61.46666999999999],"type":"Point"}
}