{
  "type": "Feature",
  "properties": {
    "gn:admin1_code":"7",
    "gn:admin2_code":"1201.0",
    "gn:asciiname":"Festervik",
    "gn:country_code":"NO",
    "gn:dem":-9999,
    "gn:feature_class":"P",
    "gn:feature_code":"PPL",
    "gn:name":"Festervik",
    "gn:population":0,
    "gn:timezone":"Europe/Oslo",
    "iso:country":"NO",
    "wof:name":"Festervik",
    "wof:placetype":"locality"
},
  "geometry": {"coordinates":[5.21667,60.31667],"type":"Point"}
}