{
  "type": "Feature",
  "properties": {
    "gn:admin1_code":"21",
    "gn:admin2_code":"5004.0",
    "gn:asciiname":"Eli",
    "gn:country_code":"NO",
    "gn:dem":49,
    "gn:feature_class":"P",
    "gn:feature_code":"PPL",
    "gn:name":"Eli",
    "gn:population":0,
    "gn:timezone":"Europe/Oslo",
    "iso:country":"NO",
    "name:ceb_x_preferred":[
        "Eli"
    ],
    "name:deu_x_preferred":[
        "Eli"
    ],
    "name:heb_x_preferred":[
        "\u05d0\u05dc\u05d9"
    ],
    "name:ind_x_preferred":[
        "Eli"
    ],
    "name:nor_x_preferred":[
        "Eli"
    ],
    "name:rus_x_preferred":[
        "\u042d\u043b\u0438"
    ],
    "name:swe_x_preferred":[
        "Eli"
    ],
    "wof:name":"Eli",
    "wof:placetype":"locality"
},
  "geometry": {"coordinates":[11.67271,64.06251],"type":"Point"}
}