{
  "type": "Feature",
  "properties": {
    "gn:admin1_code":"8",
    "gn:admin2_code":"1576.0",
    "gn:asciiname":"Asgard",
    "gn:cc2":"NO",
    "gn:country_code":"NO",
    "gn:dem":180,
    "gn:feature_class":"P",
    "gn:feature_code":"PPL",
    "gn:name":"\u00c5sgard",
    "gn:population":0,
    "gn:timezone":"Europe/Oslo",
    "iso:country":"NO",
    "name:und_x_variant":[
        "Aasgaard",
        "\u00c5sgard"
    ],
    "wof:name":"Asgard",
    "wof:placetype":"locality"
},
  "geometry": {"coordinates":[8.85,63.35],"type":"Point"}
}