{
  "type": "Feature",
  "properties": {
    "gn:admin1_code":"8",
    "gn:admin2_code":"1576.0",
    "gn:asciiname":"Akvika",
    "gn:cc2":"NO",
    "gn:country_code":"NO",
    "gn:dem":-9999,
    "gn:feature_class":"P",
    "gn:feature_code":"PPL",
    "gn:name":"\u00c5kvika",
    "gn:population":0,
    "gn:timezone":"Europe/Oslo",
    "iso:country":"NO",
    "name:und_x_variant":[
        "Aakvik",
        "\u00c5kvik"
    ],
    "wof:name":"Akvika",
    "wof:placetype":"locality"
},
  "geometry": {"coordinates":[8.45806,63.33649000000001],"type":"Point"}
}