{
  "type": "Feature",
  "properties": {
    "gn:admin1_code":"17",
    "gn:admin2_code":"806.0",
    "gn:asciiname":"Eikonrod",
    "gn:country_code":"NO",
    "gn:dem":31,
    "gn:feature_class":"P",
    "gn:feature_code":"PPL",
    "gn:name":"Eikonr\u00f8d",
    "gn:population":0,
    "gn:timezone":"Europe/Oslo",
    "iso:country":"NO",
    "wof:name":"Eikonrod",
    "wof:placetype":"neighbourhood"
},
  "geometry": {"coordinates":[9.61667,59.18333000000001],"type":"Point"}
}