{
  "type": "Feature",
  "properties": {
    "gn:admin1_code":"15",
    "gn:admin2_code":"1411.0",
    "gn:asciiname":"Glenja",
    "gn:country_code":"NO",
    "gn:dem":3,
    "gn:feature_class":"P",
    "gn:feature_code":"PPL",
    "gn:name":"Glenja",
    "gn:population":0,
    "gn:timezone":"Europe/Oslo",
    "iso:country":"NO",
    "wof:name":"Glenja",
    "wof:placetype":"locality"
},
  "geometry": {"coordinates":[5.11667,60.88333000000001],"type":"Point"}
}