{
  "type": "Feature",
  "properties": {
    "gn:admin1_code":"1.0",
    "gn:admin2_code":"237.0",
    "gn:asciiname":"Stubberuddalen",
    "gn:country_code":"NO",
    "gn:dem":123,
    "gn:feature_class":"P",
    "gn:feature_code":"PPL",
    "gn:name":"Stubberuddalen",
    "gn:population":0,
    "gn:timezone":"Europe/Oslo",
    "iso:country":"NO",
    "wof:name":"Stubberuddalen",
    "wof:placetype":"locality"
},
  "geometry": {"coordinates":[11.1884,60.54243],"type":"Point"}
}