{
  "type": "Feature",
  "properties": {
    "gn:admin1_code":"18.0",
    "gn:admin2_code":"1940.0",
    "gn:asciiname":"Fossen",
    "gn:cc2":"NO",
    "gn:country_code":"NO",
    "gn:dem":58,
    "gn:feature_class":"P",
    "gn:feature_code":"PPL",
    "gn:name":"Fossen",
    "gn:population":0,
    "gn:timezone":"Europe/Oslo",
    "iso:country":"NO",
    "name:und_x_variant":[
        "Store Vatn",
        "Fossheim"
    ],
    "wof:name":"Fossen",
    "wof:placetype":"locality"
},
  "geometry": {"coordinates":[20.52445,69.52542],"type":"Point"}
}