{
  "type": "Feature",
  "properties": {
    "gn:admin1_code":"6.0",
    "gn:admin2_code":"441.0",
    "gn:asciiname":"Oslia",
    "gn:country_code":"NO",
    "gn:dem":830,
    "gn:feature_class":"P",
    "gn:feature_code":"PPL",
    "gn:name":"Oslia",
    "gn:population":0,
    "gn:timezone":"Europe/Oslo",
    "iso:country":"NO",
    "name:nor_x_preferred":[
        "Oslia"
    ],
    "wof:name":"Oslia",
    "wof:placetype":"locality"
},
  "geometry": {"coordinates":[11.07355,62.47047],"type":"Point"}
}