{
  "type": "Feature",
  "properties": {
    "gn:admin1_code":"9.0",
    "gn:admin2_code":"1836.0",
    "gn:asciiname":"Storseloya",
    "gn:cc2":"NO",
    "gn:country_code":"NO",
    "gn:dem":5,
    "gn:feature_class":"P",
    "gn:feature_code":"PPL",
    "gn:name":"Storsel\u00f8ya",
    "gn:population":0,
    "gn:timezone":"Europe/Oslo",
    "iso:country":"NO",
    "name:und_x_variant":[
        "Sels\u00f6en",
        "Storsel\u00f8ya"
    ],
    "wof:name":"Storseloya",
    "wof:placetype":"locality"
},
  "geometry": {"coordinates":[12.85,66.55],"type":"Point"}
}