{
  "type": "Feature",
  "properties": {
    "gn:admin1_code":"7",
    "gn:admin2_code":"1264.0",
    "gn:asciiname":"Fonnes",
    "gn:country_code":"NO",
    "gn:dem":20,
    "gn:feature_class":"P",
    "gn:feature_code":"PPLL",
    "gn:name":"Fonnes",
    "gn:population":0,
    "gn:timezone":"Europe/Oslo",
    "iso:country":"NO",
    "wof:name":"Fonnes",
    "wof:placetype":"locality"
},
  "geometry": {"coordinates":[4.9798,60.80301],"type":"Point"}
}