{
  "type": "Feature",
  "properties": {
    "gn:admin1_code":"11.0",
    "gn:admin2_code":"543.0",
    "gn:asciiname":"Kvalestolen",
    "gn:country_code":"NO",
    "gn:dem":870,
    "gn:feature_class":"P",
    "gn:feature_code":"PPL",
    "gn:name":"Kv\u00e5lest\u00f8len",
    "gn:population":0,
    "gn:timezone":"Europe/Oslo",
    "iso:country":"NO",
    "name:nor_x_preferred":[
        "Kv\u00e5lest\u00f8len"
    ],
    "wof:name":"Kvalestolen",
    "wof:placetype":"locality"
},
  "geometry": {"coordinates":[8.94204,60.98517],"type":"Point"}
}