{
  "type": "Feature",
  "properties": {
    "gn:admin1_code":"14",
    "gn:admin2_code":"1103.0",
    "gn:asciiname":"Hoye",
    "gn:cc2":"NO",
    "gn:country_code":"NO",
    "gn:dem":37,
    "gn:feature_class":"P",
    "gn:feature_code":"PPL",
    "gn:name":"H\u00f8ye",
    "gn:population":0,
    "gn:timezone":"Europe/Oslo",
    "iso:country":"NO",
    "name:und_x_variant":[
        "H\u00f6ie",
        "H\u00f8ye"
    ],
    "wof:name":"Hoye",
    "wof:placetype":"locality"
},
  "geometry": {"coordinates":[5.66475,58.98813000000001],"type":"Point"}
}