{
  "type": "Feature",
  "properties": {
    "gn:admin1_code":"6",
    "gn:admin2_code":"432.0",
    "gn:asciiname":"Finnstad",
    "gn:cc2":"NO",
    "gn:country_code":"NO",
    "gn:dem":655,
    "gn:feature_class":"P",
    "gn:feature_code":"PPL",
    "gn:name":"Finnstad",
    "gn:population":0,
    "gn:timezone":"Europe/Oslo",
    "iso:country":"NO",
    "name:und_x_variant":[
        "Finstad",
        "Finnstad"
    ],
    "wof:name":"Finnstad",
    "wof:placetype":"locality"
},
  "geometry": {"coordinates":[11.04614,62.10478000000001],"type":"Point"}
}