{
  "type": "Feature",
  "properties": {
    "gn:admin1_code":"21.0",
    "gn:admin2_code":"5049.0",
    "gn:asciiname":"Smavaeret",
    "gn:country_code":"NO",
    "gn:dem":-9999,
    "gn:feature_class":"P",
    "gn:feature_code":"PPL",
    "gn:name":"Sm\u00e5v\u00e6ret",
    "gn:population":0,
    "gn:timezone":"Europe/Oslo",
    "iso:country":"NO",
    "name:nor_x_preferred":[
        "Sm\u00e5v\u00e6ret"
    ],
    "wof:name":"Smavaeret",
    "wof:placetype":"locality"
},
  "geometry": {"coordinates":[10.55203,64.4383],"type":"Point"}
}