{
  "type": "Feature",
  "properties": {
    "gn:admin1_code":"21.0",
    "gn:admin2_code":"5051.0",
    "gn:asciiname":"Selliset",
    "gn:country_code":"NO",
    "gn:dem":-9999,
    "gn:feature_class":"P",
    "gn:feature_code":"PPL",
    "gn:name":"Selliset",
    "gn:population":0,
    "gn:timezone":"Europe/Oslo",
    "iso:country":"NO",
    "name:nor_x_preferred":[
        "Selliset"
    ],
    "wof:name":"Selliset",
    "wof:placetype":"locality"
},
  "geometry": {"coordinates":[11.81667,65.03333000000001],"type":"Point"}
}