{
  "type": "Feature",
  "properties": {
    "gn:admin1_code":"1.0",
    "gn:admin2_code":"216.0",
    "gn:asciiname":"Kirkeasen",
    "gn:country_code":"NO",
    "gn:dem":87,
    "gn:feature_class":"P",
    "gn:feature_code":"PPL",
    "gn:name":"Kirke\u00e5sen",
    "gn:population":0,
    "gn:timezone":"Europe/Oslo",
    "iso:country":"NO",
    "name:nor_x_preferred":[
        "Kirke\u00e5sen"
    ],
    "wof:name":"Kirkeasen",
    "wof:placetype":"neighbourhood"
},
  "geometry": {"coordinates":[10.69159,59.80915],"type":"Point"}
}