{
  "type": "Feature",
  "properties": {
    "gn:admin1_code":"21",
    "gn:admin2_code":"5013.0",
    "gn:asciiname":"Badstuvika",
    "gn:cc2":"NO",
    "gn:country_code":"NO",
    "gn:dem":-9999,
    "gn:feature_class":"P",
    "gn:feature_code":"PPL",
    "gn:name":"Badstuvika",
    "gn:population":0,
    "gn:timezone":"Europe/Oslo",
    "iso:country":"NO",
    "name:und_x_variant":[
        "Badstuvik",
        "Badstuvika"
    ],
    "wof:name":"Badstuvika",
    "wof:placetype":"locality"
},
  "geometry": {"coordinates":[9.15,63.53333000000001],"type":"Point"}
}