{
  "type": "Feature",
  "properties": {
    "gn:admin1_code":"5.0",
    "gn:admin2_code":"2030.0",
    "gn:asciiname":"Ytre Lid",
    "gn:country_code":"NO",
    "gn:dem":-9999,
    "gn:feature_class":"P",
    "gn:feature_code":"PPL",
    "gn:name":"Ytre Lid",
    "gn:population":0,
    "gn:timezone":"Europe/Oslo",
    "iso:country":"NO",
    "name:nor_x_preferred":[
        "Ytre Lid"
    ],
    "wof:name":"Ytre Lid",
    "wof:placetype":"locality"
},
  "geometry": {"coordinates":[30.10779,69.73999000000001],"type":"Point"}
}