{
  "type": "Feature",
  "properties": {
    "gn:country":"NO",
    "gn:fcode":"PPL",
    "gn:population":0,
    "iso:country":"NO",
    "name:ceb_x_preferred":[
        "St\u00e5rheim"
    ],
    "name:deu_x_preferred":[
        "St\u00e5rheim"
    ],
    "name:eng_x_preferred":[
        "St\u00e5rheim"
    ],
    "name:fra_x_preferred":[
        "St\u00e5rheim"
    ],
    "name:msa_x_preferred":[
        "St\u00e5rheim"
    ],
    "name:nld_x_preferred":[
        "St\u00e5rheim"
    ],
    "name:nob_x_preferred":[
        "St\u00e5rheim"
    ],
    "name:pol_x_preferred":[
        "St\u00e5rheim"
    ],
    "name:und_x_variant":[
        "Staarhejm"
    ],
    "qs_pg:aaroncc":"NO",
    "qs_pg:gn_country":"NO",
    "qs_pg:gn_fcode":"PPL",
    "qs_pg:gn_pop":0,
    "qs_pg:name":"St\u00e5rheim",
    "qs_pg:name_adm0":"Norge",
    "qs_pg:name_adm1":"Sogn og Fjordane Fylke",
    "qs_pg:photos_9k":1,
    "qs_pg:photos_9r":2,
    "qs_pg:photos_all":34,
    "qs_pg:photos_sr":0,
    "qs_pg:pop_sr":0,
    "qs_pg:qs_pg_placetype":"locality",
    "qs_pg:qs_pg_placetype_gp":"Town",
    "qs_pg:woe_adm0":23424910,
    "woe:adm0_id":23424910,
    "woe:name_adm0":"Norge",
    "woe:name_adm1":"Sogn og Fjordane Fylke",
    "woe:placetype":"Town",
    "wof:name":"St\u00e5rheim",
    "wof:placetype":"locality"
},
  "geometry": {"coordinates":[5.76667,61.91667],"type":"Point"}
}