{
  "type": "Feature",
  "properties": {
    "gn:admin1_code":"18.0",
    "gn:admin2_code":"1942.0",
    "gn:asciiname":"Bjerknes",
    "gn:country_code":"NO",
    "gn:dem":42,
    "gn:feature_class":"P",
    "gn:feature_code":"PPL",
    "gn:name":"Bjerknes",
    "gn:population":0,
    "gn:timezone":"Europe/Oslo",
    "iso:country":"NO",
    "name:ces_x_preferred":[
        "Bjerknes"
    ],
    "name:deu_x_preferred":[
        "Bjerknes"
    ],
    "name:fra_x_preferred":[
        "Bjerknes"
    ],
    "name:jpn_x_preferred":[
        "\u30d3\u30e4\u30fc\u30af\u30cd\u30b9"
    ],
    "name:nor_x_preferred":[
        "Bjerknes"
    ],
    "name:por_x_preferred":[
        "Bjerknes"
    ],
    "name:rus_x_preferred":[
        "\u0411\u044c\u0435\u0440\u043a\u043d\u0435\u0441"
    ],
    "wof:name":"Bjerknes",
    "wof:placetype":"locality"
},
  "geometry": {"coordinates":[21.03694,69.83083000000001],"type":"Point"}
}