{
  "type": "Feature",
  "properties": {
    "gn:admin1_code":"11.0",
    "gn:admin2_code":"538.0",
    "gn:asciiname":"Tranligrenda",
    "gn:country_code":"NO",
    "gn:dem":135,
    "gn:feature_class":"P",
    "gn:feature_code":"PPL",
    "gn:name":"Tranligrenda",
    "gn:population":0,
    "gn:timezone":"Europe/Oslo",
    "iso:country":"NO",
    "name:nor_x_preferred":[
        "Tranligrenda"
    ],
    "wof:name":"Tranligrenda",
    "wof:placetype":"locality"
},
  "geometry": {"coordinates":[10.13175,60.7922],"type":"Point"}
}