{
  "type": "Feature",
  "properties": {
    "gn:admin1_code":"9.0",
    "gn:admin2_code":"1849.0",
    "gn:asciiname":"Overeng",
    "gn:country_code":"NO",
    "gn:dem":40,
    "gn:feature_class":"P",
    "gn:feature_code":"PPL",
    "gn:name":"\u00d8vereng",
    "gn:population":0,
    "gn:timezone":"Europe/Oslo",
    "iso:country":"NO",
    "wof:name":"Overeng",
    "wof:placetype":"locality"
},
  "geometry": {"coordinates":[15.33417,68.02611],"type":"Point"}
}