{
  "type": "Feature",
  "properties": {
    "gn:admin1_code":"13",
    "gn:admin2_code":"111",
    "gn:asciiname":"Sand",
    "gn:country_code":"NO",
    "gn:dem":16,
    "gn:feature_class":"P",
    "gn:feature_code":"PPLL",
    "gn:name":"Sand",
    "gn:population":0,
    "gn:timezone":"Europe/Oslo",
    "iso:country":"NO",
    "name:nor_x_preferred":[
        "Sand"
    ],
    "wof:name":"Sand",
    "wof:placetype":"locality"
},
  "geometry": {"coordinates":[10.92835,59.08478],"type":"Point"}
}