{
  "type": "Feature",
  "properties": {
    "gn:admin1_code":"9",
    "gn:admin2_code":"1851.0",
    "gn:asciiname":"Hesten",
    "gn:country_code":"NO",
    "gn:dem":-9999,
    "gn:feature_class":"P",
    "gn:feature_code":"PPL",
    "gn:name":"Hesten",
    "gn:population":0,
    "gn:timezone":"Europe/Oslo",
    "iso:country":"NO",
    "wof:name":"Hesten",
    "wof:placetype":"locality"
},
  "geometry": {"coordinates":[15.71667,68.38333],"type":"Point"}
}