{
  "type": "Feature",
  "properties": {
    "gn:admin1_code":"21",
    "gn:admin2_code":"5021.0",
    "gn:asciiname":"Lia",
    "gn:cc2":"NO",
    "gn:country_code":"NO",
    "gn:dem":550,
    "gn:feature_class":"P",
    "gn:feature_code":"PPL",
    "gn:name":"Lia",
    "gn:population":0,
    "gn:timezone":"Europe/Oslo",
    "iso:country":"NO",
    "name:ces_x_preferred":[
        "Lia"
    ],
    "name:deu_x_preferred":[
        "Lia"
    ],
    "name:est_x_preferred":[
        "Lia"
    ],
    "name:ita_x_preferred":[
        "Lia"
    ],
    "name:nor_x_preferred":[
        "Lia"
    ],
    "name:ron_x_preferred":[
        "Lia"
    ],
    "name:swe_x_preferred":[
        "Lia"
    ],
    "name:und_x_variant":[
        "Lien"
    ],
    "wof:name":"Lia",
    "wof:placetype":"locality"
},
  "geometry": {"coordinates":[9.78333,62.63333000000001],"type":"Point"}
}