{
  "type": "Feature",
  "properties": {
    "gn:admin1_code":"17",
    "gn:admin2_code":"805",
    "gn:asciiname":"Lovsjo",
    "gn:country_code":"NO",
    "gn:dem":58,
    "gn:feature_class":"P",
    "gn:feature_code":"PPLL",
    "gn:name":"L\u00f8vsj\u00f8",
    "gn:population":0,
    "gn:timezone":"Europe/Oslo",
    "iso:country":"NO",
    "name:nor_x_preferred":[
        "L\u00f8vsj\u00f8"
    ],
    "wof:name":"Lovsjo",
    "wof:placetype":"neighbourhood"
},
  "geometry": {"coordinates":[9.68549,59.08738],"type":"Point"}
}