{
  "type": "Feature",
  "properties": {
    "gn:admin1_code":"14",
    "gn:admin2_code":"1146.0",
    "gn:asciiname":"Brattesto",
    "gn:country_code":"NO",
    "gn:dem":0,
    "gn:feature_class":"P",
    "gn:feature_code":"PPL",
    "gn:name":"Brattest\u00f8",
    "gn:population":0,
    "gn:timezone":"Europe/Oslo",
    "iso:country":"NO",
    "wof:name":"Brattesto",
    "wof:placetype":"locality"
},
  "geometry": {"coordinates":[5.55,59.45],"type":"Point"}
}