{
  "type": "Feature",
  "properties": {
    "gn:admin1_code":"21",
    "gn:admin2_code":"5011",
    "gn:asciiname":"Stoa",
    "gn:country_code":"NO",
    "gn:dem":33,
    "gn:feature_class":"P",
    "gn:feature_code":"PPLL",
    "gn:name":"St\u00f8a",
    "gn:population":0,
    "gn:timezone":"Europe/Oslo",
    "iso:country":"NO",
    "name:bel_x_preferred":[
        "\u0421\u0442\u043e\u044f"
    ],
    "name:bul_x_preferred":[
        "\u0421\u0442\u043e\u0430"
    ],
    "name:cat_x_preferred":[
        "Estoa"
    ],
    "name:dan_x_preferred":[
        "Stoa"
    ],
    "name:deu_x_preferred":[
        "Stoa"
    ],
    "name:est_x_preferred":[
        "Stoa"
    ],
    "name:eus_x_preferred":[
        "Estoa"
    ],
    "name:fin_x_preferred":[
        "Stoa"
    ],
    "name:fra_x_preferred":[
        "Stoa"
    ],
    "name:glg_x_preferred":[
        "Sto\u00e1"
    ],
    "name:heb_x_preferred":[
        "\u05e1\u05d8\u05d5\u05d0\u05d4"
    ],
    "name:hun_x_preferred":[
        "Sztoa"
    ],
    "name:hye_x_preferred":[
        "\u054d\u057f\u0578\u0561"
    ],
    "name:ita_x_preferred":[
        "Sto\u00e0"
    ],
    "name:kat_x_preferred":[
        "\u10e1\u10e2\u10dd\u10d0"
    ],
    "name:kor_x_preferred":[
        "\uc2a4\ud1a0\uc544"
    ],
    "name:lat_x_preferred":[
        "Stoa"
    ],
    "name:lav_x_preferred":[
        "Stoja"
    ],
    "name:mkd_x_preferred":[
        "\u0421\u0442\u043e\u0430"
    ],
    "name:nld_x_preferred":[
        "Stoa"
    ],
    "name:nor_x_preferred":[
        "St\u00f8a"
    ],
    "name:nor_x_variant":[
        "Stoa"
    ],
    "name:pol_x_preferred":[
        "Stoa"
    ],
    "name:por_x_preferred":[
        "Stoa"
    ],
    "name:ron_x_preferred":[
        "Stoa"
    ],
    "name:rus_x_preferred":[
        "\u0421\u0442\u043e\u0430"
    ],
    "name:slv_x_preferred":[
        "Stoa"
    ],
    "name:spa_x_preferred":[
        "Estoa"
    ],
    "name:srp_x_preferred":[
        "\u0421\u0442\u043e\u0430"
    ],
    "name:swe_x_preferred":[
        "Stoa"
    ],
    "name:tur_x_preferred":[
        "Stoa"
    ],
    "name:ukr_x_preferred":[
        "\u0421\u0442\u043e\u0430"
    ],
    "wof:name":"Stoa",
    "wof:placetype":"locality"
},
  "geometry": {"coordinates":[9.06769,63.28776],"type":"Point"}
}