{
  "type": "Feature",
  "properties": {
    "gn:admin1_code":"21",
    "gn:admin2_code":"5011",
    "gn:asciiname":"Stoa",
    "gn:country_code":"NO",
    "gn:dem":33,
    "gn:feature_class":"P",
    "gn:feature_code":"PPLL",
    "gn:name":"St\u00f8a",
    "gn:population":0,
    "gn:timezone":"Europe/Oslo",
    "iso:country":"NO",
    "name:nor_x_preferred":[
        "St\u00f8a"
    ],
    "wof:name":"Stoa",
    "wof:placetype":"locality"
},
  "geometry": {"coordinates":[9.06769,63.28776],"type":"Point"}
}