{
  "type": "Feature",
  "properties": {
    "gn:admin1_code":"9",
    "gn:admin2_code":"1848.0",
    "gn:asciiname":"Grottoy",
    "gn:cc2":"NO",
    "gn:country_code":"NO",
    "gn:dem":3,
    "gn:feature_class":"P",
    "gn:feature_code":"PPL",
    "gn:name":"Gr\u00f8tt\u00f8y",
    "gn:population":0,
    "gn:timezone":"Europe/Oslo",
    "iso:country":"NO",
    "name:und_x_variant":[
        "Gr\u00f6t\u00f6en",
        "Gr\u00f8t\u00f8y",
        "Gr\u00f8tt\u00f8y"
    ],
    "wof:name":"Grottoy",
    "wof:placetype":"locality"
},
  "geometry": {"coordinates":[14.76667,67.83333],"type":"Point"}
}