{
  "type": "Feature",
  "properties": {
    "gn:admin1_code":"17.0",
    "gn:admin2_code":"806.0",
    "gn:asciiname":"Stulen",
    "gn:country_code":"NO",
    "gn:dem":97,
    "gn:feature_class":"P",
    "gn:feature_code":"PPL",
    "gn:name":"Stulen",
    "gn:population":0,
    "gn:timezone":"Europe/Oslo",
    "iso:country":"NO",
    "name:nor_x_preferred":[
        "Stulen"
    ],
    "wof:name":"Stulen",
    "wof:placetype":"locality"
},
  "geometry": {"coordinates":[9.52817,59.30466],"type":"Point"}
}