{
  "type": "Feature",
  "properties": {
    "gn:admin1_code":"1.0",
    "gn:admin2_code":"211.0",
    "gn:asciiname":"Holen",
    "gn:country_code":"NO",
    "gn:dem":40,
    "gn:feature_class":"P",
    "gn:feature_code":"PPL",
    "gn:name":"Holen",
    "gn:population":0,
    "gn:timezone":"Europe/Oslo",
    "iso:country":"NO",
    "name:nor_x_preferred":[
        "Holen"
    ],
    "wof:name":"Holen",
    "wof:placetype":"locality"
},
  "geometry": {"coordinates":[10.659,59.58543],"type":"Point"}
}