{
  "type": "Feature",
  "properties": {
    "gn:country":"NO",
    "gn:fcode":"PPL",
    "gn:population":0,
    "iso:country":"NO",
    "name:dan_x_preferred":[
        "Eggedal"
    ],
    "name:eng_x_preferred":[
        "Eggedal"
    ],
    "name:fra_x_preferred":[
        "Eggedal"
    ],
    "name:jav_x_preferred":[
        "Eggedal"
    ],
    "name:msa_x_preferred":[
        "Eggedal"
    ],
    "name:nld_x_preferred":[
        "Eggedal"
    ],
    "name:nno_x_preferred":[
        "Eggedal"
    ],
    "name:nob_x_preferred":[
        "Eggedal"
    ],
    "qs_pg:aaroncc":"NO",
    "qs_pg:gn_country":"NO",
    "qs_pg:gn_fcode":"PPL",
    "qs_pg:gn_pop":0,
    "qs_pg:name":"Eggedal",
    "qs_pg:name_adm0":"Norge",
    "qs_pg:name_adm1":"Buskerud Fylke",
    "qs_pg:photos":114,
    "qs_pg:photos_1k":23,
    "qs_pg:photos_9k":1,
    "qs_pg:photos_9r":3,
    "qs_pg:photos_all":114,
    "qs_pg:photos_sr":3,
    "qs_pg:pop_sr":0,
    "qs_pg:qs_pg_placetype":"locality",
    "qs_pg:qs_pg_placetype_gp":"Town",
    "qs_pg:woe_adm0":23424910,
    "woe:adm0_id":23424910,
    "woe:name_adm0":"Norge",
    "woe:name_adm1":"Buskerud Fylke",
    "woe:placetype":"Town",
    "wof:name":"Eggedal",
    "wof:placetype":"locality"
},
  "geometry": {"coordinates":[9.36667,60.23333],"type":"Point"}
}