{
  "type": "Feature",
  "properties": {
    "gn:admin1_code":"4.0",
    "gn:admin2_code":"619.0",
    "gn:asciiname":"Jornbustolen",
    "gn:country_code":"NO",
    "gn:dem":890,
    "gn:feature_class":"P",
    "gn:feature_code":"PPL",
    "gn:name":"J\u00f8rnbust\u00f8len",
    "gn:population":0,
    "gn:timezone":"Europe/Oslo",
    "iso:country":"NO",
    "name:nor_x_preferred":[
        "J\u00f8rnbust\u00f8len"
    ],
    "wof:name":"Jornbustolen",
    "wof:placetype":"locality"
},
  "geometry": {"coordinates":[8.45011,60.71614],"type":"Point"}
}