{
  "type": "Feature",
  "properties": {
    "gn:admin1_code":"15",
    "gn:admin2_code":"1429.0",
    "gn:asciiname":"Furset",
    "gn:country_code":"NO",
    "gn:dem":86,
    "gn:feature_class":"P",
    "gn:feature_code":"PPL",
    "gn:name":"Furset",
    "gn:population":0,
    "gn:timezone":"Europe/Oslo",
    "iso:country":"NO",
    "wof:name":"Furset",
    "wof:placetype":"locality"
},
  "geometry": {"coordinates":[5.05,61.28333000000001],"type":"Point"}
}