{
  "type": "Feature",
  "properties": {
    "gn:admin1_code":"5.0",
    "gn:admin2_code":"2019.0",
    "gn:asciiname":"Stranda",
    "gn:cc2":"NO",
    "gn:country_code":"NO",
    "gn:dem":1,
    "gn:feature_class":"P",
    "gn:feature_code":"PPL",
    "gn:name":"Stranda",
    "gn:population":0,
    "gn:timezone":"Europe/Oslo",
    "iso:country":"NO",
    "name:und_x_variant":[
        "Porsangvik",
        "Stranden",
        "Stranda"
    ],
    "wof:name":"Stranda",
    "wof:placetype":"locality"
},
  "geometry": {"coordinates":[25.83333,70.86667],"type":"Point"}
}