{
  "type": "Feature",
  "properties": {
    "gn:gn_country":"NO",
    "gn:gn_fcode":"PPL",
    "gn:gn_pop":1220,
    "gn:population":1220,
    "iso:country":"NO",
    "name:eng_x_preferred":[
        "Bjerkvik"
    ],
    "name:fas_x_preferred":[
        "\u0628\u06cc\u0631\u06a9\u0648\u06cc\u06a9"
    ],
    "name:fra_x_preferred":[
        "Bjerkvik"
    ],
    "name:jav_x_preferred":[
        "Bjerkvik"
    ],
    "name:jpn_x_preferred":[
        "\u30d3\u30a7\u30eb\u30af\u30d3\u30af"
    ],
    "name:msa_x_preferred":[
        "Bjerkvik"
    ],
    "name:nld_x_preferred":[
        "Bjerkvik"
    ],
    "name:nno_x_preferred":[
        "Bjerkvik"
    ],
    "name:nob_x_preferred":[
        "Bjerkvik"
    ],
    "name:ron_x_preferred":[
        "Bjerkvik"
    ],
    "name:sme_x_preferred":[
        "R\u00e1hka"
    ],
    "name:swe_x_preferred":[
        "Bjerkvik"
    ],
    "name:unk_x_variant":[
        "Bjerkvik"
    ],
    "qs_pg:aaroncc":"NO",
    "qs_pg:gn_country":"NO",
    "qs_pg:gn_fcode":"PPL",
    "qs_pg:gn_pop":1220,
    "qs_pg:name":"Bj\u00f8rkvang",
    "qs_pg:photos_9r":0,
    "qs_pg:photos_sr":0,
    "qs_pg:pop_sr":3,
    "qs_pg:qs_pg_placetype":"locality",
    "wof:name":"Bj\u00f8rkvang",
    "wof:placetype":"locality",
    "wof:population":1220
},
  "geometry": {"coordinates":[17.51889,68.55972],"type":"Point"}
}