{
  "type": "Feature",
  "properties": {
    "gn:admin1_code":"18.0",
    "gn:admin2_code":"1938.0",
    "gn:asciiname":"Ornes",
    "gn:country_code":"NO",
    "gn:dem":11,
    "gn:feature_class":"P",
    "gn:feature_code":"PPL",
    "gn:name":"\u00d8rnes",
    "gn:population":0,
    "gn:timezone":"Europe/Oslo",
    "iso:country":"NO",
    "name:nor_x_preferred":[
        "\u00d8rnes"
    ],
    "wof:name":"Ornes",
    "wof:placetype":"locality"
},
  "geometry": {"coordinates":[20.23028,69.49389000000001],"type":"Point"}
}