{
  "type": "Feature",
  "properties": {
    "gn:admin1_code":"18.0",
    "gn:admin2_code":"1938.0",
    "gn:asciiname":"Ornes",
    "gn:country_code":"NO",
    "gn:dem":11,
    "gn:feature_class":"P",
    "gn:feature_code":"PPL",
    "gn:name":"\u00d8rnes",
    "gn:population":0,
    "gn:timezone":"Europe/Oslo",
    "iso:country":"NO",
    "name:cat_x_preferred":[
        "Ornes"
    ],
    "name:ceb_x_preferred":[
        "Ornes"
    ],
    "name:che_x_preferred":[
        "\u041e\u0440\u043d"
    ],
    "name:deu_x_preferred":[
        "Ornes"
    ],
    "name:epo_x_preferred":[
        "Ornes"
    ],
    "name:eus_x_preferred":[
        "Ornes"
    ],
    "name:fin_x_preferred":[
        "Ornes"
    ],
    "name:fra_x_preferred":[
        "Ornes"
    ],
    "name:hun_x_preferred":[
        "Ornes"
    ],
    "name:ita_x_preferred":[
        "Ornes"
    ],
    "name:kaz_x_preferred":[
        "\u041e\u0440\u043d"
    ],
    "name:lat_x_preferred":[
        "Ornes"
    ],
    "name:ltz_x_preferred":[
        "Ornes"
    ],
    "name:msa_x_preferred":[
        "Ornes"
    ],
    "name:nld_x_preferred":[
        "Ornes"
    ],
    "name:nor_x_preferred":[
        "\u00d8rnes"
    ],
    "name:oci_x_preferred":[
        "Ornes"
    ],
    "name:pms_x_preferred":[
        "Ornes"
    ],
    "name:pol_x_preferred":[
        "Ornes"
    ],
    "name:por_x_preferred":[
        "Ornes"
    ],
    "name:ron_x_preferred":[
        "Ornes"
    ],
    "name:slk_x_preferred":[
        "Ornes"
    ],
    "name:spa_x_preferred":[
        "Ornes"
    ],
    "name:swe_x_preferred":[
        "Ornes"
    ],
    "name:ukr_x_preferred":[
        "\u041e\u0440\u043d"
    ],
    "name:uzb_x_preferred":[
        "Ornes"
    ],
    "name:vie_x_preferred":[
        "Ornes"
    ],
    "name:vol_x_preferred":[
        "Ornes"
    ],
    "name:war_x_preferred":[
        "Ornes"
    ],
    "name:zho_x_preferred":[
        "\u5965\u5c14\u8bb7"
    ],
    "wof:name":"Ornes",
    "wof:placetype":"locality"
},
  "geometry": {"coordinates":[20.23028,69.49389000000001],"type":"Point"}
}