{
  "type": "Feature",
  "properties": {
    "gn:admin1_code":"8",
    "gn:admin2_code":"1516.0",
    "gn:asciiname":"Eiksund",
    "gn:cc2":"NO",
    "gn:country_code":"NO",
    "gn:dem":1,
    "gn:feature_class":"P",
    "gn:feature_code":"PPL",
    "gn:name":"Eiksund",
    "gn:population":0,
    "gn:timezone":"Europe/Oslo",
    "iso:country":"NO",
    "name:und_x_variant":[
        "Eksund",
        "Eiksund"
    ],
    "wof:name":"Eiksund",
    "wof:placetype":"locality"
},
  "geometry": {"coordinates":[5.93333,62.26667],"type":"Point"}
}