{
  "type": "Feature",
  "properties": {
    "gn:country":"NO",
    "gn:fcode":"PPL",
    "gn:population":0,
    "iso:country":"NO",
    "name:nno_x_preferred":[
        "Forus"
    ],
    "name:nor_x_preferred":[
        "Forus"
    ],
    "qs_pg:aaroncc":"NO",
    "qs_pg:gn_country":"NO",
    "qs_pg:gn_fcode":"PPL",
    "qs_pg:gn_pop":0,
    "qs_pg:name":"Forus",
    "qs_pg:name_adm0":"Norge",
    "qs_pg:name_adm1":"Rogaland Fylke",
    "qs_pg:photos":760,
    "qs_pg:photos_1k":154,
    "qs_pg:photos_9k":3,
    "qs_pg:photos_9r":6,
    "qs_pg:photos_all":760,
    "qs_pg:photos_sr":9,
    "qs_pg:pop_sr":0,
    "qs_pg:qs_pg_placetype":"locality",
    "qs_pg:qs_pg_placetype_gp":"Town",
    "qs_pg:woe_adm0":23424910,
    "woe:adm0_id":23424910,
    "woe:name_adm0":"Norge",
    "woe:name_adm1":"Rogaland Fylke",
    "woe:placetype":"Town",
    "wof:name":"Forus",
    "wof:placetype":"neighbourhood"
},
  "geometry": {"coordinates":[5.73333,58.88333],"type":"Point"}
}