{
  "type": "Feature",
  "properties": {
    "gn:admin1_code":"2",
    "gn:admin2_code":"914",
    "gn:asciiname":"Sandvika",
    "gn:country_code":"NO",
    "gn:dem":11,
    "gn:feature_class":"P",
    "gn:feature_code":"PPLL",
    "gn:name":"Sandvika",
    "gn:population":0,
    "gn:timezone":"Europe/Oslo",
    "iso:country":"NO",
    "name:nor_x_preferred":[
        "Sandvika"
    ],
    "wof:name":"Sandvika",
    "wof:placetype":"locality"
},
  "geometry": {"coordinates":[9.00122,58.57003],"type":"Point"}
}