{
  "type": "Feature",
  "properties": {
    "gn:admin1_code":"2",
    "gn:admin2_code":"914",
    "gn:asciiname":"Sandvika",
    "gn:country_code":"NO",
    "gn:dem":11,
    "gn:feature_class":"P",
    "gn:feature_code":"PPLL",
    "gn:name":"Sandvika",
    "gn:population":0,
    "gn:timezone":"Europe/Oslo",
    "iso:country":"NO",
    "name:ara_x_preferred":[
        "\u0633\u0627\u0646\u062f\u0641\u064a\u0643\u0627"
    ],
    "name:bul_x_preferred":[
        "\u0421\u0430\u043d\u0432\u0438\u043a\u0430"
    ],
    "name:ceb_x_preferred":[
        "Sandvika"
    ],
    "name:ces_x_preferred":[
        "Sandvika"
    ],
    "name:dan_x_preferred":[
        "Sandvika"
    ],
    "name:deu_x_preferred":[
        "Sandvika"
    ],
    "name:fas_x_preferred":[
        "\u0633\u0646\u062f\u0648\u06cc\u06a9\u0627"
    ],
    "name:fin_x_preferred":[
        "Sandvika"
    ],
    "name:fra_x_preferred":[
        "Sandvika"
    ],
    "name:ile_x_preferred":[
        "Sandvika"
    ],
    "name:ita_x_preferred":[
        "Sandvika"
    ],
    "name:nld_x_preferred":[
        "Sandvika"
    ],
    "name:nno_x_preferred":[
        "Sandvika"
    ],
    "name:nor_x_preferred":[
        "Sandvika"
    ],
    "name:pol_x_preferred":[
        "Sandvika"
    ],
    "name:rus_x_preferred":[
        "\u0421\u0430\u043d\u043d\u0432\u0438\u043a\u0430"
    ],
    "name:spa_x_preferred":[
        "Sandvika"
    ],
    "name:sqi_x_preferred":[
        "Sandvika"
    ],
    "name:srp_x_preferred":[
        "\u0421\u0430\u043d\u0434\u0432\u0438\u043a\u0430"
    ],
    "name:swe_x_preferred":[
        "Sandvika"
    ],
    "name:zho_x_preferred":[
        "\u6851\u7dad\u5361"
    ],
    "wof:name":"Sandvika",
    "wof:placetype":"locality"
},
  "geometry": {"coordinates":[9.00122,58.57003],"type":"Point"}
}