{
  "type": "Feature",
  "properties": {
    "gn:country":"NO",
    "gn:fcode":"PPL",
    "gn:population":715,
    "iso:country":"NO",
    "name:bul_x_preferred":[
        "\u0422\u0439\u0441\u0435\u0434\u0430\u043b"
    ],
    "name:ceb_x_preferred":[
        "Tyssedal"
    ],
    "name:dan_x_preferred":[
        "Tyssedal"
    ],
    "name:deu_x_preferred":[
        "Tyssedal"
    ],
    "name:eng_x_preferred":[
        "Tyssedal"
    ],
    "name:fra_x_preferred":[
        "Tyssedal"
    ],
    "name:jav_x_preferred":[
        "Tyssedal"
    ],
    "name:msa_x_preferred":[
        "Tyssedal"
    ],
    "name:nld_x_preferred":[
        "Tyssedal"
    ],
    "name:nno_x_preferred":[
        "Tyssedal"
    ],
    "name:nob_x_preferred":[
        "Tyssedal"
    ],
    "name:ron_x_preferred":[
        "Tyssedal"
    ],
    "name:rus_x_preferred":[
        "\u0422\u044e\u0441\u0441\u0435\u0434\u0430\u043b\u044c"
    ],
    "name:spa_x_preferred":[
        "Tyssedal"
    ],
    "name:swe_x_preferred":[
        "Tyssedal"
    ],
    "name:und_x_variant":[
        "Tysso"
    ],
    "qs_pg:aaroncc":"NO",
    "qs_pg:gn_country":"NO",
    "qs_pg:gn_fcode":"PPL",
    "qs_pg:gn_pop":715,
    "qs_pg:name":"Tyssedal",
    "qs_pg:name_adm0":"Norge",
    "qs_pg:name_adm1":"Hordaland Fylke",
    "qs_pg:photos":163,
    "qs_pg:photos_1k":33,
    "qs_pg:photos_9k":1,
    "qs_pg:photos_9r":4,
    "qs_pg:photos_all":163,
    "qs_pg:photos_sr":4,
    "qs_pg:pop_sr":2,
    "qs_pg:qs_pg_placetype":"locality",
    "qs_pg:qs_pg_placetype_gp":"Town",
    "qs_pg:woe_adm0":23424910,
    "woe:adm0_id":23424910,
    "woe:name_adm0":"Norge",
    "woe:name_adm1":"Hordaland Fylke",
    "woe:placetype":"Town",
    "wof:name":"Tyssedal",
    "wof:placetype":"locality",
    "wof:population":715
},
  "geometry": {"coordinates":[6.56667,60.11667],"type":"Point"}
}