{
  "type": "Feature",
  "properties": {
    "gn:admin1_code":"19.0",
    "gn:admin2_code":"1003.0",
    "gn:asciiname":"Rodland ostre",
    "gn:country_code":"NO",
    "gn:dem":21,
    "gn:feature_class":"P",
    "gn:feature_code":"PPL",
    "gn:name":"R\u00f8dland \u00f8stre",
    "gn:population":0,
    "gn:timezone":"Europe/Oslo",
    "iso:country":"NO",
    "name:nor_x_preferred":[
        "R\u00f8dland \u00f8stre"
    ],
    "wof:name":"Rodland ostre",
    "wof:placetype":"locality"
},
  "geometry": {"coordinates":[6.70624,58.08584000000001],"type":"Point"}
}