{
  "type": "Feature",
  "properties": {
    "gn:admin1_code":"1.0",
    "gn:admin2_code":"226.0",
    "gn:asciiname":"Sandum",
    "gn:country_code":"NO",
    "gn:dem":207,
    "gn:feature_class":"P",
    "gn:feature_code":"PPL",
    "gn:name":"Sandum",
    "gn:population":0,
    "gn:timezone":"Europe/Oslo",
    "iso:country":"NO",
    "name:jav_x_preferred":[
        "Sandum"
    ],
    "name:msa_x_preferred":[
        "Sandum"
    ],
    "name:nor_x_preferred":[
        "Sandum"
    ],
    "wof:name":"Sandum",
    "wof:placetype":"locality"
},
  "geometry": {"coordinates":[11.37998,59.96426],"type":"Point"}
}