{
  "type": "Feature",
  "properties": {
    "iso:country":"NO",
    "name:eng_x_preferred":[
        "Ronglan"
    ],
    "name:fra_x_preferred":[
        "Ronglan"
    ],
    "name:jav_x_preferred":[
        "Ronglan"
    ],
    "name:msa_x_preferred":[
        "Ronglan"
    ],
    "name:nld_x_preferred":[
        "Ronglan"
    ],
    "name:nno_x_preferred":[
        "Ronglan"
    ],
    "name:nob_x_preferred":[
        "Ronglan"
    ],
    "qs_pg:aaroncc":"NO",
    "qs_pg:name":"Ronglan",
    "qs_pg:name_adm0":"Norge",
    "qs_pg:name_adm1":"Nord-Tr\u00f8ndelag Fylke",
    "qs_pg:photos":108,
    "qs_pg:photos_1k":22,
    "qs_pg:photos_9k":1,
    "qs_pg:photos_9r":3,
    "qs_pg:photos_all":108,
    "qs_pg:photos_sr":3,
    "qs_pg:pop_sr":0,
    "qs_pg:qs_pg_placetype":"locality",
    "qs_pg:qs_pg_placetype_gp":"Town",
    "qs_pg:woe_adm0":23424910,
    "woe:adm0_id":23424910,
    "woe:name_adm0":"Norge",
    "woe:name_adm1":"Nord-Tr\u00f8ndelag Fylke",
    "woe:placetype":"Town",
    "wof:name":"Ronglan",
    "wof:placetype":"locality"
},
  "geometry": {"coordinates":[11.1131,63.691677],"type":"Point"}
}