{
  "type": "Feature",
  "properties": {
    "iso:country":"NO",
    "name:nor_x_preferred":[
        "Mulen"
    ],
    "qs:gn_adm0_cc":"NO",
    "qs:gn_local":3161732,
    "qs:gn_nam_loc":"Bergen, Bergen, Hordaland Fylke, NO",
    "qs:gn_namadm1":"07",
    "qs:local_max":5825,
    "qs:local_sum":38813,
    "qs:localhoods":24,
    "qs:name":"Mulen",
    "qs:name_adm0":"Norge",
    "qs:name_adm1":"Hordaland Fylke",
    "qs:name_adm2":"Bergen Kommune",
    "qs:name_local":"Bergen",
    "qs:photo_max":64,
    "qs:photo_sum":338,
    "qs:placetype":"Suburb",
    "qs:quad_count":33,
    "qs:woe_adm0":23424910,
    "qs:woe_adm1":2346390,
    "qs:woe_adm2":12592658,
    "qs:woe_lau":0,
    "qs:woe_local":857105,
    "qs:woe_ver":"7.10.0",
    "wof:lang":[
        "nor"
    ],
    "wof:name":"Mulen",
    "wof:placetype":"neighbourhood"
},
  "geometry": {"coordinates":[5.329511,60.405369],"type":"Point"}
}