{
  "type": "Feature",
  "properties": {
    "gn:admin1_code":"7",
    "gn:admin2_code":"1263",
    "gn:asciiname":"Vikanes",
    "gn:country_code":"NO",
    "gn:dem":-9999,
    "gn:feature_class":"P",
    "gn:feature_code":"PPL",
    "gn:name":"Vikanes",
    "gn:population":0,
    "gn:timezone":"Europe/Oslo",
    "iso:country":"NO",
    "name:nor_x_preferred":[
        "Vikanes"
    ],
    "wof:name":"Vikanes",
    "wof:placetype":"locality"
},
  "geometry": {"coordinates":[5.58687,60.69851],"type":"Point"}
}