{
  "type": "Feature",
  "properties": {
    "gn:admin1_code":"14",
    "gn:admin2_code":"1146",
    "gn:asciiname":"Hindaravag",
    "gn:country_code":"NO",
    "gn:dem":15,
    "gn:feature_class":"P",
    "gn:feature_code":"PPLL",
    "gn:name":"Hindar\u00e5v\u00e5g",
    "gn:population":0,
    "gn:timezone":"Europe/Oslo",
    "iso:country":"NO",
    "name:nor_x_preferred":[
        "Hindar\u00e5v\u00e5g"
    ],
    "wof:name":"Hindaravag",
    "wof:placetype":"locality"
},
  "geometry": {"coordinates":[5.79978,59.34799],"type":"Point"}
}