{
  "type": "Feature",
  "properties": {
    "gn:country":"NO",
    "iso:country":"NO",
    "qs_pg:aaroncc":"NO",
    "qs_pg:gn_country":"NO",
    "qs_pg:name":"Fagerholt",
    "qs_pg:name_adm0":"Norge",
    "qs_pg:name_adm1":"Vest-Agder Fylke",
    "qs_pg:photos":21,
    "qs_pg:photos_1k":4,
    "qs_pg:photos_9k":1,
    "qs_pg:photos_9r":1,
    "qs_pg:photos_all":21,
    "qs_pg:photos_sr":1,
    "qs_pg:pop_sr":0,
    "qs_pg:qs_pg_placetype":"locality",
    "qs_pg:qs_pg_placetype_gp":"Town",
    "qs_pg:woe_adm0":23424910,
    "woe:adm0_id":23424910,
    "woe:name_adm0":"Norge",
    "woe:name_adm1":"Vest-Agder Fylke",
    "woe:placetype":"Town",
    "wof:name":"Fagerholt",
    "wof:placetype":"neighbourhood"
},
  "geometry": {"coordinates":[8.042163,58.167133],"type":"Point"}
}