{
  "type": "Feature",
  "properties": {
    "gn:admin1_code":"18",
    "gn:admin2_code":"1929.0",
    "gn:asciiname":"Haverjorda",
    "gn:cc2":"NO",
    "gn:country_code":"NO",
    "gn:dem":307,
    "gn:feature_class":"P",
    "gn:feature_code":"PPL",
    "gn:name":"H\u00e5verjorda",
    "gn:population":0,
    "gn:timezone":"Europe/Oslo",
    "iso:country":"NO",
    "name:und_x_variant":[
        "Haaverjorda",
        "H\u00e5verjorda"
    ],
    "wof:name":"Haverjorda",
    "wof:placetype":"locality"
},
  "geometry": {"coordinates":[17.43333,69.38333],"type":"Point"}
}