{
  "type": "Feature",
  "properties": {
    "gn:admin1_code":"17",
    "gn:admin2_code":"833.0",
    "gn:asciiname":"Bandaksli",
    "gn:country_code":"NO",
    "gn:dem":92,
    "gn:feature_class":"P",
    "gn:feature_code":"PPL",
    "gn:name":"Bandaksli",
    "gn:population":0,
    "gn:timezone":"Europe/Oslo",
    "iso:country":"NO",
    "wof:name":"Bandaksli",
    "wof:placetype":"locality"
},
  "geometry": {"coordinates":[8.18842,59.40776],"type":"Point"}
}