{
  "type": "Feature",
  "properties": {
    "gn:admin1_code":"1.0",
    "gn:admin2_code":"215.0",
    "gn:asciiname":"Ostskogen",
    "gn:country_code":"NO",
    "gn:dem":89,
    "gn:feature_class":"P",
    "gn:feature_code":"PPL",
    "gn:name":"\u00d8stskogen",
    "gn:population":0,
    "gn:timezone":"Europe/Oslo",
    "iso:country":"NO",
    "name:nor_x_preferred":[
        "\u00d8stskogen"
    ],
    "wof:name":"Ostskogen",
    "wof:placetype":"locality"
},
  "geometry": {"coordinates":[10.62057,59.7198],"type":"Point"}
}