{
  "type": "Feature",
  "properties": {
    "gn:admin1_code":"21.0",
    "gn:admin2_code":"5054.0",
    "gn:asciiname":"Sollia",
    "gn:cc2":"NO",
    "gn:country_code":"NO",
    "gn:dem":280,
    "gn:feature_class":"P",
    "gn:feature_code":"PPL",
    "gn:name":"Sollia",
    "gn:population":0,
    "gn:timezone":"Europe/Oslo",
    "iso:country":"NO",
    "name:und_x_variant":[
        "Sollien",
        "Solli",
        "Sollia"
    ],
    "wof:name":"Sollia",
    "wof:placetype":"locality"
},
  "geometry": {"coordinates":[10.63333,63.76667],"type":"Point"}
}