{
  "type": "Feature",
  "properties": {
    "gn:country":"NO",
    "gn:fcode":"PPLA2",
    "gn:population":694,
    "iso:country":"NO",
    "name:ast_x_preferred":[
        "Selje"
    ],
    "name:bpy_x_preferred":[
        "\u09b8\u09c7\u09b2\u099c\u09c7"
    ],
    "name:cat_x_preferred":[
        "Selje"
    ],
    "name:ceb_x_preferred":[
        "Selje"
    ],
    "name:dan_x_preferred":[
        "Selje"
    ],
    "name:deu_x_preferred":[
        "Selje"
    ],
    "name:eng_x_preferred":[
        "Selje"
    ],
    "name:epo_x_preferred":[
        "Selje"
    ],
    "name:eus_x_preferred":[
        "Selje"
    ],
    "name:fin_x_preferred":[
        "Selje"
    ],
    "name:fra_x_preferred":[
        "Selje"
    ],
    "name:hun_x_preferred":[
        "Selje"
    ],
    "name:ita_x_preferred":[
        "Selje"
    ],
    "name:jpn_x_preferred":[
        "\u30bb\u30eb\u30b8\u30a7"
    ],
    "name:lat_x_preferred":[
        "Selje"
    ],
    "name:lim_x_preferred":[
        "Selje"
    ],
    "name:msa_x_preferred":[
        "Selje"
    ],
    "name:nan_x_preferred":[
        "Selje"
    ],
    "name:nds_x_preferred":[
        "Kommun Selje"
    ],
    "name:nld_x_preferred":[
        "Selje"
    ],
    "name:nno_x_preferred":[
        "Selje"
    ],
    "name:nob_x_preferred":[
        "Selje"
    ],
    "name:pol_x_preferred":[
        "Selje"
    ],
    "name:por_x_preferred":[
        "Selje i Nordfjord"
    ],
    "name:ron_x_preferred":[
        "Selje"
    ],
    "name:rus_x_preferred":[
        "\u0421\u0435\u043b\u044c\u0435"
    ],
    "name:slv_x_preferred":[
        "Selje"
    ],
    "name:sme_x_preferred":[
        "Selje"
    ],
    "name:spa_x_preferred":[
        "Selje"
    ],
    "name:sqi_x_preferred":[
        "Selje"
    ],
    "name:swa_x_preferred":[
        "Selje"
    ],
    "name:swe_x_preferred":[
        "Selje"
    ],
    "name:war_x_preferred":[
        "Selje"
    ],
    "name:zho_x_preferred":[
        "\u585e\u5c14\u8036"
    ],
    "qs_pg:aaroncc":"NO",
    "qs_pg:gn_country":"NO",
    "qs_pg:gn_fcode":"PPLA2",
    "qs_pg:gn_pop":694,
    "qs_pg:name":"Selje",
    "qs_pg:photos_9r":0,
    "qs_pg:photos_sr":0,
    "qs_pg:pop_sr":2,
    "qs_pg:qs_pg_placetype":"locality",
    "wof:name":"Selje",
    "wof:placetype":"locality",
    "wof:population":694
},
  "geometry": {"coordinates":[5.35096,62.04591],"type":"Point"}
}