{
  "type": "Feature",
  "properties": {
    "gn:admin1_code":"14.0",
    "gn:admin2_code":"1122.0",
    "gn:asciiname":"Ovstabostolen",
    "gn:country_code":"NO",
    "gn:dem":575,
    "gn:feature_class":"P",
    "gn:feature_code":"PPL",
    "gn:name":"\u00d8vstab\u00f8st\u00f8len",
    "gn:population":0,
    "gn:timezone":"Europe/Oslo",
    "iso:country":"NO",
    "wof:name":"Ovstabostolen",
    "wof:placetype":"locality"
},
  "geometry": {"coordinates":[6.56667,58.86666999999999],"type":"Point"}
}