{
  "type": "Feature",
  "properties": {
    "gn:admin1_code":"7",
    "gn:admin2_code":"1238.0",
    "gn:asciiname":"Innstranda",
    "gn:country_code":"NO",
    "gn:dem":-9999,
    "gn:feature_class":"P",
    "gn:feature_code":"PPL",
    "gn:name":"Innstranda",
    "gn:population":0,
    "gn:timezone":"Europe/Oslo",
    "iso:country":"NO",
    "wof:name":"Innstranda",
    "wof:placetype":"locality"
},
  "geometry": {"coordinates":[6.11004,60.25453],"type":"Point"}
}