{
  "type": "Feature",
  "properties": {
    "gn:admin1_code":"7",
    "gn:admin2_code":"1201",
    "gn:asciiname":"Starefossen",
    "gn:country_code":"NO",
    "gn:dem":126,
    "gn:feature_class":"P",
    "gn:feature_code":"PPLL",
    "gn:name":"Starefossen",
    "gn:population":0,
    "gn:timezone":"Europe/Oslo",
    "iso:country":"NO",
    "name:nor_x_preferred":[
        "Starefossen"
    ],
    "wof:name":"Starefossen",
    "wof:placetype":"neighbourhood"
},
  "geometry": {"coordinates":[5.35434,60.38841],"type":"Point"}
}