{
  "type": "Feature",
  "properties": {
    "gn:country":"NO",
    "gn:fcode":"PPL",
    "gn:population":0,
    "iso:country":"NO",
    "name:und_x_variant":[
        "Hernsj\u00f6"
    ],
    "qs_pg:aaroncc":"NO",
    "qs_pg:gn_country":"NO",
    "qs_pg:gn_fcode":"PPL",
    "qs_pg:gn_pop":0,
    "qs_pg:name":"Hornsj\u00f8en",
    "qs_pg:name_adm0":"Norge",
    "qs_pg:name_adm1":"Oppland Fylke",
    "qs_pg:photos":16,
    "qs_pg:photos_1k":3,
    "qs_pg:photos_9k":1,
    "qs_pg:photos_9r":1,
    "qs_pg:photos_all":16,
    "qs_pg:photos_sr":1,
    "qs_pg:pop_sr":0,
    "qs_pg:qs_pg_placetype":"locality",
    "qs_pg:qs_pg_placetype_gp":"Town",
    "qs_pg:woe_adm0":23424910,
    "woe:adm0_id":23424910,
    "woe:name_adm0":"Norge",
    "woe:name_adm1":"Oppland Fylke",
    "woe:placetype":"Town",
    "wof:name":"Hornsj\u00f8en",
    "wof:placetype":"locality"
},
  "geometry": {"coordinates":[10.73333,61.25],"type":"Point"}
}