{
  "type": "Feature",
  "properties": {
    "gn:admin1_code":"15",
    "gn:admin2_code":"1401.0",
    "gn:asciiname":"Klauvene",
    "gn:country_code":"NO",
    "gn:dem":1,
    "gn:feature_class":"P",
    "gn:feature_code":"PPL",
    "gn:name":"Klauvene",
    "gn:population":0,
    "gn:timezone":"Europe/Oslo",
    "iso:country":"NO",
    "wof:name":"Klauvene",
    "wof:placetype":"locality"
},
  "geometry": {"coordinates":[5.16667,61.63333000000001],"type":"Point"}
}