{
  "type": "Feature",
  "properties": {
    "gn:admin1_code":"9.0",
    "gn:admin2_code":"1865.0",
    "gn:asciiname":"Vestpollen",
    "gn:country_code":"NO",
    "gn:dem":-9999,
    "gn:feature_class":"P",
    "gn:feature_code":"PPL",
    "gn:name":"Vestpollen",
    "gn:population":0,
    "gn:timezone":"Europe/Oslo",
    "iso:country":"NO",
    "wof:name":"Vestpollen",
    "wof:placetype":"locality"
},
  "geometry": {"coordinates":[14.69709,68.32876999999999],"type":"Point"}
}