{
  "type": "Feature",
  "properties": {
    "gn:admin1_code":"7.0",
    "gn:admin2_code":"1260.0",
    "gn:asciiname":"Vallersneset",
    "gn:cc2":"NO",
    "gn:country_code":"NO",
    "gn:dem":-9999,
    "gn:feature_class":"P",
    "gn:feature_code":"PPL",
    "gn:name":"Vallersneset",
    "gn:population":0,
    "gn:timezone":"Europe/Oslo",
    "iso:country":"NO",
    "name:und_x_variant":[
        "Vallersnes",
        "Vallersneset"
    ],
    "wof:name":"Vallersneset",
    "wof:placetype":"locality"
},
  "geometry": {"coordinates":[5.0366,60.71046],"type":"Point"}
}