{
  "type": "Feature",
  "properties": {
    "gn:admin1_code":"18",
    "gn:admin2_code":"1926.0",
    "gn:asciiname":"Lille Vinje",
    "gn:country_code":"NO",
    "gn:dem":183,
    "gn:feature_class":"P",
    "gn:feature_code":"PPL",
    "gn:name":"Lille Vinje",
    "gn:population":0,
    "gn:timezone":"Europe/Oslo",
    "iso:country":"NO",
    "wof:name":"Lille Vinje",
    "wof:placetype":"locality"
},
  "geometry": {"coordinates":[17.38332999999999,69.01666999999999],"type":"Point"}
}