{
  "type": "Feature",
  "properties": {
    "gn:admin1_code":"18",
    "gn:admin2_code":"1911.0",
    "gn:asciiname":"Berg",
    "gn:country_code":"NO",
    "gn:dem":160,
    "gn:feature_class":"P",
    "gn:feature_code":"PPL",
    "gn:name":"Berg",
    "gn:population":0,
    "gn:timezone":"Europe/Oslo",
    "iso:country":"NO",
    "wof:name":"Berg",
    "wof:placetype":"locality"
},
  "geometry": {"coordinates":[16.16667,68.78333000000001],"type":"Point"}
}