{
  "type": "Feature",
  "properties": {
    "gn:admin1_code":"4.0",
    "gn:admin2_code":"612.0",
    "gn:asciiname":"Gomnes",
    "gn:country_code":"NO",
    "gn:dem":140,
    "gn:feature_class":"P",
    "gn:feature_code":"PPL",
    "gn:name":"Gomnes",
    "gn:population":0,
    "gn:timezone":"Europe/Oslo",
    "iso:country":"NO",
    "name:jav_x_preferred":[
        "Gomnes"
    ],
    "name:msa_x_preferred":[
        "Gomnes"
    ],
    "name:nld_x_preferred":[
        "Gomnes"
    ],
    "name:nno_x_preferred":[
        "Gomnes"
    ],
    "name:nor_x_preferred":[
        "Gomnes"
    ],
    "name:ron_x_preferred":[
        "Gomnes"
    ],
    "name:spa_x_preferred":[
        "Gomnes"
    ],
    "wof:name":"Gomnes",
    "wof:placetype":"locality"
},
  "geometry": {"coordinates":[10.17432,60.07823000000001],"type":"Point"}
}