{
  "type": "Feature",
  "properties": {
    "gn:admin1_code":"1.0",
    "gn:admin2_code":"238.0",
    "gn:asciiname":"Valaugmoen",
    "gn:country_code":"NO",
    "gn:dem":190,
    "gn:feature_class":"P",
    "gn:feature_code":"PPL",
    "gn:name":"V\u00e5laugmoen",
    "gn:population":0,
    "gn:timezone":"Europe/Oslo",
    "iso:country":"NO",
    "name:nor_x_preferred":[
        "V\u00e5laugmoen"
    ],
    "name:nor_x_variant":[
        "Vaalaugmoen"
    ],
    "wof:name":"Valaugmoen",
    "wof:placetype":"locality"
},
  "geometry": {"coordinates":[10.98235,60.26542],"type":"Point"}
}