{
  "type": "Feature",
  "properties": {
    "gn:country":"NO",
    "gn:fcode":"PPL",
    "gn:population":0,
    "iso:country":"NO",
    "name:eng_x_preferred":[
        "Salhus"
    ],
    "name:fra_x_preferred":[
        "Salhus"
    ],
    "name:jav_x_preferred":[
        "Salhus"
    ],
    "name:msa_x_preferred":[
        "Salhus"
    ],
    "name:nld_x_preferred":[
        "Salhus"
    ],
    "name:nno_x_preferred":[
        "Salhus"
    ],
    "name:nob_x_preferred":[
        "Salhus"
    ],
    "qs_pg:aaroncc":"NO",
    "qs_pg:gn_country":"NO",
    "qs_pg:gn_fcode":"PPL",
    "qs_pg:gn_pop":0,
    "qs_pg:name":"Salhus",
    "qs_pg:name_adm0":"Norge",
    "qs_pg:name_adm1":"Hordaland Fylke",
    "qs_pg:photos":71,
    "qs_pg:photos_1k":14,
    "qs_pg:photos_9k":1,
    "qs_pg:photos_9r":2,
    "qs_pg:photos_all":71,
    "qs_pg:photos_sr":2,
    "qs_pg:pop_sr":0,
    "qs_pg:qs_pg_placetype":"locality",
    "qs_pg:qs_pg_placetype_gp":"Town",
    "qs_pg:woe_adm0":23424910,
    "woe:adm0_id":23424910,
    "woe:name_adm0":"Norge",
    "woe:name_adm1":"Hordaland Fylke",
    "woe:placetype":"Town",
    "wof:name":"Salhus",
    "wof:placetype":"neighbourhood"
},
  "geometry": {"coordinates":[5.26944,60.50694],"type":"Point"}
}