{
  "type": "Feature",
  "properties": {
    "gn:admin1_code":"18",
    "gn:admin2_code":"1902.0",
    "gn:asciiname":"Kraksletta",
    "gn:country_code":"NO",
    "gn:dem":-9999,
    "gn:feature_class":"P",
    "gn:feature_code":"PPL",
    "gn:name":"Kraksletta",
    "gn:population":0,
    "gn:timezone":"Europe/Oslo",
    "iso:country":"NO",
    "wof:name":"Kraksletta",
    "wof:placetype":"locality"
},
  "geometry": {"coordinates":[18.88333,69.51666999999999],"type":"Point"}
}