{
  "type": "Feature",
  "properties": {
    "gn:admin1_code":"9",
    "gn:admin2_code":"1834",
    "gn:asciiname":"Strand",
    "gn:country_code":"NO",
    "gn:dem":1,
    "gn:feature_class":"P",
    "gn:feature_code":"PPLL",
    "gn:name":"Strand",
    "gn:population":0,
    "gn:timezone":"Europe/Oslo",
    "iso:country":"NO",
    "name:nor_x_preferred":[
        "Strand"
    ],
    "wof:name":"Strand",
    "wof:placetype":"locality"
},
  "geometry": {"coordinates":[12.36013,66.37007],"type":"Point"}
}