{
  "type": "Feature",
  "properties": {
    "gn:admin1_code":"4.0",
    "gn:admin2_code":"621.0",
    "gn:asciiname":"Oya",
    "gn:country_code":"NO",
    "gn:dem":280,
    "gn:feature_class":"P",
    "gn:feature_code":"PPL",
    "gn:name":"\u00d8ya",
    "gn:population":0,
    "gn:timezone":"Europe/Oslo",
    "iso:country":"NO",
    "wof:name":"Oya",
    "wof:placetype":"locality"
},
  "geometry": {"coordinates":[9.45,60.13333000000001],"type":"Point"}
}