{
  "type": "Feature",
  "properties": {
    "gn:admin1_code":"9.0",
    "gn:admin2_code":"1834.0",
    "gn:asciiname":"Tonnes",
    "gn:cc2":"NO",
    "gn:country_code":"NO",
    "gn:dem":20,
    "gn:feature_class":"P",
    "gn:feature_code":"PPL",
    "gn:name":"Tonnes",
    "gn:population":0,
    "gn:timezone":"Europe/Oslo",
    "iso:country":"NO",
    "name:fra_x_preferred":[
        "Tonnes"
    ],
    "name:jav_x_preferred":[
        "Tonnes"
    ],
    "name:msa_x_preferred":[
        "Tonnes"
    ],
    "name:nno_x_preferred":[
        "Tonnes"
    ],
    "name:nor_x_preferred":[
        "Tonnes"
    ],
    "name:und_x_variant":[
        "Tonnes i Helgeland"
    ],
    "wof:name":"Tonnes",
    "wof:placetype":"locality"
},
  "geometry": {"coordinates":[13.01438,66.51399000000001],"type":"Point"}
}