{
  "type": "Feature",
  "properties": {
    "gn:admin1_code":"1.0",
    "gn:admin2_code":"227.0",
    "gn:asciiname":"Tofsrud",
    "gn:country_code":"NO",
    "gn:dem":136,
    "gn:feature_class":"P",
    "gn:feature_code":"PPL",
    "gn:name":"Tofsrud",
    "gn:population":0,
    "gn:timezone":"Europe/Oslo",
    "iso:country":"NO",
    "wof:name":"Tofsrud",
    "wof:placetype":"locality"
},
  "geometry": {"coordinates":[11.18333,59.93333000000001],"type":"Point"}
}