{
  "type": "Feature",
  "properties": {
    "gn:admin1_code":"14.0",
    "gn:admin2_code":"1144.0",
    "gn:asciiname":"Ystabo",
    "gn:country_code":"NO",
    "gn:dem":10,
    "gn:feature_class":"P",
    "gn:feature_code":"PPL",
    "gn:name":"Ystab\u00f8",
    "gn:population":0,
    "gn:timezone":"Europe/Oslo",
    "iso:country":"NO",
    "name:jav_x_preferred":[
        "Ystab\u00f8"
    ],
    "name:msa_x_preferred":[
        "Ystab\u00f8"
    ],
    "wof:name":"Ystabo",
    "wof:placetype":"locality"
},
  "geometry": {"coordinates":[5.39995,59.06073000000001],"type":"Point"}
}