{
  "type": "Feature",
  "properties": {
    "gn:admin1_code":"9.0",
    "gn:admin2_code":"1839.0",
    "gn:asciiname":"Soloy",
    "gn:cc2":"NO",
    "gn:country_code":"NO",
    "gn:dem":120,
    "gn:feature_class":"P",
    "gn:feature_code":"PPL",
    "gn:name":"Sol\u00f8y",
    "gn:population":0,
    "gn:timezone":"Europe/Oslo",
    "iso:country":"NO",
    "name:und_x_variant":[
        "Sol\u00f6ien",
        "Sol\u00f8y"
    ],
    "wof:name":"Soloy",
    "wof:placetype":"locality"
},
  "geometry": {"coordinates":[14.56667,67.01666999999999],"type":"Point"}
}