{
  "type": "Feature",
  "properties": {
    "gn:population":1011,
    "iso:country":"NO",
    "name:ceb_x_preferred":[
        "Hjelset"
    ],
    "name:eng_x_preferred":[
        "Hjelset"
    ],
    "name:fra_x_preferred":[
        "Hjelset"
    ],
    "name:jav_x_preferred":[
        "Hjelset"
    ],
    "name:msa_x_preferred":[
        "Hjelset"
    ],
    "name:nld_x_preferred":[
        "Hjelset"
    ],
    "name:nno_x_preferred":[
        "Hjelset"
    ],
    "name:nob_x_preferred":[
        "Hjelset"
    ],
    "name:nor_x_preferred":[
        "Hjelset"
    ],
    "name:nor_x_variant":[
        "Hjellset",
        "Hjelsets"
    ],
    "name:ron_x_preferred":[
        "Hjelset"
    ],
    "name:spa_x_preferred":[
        "Hjelset"
    ],
    "qs:a0":"Norge",
    "qs:a1":"*M\u00f8re og Romsdal",
    "qs:a1r":"0",
    "qs:adm0":"Norge",
    "qs:la_lc":"*",
    "qs:level":"locality",
    "qs:loc":"Hjelset",
    "qs:loc_alt":"Hjelset",
    "qs:pop":0,
    "qs:type":"buffered point",
    "wd:wordcount":119,
    "wof:lang":[
        "nor"
    ],
    "wof:name":"Hjelset",
    "wof:placetype":"locality",
    "wof:population":1011
},
  "geometry": {"coordinates":[7.504871,62.782952],"type":"Point"}
}