{
  "type": "Feature",
  "properties": {
    "gn:admin1_code":"11.0",
    "gn:admin2_code":"521.0",
    "gn:asciiname":"Roaker",
    "gn:country_code":"NO",
    "gn:dem":760,
    "gn:feature_class":"P",
    "gn:feature_code":"PPL",
    "gn:name":"Ro\u00e5ker",
    "gn:population":0,
    "gn:timezone":"Europe/Oslo",
    "iso:country":"NO",
    "name:nor_x_preferred":[
        "Ro\u00e5ker"
    ],
    "wof:name":"Roaker",
    "wof:placetype":"locality"
},
  "geometry": {"coordinates":[10.20231,61.35868000000001],"type":"Point"}
}