{
  "type": "Feature",
  "properties": {
    "gn:admin1_code":"21",
    "gn:admin2_code":"5025.0",
    "gn:asciiname":"Galaa",
    "gn:cc2":"NO",
    "gn:country_code":"NO",
    "gn:dem":630,
    "gn:feature_class":"P",
    "gn:feature_code":"PPL",
    "gn:name":"Gal\u00e5a",
    "gn:population":0,
    "gn:timezone":"Europe/Oslo",
    "iso:country":"NO",
    "name:msa_x_preferred":[
        "Gal\u00e5a"
    ],
    "name:nor_x_preferred":[
        "Gal\u00e5a"
    ],
    "name:nor_x_variant":[
        "Gal\u00e5en"
    ],
    "name:und_x_variant":[
        "Galaaen"
    ],
    "wof:name":"Galaa",
    "wof:placetype":"locality"
},
  "geometry": {"coordinates":[11.28733,62.55426],"type":"Point"}
}