{
  "type": "Feature",
  "properties": {
    "gn:admin1_code":"9",
    "gn:admin2_code":"1859.0",
    "gn:asciiname":"Kvalvik",
    "gn:country_code":"NO",
    "gn:dem":560,
    "gn:feature_class":"P",
    "gn:feature_code":"PPL",
    "gn:name":"Kvalvik",
    "gn:population":0,
    "gn:timezone":"Europe/Oslo",
    "iso:country":"NO",
    "wof:name":"Kvalvik",
    "wof:placetype":"locality"
},
  "geometry": {"coordinates":[13.26667,68.03333000000001],"type":"Point"}
}