{
  "type": "Feature",
  "properties": {
    "gn:admin1_code":"21",
    "gn:admin2_code":"5011.0",
    "gn:asciiname":"Eidsli",
    "gn:cc2":"NO",
    "gn:country_code":"NO",
    "gn:dem":60,
    "gn:feature_class":"P",
    "gn:feature_code":"PPL",
    "gn:name":"Eidsli",
    "gn:population":0,
    "gn:timezone":"Europe/Oslo",
    "iso:country":"NO",
    "name:und_x_variant":[
        "Eidslu",
        "Eidsli"
    ],
    "wof:name":"Eidsli",
    "wof:placetype":"locality"
},
  "geometry": {"coordinates":[9.01667,63.21666999999999],"type":"Point"}
}