{
  "type": "Feature",
  "properties": {
    "gn:admin1_code":"11.0",
    "gn:admin2_code":"532.0",
    "gn:asciiname":"Ronnerud",
    "gn:country_code":"NO",
    "gn:dem":300,
    "gn:feature_class":"P",
    "gn:feature_code":"PPL",
    "gn:name":"R\u00f8nnerud",
    "gn:population":0,
    "gn:timezone":"Europe/Oslo",
    "iso:country":"NO",
    "wof:name":"Ronnerud",
    "wof:placetype":"locality"
},
  "geometry": {"coordinates":[10.41667,60.23333],"type":"Point"}
}