{
  "type": "Feature",
  "properties": {
    "gn:admin1_code":"18.0",
    "gn:admin2_code":"1941.0",
    "gn:asciiname":"Arvik",
    "gn:cc2":"NO",
    "gn:country_code":"NO",
    "gn:dem":94,
    "gn:feature_class":"P",
    "gn:feature_code":"PPL",
    "gn:name":"\u00c5rvik",
    "gn:population":0,
    "gn:timezone":"Europe/Oslo",
    "iso:country":"NO",
    "name:nor_x_preferred":[
        "\u00c5rvik"
    ],
    "name:nor_x_variant":[
        "\u00c5rviksand",
        "\u00c5rviksanden"
    ],
    "name:und_x_variant":[
        "\u00c5rvik",
        "Aarviksand",
        "Aarvik",
        "\u00c5rviksand"
    ],
    "wof:name":"Arvik",
    "wof:placetype":"locality"
},
  "geometry": {"coordinates":[20.5313,70.19354],"type":"Point"}
}