{
  "type": "Feature",
  "properties": {
    "gn:admin1_code":"14",
    "gn:admin2_code":"1130.0",
    "gn:asciiname":"Geitaskjer",
    "gn:country_code":"NO",
    "gn:dem":312,
    "gn:feature_class":"P",
    "gn:feature_code":"PPL",
    "gn:name":"Geitaskjer",
    "gn:population":0,
    "gn:timezone":"Europe/Oslo",
    "iso:country":"NO",
    "wof:name":"Geitaskjer",
    "wof:placetype":"locality"
},
  "geometry": {"coordinates":[6.06667,59.11666999999999],"type":"Point"}
}