{
  "type": "Feature",
  "properties": {
    "gn:admin1_code":"9",
    "gn:admin2_code":"1860.0",
    "gn:asciiname":"Bergsdalen",
    "gn:country_code":"NO",
    "gn:dem":160,
    "gn:feature_class":"P",
    "gn:feature_code":"PPL",
    "gn:name":"Bergsdalen",
    "gn:population":0,
    "gn:timezone":"Europe/Oslo",
    "iso:country":"NO",
    "name:nno_x_preferred":[
        "Bergsdalen"
    ],
    "name:nor_x_preferred":[
        "Bergsdalen"
    ],
    "wof:name":"Bergsdalen",
    "wof:placetype":"locality"
},
  "geometry": {"coordinates":[13.66667,68.13333],"type":"Point"}
}