{
  "type": "Feature",
  "properties": {
    "gn:admin1_code":"19.0",
    "gn:admin2_code":"1037.0",
    "gn:asciiname":"Forland",
    "gn:country_code":"NO",
    "gn:dem":255,
    "gn:feature_class":"P",
    "gn:feature_code":"PPL",
    "gn:name":"F\u00f8rland",
    "gn:population":0,
    "gn:timezone":"Europe/Oslo",
    "iso:country":"NO",
    "name:nor_x_preferred":[
        "F\u00f8rland"
    ],
    "wof:name":"Forland",
    "wof:placetype":"locality"
},
  "geometry": {"coordinates":[7.02132,58.26371],"type":"Point"}
}