{
  "type": "Feature",
  "properties": {
    "gn:admin1_code":"19.0",
    "gn:admin2_code":"1018.0",
    "gn:asciiname":"Ormestad",
    "gn:country_code":"NO",
    "gn:dem":15,
    "gn:feature_class":"P",
    "gn:feature_code":"PPL",
    "gn:name":"Ormestad",
    "gn:population":0,
    "gn:timezone":"Europe/Oslo",
    "iso:country":"NO",
    "wof:name":"Ormestad",
    "wof:placetype":"locality"
},
  "geometry": {"coordinates":[7.73333,58.06667],"type":"Point"}
}