{
  "type": "Feature",
  "properties": {
    "gn:admin1_code":"6",
    "gn:admin2_code":"412.0",
    "gn:asciiname":"Maelum",
    "gn:country_code":"NO",
    "gn:dem":130,
    "gn:feature_class":"P",
    "gn:feature_code":"PPL",
    "gn:name":"M\u00e6lum",
    "gn:population":0,
    "gn:timezone":"Europe/Oslo",
    "iso:country":"NO",
    "wof:name":"Maelum",
    "wof:placetype":"locality"
},
  "geometry": {"coordinates":[10.98333,60.83333],"type":"Point"}
}