{
  "type": "Feature",
  "properties": {
    "gn:admin1_code":"21",
    "gn:admin2_code":"5013.0",
    "gn:asciiname":"Fjellvaer",
    "gn:cc2":"NO",
    "gn:country_code":"NO",
    "gn:dem":-9999,
    "gn:feature_class":"P",
    "gn:feature_code":"PPL",
    "gn:name":"Fjellv\u00e6r",
    "gn:population":0,
    "gn:timezone":"Europe/Oslo",
    "iso:country":"NO",
    "name:und_x_variant":[
        "Fjeldv\u00e6r",
        "Fjellv\u00e6roy",
        "Fjellv\u00e6r"
    ],
    "wof:name":"Fjellvaer",
    "wof:placetype":"locality"
},
  "geometry": {"coordinates":[9.15,63.63333000000001],"type":"Point"}
}