{
  "type": "Feature",
  "properties": {
    "gn:admin1_code":"19.0",
    "gn:admin2_code":"1037.0",
    "gn:asciiname":"Seland",
    "gn:country_code":"NO",
    "gn:dem":310,
    "gn:feature_class":"P",
    "gn:feature_code":"PPL",
    "gn:name":"Seland",
    "gn:population":0,
    "gn:timezone":"Europe/Oslo",
    "iso:country":"NO",
    "wof:name":"Seland",
    "wof:placetype":"locality"
},
  "geometry": {"coordinates":[6.86667,58.55],"type":"Point"}
}