{
  "type": "Feature",
  "properties": {
    "gn:admin1_code":"14.0",
    "gn:admin2_code":"1133.0",
    "gn:asciiname":"Gronvik",
    "gn:country_code":"NO",
    "gn:dem":24,
    "gn:feature_class":"P",
    "gn:feature_code":"PPL",
    "gn:name":"Gr\u00f8nvik",
    "gn:population":0,
    "gn:timezone":"Europe/Oslo",
    "iso:country":"NO",
    "name:nor_x_preferred":[
        "Gr\u00f8nvik"
    ],
    "wof:name":"Gronvik",
    "wof:placetype":"locality"
},
  "geometry": {"coordinates":[6.04339,59.1411],"type":"Point"}
}