{
  "type": "Feature",
  "properties": {
    "gn:admin1_code":"18",
    "gn:admin2_code":"1933.0",
    "gn:asciiname":"Nordeng",
    "gn:country_code":"NO",
    "gn:dem":219,
    "gn:feature_class":"P",
    "gn:feature_code":"PPL",
    "gn:name":"Nordeng",
    "gn:population":0,
    "gn:timezone":"Europe/Oslo",
    "iso:country":"NO",
    "wof:name":"Nordeng",
    "wof:placetype":"locality"
},
  "geometry": {"coordinates":[18.71667,69.40000000000001],"type":"Point"}
}