{
  "type": "Feature",
  "properties": {
    "gn:admin1_code":"9",
    "gn:admin2_code":"1824.0",
    "gn:asciiname":"Hellfjellbygda",
    "gn:cc2":"NO",
    "gn:country_code":"NO",
    "gn:dem":60,
    "gn:feature_class":"P",
    "gn:feature_code":"PPL",
    "gn:name":"Hellfjellbygda",
    "gn:population":0,
    "gn:timezone":"Europe/Oslo",
    "iso:country":"NO",
    "name:und_x_variant":[
        "Helfjeldbygden",
        "Hellfjellbygda"
    ],
    "wof:name":"Hellfjellbygda",
    "wof:placetype":"locality"
},
  "geometry": {"coordinates":[13.28885,65.92288000000001],"type":"Point"}
}