{
  "type": "Feature",
  "properties": {
    "gn:admin1_code":"17",
    "gn:admin2_code":"807.0",
    "gn:asciiname":"Grini",
    "gn:country_code":"NO",
    "gn:dem":79,
    "gn:feature_class":"P",
    "gn:feature_code":"PPL",
    "gn:name":"Grini",
    "gn:population":0,
    "gn:timezone":"Europe/Oslo",
    "iso:country":"NO",
    "name:nno_x_preferred":[
        "Grini"
    ],
    "name:nor_x_preferred":[
        "Grini"
    ],
    "wof:name":"Grini",
    "wof:placetype":"locality"
},
  "geometry": {"coordinates":[9.13333,59.58333],"type":"Point"}
}