{
  "type": "Feature",
  "properties": {
    "gn:admin1_code":"9.0",
    "gn:admin2_code":"1845.0",
    "gn:asciiname":"Styrkesnes",
    "gn:country_code":"NO",
    "gn:dem":-9999,
    "gn:feature_class":"P",
    "gn:feature_code":"PPL",
    "gn:name":"Styrkesnes",
    "gn:population":0,
    "gn:timezone":"Europe/Oslo",
    "iso:country":"NO",
    "name:nor_x_preferred":[
        "Styrkesnes"
    ],
    "wof:name":"Styrkesnes",
    "wof:placetype":"locality"
},
  "geometry": {"coordinates":[15.51487,67.51536],"type":"Point"}
}