{
  "type": "Feature",
  "properties": {
    "gn:admin1_code":"14",
    "gn:admin2_code":"1112.0",
    "gn:asciiname":"Bilstad",
    "gn:country_code":"NO",
    "gn:dem":193,
    "gn:feature_class":"P",
    "gn:feature_code":"PPL",
    "gn:name":"Bilstad",
    "gn:population":0,
    "gn:timezone":"Europe/Oslo",
    "iso:country":"NO",
    "wof:name":"Bilstad",
    "wof:placetype":"locality"
},
  "geometry": {"coordinates":[6.33333,58.53333000000001],"type":"Point"}
}