{
  "type": "Feature",
  "properties": {
    "gn:admin1_code":"20",
    "gn:admin2_code":"710.0",
    "gn:asciiname":"From",
    "gn:country_code":"NO",
    "gn:dem":23,
    "gn:feature_class":"P",
    "gn:feature_code":"PPL",
    "gn:name":"From",
    "gn:population":0,
    "gn:timezone":"Europe/Oslo",
    "iso:country":"NO",
    "name:deu_x_preferred":[
        "From"
    ],
    "name:nld_x_preferred":[
        "From"
    ],
    "name:por_x_preferred":[
        "From"
    ],
    "name:swe_x_preferred":[
        "From"
    ],
    "wof:name":"From",
    "wof:placetype":"locality"
},
  "geometry": {"coordinates":[10.26667,59.15],"type":"Point"}
}