{
  "type": "Feature",
  "properties": {
    "gn:admin1_code":"8.0",
    "gn:admin2_code":"1566.0",
    "gn:asciiname":"Sjoheim",
    "gn:country_code":"NO",
    "gn:dem":170,
    "gn:feature_class":"P",
    "gn:feature_code":"PPL",
    "gn:name":"Sj\u00f8heim",
    "gn:population":0,
    "gn:timezone":"Europe/Oslo",
    "iso:country":"NO",
    "wof:name":"Sjoheim",
    "wof:placetype":"locality"
},
  "geometry": {"coordinates":[8.51667,63.01667],"type":"Point"}
}