{
  "type": "Feature",
  "properties": {
    "gn:admin1_code":"4.0",
    "gn:admin2_code":"620.0",
    "gn:asciiname":"Saballie",
    "gn:country_code":"NO",
    "gn:dem":920,
    "gn:feature_class":"P",
    "gn:feature_code":"PPL",
    "gn:name":"S\u00e5ballie",
    "gn:population":0,
    "gn:timezone":"Europe/Oslo",
    "iso:country":"NO",
    "name:nor_x_preferred":[
        "S\u00e5ballie"
    ],
    "wof:name":"Saballie",
    "wof:placetype":"locality"
},
  "geometry": {"coordinates":[8.10176,60.51713],"type":"Point"}
}