{
  "type": "Feature",
  "properties": {
    "gn:admin1_code":"17",
    "gn:admin2_code":"805.0",
    "gn:asciiname":"Dalen",
    "gn:country_code":"NO",
    "gn:dem":87,
    "gn:feature_class":"P",
    "gn:feature_code":"PPL",
    "gn:name":"Dalen",
    "gn:population":0,
    "gn:timezone":"Europe/Oslo",
    "iso:country":"NO",
    "name:ceb_x_preferred":[
        "Dalen"
    ],
    "name:cym_x_preferred":[
        "Dalen"
    ],
    "name:fra_x_preferred":[
        "Dalen"
    ],
    "name:fry_x_preferred":[
        "Dalen"
    ],
    "name:ita_x_preferred":[
        "Dalen"
    ],
    "name:nld_x_preferred":[
        "Dalen"
    ],
    "name:pol_x_preferred":[
        "Dalen"
    ],
    "wof:name":"Dalen",
    "wof:placetype":"locality"
},
  "geometry": {"coordinates":[9.68333,59.06667],"type":"Point"}
}