{
  "type": "Feature",
  "properties": {
    "gn:admin1_code":"18",
    "gn:admin2_code":"1933.0",
    "gn:asciiname":"Hamran",
    "gn:country_code":"NO",
    "gn:dem":-9999,
    "gn:feature_class":"P",
    "gn:feature_code":"PPL",
    "gn:name":"Hamran",
    "gn:population":0,
    "gn:timezone":"Europe/Oslo",
    "iso:country":"NO",
    "name:azb_x_preferred":[
        "\u0647\u0645\u0631\u0627\u0646"
    ],
    "name:ceb_x_preferred":[
        "Hamr\u0101n"
    ],
    "name:ckb_x_preferred":[
        "\u06be\u06d5\u0645\u0631\u0627\u0646"
    ],
    "name:fas_x_preferred":[
        "\u0647\u0645\u0631\u0627\u0646"
    ],
    "name:kur_x_preferred":[
        "Hemran"
    ],
    "name:msa_x_preferred":[
        "Hamran"
    ],
    "name:swe_x_preferred":[
        "Hamr\u0101n"
    ],
    "wof:name":"Hamran",
    "wof:placetype":"locality"
},
  "geometry": {"coordinates":[18.63389,69.37139000000001],"type":"Point"}
}