{
  "type": "Feature",
  "properties": {
    "gn:admin1_code":"1",
    "gn:admin2_code":"236.0",
    "gn:asciiname":"Fenstad",
    "gn:country_code":"NO",
    "gn:dem":175,
    "gn:feature_class":"P",
    "gn:feature_code":"PPL",
    "gn:name":"Fenstad",
    "gn:population":0,
    "gn:timezone":"Europe/Oslo",
    "iso:country":"NO",
    "wof:name":"Fenstad",
    "wof:placetype":"locality"
},
  "geometry": {"coordinates":[11.39274,60.21978000000001],"type":"Point"}
}