{
  "type": "Feature",
  "properties": {
    "gn:admin1_code":"4.0",
    "gn:admin2_code":"616.0",
    "gn:asciiname":"Lyseren",
    "gn:country_code":"NO",
    "gn:dem":933,
    "gn:feature_class":"P",
    "gn:feature_code":"PPL",
    "gn:name":"Lyseren",
    "gn:population":0,
    "gn:timezone":"Europe/Oslo",
    "iso:country":"NO",
    "name:ceb_x_preferred":[
        "Lyseren"
    ],
    "name:nno_x_preferred":[
        "Lyseren"
    ],
    "name:nor_x_preferred":[
        "Lyseren"
    ],
    "wof:name":"Lyseren",
    "wof:placetype":"locality"
},
  "geometry": {"coordinates":[8.82238,60.50141],"type":"Point"}
}