{
  "type": "Feature",
  "properties": {
    "gn:admin1_code":"19",
    "gn:admin2_code":"1046.0",
    "gn:asciiname":"Linland",
    "gn:cc2":"NO",
    "gn:country_code":"NO",
    "gn:dem":617,
    "gn:feature_class":"P",
    "gn:feature_code":"PPL",
    "gn:name":"Linland",
    "gn:population":0,
    "gn:timezone":"Europe/Oslo",
    "iso:country":"NO",
    "name:und_x_variant":[
        "Lindeland",
        "Linland"
    ],
    "wof:name":"Linland",
    "wof:placetype":"locality"
},
  "geometry": {"coordinates":[6.75,58.76667],"type":"Point"}
}