{
  "type": "Feature",
  "properties": {
    "gn:country":"NO",
    "gn:fcode":"PPLA2",
    "gn:population":0,
    "iso:country":"NO",
    "name:dan_x_preferred":[
        "Treungen"
    ],
    "name:eng_x_preferred":[
        "Treungen"
    ],
    "name:fra_x_preferred":[
        "Treungen"
    ],
    "name:kor_x_preferred":[
        "\ud2b8\ub808\uc751\uc5d4"
    ],
    "name:msa_x_preferred":[
        "Treungen"
    ],
    "name:nld_x_preferred":[
        "Treungen"
    ],
    "name:nno_x_preferred":[
        "Treungen"
    ],
    "name:nob_x_preferred":[
        "Treungen"
    ],
    "name:swe_x_preferred":[
        "Treungen"
    ],
    "qs_pg:aaroncc":"NO",
    "qs_pg:gn_country":"NO",
    "qs_pg:gn_fcode":"PPLA2",
    "qs_pg:gn_pop":0,
    "qs_pg:name":"Treungen",
    "qs_pg:name_adm0":"Norge",
    "qs_pg:name_adm1":"Telemark Fylke",
    "qs_pg:photos":201,
    "qs_pg:photos_1k":41,
    "qs_pg:photos_9k":1,
    "qs_pg:photos_9r":4,
    "qs_pg:photos_all":201,
    "qs_pg:photos_sr":4,
    "qs_pg:pop_sr":0,
    "qs_pg:qs_pg_placetype":"locality",
    "qs_pg:qs_pg_placetype_gp":"Town",
    "qs_pg:woe_adm0":23424910,
    "woe:adm0_id":23424910,
    "woe:name_adm0":"Norge",
    "woe:name_adm1":"Telemark Fylke",
    "woe:placetype":"Town",
    "wof:name":"Treungen",
    "wof:placetype":"locality"
},
  "geometry": {"coordinates":[8.52375,59.02154],"type":"Point"}
}