{
  "type": "Feature",
  "properties": {
    "gn:admin1_code":"11.0",
    "gn:admin2_code":"528.0",
    "gn:asciiname":"Steinsjo",
    "gn:country_code":"NO",
    "gn:dem":480,
    "gn:feature_class":"P",
    "gn:feature_code":"PPL",
    "gn:name":"Steinsj\u00f8",
    "gn:population":0,
    "gn:timezone":"Europe/Oslo",
    "iso:country":"NO",
    "name:nor_x_preferred":[
        "Steinsj\u00f8"
    ],
    "wof:name":"Steinsjo",
    "wof:placetype":"locality"
},
  "geometry": {"coordinates":[11.06734,60.52158000000001],"type":"Point"}
}