{
  "type": "Feature",
  "properties": {
    "gn:gn_country":"NO",
    "gn:gn_fcode":"PPLL",
    "gn:gn_pop":100,
    "gn:population":100,
    "iso:country":"NO",
    "name:eng_x_preferred":[
        "Tyinkrysset"
    ],
    "name:fra_x_preferred":[
        "Tyinkrysset"
    ],
    "name:jav_x_preferred":[
        "Tyinkrysset"
    ],
    "name:msa_x_preferred":[
        "Tyinkrysset"
    ],
    "name:nld_x_preferred":[
        "Tyinkrysset"
    ],
    "name:nno_x_preferred":[
        "Tyinkrysset"
    ],
    "name:nob_x_preferred":[
        "Tyinkrysset"
    ],
    "qs_pg:aaroncc":"NO",
    "qs_pg:gn_country":"NO",
    "qs_pg:gn_fcode":"PPLL",
    "qs_pg:gn_pop":100,
    "qs_pg:name":"Tyinkrysset",
    "qs_pg:photos_9r":0,
    "qs_pg:photos_sr":0,
    "qs_pg:pop_sr":1,
    "qs_pg:qs_pg_placetype":"locality",
    "wof:name":"Tyinkrysset",
    "wof:placetype":"locality",
    "wof:population":100
},
  "geometry": {"coordinates":[8.23949,61.20403],"type":"Point"}
}