{
  "type": "Feature",
  "properties": {
    "gn:admin1_code":"18.0",
    "gn:admin2_code":"1924.0",
    "gn:asciiname":"Lauvhaugen",
    "gn:country_code":"NO",
    "gn:dem":84,
    "gn:feature_class":"P",
    "gn:feature_code":"PPL",
    "gn:name":"Lauvhaugen",
    "gn:population":0,
    "gn:timezone":"Europe/Oslo",
    "iso:country":"NO",
    "name:nor_x_preferred":[
        "Lauvhaugen"
    ],
    "wof:name":"Lauvhaugen",
    "wof:placetype":"locality"
},
  "geometry": {"coordinates":[18.90563,69.01776],"type":"Point"}
}