{
  "type": "Feature",
  "properties": {
    "gn:admin1_code":"9",
    "gn:admin2_code":"1866.0",
    "gn:asciiname":"Budalen",
    "gn:country_code":"NO",
    "gn:dem":300,
    "gn:feature_class":"P",
    "gn:feature_code":"PPL",
    "gn:name":"Budalen",
    "gn:population":0,
    "gn:timezone":"Europe/Oslo",
    "iso:country":"NO",
    "wof:name":"Budalen",
    "wof:placetype":"locality"
},
  "geometry": {"coordinates":[14.81667,68.38333],"type":"Point"}
}