{
  "type": "Feature",
  "properties": {
    "gn:admin1_code":"4",
    "gn:admin2_code":"624.0",
    "gn:asciiname":"Berg",
    "gn:country_code":"NO",
    "gn:dem":36,
    "gn:feature_class":"P",
    "gn:feature_code":"PPL",
    "gn:name":"Berg",
    "gn:population":0,
    "gn:timezone":"Europe/Oslo",
    "iso:country":"NO",
    "wof:name":"Berg",
    "wof:placetype":"locality"
},
  "geometry": {"coordinates":[9.86667,59.75],"type":"Point"}
}