{
  "type": "Feature",
  "properties": {
    "gn:admin1_code":"6.0",
    "gn:admin2_code":"419.0",
    "gn:asciiname":"Sandnes",
    "gn:country_code":"NO",
    "gn:dem":139,
    "gn:feature_class":"P",
    "gn:feature_code":"PPL",
    "gn:name":"Sandnes",
    "gn:population":0,
    "gn:timezone":"Europe/Oslo",
    "iso:country":"NO",
    "wof:name":"Sandnes",
    "wof:placetype":"locality"
},
  "geometry": {"coordinates":[11.65,60.21666999999999],"type":"Point"}
}