{
  "type": "Feature",
  "properties": {
    "gn:admin1_code":"15",
    "gn:admin2_code":"1416.0",
    "gn:asciiname":"Hjelmeland",
    "gn:country_code":"NO",
    "gn:dem":380,
    "gn:feature_class":"P",
    "gn:feature_code":"PPL",
    "gn:name":"Hjelmeland",
    "gn:population":0,
    "gn:timezone":"Europe/Oslo",
    "iso:country":"NO",
    "wof:name":"Hjelmeland",
    "wof:placetype":"locality"
},
  "geometry": {"coordinates":[5.48333,61.15],"type":"Point"}
}