{
  "type": "Feature",
  "properties": {
    "gn:admin1_code":"15",
    "gn:admin2_code":"1416.0",
    "gn:asciiname":"Hjelmeland",
    "gn:country_code":"NO",
    "gn:dem":380,
    "gn:feature_class":"P",
    "gn:feature_code":"PPL",
    "gn:name":"Hjelmeland",
    "gn:population":0,
    "gn:timezone":"Europe/Oslo",
    "iso:country":"NO",
    "name:bar_x_preferred":[
        "Hjelmeland"
    ],
    "name:bpy_x_preferred":[
        "\u09b9\u099c\u09c7\u09b2\u09ae\u09c7\u09b2\u09c7\u09a8\u09cd\u09a1"
    ],
    "name:cat_x_preferred":[
        "Hjelmeland"
    ],
    "name:ceb_x_preferred":[
        "Hjelmeland"
    ],
    "name:dan_x_preferred":[
        "Hjelmeland"
    ],
    "name:deu_x_preferred":[
        "Hjelmeland"
    ],
    "name:epo_x_preferred":[
        "Hjelmeland"
    ],
    "name:eus_x_preferred":[
        "Hjelmeland"
    ],
    "name:fin_x_preferred":[
        "Hjelmeland"
    ],
    "name:fra_x_preferred":[
        "Hjelmeland"
    ],
    "name:hun_x_preferred":[
        "Hjelmeland"
    ],
    "name:hye_x_preferred":[
        "\u0537\u056c\u0574\u0565\u056c\u0561\u0576"
    ],
    "name:ita_x_preferred":[
        "Hjelmeland"
    ],
    "name:jav_x_preferred":[
        "Hjelmeland"
    ],
    "name:lat_x_preferred":[
        "Hjelmeland"
    ],
    "name:lim_x_preferred":[
        "Hjelmeland"
    ],
    "name:msa_x_preferred":[
        "Hjelmeland"
    ],
    "name:nds_x_preferred":[
        "Kommun Hjelmeland"
    ],
    "name:nld_x_preferred":[
        "Hjelmeland"
    ],
    "name:nno_x_preferred":[
        "Hjelmeland kommune"
    ],
    "name:nor_x_preferred":[
        "Hjelmeland"
    ],
    "name:pol_x_preferred":[
        "Hjelmeland"
    ],
    "name:por_x_preferred":[
        "Hjelmeland"
    ],
    "name:ron_x_preferred":[
        "Hjelmeland"
    ],
    "name:rus_x_preferred":[
        "\u0415\u043b\u044c\u043c\u0435\u043b\u0430\u043d\u043d"
    ],
    "name:slv_x_preferred":[
        "Hjelmeland"
    ],
    "name:sme_x_preferred":[
        "Hjelmeland"
    ],
    "name:spa_x_preferred":[
        "Hjelmeland"
    ],
    "name:sqi_x_preferred":[
        "Hjelmeland"
    ],
    "name:swe_x_preferred":[
        "Hjelmelands kommun"
    ],
    "name:war_x_preferred":[
        "Hjelmeland"
    ],
    "name:zho_x_preferred":[
        "\u8036\u723e\u9ed8\u862d"
    ],
    "wof:name":"Hjelmeland",
    "wof:placetype":"locality"
},
  "geometry": {"coordinates":[5.48333,61.15],"type":"Point"}
}