{
  "type": "Feature",
  "properties": {
    "gn:admin1_code":"19.0",
    "gn:admin2_code":"1003.0",
    "gn:asciiname":"Bekkevika",
    "gn:country_code":"NO",
    "gn:dem":17,
    "gn:feature_class":"P",
    "gn:feature_code":"PPL",
    "gn:name":"Bekkevika",
    "gn:population":0,
    "gn:timezone":"Europe/Oslo",
    "iso:country":"NO",
    "name:nor_x_preferred":[
        "Bekkevika"
    ],
    "wof:name":"Bekkevika",
    "wof:placetype":"locality"
},
  "geometry": {"coordinates":[6.83603,58.0931],"type":"Point"}
}