{
  "type": "Feature",
  "properties": {
    "gn:admin1_code":"5.0",
    "gn:admin2_code":"2030.0",
    "gn:asciiname":"Saga",
    "gn:country_code":"NO",
    "gn:dem":21,
    "gn:feature_class":"P",
    "gn:feature_code":"PPL",
    "gn:name":"Saga",
    "gn:population":0,
    "gn:timezone":"Europe/Oslo",
    "iso:country":"NO",
    "name:nor_x_preferred":[
        "Saga"
    ],
    "wof:name":"Saga",
    "wof:placetype":"locality"
},
  "geometry": {"coordinates":[30.10717,69.5299],"type":"Point"}
}