{
  "type": "Feature",
  "properties": {
    "gn:admin1_code":"21",
    "gn:admin2_code":"5045.0",
    "gn:asciiname":"Jorem",
    "gn:country_code":"NO",
    "gn:dem":14,
    "gn:feature_class":"P",
    "gn:feature_code":"PPL",
    "gn:name":"J\u00f8rem",
    "gn:population":0,
    "gn:timezone":"Europe/Oslo",
    "iso:country":"NO",
    "wof:name":"Jorem",
    "wof:placetype":"locality"
},
  "geometry": {"coordinates":[12.18848,64.45744000000001],"type":"Point"}
}