{
  "type": "Feature",
  "properties": {
    "gn:admin1_code":"2.0",
    "gn:admin2_code":"914.0",
    "gn:asciiname":"Valle",
    "gn:country_code":"NO",
    "gn:dem":146,
    "gn:feature_class":"P",
    "gn:feature_code":"PPL",
    "gn:name":"Valle",
    "gn:population":0,
    "gn:timezone":"Europe/Oslo",
    "iso:country":"NO",
    "wof:name":"Valle",
    "wof:placetype":"locality"
},
  "geometry": {"coordinates":[8.96667,58.65],"type":"Point"}
}