{
  "type": "Feature",
  "properties": {
    "gn:admin1_code":"2.0",
    "gn:admin2_code":"914.0",
    "gn:asciiname":"Valle",
    "gn:country_code":"NO",
    "gn:dem":146,
    "gn:feature_class":"P",
    "gn:feature_code":"PPL",
    "gn:name":"Valle",
    "gn:population":0,
    "gn:timezone":"Europe/Oslo",
    "iso:country":"NO",
    "name:ast_x_preferred":[
        "Valle"
    ],
    "name:cat_x_preferred":[
        "Valle"
    ],
    "name:ceb_x_preferred":[
        "Valle"
    ],
    "name:dan_x_preferred":[
        "Valle"
    ],
    "name:deu_x_preferred":[
        "Valle"
    ],
    "name:epo_x_preferred":[
        "Valle"
    ],
    "name:est_x_preferred":[
        "Valle"
    ],
    "name:eus_x_preferred":[
        "Valle"
    ],
    "name:fin_x_preferred":[
        "Valle"
    ],
    "name:fra_x_preferred":[
        "Valle"
    ],
    "name:hrv_x_preferred":[
        "Valle"
    ],
    "name:ita_x_preferred":[
        "Valle"
    ],
    "name:nld_x_preferred":[
        "Valle"
    ],
    "name:nor_x_preferred":[
        "Valle"
    ],
    "name:pol_x_preferred":[
        "Valle"
    ],
    "name:ron_x_preferred":[
        "Valle"
    ],
    "name:rus_x_preferred":[
        "\u0412\u0430\u043b\u044c\u0435"
    ],
    "name:spa_x_preferred":[
        "Valle"
    ],
    "name:srp_x_preferred":[
        "\u0412\u0430\u043b\u0435"
    ],
    "name:swe_x_preferred":[
        "Valle"
    ],
    "wof:name":"Valle",
    "wof:placetype":"locality"
},
  "geometry": {"coordinates":[8.96667,58.65],"type":"Point"}
}