{
  "type": "Feature",
  "properties": {
    "gn:admin1_code":"7",
    "gn:admin2_code":"1201.0",
    "gn:asciiname":"Breidvika",
    "gn:cc2":"NO",
    "gn:country_code":"NO",
    "gn:dem":50,
    "gn:feature_class":"P",
    "gn:feature_code":"PPL",
    "gn:name":"Breidvika",
    "gn:population":0,
    "gn:timezone":"Europe/Oslo",
    "iso:country":"NO",
    "name:und_x_variant":[
        "Breidvik",
        "Breidvika"
    ],
    "wof:name":"Breidvika",
    "wof:placetype":"neighbourhood"
},
  "geometry": {"coordinates":[5.18729,60.37475],"type":"Point"}
}