{
  "type": "Feature",
  "properties": {
    "gn:admin1_code":"21",
    "gn:admin2_code":"5005.0",
    "gn:asciiname":"Fosslandsosen",
    "gn:cc2":"NO",
    "gn:country_code":"NO",
    "gn:dem":20,
    "gn:feature_class":"P",
    "gn:feature_code":"PPL",
    "gn:name":"Fosslandsosen",
    "gn:population":0,
    "gn:timezone":"Europe/Oslo",
    "iso:country":"NO",
    "name:und_x_variant":[
        "Foslandsosen",
        "Fosslandsosen"
    ],
    "wof:name":"Fosslandsosen",
    "wof:placetype":"locality"
},
  "geometry": {"coordinates":[11.26667,64.53333000000001],"type":"Point"}
}