{
  "type": "Feature",
  "properties": {
    "gn:admin1_code":"15",
    "gn:admin2_code":"1417.0",
    "gn:asciiname":"Brekka",
    "gn:country_code":"NO",
    "gn:dem":110,
    "gn:feature_class":"P",
    "gn:feature_code":"PPL",
    "gn:name":"Brekka",
    "gn:population":0,
    "gn:timezone":"Europe/Oslo",
    "iso:country":"NO",
    "name:ceb_x_preferred":[
        "Brekka"
    ],
    "name:jav_x_preferred":[
        "Brekka"
    ],
    "name:msa_x_preferred":[
        "Brekka"
    ],
    "name:nor_x_preferred":[
        "Brekka"
    ],
    "wof:name":"Brekka",
    "wof:placetype":"locality"
},
  "geometry": {"coordinates":[6.55,61.06667],"type":"Point"}
}