{
  "type": "Feature",
  "properties": {
    "gn:country":"NO",
    "gn:fcode":"PPLA2",
    "gn:population":0,
    "iso:country":"NO",
    "name:ceb_x_preferred":[
        "Roa"
    ],
    "name:fra_x_preferred":[
        "Roa"
    ],
    "name:heb_x_preferred":[
        "\u05e8\u05d5\u05d0\u05d4"
    ],
    "name:por_x_preferred":[
        "Roa"
    ],
    "name:spa_x_preferred":[
        "Roa"
    ],
    "name:srp_x_preferred":[
        "\u0420\u043e\u0430"
    ],
    "name:swe_x_preferred":[
        "Roa"
    ],
    "qs_pg:aaroncc":"NO",
    "qs_pg:gn_country":"NO",
    "qs_pg:gn_fcode":"PPLA2",
    "qs_pg:gn_pop":0,
    "qs_pg:name":"Roa",
    "qs_pg:name_adm0":"Norge",
    "qs_pg:name_adm1":"Oppland Fylke",
    "qs_pg:photos":34,
    "qs_pg:photos_1k":7,
    "qs_pg:photos_9k":1,
    "qs_pg:photos_9r":2,
    "qs_pg:photos_all":34,
    "qs_pg:photos_sr":2,
    "qs_pg:pop_sr":0,
    "qs_pg:qs_pg_placetype":"locality",
    "qs_pg:qs_pg_placetype_gp":"Town",
    "qs_pg:woe_adm0":23424910,
    "woe:adm0_id":23424910,
    "woe:name_adm0":"Norge",
    "woe:name_adm1":"Oppland Fylke",
    "woe:placetype":"Town",
    "wof:name":"Roa",
    "wof:placetype":"neighbourhood"
},
  "geometry": {"coordinates":[10.61585,60.29093],"type":"Point"}
}