{
  "type": "Feature",
  "properties": {
    "iso:country":"NO",
    "qs_pg:aaroncc":"NO",
    "qs_pg:name":"\u00c5fosstrand",
    "qs_pg:name_adm0":"Norge",
    "qs_pg:name_adm1":"Telemark Fylke",
    "qs_pg:photos":26,
    "qs_pg:photos_1k":5,
    "qs_pg:photos_9k":1,
    "qs_pg:photos_9r":2,
    "qs_pg:photos_all":26,
    "qs_pg:photos_sr":2,
    "qs_pg:pop_sr":0,
    "qs_pg:qs_pg_placetype":"locality",
    "qs_pg:qs_pg_placetype_gp":"Town",
    "qs_pg:woe_adm0":23424910,
    "woe:adm0_id":23424910,
    "woe:name_adm0":"Norge",
    "woe:name_adm1":"Telemark Fylke",
    "woe:placetype":"Town",
    "wof:name":"\u00c5fosstrand",
    "wof:placetype":"locality"
},
  "geometry": {"coordinates":[9.533848,59.206876],"type":"Point"}
}