{
  "type": "Feature",
  "properties": {
    "gn:admin1_code":"19.0",
    "gn:admin2_code":"1032.0",
    "gn:asciiname":"Svenevik",
    "gn:country_code":"NO",
    "gn:dem":16,
    "gn:feature_class":"P",
    "gn:feature_code":"PPL",
    "gn:name":"Svenevik",
    "gn:population":0,
    "gn:timezone":"Europe/Oslo",
    "iso:country":"NO",
    "name:nor_x_preferred":[
        "Svenevik"
    ],
    "wof:name":"Svenevik",
    "wof:placetype":"locality"
},
  "geometry": {"coordinates":[7.02611,58.11015],"type":"Point"}
}