{
  "type": "Feature",
  "properties": {
    "gn:admin1_code":"6.0",
    "gn:admin2_code":"426.0",
    "gn:asciiname":"Sondre Fjellsaetra",
    "gn:country_code":"NO",
    "gn:dem":550,
    "gn:feature_class":"P",
    "gn:feature_code":"PPL",
    "gn:name":"S\u00f8ndre Fjells\u00e6tra",
    "gn:population":0,
    "gn:timezone":"Europe/Oslo",
    "iso:country":"NO",
    "name:nor_x_preferred":[
        "S\u00f8ndre Fjells\u00e6tra"
    ],
    "wof:name":"Sondre Fjellsaetra",
    "wof:placetype":"locality"
},
  "geometry": {"coordinates":[11.69917,60.58393],"type":"Point"}
}