{
  "type": "Feature",
  "properties": {
    "gn:admin1_code":"18.0",
    "gn:admin2_code":"1924.0",
    "gn:asciiname":"Vestgard",
    "gn:country_code":"NO",
    "gn:dem":156,
    "gn:feature_class":"P",
    "gn:feature_code":"PPL",
    "gn:name":"Vestgard",
    "gn:population":0,
    "gn:timezone":"Europe/Oslo",
    "iso:country":"NO",
    "wof:name":"Vestgard",
    "wof:placetype":"locality"
},
  "geometry": {"coordinates":[18.63333,69.21666999999999],"type":"Point"}
}