{
  "type": "Feature",
  "properties": {
    "gn:admin1_code":"15",
    "gn:admin2_code":"1449.0",
    "gn:asciiname":"Loen",
    "gn:cc2":"NO",
    "gn:country_code":"NO",
    "gn:dem":19,
    "gn:feature_class":"P",
    "gn:feature_code":"PPL",
    "gn:name":"Loen",
    "gn:population":0,
    "gn:timezone":"Europe/Oslo",
    "iso:country":"NO",
    "name:dan_x_preferred":[
        "Loen"
    ],
    "name:deu_x_preferred":[
        "Loen"
    ],
    "name:fas_x_preferred":[
        "\u0644\u0648\u0626\u0646"
    ],
    "name:fin_x_preferred":[
        "Loen"
    ],
    "name:msa_x_preferred":[
        "Loen"
    ],
    "name:nld_x_preferred":[
        "Loen"
    ],
    "name:nno_x_preferred":[
        "Loen"
    ],
    "name:nor_x_preferred":[
        "Loen"
    ],
    "name:pol_x_preferred":[
        "Loen"
    ],
    "name:por_x_preferred":[
        "Loen"
    ],
    "name:swe_x_preferred":[
        "Loen"
    ],
    "name:und_x_variant":[
        "Loen i Nordfjord"
    ],
    "wof:name":"Loen",
    "wof:placetype":"locality"
},
  "geometry": {"coordinates":[6.8459,61.87151],"type":"Point"}
}