{
  "type": "Feature",
  "properties": {
    "gn:admin1_code":"6.0",
    "gn:admin2_code":"425.0",
    "gn:asciiname":"Sonsterudmoen",
    "gn:country_code":"NO",
    "gn:dem":190,
    "gn:feature_class":"P",
    "gn:feature_code":"PPL",
    "gn:name":"S\u00f8nsterudmoen",
    "gn:population":0,
    "gn:timezone":"Europe/Oslo",
    "iso:country":"NO",
    "name:nor_x_preferred":[
        "S\u00f8nsterudmoen"
    ],
    "wof:name":"Sonsterudmoen",
    "wof:placetype":"locality"
},
  "geometry": {"coordinates":[12.05047,60.65204],"type":"Point"}
}