{
  "type": "Feature",
  "properties": {
    "gn:admin1_code":"4",
    "gn:admin2_code":"631.0",
    "gn:asciiname":"Flesberg",
    "gn:country_code":"NO",
    "gn:dem":189,
    "gn:feature_class":"P",
    "gn:feature_code":"PPLL",
    "gn:name":"Flesberg",
    "gn:population":0,
    "gn:timezone":"Europe/Oslo",
    "iso:country":"NO",
    "name:ara_x_preferred":[
        "\u0641\u0644\u064a\u0633\u0628\u0631\u063a"
    ],
    "name:bpy_x_preferred":[
        "\u09ab\u09cd\u09b2\u09c7\u09b6\u09ac\u09be\u09b0\u09cd\u0997"
    ],
    "name:cat_x_preferred":[
        "Flesberg"
    ],
    "name:ceb_x_preferred":[
        "Flesberg"
    ],
    "name:dan_x_preferred":[
        "Flesberg"
    ],
    "name:deu_x_preferred":[
        "Flesberg"
    ],
    "name:epo_x_preferred":[
        "Flesberg"
    ],
    "name:eus_x_preferred":[
        "Flesberg"
    ],
    "name:fin_x_preferred":[
        "Flesberg"
    ],
    "name:fra_x_preferred":[
        "Flesberg"
    ],
    "name:hye_x_preferred":[
        "\u0556\u056c\u0565\u057d\u0562\u0565\u0580\u0563"
    ],
    "name:ita_x_preferred":[
        "Flesberg"
    ],
    "name:jav_x_preferred":[
        "Flesberg"
    ],
    "name:lat_x_preferred":[
        "Flesberg"
    ],
    "name:lim_x_preferred":[
        "Flesberg"
    ],
    "name:msa_x_preferred":[
        "Flesberg"
    ],
    "name:nds_x_preferred":[
        "Kommun Flesberg"
    ],
    "name:nld_x_preferred":[
        "Flesberg"
    ],
    "name:nno_x_preferred":[
        "Flesberg kommune"
    ],
    "name:nor_x_preferred":[
        "Flesberg"
    ],
    "name:pol_x_preferred":[
        "Flesberg"
    ],
    "name:por_x_preferred":[
        "Flesberg"
    ],
    "name:ron_x_preferred":[
        "Flesberg"
    ],
    "name:rus_x_preferred":[
        "\u0424\u043b\u0435\u0441\u0431\u0435\u0440\u0433"
    ],
    "name:slv_x_preferred":[
        "Flesberg"
    ],
    "name:sme_x_preferred":[
        "Flesberg"
    ],
    "name:spa_x_preferred":[
        "Flesberg"
    ],
    "name:sqi_x_preferred":[
        "Flesberg"
    ],
    "name:swe_x_preferred":[
        "Flesbergs kommun"
    ],
    "name:vie_x_preferred":[
        "Flesberg"
    ],
    "name:war_x_preferred":[
        "Flesberg"
    ],
    "name:zho_x_preferred":[
        "\u5f17\u840a\u65af\u8c9d\u683c"
    ],
    "wof:name":"Flesberg",
    "wof:placetype":"locality"
},
  "geometry": {"coordinates":[9.43246,59.86298000000001],"type":"Point"}
}