{
  "type": "Feature",
  "properties": {
    "gn:admin1_code":"4",
    "gn:admin2_code":"631.0",
    "gn:asciiname":"Flesberg",
    "gn:country_code":"NO",
    "gn:dem":189,
    "gn:feature_class":"P",
    "gn:feature_code":"PPLL",
    "gn:name":"Flesberg",
    "gn:population":0,
    "gn:timezone":"Europe/Oslo",
    "iso:country":"NO",
    "wof:name":"Flesberg",
    "wof:placetype":"locality"
},
  "geometry": {"coordinates":[9.43246,59.86298000000001],"type":"Point"}
}