{
  "type": "Feature",
  "properties": {
    "gn:admin1_code":"18.0",
    "gn:admin2_code":"1902.0",
    "gn:asciiname":"Loksfjord",
    "gn:country_code":"NO",
    "gn:dem":114,
    "gn:feature_class":"P",
    "gn:feature_code":"PPL",
    "gn:name":"L\u00f8ksfjord",
    "gn:population":0,
    "gn:timezone":"Europe/Oslo",
    "iso:country":"NO",
    "name:nor_x_preferred":[
        "L\u00f8ksfjord"
    ],
    "wof:name":"Loksfjord",
    "wof:placetype":"locality"
},
  "geometry": {"coordinates":[18.71827,70.03045999999999],"type":"Point"}
}