{
  "type": "Feature",
  "properties": {
    "gn:admin1_code":"9",
    "gn:admin2_code":"1832",
    "gn:asciiname":"Svartmarka",
    "gn:country_code":"NO",
    "gn:dem":40,
    "gn:feature_class":"P",
    "gn:feature_code":"PPLL",
    "gn:name":"Svartmarka",
    "gn:population":0,
    "gn:timezone":"Europe/Oslo",
    "iso:country":"NO",
    "name:nor_x_preferred":[
        "Svartmarka"
    ],
    "wof:name":"Svartmarka",
    "wof:placetype":"locality"
},
  "geometry": {"coordinates":[13.80072,66.07896],"type":"Point"}
}