{
  "type": "Feature",
  "properties": {
    "gn:admin1_code":"11.0",
    "gn:admin2_code":"512.0",
    "gn:asciiname":"Nysaetri",
    "gn:country_code":"NO",
    "gn:dem":840,
    "gn:feature_class":"P",
    "gn:feature_code":"PPL",
    "gn:name":"Nys\u00e6tri",
    "gn:population":0,
    "gn:timezone":"Europe/Oslo",
    "iso:country":"NO",
    "name:nor_x_preferred":[
        "Nys\u00e6tri"
    ],
    "wof:name":"Nysaetri",
    "wof:placetype":"locality"
},
  "geometry": {"coordinates":[8.92463,62.19774],"type":"Point"}
}