{
  "type": "Feature",
  "properties": {
    "gn:admin1_code":"5.0",
    "gn:admin2_code":"2019.0",
    "gn:asciiname":"Nordmannset",
    "gn:country_code":"NO",
    "gn:dem":20,
    "gn:feature_class":"P",
    "gn:feature_code":"PPL",
    "gn:name":"Nordmannset",
    "gn:population":0,
    "gn:timezone":"Europe/Oslo",
    "iso:country":"NO",
    "wof:name":"Nordmannset",
    "wof:placetype":"neighbourhood"
},
  "geometry": {"coordinates":[25.96151,71.00744],"type":"Point"}
}