{
  "type": "Feature",
  "properties": {
    "gn:admin1_code":"5",
    "gn:admin2_code":"2003",
    "gn:asciiname":"Annijaki",
    "gn:country_code":"NO",
    "gn:dem":8,
    "gn:feature_class":"P",
    "gn:feature_code":"PPL",
    "gn:name":"Annij\u00e5ki",
    "gn:population":0,
    "gn:timezone":"Europe/Oslo",
    "iso:country":"NO",
    "name:fkv_x_preferred":[
        "Annij\u00e5ki"
    ],
    "name:fkv_x_variant":[
        "Annijoki"
    ],
    "name:jav_x_preferred":[
        "Vestre Jakobselv"
    ],
    "name:msa_x_preferred":[
        "Vestre Jakobselv"
    ],
    "name:nld_x_preferred":[
        "Vestre Jakobselv"
    ],
    "name:nno_x_preferred":[
        "Vestre Jakobselv"
    ],
    "name:nor_x_preferred":[
        "Vestre Jakobselv"
    ],
    "name:ron_x_preferred":[
        "Vestre Jakobselv"
    ],
    "name:sme_x_preferred":[
        "\u00c1nnejohka"
    ],
    "name:spa_x_preferred":[
        "Vestre Jakobselv"
    ],
    "name:swe_x_preferred":[
        "Vestre Jakobselv"
    ],
    "wof:name":"Annijaki",
    "wof:placetype":"locality"
},
  "geometry": {"coordinates":[29.33298,70.11149],"type":"Point"}
}