{
  "type": "Feature",
  "properties": {
    "gn:country":"NO",
    "iso:country":"NO",
    "name:cat_x_preferred":[
        "Ellings\u00f8y"
    ],
    "name:ceb_x_preferred":[
        "Ellings\u00f8ya"
    ],
    "name:nno_x_preferred":[
        "Ellings\u00f8ya"
    ],
    "name:nor_x_preferred":[
        "Ellings\u00f8ya"
    ],
    "qs_pg:aaroncc":"NO",
    "qs_pg:gn_country":"NO",
    "qs_pg:name":"Ellings\u00f8y",
    "qs_pg:name_adm0":"Norge",
    "qs_pg:name_adm1":"M\u00f8re og Romsdal Fylke",
    "qs_pg:photos":119,
    "qs_pg:photos_1k":24,
    "qs_pg:photos_9k":1,
    "qs_pg:photos_9r":3,
    "qs_pg:photos_all":119,
    "qs_pg:photos_sr":3,
    "qs_pg:pop_sr":0,
    "qs_pg:qs_pg_placetype":"locality",
    "qs_pg:qs_pg_placetype_gp":"Town",
    "qs_pg:woe_adm0":23424910,
    "woe:adm0_id":23424910,
    "woe:name_adm0":"Norge",
    "woe:name_adm1":"M\u00f8re og Romsdal Fylke",
    "woe:placetype":"Town",
    "wof:name":"Ellings\u00f8y",
    "wof:placetype":"neighbourhood"
},
  "geometry": {"coordinates":[6.37516,62.483186],"type":"Point"}
}