{
  "type": "Feature",
  "properties": {
    "gn:admin1_code":"21.0",
    "gn:admin2_code":"5012.0",
    "gn:asciiname":"Vutudal",
    "gn:cc2":"NO",
    "gn:country_code":"NO",
    "gn:dem":290,
    "gn:feature_class":"P",
    "gn:feature_code":"PPL",
    "gn:name":"Vutudal",
    "gn:population":0,
    "gn:timezone":"Europe/Oslo",
    "iso:country":"NO",
    "name:und_x_variant":[
        "Vutudalen",
        "Vutudal"
    ],
    "wof:name":"Vutudal",
    "wof:placetype":"locality"
},
  "geometry": {"coordinates":[9.42778,63.34633],"type":"Point"}
}