{
  "type": "Feature",
  "properties": {
    "gn:country":"NO",
    "gn:fcode":"PPL",
    "gn:population":0,
    "iso:country":"NO",
    "name:jav_x_preferred":[
        "Sunndal"
    ],
    "name:msa_x_preferred":[
        "Sunndal"
    ],
    "name:nld_x_preferred":[
        "Sundal"
    ],
    "name:nor_x_preferred":[
        "Sundal"
    ],
    "name:swe_x_preferred":[
        "Sunndal"
    ],
    "qs_pg:aaroncc":"NO",
    "qs_pg:gn_country":"NO",
    "qs_pg:gn_fcode":"PPL",
    "qs_pg:gn_pop":0,
    "qs_pg:name":"Sundal",
    "qs_pg:name_adm0":"Norge",
    "qs_pg:name_adm1":"Sogn og Fjordane Fylke",
    "qs_pg:photos_9r":0,
    "qs_pg:photos_sr":0,
    "qs_pg:pop_sr":0,
    "qs_pg:qs_pg_placetype":"locality",
    "qs_pg:qs_pg_placetype_gp":"Town",
    "qs_pg:woe_adm0":23424910,
    "woe:adm0_id":23424910,
    "woe:name_adm0":"Norge",
    "woe:name_adm1":"Sogn og Fjordane Fylke",
    "woe:placetype":"Town",
    "wof:name":"Sundal",
    "wof:placetype":"locality"
},
  "geometry": {"coordinates":[5.65,61.93333],"type":"Point"}
}