{
  "type": "Feature",
  "properties": {
    "gn:admin1_code":"6.0",
    "gn:admin2_code":"437.0",
    "gn:asciiname":"Rostvangen",
    "gn:country_code":"NO",
    "gn:dem":740,
    "gn:feature_class":"P",
    "gn:feature_code":"PPL",
    "gn:name":"R\u00f8stvangen",
    "gn:population":0,
    "gn:timezone":"Europe/Oslo",
    "iso:country":"NO",
    "wof:name":"Rostvangen",
    "wof:placetype":"locality"
},
  "geometry": {"coordinates":[10.41667,62.38333000000001],"type":"Point"}
}