{
  "type": "Feature",
  "properties": {
    "gn:admin1_code":"19",
    "gn:admin2_code":"1029.0",
    "gn:asciiname":"Lone",
    "gn:country_code":"NO",
    "gn:dem":34,
    "gn:feature_class":"P",
    "gn:feature_code":"PPL",
    "gn:name":"Lone",
    "gn:population":0,
    "gn:timezone":"Europe/Oslo",
    "iso:country":"NO",
    "name:ceb_x_preferred":[
        "Lone"
    ],
    "name:deu_x_preferred":[
        "Lone"
    ],
    "name:fra_x_preferred":[
        "Lone"
    ],
    "name:nor_x_preferred":[
        "Lone"
    ],
    "name:rus_x_preferred":[
        "\u041b\u043e\u0443\u043d"
    ],
    "name:swe_x_preferred":[
        "Lone"
    ],
    "wof:name":"Lone",
    "wof:placetype":"locality"
},
  "geometry": {"coordinates":[7.23333,58.06667],"type":"Point"}
}