{
  "type": "Feature",
  "properties": {
    "gn:admin1_code":"4.0",
    "gn:admin2_code":"621.0",
    "gn:asciiname":"Tempelseter",
    "gn:country_code":"NO",
    "gn:dem":913,
    "gn:feature_class":"P",
    "gn:feature_code":"PPL",
    "gn:name":"Tempelseter",
    "gn:population":0,
    "gn:timezone":"Europe/Oslo",
    "iso:country":"NO",
    "name:nor_x_preferred":[
        "Tempelseter"
    ],
    "name:nor_x_variant":[
        "Tempelsetra"
    ],
    "wof:name":"Tempelseter",
    "wof:placetype":"locality"
},
  "geometry": {"coordinates":[9.40819,60.27023000000001],"type":"Point"}
}