{
  "type": "Feature",
  "properties": {
    "gn:admin1_code":"11.0",
    "gn:admin2_code":"515.0",
    "gn:asciiname":"Storrvikroe",
    "gn:country_code":"NO",
    "gn:dem":520,
    "gn:feature_class":"P",
    "gn:feature_code":"PPL",
    "gn:name":"Storrvikroe",
    "gn:population":0,
    "gn:timezone":"Europe/Oslo",
    "iso:country":"NO",
    "wof:name":"Storrvikroe",
    "wof:placetype":"locality"
},
  "geometry": {"coordinates":[8.90254,61.84426],"type":"Point"}
}