{
  "type": "Feature",
  "properties": {
    "gn:admin1_code":"15",
    "gn:admin2_code":"1416.0",
    "gn:asciiname":"Klevoll",
    "gn:cc2":"NO",
    "gn:country_code":"NO",
    "gn:dem":335,
    "gn:feature_class":"P",
    "gn:feature_code":"PPL",
    "gn:name":"Klevoll",
    "gn:population":0,
    "gn:timezone":"Europe/Oslo",
    "iso:country":"NO",
    "name:und_x_variant":[
        "Plevoll",
        "Kl\u00e6vold",
        "Kl\u00e6voll",
        "Klevald",
        "Klevoll"
    ],
    "wof:name":"Klevoll",
    "wof:placetype":"locality"
},
  "geometry": {"coordinates":[5.83333,61.16667],"type":"Point"}
}