{
  "type": "Feature",
  "properties": {
    "gn:country":"NO",
    "gn:fcode":"PPLX",
    "gn:population":0,
    "iso:country":"NO",
    "name:ceb_x_preferred":[
        "Kolbj\u00f8rnsvik"
    ],
    "name:dan_x_preferred":[
        "Kolbj\u00f8rnsvik"
    ],
    "name:eng_x_preferred":[
        "Kolbj\u00f8rnsvik"
    ],
    "name:fra_x_preferred":[
        "Kolbj\u00f8rnsvik"
    ],
    "name:jav_x_preferred":[
        "Kolbj\u00f8rnsvik"
    ],
    "name:msa_x_preferred":[
        "Kolbj\u00f8rnsvik"
    ],
    "name:nld_x_preferred":[
        "Kolbj\u00f8rnsvik"
    ],
    "name:nno_x_preferred":[
        "Kolbj\u00f8rnsvik"
    ],
    "name:nob_x_preferred":[
        "Kolbj\u00f8rnsvik"
    ],
    "name:swe_x_preferred":[
        "Kolbj\u00f8rnsvik"
    ],
    "name:und_x_variant":[
        "Kolbjornsvik"
    ],
    "qs_pg:aaroncc":"NO",
    "qs_pg:gn_country":"NO",
    "qs_pg:gn_fcode":"PPLX",
    "qs_pg:gn_pop":0,
    "qs_pg:name":"Kolbj\u00f8rnsvik",
    "qs_pg:name_adm0":"Norge",
    "qs_pg:name_adm1":"Aust-Agder Fylke",
    "qs_pg:photos":158,
    "qs_pg:photos_1k":32,
    "qs_pg:photos_9k":1,
    "qs_pg:photos_9r":4,
    "qs_pg:photos_all":158,
    "qs_pg:photos_sr":4,
    "qs_pg:pop_sr":0,
    "qs_pg:qs_pg_placetype":"locality_gp_neighbourhood_gn",
    "qs_pg:qs_pg_placetype_gp":"Town",
    "qs_pg:woe_adm0":23424910,
    "woe:adm0_id":23424910,
    "woe:name_adm0":"Norge",
    "woe:name_adm1":"Aust-Agder Fylke",
    "woe:placetype":"Town",
    "wof:name":"Kolbj\u00f8rnsvik",
    "wof:placetype":"neighbourhood"
},
  "geometry": {"coordinates":[8.77056,58.45306],"type":"Point"}
}