{
  "type": "Feature",
  "properties": {
    "gn:admin1_code":"6",
    "gn:admin2_code":"425.0",
    "gn:asciiname":"Knappom",
    "gn:country_code":"NO",
    "gn:dem":180,
    "gn:feature_class":"P",
    "gn:feature_code":"PPL",
    "gn:name":"Knappom",
    "gn:population":0,
    "gn:timezone":"Europe/Oslo",
    "iso:country":"NO",
    "wof:name":"Knappom",
    "wof:placetype":"locality"
},
  "geometry": {"coordinates":[12.04516,60.63536],"type":"Point"}
}