{
  "type": "Feature",
  "properties": {
    "gn:admin1_code":"11",
    "gn:admin2_code":"519.0",
    "gn:asciiname":"Frya",
    "gn:country_code":"NO",
    "gn:dem":199,
    "gn:feature_class":"P",
    "gn:feature_code":"PPL",
    "gn:name":"Frya",
    "gn:population":0,
    "gn:timezone":"Europe/Oslo",
    "iso:country":"NO",
    "wof:name":"Frya",
    "wof:placetype":"locality"
},
  "geometry": {"coordinates":[10.04505,61.54869],"type":"Point"}
}