{
  "type": "Feature",
  "properties": {
    "gn:admin1_code":"8",
    "gn:admin2_code":"1548.0",
    "gn:asciiname":"Askvag",
    "gn:cc2":"NO",
    "gn:country_code":"NO",
    "gn:dem":-9999,
    "gn:feature_class":"P",
    "gn:feature_code":"PPL",
    "gn:name":"Askv\u00e5g",
    "gn:population":0,
    "gn:timezone":"Europe/Oslo",
    "iso:country":"NO",
    "name:und_x_variant":[
        "Askevag",
        "Askv\u00e5g"
    ],
    "wof:name":"Askvag",
    "wof:placetype":"locality"
},
  "geometry": {"coordinates":[7.08333,62.98333],"type":"Point"}
}