{
  "type": "Feature",
  "properties": {
    "gn:admin1_code":"9.0",
    "gn:admin2_code":"1850.0",
    "gn:asciiname":"Fredagsvika",
    "gn:country_code":"NO",
    "gn:dem":220,
    "gn:feature_class":"P",
    "gn:feature_code":"PPL",
    "gn:name":"Fredagsvika",
    "gn:population":0,
    "gn:timezone":"Europe/Oslo",
    "iso:country":"NO",
    "name:nor_x_preferred":[
        "Fredagsvika"
    ],
    "name:smj_x_preferred":[
        "R\u00e1ht\u00e1luokta"
    ],
    "wof:name":"Fredagsvika",
    "wof:placetype":"locality"
},
  "geometry": {"coordinates":[16.30136,68.12768],"type":"Point"}
}