{
  "type": "Feature",
  "properties": {
    "gn:admin1_code":"9",
    "gn:admin2_code":"1804",
    "gn:asciiname":"Reinsletta",
    "gn:country_code":"NO",
    "gn:dem":23,
    "gn:feature_class":"P",
    "gn:feature_code":"PPLL",
    "gn:name":"Reinsletta",
    "gn:population":0,
    "gn:timezone":"Europe/Oslo",
    "iso:country":"NO",
    "name:nor_x_preferred":[
        "Reinsletta"
    ],
    "wof:name":"Reinsletta",
    "wof:placetype":"neighbourhood"
},
  "geometry": {"coordinates":[14.40728,67.28652],"type":"Point"}
}