{
  "type": "Feature",
  "properties": {
    "gn:admin1_code":"18.0",
    "gn:admin2_code":"1940.0",
    "gn:asciiname":"Soleng",
    "gn:country_code":"NO",
    "gn:dem":-9999,
    "gn:feature_class":"P",
    "gn:feature_code":"PPL",
    "gn:name":"Soleng",
    "gn:population":0,
    "gn:timezone":"Europe/Oslo",
    "iso:country":"NO",
    "wof:name":"Soleng",
    "wof:placetype":"locality"
},
  "geometry": {"coordinates":[20.55105,69.59735000000001],"type":"Point"}
}