{
  "type": "Feature",
  "properties": {
    "gn:admin1_code":"11.0",
    "gn:admin2_code":"520.0",
    "gn:asciiname":"Liagrenda",
    "gn:country_code":"NO",
    "gn:dem":526,
    "gn:feature_class":"P",
    "gn:feature_code":"PPL",
    "gn:name":"Liagrenda",
    "gn:population":0,
    "gn:timezone":"Europe/Oslo",
    "iso:country":"NO",
    "name:nor_x_preferred":[
        "Liagrenda"
    ],
    "wof:name":"Liagrenda",
    "wof:placetype":"locality"
},
  "geometry": {"coordinates":[10.13626,61.43859000000001],"type":"Point"}
}