{
  "type": "Feature",
  "properties": {
    "gn:admin1_code":"17",
    "gn:admin2_code":"805.0",
    "gn:asciiname":"Sandoystrand",
    "gn:country_code":"NO",
    "gn:dem":9,
    "gn:feature_class":"P",
    "gn:feature_code":"PPL",
    "gn:name":"Sand\u00f8ystrand",
    "gn:population":0,
    "gn:timezone":"Europe/Oslo",
    "iso:country":"NO",
    "wof:name":"Sandoystrand",
    "wof:placetype":"locality"
},
  "geometry": {"coordinates":[9.72784,59.04993],"type":"Point"}
}