{
  "type": "Feature",
  "properties": {
    "gn:admin1_code":"14",
    "gn:admin2_code":"1111.0",
    "gn:asciiname":"Amot",
    "gn:cc2":"NO",
    "gn:country_code":"NO",
    "gn:dem":133,
    "gn:feature_class":"P",
    "gn:feature_code":"PPL",
    "gn:name":"\u00c5mot",
    "gn:population":0,
    "gn:timezone":"Europe/Oslo",
    "iso:country":"NO",
    "name:und_x_variant":[
        "Aamot",
        "\u00c5mot"
    ],
    "wof:name":"Amot",
    "wof:placetype":"locality"
},
  "geometry": {"coordinates":[6.31667,58.35],"type":"Point"}
}