{
  "type": "Feature",
  "properties": {
    "gn:admin1_code":"4",
    "gn:admin2_code":"605",
    "gn:asciiname":"Balerud",
    "gn:country_code":"NO",
    "gn:dem":180,
    "gn:feature_class":"P",
    "gn:feature_code":"PPL",
    "gn:name":"B\u00e5lerud",
    "gn:population":0,
    "gn:timezone":"Europe/Oslo",
    "iso:country":"NO",
    "name:nor_x_preferred":[
        "B\u00e5lerud"
    ],
    "wof:name":"Balerud",
    "wof:placetype":"locality"
},
  "geometry": {"coordinates":[10.2004,60.18354],"type":"Point"}
}