{
  "type": "Feature",
  "properties": {
    "gn:admin1_code":"4.0",
    "gn:admin2_code":"620.0",
    "gn:asciiname":"Geilo hyttegrend",
    "gn:country_code":"NO",
    "gn:dem":800,
    "gn:feature_class":"P",
    "gn:feature_code":"PPL",
    "gn:name":"Geilo hyttegrend",
    "gn:population":0,
    "gn:timezone":"Europe/Oslo",
    "iso:country":"NO",
    "name:nor_x_preferred":[
        "Geilo hyttegrend"
    ],
    "wof:name":"Geilo hyttegrend",
    "wof:placetype":"locality"
},
  "geometry": {"coordinates":[8.19571,60.51926],"type":"Point"}
}