{
  "type": "Feature",
  "properties": {
    "gn:admin1_code":"9",
    "gn:admin2_code":"1848.0",
    "gn:asciiname":"Dyping",
    "gn:cc2":"NO",
    "gn:country_code":"NO",
    "gn:dem":173,
    "gn:feature_class":"P",
    "gn:feature_code":"PPL",
    "gn:name":"Dyping",
    "gn:population":0,
    "gn:timezone":"Europe/Oslo",
    "iso:country":"NO",
    "name:und_x_variant":[
        "Djuping",
        "Dypingen",
        "Dyping"
    ],
    "wof:name":"Dyping",
    "wof:placetype":"locality"
},
  "geometry": {"coordinates":[15.33333,67.90000000000001],"type":"Point"}
}