{
  "type": "Feature",
  "properties": {
    "gn:admin1_code":"15.0",
    "gn:admin2_code":"1429.0",
    "gn:asciiname":"Strand",
    "gn:country_code":"NO",
    "gn:dem":41,
    "gn:feature_class":"P",
    "gn:feature_code":"PPL",
    "gn:name":"Strand",
    "gn:population":0,
    "gn:timezone":"Europe/Oslo",
    "iso:country":"NO",
    "wof:name":"Strand",
    "wof:placetype":"locality"
},
  "geometry": {"coordinates":[5.48333,61.36666999999999],"type":"Point"}
}