{
  "type": "Feature",
  "properties": {
    "iso:country":"NO",
    "qs_pg:aaroncc":"NO",
    "qs_pg:name":"Sor-Jan",
    "qs_pg:name_adm0":"Svalbard",
    "qs_pg:name_adm1":"Jan Mayen",
    "qs_pg:photos":5,
    "qs_pg:photos_1k":1,
    "qs_pg:photos_9k":1,
    "qs_pg:photos_9r":1,
    "qs_pg:photos_all":5,
    "qs_pg:photos_sr":1,
    "qs_pg:pop_sr":0,
    "qs_pg:qs_pg_placetype":"locality",
    "qs_pg:qs_pg_placetype_gp":"Town",
    "qs_pg:woe_adm0":28289413,
    "woe:adm0_id":28289413,
    "woe:name_adm0":"Svalbard",
    "woe:name_adm1":"Jan Mayen",
    "woe:placetype":"Town",
    "wof:name":"Sor-Jan",
    "wof:placetype":"locality"
},
  "geometry": {"coordinates":[-8.97583,70.858636],"type":"Point"}
}