{
  "type": "Feature",
  "properties": {
    "gn:gn_country":"NO",
    "gn:gn_fcode":"PPL",
    "gn:gn_pop":0,
    "iso:country":"NO",
    "name:eng_x_preferred":[
        "Kj\u00f8vangen"
    ],
    "name:fra_x_preferred":[
        "Kj\u00f8vangen"
    ],
    "name:jav_x_preferred":[
        "Kj\u00f8vangen"
    ],
    "name:msa_x_preferred":[
        "Kj\u00f8vangen"
    ],
    "name:nld_x_preferred":[
        "Kj\u00f8vangen"
    ],
    "qs_pg:aaroncc":"NO",
    "qs_pg:gn_country":"NO",
    "qs_pg:gn_fcode":"PPL",
    "qs_pg:gn_pop":0,
    "qs_pg:name":"Kj\u00f8vangen",
    "qs_pg:name_adm0":"Norge",
    "qs_pg:name_adm1":"Akershus Fylke",
    "qs_pg:photos":17,
    "qs_pg:photos_1k":3,
    "qs_pg:photos_9k":1,
    "qs_pg:photos_9r":1,
    "qs_pg:photos_all":17,
    "qs_pg:photos_sr":1,
    "qs_pg:pop_sr":0,
    "qs_pg:qs_pg_placetype":"locality",
    "qs_pg:qs_pg_placetype_gp":"Town",
    "qs_pg:woe_adm0":23424910,
    "woe:adm0_id":23424910,
    "woe:name_adm0":"Norge",
    "woe:name_adm1":"Akershus Fylke",
    "woe:placetype":"Town",
    "wof:name":"Kj\u00f8vangen",
    "wof:placetype":"locality"
},
  "geometry": {"coordinates":[10.66611,59.54056],"type":"Point"}
}