{
  "type": "Feature",
  "properties": {
    "gn:admin1_code":"18.0",
    "gn:admin2_code":"1925.0",
    "gn:asciiname":"Gumpedalen",
    "gn:country_code":"NO",
    "gn:dem":227,
    "gn:feature_class":"P",
    "gn:feature_code":"PPL",
    "gn:name":"Gumpedalen",
    "gn:population":0,
    "gn:timezone":"Europe/Oslo",
    "iso:country":"NO",
    "name:nor_x_preferred":[
        "Gumpedalen"
    ],
    "wof:name":"Gumpedalen",
    "wof:placetype":"locality"
},
  "geometry": {"coordinates":[17.95877999999999,69.04671],"type":"Point"}
}