{
  "type": "Feature",
  "properties": {
    "gn:admin1_code":"19",
    "gn:admin2_code":"1046.0",
    "gn:asciiname":"Hompland",
    "gn:country_code":"NO",
    "gn:dem":110,
    "gn:feature_class":"P",
    "gn:feature_code":"PPL",
    "gn:name":"Hompland",
    "gn:population":0,
    "gn:timezone":"Europe/Oslo",
    "iso:country":"NO",
    "wof:name":"Hompland",
    "wof:placetype":"locality"
},
  "geometry": {"coordinates":[6.73333,58.71666999999999],"type":"Point"}
}