{
  "type": "Feature",
  "properties": {
    "gn:admin1_code":"21.0",
    "gn:admin2_code":"5017.0",
    "gn:asciiname":"Rommen",
    "gn:country_code":"NO",
    "gn:dem":60,
    "gn:feature_class":"P",
    "gn:feature_code":"PPL",
    "gn:name":"R\u00f8mmen",
    "gn:population":0,
    "gn:timezone":"Europe/Oslo",
    "iso:country":"NO",
    "wof:name":"Rommen",
    "wof:placetype":"locality"
},
  "geometry": {"coordinates":[9.85999,63.86683000000001],"type":"Point"}
}