{
  "type": "Feature",
  "properties": {
    "gn:admin1_code":"15",
    "gn:admin2_code":"1418.0",
    "gn:asciiname":"Lane",
    "gn:cc2":"NO",
    "gn:country_code":"NO",
    "gn:dem":918,
    "gn:feature_class":"P",
    "gn:feature_code":"PPL",
    "gn:name":"L\u00e5ne",
    "gn:population":0,
    "gn:timezone":"Europe/Oslo",
    "iso:country":"NO",
    "name:ara_x_preferred":[
        "\u062d\u0627\u0631\u0629"
    ],
    "name:bos_x_preferred":[
        "Saobra\u0107ajna traka"
    ],
    "name:cat_x_preferred":[
        "Carril"
    ],
    "name:dan_x_preferred":[
        "K\u00f8rebane"
    ],
    "name:deu_x_preferred":[
        "Fahrstreifen"
    ],
    "name:epo_x_preferred":[
        "Leno"
    ],
    "name:eus_x_preferred":[
        "Lerro"
    ],
    "name:fas_x_preferred":[
        "\u062e\u0637"
    ],
    "name:fin_x_preferred":[
        "Ajokaista"
    ],
    "name:glg_x_preferred":[
        "Carril"
    ],
    "name:isl_x_preferred":[
        "Akrein"
    ],
    "name:lat_x_preferred":[
        "Curriculum"
    ],
    "name:mar_x_preferred":[
        "\u092e\u093e\u0930\u094d\u0917\u093f\u0915\u093e"
    ],
    "name:msa_x_preferred":[
        "Lorong"
    ],
    "name:nld_x_preferred":[
        "Rijstrook"
    ],
    "name:nor_x_preferred":[
        "Kj\u00f8refelt"
    ],
    "name:pol_x_preferred":[
        "Pas ruchu"
    ],
    "name:rus_x_preferred":[
        "\u041f\u043e\u043b\u043e\u0441\u0430 \u0434\u0432\u0438\u0436\u0435\u043d\u0438\u044f"
    ],
    "name:spa_x_preferred":[
        "Carril"
    ],
    "name:srp_x_preferred":[
        "\u0421\u0430\u043e\u0431\u0440\u0430\u045b\u0430\u0458\u043d\u0430 \u0442\u0440\u0430\u043a\u0430"
    ],
    "name:swe_x_preferred":[
        "K\u00f6rf\u00e4lt"
    ],
    "name:tha_x_preferred":[
        "\u0e0a\u0e48\u0e2d\u0e07\u0e08\u0e23\u0e32\u0e08\u0e23"
    ],
    "name:ukr_x_preferred":[
        "\u0421\u043c\u0443\u0433\u0430 \u0440\u0443\u0445\u0443"
    ],
    "name:und_x_variant":[
        "L\u00e5nefjord",
        "L\u00e5ne"
    ],
    "name:urd_x_preferred":[
        "\u0631\u0648\u06cc\u06c1"
    ],
    "wof:name":"Lane",
    "wof:placetype":"locality"
},
  "geometry": {"coordinates":[6.23333,61.18333000000001],"type":"Point"}
}