{
  "type": "Feature",
  "properties": {
    "gn:admin1_code":"15",
    "gn:admin2_code":"1418.0",
    "gn:asciiname":"Lane",
    "gn:cc2":"NO",
    "gn:country_code":"NO",
    "gn:dem":918,
    "gn:feature_class":"P",
    "gn:feature_code":"PPL",
    "gn:name":"L\u00e5ne",
    "gn:population":0,
    "gn:timezone":"Europe/Oslo",
    "iso:country":"NO",
    "name:und_x_variant":[
        "L\u00e5nefjord",
        "L\u00e5ne"
    ],
    "wof:name":"Lane",
    "wof:placetype":"locality"
},
  "geometry": {"coordinates":[6.23333,61.18333000000001],"type":"Point"}
}