{
  "type": "Feature",
  "properties": {
    "gn:admin1_code":"4.0",
    "gn:admin2_code":"628.0",
    "gn:asciiname":"Stromhella",
    "gn:country_code":"NO",
    "gn:dem":15,
    "gn:feature_class":"P",
    "gn:feature_code":"PPL",
    "gn:name":"Str\u00f8mhella",
    "gn:population":0,
    "gn:timezone":"Europe/Oslo",
    "iso:country":"NO",
    "name:nor_x_preferred":[
        "Str\u00f8mhella"
    ],
    "wof:name":"Stromhella",
    "wof:placetype":"locality"
},
  "geometry": {"coordinates":[10.42054,59.55541],"type":"Point"}
}