{
  "type": "Feature",
  "properties": {
    "gn:admin1_code":"21.0",
    "gn:admin2_code":"5011.0",
    "gn:asciiname":"Lenes",
    "gn:country_code":"NO",
    "gn:dem":33,
    "gn:feature_class":"P",
    "gn:feature_code":"PPL",
    "gn:name":"Lenes",
    "gn:population":0,
    "gn:timezone":"Europe/Oslo",
    "iso:country":"NO",
    "name:nor_x_preferred":[
        "Lenes"
    ],
    "wof:name":"Lenes",
    "wof:placetype":"locality"
},
  "geometry": {"coordinates":[9.00689,63.25914],"type":"Point"}
}