{
  "type": "Feature",
  "properties": {
    "gn:country":"NO",
    "gn:fcode":"PPL",
    "gn:population":0,
    "iso:country":"NO",
    "name:eng_x_preferred":[
        "Stamneshella"
    ],
    "name:fra_x_preferred":[
        "Stamneshella"
    ],
    "name:jav_x_preferred":[
        "Stamneshella"
    ],
    "name:msa_x_preferred":[
        "Stamneshella"
    ],
    "name:nld_x_preferred":[
        "Stamneshella"
    ],
    "name:nno_x_preferred":[
        "Stamnes"
    ],
    "name:nob_x_preferred":[
        "Stamnes"
    ],
    "qs_pg:aaroncc":"NO",
    "qs_pg:gn_country":"NO",
    "qs_pg:gn_fcode":"PPL",
    "qs_pg:gn_pop":0,
    "qs_pg:name":"Stamnes",
    "qs_pg:name_adm0":"Norge",
    "qs_pg:name_adm1":"Hordaland Fylke",
    "qs_pg:photos":43,
    "qs_pg:photos_1k":9,
    "qs_pg:photos_9k":1,
    "qs_pg:photos_9r":2,
    "qs_pg:photos_all":43,
    "qs_pg:photos_sr":2,
    "qs_pg:pop_sr":0,
    "qs_pg:qs_pg_placetype":"locality",
    "qs_pg:qs_pg_placetype_gp":"Town",
    "qs_pg:woe_adm0":23424910,
    "woe:adm0_id":23424910,
    "woe:name_adm0":"Norge",
    "woe:name_adm1":"Hordaland Fylke",
    "woe:placetype":"Town",
    "wof:name":"Stamnes",
    "wof:placetype":"locality"
},
  "geometry": {"coordinates":[5.75,60.66667],"type":"Point"}
}