{
  "type": "Feature",
  "properties": {
    "gn:admin1_code":"7",
    "gn:admin2_code":"1242.0",
    "gn:asciiname":"Litangen",
    "gn:country_code":"NO",
    "gn:dem":1,
    "gn:feature_class":"P",
    "gn:feature_code":"PPL",
    "gn:name":"Litangen",
    "gn:population":0,
    "gn:timezone":"Europe/Oslo",
    "iso:country":"NO",
    "wof:name":"Litangen",
    "wof:placetype":"locality"
},
  "geometry": {"coordinates":[5.68333,60.36666999999999],"type":"Point"}
}