{
  "type": "Feature",
  "properties": {
    "gn:admin1_code":"9",
    "gn:admin2_code":"1859",
    "gn:asciiname":"Sund",
    "gn:country_code":"NO",
    "gn:dem":-9999,
    "gn:feature_class":"P",
    "gn:feature_code":"PPLL",
    "gn:name":"Sund",
    "gn:population":0,
    "gn:timezone":"Europe/Oslo",
    "iso:country":"NO",
    "name:nor_x_preferred":[
        "Sund"
    ],
    "wof:name":"Sund",
    "wof:placetype":"locality"
},
  "geometry": {"coordinates":[13.20789,68.00518000000001],"type":"Point"}
}