{
  "type": "Feature",
  "properties": {
    "gn:admin1_code":"9",
    "gn:admin2_code":"1859",
    "gn:asciiname":"Sund",
    "gn:country_code":"NO",
    "gn:dem":-9999,
    "gn:feature_class":"P",
    "gn:feature_code":"PPLL",
    "gn:name":"Sund",
    "gn:population":0,
    "gn:timezone":"Europe/Oslo",
    "iso:country":"NO",
    "name:ceb_x_preferred":[
        "Sund"
    ],
    "name:dan_x_preferred":[
        "Sund"
    ],
    "name:deu_x_preferred":[
        "Sund"
    ],
    "name:eus_x_preferred":[
        "Sund"
    ],
    "name:fao_x_preferred":[
        "Sund"
    ],
    "name:fin_x_preferred":[
        "Sund"
    ],
    "name:fra_x_preferred":[
        "Sund"
    ],
    "name:hrv_x_preferred":[
        "Sund"
    ],
    "name:hun_x_preferred":[
        "Sund"
    ],
    "name:isl_x_preferred":[
        "Sund"
    ],
    "name:ita_x_preferred":[
        "Sund"
    ],
    "name:lim_x_preferred":[
        "Sund"
    ],
    "name:nld_x_preferred":[
        "Sund"
    ],
    "name:nno_x_preferred":[
        "Sund"
    ],
    "name:nor_x_preferred":[
        "Sund"
    ],
    "name:ron_x_preferred":[
        "Sund"
    ],
    "name:sco_x_preferred":[
        "Sund"
    ],
    "name:sme_x_preferred":[
        "Sund"
    ],
    "name:spa_x_preferred":[
        "Sund"
    ],
    "name:swe_x_preferred":[
        "Sund"
    ],
    "wof:name":"Sund",
    "wof:placetype":"locality"
},
  "geometry": {"coordinates":[13.20789,68.00518000000001],"type":"Point"}
}