{
  "type": "Feature",
  "properties": {
    "gn:admin1_code":"18",
    "gn:admin2_code":"1936.0",
    "gn:asciiname":"Gammnes",
    "gn:cc2":"NO",
    "gn:country_code":"NO",
    "gn:dem":1,
    "gn:feature_class":"P",
    "gn:feature_code":"PPL",
    "gn:name":"Gammnes",
    "gn:population":0,
    "gn:timezone":"Europe/Oslo",
    "iso:country":"NO",
    "name:und_x_variant":[
        "Gamnes",
        "Gammnes"
    ],
    "wof:name":"Gammnes",
    "wof:placetype":"locality"
},
  "geometry": {"coordinates":[19.48068,69.9091],"type":"Point"}
}