{
  "type": "Feature",
  "properties": {
    "gn:country":"NO",
    "gn:fcode":"PPL",
    "gn:population":0,
    "iso:country":"NO",
    "name:dan_x_preferred":[
        "Gj\u00f8ra"
    ],
    "name:eng_x_preferred":[
        "Gj\u00f8ra"
    ],
    "name:fra_x_preferred":[
        "Gj\u00f8ra"
    ],
    "name:jav_x_preferred":[
        "Gj\u00f8ra"
    ],
    "name:msa_x_preferred":[
        "Gj\u00f8ra"
    ],
    "name:nld_x_preferred":[
        "Gj\u00f8ra"
    ],
    "name:nno_x_preferred":[
        "Gj\u00f8ra"
    ],
    "name:nob_x_preferred":[
        "Gj\u00f8ra"
    ],
    "qs_pg:aaroncc":"NO",
    "qs_pg:gn_country":"NO",
    "qs_pg:gn_fcode":"PPL",
    "qs_pg:gn_pop":0,
    "qs_pg:name":"Gj\u00f8ra",
    "qs_pg:name_adm0":"Norge",
    "qs_pg:name_adm1":"M\u00f8re og Romsdal Fylke",
    "qs_pg:photos_9k":1,
    "qs_pg:photos_9r":1,
    "qs_pg:photos_all":2,
    "qs_pg:photos_sr":0,
    "qs_pg:pop_sr":4,
    "qs_pg:qs_pg_placetype":"locality",
    "qs_pg:qs_pg_placetype_gp":"Town",
    "qs_pg:woe_adm0":23424910,
    "woe:adm0_id":23424910,
    "woe:name_adm0":"Norge",
    "woe:name_adm1":"M\u00f8re og Romsdal Fylke",
    "woe:placetype":"Town",
    "wof:name":"Gj\u00f8ra",
    "wof:placetype":"locality"
},
  "geometry": {"coordinates":[9.11667,62.55],"type":"Point"}
}