{
  "type": "Feature",
  "properties": {
    "gn:admin1_code":"15",
    "gn:admin2_code":"1413.0",
    "gn:asciiname":"Berge",
    "gn:country_code":"NO",
    "gn:dem":200,
    "gn:feature_class":"P",
    "gn:feature_code":"PPL",
    "gn:name":"Berge",
    "gn:population":0,
    "gn:timezone":"Europe/Oslo",
    "iso:country":"NO",
    "wof:name":"Berge",
    "wof:placetype":"locality"
},
  "geometry": {"coordinates":[5.31667,61.18333000000001],"type":"Point"}
}