{
  "type": "Feature",
  "properties": {
    "gn:admin1_code":"17",
    "gn:admin2_code":"805",
    "gn:asciiname":"Enger",
    "gn:country_code":"NO",
    "gn:dem":20,
    "gn:feature_class":"P",
    "gn:feature_code":"PPLL",
    "gn:name":"Enger",
    "gn:population":0,
    "gn:timezone":"Europe/Oslo",
    "iso:country":"NO",
    "name:cat_x_preferred":[
        "Enger"
    ],
    "name:deu_x_preferred":[
        "Enger"
    ],
    "name:epo_x_preferred":[
        "Enger"
    ],
    "name:eus_x_preferred":[
        "Enger"
    ],
    "name:fra_x_preferred":[
        "Enger"
    ],
    "name:fry_x_preferred":[
        "Enger"
    ],
    "name:hun_x_preferred":[
        "Enger"
    ],
    "name:ita_x_preferred":[
        "Enger"
    ],
    "name:jpn_x_preferred":[
        "\u30a8\u30f3\u30ac\u30fc"
    ],
    "name:msa_x_preferred":[
        "Enger"
    ],
    "name:nds_x_preferred":[
        "Enger"
    ],
    "name:nld_x_preferred":[
        "Enger"
    ],
    "name:nor_x_preferred":[
        "Enger"
    ],
    "name:pol_x_preferred":[
        "Enger"
    ],
    "name:por_x_preferred":[
        "Enger"
    ],
    "name:ron_x_preferred":[
        "Enger"
    ],
    "name:rus_x_preferred":[
        "\u042d\u043d\u0433\u0435\u0440"
    ],
    "name:spa_x_preferred":[
        "Enger"
    ],
    "name:srp_x_preferred":[
        "\u0415\u043d\u0433\u0435\u0440"
    ],
    "name:swe_x_preferred":[
        "Enger"
    ],
    "name:tur_x_preferred":[
        "Enger"
    ],
    "name:ukr_x_preferred":[
        "\u0415\u043d\u0433\u0435\u0440"
    ],
    "name:uzb_x_preferred":[
        "Enger"
    ],
    "name:vol_x_preferred":[
        "Enger"
    ],
    "name:war_x_preferred":[
        "Enger"
    ],
    "wof:name":"Enger",
    "wof:placetype":"locality"
},
  "geometry": {"coordinates":[9.68969,59.1236],"type":"Point"}
}