{
  "type": "Feature",
  "properties": {
    "gn:admin1_code":"17",
    "gn:admin2_code":"805",
    "gn:asciiname":"Enger",
    "gn:country_code":"NO",
    "gn:dem":20,
    "gn:feature_class":"P",
    "gn:feature_code":"PPLL",
    "gn:name":"Enger",
    "gn:population":0,
    "gn:timezone":"Europe/Oslo",
    "iso:country":"NO",
    "name:nor_x_preferred":[
        "Enger"
    ],
    "wof:name":"Enger",
    "wof:placetype":"locality"
},
  "geometry": {"coordinates":[9.68969,59.1236],"type":"Point"}
}