{
  "type": "Feature",
  "properties": {
    "gn:gn_country":"NO",
    "gn:gn_fcode":"PPL",
    "gn:gn_pop":269,
    "gn:population":269,
    "iso:country":"NO",
    "name:bul_x_preferred":[
        "\u0421\u043e\u043a\u043d\u0435\u0434\u0430\u043b"
    ],
    "name:dut_x_preferred":[
        "Soknedal"
    ],
    "name:eng_x_preferred":[
        "Soknedal"
    ],
    "name:fre_x_preferred":[
        "Soknedal"
    ],
    "name:may_x_preferred":[
        "Soknedal"
    ],
    "name:nno_x_preferred":[
        "Soknedal"
    ],
    "name:nob_x_preferred":[
        "Soknedal"
    ],
    "name:rum_x_preferred":[
        "Soknedal"
    ],
    "name:swe_x_preferred":[
        "Soknedal"
    ],
    "qs_pg:aaroncc":"NO",
    "qs_pg:gn_country":"NO",
    "qs_pg:gn_fcode":"PPL",
    "qs_pg:gn_pop":269,
    "qs_pg:name":"Soknedal",
    "qs_pg:name_adm0":"Norge",
    "qs_pg:name_adm1":"S\u00f8r-Tr\u00f8ndelag Fylke",
    "qs_pg:photos_9k":1,
    "qs_pg:photos_9r":4,
    "qs_pg:photos_all":155,
    "qs_pg:photos_sr":0,
    "qs_pg:pop_sr":2,
    "qs_pg:qs_pg_placetype":"locality",
    "qs_pg:qs_pg_placetype_gp":"Town",
    "qs_pg:woe_adm0":23424910,
    "woe:adm0_id":23424910,
    "woe:name_adm0":"Norge",
    "woe:name_adm1":"S\u00f8r-Tr\u00f8ndelag Fylke",
    "woe:placetype":"Town",
    "wof:name":"Soknedal",
    "wof:placetype":"locality",
    "wof:population":269
},
  "geometry": {"coordinates":[10.18333,62.95],"type":"Point"}
}