{
  "type": "Feature",
  "properties": {
    "gn:admin1_code":"7",
    "gn:admin2_code":"1228.0",
    "gn:asciiname":"Hildal",
    "gn:country_code":"NO",
    "gn:dem":139,
    "gn:feature_class":"P",
    "gn:feature_code":"PPL",
    "gn:name":"Hildal",
    "gn:population":0,
    "gn:timezone":"Europe/Oslo",
    "iso:country":"NO",
    "wof:name":"Hildal",
    "wof:placetype":"locality"
},
  "geometry": {"coordinates":[6.56667,59.98333],"type":"Point"}
}