{
  "type": "Feature",
  "properties": {
    "gn:admin1_code":"18.0",
    "gn:admin2_code":"1938.0",
    "gn:asciiname":"Ytre Berg",
    "gn:country_code":"NO",
    "gn:dem":103,
    "gn:feature_class":"P",
    "gn:feature_code":"PPL",
    "gn:name":"Ytre Berg",
    "gn:population":0,
    "gn:timezone":"Europe/Oslo",
    "iso:country":"NO",
    "wof:name":"Ytre Berg",
    "wof:placetype":"locality"
},
  "geometry": {"coordinates":[19.83333,69.65000000000001],"type":"Point"}
}