{
  "type": "Feature",
  "properties": {
    "gn:gn_country":"NO",
    "gn:gn_fcode":"PPL",
    "gn:gn_pop":0,
    "iso:country":"NO",
    "name:eng_x_preferred":[
        "B\u00e5tst\u00f8"
    ],
    "name:fra_x_preferred":[
        "B\u00e5tst\u00f8"
    ],
    "name:jav_x_preferred":[
        "B\u00e5tst\u00f8"
    ],
    "name:msa_x_preferred":[
        "B\u00e5tst\u00f8"
    ],
    "name:nld_x_preferred":[
        "B\u00e5tst\u00f8"
    ],
    "name:nno_x_preferred":[
        "B\u00e5tst\u00f8"
    ],
    "name:nob_x_preferred":[
        "B\u00e5tst\u00f8"
    ],
    "name:ron_x_preferred":[
        "B\u00e5tst\u00f8"
    ],
    "name:swe_x_preferred":[
        "B\u00e5tst\u00f8"
    ],
    "name:unk_x_variant":[
        "Baatst\u00f6"
    ],
    "qs_pg:aaroncc":"NO",
    "qs_pg:gn_country":"NO",
    "qs_pg:gn_fcode":"PPL",
    "qs_pg:gn_pop":0,
    "qs_pg:name":"B\u00e5tst\u00f8",
    "qs_pg:name_adm0":"Norge",
    "qs_pg:name_adm1":"Buskerud Fylke",
    "qs_pg:photos":191,
    "qs_pg:photos_1k":39,
    "qs_pg:photos_9k":1,
    "qs_pg:photos_9r":4,
    "qs_pg:photos_all":191,
    "qs_pg:photos_sr":4,
    "qs_pg:pop_sr":0,
    "qs_pg:qs_pg_placetype":"locality",
    "qs_pg:qs_pg_placetype_gp":"Town",
    "qs_pg:woe_adm0":23424910,
    "woe:adm0_id":23424910,
    "woe:name_adm0":"Norge",
    "woe:name_adm1":"Buskerud Fylke",
    "woe:placetype":"Town",
    "wof:name":"B\u00e5tst\u00f8",
    "wof:placetype":"locality"
},
  "geometry": {"coordinates":[10.51806,59.72417],"type":"Point"}
}