{
  "type": "Feature",
  "properties": {
    "gn:admin1_code":"21.0",
    "gn:admin2_code":"5029.0",
    "gn:asciiname":"Furuvika",
    "gn:country_code":"NO",
    "gn:dem":100,
    "gn:feature_class":"P",
    "gn:feature_code":"PPL",
    "gn:name":"Furuvika",
    "gn:population":0,
    "gn:timezone":"Europe/Oslo",
    "iso:country":"NO",
    "name:nor_x_preferred":[
        "Furuvika"
    ],
    "wof:name":"Furuvika",
    "wof:placetype":"locality"
},
  "geometry": {"coordinates":[10.11991,63.3238],"type":"Point"}
}