{
  "type": "Feature",
  "properties": {
    "gn:admin1_code":"15",
    "gn:admin2_code":"1428.0",
    "gn:asciiname":"Lovik",
    "gn:cc2":"NO",
    "gn:country_code":"NO",
    "gn:dem":20,
    "gn:feature_class":"P",
    "gn:feature_code":"PPL",
    "gn:name":"L\u00f8vik",
    "gn:population":0,
    "gn:timezone":"Europe/Oslo",
    "iso:country":"NO",
    "name:und_x_variant":[
        "L\u00f6vvik",
        "L\u00f8vik"
    ],
    "wof:name":"Lovik",
    "wof:placetype":"locality"
},
  "geometry": {"coordinates":[5.45,61.45],"type":"Point"}
}