{
  "type": "Feature",
  "properties": {
    "gn:admin1_code":"21.0",
    "gn:admin2_code":"5045.0",
    "gn:asciiname":"Valdskra",
    "gn:country_code":"NO",
    "gn:dem":20,
    "gn:feature_class":"P",
    "gn:feature_code":"PPL",
    "gn:name":"Valdskr\u00e5",
    "gn:population":0,
    "gn:timezone":"Europe/Oslo",
    "iso:country":"NO",
    "name:nor_x_preferred":[
        "Valdskr\u00e5"
    ],
    "wof:name":"Valdskra",
    "wof:placetype":"locality"
},
  "geometry": {"coordinates":[12.15331,64.46728],"type":"Point"}
}