{
  "type": "Feature",
  "properties": {
    "gn:admin1_code":"11.0",
    "gn:admin2_code":"542.0",
    "gn:asciiname":"Breidsetstolan",
    "gn:country_code":"NO",
    "gn:dem":992,
    "gn:feature_class":"P",
    "gn:feature_code":"PPL",
    "gn:name":"Breidsetst\u00f8lan",
    "gn:population":0,
    "gn:timezone":"Europe/Oslo",
    "iso:country":"NO",
    "name:nor_x_preferred":[
        "Breidsetst\u00f8lan"
    ],
    "wof:name":"Breidsetstolan",
    "wof:placetype":"locality"
},
  "geometry": {"coordinates":[9.12443,60.93292],"type":"Point"}
}