{
  "type": "Feature",
  "properties": {
    "gn:admin1_code":"7",
    "gn:admin2_code":"1260.0",
    "gn:asciiname":"Haugland",
    "gn:country_code":"NO",
    "gn:dem":25,
    "gn:feature_class":"P",
    "gn:feature_code":"PPL",
    "gn:name":"Haugland",
    "gn:population":0,
    "gn:timezone":"Europe/Oslo",
    "iso:country":"NO",
    "name:ceb_x_preferred":[
        "Haugland"
    ],
    "name:jav_x_preferred":[
        "Haugland"
    ],
    "name:msa_x_preferred":[
        "Haugland"
    ],
    "name:nld_x_preferred":[
        "Haugland"
    ],
    "name:nor_x_preferred":[
        "Haugland"
    ],
    "name:ron_x_preferred":[
        "Haugland"
    ],
    "wof:name":"Haugland",
    "wof:placetype":"locality"
},
  "geometry": {"coordinates":[4.9331,60.69448000000001],"type":"Point"}
}