{
  "type": "Feature",
  "properties": {
    "gn:admin1_code":"9",
    "gn:admin2_code":"1868.0",
    "gn:asciiname":"Gisloy",
    "gn:country_code":"NO",
    "gn:dem":1,
    "gn:feature_class":"P",
    "gn:feature_code":"PPL",
    "gn:name":"Gisl\u00f8y",
    "gn:population":0,
    "gn:timezone":"Europe/Oslo",
    "iso:country":"NO",
    "wof:name":"Gisloy",
    "wof:placetype":"locality"
},
  "geometry": {"coordinates":[15.27266,68.93516],"type":"Point"}
}