{
  "type": "Feature",
  "properties": {
    "gn:admin1_code":"11.0",
    "gn:admin2_code":"522.0",
    "gn:asciiname":"Hornsjosaetra",
    "gn:country_code":"NO",
    "gn:dem":880,
    "gn:feature_class":"P",
    "gn:feature_code":"PPL",
    "gn:name":"Hornsj\u00f8s\u00e6tra",
    "gn:population":0,
    "gn:timezone":"Europe/Oslo",
    "iso:country":"NO",
    "name:nor_x_preferred":[
        "Hornsj\u00f8s\u00e6tra"
    ],
    "wof:name":"Hornsjosaetra",
    "wof:placetype":"locality"
},
  "geometry": {"coordinates":[9.82834,61.25855],"type":"Point"}
}