{
  "type": "Feature",
  "properties": {
    "gn:admin1_code":"9",
    "gn:admin2_code":"1848",
    "gn:asciiname":"Helnes",
    "gn:country_code":"NO",
    "gn:dem":3,
    "gn:feature_class":"P",
    "gn:feature_code":"PPLL",
    "gn:name":"Helnes",
    "gn:population":0,
    "gn:timezone":"Europe/Oslo",
    "iso:country":"NO",
    "name:nor_x_preferred":[
        "Helnes"
    ],
    "wof:name":"Helnes",
    "wof:placetype":"locality"
},
  "geometry": {"coordinates":[14.77342,67.73085999999999],"type":"Point"}
}