{
  "type": "Feature",
  "properties": {
    "gn:admin1_code":"21",
    "gn:admin2_code":"5023",
    "gn:asciiname":"Stensmoen",
    "gn:country_code":"NO",
    "gn:dem":360,
    "gn:feature_class":"P",
    "gn:feature_code":"PPLL",
    "gn:name":"Stensmoen",
    "gn:population":0,
    "gn:timezone":"Europe/Oslo",
    "iso:country":"NO",
    "name:nor_x_preferred":[
        "Stensmoen"
    ],
    "wof:name":"Stensmoen",
    "wof:placetype":"locality"
},
  "geometry": {"coordinates":[9.70882,63.12928],"type":"Point"}
}