{
  "type": "Feature",
  "properties": {
    "gn:admin1_code":"9.0",
    "gn:admin2_code":"1868.0",
    "gn:asciiname":"Sorsand",
    "gn:country_code":"NO",
    "gn:dem":60,
    "gn:feature_class":"P",
    "gn:feature_code":"PPL",
    "gn:name":"S\u00f8rsand",
    "gn:population":0,
    "gn:timezone":"Europe/Oslo",
    "iso:country":"NO",
    "wof:name":"Sorsand",
    "wof:placetype":"locality"
},
  "geometry": {"coordinates":[14.85,68.91667],"type":"Point"}
}