{
  "type": "Feature",
  "properties": {
    "gn:admin1_code":"21.0",
    "gn:admin2_code":"5001.0",
    "gn:asciiname":"Klefstadhaugen",
    "gn:country_code":"NO",
    "gn:dem":130,
    "gn:feature_class":"P",
    "gn:feature_code":"PPL",
    "gn:name":"Klefstadhaugen",
    "gn:population":0,
    "gn:timezone":"Europe/Oslo",
    "iso:country":"NO",
    "name:nor_x_preferred":[
        "Klefstadhaugen"
    ],
    "name:nor_x_variant":[
        "Berghaugen",
        "Haugan"
    ],
    "wof:name":"Klefstadhaugen",
    "wof:placetype":"locality"
},
  "geometry": {"coordinates":[10.18324,63.43351],"type":"Point"}
}