{
  "type": "Feature",
  "properties": {
    "gn:admin1_code":"18.0",
    "gn:admin2_code":"1933.0",
    "gn:asciiname":"Storli",
    "gn:country_code":"NO",
    "gn:dem":93,
    "gn:feature_class":"P",
    "gn:feature_code":"PPL",
    "gn:name":"Storli",
    "gn:population":0,
    "gn:timezone":"Europe/Oslo",
    "iso:country":"NO",
    "wof:name":"Storli",
    "wof:placetype":"locality"
},
  "geometry": {"coordinates":[18.75,69.26666999999999],"type":"Point"}
}