{
  "type": "Feature",
  "properties": {
    "gn:admin1_code":"6",
    "gn:admin2_code":"420.0",
    "gn:asciiname":"Gaustad",
    "gn:country_code":"NO",
    "gn:dem":145,
    "gn:feature_class":"P",
    "gn:feature_code":"PPL",
    "gn:name":"Gaustad",
    "gn:population":0,
    "gn:timezone":"Europe/Oslo",
    "iso:country":"NO",
    "name:dan_x_preferred":[
        "Gaustad"
    ],
    "name:nor_x_preferred":[
        "Gaustad"
    ],
    "wof:name":"Gaustad",
    "wof:placetype":"locality"
},
  "geometry": {"coordinates":[12.14648,59.96402],"type":"Point"}
}