{
  "type": "Feature",
  "properties": {
    "gn:admin1_code":"9",
    "gn:admin2_code":"1840.0",
    "gn:asciiname":"Bleiknes",
    "gn:country_code":"NO",
    "gn:dem":75,
    "gn:feature_class":"P",
    "gn:feature_code":"PPL",
    "gn:name":"Bleiknes",
    "gn:population":0,
    "gn:timezone":"Europe/Oslo",
    "iso:country":"NO",
    "wof:name":"Bleiknes",
    "wof:placetype":"locality"
},
  "geometry": {"coordinates":[15.3165,66.90861],"type":"Point"}
}