{
  "type": "Feature",
  "properties": {
    "gn:admin1_code":"14",
    "gn:admin2_code":"1114.0",
    "gn:asciiname":"Holmen",
    "gn:country_code":"NO",
    "gn:dem":169,
    "gn:feature_class":"P",
    "gn:feature_code":"PPL",
    "gn:name":"Holmen",
    "gn:population":0,
    "gn:timezone":"Europe/Oslo",
    "iso:country":"NO",
    "wof:name":"Holmen",
    "wof:placetype":"locality"
},
  "geometry": {"coordinates":[6.08333,58.61666999999999],"type":"Point"}
}