{
  "type": "Feature",
  "properties": {
    "gn:admin1_code":"9.0",
    "gn:admin2_code":"1859.0",
    "gn:asciiname":"Skjenfjorden",
    "gn:country_code":"NO",
    "gn:dem":318,
    "gn:feature_class":"P",
    "gn:feature_code":"PPL",
    "gn:name":"Skjenfjorden",
    "gn:population":0,
    "gn:timezone":"Europe/Oslo",
    "iso:country":"NO",
    "name:nor_x_preferred":[
        "Skjenfjorden"
    ],
    "wof:name":"Skjenfjorden",
    "wof:placetype":"locality"
},
  "geometry": {"coordinates":[13.20226,68.01982],"type":"Point"}
}