{
  "type": "Feature",
  "properties": {
    "gn:admin1_code":"15",
    "gn:admin2_code":"1429.0",
    "gn:asciiname":"Bjerga",
    "gn:country_code":"NO",
    "gn:dem":-9999,
    "gn:feature_class":"P",
    "gn:feature_code":"PPL",
    "gn:name":"Bjerga",
    "gn:population":0,
    "gn:timezone":"Europe/Oslo",
    "iso:country":"NO",
    "wof:name":"Bjerga",
    "wof:placetype":"locality"
},
  "geometry": {"coordinates":[5.38333,61.36666999999999],"type":"Point"}
}