{
  "type": "Feature",
  "properties": {
    "gn:admin1_code":"21.0",
    "gn:admin2_code":"5022.0",
    "gn:asciiname":"Herrem",
    "gn:country_code":"NO",
    "gn:dem":300,
    "gn:feature_class":"P",
    "gn:feature_code":"PPL",
    "gn:name":"Herrem",
    "gn:population":0,
    "gn:timezone":"Europe/Oslo",
    "iso:country":"NO",
    "name:nor_x_preferred":[
        "Herrem"
    ],
    "wof:name":"Herrem",
    "wof:placetype":"locality"
},
  "geometry": {"coordinates":[9.83018,62.89073000000001],"type":"Point"}
}