{
  "type": "Feature",
  "properties": {
    "gn:admin1_code":"15",
    "gn:admin2_code":"1413.0",
    "gn:asciiname":"Lekva",
    "gn:country_code":"NO",
    "gn:dem":178,
    "gn:feature_class":"P",
    "gn:feature_code":"PPL",
    "gn:name":"Lekva",
    "gn:population":0,
    "gn:timezone":"Europe/Oslo",
    "iso:country":"NO",
    "wof:name":"Lekva",
    "wof:placetype":"locality"
},
  "geometry": {"coordinates":[5.23333,61.16667],"type":"Point"}
}