{
  "type": "Feature",
  "properties": {
    "gn:admin1_code":"9",
    "gn:admin2_code":"1813.0",
    "gn:asciiname":"Horn",
    "gn:country_code":"NO",
    "gn:dem":-9999,
    "gn:feature_class":"P",
    "gn:feature_code":"PPL",
    "gn:name":"Horn",
    "gn:population":0,
    "gn:timezone":"Europe/Oslo",
    "iso:country":"NO",
    "wof:name":"Horn",
    "wof:placetype":"locality"
},
  "geometry": {"coordinates":[12.33333,65.58333],"type":"Point"}
}