{
  "type": "Feature",
  "properties": {
    "gn:admin1_code":"8",
    "gn:admin2_code":"1539.0",
    "gn:asciiname":"Hovde",
    "gn:country_code":"NO",
    "gn:dem":-9999,
    "gn:feature_class":"P",
    "gn:feature_code":"PPL",
    "gn:name":"Hovde",
    "gn:population":0,
    "gn:timezone":"Europe/Oslo",
    "iso:country":"NO",
    "wof:name":"Hovde",
    "wof:placetype":"locality"
},
  "geometry": {"coordinates":[7.51667,62.55],"type":"Point"}
}