{
  "type": "Feature",
  "properties": {
    "gn:admin1_code":"8.0",
    "gn:admin2_code":"1523.0",
    "gn:asciiname":"Lande",
    "gn:country_code":"NO",
    "gn:dem":89,
    "gn:feature_class":"P",
    "gn:feature_code":"PPL",
    "gn:name":"Lande",
    "gn:population":0,
    "gn:timezone":"Europe/Oslo",
    "iso:country":"NO",
    "name:bre_x_preferred":[
        "Lande"
    ],
    "name:deu_x_preferred":[
        "Lande"
    ],
    "name:nor_x_preferred":[
        "Lande"
    ],
    "name:rus_x_preferred":[
        "\u041b\u0430\u043d\u0434\u0435"
    ],
    "name:ukr_x_preferred":[
        "\u041b\u0430\u043d\u0434\u0435"
    ],
    "wof:name":"Lande",
    "wof:placetype":"locality"
},
  "geometry": {"coordinates":[6.85361,62.48266],"type":"Point"}
}