{
  "type": "Feature",
  "properties": {
    "gn:admin1_code":"8.0",
    "gn:admin2_code":"1523.0",
    "gn:asciiname":"Lande",
    "gn:country_code":"NO",
    "gn:dem":89,
    "gn:feature_class":"P",
    "gn:feature_code":"PPL",
    "gn:name":"Lande",
    "gn:population":0,
    "gn:timezone":"Europe/Oslo",
    "iso:country":"NO",
    "name:nor_x_preferred":[
        "Lande"
    ],
    "wof:name":"Lande",
    "wof:placetype":"locality"
},
  "geometry": {"coordinates":[6.85361,62.48266],"type":"Point"}
}