{
  "type": "Feature",
  "properties": {
    "gn:admin1_code":"7",
    "gn:admin2_code":"1219.0",
    "gn:asciiname":"Kalavag",
    "gn:cc2":"NO",
    "gn:country_code":"NO",
    "gn:dem":35,
    "gn:feature_class":"P",
    "gn:feature_code":"PPL",
    "gn:name":"Kalav\u00e5g",
    "gn:population":0,
    "gn:timezone":"Europe/Oslo",
    "iso:country":"NO",
    "name:und_x_variant":[
        "Kalavaag",
        "Kalav\u00e5g"
    ],
    "wof:name":"Kalavag",
    "wof:placetype":"locality"
},
  "geometry": {"coordinates":[5.19928,59.59298],"type":"Point"}
}