{
  "type": "Feature",
  "properties": {
    "gn:admin1_code":"20",
    "gn:admin2_code":"701.0",
    "gn:asciiname":"Falkensten",
    "gn:cc2":"NO",
    "gn:country_code":"NO",
    "gn:dem":18,
    "gn:feature_class":"P",
    "gn:feature_code":"PPL",
    "gn:name":"Falkensten",
    "gn:population":0,
    "gn:timezone":"Europe/Oslo",
    "iso:country":"NO",
    "name:und_x_variant":[
        "Falkenstein"
    ],
    "wof:name":"Falkensten",
    "wof:placetype":"locality"
},
  "geometry": {"coordinates":[10.43286,59.44259],"type":"Point"}
}