{
  "type": "Feature",
  "properties": {
    "gn:admin1_code":"21",
    "gn:admin2_code":"5005.0",
    "gn:asciiname":"Hoyknes",
    "gn:cc2":"NO",
    "gn:country_code":"NO",
    "gn:dem":-9999,
    "gn:feature_class":"P",
    "gn:feature_code":"PPL",
    "gn:name":"H\u00f8yknes",
    "gn:population":0,
    "gn:timezone":"Europe/Oslo",
    "iso:country":"NO",
    "name:und_x_variant":[
        "H\u00f6knes",
        "H\u00f8yknes"
    ],
    "wof:name":"Hoyknes",
    "wof:placetype":"locality"
},
  "geometry": {"coordinates":[11.56667,64.46666999999999],"type":"Point"}
}