{
  "type": "Feature",
  "properties": {
    "gn:admin1_code":"7.0",
    "gn:admin2_code":"1246.0",
    "gn:asciiname":"Olveset",
    "gn:country_code":"NO",
    "gn:dem":47,
    "gn:feature_class":"P",
    "gn:feature_code":"PPL",
    "gn:name":"\u00d8lveset",
    "gn:population":0,
    "gn:timezone":"Europe/Oslo",
    "iso:country":"NO",
    "wof:name":"Olveset",
    "wof:placetype":"locality"
},
  "geometry": {"coordinates":[5.04583,60.32611],"type":"Point"}
}