{
  "type": "Feature",
  "properties": {
    "gn:admin1_code":"21",
    "gn:admin2_code":"5032.0",
    "gn:asciiname":"Eidem",
    "gn:country_code":"NO",
    "gn:dem":157,
    "gn:feature_class":"P",
    "gn:feature_code":"PPL",
    "gn:name":"Eidem",
    "gn:population":0,
    "gn:timezone":"Europe/Oslo",
    "iso:country":"NO",
    "name:nor_x_preferred":[
        "Eidem"
    ],
    "wof:name":"Eidem",
    "wof:placetype":"locality"
},
  "geometry": {"coordinates":[11.06667,63.25],"type":"Point"}
}