{
  "type": "Feature",
  "properties": {
    "gn:country":"NO",
    "gn:fcode":"PPL",
    "gn:population":892,
    "iso:country":"NO",
    "name:bul_x_preferred":[
        "\u041a\u0430\u0443\u043f\u0430\u043d\u0433\u0435\u0440"
    ],
    "name:ceb_x_preferred":[
        "Kaupanger"
    ],
    "name:dan_x_preferred":[
        "Kaupanger"
    ],
    "name:deu_x_preferred":[
        "Kaupanger"
    ],
    "name:eng_x_preferred":[
        "Kaupanger"
    ],
    "name:fra_x_preferred":[
        "Kaupanger"
    ],
    "name:ita_x_preferred":[
        "Kaupanger"
    ],
    "name:lat_x_preferred":[
        "Kaupanger"
    ],
    "name:msa_x_preferred":[
        "Kaupanger"
    ],
    "name:nld_x_preferred":[
        "Kaupanger"
    ],
    "name:nno_x_preferred":[
        "Kaupanger"
    ],
    "name:nob_x_preferred":[
        "Kaupanger"
    ],
    "name:nor_x_preferred":[
        "Moldjord"
    ],
    "name:ron_x_preferred":[
        "Kaupanger"
    ],
    "name:spa_x_preferred":[
        "Kaupanger"
    ],
    "qs_pg:aaroncc":"NO",
    "qs_pg:gn_country":"NO",
    "qs_pg:gn_fcode":"PPL",
    "qs_pg:gn_pop":892,
    "qs_pg:name":"Kaupanger",
    "qs_pg:name_adm0":"Norge",
    "qs_pg:name_adm1":"Sogn og Fjordane Fylke",
    "qs_pg:photos":628,
    "qs_pg:photos_1k":127,
    "qs_pg:photos_9k":3,
    "qs_pg:photos_9r":5,
    "qs_pg:photos_all":628,
    "qs_pg:photos_sr":8,
    "qs_pg:pop_sr":2,
    "qs_pg:qs_pg_placetype":"locality",
    "qs_pg:qs_pg_placetype_gp":"Town",
    "qs_pg:woe_adm0":23424910,
    "woe:adm0_id":23424910,
    "woe:name_adm0":"Norge",
    "woe:name_adm1":"Sogn og Fjordane Fylke",
    "woe:placetype":"Town",
    "wof:name":"Kaupanger",
    "wof:placetype":"locality",
    "wof:population":892
},
  "geometry": {"coordinates":[7.23333,61.18333],"type":"Point"}
}