{
  "type": "Feature",
  "properties": {
    "gn:admin1_code":"21",
    "gn:admin2_code":"5014.0",
    "gn:asciiname":"Halten",
    "gn:country_code":"NO",
    "gn:dem":30,
    "gn:feature_class":"P",
    "gn:feature_code":"PPL",
    "gn:name":"Halten",
    "gn:population":0,
    "gn:timezone":"Europe/Oslo",
    "iso:country":"NO",
    "name:als_x_preferred":[
        "Halten"
    ],
    "name:ceb_x_preferred":[
        "Halten"
    ],
    "name:deu_x_preferred":[
        "Halten"
    ],
    "name:epo_x_preferred":[
        "Halten"
    ],
    "name:eus_x_preferred":[
        "Halten"
    ],
    "name:fra_x_preferred":[
        "Halten"
    ],
    "name:ita_x_preferred":[
        "Halten"
    ],
    "name:kaz_x_preferred":[
        "\u0425\u0430\u043b\u044c\u0442\u0435\u043d"
    ],
    "name:lmo_x_preferred":[
        "Halten"
    ],
    "name:msa_x_preferred":[
        "Halten"
    ],
    "name:nld_x_preferred":[
        "Halten"
    ],
    "name:rus_x_preferred":[
        "\u0425\u0430\u043b\u044c\u0442\u0435\u043d"
    ],
    "name:spa_x_preferred":[
        "Halten"
    ],
    "name:sqi_x_preferred":[
        "Halten"
    ],
    "name:swe_x_preferred":[
        "Halten"
    ],
    "name:uzb_x_preferred":[
        "Halten"
    ],
    "name:vie_x_preferred":[
        "Halten"
    ],
    "name:vol_x_preferred":[
        "Halten"
    ],
    "name:war_x_preferred":[
        "Halten"
    ],
    "name:zho_x_preferred":[
        "\u54c8\u723e\u6ed5"
    ],
    "wof:name":"Halten",
    "wof:placetype":"locality"
},
  "geometry": {"coordinates":[8.48406,63.69019],"type":"Point"}
}