{
  "type": "Feature",
  "properties": {
    "gn:admin1_code":"21",
    "gn:admin2_code":"5014.0",
    "gn:asciiname":"Halten",
    "gn:country_code":"NO",
    "gn:dem":30,
    "gn:feature_class":"P",
    "gn:feature_code":"PPL",
    "gn:name":"Halten",
    "gn:population":0,
    "gn:timezone":"Europe/Oslo",
    "iso:country":"NO",
    "wof:name":"Halten",
    "wof:placetype":"locality"
},
  "geometry": {"coordinates":[8.48406,63.69019],"type":"Point"}
}