{
  "type": "Feature",
  "properties": {
    "gn:admin1_code":"11.0",
    "gn:admin2_code":"541.0",
    "gn:asciiname":"Rust",
    "gn:country_code":"NO",
    "gn:dem":811,
    "gn:feature_class":"P",
    "gn:feature_code":"PPL",
    "gn:name":"Rust",
    "gn:population":0,
    "gn:timezone":"Europe/Oslo",
    "iso:country":"NO",
    "name:nor_x_preferred":[
        "Rust"
    ],
    "wof:name":"Rust",
    "wof:placetype":"locality"
},
  "geometry": {"coordinates":[9.60033,61.00005],"type":"Point"}
}