{
  "type": "Feature",
  "properties": {
    "gn:admin1_code":"7.0",
    "gn:admin2_code":"1263.0",
    "gn:asciiname":"Dalabygdi",
    "gn:country_code":"NO",
    "gn:dem":90,
    "gn:feature_class":"P",
    "gn:feature_code":"PPL",
    "gn:name":"Dalabygdi",
    "gn:population":0,
    "gn:timezone":"Europe/Oslo",
    "iso:country":"NO",
    "name:nor_x_preferred":[
        "Dalabygdi"
    ],
    "wof:name":"Dalabygdi",
    "wof:placetype":"locality"
},
  "geometry": {"coordinates":[5.3457,60.57532],"type":"Point"}
}