{
  "type": "Feature",
  "properties": {
    "gn:admin1_code":"6.0",
    "gn:admin2_code":"432.0",
    "gn:asciiname":"Vestgrenda",
    "gn:country_code":"NO",
    "gn:dem":285,
    "gn:feature_class":"P",
    "gn:feature_code":"PPL",
    "gn:name":"Vestgrenda",
    "gn:population":0,
    "gn:timezone":"Europe/Oslo",
    "iso:country":"NO",
    "name:nor_x_preferred":[
        "Vestgrenda"
    ],
    "wof:name":"Vestgrenda",
    "wof:placetype":"locality"
},
  "geometry": {"coordinates":[11.07544,61.89689],"type":"Point"}
}