{
  "type": "Feature",
  "properties": {
    "gn:admin1_code":"5.0",
    "gn:admin2_code":"2003.0",
    "gn:asciiname":"Sollnes",
    "gn:country_code":"NO",
    "gn:dem":-9999,
    "gn:feature_class":"P",
    "gn:feature_code":"PPL",
    "gn:name":"Sollnes",
    "gn:population":0,
    "gn:timezone":"Europe/Oslo",
    "iso:country":"NO",
    "name:und_x_variant":[
        "Solnes",
        "Sollnes"
    ],
    "wof:name":"Sollnes",
    "wof:placetype":"locality"
},
  "geometry": {"coordinates":[30.09039000000001,70.08125],"type":"Point"}
}