{
  "type": "Feature",
  "properties": {
    "iso:country":"NO",
    "name:dan_x_preferred":[
        "\u00c5krestr\u00f8mmen"
    ],
    "name:eng_x_preferred":[
        "\u00c5krestr\u00f8mmen"
    ],
    "name:fra_x_preferred":[
        "\u00c5krestr\u00f8mmen"
    ],
    "name:jav_x_preferred":[
        "\u00c5krestr\u00f8mmen"
    ],
    "name:msa_x_preferred":[
        "\u00c5krestr\u00f8mmen"
    ],
    "name:nld_x_preferred":[
        "\u00c5krestr\u00f8mmen"
    ],
    "name:nno_x_preferred":[
        "\u00c5krestr\u00f8mmen"
    ],
    "name:nob_x_preferred":[
        "\u00c5krestr\u00f8mmen"
    ],
    "qs_pg:aaroncc":"NO",
    "qs_pg:name":"\u00c5krestr\u00f8mmen",
    "qs_pg:name_adm0":"Norge",
    "qs_pg:name_adm1":"Hedmark Fylke",
    "qs_pg:photos":20,
    "qs_pg:photos_1k":4,
    "qs_pg:photos_9k":1,
    "qs_pg:photos_9r":1,
    "qs_pg:photos_all":20,
    "qs_pg:photos_sr":1,
    "qs_pg:pop_sr":0,
    "qs_pg:qs_pg_placetype":"locality",
    "qs_pg:qs_pg_placetype_gp":"Town",
    "qs_pg:woe_adm0":23424910,
    "woe:adm0_id":23424910,
    "woe:name_adm0":"Norge",
    "woe:name_adm1":"Hedmark Fylke",
    "woe:placetype":"Town",
    "wof:name":"\u00c5krestr\u00f8mmen",
    "wof:placetype":"locality"
},
  "geometry": {"coordinates":[11.213972,61.696435],"type":"Point"}
}