{
  "type": "Feature",
  "properties": {
    "gn:admin1_code":"8",
    "gn:admin2_code":"1535.0",
    "gn:asciiname":"Gjermundsnes",
    "gn:country_code":"NO",
    "gn:dem":-9999,
    "gn:feature_class":"P",
    "gn:feature_code":"PPL",
    "gn:name":"Gjermundsnes",
    "gn:population":0,
    "gn:timezone":"Europe/Oslo",
    "iso:country":"NO",
    "wof:name":"Gjermundsnes",
    "wof:placetype":"locality"
},
  "geometry": {"coordinates":[7.18333,62.63333000000001],"type":"Point"}
}