{
  "type": "Feature",
  "properties": {
    "gn:admin1_code":"9",
    "gn:admin2_code":"1848.0",
    "gn:asciiname":"Sandvagen",
    "gn:country_code":"NO",
    "gn:dem":-9999,
    "gn:feature_class":"P",
    "gn:feature_code":"PPL",
    "gn:name":"Sandv\u00e5gen",
    "gn:population":0,
    "gn:timezone":"Europe/Oslo",
    "iso:country":"NO",
    "wof:name":"Sandvagen",
    "wof:placetype":"locality"
},
  "geometry": {"coordinates":[15.06944,67.91889],"type":"Point"}
}