{
  "type": "Feature",
  "properties": {
    "gn:admin1_code":"14.0",
    "gn:admin2_code":"1103.0",
    "gn:asciiname":"Lindoy",
    "gn:country_code":"NO",
    "gn:dem":18,
    "gn:feature_class":"P",
    "gn:feature_code":"PPL",
    "gn:name":"Lind\u00f8y",
    "gn:population":0,
    "gn:timezone":"Europe/Oslo",
    "iso:country":"NO",
    "name:nor_x_preferred":[
        "Lind\u00f8y"
    ],
    "wof:name":"Lindoy",
    "wof:placetype":"locality"
},
  "geometry": {"coordinates":[5.80803,58.99053000000001],"type":"Point"}
}