{
  "type": "Feature",
  "properties": {
    "gn:admin1_code":"21.0",
    "gn:admin2_code":"5054.0",
    "gn:asciiname":"Denstad",
    "gn:country_code":"NO",
    "gn:dem":100,
    "gn:feature_class":"P",
    "gn:feature_code":"PPL",
    "gn:name":"Denstad",
    "gn:population":0,
    "gn:timezone":"Europe/Oslo",
    "iso:country":"NO",
    "name:nor_x_preferred":[
        "Denstad"
    ],
    "wof:name":"Denstad",
    "wof:placetype":"locality"
},
  "geometry": {"coordinates":[10.06819,63.58503],"type":"Point"}
}