{
  "type": "Feature",
  "properties": {
    "gn:admin1_code":"7",
    "gn:admin2_code":"1245.0",
    "gn:asciiname":"Skoge",
    "gn:country_code":"NO",
    "gn:dem":-9999,
    "gn:feature_class":"P",
    "gn:feature_code":"PPLL",
    "gn:name":"Skoge",
    "gn:population":0,
    "gn:timezone":"Europe/Oslo",
    "iso:country":"NO",
    "wof:name":"Skoge",
    "wof:placetype":"locality"
},
  "geometry": {"coordinates":[5.09194,60.26694000000001],"type":"Point"}
}