{
  "type": "Feature",
  "properties": {
    "gn:admin1_code":"6",
    "gn:admin2_code":"420.0",
    "gn:asciiname":"Langfoss",
    "gn:cc2":"NO",
    "gn:country_code":"NO",
    "gn:dem":210,
    "gn:feature_class":"P",
    "gn:feature_code":"PPL",
    "gn:name":"Langfoss",
    "gn:population":0,
    "gn:timezone":"Europe/Oslo",
    "iso:country":"NO",
    "name:und_x_variant":[
        "Langfos",
        "Langfoss"
    ],
    "wof:name":"Langfoss",
    "wof:placetype":"locality"
},
  "geometry": {"coordinates":[12.15725,60.06834],"type":"Point"}
}