{
  "type": "Feature",
  "properties": {
    "gn:country":"NO",
    "gn:fcode":"PPL",
    "gn:population":578,
    "iso:country":"NO",
    "name:nno_x_preferred":[
        "Smestad"
    ],
    "name:nor_x_preferred":[
        "Smestad"
    ],
    "name:und_x_variant":[
        "Smedstad"
    ],
    "qs_pg:aaroncc":"NO",
    "qs_pg:gn_country":"NO",
    "qs_pg:gn_fcode":"PPL",
    "qs_pg:gn_pop":578,
    "qs_pg:name":"Smestad",
    "qs_pg:name_adm0":"Norge",
    "qs_pg:name_adm1":"Akershus Fylke",
    "qs_pg:photos_9r":0,
    "qs_pg:photos_sr":0,
    "qs_pg:pop_sr":2,
    "qs_pg:qs_pg_placetype":"locality",
    "qs_pg:qs_pg_placetype_gp":"Town",
    "qs_pg:woe_adm0":23424910,
    "woe:adm0_id":23424910,
    "woe:name_adm0":"Norge",
    "woe:name_adm1":"Akershus Fylke",
    "woe:placetype":"Town",
    "wof:name":"Smestad",
    "wof:placetype":"locality",
    "wof:population":578
},
  "geometry": {"coordinates":[10.43333,59.93333],"type":"Point"}
}