{
  "type": "Feature",
  "properties": {
    "gn:admin1_code":"20",
    "gn:admin2_code":"712.0",
    "gn:asciiname":"Nalum",
    "gn:country_code":"NO",
    "gn:dem":27,
    "gn:feature_class":"P",
    "gn:feature_code":"PPL",
    "gn:name":"Nalum",
    "gn:population":0,
    "gn:timezone":"Europe/Oslo",
    "iso:country":"NO",
    "name:und_x_variant":[
        "Nalom"
    ],
    "wof:name":"Nalum",
    "wof:placetype":"locality"
},
  "geometry": {"coordinates":[9.98636,58.99052],"type":"Point"}
}