{
  "type": "Feature",
  "properties": {
    "gn:admin1_code":"11.0",
    "gn:admin2_code":"542.0",
    "gn:asciiname":"Olsjobakkadn",
    "gn:country_code":"NO",
    "gn:dem":913,
    "gn:feature_class":"P",
    "gn:feature_code":"PPL",
    "gn:name":"\u00d8lsj\u00f8bakkadn",
    "gn:population":0,
    "gn:timezone":"Europe/Oslo",
    "iso:country":"NO",
    "wof:name":"Olsjobakkadn",
    "wof:placetype":"locality"
},
  "geometry": {"coordinates":[9.22053,60.88723],"type":"Point"}
}