{
  "type": "Feature",
  "properties": {
    "gn:admin1_code":"13",
    "gn:admin2_code":"106",
    "gn:asciiname":"Glombu",
    "gn:country_code":"NO",
    "gn:dem":24,
    "gn:feature_class":"P",
    "gn:feature_code":"PPLL",
    "gn:name":"Glombu",
    "gn:population":0,
    "gn:timezone":"Europe/Oslo",
    "iso:country":"NO",
    "name:nor_x_preferred":[
        "Glombu"
    ],
    "name:nor_x_variant":[
        "Glombo"
    ],
    "wof:name":"Glombu",
    "wof:placetype":"neighbourhood"
},
  "geometry": {"coordinates":[10.90696,59.2047],"type":"Point"}
}