{
  "type": "Feature",
  "properties": {
    "gn:admin1_code":"15.0",
    "gn:admin2_code":"1401.0",
    "gn:asciiname":"Seljestokken",
    "gn:cc2":"NO",
    "gn:country_code":"NO",
    "gn:dem":100,
    "gn:feature_class":"P",
    "gn:feature_code":"PPL",
    "gn:name":"Seljestokken",
    "gn:population":0,
    "gn:timezone":"Europe/Oslo",
    "iso:country":"NO",
    "name:und_x_variant":[
        "Seljestok",
        "Seljestokken"
    ],
    "wof:name":"Seljestokken",
    "wof:placetype":"locality"
},
  "geometry": {"coordinates":[4.98333,61.68333000000001],"type":"Point"}
}