{
  "type": "Feature",
  "properties": {
    "gn:admin1_code":"7",
    "gn:admin2_code":"1235.0",
    "gn:asciiname":"Arhus",
    "gn:country_code":"NO",
    "gn:dem":508,
    "gn:feature_class":"P",
    "gn:feature_code":"PPL",
    "gn:name":"\u00c5rhus",
    "gn:population":0,
    "gn:timezone":"Europe/Oslo",
    "iso:country":"NO",
    "name:und_x_variant":[
        "\u00c5rhus"
    ],
    "wof:name":"Arhus",
    "wof:placetype":"locality"
},
  "geometry": {"coordinates":[6.15,60.73333],"type":"Point"}
}