{
  "type": "Feature",
  "properties": {
    "gn:admin1_code":"15.0",
    "gn:admin2_code":"1411.0",
    "gn:asciiname":"Takle",
    "gn:country_code":"NO",
    "gn:dem":1,
    "gn:feature_class":"P",
    "gn:feature_code":"PPL",
    "gn:name":"Takle",
    "gn:population":0,
    "gn:timezone":"Europe/Oslo",
    "iso:country":"NO",
    "wof:name":"Takle",
    "wof:placetype":"locality"
},
  "geometry": {"coordinates":[5.37869,61.02683],"type":"Point"}
}