{
  "type": "Feature",
  "properties": {
    "gn:admin1_code":"9",
    "gn:admin2_code":"1824.0",
    "gn:asciiname":"Anes",
    "gn:cc2":"NO",
    "gn:country_code":"NO",
    "gn:dem":80,
    "gn:feature_class":"P",
    "gn:feature_code":"PPL",
    "gn:name":"\u00c5nes",
    "gn:population":0,
    "gn:timezone":"Europe/Oslo",
    "iso:country":"NO",
    "name:cat_x_preferred":[
        "Anes"
    ],
    "name:spa_x_preferred":[
        "Anes"
    ],
    "name:und_x_variant":[
        "Aanes",
        "\u00c5nes"
    ],
    "wof:name":"Anes",
    "wof:placetype":"locality"
},
  "geometry": {"coordinates":[13.45,65.90000000000001],"type":"Point"}
}