{
  "type": "Feature",
  "properties": {
    "gn:admin1_code":"9.0",
    "gn:admin2_code":"1845.0",
    "gn:asciiname":"Sjunkan",
    "gn:country_code":"NO",
    "gn:dem":1,
    "gn:feature_class":"P",
    "gn:feature_code":"PPL",
    "gn:name":"Sjunkan",
    "gn:population":0,
    "gn:timezone":"Europe/Oslo",
    "iso:country":"NO",
    "wof:name":"Sjunkan",
    "wof:placetype":"locality"
},
  "geometry": {"coordinates":[15.15582,67.49964],"type":"Point"}
}