{
  "type": "Feature",
  "properties": {
    "gn:admin1_code":"15.0",
    "gn:admin2_code":"1433.0",
    "gn:asciiname":"Ullaland",
    "gn:country_code":"NO",
    "gn:dem":140,
    "gn:feature_class":"P",
    "gn:feature_code":"PPL",
    "gn:name":"Ullaland",
    "gn:population":0,
    "gn:timezone":"Europe/Oslo",
    "iso:country":"NO",
    "wof:name":"Ullaland",
    "wof:placetype":"locality"
},
  "geometry": {"coordinates":[5.81667,61.56667],"type":"Point"}
}