{
  "type": "Feature",
  "properties": {
    "gn:admin1_code":"8",
    "gn:admin2_code":"1566.0",
    "gn:asciiname":"Bo",
    "gn:country_code":"NO",
    "gn:dem":-9999,
    "gn:feature_class":"P",
    "gn:feature_code":"PPL",
    "gn:name":"B\u00f8",
    "gn:population":0,
    "gn:timezone":"Europe/Oslo",
    "iso:country":"NO",
    "name:dan_x_preferred":[
        "Bo"
    ],
    "name:fas_x_preferred":[
        "\u0628\u0648"
    ],
    "name:hun_x_preferred":[
        "Bo"
    ],
    "name:hye_x_preferred":[
        "\u0532\u0578"
    ],
    "name:lit_x_preferred":[
        "Bo"
    ],
    "wof:name":"Bo",
    "wof:placetype":"locality"
},
  "geometry": {"coordinates":[8.38333,63.01667],"type":"Point"}
}