{
  "type": "Feature",
  "properties": {
    "gn:admin1_code":"9",
    "gn:admin2_code":"1854.0",
    "gn:asciiname":"Kjelde",
    "gn:cc2":"NO",
    "gn:country_code":"NO",
    "gn:dem":1,
    "gn:feature_class":"P",
    "gn:feature_code":"PPL",
    "gn:name":"Kjelde",
    "gn:population":0,
    "gn:timezone":"Europe/Oslo",
    "iso:country":"NO",
    "name:und_x_variant":[
        "Tjelle",
        "Kjelde"
    ],
    "wof:name":"Kjelde",
    "wof:placetype":"locality"
},
  "geometry": {"coordinates":[16.63332999999999,68.41667],"type":"Point"}
}