{
  "type": "Feature",
  "properties": {
    "iso:country":"NO",
    "qs_pg:aaroncc":"NO",
    "qs_pg:name":"Hegde Haugen",
    "qs_pg:name_adm0":"Norge",
    "qs_pg:name_adm1":"Oslo Fylke",
    "qs_pg:photos":235,
    "qs_pg:photos_1k":48,
    "qs_pg:photos_9k":1,
    "qs_pg:photos_9r":4,
    "qs_pg:photos_all":235,
    "qs_pg:photos_sr":4,
    "qs_pg:pop_sr":0,
    "qs_pg:qs_pg_placetype":"neighbourhood",
    "qs_pg:qs_pg_placetype_gp":"Suburb",
    "qs_pg:woe_adm0":23424910,
    "woe:adm0_id":23424910,
    "woe:name_adm0":"Norge",
    "woe:name_adm1":"Oslo Fylke",
    "woe:placetype":"Suburb",
    "wof:name":"Hegde Haugen",
    "wof:placetype":"neighbourhood"
},
  "geometry": {"coordinates":[10.722812,59.927495],"type":"Point"}
}