{
  "type": "Feature",
  "properties": {
    "gn:admin1_code":"9.0",
    "gn:admin2_code":"1827.0",
    "gn:asciiname":"Hammarvik",
    "gn:country_code":"NO",
    "gn:dem":17,
    "gn:feature_class":"P",
    "gn:feature_code":"PPL",
    "gn:name":"Hammarvik",
    "gn:population":0,
    "gn:timezone":"Europe/Oslo",
    "iso:country":"NO",
    "name:nor_x_preferred":[
        "Hammarvik"
    ],
    "wof:name":"Hammarvik",
    "wof:placetype":"locality"
},
  "geometry": {"coordinates":[12.57234,66.21564000000001],"type":"Point"}
}