{
  "type": "Feature",
  "properties": {
    "gn:admin1_code":"5.0",
    "gn:admin2_code":"2011.0",
    "gn:asciiname":"Suotnjorohtu",
    "gn:country_code":"NO",
    "gn:dem":320,
    "gn:feature_class":"P",
    "gn:feature_code":"PPL",
    "gn:name":"Suotnjorohtu",
    "gn:population":0,
    "gn:timezone":"Europe/Oslo",
    "iso:country":"NO",
    "name:sme_x_preferred":[
        "Suotnjorohtu"
    ],
    "name:sme_x_variant":[
        "Suoidnerohtu"
    ],
    "wof:name":"Suotnjorohtu",
    "wof:placetype":"locality"
},
  "geometry": {"coordinates":[24.20312,69.37725999999999],"type":"Point"}
}