{
  "type": "Feature",
  "properties": {
    "gn:admin1_code":"13",
    "gn:admin2_code":"128.0",
    "gn:asciiname":"Heia",
    "gn:cc2":"NO",
    "gn:country_code":"NO",
    "gn:dem":130,
    "gn:feature_class":"P",
    "gn:feature_code":"PPL",
    "gn:name":"Heia",
    "gn:population":0,
    "gn:timezone":"Europe/Oslo",
    "iso:country":"NO",
    "name:dan_x_preferred":[
        "Heia Station"
    ],
    "name:fra_x_preferred":[
        "Gare d'Heia"
    ],
    "name:jav_x_preferred":[
        "Heia"
    ],
    "name:msa_x_preferred":[
        "Heia"
    ],
    "name:nld_x_preferred":[
        "Station Heia"
    ],
    "name:nor_x_preferred":[
        "Heia stasjon"
    ],
    "name:pol_x_preferred":[
        "Heia"
    ],
    "name:und_x_variant":[
        "Heia Stasjon",
        "Heia"
    ],
    "wof:name":"Heia",
    "wof:placetype":"locality"
},
  "geometry": {"coordinates":[11.33333,59.46666999999999],"type":"Point"}
}