{
  "type": "Feature",
  "properties": {
    "gn:admin1_code":"11",
    "gn:admin2_code":"516.0",
    "gn:asciiname":"Fefor",
    "gn:country_code":"NO",
    "gn:dem":882,
    "gn:feature_class":"P",
    "gn:feature_code":"PPL",
    "gn:name":"Fefor",
    "gn:population":0,
    "gn:timezone":"Europe/Oslo",
    "iso:country":"NO",
    "name:deu_x_preferred":[
        "Fefor"
    ],
    "wof:name":"Fefor",
    "wof:placetype":"locality"
},
  "geometry": {"coordinates":[9.65,61.53333000000001],"type":"Point"}
}