{
  "type": "Feature",
  "properties": {
    "gn:admin1_code":"7.0",
    "gn:admin2_code":"1245.0",
    "gn:asciiname":"Spilda",
    "gn:country_code":"NO",
    "gn:dem":20,
    "gn:feature_class":"P",
    "gn:feature_code":"PPL",
    "gn:name":"Spilda",
    "gn:population":0,
    "gn:timezone":"Europe/Oslo",
    "iso:country":"NO",
    "wof:name":"Spilda",
    "wof:placetype":"locality"
},
  "geometry": {"coordinates":[5.05,60.25],"type":"Point"}
}