{
  "type": "Feature",
  "properties": {
    "gn:admin1_code":"21",
    "gn:admin2_code":"5001.0",
    "gn:asciiname":"Lian",
    "gn:country_code":"NO",
    "gn:dem":250,
    "gn:feature_class":"P",
    "gn:feature_code":"PPL",
    "gn:name":"Lian",
    "gn:population":0,
    "gn:timezone":"Europe/Oslo",
    "iso:country":"NO",
    "name:ceb_x_preferred":[
        "Lian"
    ],
    "name:deu_x_preferred":[
        "Lian"
    ],
    "name:fra_x_preferred":[
        "Lian"
    ],
    "name:nno_x_preferred":[
        "Lian"
    ],
    "name:nor_x_preferred":[
        "Lian"
    ],
    "name:rus_x_preferred":[
        "\u041b\u0438\u0430\u043d"
    ],
    "name:sco_x_preferred":[
        "Lian"
    ],
    "wof:name":"Lian",
    "wof:placetype":"locality"
},
  "geometry": {"coordinates":[10.30101,63.40077],"type":"Point"}
}