{
  "type": "Feature",
  "properties": {
    "gn:admin1_code":"8.0",
    "gn:admin2_code":"1535.0",
    "gn:asciiname":"Rypdal",
    "gn:country_code":"NO",
    "gn:dem":126,
    "gn:feature_class":"P",
    "gn:feature_code":"PPL",
    "gn:name":"Rypdal",
    "gn:population":0,
    "gn:timezone":"Europe/Oslo",
    "iso:country":"NO",
    "name:nor_x_preferred":[
        "Rypdal"
    ],
    "wof:name":"Rypdal",
    "wof:placetype":"locality"
},
  "geometry": {"coordinates":[7.14182,62.50507],"type":"Point"}
}