{
  "type": "Feature",
  "properties": {
    "gn:admin1_code":"15",
    "gn:admin2_code":"1428.0",
    "gn:asciiname":"Kvammen",
    "gn:country_code":"NO",
    "gn:dem":3,
    "gn:feature_class":"P",
    "gn:feature_code":"PPL",
    "gn:name":"Kvammen",
    "gn:population":0,
    "gn:timezone":"Europe/Oslo",
    "iso:country":"NO",
    "name:msa_x_preferred":[
        "Kvammen"
    ],
    "name:nno_x_preferred":[
        "Kvammen"
    ],
    "name:nor_x_preferred":[
        "Kvammen"
    ],
    "wof:name":"Kvammen",
    "wof:placetype":"locality"
},
  "geometry": {"coordinates":[5.41684,61.45868000000001],"type":"Point"}
}