{
  "type": "Feature",
  "properties": {
    "gn:admin1_code":"19",
    "gn:admin2_code":"1004",
    "gn:asciiname":"Prestmoen",
    "gn:country_code":"NO",
    "gn:dem":79,
    "gn:feature_class":"P",
    "gn:feature_code":"PPLL",
    "gn:name":"Prestmoen",
    "gn:population":0,
    "gn:timezone":"Europe/Oslo",
    "iso:country":"NO",
    "name:fra_x_preferred":[
        "Prestmoen"
    ],
    "name:jav_x_preferred":[
        "Prestmoen"
    ],
    "name:msa_x_preferred":[
        "Prestmoen"
    ],
    "name:nld_x_preferred":[
        "Prestmoen"
    ],
    "name:nno_x_preferred":[
        "Prestmoen"
    ],
    "name:nor_x_preferred":[
        "Prestmoen"
    ],
    "name:ron_x_preferred":[
        "Prestmoen"
    ],
    "name:spa_x_preferred":[
        "Prestmoen"
    ],
    "wof:name":"Prestmoen",
    "wof:placetype":"locality"
},
  "geometry": {"coordinates":[6.66085,58.42189000000001],"type":"Point"}
}