{
  "type": "Feature",
  "properties": {
    "gn:admin1_code":"8",
    "gn:admin2_code":"1515.0",
    "gn:asciiname":"Leikang",
    "gn:country_code":"NO",
    "gn:dem":1,
    "gn:feature_class":"P",
    "gn:feature_code":"PPL",
    "gn:name":"Leikang",
    "gn:population":0,
    "gn:timezone":"Europe/Oslo",
    "iso:country":"NO",
    "name:nor_x_preferred":[
        "Leikang"
    ],
    "name:nor_x_variant":[
        "Leikong"
    ],
    "wof:name":"Leikang",
    "wof:placetype":"locality"
},
  "geometry": {"coordinates":[5.78169,62.24722],"type":"Point"}
}