{
  "type": "Feature",
  "properties": {
    "gn:admin1_code":"8.0",
    "gn:admin2_code":"1576.0",
    "gn:asciiname":"Vollen",
    "gn:cc2":"NO",
    "gn:country_code":"NO",
    "gn:dem":1,
    "gn:feature_class":"P",
    "gn:feature_code":"PPL",
    "gn:name":"Vollen",
    "gn:population":0,
    "gn:timezone":"Europe/Oslo",
    "iso:country":"NO",
    "name:und_x_variant":[
        "Volden",
        "Vollen"
    ],
    "wof:name":"Vollen",
    "wof:placetype":"locality"
},
  "geometry": {"coordinates":[8.71667,63.41667],"type":"Point"}
}