{
  "type": "Feature",
  "properties": {
    "gn:admin1_code":"21.0",
    "gn:admin2_code":"5013.0",
    "gn:asciiname":"Risoysund",
    "gn:cc2":"NO",
    "gn:country_code":"NO",
    "gn:dem":-9999,
    "gn:feature_class":"P",
    "gn:feature_code":"PPL",
    "gn:name":"Ris\u00f8ysund",
    "gn:population":0,
    "gn:timezone":"Europe/Oslo",
    "iso:country":"NO",
    "name:und_x_variant":[
        "Ris\u00f6sund",
        "Ris\u00f8ysund"
    ],
    "wof:name":"Risoysund",
    "wof:placetype":"locality"
},
  "geometry": {"coordinates":[8.28333,63.48333],"type":"Point"}
}