{
  "type": "Feature",
  "properties": {
    "iso:country":"NO",
    "name:nor_x_preferred":[
        "Nypan"
    ],
    "name:unk_x_variant":[
        "Nypan"
    ],
    "qs:gn_adm0_cc":"NO",
    "qs:gn_local":3151029,
    "qs:gn_nam_loc":"vollen",
    "qs:gn_namadm1":"16",
    "qs:local_max":296,
    "qs:local_sum":296,
    "qs:localhoods":1,
    "qs:name":"Nypan",
    "qs:name_adm0":"Norge",
    "qs:name_adm1":"S\u00f8r-Tr\u00f8ndelag Fylke",
    "qs:name_adm2":"Trondheim Kommune",
    "qs:name_local":"Leinstrand",
    "qs:photo_max":61,
    "qs:photo_sum":296,
    "qs:placetype":"Suburb",
    "qs:quad_count":45,
    "qs:woe_adm0":23424910,
    "qs:woe_adm1":2346399,
    "qs:woe_adm2":12592932,
    "qs:woe_lau":0,
    "qs:woe_local":15000815,
    "qs:woe_ver":"7.10.0",
    "wof:lang":[
        "nor"
    ],
    "wof:name":"Nypan",
    "wof:placetype":"neighbourhood"
},
  "geometry": {"coordinates":[10.310395,63.33094],"type":"Point"}
}