{
  "type": "Feature",
  "properties": {
    "gn:admin1_code":"21",
    "gn:admin2_code":"5021.0",
    "gn:asciiname":"Bo",
    "gn:country_code":"NO",
    "gn:dem":560,
    "gn:feature_class":"P",
    "gn:feature_code":"PPL",
    "gn:name":"B\u00f8",
    "gn:population":0,
    "gn:timezone":"Europe/Oslo",
    "iso:country":"NO",
    "name:nor_x_preferred":[
        "B\u00f8"
    ],
    "wof:name":"Bo",
    "wof:placetype":"locality"
},
  "geometry": {"coordinates":[9.41667,62.58333],"type":"Point"}
}