{
  "type": "Feature",
  "properties": {
    "gn:admin1_code":"18",
    "gn:admin2_code":"1919.0",
    "gn:asciiname":"Elveneset",
    "gn:country_code":"NO",
    "gn:dem":1,
    "gn:feature_class":"P",
    "gn:feature_code":"PPL",
    "gn:name":"Elveneset",
    "gn:population":0,
    "gn:timezone":"Europe/Oslo",
    "iso:country":"NO",
    "wof:name":"Elveneset",
    "wof:placetype":"locality"
},
  "geometry": {"coordinates":[17.66096,68.67041],"type":"Point"}
}