{
  "type": "Feature",
  "properties": {
    "gn:admin1_code":"17.0",
    "gn:admin2_code":"834.0",
    "gn:asciiname":"Oyi",
    "gn:country_code":"NO",
    "gn:dem":691,
    "gn:feature_class":"P",
    "gn:feature_code":"PPL",
    "gn:name":"\u00d8yi",
    "gn:population":0,
    "gn:timezone":"Europe/Oslo",
    "iso:country":"NO",
    "name:ceb_x_preferred":[
        "Oyi"
    ],
    "name:fra_x_preferred":[
        "Oyi"
    ],
    "name:hau_x_preferred":[
        "Oyi"
    ],
    "name:ita_x_preferred":[
        "Oyi"
    ],
    "name:spa_x_preferred":[
        "Oyi"
    ],
    "wof:name":"Oyi",
    "wof:placetype":"locality"
},
  "geometry": {"coordinates":[8.01667,59.65],"type":"Point"}
}