{
  "type": "Feature",
  "properties": {
    "gn:admin1_code":"6",
    "gn:admin2_code":"420.0",
    "gn:asciiname":"Borrud",
    "gn:cc2":"NO",
    "gn:country_code":"NO",
    "gn:dem":147,
    "gn:feature_class":"P",
    "gn:feature_code":"PPL",
    "gn:name":"B\u00f8rrud",
    "gn:population":0,
    "gn:timezone":"Europe/Oslo",
    "iso:country":"NO",
    "name:und_x_variant":[
        "B\u00f8rgerud",
        "B\u00f8rrud"
    ],
    "wof:name":"Borrud",
    "wof:placetype":"locality"
},
  "geometry": {"coordinates":[12.08333,59.98333],"type":"Point"}
}