{
  "type": "Feature",
  "properties": {
    "gn:admin1_code":"1",
    "gn:admin2_code":"233",
    "gn:asciiname":"Kjul",
    "gn:country_code":"NO",
    "gn:dem":120,
    "gn:feature_class":"P",
    "gn:feature_code":"PPLL",
    "gn:name":"Kjul",
    "gn:population":0,
    "gn:timezone":"Europe/Oslo",
    "iso:country":"NO",
    "name:ceb_x_preferred":[
        "Kjul"
    ],
    "name:jav_x_preferred":[
        "Kjul"
    ],
    "name:msa_x_preferred":[
        "Kjul"
    ],
    "name:nor_x_preferred":[
        "Kjul"
    ],
    "wof:name":"Kjul",
    "wof:placetype":"neighbourhood"
},
  "geometry": {"coordinates":[10.8951,60.02711],"type":"Point"}
}