{
  "type": "Feature",
  "properties": {
    "gn:country":"NO",
    "gn:fcode":"FRM",
    "gn:population":10,
    "iso:country":"NO",
    "qs_pg:aaroncc":"NO",
    "qs_pg:gn_country":"NO",
    "qs_pg:gn_fcode":"FRM",
    "qs_pg:gn_pop":10,
    "qs_pg:name":"Skui g\u00e5rd",
    "qs_pg:photos_9r":0,
    "qs_pg:photos_sr":0,
    "qs_pg:pop_sr":1,
    "qs_pg:qs_pg_placetype":"locality",
    "wof:name":"Skui g\u00e5rd",
    "wof:placetype":"locality",
    "wof:population":10
},
  "geometry": {"coordinates":[10.45241,59.92002],"type":"Point"}
}