{
  "type": "Feature",
  "properties": {
    "gn:admin1_code":"8.0",
    "gn:admin2_code":"1545.0",
    "gn:asciiname":"Raknes",
    "gn:country_code":"NO",
    "gn:dem":1,
    "gn:feature_class":"P",
    "gn:feature_code":"PPL",
    "gn:name":"Raknes",
    "gn:population":0,
    "gn:timezone":"Europe/Oslo",
    "iso:country":"NO",
    "wof:name":"Raknes",
    "wof:placetype":"locality"
},
  "geometry": {"coordinates":[6.72206,62.72161],"type":"Point"}
}