{
  "type": "Feature",
  "properties": {
    "gn:admin1_code":"21",
    "gn:admin2_code":"5025",
    "gn:asciiname":"Smahagan",
    "gn:country_code":"NO",
    "gn:dem":680,
    "gn:feature_class":"P",
    "gn:feature_code":"PPLL",
    "gn:name":"Sm\u00e5hagan",
    "gn:population":0,
    "gn:timezone":"Europe/Oslo",
    "iso:country":"NO",
    "name:nor_x_preferred":[
        "Sm\u00e5hagan"
    ],
    "wof:name":"Smahagan",
    "wof:placetype":"neighbourhood"
},
  "geometry": {"coordinates":[11.39902,62.57665],"type":"Point"}
}