{
  "type": "Feature",
  "properties": {
    "gn:admin1_code":"2",
    "gn:admin2_code":"904",
    "gn:asciiname":"Vik",
    "gn:country_code":"NO",
    "gn:dem":44,
    "gn:feature_class":"P",
    "gn:feature_code":"PPL",
    "gn:name":"Vik",
    "gn:population":0,
    "gn:timezone":"Europe/Oslo",
    "iso:country":"NO",
    "name:bpy_x_preferred":[
        "\u09ad\u09bf\u0995"
    ],
    "name:cat_x_preferred":[
        "Vik"
    ],
    "name:ceb_x_preferred":[
        "Vik"
    ],
    "name:dan_x_preferred":[
        "Vik"
    ],
    "name:deu_x_preferred":[
        "Vik"
    ],
    "name:epo_x_preferred":[
        "Vik"
    ],
    "name:est_x_preferred":[
        "Viki vald"
    ],
    "name:eus_x_preferred":[
        "Vik"
    ],
    "name:fin_x_preferred":[
        "Vik"
    ],
    "name:ita_x_preferred":[
        "Vik"
    ],
    "name:lat_x_preferred":[
        "Vik"
    ],
    "name:lim_x_preferred":[
        "Vik"
    ],
    "name:msa_x_preferred":[
        "Vik"
    ],
    "name:nds_x_preferred":[
        "Kommun Vik"
    ],
    "name:nld_x_preferred":[
        "Vik"
    ],
    "name:nno_x_preferred":[
        "Vik kommune"
    ],
    "name:nor_x_preferred":[
        "Vik"
    ],
    "name:pol_x_preferred":[
        "Vik"
    ],
    "name:por_x_preferred":[
        "Vik"
    ],
    "name:ron_x_preferred":[
        "Vik"
    ],
    "name:rus_x_preferred":[
        "\u0412\u0438\u043a"
    ],
    "name:slv_x_preferred":[
        "Vik"
    ],
    "name:sme_x_preferred":[
        "Vik"
    ],
    "name:spa_x_preferred":[
        "Vik"
    ],
    "name:sqi_x_preferred":[
        "Vik"
    ],
    "name:swe_x_preferred":[
        "Viks kommun"
    ],
    "name:war_x_preferred":[
        "Vik"
    ],
    "name:zho_x_preferred":[
        "\u7dad\u514b"
    ],
    "wof:name":"Vik",
    "wof:placetype":"locality"
},
  "geometry": {"coordinates":[8.62271,58.36833000000001],"type":"Point"}
}