{
  "type": "Feature",
  "properties": {
    "gn:admin1_code":"2",
    "gn:admin2_code":"904",
    "gn:asciiname":"Vik",
    "gn:country_code":"NO",
    "gn:dem":44,
    "gn:feature_class":"P",
    "gn:feature_code":"PPL",
    "gn:name":"Vik",
    "gn:population":0,
    "gn:timezone":"Europe/Oslo",
    "iso:country":"NO",
    "name:nor_x_preferred":[
        "Vik"
    ],
    "wof:name":"Vik",
    "wof:placetype":"locality"
},
  "geometry": {"coordinates":[8.62271,58.36833000000001],"type":"Point"}
}