{
  "type": "Feature",
  "properties": {
    "gn:admin1_code":"9.0",
    "gn:admin2_code":"1804.0",
    "gn:asciiname":"Tarnvika",
    "gn:cc2":"NO",
    "gn:country_code":"NO",
    "gn:dem":80,
    "gn:feature_class":"P",
    "gn:feature_code":"PPL",
    "gn:name":"T\u00e5rnvika",
    "gn:population":0,
    "gn:timezone":"Europe/Oslo",
    "iso:country":"NO",
    "name:und_x_variant":[
        "Taarnvik",
        "T\u00e5rnvik"
    ],
    "wof:name":"Tarnvika",
    "wof:placetype":"locality"
},
  "geometry": {"coordinates":[15.12001,67.56653],"type":"Point"}
}