{
  "type": "Feature",
  "properties": {
    "gn:admin1_code":"8.0",
    "gn:admin2_code":"1516.0",
    "gn:asciiname":"Ulstein",
    "gn:cc2":"NO",
    "gn:country_code":"NO",
    "gn:dem":-9999,
    "gn:feature_class":"P",
    "gn:feature_code":"PPL",
    "gn:name":"Ulstein",
    "gn:population":0,
    "gn:timezone":"Europe/Oslo",
    "iso:country":"NO",
    "name:bar_x_preferred":[
        "Ulstein"
    ],
    "name:bpy_x_preferred":[
        "\u0986\u09b2\u09b8\u099f\u09c7\u0987\u09a8"
    ],
    "name:cat_x_preferred":[
        "Ulstein"
    ],
    "name:ceb_x_preferred":[
        "Ulstein"
    ],
    "name:dan_x_preferred":[
        "Ulstein"
    ],
    "name:deu_x_preferred":[
        "Ulstein"
    ],
    "name:epo_x_preferred":[
        "Ulstein"
    ],
    "name:eus_x_preferred":[
        "Ulstein"
    ],
    "name:fas_x_preferred":[
        "\u0627\u0648\u0644\u0633\u062a\u0627\u06cc\u0646"
    ],
    "name:fin_x_preferred":[
        "Ulstein"
    ],
    "name:fra_x_preferred":[
        "Ulstein"
    ],
    "name:ita_x_preferred":[
        "Ulstein"
    ],
    "name:jav_x_preferred":[
        "Ulstein"
    ],
    "name:kor_x_preferred":[
        "\uc6b8\uc2a4\ud14c\uc778"
    ],
    "name:lat_x_preferred":[
        "Ulstein"
    ],
    "name:lim_x_preferred":[
        "Ulstein"
    ],
    "name:msa_x_preferred":[
        "Ulstein"
    ],
    "name:nds_x_preferred":[
        "Kommun Ulstein"
    ],
    "name:nld_x_preferred":[
        "Ulstein"
    ],
    "name:nno_x_preferred":[
        "Ulstein kommune"
    ],
    "name:nor_x_preferred":[
        "Ulstein"
    ],
    "name:pol_x_preferred":[
        "Ulstein"
    ],
    "name:por_x_preferred":[
        "Ulstein"
    ],
    "name:ron_x_preferred":[
        "Ulstein"
    ],
    "name:rus_x_preferred":[
        "\u0423\u043b\u044c\u0441\u0442\u0435\u0439\u043d"
    ],
    "name:slv_x_preferred":[
        "Ulstein"
    ],
    "name:sme_x_preferred":[
        "Ulstein"
    ],
    "name:spa_x_preferred":[
        "Ulstein"
    ],
    "name:sqi_x_preferred":[
        "Ulstein"
    ],
    "name:swe_x_preferred":[
        "Ulsteins kommun"
    ],
    "name:und_x_variant":[
        "Ulfsten",
        "Ulvsten"
    ],
    "name:vie_x_preferred":[
        "Ulstein"
    ],
    "name:war_x_preferred":[
        "Ulstein"
    ],
    "name:zho_x_preferred":[
        "\u70cf\u723e\u65af\u6cf0\u56e0"
    ],
    "wof:name":"Ulstein",
    "wof:placetype":"locality"
},
  "geometry": {"coordinates":[5.82167,62.36065],"type":"Point"}
}