{
  "type": "Feature",
  "properties": {
    "gn:admin1_code":"8.0",
    "gn:admin2_code":"1516.0",
    "gn:asciiname":"Ulstein",
    "gn:cc2":"NO",
    "gn:country_code":"NO",
    "gn:dem":-9999,
    "gn:feature_class":"P",
    "gn:feature_code":"PPL",
    "gn:name":"Ulstein",
    "gn:population":0,
    "gn:timezone":"Europe/Oslo",
    "iso:country":"NO",
    "name:und_x_variant":[
        "Ulfsten",
        "Ulvsten",
        "Ulstein"
    ],
    "wof:name":"Ulstein",
    "wof:placetype":"locality"
},
  "geometry": {"coordinates":[5.82167,62.36065],"type":"Point"}
}