{
  "type": "Feature",
  "properties": {
    "gn:admin1_code":"11.0",
    "gn:admin2_code":"520.0",
    "gn:asciiname":"Sore Brekkom",
    "gn:country_code":"NO",
    "gn:dem":760,
    "gn:feature_class":"P",
    "gn:feature_code":"PPL",
    "gn:name":"S\u00f8re Brekkom",
    "gn:population":0,
    "gn:timezone":"Europe/Oslo",
    "iso:country":"NO",
    "name:nor_x_preferred":[
        "S\u00f8re Brekkom"
    ],
    "wof:name":"Sore Brekkom",
    "wof:placetype":"locality"
},
  "geometry": {"coordinates":[10.33011,61.46008000000001],"type":"Point"}
}