{
  "type": "Feature",
  "properties": {
    "gn:admin1_code":"13.0",
    "gn:admin2_code":"105.0",
    "gn:asciiname":"Ryen",
    "gn:country_code":"NO",
    "gn:dem":37,
    "gn:feature_class":"P",
    "gn:feature_code":"PPL",
    "gn:name":"Ryen",
    "gn:population":0,
    "gn:timezone":"Europe/Oslo",
    "iso:country":"NO",
    "name:msa_x_preferred":[
        "Ryen"
    ],
    "name:nor_x_preferred":[
        "Ryen"
    ],
    "name:swe_x_preferred":[
        "Ryen"
    ],
    "wof:name":"Ryen",
    "wof:placetype":"locality"
},
  "geometry": {"coordinates":[10.98333,59.31667],"type":"Point"}
}