{
  "type": "Feature",
  "properties": {
    "gn:country":"NO",
    "gn:fcode":"PPL",
    "gn:population":0,
    "iso:country":"NO",
    "name:cat_x_preferred":[
        "Holm"
    ],
    "name:ceb_x_preferred":[
        "Holm"
    ],
    "name:dan_x_preferred":[
        "Holm"
    ],
    "name:deu_x_preferred":[
        "Holm"
    ],
    "name:epo_x_preferred":[
        "Holm"
    ],
    "name:est_x_preferred":[
        "Holm"
    ],
    "name:eus_x_preferred":[
        "Holm"
    ],
    "name:fin_x_preferred":[
        "Holm"
    ],
    "name:fra_x_preferred":[
        "Holm"
    ],
    "name:heb_x_preferred":[
        "\u05d4\u05d5\u05dc\u05dd"
    ],
    "name:hun_x_preferred":[
        "Holm"
    ],
    "name:ita_x_preferred":[
        "Holm"
    ],
    "name:jpn_x_preferred":[
        "\u30db\u30eb\u30e0"
    ],
    "name:lav_x_preferred":[
        "Holms"
    ],
    "name:mkd_x_preferred":[
        "\u0425\u043e\u043b\u043c"
    ],
    "name:nds_x_preferred":[
        "Holm"
    ],
    "name:nld_x_preferred":[
        "Holm"
    ],
    "name:nor_x_preferred":[
        "Holm"
    ],
    "name:pol_x_preferred":[
        "Holm"
    ],
    "name:ron_x_preferred":[
        "Holm"
    ],
    "name:rus_x_preferred":[
        "\u0425\u043e\u043b\u044c\u043c"
    ],
    "name:spa_x_preferred":[
        "Holm"
    ],
    "name:srp_x_preferred":[
        "\u0425\u043e\u043b\u043c"
    ],
    "name:swe_x_preferred":[
        "Holm"
    ],
    "qs_pg:aaroncc":"NO",
    "qs_pg:gn_country":"NO",
    "qs_pg:gn_fcode":"PPL",
    "qs_pg:gn_pop":0,
    "qs_pg:name":"Holm",
    "qs_pg:name_adm0":"Norge",
    "qs_pg:name_adm1":"\u00d8stfold Fylke",
    "qs_pg:photos":21,
    "qs_pg:photos_1k":4,
    "qs_pg:photos_9k":1,
    "qs_pg:photos_9r":1,
    "qs_pg:photos_all":21,
    "qs_pg:photos_sr":1,
    "qs_pg:pop_sr":0,
    "qs_pg:qs_pg_placetype":"locality",
    "qs_pg:qs_pg_placetype_gp":"Town",
    "qs_pg:woe_adm0":23424910,
    "woe:adm0_id":23424910,
    "woe:name_adm0":"Norge",
    "woe:name_adm1":"\u00d8stfold Fylke",
    "woe:placetype":"Town",
    "wof:name":"Holm",
    "wof:placetype":"locality"
},
  "geometry": {"coordinates":[10.23333,59.55],"type":"Point"}
}