{
  "type": "Feature",
  "properties": {
    "gn:country":"NO",
    "gn:fcode":"PPL",
    "gn:population":534,
    "iso:country":"NO",
    "name:ceb_x_preferred":[
        "Sandeid"
    ],
    "name:eng_x_preferred":[
        "Sandeid"
    ],
    "name:fra_x_preferred":[
        "Sandeid"
    ],
    "name:msa_x_preferred":[
        "Sandeid"
    ],
    "name:nld_x_preferred":[
        "Sandeid"
    ],
    "name:nno_x_preferred":[
        "Sandeid"
    ],
    "name:nob_x_preferred":[
        "Sandeid"
    ],
    "name:ron_x_preferred":[
        "Sandeid"
    ],
    "name:spa_x_preferred":[
        "Sandeid"
    ],
    "qs_pg:aaroncc":"NO",
    "qs_pg:gn_country":"NO",
    "qs_pg:gn_fcode":"PPL",
    "qs_pg:gn_pop":534,
    "qs_pg:name":"Sandeid",
    "qs_pg:name_adm0":"Norge",
    "qs_pg:name_adm1":"Rogaland Fylke",
    "qs_pg:photos":62,
    "qs_pg:photos_1k":13,
    "qs_pg:photos_9k":1,
    "qs_pg:photos_9r":2,
    "qs_pg:photos_all":62,
    "qs_pg:photos_sr":2,
    "qs_pg:pop_sr":2,
    "qs_pg:qs_pg_placetype":"locality",
    "qs_pg:qs_pg_placetype_gp":"Town",
    "qs_pg:woe_adm0":23424910,
    "woe:adm0_id":23424910,
    "woe:name_adm0":"Norge",
    "woe:name_adm1":"Rogaland Fylke",
    "woe:placetype":"Town",
    "wof:name":"Sandeid",
    "wof:placetype":"locality",
    "wof:population":534
},
  "geometry": {"coordinates":[5.83333,59.55],"type":"Point"}
}