{
  "type": "Feature",
  "properties": {
    "gn:admin1_code":"21.0",
    "gn:admin2_code":"5051.0",
    "gn:asciiname":"Soraa",
    "gn:country_code":"NO",
    "gn:dem":20,
    "gn:feature_class":"P",
    "gn:feature_code":"PPL",
    "gn:name":"S\u00f8r\u00e5a",
    "gn:population":0,
    "gn:timezone":"Europe/Oslo",
    "iso:country":"NO",
    "wof:name":"Soraa",
    "wof:placetype":"locality"
},
  "geometry": {"coordinates":[11.42342,64.87971999999999],"type":"Point"}
}