{
  "type": "Feature",
  "properties": {
    "gn:admin1_code":"6",
    "gn:admin2_code":"415.0",
    "gn:asciiname":"Ebru",
    "gn:country_code":"NO",
    "gn:dem":260,
    "gn:feature_class":"P",
    "gn:feature_code":"PPL",
    "gn:name":"Ebru",
    "gn:population":0,
    "gn:timezone":"Europe/Oslo",
    "iso:country":"NO",
    "name:bre_x_preferred":[
        "Ebru"
    ],
    "name:fra_x_preferred":[
        "Ebru"
    ],
    "name:tur_x_preferred":[
        "Ebru"
    ],
    "wof:name":"Ebru",
    "wof:placetype":"locality"
},
  "geometry": {"coordinates":[11.41667,60.86666999999999],"type":"Point"}
}