{
  "type": "Feature",
  "properties": {
    "gn:admin1_code":"15",
    "gn:admin2_code":"1438.0",
    "gn:asciiname":"Dyrstad",
    "gn:country_code":"NO",
    "gn:dem":-9999,
    "gn:feature_class":"P",
    "gn:feature_code":"PPL",
    "gn:name":"Dyrstad",
    "gn:population":0,
    "gn:timezone":"Europe/Oslo",
    "iso:country":"NO",
    "wof:name":"Dyrstad",
    "wof:placetype":"locality"
},
  "geometry": {"coordinates":[5.18333,61.76667],"type":"Point"}
}