{
  "type": "Feature",
  "properties": {
    "gn:admin1_code":"17.0",
    "gn:admin2_code":"827.0",
    "gn:asciiname":"Tjornegrendi",
    "gn:country_code":"NO",
    "gn:dem":480,
    "gn:feature_class":"P",
    "gn:feature_code":"PPL",
    "gn:name":"Tj\u00f8rnegrendi",
    "gn:population":0,
    "gn:timezone":"Europe/Oslo",
    "iso:country":"NO",
    "name:nor_x_preferred":[
        "Tj\u00f8rnegrendi"
    ],
    "wof:name":"Tjornegrendi",
    "wof:placetype":"locality"
},
  "geometry": {"coordinates":[8.82659,59.73416],"type":"Point"}
}