{
  "type": "Feature",
  "properties": {
    "gn:admin1_code":"13.0",
    "gn:admin2_code":"138.0",
    "gn:asciiname":"Svenneby",
    "gn:country_code":"NO",
    "gn:dem":154,
    "gn:feature_class":"P",
    "gn:feature_code":"PPL",
    "gn:name":"Svenneby",
    "gn:population":0,
    "gn:timezone":"Europe/Oslo",
    "iso:country":"NO",
    "wof:name":"Svenneby",
    "wof:placetype":"locality"
},
  "geometry": {"coordinates":[11.05,59.68333000000001],"type":"Point"}
}