{
  "type": "Feature",
  "properties": {
    "gn:admin1_code":"7",
    "gn:admin2_code":"1259.0",
    "gn:asciiname":"Sele",
    "gn:cc2":"NO",
    "gn:country_code":"NO",
    "gn:dem":20,
    "gn:feature_class":"P",
    "gn:feature_code":"PPL",
    "gn:name":"Sele",
    "gn:population":0,
    "gn:timezone":"Europe/Oslo",
    "iso:country":"NO",
    "name:bos_x_preferred":[
        "Sele"
    ],
    "name:ceb_x_preferred":[
        "Sele"
    ],
    "name:dan_x_preferred":[
        "Sele"
    ],
    "name:deu_x_preferred":[
        "Sele"
    ],
    "name:hrv_x_preferred":[
        "Sele"
    ],
    "name:nld_x_preferred":[
        "Sele"
    ],
    "name:nor_x_preferred":[
        "Sele"
    ],
    "name:pms_x_preferred":[
        "Sele"
    ],
    "name:pol_x_preferred":[
        "Sele"
    ],
    "name:rus_x_preferred":[
        "\u0421\u0435\u043b\u0435"
    ],
    "name:slv_x_preferred":[
        "Sele"
    ],
    "name:srp_x_preferred":[
        "\u0421\u0435\u043b\u0435"
    ],
    "name:swe_x_preferred":[
        "Sele"
    ],
    "name:und_x_variant":[
        "S\u00e6le"
    ],
    "wof:name":"Sele",
    "wof:placetype":"locality"
},
  "geometry": {"coordinates":[4.89417,60.53139],"type":"Point"}
}