{
  "type": "Feature",
  "properties": {
    "gn:admin1_code":"7",
    "gn:admin2_code":"1259.0",
    "gn:asciiname":"Sele",
    "gn:cc2":"NO",
    "gn:country_code":"NO",
    "gn:dem":20,
    "gn:feature_class":"P",
    "gn:feature_code":"PPL",
    "gn:name":"Sele",
    "gn:population":0,
    "gn:timezone":"Europe/Oslo",
    "iso:country":"NO",
    "name:und_x_variant":[
        "S\u00e6le",
        "Sele"
    ],
    "wof:name":"Sele",
    "wof:placetype":"locality"
},
  "geometry": {"coordinates":[4.89417,60.53139],"type":"Point"}
}