{
  "type": "Feature",
  "properties": {
    "gn:admin1_code":"14.0",
    "gn:admin2_code":"1134.0",
    "gn:asciiname":"Vormestrand",
    "gn:country_code":"NO",
    "gn:dem":22,
    "gn:feature_class":"P",
    "gn:feature_code":"PPL",
    "gn:name":"Vormestrand",
    "gn:population":0,
    "gn:timezone":"Europe/Oslo",
    "iso:country":"NO",
    "wof:name":"Vormestrand",
    "wof:placetype":"locality"
},
  "geometry": {"coordinates":[5.91694,59.42174],"type":"Point"}
}