{
  "type": "Feature",
  "properties": {
    "gn:admin1_code":"21.0",
    "gn:admin2_code":"5027.0",
    "gn:asciiname":"Saeter",
    "gn:country_code":"NO",
    "gn:dem":540,
    "gn:feature_class":"P",
    "gn:feature_code":"PPL",
    "gn:name":"S\u00e6ter",
    "gn:population":0,
    "gn:timezone":"Europe/Oslo",
    "iso:country":"NO",
    "name:nor_x_preferred":[
        "S\u00e6ter"
    ],
    "wof:name":"Saeter",
    "wof:placetype":"locality"
},
  "geometry": {"coordinates":[10.39815,62.90405],"type":"Point"}
}