{
  "type": "Feature",
  "properties": {
    "gn:admin1_code":"14",
    "gn:admin2_code":"1106",
    "gn:asciiname":"Rossabo",
    "gn:country_code":"NO",
    "gn:dem":30,
    "gn:feature_class":"P",
    "gn:feature_code":"PPL",
    "gn:name":"Rossab\u00f8",
    "gn:population":0,
    "gn:timezone":"Europe/Oslo",
    "iso:country":"NO",
    "name:nor_x_preferred":[
        "Rossab\u00f8"
    ],
    "wof:name":"Rossabo",
    "wof:placetype":"neighbourhood"
},
  "geometry": {"coordinates":[5.29663,59.39856],"type":"Point"}
}