{
  "type": "Feature",
  "properties": {
    "gn:admin1_code":"15",
    "gn:admin2_code":"1438.0",
    "gn:asciiname":"Lovikneset",
    "gn:cc2":"NO",
    "gn:country_code":"NO",
    "gn:dem":8,
    "gn:feature_class":"P",
    "gn:feature_code":"PPL",
    "gn:name":"L\u00f8vikneset",
    "gn:population":0,
    "gn:timezone":"Europe/Oslo",
    "iso:country":"NO",
    "name:und_x_variant":[
        "L\u00f6vikn\u00e6s",
        "L\u00f8vikneset"
    ],
    "wof:name":"Lovikneset",
    "wof:placetype":"locality"
},
  "geometry": {"coordinates":[4.95,61.81667],"type":"Point"}
}