{
  "type": "Feature",
  "properties": {
    "gn:country":"NO",
    "iso:country":"NO",
    "qs_pg:aaroncc":"NO",
    "qs_pg:gn_country":"NO",
    "qs_pg:name":"Storemolla",
    "qs_pg:name_adm0":"Norge",
    "qs_pg:name_adm1":"Nordland Fylke",
    "qs_pg:photos":71,
    "qs_pg:photos_1k":14,
    "qs_pg:photos_9k":1,
    "qs_pg:photos_9r":2,
    "qs_pg:photos_all":71,
    "qs_pg:photos_sr":2,
    "qs_pg:pop_sr":0,
    "qs_pg:qs_pg_placetype":"locality",
    "qs_pg:qs_pg_placetype_gp":"Town",
    "qs_pg:woe_adm0":23424910,
    "woe:adm0_id":23424910,
    "woe:name_adm0":"Norge",
    "woe:name_adm1":"Nordland Fylke",
    "woe:placetype":"Town",
    "wof:name":"Storemolla",
    "wof:placetype":"locality"
},
  "geometry": {"coordinates":[14.867591,68.287239],"type":"Point"}
}