{
  "type": "Feature",
  "properties": {
    "iso:country":"NO",
    "qs_pg:aaroncc":"NO",
    "qs_pg:name":"Larsbyen",
    "qs_pg:name_adm0":"Norge",
    "qs_pg:name_adm1":"S\u00f8r-Tr\u00f8ndelag Fylke",
    "qs_pg:photos":38,
    "qs_pg:photos_1k":8,
    "qs_pg:photos_9k":1,
    "qs_pg:photos_9r":2,
    "qs_pg:photos_all":38,
    "qs_pg:photos_sr":2,
    "qs_pg:pop_sr":0,
    "qs_pg:qs_pg_placetype":"neighbourhood",
    "qs_pg:qs_pg_placetype_gp":"Suburb",
    "qs_pg:woe_adm0":23424910,
    "woe:adm0_id":23424910,
    "woe:name_adm0":"Norge",
    "woe:name_adm1":"S\u00f8r-Tr\u00f8ndelag Fylke",
    "woe:placetype":"Suburb",
    "wof:name":"Larsbyen",
    "wof:placetype":"neighbourhood"
},
  "geometry": {"coordinates":[10.318334,63.3946875],"type":"Point"}
}