{
  "type": "Feature",
  "properties": {
    "gn:country":"NO",
    "gn:fcode":"PPL",
    "gn:population":0,
    "iso:country":"NO",
    "name:deu_x_preferred":[
        "Heddal"
    ],
    "name:ita_x_preferred":[
        "Heddal"
    ],
    "name:msa_x_preferred":[
        "Heddal"
    ],
    "name:nno_x_preferred":[
        "Heddal"
    ],
    "name:nor_x_preferred":[
        "Eiddal"
    ],
    "name:nor_x_variant":[
        "Eidal",
        "Heddal"
    ],
    "name:pol_x_preferred":[
        "Heddal"
    ],
    "name:spa_x_preferred":[
        "Heddal"
    ],
    "qs_pg:aaroncc":"NO",
    "qs_pg:gn_country":"NO",
    "qs_pg:gn_fcode":"PPL",
    "qs_pg:gn_pop":0,
    "qs_pg:name":"Heddal",
    "qs_pg:name_adm0":"Norge",
    "qs_pg:name_adm1":"Telemark Fylke",
    "qs_pg:photos":356,
    "qs_pg:photos_1k":72,
    "qs_pg:photos_9k":2,
    "qs_pg:photos_9r":5,
    "qs_pg:photos_all":356,
    "qs_pg:photos_sr":6,
    "qs_pg:pop_sr":0,
    "qs_pg:qs_pg_placetype":"locality",
    "qs_pg:qs_pg_placetype_gp":"Town",
    "qs_pg:woe_adm0":23424910,
    "woe:adm0_id":23424910,
    "woe:name_adm0":"Norge",
    "woe:name_adm1":"Telemark Fylke",
    "woe:placetype":"Town",
    "wof:name":"Heddal",
    "wof:placetype":"locality"
},
  "geometry": {"coordinates":[9.53333,60.08333],"type":"Point"}
}