{
  "type": "Feature",
  "properties": {
    "gn:admin1_code":"7",
    "gn:admin2_code":"1219",
    "gn:asciiname":"Ovra Skimmeland",
    "gn:country_code":"NO",
    "gn:dem":25,
    "gn:feature_class":"P",
    "gn:feature_code":"PPLL",
    "gn:name":"\u00d8vra Skimmeland",
    "gn:population":0,
    "gn:timezone":"Europe/Oslo",
    "iso:country":"NO",
    "name:nor_x_preferred":[
        "\u00d8vra Skimmeland"
    ],
    "wof:name":"Ovra Skimmeland",
    "wof:placetype":"neighbourhood"
},
  "geometry": {"coordinates":[5.36424,59.69704],"type":"Point"}
}