{
  "type": "Feature",
  "properties": {
    "gn:admin1_code":"11.0",
    "gn:admin2_code":"538.0",
    "gn:asciiname":"Fagerlund",
    "gn:country_code":"NO",
    "gn:dem":480,
    "gn:feature_class":"P",
    "gn:feature_code":"PPL",
    "gn:name":"Fagerlund",
    "gn:population":0,
    "gn:timezone":"Europe/Oslo",
    "iso:country":"NO",
    "name:nor_x_preferred":[
        "Fagerlund"
    ],
    "wof:name":"Fagerlund",
    "wof:placetype":"locality"
},
  "geometry": {"coordinates":[10.01572,61.00028],"type":"Point"}
}