{
  "type": "Feature",
  "properties": {
    "gn:admin1_code":"1.0",
    "gn:admin2_code":"227.0",
    "gn:asciiname":"Guttersrud",
    "gn:country_code":"NO",
    "gn:dem":112,
    "gn:feature_class":"P",
    "gn:feature_code":"PPL",
    "gn:name":"Guttersrud",
    "gn:population":0,
    "gn:timezone":"Europe/Oslo",
    "iso:country":"NO",
    "wof:name":"Guttersrud",
    "wof:placetype":"locality"
},
  "geometry": {"coordinates":[11.2003,59.96498],"type":"Point"}
}