{
  "type": "Feature",
  "properties": {
    "gn:admin1_code":"9",
    "gn:admin2_code":"1845.0",
    "gn:asciiname":"Djupvik",
    "gn:cc2":"NO",
    "gn:country_code":"NO",
    "gn:dem":80,
    "gn:feature_class":"P",
    "gn:feature_code":"PPL",
    "gn:name":"Djupvik",
    "gn:population":0,
    "gn:timezone":"Europe/Oslo",
    "iso:country":"NO",
    "name:msa_x_preferred":[
        "Djupvik"
    ],
    "name:nld_x_preferred":[
        "Djupvik"
    ],
    "name:swe_x_preferred":[
        "Djupvik"
    ],
    "name:und_x_variant":[
        "Djupvik i Salten"
    ],
    "wof:name":"Djupvik",
    "wof:placetype":"locality"
},
  "geometry": {"coordinates":[15.55,67.36667],"type":"Point"}
}