{
  "type": "Feature",
  "properties": {
    "gn:admin1_code":"8",
    "gn:admin2_code":"1571.0",
    "gn:asciiname":"Fjaerli",
    "gn:cc2":"NO",
    "gn:country_code":"NO",
    "gn:dem":200,
    "gn:feature_class":"P",
    "gn:feature_code":"PPL",
    "gn:name":"Fj\u00e6rli",
    "gn:population":0,
    "gn:timezone":"Europe/Oslo",
    "iso:country":"NO",
    "name:und_x_variant":[
        "Ytre Fj\u00e6rli",
        "Fj\u00e6rlien",
        "Fjer",
        "Fj\u00e6rli"
    ],
    "wof:name":"Fjaerli",
    "wof:placetype":"locality"
},
  "geometry": {"coordinates":[8.61667,63.11666999999999],"type":"Point"}
}