{
  "type": "Feature",
  "properties": {
    "gn:admin1_code":"6.0",
    "gn:admin2_code":"434.0",
    "gn:asciiname":"Somadalen",
    "gn:country_code":"NO",
    "gn:dem":700,
    "gn:feature_class":"P",
    "gn:feature_code":"PPL",
    "gn:name":"S\u00f8m\u00e5dalen",
    "gn:population":0,
    "gn:timezone":"Europe/Oslo",
    "iso:country":"NO",
    "wof:name":"Somadalen",
    "wof:placetype":"locality"
},
  "geometry": {"coordinates":[11.66439,62.10236],"type":"Point"}
}