{
  "type": "Feature",
  "properties": {
    "gn:admin1_code":"5.0",
    "gn:admin2_code":"2021.0",
    "gn:asciiname":"Coallejarnjarga",
    "gn:country_code":"NO",
    "gn:dem":160,
    "gn:feature_class":"P",
    "gn:feature_code":"PPL",
    "gn:name":"\u010coallej\u00e1rnj\u00e1rga",
    "gn:population":0,
    "gn:timezone":"Europe/Oslo",
    "iso:country":"NO",
    "name:sme_x_preferred":[
        "\u010coallej\u00e1rnj\u00e1rga"
    ],
    "wof:name":"Coallejarnjarga",
    "wof:placetype":"locality"
},
  "geometry": {"coordinates":[25.14364,69.41563000000001],"type":"Point"}
}