{
  "type": "Feature",
  "properties": {
    "gn:admin1_code":"7",
    "gn:admin2_code":"1264.0",
    "gn:asciiname":"Borilden",
    "gn:country_code":"NO",
    "gn:dem":1,
    "gn:feature_class":"P",
    "gn:feature_code":"PPL",
    "gn:name":"B\u00f8rilden",
    "gn:population":0,
    "gn:timezone":"Europe/Oslo",
    "iso:country":"NO",
    "wof:name":"Borilden",
    "wof:placetype":"locality"
},
  "geometry": {"coordinates":[4.86667,60.81667],"type":"Point"}
}