{
  "type": "Feature",
  "properties": {
    "gn:admin1_code":"20.0",
    "gn:admin2_code":"712.0",
    "gn:asciiname":"Vaervagen",
    "gn:cc2":"NO",
    "gn:country_code":"NO",
    "gn:dem":-9999,
    "gn:feature_class":"P",
    "gn:feature_code":"PPL",
    "gn:name":"V\u00e6rv\u00e5gen",
    "gn:population":0,
    "gn:timezone":"Europe/Oslo",
    "iso:country":"NO",
    "name:und_x_variant":[
        "V\u00e6rvaagen",
        "V\u00e6rv\u00e5gen"
    ],
    "wof:name":"Vaervagen",
    "wof:placetype":"locality"
},
  "geometry": {"coordinates":[9.83333,58.98333],"type":"Point"}
}