{
  "type": "Feature",
  "properties": {
    "gn:admin1_code":"7.0",
    "gn:admin2_code":"1263.0",
    "gn:asciiname":"Vollo",
    "gn:cc2":"NO",
    "gn:country_code":"NO",
    "gn:dem":1,
    "gn:feature_class":"P",
    "gn:feature_code":"PPLL",
    "gn:name":"Vollo",
    "gn:population":0,
    "gn:timezone":"Europe/Oslo",
    "iso:country":"NO",
    "name:und_x_variant":[
        "Vollom",
        "Vollo"
    ],
    "wof:name":"Vollo",
    "wof:placetype":"locality"
},
  "geometry": {"coordinates":[5.21,60.63944],"type":"Point"}
}