{
  "type": "Feature",
  "properties": {
    "gn:admin1_code":"11",
    "gn:admin2_code":"540.0",
    "gn:asciiname":"Breidablik",
    "gn:country_code":"NO",
    "gn:dem":512,
    "gn:feature_class":"P",
    "gn:feature_code":"PPL",
    "gn:name":"Breidablik",
    "gn:population":0,
    "gn:timezone":"Europe/Oslo",
    "iso:country":"NO",
    "name:dan_x_preferred":[
        "Breidablik"
    ],
    "name:deu_x_preferred":[
        "Breidablik"
    ],
    "name:eus_x_preferred":[
        "Brei\u00f0ablik"
    ],
    "name:fra_x_preferred":[
        "Breidablik"
    ],
    "name:jpn_x_preferred":[
        "\u30d6\u30ec\u30a4\u30b6\u30d6\u30ea\u30af"
    ],
    "name:nld_x_preferred":[
        "Breidablik"
    ],
    "name:nor_x_preferred":[
        "Breidablik"
    ],
    "name:por_x_preferred":[
        "Breidablik"
    ],
    "name:spa_x_preferred":[
        "Brei\u00f0ablik"
    ],
    "name:swe_x_preferred":[
        "Bredablick"
    ],
    "name:ukr_x_preferred":[
        "\u0411\u0440\u0435\u0439\u0434\u0430\u0431\u043b\u0456\u043a"
    ],
    "name:zho_x_preferred":[
        "\u5149\u660e\u5bae"
    ],
    "wof:name":"Breidablik",
    "wof:placetype":"locality"
},
  "geometry": {"coordinates":[9.58333,60.81667],"type":"Point"}
}