{
  "type": "Feature",
  "properties": {
    "gn:admin1_code":"4.0",
    "gn:admin2_code":"605.0",
    "gn:asciiname":"Haegglien",
    "gn:country_code":"NO",
    "gn:dem":240,
    "gn:feature_class":"P",
    "gn:feature_code":"PPL",
    "gn:name":"H\u00e6gglien",
    "gn:population":0,
    "gn:timezone":"Europe/Oslo",
    "iso:country":"NO",
    "name:nor_x_preferred":[
        "H\u00e6gglien"
    ],
    "name:nor_x_variant":[
        "Heggelia"
    ],
    "wof:name":"Haegglien",
    "wof:placetype":"locality"
},
  "geometry": {"coordinates":[10.11444,60.22781],"type":"Point"}
}