{
  "type": "Feature",
  "properties": {
    "gn:admin1_code":"9",
    "gn:admin2_code":"1848.0",
    "gn:asciiname":"Breidvik",
    "gn:cc2":"NO",
    "gn:country_code":"NO",
    "gn:dem":20,
    "gn:feature_class":"P",
    "gn:feature_code":"PPL",
    "gn:name":"Breidvik",
    "gn:population":0,
    "gn:timezone":"Europe/Oslo",
    "iso:country":"NO",
    "name:und_x_variant":[
        "Breivik",
        "Breidvik"
    ],
    "wof:name":"Breidvik",
    "wof:placetype":"locality"
},
  "geometry": {"coordinates":[15.15,67.71666999999999],"type":"Point"}
}