{
  "type": "Feature",
  "properties": {
    "gn:admin1_code":"13",
    "gn:admin2_code":"106",
    "gn:asciiname":"Nokleby",
    "gn:country_code":"NO",
    "gn:dem":9,
    "gn:feature_class":"P",
    "gn:feature_code":"PPLL",
    "gn:name":"N\u00f8kleby",
    "gn:population":0,
    "gn:timezone":"Europe/Oslo",
    "iso:country":"NO",
    "name:nor_x_preferred":[
        "N\u00f8kleby"
    ],
    "wof:name":"Nokleby",
    "wof:placetype":"neighbourhood"
},
  "geometry": {"coordinates":[10.98794,59.23617],"type":"Point"}
}