{
  "type": "Feature",
  "properties": {
    "gn:admin1_code":"17",
    "gn:admin2_code":"827.0",
    "gn:asciiname":"Hovde",
    "gn:country_code":"NO",
    "gn:dem":566,
    "gn:feature_class":"P",
    "gn:feature_code":"PPL",
    "gn:name":"Hovde",
    "gn:population":0,
    "gn:timezone":"Europe/Oslo",
    "iso:country":"NO",
    "wof:name":"Hovde",
    "wof:placetype":"locality"
},
  "geometry": {"coordinates":[8.81992,59.75048],"type":"Point"}
}