{
  "type": "Feature",
  "properties": {
    "gn:admin1_code":"11.0",
    "gn:admin2_code":"534.0",
    "gn:asciiname":"Toverud",
    "gn:country_code":"NO",
    "gn:dem":135,
    "gn:feature_class":"P",
    "gn:feature_code":"PPL",
    "gn:name":"Toverud",
    "gn:population":0,
    "gn:timezone":"Europe/Oslo",
    "iso:country":"NO",
    "wof:name":"Toverud",
    "wof:placetype":"locality"
},
  "geometry": {"coordinates":[10.38333,60.41667],"type":"Point"}
}