{
  "type": "Feature",
  "properties": {
    "gn:admin1_code":"6.0",
    "gn:admin2_code":"402.0",
    "gn:asciiname":"Skullerud",
    "gn:country_code":"NO",
    "gn:dem":218,
    "gn:feature_class":"P",
    "gn:feature_code":"PPL",
    "gn:name":"Skullerud",
    "gn:population":0,
    "gn:timezone":"Europe/Oslo",
    "iso:country":"NO",
    "name:nor_x_preferred":[
        "Skullerud"
    ],
    "wof:name":"Skullerud",
    "wof:placetype":"locality"
},
  "geometry": {"coordinates":[12.32511,60.1037],"type":"Point"}
}