{
  "type": "Feature",
  "properties": {
    "gn:admin1_code":"15",
    "gn:admin2_code":"1441.0",
    "gn:asciiname":"Hoddevik",
    "gn:cc2":"NO",
    "gn:country_code":"NO",
    "gn:dem":60,
    "gn:feature_class":"P",
    "gn:feature_code":"PPL",
    "gn:name":"Hoddevik",
    "gn:population":0,
    "gn:timezone":"Europe/Oslo",
    "iso:country":"NO",
    "name:und_x_variant":[
        "Hovdevik",
        "Hoddevik"
    ],
    "wof:name":"Hoddevik",
    "wof:placetype":"locality"
},
  "geometry": {"coordinates":[5.16667,62.11666999999999],"type":"Point"}
}