{
  "type": "Feature",
  "properties": {
    "gn:gn_country":"NO",
    "gn:gn_fcode":"PPL",
    "gn:gn_pop":0,
    "iso:country":"NO",
    "name:dut_x_preferred":[
        "Saltr\u00f8d"
    ],
    "name:eng_x_preferred":[
        "Saltr\u00f8d"
    ],
    "name:fre_x_preferred":[
        "Saltr\u00f8d"
    ],
    "name:jav_x_preferred":[
        "Saltr\u00f8d"
    ],
    "name:may_x_preferred":[
        "Saltr\u00f8d"
    ],
    "name:nob_x_preferred":[
        "Saltr\u00f8d"
    ],
    "name:rum_x_preferred":[
        "Saltr\u00f8d"
    ],
    "qs_pg:aaroncc":"NO",
    "qs_pg:gn_country":"NO",
    "qs_pg:gn_fcode":"PPL",
    "qs_pg:gn_pop":0,
    "qs_pg:name":"Salter\u00f8d",
    "qs_pg:name_adm0":"Norge",
    "qs_pg:name_adm1":"Aust-Agder Fylke",
    "qs_pg:photos":43,
    "qs_pg:photos_1k":9,
    "qs_pg:photos_9k":1,
    "qs_pg:photos_9r":2,
    "qs_pg:photos_all":43,
    "qs_pg:photos_sr":2,
    "qs_pg:pop_sr":0,
    "qs_pg:qs_pg_placetype":"locality",
    "qs_pg:qs_pg_placetype_gp":"Town",
    "qs_pg:woe_adm0":23424910,
    "woe:adm0_id":23424910,
    "woe:name_adm0":"Norge",
    "woe:name_adm1":"Aust-Agder Fylke",
    "woe:placetype":"Town",
    "wof:name":"Salter\u00f8d",
    "wof:placetype":"locality"
},
  "geometry": {"coordinates":[8.84361,58.49083],"type":"Point"}
}