{
  "type": "Feature",
  "properties": {
    "gn:admin1_code":"6.0",
    "gn:admin2_code":"427.0",
    "gn:asciiname":"Nordre Agassaeter",
    "gn:country_code":"NO",
    "gn:dem":360,
    "gn:feature_class":"P",
    "gn:feature_code":"PPL",
    "gn:name":"Nordre Ag\u00e5ss\u00e6ter",
    "gn:population":0,
    "gn:timezone":"Europe/Oslo",
    "iso:country":"NO",
    "name:nor_x_preferred":[
        "Nordre Ag\u00e5ss\u00e6ter"
    ],
    "wof:name":"Nordre Agassaeter",
    "wof:placetype":"locality"
},
  "geometry": {"coordinates":[11.77456,60.85729],"type":"Point"}
}