{
  "type": "Feature",
  "properties": {
    "gn:country":"NO",
    "gn:fcode":"PPL",
    "gn:population":0,
    "iso:country":"NO",
    "name:ceb_x_preferred":[
        "Vikav\u00e5gen"
    ],
    "name:eng_x_preferred":[
        "Vikav\u00e5gen"
    ],
    "name:fra_x_preferred":[
        "Vikav\u00e5gen"
    ],
    "name:jav_x_preferred":[
        "Vikav\u00e5gen"
    ],
    "name:msa_x_preferred":[
        "Vikav\u00e5gen"
    ],
    "name:nld_x_preferred":[
        "Vikav\u00e5gen"
    ],
    "name:spa_x_preferred":[
        "Vikav\u00e5gen"
    ],
    "qs_pg:aaroncc":"NO",
    "qs_pg:gn_country":"NO",
    "qs_pg:gn_fcode":"PPL",
    "qs_pg:gn_pop":0,
    "qs_pg:name":"Vikav\u00e5g",
    "qs_pg:name_adm0":"Norge",
    "qs_pg:name_adm1":"Hordaland Fylke",
    "qs_pg:photos":18,
    "qs_pg:photos_1k":4,
    "qs_pg:photos_9k":1,
    "qs_pg:photos_9r":1,
    "qs_pg:photos_all":18,
    "qs_pg:photos_sr":1,
    "qs_pg:pop_sr":0,
    "qs_pg:qs_pg_placetype":"locality",
    "qs_pg:qs_pg_placetype_gp":"Town",
    "qs_pg:woe_adm0":23424910,
    "woe:adm0_id":23424910,
    "woe:name_adm0":"Norge",
    "woe:name_adm1":"Hordaland Fylke",
    "woe:placetype":"Town",
    "wof:name":"Vikav\u00e5g",
    "wof:placetype":"locality"
},
  "geometry": {"coordinates":[4.9575,60.46889],"type":"Point"}
}