{
  "type": "Feature",
  "properties": {
    "gn:admin1_code":"14",
    "gn:admin2_code":"1134.0",
    "gn:asciiname":"Fjetland",
    "gn:country_code":"NO",
    "gn:dem":325,
    "gn:feature_class":"P",
    "gn:feature_code":"PPL",
    "gn:name":"Fjetland",
    "gn:population":0,
    "gn:timezone":"Europe/Oslo",
    "iso:country":"NO",
    "wof:name":"Fjetland",
    "wof:placetype":"locality"
},
  "geometry": {"coordinates":[6.06667,59.43333000000001],"type":"Point"}
}