{
  "type": "Feature",
  "properties": {
    "gn:admin1_code":"21",
    "gn:admin2_code":"5023",
    "gn:asciiname":"Dragsetmoen",
    "gn:country_code":"NO",
    "gn:dem":132,
    "gn:feature_class":"P",
    "gn:feature_code":"PPLL",
    "gn:name":"Dragsetmoen",
    "gn:population":0,
    "gn:timezone":"Europe/Oslo",
    "iso:country":"NO",
    "name:nor_x_preferred":[
        "Dragsetmoen"
    ],
    "name:nor_x_variant":[
        "Drogsetmoen"
    ],
    "wof:name":"Dragsetmoen",
    "wof:placetype":"locality"
},
  "geometry": {"coordinates":[9.61175,63.1184],"type":"Point"}
}