{
  "type": "Feature",
  "properties": {
    "gn:admin1_code":"9.0",
    "gn:admin2_code":"1850.0",
    "gn:asciiname":"Sommarset",
    "gn:country_code":"NO",
    "gn:dem":-9999,
    "gn:feature_class":"P",
    "gn:feature_code":"PPL",
    "gn:name":"Sommarset",
    "gn:population":0,
    "gn:timezone":"Europe/Oslo",
    "iso:country":"NO",
    "name:nor_x_preferred":[
        "Sommarset"
    ],
    "wof:name":"Sommarset",
    "wof:placetype":"locality"
},
  "geometry": {"coordinates":[16.04001,68.19438000000001],"type":"Point"}
}