{
  "type": "Feature",
  "properties": {
    "gn:admin1_code":"18.0",
    "gn:admin2_code":"1913.0",
    "gn:asciiname":"Marrskardet",
    "gn:country_code":"NO",
    "gn:dem":1,
    "gn:feature_class":"P",
    "gn:feature_code":"PPL",
    "gn:name":"Marrskardet",
    "gn:population":0,
    "gn:timezone":"Europe/Oslo",
    "iso:country":"NO",
    "name:nor_x_preferred":[
        "Marrskardet"
    ],
    "wof:name":"Marrskardet",
    "wof:placetype":"locality"
},
  "geometry": {"coordinates":[17.13287,68.64440999999999],"type":"Point"}
}