{
  "type": "Feature",
  "properties": {
    "gn:admin1_code":"19.0",
    "gn:admin2_code":"1001.0",
    "gn:asciiname":"Krageboen",
    "gn:country_code":"NO",
    "gn:dem":43,
    "gn:feature_class":"P",
    "gn:feature_code":"PPL",
    "gn:name":"Krageboen",
    "gn:population":0,
    "gn:timezone":"Europe/Oslo",
    "iso:country":"NO",
    "name:nor_x_preferred":[
        "Krageboen"
    ],
    "wof:name":"Krageboen",
    "wof:placetype":"locality"
},
  "geometry": {"coordinates":[8.13547,58.24461],"type":"Point"}
}