{
  "type": "Feature",
  "properties": {
    "gn:admin1_code":"1",
    "gn:admin2_code":"221.0",
    "gn:asciiname":"Lierfoss",
    "gn:country_code":"NO",
    "gn:dem":136,
    "gn:feature_class":"P",
    "gn:feature_code":"PPL",
    "gn:name":"Lierfoss",
    "gn:population":0,
    "gn:timezone":"Europe/Oslo",
    "iso:country":"NO",
    "wof:name":"Lierfoss",
    "wof:placetype":"locality"
},
  "geometry": {"coordinates":[11.53184,59.91867],"type":"Point"}
}