{
  "type": "Feature",
  "properties": {
    "gn:admin1_code":"9",
    "gn:admin2_code":"1804.0",
    "gn:asciiname":"Heggmoen",
    "gn:cc2":"NO",
    "gn:country_code":"NO",
    "gn:dem":60,
    "gn:feature_class":"P",
    "gn:feature_code":"PPL",
    "gn:name":"Heggmoen",
    "gn:population":0,
    "gn:timezone":"Europe/Oslo",
    "iso:country":"NO",
    "name:und_x_variant":[
        "Hegmoen",
        "Heggmoen"
    ],
    "wof:name":"Heggmoen",
    "wof:placetype":"locality"
},
  "geometry": {"coordinates":[14.86667,67.34999999999999],"type":"Point"}
}