{
  "type": "Feature",
  "properties": {
    "gn:admin1_code":"4",
    "gn:admin2_code":"617.0",
    "gn:asciiname":"Liagardan",
    "gn:cc2":"NO",
    "gn:country_code":"NO",
    "gn:dem":480,
    "gn:feature_class":"P",
    "gn:feature_code":"PPL",
    "gn:name":"Liagardan",
    "gn:population":0,
    "gn:timezone":"Europe/Oslo",
    "iso:country":"NO",
    "name:nor_x_preferred":[
        "Liagardan"
    ],
    "name:nor_x_variant":[
        "Liagardann",
        "Liagardane"
    ],
    "wof:name":"Liagardan",
    "wof:placetype":"locality"
},
  "geometry": {"coordinates":[9.03046,60.69447],"type":"Point"}
}