{
  "type": "Feature",
  "properties": {
    "gn:admin1_code":"6.0",
    "gn:admin2_code":"437.0",
    "gn:asciiname":"Kvikne",
    "gn:country_code":"NO",
    "gn:dem":750,
    "gn:feature_class":"P",
    "gn:feature_code":"PPL",
    "gn:name":"Kvikne",
    "gn:population":0,
    "gn:timezone":"Europe/Oslo",
    "iso:country":"NO",
    "name:dan_x_preferred":[
        "Kvikne"
    ],
    "name:gla_x_preferred":[
        "Kvikne"
    ],
    "name:jav_x_preferred":[
        "Kvikne"
    ],
    "name:msa_x_preferred":[
        "Kvikne"
    ],
    "name:nld_x_preferred":[
        "Kvikne"
    ],
    "name:nno_x_preferred":[
        "Kvikne"
    ],
    "name:nor_x_preferred":[
        "Kvikne"
    ],
    "name:pol_x_preferred":[
        "Kvikne"
    ],
    "name:por_x_preferred":[
        "Kvikne"
    ],
    "name:spa_x_preferred":[
        "Kvikne"
    ],
    "wof:name":"Kvikne",
    "wof:placetype":"locality"
},
  "geometry": {"coordinates":[10.33138,62.57895],"type":"Point"}
}