{
  "type": "Feature",
  "properties": {
    "gn:admin1_code":"11.0",
    "gn:admin2_code":"514.0",
    "gn:asciiname":"Synstnes",
    "gn:country_code":"NO",
    "gn:dem":480,
    "gn:feature_class":"P",
    "gn:feature_code":"PPL",
    "gn:name":"Synstnes",
    "gn:population":0,
    "gn:timezone":"Europe/Oslo",
    "iso:country":"NO",
    "wof:name":"Synstnes",
    "wof:placetype":"locality"
},
  "geometry": {"coordinates":[8.51667,61.85],"type":"Point"}
}