{
  "type": "Feature",
  "properties": {
    "gn:gn_country":"NO",
    "gn:gn_fcode":"PPL",
    "gn:gn_pop":349,
    "gn:population":349,
    "iso:country":"NO",
    "name:dut_x_preferred":[
        "Lovund"
    ],
    "name:eng_x_preferred":[
        "Lovund"
    ],
    "name:fre_x_preferred":[
        "Lovund"
    ],
    "name:jav_x_preferred":[
        "Lovund"
    ],
    "name:may_x_preferred":[
        "Lovund"
    ],
    "name:nno_x_preferred":[
        "Lovund"
    ],
    "name:nob_x_preferred":[
        "Lovund"
    ],
    "name:rum_x_preferred":[
        "Lovund"
    ],
    "name:rus_x_preferred":[
        "\u041b\u043e\u0432\u0443\u043d\u043d"
    ],
    "name:unk_x_variant":[
        "Lovunden"
    ],
    "qs_pg:aaroncc":"NO",
    "qs_pg:gn_country":"NO",
    "qs_pg:gn_fcode":"PPL",
    "qs_pg:gn_pop":349,
    "qs_pg:name":"Lovund",
    "qs_pg:photos_9r":0,
    "qs_pg:photos_sr":0,
    "qs_pg:pop_sr":2,
    "qs_pg:qs_pg_placetype":"locality",
    "wof:name":"Lovund",
    "wof:placetype":"locality",
    "wof:population":349
},
  "geometry": {"coordinates":[12.38333,66.36667],"type":"Point"}
}