{
  "type": "Feature",
  "properties": {
    "gn:admin1_code":"11",
    "gn:admin2_code":"533.0",
    "gn:asciiname":"Flatla",
    "gn:country_code":"NO",
    "gn:dem":240,
    "gn:feature_class":"P",
    "gn:feature_code":"PPL",
    "gn:name":"Flatla",
    "gn:population":0,
    "gn:timezone":"Europe/Oslo",
    "iso:country":"NO",
    "wof:name":"Flatla",
    "wof:placetype":"locality"
},
  "geometry": {"coordinates":[10.56667,60.31667],"type":"Point"}
}