{
  "type": "Feature",
  "properties": {
    "gn:admin1_code":"7",
    "gn:admin2_code":"1201.0",
    "gn:asciiname":"Bjorge",
    "gn:country_code":"NO",
    "gn:dem":3,
    "gn:feature_class":"P",
    "gn:feature_code":"PPL",
    "gn:name":"Bj\u00f8rge",
    "gn:population":0,
    "gn:timezone":"Europe/Oslo",
    "iso:country":"NO",
    "name:und_x_variant":[
        "Bj\u00f8rgi"
    ],
    "wof:name":"Bjorge",
    "wof:placetype":"neighbourhood"
},
  "geometry": {"coordinates":[5.24969,60.33367],"type":"Point"}
}