{
  "type": "Feature",
  "properties": {
    "gn:admin1_code":"19",
    "gn:admin2_code":"1003.0",
    "gn:asciiname":"Adneskor",
    "gn:cc2":"NO",
    "gn:country_code":"NO",
    "gn:dem":100,
    "gn:feature_class":"P",
    "gn:feature_code":"PPL",
    "gn:name":"\u00c5dneskor",
    "gn:population":0,
    "gn:timezone":"Europe/Oslo",
    "iso:country":"NO",
    "name:und_x_variant":[
        "Aadneskaar",
        "\u00c5dneskor"
    ],
    "wof:name":"Adneskor",
    "wof:placetype":"locality"
},
  "geometry": {"coordinates":[6.98333,58.08333],"type":"Point"}
}