{
  "type": "Feature",
  "properties": {
    "gn:admin1_code":"6",
    "gn:admin2_code":"427.0",
    "gn:asciiname":"Hovin",
    "gn:country_code":"NO",
    "gn:dem":305,
    "gn:feature_class":"P",
    "gn:feature_code":"PPL",
    "gn:name":"Hovin",
    "gn:population":0,
    "gn:timezone":"Europe/Oslo",
    "iso:country":"NO",
    "name:nno_x_preferred":[
        "Hovin"
    ],
    "name:nor_x_preferred":[
        "Hovin"
    ],
    "wof:name":"Hovin",
    "wof:placetype":"locality"
},
  "geometry": {"coordinates":[11.63333,60.93333000000001],"type":"Point"}
}