{
  "type": "Feature",
  "properties": {
    "gn:admin1_code":"11.0",
    "gn:admin2_code":"545.0",
    "gn:asciiname":"Vevle",
    "gn:country_code":"NO",
    "gn:dem":510,
    "gn:feature_class":"P",
    "gn:feature_code":"PPL",
    "gn:name":"Vevle",
    "gn:population":0,
    "gn:timezone":"Europe/Oslo",
    "iso:country":"NO",
    "wof:name":"Vevle",
    "wof:placetype":"locality"
},
  "geometry": {"coordinates":[8.81667,61.15],"type":"Point"}
}