{
  "type": "Feature",
  "properties": {
    "iso:country":"NO",
    "name:eng_x_preferred":[
        "Straumgjerde"
    ],
    "name:fra_x_preferred":[
        "Straumgjerde"
    ],
    "name:jav_x_preferred":[
        "Straumgjerde"
    ],
    "name:msa_x_preferred":[
        "Straumgjerde"
    ],
    "name:nld_x_preferred":[
        "Straumgjerde"
    ],
    "name:nno_x_preferred":[
        "Straumgjerde"
    ],
    "name:nob_x_preferred":[
        "Straumgjerde"
    ],
    "name:ron_x_preferred":[
        "Straumgjerde"
    ],
    "name:spa_x_preferred":[
        "Straumgjerde"
    ],
    "qs_pg:aaroncc":"NO",
    "qs_pg:name":"Straumgjerde",
    "qs_pg:name_adm0":"Norge",
    "qs_pg:name_adm1":"M\u00f8re og Romsdal Fylke",
    "qs_pg:photos":344,
    "qs_pg:photos_1k":70,
    "qs_pg:photos_9k":2,
    "qs_pg:photos_9r":5,
    "qs_pg:photos_all":344,
    "qs_pg:photos_sr":5,
    "qs_pg:pop_sr":0,
    "qs_pg:qs_pg_placetype":"locality",
    "qs_pg:qs_pg_placetype_gp":"Town",
    "qs_pg:woe_adm0":23424910,
    "woe:adm0_id":23424910,
    "woe:name_adm0":"Norge",
    "woe:name_adm1":"M\u00f8re og Romsdal Fylke",
    "woe:placetype":"Town",
    "wof:name":"Straumgjerde",
    "wof:placetype":"locality"
},
  "geometry": {"coordinates":[6.5760035,62.332038],"type":"Point"}
}