{
  "type": "Feature",
  "properties": {
    "gn:admin1_code":"19",
    "gn:admin2_code":"1029.0",
    "gn:asciiname":"Fidje",
    "gn:country_code":"NO",
    "gn:dem":34,
    "gn:feature_class":"P",
    "gn:feature_code":"PPL",
    "gn:name":"Fidje",
    "gn:population":0,
    "gn:timezone":"Europe/Oslo",
    "iso:country":"NO",
    "wof:name":"Fidje",
    "wof:placetype":"locality"
},
  "geometry": {"coordinates":[7.23333,58.06667],"type":"Point"}
}