{
  "type": "Feature",
  "properties": {
    "gn:admin1_code":"17",
    "gn:admin2_code":"805",
    "gn:asciiname":"Nystrand",
    "gn:country_code":"NO",
    "gn:dem":21,
    "gn:feature_class":"P",
    "gn:feature_code":"PPLL",
    "gn:name":"Nystrand",
    "gn:population":0,
    "gn:timezone":"Europe/Oslo",
    "iso:country":"NO",
    "name:nor_x_preferred":[
        "Nystrand"
    ],
    "wof:name":"Nystrand",
    "wof:placetype":"locality"
},
  "geometry": {"coordinates":[9.70232,59.1096],"type":"Point"}
}