{
  "type": "Feature",
  "properties": {
    "gn:admin1_code":"4",
    "gn:admin2_code":"605.0",
    "gn:asciiname":"Blakstveit",
    "gn:country_code":"NO",
    "gn:dem":340,
    "gn:feature_class":"P",
    "gn:feature_code":"PPL",
    "gn:name":"Blakstveit",
    "gn:population":0,
    "gn:timezone":"Europe/Oslo",
    "iso:country":"NO",
    "wof:name":"Blakstveit",
    "wof:placetype":"locality"
},
  "geometry": {"coordinates":[10.06667,60.46666999999999],"type":"Point"}
}