{
  "type": "Feature",
  "properties": {
    "gn:admin1_code":"6.0",
    "gn:admin2_code":"402.0",
    "gn:asciiname":"Slettholen",
    "gn:country_code":"NO",
    "gn:dem":150,
    "gn:feature_class":"P",
    "gn:feature_code":"PPL",
    "gn:name":"Slettholen",
    "gn:population":0,
    "gn:timezone":"Europe/Oslo",
    "iso:country":"NO",
    "name:nor_x_preferred":[
        "Slettholen"
    ],
    "wof:name":"Slettholen",
    "wof:placetype":"locality"
},
  "geometry": {"coordinates":[11.99048,60.26724],"type":"Point"}
}