{
  "type": "Feature",
  "properties": {
    "gn:admin1_code":"19.0",
    "gn:admin2_code":"1018.0",
    "gn:asciiname":"Tangvall",
    "gn:cc2":"NO",
    "gn:country_code":"NO",
    "gn:dem":15,
    "gn:feature_class":"P",
    "gn:feature_code":"PPLA2",
    "gn:name":"Tangvall",
    "gn:population":0,
    "gn:timezone":"Europe/Oslo",
    "iso:country":"NO",
    "name:msa_x_preferred":[
        "Tangvall"
    ],
    "name:nno_x_preferred":[
        "S\u00f8gne"
    ],
    "name:nor_x_preferred":[
        "Tangvall"
    ],
    "name:ron_x_preferred":[
        "Tangvall"
    ],
    "name:und_x_variant":[
        "Tufteland"
    ],
    "wof:name":"Tangvall",
    "wof:placetype":"neighbourhood"
},
  "geometry": {"coordinates":[7.81529,58.09781],"type":"Point"}
}