{
  "type": "Feature",
  "properties": {
    "gn:country":"NO",
    "gn:fcode":"PPLA2",
    "gn:population":3166,
    "iso:country":"NO",
    "name:ast_x_preferred":[
        "Spydeberg"
    ],
    "name:bpy_x_preferred":[
        "\u09b8\u09cd\u09aa\u09be\u0987\u09a1\u09ac\u09be\u09b0\u09cd\u0997"
    ],
    "name:cat_x_preferred":[
        "Spydeberg"
    ],
    "name:ceb_x_preferred":[
        "Spydeberg"
    ],
    "name:dan_x_preferred":[
        "Spydeberg"
    ],
    "name:deu_x_preferred":[
        "Spydeberg"
    ],
    "name:eng_x_preferred":[
        "Spydeberg"
    ],
    "name:epo_x_preferred":[
        "Spydeberg"
    ],
    "name:est_x_preferred":[
        "Spydebergi vald"
    ],
    "name:eus_x_preferred":[
        "Spydeberg"
    ],
    "name:fin_x_preferred":[
        "Spydeberg"
    ],
    "name:fra_x_preferred":[
        "Spydeberg"
    ],
    "name:ita_x_preferred":[
        "Spydeberg"
    ],
    "name:jav_x_preferred":[
        "Spydeberg"
    ],
    "name:lat_x_preferred":[
        "Spydeberg"
    ],
    "name:lim_x_preferred":[
        "Spydeberg"
    ],
    "name:msa_x_preferred":[
        "Spydeberg"
    ],
    "name:nan_x_preferred":[
        "Spydeberg"
    ],
    "name:nds_x_preferred":[
        "Kommun Spydeberg"
    ],
    "name:nld_x_preferred":[
        "Spydeberg"
    ],
    "name:nno_x_preferred":[
        "Spydeberg"
    ],
    "name:nob_x_preferred":[
        "Spydeberg"
    ],
    "name:oci_x_preferred":[
        "Spydeberg"
    ],
    "name:pol_x_preferred":[
        "Spydeberg"
    ],
    "name:por_x_preferred":[
        "Spydeberg"
    ],
    "name:ron_x_preferred":[
        "Spydeberg"
    ],
    "name:rus_x_preferred":[
        "\u0421\u043f\u044e\u0434\u0435\u0431\u0435\u0440\u0433"
    ],
    "name:sme_x_preferred":[
        "Spydeberg"
    ],
    "name:spa_x_preferred":[
        "Spydeberg"
    ],
    "name:sqi_x_preferred":[
        "Spydeberg"
    ],
    "name:swa_x_preferred":[
        "Spydeberg"
    ],
    "name:swe_x_preferred":[
        "Spydebergs kommun"
    ],
    "name:vie_x_preferred":[
        "Spydeberg"
    ],
    "name:war_x_preferred":[
        "Spydeberg"
    ],
    "name:zho_x_preferred":[
        "\u65af\u5f7c\u5f97\u8d1d\u683c"
    ],
    "qs_pg:aaroncc":"NO",
    "qs_pg:gn_country":"NO",
    "qs_pg:gn_fcode":"PPLA2",
    "qs_pg:gn_pop":3166,
    "qs_pg:name":"Spydeberg",
    "qs_pg:name_adm0":"Norge",
    "qs_pg:name_adm1":"\u00d8stfold Fylke",
    "qs_pg:photos":226,
    "qs_pg:photos_1k":46,
    "qs_pg:photos_9k":1,
    "qs_pg:photos_9r":4,
    "qs_pg:photos_all":226,
    "qs_pg:photos_sr":4,
    "qs_pg:pop_sr":4,
    "qs_pg:qs_pg_placetype":"locality",
    "qs_pg:qs_pg_placetype_gp":"Town",
    "qs_pg:woe_adm0":23424910,
    "woe:adm0_id":23424910,
    "woe:name_adm0":"Norge",
    "woe:name_adm1":"\u00d8stfold Fylke",
    "woe:placetype":"Town",
    "wof:name":"Spydeberg",
    "wof:placetype":"locality",
    "wof:population":3166
},
  "geometry": {"coordinates":[11.08559,59.61709],"type":"Point"}
}