{
  "type": "Feature",
  "properties": {
    "gn:admin1_code":"7",
    "gn:admin2_code":"1201.0",
    "gn:asciiname":"Biskopshavn",
    "gn:country_code":"NO",
    "gn:dem":-9999,
    "gn:feature_class":"P",
    "gn:feature_code":"PPLL",
    "gn:name":"Biskopshavn",
    "gn:population":0,
    "gn:timezone":"Europe/Oslo",
    "iso:country":"NO",
    "wof:name":"Biskopshavn",
    "wof:placetype":"locality"
},
  "geometry": {"coordinates":[5.29532,60.4238],"type":"Point"}
}