{
  "type": "Feature",
  "properties": {
    "gn:country":"NO",
    "gn:fcode":"EST",
    "gn:population":4,
    "iso:country":"NO",
    "qs_pg:aaroncc":"NO",
    "qs_pg:gn_country":"NO",
    "qs_pg:gn_fcode":"EST",
    "qs_pg:gn_pop":4,
    "qs_pg:name":"Berglund",
    "qs_pg:photos_9r":0,
    "qs_pg:photos_sr":0,
    "qs_pg:pop_sr":1,
    "qs_pg:qs_pg_placetype":"locality",
    "wof:name":"Berglund",
    "wof:placetype":"locality",
    "wof:population":4
},
  "geometry": {"coordinates":[12.35612,66.36924],"type":"Point"}
}