{
  "type": "Feature",
  "properties": {
    "gn:admin1_code":"19",
    "gn:admin2_code":"1037.0",
    "gn:asciiname":"Leirvika",
    "gn:cc2":"NO",
    "gn:country_code":"NO",
    "gn:dem":172,
    "gn:feature_class":"P",
    "gn:feature_code":"PPL",
    "gn:name":"Leirvika",
    "gn:population":0,
    "gn:timezone":"Europe/Oslo",
    "iso:country":"NO",
    "name:und_x_variant":[
        "Lervigen",
        "Leirvika"
    ],
    "wof:name":"Leirvika",
    "wof:placetype":"locality"
},
  "geometry": {"coordinates":[6.88333,58.26667],"type":"Point"}
}