{
  "type": "Feature",
  "properties": {
    "gn:admin1_code":"9.0",
    "gn:admin2_code":"1833.0",
    "gn:asciiname":"Gjerdvollen",
    "gn:country_code":"NO",
    "gn:dem":-9999,
    "gn:feature_class":"P",
    "gn:feature_code":"PPL",
    "gn:name":"Gjerdvollen",
    "gn:population":0,
    "gn:timezone":"Europe/Oslo",
    "iso:country":"NO",
    "name:nor_x_preferred":[
        "Gjerdvollen"
    ],
    "wof:name":"Gjerdvollen",
    "wof:placetype":"locality"
},
  "geometry": {"coordinates":[13.97481,66.26425],"type":"Point"}
}