{
  "type": "Feature",
  "properties": {
    "gn:admin1_code":"19",
    "gn:admin2_code":"1032",
    "gn:asciiname":"Oftebro",
    "gn:country_code":"NO",
    "gn:dem":36,
    "gn:feature_class":"P",
    "gn:feature_code":"PPLL",
    "gn:name":"Oftebro",
    "gn:population":0,
    "gn:timezone":"Europe/Oslo",
    "iso:country":"NO",
    "name:nor_x_preferred":[
        "Oftebro"
    ],
    "wof:name":"Oftebro",
    "wof:placetype":"locality"
},
  "geometry": {"coordinates":[7.09212,58.14874],"type":"Point"}
}