{
  "type": "Feature",
  "properties": {
    "gn:admin1_code":"20.0",
    "gn:admin2_code":"729.0",
    "gn:asciiname":"Grimestadgrinda",
    "gn:country_code":"NO",
    "gn:dem":43,
    "gn:feature_class":"P",
    "gn:feature_code":"PPL",
    "gn:name":"Grimestadgrinda",
    "gn:population":0,
    "gn:timezone":"Europe/Oslo",
    "iso:country":"NO",
    "name:nor_x_preferred":[
        "Grimestadgrinda"
    ],
    "wof:name":"Grimestadgrinda",
    "wof:placetype":"neighbourhood"
},
  "geometry": {"coordinates":[10.4028,59.12962],"type":"Point"}
}