{
  "type": "Feature",
  "properties": {
    "gn:admin1_code":"7.0",
    "gn:admin2_code":"1263.0",
    "gn:asciiname":"Selevoll",
    "gn:country_code":"NO",
    "gn:dem":115,
    "gn:feature_class":"P",
    "gn:feature_code":"PPL",
    "gn:name":"Selevoll",
    "gn:population":0,
    "gn:timezone":"Europe/Oslo",
    "iso:country":"NO",
    "wof:name":"Selevoll",
    "wof:placetype":"locality"
},
  "geometry": {"coordinates":[5.21278,60.60861],"type":"Point"}
}