{
  "type": "Feature",
  "properties": {
    "gn:country":"NO",
    "gn:fcode":"PPL",
    "gn:population":0,
    "iso:country":"NO",
    "qs_pg:aaroncc":"NO",
    "qs_pg:gn_country":"NO",
    "qs_pg:gn_fcode":"PPL",
    "qs_pg:gn_pop":0,
    "qs_pg:name":"Eggum",
    "qs_pg:name_adm0":"Norge",
    "qs_pg:name_adm1":"Nordland Fylke",
    "qs_pg:photos":386,
    "qs_pg:photos_1k":78,
    "qs_pg:photos_9k":2,
    "qs_pg:photos_9r":5,
    "qs_pg:photos_all":386,
    "qs_pg:photos_sr":6,
    "qs_pg:pop_sr":0,
    "qs_pg:qs_pg_placetype":"locality",
    "qs_pg:qs_pg_placetype_gp":"Town",
    "qs_pg:woe_adm0":23424910,
    "woe:adm0_id":23424910,
    "woe:name_adm0":"Norge",
    "woe:name_adm1":"Nordland Fylke",
    "woe:placetype":"Town",
    "wof:name":"Eggum",
    "wof:placetype":"locality"
},
  "geometry": {"coordinates":[13.695,68.31028000000001],"type":"Point"}
}