{
  "type": "Feature",
  "properties": {
    "iso:country":"NO",
    "name:cat_x_preferred":[
        "Fyllingsdalen"
    ],
    "name:fra_x_preferred":[
        "Fyllingsdalen"
    ],
    "name:jav_x_preferred":[
        "Fyllingsdalen"
    ],
    "name:msa_x_preferred":[
        "Fyllingsdalen"
    ],
    "name:nld_x_preferred":[
        "Fyllingsdalen"
    ],
    "name:nno_x_preferred":[
        "Fyllingsdalen"
    ],
    "name:nor_x_preferred":[
        "Fyllingsdalen"
    ],
    "qs_pg:aaroncc":"NO",
    "qs_pg:name":"Fyllingsdalen",
    "qs_pg:name_adm0":"Norge",
    "qs_pg:name_adm1":"Hordaland Fylke",
    "qs_pg:photos":154,
    "qs_pg:photos_1k":31,
    "qs_pg:photos_9k":4,
    "qs_pg:photos_9r":6,
    "qs_pg:photos_all":995,
    "qs_pg:photos_sr":4,
    "qs_pg:pop_sr":0,
    "qs_pg:qs_pg_placetype":"locality",
    "qs_pg:qs_pg_placetype_gp":"Town",
    "qs_pg:woe_adm0":23424910,
    "woe:adm0_id":23424910,
    "woe:name_adm0":"Norge",
    "woe:name_adm1":"Hordaland Fylke",
    "woe:placetype":"Town",
    "wof:name":"Fyllingsdalen",
    "wof:placetype":"locality"
},
  "geometry": {"coordinates":[5.283308,60.352729],"type":"Point"}
}