{
  "type": "Feature",
  "properties": {
    "gn:admin1_code":"15",
    "gn:admin2_code":"1432.0",
    "gn:asciiname":"Bruland",
    "gn:country_code":"NO",
    "gn:dem":20,
    "gn:feature_class":"P",
    "gn:feature_code":"PPL",
    "gn:name":"Bruland",
    "gn:population":0,
    "gn:timezone":"Europe/Oslo",
    "iso:country":"NO",
    "name:ceb_x_preferred":[
        "Bruland"
    ],
    "name:jav_x_preferred":[
        "Bruland"
    ],
    "name:msa_x_preferred":[
        "Bruland"
    ],
    "name:nno_x_preferred":[
        "Bruland"
    ],
    "name:nor_x_preferred":[
        "Bruland"
    ],
    "wof:name":"Bruland",
    "wof:placetype":"locality"
},
  "geometry": {"coordinates":[5.89665,61.43823],"type":"Point"}
}