{
  "type": "Feature",
  "properties": {
    "gn:country":"NO",
    "gn:fcode":"PPL",
    "gn:population":0,
    "iso:country":"NO",
    "name:nor_x_preferred":[
        "Veiholmen"
    ],
    "name:nor_x_variant":[
        "Veidholmen"
    ],
    "name:und_x_variant":[
        "S\u00f8ndre Veiholmen"
    ],
    "qs_pg:aaroncc":"NO",
    "qs_pg:gn_country":"NO",
    "qs_pg:gn_fcode":"PPL",
    "qs_pg:gn_pop":0,
    "qs_pg:name":"Veidholmen",
    "qs_pg:name_adm0":"Norge",
    "qs_pg:name_adm1":"M\u00f8re og Romsdal Fylke",
    "qs_pg:photos":98,
    "qs_pg:photos_1k":20,
    "qs_pg:photos_9k":1,
    "qs_pg:photos_9r":3,
    "qs_pg:photos_all":98,
    "qs_pg:photos_sr":3,
    "qs_pg:pop_sr":0,
    "qs_pg:qs_pg_placetype":"locality",
    "qs_pg:qs_pg_placetype_gp":"Town",
    "qs_pg:woe_adm0":23424910,
    "woe:adm0_id":23424910,
    "woe:name_adm0":"Norge",
    "woe:name_adm1":"M\u00f8re og Romsdal Fylke",
    "woe:placetype":"Town",
    "wof:name":"Veidholmen",
    "wof:placetype":"locality"
},
  "geometry": {"coordinates":[7.95,63.51667],"type":"Point"}
}