{
  "type": "Feature",
  "properties": {
    "gn:admin1_code":"7",
    "gn:admin2_code":"1247.0",
    "gn:asciiname":"Hop",
    "gn:country_code":"NO",
    "gn:dem":1,
    "gn:feature_class":"P",
    "gn:feature_code":"PPLL",
    "gn:name":"Hop",
    "gn:population":0,
    "gn:timezone":"Europe/Oslo",
    "iso:country":"NO",
    "name:ceb_x_preferred":[
        "Hop"
    ],
    "name:ces_x_preferred":[
        "Hop"
    ],
    "name:deu_x_preferred":[
        "Hop"
    ],
    "name:diq_x_preferred":[
        "Hop"
    ],
    "name:fra_x_preferred":[
        "Hop"
    ],
    "name:jpn_x_preferred":[
        "\u30db\u30c3\u30d7"
    ],
    "name:lav_x_preferred":[
        "Hop"
    ],
    "name:nld_x_preferred":[
        "Hop"
    ],
    "name:nor_x_preferred":[
        "Hop"
    ],
    "name:pol_x_preferred":[
        "Hop"
    ],
    "name:por_x_preferred":[
        "Hop"
    ],
    "name:spa_x_preferred":[
        "Hop"
    ],
    "name:swe_x_preferred":[
        "Hop"
    ],
    "wof:name":"Hop",
    "wof:placetype":"locality"
},
  "geometry": {"coordinates":[5.21806,60.47167],"type":"Point"}
}