{
  "type": "Feature",
  "properties": {
    "gn:admin1_code":"14.0",
    "gn:admin2_code":"1120.0",
    "gn:asciiname":"Tu",
    "gn:country_code":"NO",
    "gn:dem":44,
    "gn:feature_class":"P",
    "gn:feature_code":"PPL",
    "gn:name":"Tu",
    "gn:population":0,
    "gn:timezone":"Europe/Oslo",
    "iso:country":"NO",
    "wof:name":"Tu",
    "wof:placetype":"locality"
},
  "geometry": {"coordinates":[5.65,58.75],"type":"Point"}
}