{
  "type": "Feature",
  "properties": {
    "gn:admin1_code":"4",
    "gn:admin2_code":"633.0",
    "gn:asciiname":"Nore",
    "gn:country_code":"NO",
    "gn:dem":300,
    "gn:feature_class":"P",
    "gn:feature_code":"PPLL",
    "gn:name":"Nore",
    "gn:population":0,
    "gn:timezone":"Europe/Oslo",
    "iso:country":"NO",
    "name:ara_x_preferred":[
        "\u0646\u0648\u0631"
    ],
    "name:ceb_x_preferred":[
        "Great Nore"
    ],
    "name:fin_x_preferred":[
        "Nore"
    ],
    "name:fra_x_preferred":[
        "Nore"
    ],
    "name:heb_x_preferred":[
        "\u05e0\u05d5\u05e8"
    ],
    "name:ita_x_preferred":[
        "Nore"
    ],
    "name:jpn_x_preferred":[
        "\u30ce\u30a2"
    ],
    "name:kor_x_preferred":[
        "\ub178\uc5b4"
    ],
    "name:rus_x_preferred":[
        "\u041d\u043e\u0440"
    ],
    "name:swe_x_preferred":[
        "Nore"
    ],
    "wof:name":"Nore",
    "wof:placetype":"locality"
},
  "geometry": {"coordinates":[9.01125,60.16884],"type":"Point"}
}