{
  "type": "Feature",
  "properties": {
    "gn:admin1_code":"21",
    "gn:admin2_code":"5018.0",
    "gn:asciiname":"Lauvstrand",
    "gn:cc2":"NO",
    "gn:country_code":"NO",
    "gn:dem":76,
    "gn:feature_class":"P",
    "gn:feature_code":"PPL",
    "gn:name":"Lauvstrand",
    "gn:population":0,
    "gn:timezone":"Europe/Oslo",
    "iso:country":"NO",
    "name:und_x_variant":[
        "L\u00f6vstrand",
        "Lauvstrand"
    ],
    "wof:name":"Lauvstrand",
    "wof:placetype":"locality"
},
  "geometry": {"coordinates":[10.03333,64.01666999999999],"type":"Point"}
}