{
  "type": "Feature",
  "properties": {
    "gn:admin1_code":"9",
    "gn:admin2_code":"1860.0",
    "gn:asciiname":"Hol",
    "gn:country_code":"NO",
    "gn:dem":40,
    "gn:feature_class":"P",
    "gn:feature_code":"PPL",
    "gn:name":"Hol",
    "gn:population":0,
    "gn:timezone":"Europe/Oslo",
    "iso:country":"NO",
    "name:rus_x_preferred":[
        "\u0425\u0443\u043b\u044c"
    ],
    "wof:name":"Hol",
    "wof:placetype":"locality"
},
  "geometry": {"coordinates":[13.65063,68.14451],"type":"Point"}
}