{
  "type": "Feature",
  "properties": {
    "gn:gn_country":"NO",
    "iso:country":"NO",
    "name:ceb_x_preferred":[
        "Hernar"
    ],
    "name:jav_x_preferred":[
        "Hernar"
    ],
    "name:msa_x_preferred":[
        "Hernar"
    ],
    "name:nno_x_preferred":[
        "Hernar"
    ],
    "name:nor_x_preferred":[
        "Hernar"
    ],
    "qs_pg:aaroncc":"NO",
    "qs_pg:gn_country":"NO",
    "qs_pg:name":"Hernar",
    "qs_pg:name_adm0":"Norge",
    "qs_pg:name_adm1":"Hordaland Fylke",
    "qs_pg:photos":26,
    "qs_pg:photos_1k":5,
    "qs_pg:photos_9k":1,
    "qs_pg:photos_9r":2,
    "qs_pg:photos_all":26,
    "qs_pg:photos_sr":2,
    "qs_pg:pop_sr":0,
    "qs_pg:qs_pg_placetype":"locality",
    "qs_pg:qs_pg_placetype_gp":"Town",
    "qs_pg:woe_adm0":23424910,
    "woe:adm0_id":23424910,
    "woe:name_adm0":"Norge",
    "woe:name_adm1":"Hordaland Fylke",
    "woe:placetype":"Town",
    "wof:name":"Hernar",
    "wof:placetype":"locality"
},
  "geometry": {"coordinates":[4.744634,60.688729],"type":"Point"}
}