{
  "type": "Feature",
  "properties": {
    "gn:admin1_code":"21",
    "gn:admin2_code":"5013.0",
    "gn:asciiname":"Hestnes",
    "gn:cc2":"NO",
    "gn:country_code":"NO",
    "gn:dem":-9999,
    "gn:feature_class":"P",
    "gn:feature_code":"PPL",
    "gn:name":"Hestnes",
    "gn:population":0,
    "gn:timezone":"Europe/Oslo",
    "iso:country":"NO",
    "name:jav_x_preferred":[
        "Hestnes"
    ],
    "name:msa_x_preferred":[
        "Hestnes"
    ],
    "name:nld_x_preferred":[
        "Hestnes"
    ],
    "name:nor_x_preferred":[
        "Hestnes"
    ],
    "name:und_x_variant":[
        "Hestn\u00e6s"
    ],
    "wof:name":"Hestnes",
    "wof:placetype":"locality"
},
  "geometry": {"coordinates":[8.60507,63.58569],"type":"Point"}
}