{
  "type": "Feature",
  "properties": {
    "gn:admin1_code":"19.0",
    "gn:admin2_code":"1034.0",
    "gn:asciiname":"Snartemo",
    "gn:country_code":"NO",
    "gn:dem":147,
    "gn:feature_class":"P",
    "gn:feature_code":"PPL",
    "gn:name":"Snartemo",
    "gn:population":0,
    "gn:timezone":"Europe/Oslo",
    "iso:country":"NO",
    "name:msa_x_preferred":[
        "Snartemo"
    ],
    "name:nno_x_preferred":[
        "Snartemo"
    ],
    "wof:name":"Snartemo",
    "wof:placetype":"locality"
},
  "geometry": {"coordinates":[7.21252,58.33313],"type":"Point"}
}