{
  "type": "Feature",
  "properties": {
    "gn:admin1_code":"17.0",
    "gn:admin2_code":"817.0",
    "gn:asciiname":"Solli",
    "gn:country_code":"NO",
    "gn:dem":449,
    "gn:feature_class":"P",
    "gn:feature_code":"PPL",
    "gn:name":"Solli",
    "gn:population":0,
    "gn:timezone":"Europe/Oslo",
    "iso:country":"NO",
    "name:ceb_x_preferred":[
        "Solli"
    ],
    "name:deu_x_preferred":[
        "Solli"
    ],
    "name:nor_x_preferred":[
        "Solli"
    ],
    "name:rus_x_preferred":[
        "\u0421\u043e\u043b\u043b\u0438"
    ],
    "wof:name":"Solli",
    "wof:placetype":"locality"
},
  "geometry": {"coordinates":[8.73333,59.15],"type":"Point"}
}