{
  "type": "Feature",
  "properties": {
    "gn:admin1_code":"17.0",
    "gn:admin2_code":"817.0",
    "gn:asciiname":"Solli",
    "gn:country_code":"NO",
    "gn:dem":449,
    "gn:feature_class":"P",
    "gn:feature_code":"PPL",
    "gn:name":"Solli",
    "gn:population":0,
    "gn:timezone":"Europe/Oslo",
    "iso:country":"NO",
    "wof:name":"Solli",
    "wof:placetype":"locality"
},
  "geometry": {"coordinates":[8.73333,59.15],"type":"Point"}
}