{
  "type": "Feature",
  "properties": {
    "gn:admin1_code":"4.0",
    "gn:admin2_code":"620.0",
    "gn:asciiname":"Haee",
    "gn:country_code":"NO",
    "gn:dem":1124,
    "gn:feature_class":"P",
    "gn:feature_code":"PPL",
    "gn:name":"H\u00e6e",
    "gn:population":0,
    "gn:timezone":"Europe/Oslo",
    "iso:country":"NO",
    "name:nor_x_preferred":[
        "H\u00e6e"
    ],
    "wof:name":"Haee",
    "wof:placetype":"locality"
},
  "geometry": {"coordinates":[8.26282,60.64779],"type":"Point"}
}