{
  "type": "Feature",
  "properties": {
    "gn:admin1_code":"18.0",
    "gn:admin2_code":"1942.0",
    "gn:asciiname":"Hamneidet",
    "gn:cc2":"NO",
    "gn:country_code":"NO",
    "gn:dem":37,
    "gn:feature_class":"P",
    "gn:feature_code":"PPL",
    "gn:name":"Hamneidet",
    "gn:population":0,
    "gn:timezone":"Europe/Oslo",
    "iso:country":"NO",
    "name:und_x_variant":[
        "Hamneide"
    ],
    "wof:name":"Hamneidet",
    "wof:placetype":"locality"
},
  "geometry": {"coordinates":[20.9592,69.92886],"type":"Point"}
}