{
  "type": "Feature",
  "properties": {
    "gn:admin1_code":"17",
    "gn:admin2_code":"817.0",
    "gn:asciiname":"Grova",
    "gn:country_code":"NO",
    "gn:dem":153,
    "gn:feature_class":"P",
    "gn:feature_code":"PPL",
    "gn:name":"Grova",
    "gn:population":0,
    "gn:timezone":"Europe/Oslo",
    "iso:country":"NO",
    "wof:name":"Grova",
    "wof:placetype":"locality"
},
  "geometry": {"coordinates":[8.77157,59.21704],"type":"Point"}
}