{
  "type": "Feature",
  "properties": {
    "gn:admin1_code":"7",
    "gn:admin2_code":"1260.0",
    "gn:asciiname":"Straume",
    "gn:country_code":"NO",
    "gn:dem":1,
    "gn:feature_class":"P",
    "gn:feature_code":"PPLL",
    "gn:name":"Straume",
    "gn:population":0,
    "gn:timezone":"Europe/Oslo",
    "iso:country":"NO",
    "name:ceb_x_preferred":[
        "Straume"
    ],
    "name:lav_x_preferred":[
        "Straume"
    ],
    "name:nno_x_preferred":[
        "Straume"
    ],
    "name:nor_x_preferred":[
        "Straume"
    ],
    "name:rus_x_preferred":[
        "\u0421\u0442\u0440\u0430\u0443\u043c\u0435"
    ],
    "wof:name":"Straume",
    "wof:placetype":"locality"
},
  "geometry": {"coordinates":[4.97611,60.72556],"type":"Point"}
}