{
  "type": "Feature",
  "properties": {
    "gn:admin1_code":"5.0",
    "gn:admin2_code":"2012.0",
    "gn:asciiname":"Rognskog",
    "gn:country_code":"NO",
    "gn:dem":45,
    "gn:feature_class":"P",
    "gn:feature_code":"PPL",
    "gn:name":"Rognskog",
    "gn:population":0,
    "gn:timezone":"Europe/Oslo",
    "iso:country":"NO",
    "wof:name":"Rognskog",
    "wof:placetype":"locality"
},
  "geometry": {"coordinates":[23.41917,69.93656],"type":"Point"}
}