{
  "type": "Feature",
  "properties": {
    "gn:admin1_code":"8",
    "gn:admin2_code":"1573.0",
    "gn:asciiname":"Holmen",
    "gn:country_code":"NO",
    "gn:dem":-9999,
    "gn:feature_class":"P",
    "gn:feature_code":"PPL",
    "gn:name":"Holmen",
    "gn:population":0,
    "gn:timezone":"Europe/Oslo",
    "iso:country":"NO",
    "wof:name":"Holmen",
    "wof:placetype":"locality"
},
  "geometry": {"coordinates":[8.11667,63.46666999999999],"type":"Point"}
}