{
  "type": "Feature",
  "properties": {
    "gn:admin1_code":"21.0",
    "gn:admin2_code":"5021.0",
    "gn:asciiname":"Saetersgrenda",
    "gn:country_code":"NO",
    "gn:dem":620,
    "gn:feature_class":"P",
    "gn:feature_code":"PPL",
    "gn:name":"S\u00e6tersgrenda",
    "gn:population":0,
    "gn:timezone":"Europe/Oslo",
    "iso:country":"NO",
    "name:nor_x_preferred":[
        "S\u00e6tersgrenda"
    ],
    "wof:name":"Saetersgrenda",
    "wof:placetype":"locality"
},
  "geometry": {"coordinates":[9.66291,62.60206],"type":"Point"}
}