{
  "type": "Feature",
  "properties": {
    "gn:country":"NO",
    "gn:fcode":"PPL",
    "gn:population":454,
    "iso:country":"NO",
    "name:nno_x_preferred":[
        "Myklebost"
    ],
    "name:spa_x_preferred":[
        "Myklebost"
    ],
    "name:und_x_variant":[
        "Myklebostad"
    ],
    "qs_pg:aaroncc":"NO",
    "qs_pg:gn_country":"NO",
    "qs_pg:gn_fcode":"PPL",
    "qs_pg:gn_pop":454,
    "qs_pg:name":"Myklebost",
    "qs_pg:name_adm0":"Norge",
    "qs_pg:name_adm1":"M\u00f8re og Romsdal Fylke",
    "qs_pg:photos":31,
    "qs_pg:photos_1k":6,
    "qs_pg:photos_9k":1,
    "qs_pg:photos_9r":2,
    "qs_pg:photos_all":31,
    "qs_pg:photos_sr":2,
    "qs_pg:pop_sr":2,
    "qs_pg:qs_pg_placetype":"locality",
    "qs_pg:qs_pg_placetype_gp":"Town",
    "qs_pg:woe_adm0":23424910,
    "woe:adm0_id":23424910,
    "woe:name_adm0":"Norge",
    "woe:name_adm1":"M\u00f8re og Romsdal Fylke",
    "woe:placetype":"Town",
    "wof:name":"Myklebost",
    "wof:placetype":"locality",
    "wof:population":454
},
  "geometry": {"coordinates":[6.45,62.73333],"type":"Point"}
}