{
  "type": "Feature",
  "properties": {
    "gn:admin1_code":"9.0",
    "gn:admin2_code":"1804.0",
    "gn:asciiname":"Stover",
    "gn:country_code":"NO",
    "gn:dem":-9999,
    "gn:feature_class":"P",
    "gn:feature_code":"PPL",
    "gn:name":"St\u00f8ver",
    "gn:population":0,
    "gn:timezone":"Europe/Oslo",
    "iso:country":"NO",
    "wof:name":"Stover",
    "wof:placetype":"locality"
},
  "geometry": {"coordinates":[14.61667,67.28333000000001],"type":"Point"}
}