{
  "type": "Feature",
  "properties": {
    "gn:admin1_code":"9.0",
    "gn:admin2_code":"1804.0",
    "gn:asciiname":"Stover",
    "gn:country_code":"NO",
    "gn:dem":-9999,
    "gn:feature_class":"P",
    "gn:feature_code":"PPL",
    "gn:name":"St\u00f8ver",
    "gn:population":0,
    "gn:timezone":"Europe/Oslo",
    "iso:country":"NO",
    "name:bel_x_preferred":[
        "\u0420\u0436\u044b\u0448\u0447\u0430"
    ],
    "name:ces_x_preferred":[
        "Strni\u0161t\u011b"
    ],
    "name:deu_x_preferred":[
        "Stoppelfeld"
    ],
    "name:epo_x_preferred":[
        "Stoplo"
    ],
    "name:fra_x_preferred":[
        "Chaume"
    ],
    "name:ind_x_preferred":[
        "Brangkasan"
    ],
    "name:por_x_preferred":[
        "Restolho"
    ],
    "name:rus_x_preferred":[
        "\u0421\u0442\u0435\u0440\u043d\u044f"
    ],
    "name:scn_x_preferred":[
        "Mecciu"
    ],
    "name:spa_x_preferred":[
        "Rastrojo"
    ],
    "name:ukr_x_preferred":[
        "\u0421\u0442\u0435\u0440\u043d\u044f"
    ],
    "wof:name":"Stover",
    "wof:placetype":"locality"
},
  "geometry": {"coordinates":[14.61667,67.28333000000001],"type":"Point"}
}