{
  "type": "Feature",
  "properties": {
    "gn:admin1_code":"14.0",
    "gn:admin2_code":"1141.0",
    "gn:asciiname":"Sor Vignes",
    "gn:cc2":"NO",
    "gn:country_code":"NO",
    "gn:dem":64,
    "gn:feature_class":"P",
    "gn:feature_code":"PPL",
    "gn:name":"S\u00f8r Vignes",
    "gn:population":0,
    "gn:timezone":"Europe/Oslo",
    "iso:country":"NO",
    "name:und_x_variant":[
        "Vign\u00e6s S\u00f8r",
        "Vignes",
        "S\u00f8r Vignes"
    ],
    "wof:name":"Sor Vignes",
    "wof:placetype":"locality"
},
  "geometry": {"coordinates":[5.78333,59.15],"type":"Point"}
}