{
  "type": "Feature",
  "properties": {
    "gn:admin1_code":"5.0",
    "gn:admin2_code":"2011.0",
    "gn:asciiname":"Gavdavuopppenjarga",
    "gn:country_code":"NO",
    "gn:dem":301,
    "gn:feature_class":"P",
    "gn:feature_code":"PPL",
    "gn:name":"G\u00e5vdavuopppenjarga",
    "gn:population":0,
    "gn:timezone":"Europe/Oslo",
    "iso:country":"NO",
    "name:nor_x_preferred":[
        "Bredbuktnes"
    ],
    "name:sme_x_preferred":[
        "G\u00e5vdavuopppenjarga"
    ],
    "name:sme_x_variant":[
        "Govdavuohpenj\u00e1rga"
    ],
    "wof:name":"Gavdavuopppenjarga",
    "wof:placetype":"locality"
},
  "geometry": {"coordinates":[23.10668,69.0467],"type":"Point"}
}