{
  "type": "Feature",
  "properties": {
    "gn:admin1_code":"7",
    "gn:admin2_code":"1260.0",
    "gn:asciiname":"Villanger",
    "gn:country_code":"NO",
    "gn:dem":20,
    "gn:feature_class":"P",
    "gn:feature_code":"PPL",
    "gn:name":"Villanger",
    "gn:population":0,
    "gn:timezone":"Europe/Oslo",
    "iso:country":"NO",
    "wof:name":"Villanger",
    "wof:placetype":"locality"
},
  "geometry": {"coordinates":[4.91708,60.72994],"type":"Point"}
}