{
  "type": "Feature",
  "properties": {
    "gn:admin1_code":"18.0",
    "gn:admin2_code":"1933.0",
    "gn:asciiname":"Labukta",
    "gn:country_code":"NO",
    "gn:dem":40,
    "gn:feature_class":"P",
    "gn:feature_code":"PPL",
    "gn:name":"Labukta",
    "gn:population":0,
    "gn:timezone":"Europe/Oslo",
    "iso:country":"NO",
    "name:nor_x_preferred":[
        "Labukta"
    ],
    "wof:name":"Labukta",
    "wof:placetype":"locality"
},
  "geometry": {"coordinates":[18.99021,69.45159],"type":"Point"}
}