{
  "type": "Feature",
  "properties": {
    "gn:admin1_code":"8.0",
    "gn:admin2_code":"1534.0",
    "gn:asciiname":"Slyngstad",
    "gn:country_code":"NO",
    "gn:dem":74,
    "gn:feature_class":"P",
    "gn:feature_code":"PPL",
    "gn:name":"Slyngstad",
    "gn:population":0,
    "gn:timezone":"Europe/Oslo",
    "iso:country":"NO",
    "wof:name":"Slyngstad",
    "wof:placetype":"locality"
},
  "geometry": {"coordinates":[6.5228,62.5435],"type":"Point"}
}