{
  "type": "Feature",
  "properties": {
    "gn:admin1_code":"6.0",
    "gn:admin2_code":"434.0",
    "gn:asciiname":"Veundasaetrene",
    "gn:country_code":"NO",
    "gn:dem":857,
    "gn:feature_class":"P",
    "gn:feature_code":"PPL",
    "gn:name":"Veund\u00e5s\u00e6trene",
    "gn:population":0,
    "gn:timezone":"Europe/Oslo",
    "iso:country":"NO",
    "name:nor_x_preferred":[
        "Veund\u00e5s\u00e6trene"
    ],
    "wof:name":"Veundasaetrene",
    "wof:placetype":"locality"
},
  "geometry": {"coordinates":[11.81262,61.74026],"type":"Point"}
}