{
  "type": "Feature",
  "properties": {
    "gn:admin1_code":"5.0",
    "gn:admin2_code":"2021.0",
    "gn:asciiname":"Spiinniidgieddi",
    "gn:country_code":"NO",
    "gn:dem":160,
    "gn:feature_class":"P",
    "gn:feature_code":"PPL",
    "gn:name":"Spiinniidgieddi",
    "gn:population":0,
    "gn:timezone":"Europe/Oslo",
    "iso:country":"NO",
    "name:sme_x_preferred":[
        "Spiinniidgieddi"
    ],
    "wof:name":"Spiinniidgieddi",
    "wof:placetype":"locality"
},
  "geometry": {"coordinates":[25.32151,69.44001],"type":"Point"}
}