{
  "type": "Feature",
  "properties": {
    "gn:admin1_code":"17",
    "gn:admin2_code":"819.0",
    "gn:asciiname":"Norheim",
    "gn:country_code":"NO",
    "gn:dem":84,
    "gn:feature_class":"P",
    "gn:feature_code":"PPL",
    "gn:name":"Norheim",
    "gn:population":0,
    "gn:timezone":"Europe/Oslo",
    "iso:country":"NO",
    "wof:name":"Norheim",
    "wof:placetype":"locality"
},
  "geometry": {"coordinates":[9.08333,59.35],"type":"Point"}
}