{
  "type": "Feature",
  "properties": {
    "gn:admin1_code":"17",
    "gn:admin2_code":"819.0",
    "gn:asciiname":"Norheim",
    "gn:country_code":"NO",
    "gn:dem":84,
    "gn:feature_class":"P",
    "gn:feature_code":"PPL",
    "gn:name":"Norheim",
    "gn:population":0,
    "gn:timezone":"Europe/Oslo",
    "iso:country":"NO",
    "name:ara_x_preferred":[
        "\u0646\u0648\u0631\u0647\u0622\u064a\u0645"
    ],
    "name:ceb_x_preferred":[
        "Norheim"
    ],
    "name:deu_x_preferred":[
        "Norheim"
    ],
    "name:epo_x_preferred":[
        "Norheim"
    ],
    "name:eus_x_preferred":[
        "Norheim"
    ],
    "name:fas_x_preferred":[
        "\u0646\u0648\u0631\u0647\u0627\u06cc\u0645"
    ],
    "name:fra_x_preferred":[
        "Norheim"
    ],
    "name:hun_x_preferred":[
        "Norheim"
    ],
    "name:ita_x_preferred":[
        "Norheim"
    ],
    "name:msa_x_preferred":[
        "Norheim"
    ],
    "name:nld_x_preferred":[
        "Norheim"
    ],
    "name:pol_x_preferred":[
        "Norheim"
    ],
    "name:por_x_preferred":[
        "Norheim"
    ],
    "name:ron_x_preferred":[
        "Norheim"
    ],
    "name:rus_x_preferred":[
        "\u041d\u043e\u0440\u0445\u0430\u0439\u043c"
    ],
    "name:spa_x_preferred":[
        "Norheim"
    ],
    "name:srp_x_preferred":[
        "\u041d\u043e\u0440\u0445\u0430\u0458\u043c"
    ],
    "name:ukr_x_preferred":[
        "\u041d\u043e\u0440\u0433\u0430\u0439\u043c"
    ],
    "name:uzb_x_preferred":[
        "Norheim"
    ],
    "name:vie_x_preferred":[
        "Norheim"
    ],
    "name:vol_x_preferred":[
        "Norheim"
    ],
    "name:war_x_preferred":[
        "Norheim"
    ],
    "name:zho_x_preferred":[
        "\u8bfa\u5c14\u6d77\u59c6"
    ],
    "wof:name":"Norheim",
    "wof:placetype":"locality"
},
  "geometry": {"coordinates":[9.08333,59.35],"type":"Point"}
}