{
  "type": "Feature",
  "properties": {
    "gn:country":"NO",
    "gn:fcode":"PPL",
    "gn:population":0,
    "iso:country":"NO",
    "name:deu_x_preferred":[
        "Knaben"
    ],
    "name:eng_x_preferred":[
        "Knaben"
    ],
    "name:fra_x_preferred":[
        "Knaben"
    ],
    "name:msa_x_preferred":[
        "Knaben"
    ],
    "name:nld_x_preferred":[
        "Knaben"
    ],
    "name:nob_x_preferred":[
        "Knaben"
    ],
    "qs_pg:aaroncc":"NO",
    "qs_pg:gn_country":"NO",
    "qs_pg:gn_fcode":"PPL",
    "qs_pg:gn_pop":0,
    "qs_pg:name":"Knaben",
    "qs_pg:name_adm0":"Norge",
    "qs_pg:name_adm1":"Vest-Agder Fylke",
    "qs_pg:photos_9k":1,
    "qs_pg:photos_9r":1,
    "qs_pg:photos_all":1,
    "qs_pg:photos_sr":0,
    "qs_pg:pop_sr":0,
    "qs_pg:qs_pg_placetype":"locality",
    "qs_pg:qs_pg_placetype_gp":"Town",
    "qs_pg:woe_adm0":23424910,
    "woe:adm0_id":23424910,
    "woe:name_adm0":"Norge",
    "woe:name_adm1":"Vest-Agder Fylke",
    "woe:placetype":"Town",
    "wof:name":"Knaben",
    "wof:placetype":"locality"
},
  "geometry": {"coordinates":[6.96667,58.66667],"type":"Point"}
}