{
  "type": "Feature",
  "properties": {
    "iso:country":"NO",
    "name:ceb_x_preferred":[
        "Haslum"
    ],
    "name:fas_x_preferred":[
        "\u0647\u0627\u0633\u0644\u0648\u0645"
    ],
    "name:jav_x_preferred":[
        "Haslum"
    ],
    "name:msa_x_preferred":[
        "Haslum"
    ],
    "name:nor_x_preferred":[
        "Haslum"
    ],
    "name:swe_x_preferred":[
        "Haslum"
    ],
    "qs_pg:aaroncc":"NO",
    "qs_pg:name":"Haslum",
    "qs_pg:name_adm0":"Norge",
    "qs_pg:name_adm1":"Akershus Fylke",
    "qs_pg:photos":294,
    "qs_pg:photos_1k":60,
    "qs_pg:photos_9k":1,
    "qs_pg:photos_9r":4,
    "qs_pg:photos_all":294,
    "qs_pg:photos_sr":5,
    "qs_pg:pop_sr":0,
    "qs_pg:qs_pg_placetype":"locality",
    "qs_pg:qs_pg_placetype_gp":"Town",
    "qs_pg:woe_adm0":23424910,
    "woe:adm0_id":23424910,
    "woe:name_adm0":"Norge",
    "woe:name_adm1":"Akershus Fylke",
    "woe:placetype":"Town",
    "wof:name":"Haslum",
    "wof:placetype":"locality"
},
  "geometry": {"coordinates":[10.5537,59.919441],"type":"Point"}
}