{
  "type": "Feature",
  "properties": {
    "gn:admin1_code":"7.0",
    "gn:admin2_code":"1259.0",
    "gn:asciiname":"Stura",
    "gn:country_code":"NO",
    "gn:dem":20,
    "gn:feature_class":"P",
    "gn:feature_code":"PPL",
    "gn:name":"Stura",
    "gn:population":0,
    "gn:timezone":"Europe/Oslo",
    "iso:country":"NO",
    "name:bre_x_preferred":[
        "Stura"
    ],
    "name:fra_x_preferred":[
        "Stura"
    ],
    "wof:name":"Stura",
    "wof:placetype":"locality"
},
  "geometry": {"coordinates":[4.83778,60.62139000000001],"type":"Point"}
}