{
  "type": "Feature",
  "properties": {
    "gn:admin1_code":"6.0",
    "gn:admin2_code":"403.0",
    "gn:asciiname":"Stavsberg",
    "gn:country_code":"NO",
    "gn:dem":185,
    "gn:feature_class":"P",
    "gn:feature_code":"PPL",
    "gn:name":"Stavsberg",
    "gn:population":0,
    "gn:timezone":"Europe/Oslo",
    "iso:country":"NO",
    "wof:name":"Stavsberg",
    "wof:placetype":"neighbourhood"
},
  "geometry": {"coordinates":[11.06667,60.81667],"type":"Point"}
}