{
  "type": "Feature",
  "properties": {
    "gn:country":"NO",
    "gn:fcode":"PPL",
    "gn:population":0,
    "iso:country":"NO",
    "name:eng_x_preferred":[
        "Hoppestad"
    ],
    "name:fra_x_preferred":[
        "Hoppestad"
    ],
    "name:msa_x_preferred":[
        "Hoppestad"
    ],
    "name:nld_x_preferred":[
        "Hoppstad"
    ],
    "name:nno_x_preferred":[
        "Hoppestad"
    ],
    "name:nob_x_preferred":[
        "Hoppestad"
    ],
    "name:ron_x_preferred":[
        "Hoppestad"
    ],
    "qs_pg:aaroncc":"NO",
    "qs_pg:gn_country":"NO",
    "qs_pg:gn_fcode":"PPL",
    "qs_pg:gn_pop":0,
    "qs_pg:name":"Hoppestad",
    "qs_pg:name_adm0":"Norge",
    "qs_pg:name_adm1":"Telemark Fylke",
    "qs_pg:photos":74,
    "qs_pg:photos_1k":15,
    "qs_pg:photos_9k":1,
    "qs_pg:photos_9r":2,
    "qs_pg:photos_all":74,
    "qs_pg:photos_sr":2,
    "qs_pg:pop_sr":0,
    "qs_pg:qs_pg_placetype":"locality",
    "qs_pg:qs_pg_placetype_gp":"Town",
    "qs_pg:woe_adm0":23424910,
    "woe:adm0_id":23424910,
    "woe:name_adm0":"Norge",
    "woe:name_adm1":"Telemark Fylke",
    "woe:placetype":"Town",
    "wof:name":"Hoppestad",
    "wof:placetype":"locality"
},
  "geometry": {"coordinates":[9.56667,59.25],"type":"Point"}
}