{
  "type": "Feature",
  "properties": {
    "gn:admin1_code":"21.0",
    "gn:admin2_code":"5025.0",
    "gn:asciiname":"Vika",
    "gn:cc2":"NO",
    "gn:country_code":"NO",
    "gn:dem":760,
    "gn:feature_class":"P",
    "gn:feature_code":"PPL",
    "gn:name":"Vika",
    "gn:population":0,
    "gn:timezone":"Europe/Oslo",
    "iso:country":"NO",
    "name:und_x_variant":[
        "Viken",
        "Vika"
    ],
    "wof:name":"Vika",
    "wof:placetype":"locality"
},
  "geometry": {"coordinates":[11.53333,62.66667],"type":"Point"}
}