{
  "type": "Feature",
  "properties": {
    "gn:admin1_code":"21.0",
    "gn:admin2_code":"5025.0",
    "gn:asciiname":"Vika",
    "gn:cc2":"NO",
    "gn:country_code":"NO",
    "gn:dem":760,
    "gn:feature_class":"P",
    "gn:feature_code":"PPL",
    "gn:name":"Vika",
    "gn:population":0,
    "gn:timezone":"Europe/Oslo",
    "iso:country":"NO",
    "name:ceb_x_preferred":[
        "Vika"
    ],
    "name:deu_x_preferred":[
        "Vika"
    ],
    "name:fin_x_preferred":[
        "Vika"
    ],
    "name:ita_x_preferred":[
        "Vika"
    ],
    "name:nor_x_preferred":[
        "Vika"
    ],
    "name:rus_x_preferred":[
        "\u0412\u0438\u043a\u0430"
    ],
    "name:slk_x_preferred":[
        "Vika"
    ],
    "name:swe_x_preferred":[
        "Vika"
    ],
    "name:und_x_variant":[
        "Viken"
    ],
    "wof:name":"Vika",
    "wof:placetype":"locality"
},
  "geometry": {"coordinates":[11.53333,62.66667],"type":"Point"}
}