{
  "type": "Feature",
  "properties": {
    "gn:admin1_code":"7",
    "gn:admin2_code":"1247.0",
    "gn:asciiname":"Hanevik",
    "gn:country_code":"NO",
    "gn:dem":12,
    "gn:feature_class":"P",
    "gn:feature_code":"PPLL",
    "gn:name":"Hanevik",
    "gn:population":0,
    "gn:timezone":"Europe/Oslo",
    "iso:country":"NO",
    "name:jav_x_preferred":[
        "Hanevik"
    ],
    "name:msa_x_preferred":[
        "Hanevik"
    ],
    "name:spa_x_preferred":[
        "Hanevik"
    ],
    "wof:name":"Hanevik",
    "wof:placetype":"locality"
},
  "geometry": {"coordinates":[5.15064,60.49925],"type":"Point"}
}