{
  "type": "Feature",
  "properties": {
    "gn:admin1_code":"19",
    "gn:admin2_code":"1002",
    "gn:asciiname":"Skinnsnes",
    "gn:country_code":"NO",
    "gn:dem":2,
    "gn:feature_class":"P",
    "gn:feature_code":"PPL",
    "gn:name":"Skinnsnes",
    "gn:population":0,
    "gn:timezone":"Europe/Oslo",
    "iso:country":"NO",
    "name:nor_x_preferred":[
        "Skinnsnes"
    ],
    "wof:name":"Skinnsnes",
    "wof:placetype":"neighbourhood"
},
  "geometry": {"coordinates":[7.47444,58.02817],"type":"Point"}
}