{
  "type": "Feature",
  "properties": {
    "gn:admin1_code":"7",
    "gn:admin2_code":"1263.0",
    "gn:asciiname":"Leivestad",
    "gn:country_code":"NO",
    "gn:dem":20,
    "gn:feature_class":"P",
    "gn:feature_code":"PPL",
    "gn:name":"Leivestad",
    "gn:population":0,
    "gn:timezone":"Europe/Oslo",
    "iso:country":"NO",
    "wof:name":"Leivestad",
    "wof:placetype":"locality"
},
  "geometry": {"coordinates":[5.28333,60.65],"type":"Point"}
}