{
  "type": "Feature",
  "properties": {
    "gn:country":"NO",
    "gn:fcode":"PPLA2",
    "gn:population":0,
    "iso:country":"NO",
    "name:dan_x_preferred":[
        "Straume"
    ],
    "name:eng_x_preferred":[
        "Straume"
    ],
    "name:fra_x_preferred":[
        "Straume"
    ],
    "name:jav_x_preferred":[
        "Straume"
    ],
    "name:msa_x_preferred":[
        "Straume"
    ],
    "name:nld_x_preferred":[
        "Straume"
    ],
    "name:nno_x_preferred":[
        "Straume"
    ],
    "name:nob_x_preferred":[
        "Straume"
    ],
    "name:spa_x_preferred":[
        "Straume"
    ],
    "qs_pg:aaroncc":"NO",
    "qs_pg:gn_country":"NO",
    "qs_pg:gn_fcode":"PPLA2",
    "qs_pg:gn_pop":0,
    "qs_pg:name":"Straume",
    "qs_pg:name_adm0":"Norge",
    "qs_pg:name_adm1":"Hordaland Fylke",
    "qs_pg:photos":197,
    "qs_pg:photos_1k":40,
    "qs_pg:photos_9k":1,
    "qs_pg:photos_9r":4,
    "qs_pg:photos_all":197,
    "qs_pg:photos_sr":4,
    "qs_pg:pop_sr":0,
    "qs_pg:qs_pg_placetype":"locality",
    "qs_pg:qs_pg_placetype_gp":"Town",
    "qs_pg:woe_adm0":23424910,
    "woe:adm0_id":23424910,
    "woe:name_adm0":"Norge",
    "woe:name_adm1":"Hordaland Fylke",
    "woe:placetype":"Town",
    "wof:name":"Straume",
    "wof:placetype":"neighbourhood"
},
  "geometry": {"coordinates":[5.12415,60.3571],"type":"Point"}
}