{
  "type": "Feature",
  "properties": {
    "gn:admin1_code":"9",
    "gn:admin2_code":"1832.0",
    "gn:asciiname":"Finneid",
    "gn:country_code":"NO",
    "gn:dem":280,
    "gn:feature_class":"P",
    "gn:feature_code":"PPL",
    "gn:name":"Finneid",
    "gn:population":0,
    "gn:timezone":"Europe/Oslo",
    "iso:country":"NO",
    "name:deu_x_preferred":[
        "Finneid"
    ],
    "name:nno_x_preferred":[
        "Finneid"
    ],
    "name:nor_x_preferred":[
        "Finneid"
    ],
    "wof:name":"Finneid",
    "wof:placetype":"locality"
},
  "geometry": {"coordinates":[13.81667,66.18333],"type":"Point"}
}