{
  "type": "Feature",
  "properties": {
    "iso:country":"NO",
    "name:ast_x_preferred":[
        "Sm\u00f8la"
    ],
    "name:bpy_x_preferred":[
        "\u09b8\u09ae\u09be\u09b2\u09be"
    ],
    "name:cat_x_preferred":[
        "Sm\u00f8la"
    ],
    "name:ceb_x_preferred":[
        "Sm\u00f8la"
    ],
    "name:ces_x_preferred":[
        "Sm\u00f8la"
    ],
    "name:dan_x_preferred":[
        "Sm\u00f8la"
    ],
    "name:deu_x_preferred":[
        "Sm\u00f8la"
    ],
    "name:eng_x_preferred":[
        "Sm\u00f8la"
    ],
    "name:epo_x_preferred":[
        "Sm\u00f8la"
    ],
    "name:eus_x_preferred":[
        "Sm\u00f8la"
    ],
    "name:fas_x_preferred":[
        "\u0627\u0633\u0645\u0648\u0644\u0627"
    ],
    "name:fin_x_preferred":[
        "Sm\u00f8la"
    ],
    "name:fra_x_preferred":[
        "Sm\u00f8la"
    ],
    "name:gle_x_preferred":[
        "Sm\u00f8la"
    ],
    "name:ind_x_preferred":[
        "Sm\u00f8la"
    ],
    "name:isl_x_preferred":[
        "Sm\u00f8la"
    ],
    "name:ita_x_preferred":[
        "Sm\u00f8la"
    ],
    "name:jav_x_preferred":[
        "Sm\u00f8la"
    ],
    "name:jpn_x_preferred":[
        "\u30b9\u30e1\u30e9"
    ],
    "name:lat_x_preferred":[
        "Sm\u00f8la"
    ],
    "name:lim_x_preferred":[
        "Sm\u00f8la"
    ],
    "name:msa_x_preferred":[
        "Sm\u00f8la"
    ],
    "name:nan_x_preferred":[
        "Sm\u00f8la"
    ],
    "name:nds_x_preferred":[
        "Kommun Sm\u00f8la"
    ],
    "name:nld_x_preferred":[
        "Sm\u00f8la"
    ],
    "name:nno_x_preferred":[
        "Sm\u00f8la"
    ],
    "name:nob_x_preferred":[
        "Sm\u00f8la"
    ],
    "name:pol_x_preferred":[
        "Sm\u00f8la"
    ],
    "name:por_x_preferred":[
        "Sm\u00f8la"
    ],
    "name:ron_x_preferred":[
        "Sm\u00f8la"
    ],
    "name:rus_x_preferred":[
        "\u0421\u043c\u0451\u043b\u0430"
    ],
    "name:slv_x_preferred":[
        "Sm\u00f8la"
    ],
    "name:sme_x_preferred":[
        "Sm\u00f8la"
    ],
    "name:spa_x_preferred":[
        "Sm\u00f8la"
    ],
    "name:sqi_x_preferred":[
        "Sm\u00f8la"
    ],
    "name:swa_x_preferred":[
        "Sm\u00f8la"
    ],
    "name:swe_x_preferred":[
        "Sm\u00f8la"
    ],
    "name:ukr_x_preferred":[
        "\u0421\u043c\u0435\u043b\u0430"
    ],
    "name:vie_x_preferred":[
        "Sm\u00f8la"
    ],
    "name:war_x_preferred":[
        "Sm\u00f8la"
    ],
    "name:zho_x_preferred":[
        "\u65af\u83ab\u62c9\u5cf6"
    ],
    "name:zho_x_variant":[
        "\u65af\u9ed8\u62c9"
    ],
    "qs_pg:aaroncc":"NO",
    "qs_pg:name":"Sm\u00f8la",
    "qs_pg:name_adm0":"Norge",
    "qs_pg:name_adm1":"M\u00f8re og Romsdal Fylke",
    "qs_pg:photos":65,
    "qs_pg:photos_1k":13,
    "qs_pg:photos_9k":1,
    "qs_pg:photos_9r":2,
    "qs_pg:photos_all":65,
    "qs_pg:photos_sr":2,
    "qs_pg:pop_sr":0,
    "qs_pg:qs_pg_placetype":"locality",
    "qs_pg:qs_pg_placetype_gp":"Town",
    "qs_pg:woe_adm0":23424910,
    "woe:adm0_id":23424910,
    "woe:name_adm0":"Norge",
    "woe:name_adm1":"M\u00f8re og Romsdal Fylke",
    "woe:placetype":"Town",
    "wof:name":"Sm\u00f8la",
    "wof:placetype":"locality"
},
  "geometry": {"coordinates":[8.003153,63.466011],"type":"Point"}
}