{
  "type": "Feature",
  "properties": {
    "gn:admin1_code":"8.0",
    "gn:admin2_code":"1520.0",
    "gn:asciiname":"Kvistad",
    "gn:country_code":"NO",
    "gn:dem":60,
    "gn:feature_class":"P",
    "gn:feature_code":"PPL",
    "gn:name":"Kvistad",
    "gn:population":0,
    "gn:timezone":"Europe/Oslo",
    "iso:country":"NO",
    "name:nor_x_preferred":[
        "Kvistad"
    ],
    "wof:name":"Kvistad",
    "wof:placetype":"locality"
},
  "geometry": {"coordinates":[6.41837,62.19364],"type":"Point"}
}