{
  "type": "Feature",
  "properties": {
    "gn:admin1_code":"11",
    "gn:admin2_code":"521.0",
    "gn:asciiname":"Mo",
    "gn:country_code":"NO",
    "gn:dem":640,
    "gn:feature_class":"P",
    "gn:feature_code":"PPL",
    "gn:name":"Mo",
    "gn:population":0,
    "gn:timezone":"Europe/Oslo",
    "iso:country":"NO",
    "name:bar_x_preferred":[
        "Mo"
    ],
    "name:hun_x_preferred":[
        "Mo"
    ],
    "name:ind_x_preferred":[
        "Mo"
    ],
    "name:rus_x_preferred":[
        "Mo"
    ],
    "wof:name":"Mo",
    "wof:placetype":"locality"
},
  "geometry": {"coordinates":[10.33333,61.31667],"type":"Point"}
}