{
  "type": "Feature",
  "properties": {
    "gn:admin1_code":"9",
    "gn:admin2_code":"1837.0",
    "gn:asciiname":"Harfjell",
    "gn:country_code":"NO",
    "gn:dem":-9999,
    "gn:feature_class":"P",
    "gn:feature_code":"PPL",
    "gn:name":"Harfjell",
    "gn:population":0,
    "gn:timezone":"Europe/Oslo",
    "iso:country":"NO",
    "wof:name":"Harfjell",
    "wof:placetype":"locality"
},
  "geometry": {"coordinates":[13.28333,66.75],"type":"Point"}
}