{
  "type": "Feature",
  "properties": {
    "iso:country":"NO",
    "name:ceb_x_preferred":[
        "T\u00e5rn\u00e5sen"
    ],
    "name:fas_x_preferred":[
        "\u062a\u0627\u0631\u0646\u0627\u0633\u0646"
    ],
    "name:jav_x_preferred":[
        "T\u00e5rn\u00e5sen"
    ],
    "name:msa_x_preferred":[
        "T\u00e5rn\u00e5sen"
    ],
    "name:nor_x_preferred":[
        "T\u00e5rn\u00e5sen"
    ],
    "qs_pg:aaroncc":"NO",
    "qs_pg:name":"T\u00e5rn\u00e5sen",
    "qs_pg:name_adm0":"Norge",
    "qs_pg:name_adm1":"Akershus Fylke",
    "qs_pg:photos":61,
    "qs_pg:photos_1k":12,
    "qs_pg:photos_9k":1,
    "qs_pg:photos_9r":2,
    "qs_pg:photos_all":61,
    "qs_pg:photos_sr":2,
    "qs_pg:pop_sr":0,
    "qs_pg:qs_pg_placetype":"locality",
    "qs_pg:qs_pg_placetype_gp":"Town",
    "qs_pg:woe_adm0":23424910,
    "woe:adm0_id":23424910,
    "woe:name_adm0":"Norge",
    "woe:name_adm1":"Akershus Fylke",
    "woe:placetype":"Town",
    "wof:name":"T\u00e5rn\u00e5sen",
    "wof:placetype":"locality"
},
  "geometry": {"coordinates":[10.815482,59.816583],"type":"Point"}
}