{
  "type": "Feature",
  "properties": {
    "gn:country":"NO",
    "gn:fcode":"PPL",
    "gn:population":0,
    "iso:country":"NO",
    "name:eng_x_preferred":[
        "S\u00f8rrollnes"
    ],
    "name:fra_x_preferred":[
        "S\u00f8rrollnes"
    ],
    "name:msa_x_preferred":[
        "S\u00f8rrollnes"
    ],
    "name:nld_x_preferred":[
        "S\u00f8rrollnes"
    ],
    "name:nno_x_preferred":[
        "S\u00f8rrollnes"
    ],
    "name:nob_x_preferred":[
        "S\u00f8rrollnes"
    ],
    "name:spa_x_preferred":[
        "S\u00f8rrollnes"
    ],
    "name:und_x_variant":[
        "Roldnes"
    ],
    "qs_pg:aaroncc":"NO",
    "qs_pg:gn_country":"NO",
    "qs_pg:gn_fcode":"PPL",
    "qs_pg:gn_pop":0,
    "qs_pg:name":"S\u00f6rrollnes",
    "qs_pg:name_adm0":"Norge",
    "qs_pg:name_adm1":"Troms Fylke",
    "qs_pg:photos":141,
    "qs_pg:photos_1k":29,
    "qs_pg:photos_9k":1,
    "qs_pg:photos_9r":3,
    "qs_pg:photos_all":141,
    "qs_pg:photos_sr":3,
    "qs_pg:pop_sr":0,
    "qs_pg:qs_pg_placetype":"locality",
    "qs_pg:qs_pg_placetype_gp":"Town",
    "qs_pg:woe_adm0":23424910,
    "woe:adm0_id":23424910,
    "woe:name_adm0":"Norge",
    "woe:name_adm1":"Troms Fylke",
    "woe:placetype":"Town",
    "wof:name":"S\u00f6rrollnes",
    "wof:placetype":"locality"
},
  "geometry": {"coordinates":[16.86417,68.72667],"type":"Point"}
}