{
  "type": "Feature",
  "properties": {
    "gn:admin1_code":"19.0",
    "gn:admin2_code":"1018.0",
    "gn:asciiname":"Songvik",
    "gn:cc2":"NO",
    "gn:country_code":"NO",
    "gn:dem":7,
    "gn:feature_class":"P",
    "gn:feature_code":"PPL",
    "gn:name":"Songvik",
    "gn:population":0,
    "gn:timezone":"Europe/Oslo",
    "iso:country":"NO",
    "name:und_x_variant":[
        "Songvig",
        "Songvik"
    ],
    "wof:name":"Songvik",
    "wof:placetype":"locality"
},
  "geometry": {"coordinates":[7.83333,58.08333],"type":"Point"}
}