{
  "type": "Feature",
  "properties": {
    "gn:admin1_code":"21",
    "gn:admin2_code":"5028.0",
    "gn:asciiname":"Boland",
    "gn:country_code":"NO",
    "gn:dem":155,
    "gn:feature_class":"P",
    "gn:feature_code":"PPL",
    "gn:name":"B\u00f8land",
    "gn:population":0,
    "gn:timezone":"Europe/Oslo",
    "iso:country":"NO",
    "name:deu_x_preferred":[
        "Boland"
    ],
    "name:fra_x_preferred":[
        "Boland"
    ],
    "name:ita_x_preferred":[
        "Boland"
    ],
    "name:rus_x_preferred":[
        "\u0411\u043e\u043b\u0430\u043d\u0434"
    ],
    "name:slv_x_preferred":[
        "Boland"
    ],
    "name:swe_x_preferred":[
        "Boland"
    ],
    "name:ukr_x_preferred":[
        "\u0411\u043e\u043b\u0430\u043d\u0434"
    ],
    "wof:name":"Boland",
    "wof:placetype":"locality"
},
  "geometry": {"coordinates":[10.3563,63.20299],"type":"Point"}
}