{
  "type": "Feature",
  "properties": {
    "gn:admin1_code":"5.0",
    "gn:admin2_code":"2017.0",
    "gn:asciiname":"Goavkejohka",
    "gn:cc2":"NO",
    "gn:country_code":"NO",
    "gn:dem":40,
    "gn:feature_class":"P",
    "gn:feature_code":"PPL",
    "gn:name":"Goavkejohka",
    "gn:population":0,
    "gn:timezone":"Europe/Oslo",
    "iso:country":"NO",
    "name:jav_x_preferred":[
        "Kokelv"
    ],
    "name:msa_x_preferred":[
        "Kokelv"
    ],
    "name:nno_x_preferred":[
        "Kokelv"
    ],
    "name:nor_x_preferred":[
        "Kokelv"
    ],
    "name:sme_x_preferred":[
        "Goavkej\u00e5kka"
    ],
    "name:sme_x_variant":[
        "Goavkejohka"
    ],
    "name:swe_x_preferred":[
        "Kokelv"
    ],
    "wof:name":"Goavkejohka",
    "wof:placetype":"locality"
},
  "geometry": {"coordinates":[24.65272,70.61324],"type":"Point"}
}