{
  "type": "Feature",
  "properties": {
    "gn:admin1_code":"17",
    "gn:admin2_code":"833.0",
    "gn:asciiname":"Heggtveit",
    "gn:country_code":"NO",
    "gn:dem":618,
    "gn:feature_class":"P",
    "gn:feature_code":"PPL",
    "gn:name":"Heggtveit",
    "gn:population":0,
    "gn:timezone":"Europe/Oslo",
    "iso:country":"NO",
    "wof:name":"Heggtveit",
    "wof:placetype":"locality"
},
  "geometry": {"coordinates":[8.16667,59.45],"type":"Point"}
}