{
  "type": "Feature",
  "properties": {
    "gn:admin1_code":"9.0",
    "gn:admin2_code":"1845.0",
    "gn:asciiname":"Sorfjordskardet",
    "gn:cc2":"NO",
    "gn:country_code":"NO",
    "gn:dem":380,
    "gn:feature_class":"P",
    "gn:feature_code":"PPL",
    "gn:name":"S\u00f8rfjordskardet",
    "gn:population":0,
    "gn:timezone":"Europe/Oslo",
    "iso:country":"NO",
    "name:und_x_variant":[
        "S\u00f8rfj\u00f6rdskaret",
        "S\u00f8rfjordskardet"
    ],
    "wof:name":"Sorfjordskardet",
    "wof:placetype":"locality"
},
  "geometry": {"coordinates":[15.91667,67.58333],"type":"Point"}
}