{
  "type": "Feature",
  "properties": {
    "gn:admin1_code":"21",
    "gn:admin2_code":"5015.0",
    "gn:asciiname":"Melskardet",
    "gn:cc2":"NO",
    "gn:country_code":"NO",
    "gn:dem":15,
    "gn:feature_class":"P",
    "gn:feature_code":"PPL",
    "gn:name":"Melskardet",
    "gn:population":0,
    "gn:timezone":"Europe/Oslo",
    "iso:country":"NO",
    "name:und_x_variant":[
        "Melskaret",
        "Melskardet"
    ],
    "wof:name":"Melskardet",
    "wof:placetype":"locality"
},
  "geometry": {"coordinates":[9.40189,63.67213],"type":"Point"}
}