{
  "type": "Feature",
  "properties": {
    "gn:admin1_code":"9.0",
    "gn:admin2_code":"1822.0",
    "gn:asciiname":"Tjaerstad",
    "gn:country_code":"NO",
    "gn:dem":100,
    "gn:feature_class":"P",
    "gn:feature_code":"PPL",
    "gn:name":"Tj\u00e6rstad",
    "gn:population":0,
    "gn:timezone":"Europe/Oslo",
    "iso:country":"NO",
    "wof:name":"Tjaerstad",
    "wof:placetype":"locality"
},
  "geometry": {"coordinates":[12.95,66.03333000000001],"type":"Point"}
}