{
  "type": "Feature",
  "properties": {
    "gn:admin1_code":"18",
    "gn:admin2_code":"1926.0",
    "gn:asciiname":"Faksfjord",
    "gn:country_code":"NO",
    "gn:dem":180,
    "gn:feature_class":"P",
    "gn:feature_code":"PPL",
    "gn:name":"Faksfjord",
    "gn:population":0,
    "gn:timezone":"Europe/Oslo",
    "iso:country":"NO",
    "wof:name":"Faksfjord",
    "wof:placetype":"locality"
},
  "geometry": {"coordinates":[17.56667,68.98333000000001],"type":"Point"}
}