{
  "type": "Feature",
  "properties": {
    "gn:admin1_code":"21",
    "gn:admin2_code":"5040.0",
    "gn:asciiname":"Ledang",
    "gn:country_code":"NO",
    "gn:dem":48,
    "gn:feature_class":"P",
    "gn:feature_code":"PPL",
    "gn:name":"Ledang",
    "gn:population":0,
    "gn:timezone":"Europe/Oslo",
    "iso:country":"NO",
    "wof:name":"Ledang",
    "wof:placetype":"locality"
},
  "geometry": {"coordinates":[11.10969,64.50979],"type":"Point"}
}