{
  "type": "Feature",
  "properties": {
    "gn:admin1_code":"21.0",
    "gn:admin2_code":"5011.0",
    "gn:asciiname":"Svanem",
    "gn:cc2":"NO",
    "gn:country_code":"NO",
    "gn:dem":180,
    "gn:feature_class":"P",
    "gn:feature_code":"PPL",
    "gn:name":"Svanem",
    "gn:population":0,
    "gn:timezone":"Europe/Oslo",
    "iso:country":"NO",
    "name:und_x_variant":[
        "Svanum",
        "Svanem"
    ],
    "wof:name":"Svanem",
    "wof:placetype":"locality"
},
  "geometry": {"coordinates":[8.98333,63.38333000000001],"type":"Point"}
}