{
  "type": "Feature",
  "properties": {
    "gn:admin1_code":"6.0",
    "gn:admin2_code":"426.0",
    "gn:asciiname":"Hebergsaetrene",
    "gn:country_code":"NO",
    "gn:dem":512,
    "gn:feature_class":"P",
    "gn:feature_code":"PPL",
    "gn:name":"Hebergs\u00e6trene",
    "gn:population":0,
    "gn:timezone":"Europe/Oslo",
    "iso:country":"NO",
    "name:nor_x_preferred":[
        "Hebergs\u00e6trene"
    ],
    "wof:name":"Hebergsaetrene",
    "wof:placetype":"locality"
},
  "geometry": {"coordinates":[11.96508,60.76534],"type":"Point"}
}