{
  "type": "Feature",
  "properties": {
    "gn:admin1_code":"5.0",
    "gn:admin2_code":"2020.0",
    "gn:asciiname":"Njarga",
    "gn:cc2":"NO",
    "gn:country_code":"NO",
    "gn:dem":60,
    "gn:feature_class":"P",
    "gn:feature_code":"PPL",
    "gn:name":"Nj\u00e1rga",
    "gn:population":0,
    "gn:timezone":"Europe/Oslo",
    "iso:country":"NO",
    "name:eng_x_preferred":[
        "Indre Sandvik"
    ],
    "name:nor_x_preferred":[
        "Sandvik"
    ],
    "name:rus_x_preferred":[
        "\u0421\u0430\u043d\u043d\u0432\u0438\u043a"
    ],
    "name:sme_x_preferred":[
        "Nj\u00e1rga"
    ],
    "wof:name":"Njarga",
    "wof:placetype":"locality"
},
  "geometry": {"coordinates":[25.13794,70.32255000000001],"type":"Point"}
}