{
  "type": "Feature",
  "properties": {
    "gn:admin1_code":"7",
    "gn:admin2_code":"1259.0",
    "gn:asciiname":"Blom",
    "gn:country_code":"NO",
    "gn:dem":3,
    "gn:feature_class":"P",
    "gn:feature_code":"PPL",
    "gn:name":"Blom",
    "gn:population":0,
    "gn:timezone":"Europe/Oslo",
    "iso:country":"NO",
    "wof:name":"Blom",
    "wof:placetype":"locality"
},
  "geometry": {"coordinates":[4.89167,60.53556],"type":"Point"}
}