{
  "type": "Feature",
  "properties": {
    "gn:admin1_code":"17.0",
    "gn:admin2_code":"815.0",
    "gn:asciiname":"Tveitereid",
    "gn:cc2":"NO",
    "gn:country_code":"NO",
    "gn:dem":63,
    "gn:feature_class":"P",
    "gn:feature_code":"PPL",
    "gn:name":"Tveitereid",
    "gn:population":0,
    "gn:timezone":"Europe/Oslo",
    "iso:country":"NO",
    "name:und_x_variant":[
        "Tveiterei",
        "Tveitereid"
    ],
    "wof:name":"Tveitereid",
    "wof:placetype":"locality"
},
  "geometry": {"coordinates":[9.33333,58.91667],"type":"Point"}
}