{
  "type": "Feature",
  "properties": {
    "gn:admin1_code":"15",
    "gn:admin2_code":"1429.0",
    "gn:asciiname":"Asnes",
    "gn:cc2":"NO",
    "gn:country_code":"NO",
    "gn:dem":60,
    "gn:feature_class":"P",
    "gn:feature_code":"PPL",
    "gn:name":"\u00c5snes",
    "gn:population":0,
    "gn:timezone":"Europe/Oslo",
    "iso:country":"NO",
    "name:und_x_variant":[
        "Aasn\u00e6s",
        "\u00c5snes"
    ],
    "wof:name":"Asnes",
    "wof:placetype":"locality"
},
  "geometry": {"coordinates":[5.20252,61.3362],"type":"Point"}
}