{
  "type": "Feature",
  "properties": {
    "gn:admin1_code":"18.0",
    "gn:admin2_code":"1942.0",
    "gn:asciiname":"Bakkeby",
    "gn:country_code":"NO",
    "gn:dem":1,
    "gn:feature_class":"P",
    "gn:feature_code":"PPL",
    "gn:name":"Bakkeby",
    "gn:population":0,
    "gn:timezone":"Europe/Oslo",
    "iso:country":"NO",
    "name:fkv_x_preferred":[
        "Sokkuvuono"
    ],
    "name:nor_x_preferred":[
        "Bakkeby"
    ],
    "wof:name":"Bakkeby",
    "wof:placetype":"locality"
},
  "geometry": {"coordinates":[20.84865,69.85061],"type":"Point"}
}