{
  "type": "Feature",
  "properties": {
    "gn:admin1_code":"1.0",
    "gn:admin2_code":"236.0",
    "gn:asciiname":"Valer",
    "gn:cc2":"NO",
    "gn:country_code":"NO",
    "gn:dem":160,
    "gn:feature_class":"P",
    "gn:feature_code":"PPL",
    "gn:name":"V\u00e5ler",
    "gn:population":0,
    "gn:timezone":"Europe/Oslo",
    "iso:country":"NO",
    "name:und_x_variant":[
        "Vaaler",
        "V\u00e5ler"
    ],
    "wof:name":"Valer",
    "wof:placetype":"locality"
},
  "geometry": {"coordinates":[11.31667,60.23333],"type":"Point"}
}