{
  "type": "Feature",
  "properties": {
    "gn:admin1_code":"13.0",
    "gn:admin2_code":"105.0",
    "gn:asciiname":"Vister",
    "gn:cc2":"NO",
    "gn:country_code":"NO",
    "gn:dem":0,
    "gn:feature_class":"P",
    "gn:feature_code":"PPL",
    "gn:name":"Vister",
    "gn:population":0,
    "gn:timezone":"Europe/Oslo",
    "iso:country":"NO",
    "name:und_x_variant":[
        "Viste",
        "Vister"
    ],
    "wof:name":"Vister",
    "wof:placetype":"locality"
},
  "geometry": {"coordinates":[11.01667,59.28333000000001],"type":"Point"}
}