{
  "type": "Feature",
  "properties": {
    "gn:admin1_code":"6.0",
    "gn:admin2_code":"412.0",
    "gn:asciiname":"Sjusjoen",
    "gn:cc2":"NO",
    "gn:country_code":"NO",
    "gn:dem":830,
    "gn:feature_class":"P",
    "gn:feature_code":"PPL",
    "gn:name":"Sjusj\u00f8en",
    "gn:population":0,
    "gn:timezone":"Europe/Oslo",
    "iso:country":"NO",
    "name:bul_x_preferred":[
        "\u0428\u0443\u0448\u044c\u043e\u0435\u043d"
    ],
    "name:deu_x_preferred":[
        "Sjusj\u00f8en"
    ],
    "name:est_x_preferred":[
        "Sjusj\u00f8en"
    ],
    "name:fra_x_preferred":[
        "Sjusj\u00f8en"
    ],
    "name:ita_x_preferred":[
        "Sjusj\u00f8en"
    ],
    "name:jav_x_preferred":[
        "Sjusj\u00f8en"
    ],
    "name:msa_x_preferred":[
        "Sjusj\u00f8en"
    ],
    "name:pol_x_preferred":[
        "Sjusj\u00f8en"
    ],
    "name:rus_x_preferred":[
        "\u0428\u0443\u0448\u0435\u043d"
    ],
    "name:swe_x_preferred":[
        "Sjusj\u00f8en"
    ],
    "name:und_x_variant":[
        "Sjusjo"
    ],
    "wof:name":"Sjusjoen",
    "wof:placetype":"locality"
},
  "geometry": {"coordinates":[10.69184,61.15296],"type":"Point"}
}