{
  "type": "Feature",
  "properties": {
    "gn:admin1_code":"18",
    "gn:admin2_code":"1917.0",
    "gn:asciiname":"Stridsvollen",
    "gn:country_code":"NO",
    "gn:dem":-9999,
    "gn:feature_class":"P",
    "gn:feature_code":"PPL",
    "gn:name":"Stridsvollen",
    "gn:population":0,
    "gn:timezone":"Europe/Oslo",
    "iso:country":"NO",
    "wof:name":"Stridsvollen",
    "wof:placetype":"locality"
},
  "geometry": {"coordinates":[17.15444,68.76389],"type":"Point"}
}