{
  "type": "Feature",
  "properties": {
    "gn:admin1_code":"4",
    "gn:admin2_code":"605.0",
    "gn:asciiname":"Land",
    "gn:country_code":"NO",
    "gn:dem":240,
    "gn:feature_class":"P",
    "gn:feature_code":"PPL",
    "gn:name":"Land",
    "gn:population":0,
    "gn:timezone":"Europe/Oslo",
    "iso:country":"NO",
    "name:ben_x_preferred":[
        "\u09ad\u09c2\u09ae\u09bf"
    ],
    "name:bih_x_preferred":[
        "\u091c\u092e\u0940\u0928"
    ],
    "name:cdo_x_preferred":[
        "L\u1e73\u0306k-d\u00ea"
    ],
    "name:ceb_x_preferred":[
        "Yuta"
    ],
    "name:ckb_x_preferred":[
        "\u062e\u0627\u06a9"
    ],
    "name:ell_x_preferred":[
        "\u03a3\u03c4\u03b5\u03c1\u03b9\u03ac"
    ],
    "name:fas_x_preferred":[
        "\u062e\u0634\u06a9\u06cc"
    ],
    "name:gle_x_preferred":[
        "Talamh"
    ],
    "name:hin_x_preferred":[
        "\u092d\u0942\u092e\u093f"
    ],
    "name:ind_x_preferred":[
        "Daratan"
    ],
    "name:isl_x_preferred":[
        "Land"
    ],
    "name:kaz_x_preferred":[
        "\u049a\u04b1\u0440\u044b \u0436\u0435\u0440"
    ],
    "name:lat_x_preferred":[
        "Terra"
    ],
    "name:msa_x_preferred":[
        "Darat"
    ],
    "name:pan_x_preferred":[
        "\u0a1c\u0a3c\u0a2e\u0a40\u0a28"
    ],
    "name:sco_x_preferred":[
        "Laund"
    ],
    "name:sna_x_preferred":[
        "Ivhu"
    ],
    "name:sqi_x_preferred":[
        "Trualli"
    ],
    "name:swa_x_preferred":[
        "Nchi kavu"
    ],
    "name:tam_x_preferred":[
        "\u0ba8\u0bbf\u0bb2\u0bae\u0bcd"
    ],
    "name:tha_x_preferred":[
        "\u0e1e\u0e37\u0e49\u0e19\u0e14\u0e34\u0e19"
    ],
    "name:ukr_x_preferred":[
        "\u0421\u0443\u0445\u043e\u0434\u0456\u043b"
    ],
    "name:vie_x_preferred":[
        "\u0110\u1ea5t li\u1ec1n"
    ],
    "wof:name":"Land",
    "wof:placetype":"locality"
},
  "geometry": {"coordinates":[9.86667,60.23333],"type":"Point"}
}