{
  "type": "Feature",
  "properties": {
    "gn:admin1_code":"4",
    "gn:admin2_code":"605.0",
    "gn:asciiname":"Land",
    "gn:country_code":"NO",
    "gn:dem":240,
    "gn:feature_class":"P",
    "gn:feature_code":"PPL",
    "gn:name":"Land",
    "gn:population":0,
    "gn:timezone":"Europe/Oslo",
    "iso:country":"NO",
    "wof:name":"Land",
    "wof:placetype":"locality"
},
  "geometry": {"coordinates":[9.86667,60.23333],"type":"Point"}
}