{
  "type": "Feature",
  "properties": {
    "gn:admin1_code":"1.0",
    "gn:admin2_code":"237.0",
    "gn:asciiname":"Tunneltoppen",
    "gn:country_code":"NO",
    "gn:dem":140,
    "gn:feature_class":"P",
    "gn:feature_code":"PPL",
    "gn:name":"Tunneltoppen",
    "gn:population":0,
    "gn:timezone":"Europe/Oslo",
    "iso:country":"NO",
    "name:nor_x_preferred":[
        "Tunneltoppen"
    ],
    "wof:name":"Tunneltoppen",
    "wof:placetype":"locality"
},
  "geometry": {"coordinates":[11.2657,60.32121],"type":"Point"}
}