{
  "type": "Feature",
  "properties": {
    "gn:admin1_code":"9.0",
    "gn:admin2_code":"1841.0",
    "gn:asciiname":"Oynes",
    "gn:cc2":"NO",
    "gn:country_code":"NO",
    "gn:dem":-9999,
    "gn:feature_class":"P",
    "gn:feature_code":"PPL",
    "gn:name":"\u00d8ynes",
    "gn:population":0,
    "gn:timezone":"Europe/Oslo",
    "iso:country":"NO",
    "name:und_x_variant":[
        "Oines",
        "\u00d8ynes"
    ],
    "wof:name":"Oynes",
    "wof:placetype":"locality"
},
  "geometry": {"coordinates":[15.26667,67.23333000000001],"type":"Point"}
}