{
  "type": "Feature",
  "properties": {
    "gn:admin1_code":"13.0",
    "gn:admin2_code":"106.0",
    "gn:asciiname":"Skara",
    "gn:country_code":"NO",
    "gn:dem":20,
    "gn:feature_class":"P",
    "gn:feature_code":"PPL",
    "gn:name":"Sk\u00e5ra",
    "gn:population":0,
    "gn:timezone":"Europe/Oslo",
    "iso:country":"NO",
    "name:ara_x_preferred":[
        "\u0633\u0643\u0627\u0631\u0627"
    ],
    "name:bul_x_preferred":[
        "\u0421\u043a\u0430\u0440\u0430"
    ],
    "name:cat_x_preferred":[
        "Skara"
    ],
    "name:ceb_x_preferred":[
        "Skara"
    ],
    "name:dan_x_preferred":[
        "Skara"
    ],
    "name:deu_x_preferred":[
        "Skara"
    ],
    "name:est_x_preferred":[
        "Skara"
    ],
    "name:eus_x_preferred":[
        "Skara"
    ],
    "name:fao_x_preferred":[
        "Skara"
    ],
    "name:fas_x_preferred":[
        "\u0633\u06a9\u0648\u0631\u0627"
    ],
    "name:fin_x_preferred":[
        "Skaran kunta"
    ],
    "name:fra_x_preferred":[
        "Skara"
    ],
    "name:gla_x_preferred":[
        "Skara"
    ],
    "name:hrv_x_preferred":[
        "Skara"
    ],
    "name:ind_x_preferred":[
        "Skara"
    ],
    "name:isl_x_preferred":[
        "Skara"
    ],
    "name:ita_x_preferred":[
        "Skara"
    ],
    "name:kor_x_preferred":[
        "\uc2a4\uce74\ub77c"
    ],
    "name:lat_x_preferred":[
        "Scara"
    ],
    "name:mrj_x_preferred":[
        "\u0421\u043a\u0430\u0440\u0430"
    ],
    "name:nld_x_preferred":[
        "Skara"
    ],
    "name:nno_x_preferred":[
        "Skara"
    ],
    "name:nor_x_preferred":[
        "Sk\u00e5ra"
    ],
    "name:nor_x_variant":[
        "Skara"
    ],
    "name:pol_x_preferred":[
        "Skara"
    ],
    "name:por_x_preferred":[
        "Skara"
    ],
    "name:ron_x_preferred":[
        "Skara"
    ],
    "name:rus_x_preferred":[
        "\u0421\u043a\u0430\u0440\u0430"
    ],
    "name:spa_x_preferred":[
        "Skara"
    ],
    "name:sqi_x_preferred":[
        "Skara"
    ],
    "name:srp_x_preferred":[
        "\u0421\u043a\u0430\u0440\u0430"
    ],
    "name:swe_x_preferred":[
        "Skara"
    ],
    "name:tur_x_preferred":[
        "Skara"
    ],
    "name:ukr_x_preferred":[
        "\u0421\u043a\u0430\u0440\u0430"
    ],
    "name:vol_x_preferred":[
        "Skara"
    ],
    "name:zho_x_preferred":[
        "\u65af\u5361\u62c9"
    ],
    "wof:name":"Skara",
    "wof:placetype":"locality"
},
  "geometry": {"coordinates":[10.90074,59.24423],"type":"Point"}
}