{
  "type": "Feature",
  "properties": {
    "gn:admin1_code":"13.0",
    "gn:admin2_code":"106.0",
    "gn:asciiname":"Skara",
    "gn:country_code":"NO",
    "gn:dem":20,
    "gn:feature_class":"P",
    "gn:feature_code":"PPL",
    "gn:name":"Sk\u00e5ra",
    "gn:population":0,
    "gn:timezone":"Europe/Oslo",
    "iso:country":"NO",
    "name:nor_x_preferred":[
        "Sk\u00e5ra"
    ],
    "wof:name":"Skara",
    "wof:placetype":"locality"
},
  "geometry": {"coordinates":[10.90074,59.24423],"type":"Point"}
}