{
  "type": "Feature",
  "properties": {
    "gn:country":"NO",
    "gn:fcode":"PPLA2",
    "gn:population":914,
    "iso:country":"NO",
    "name:ceb_x_preferred":[
        "Berk\u00e5k"
    ],
    "name:dan_x_preferred":[
        "Berk\u00e5k"
    ],
    "name:deu_x_preferred":[
        "Berk\u00e5k"
    ],
    "name:eng_x_preferred":[
        "Berk\u00e5k"
    ],
    "name:fra_x_preferred":[
        "Berk\u00e5k"
    ],
    "name:heb_x_preferred":[
        "\u05d1\u05e8\u05e7\u05d0\u05e7"
    ],
    "name:isl_x_preferred":[
        "Berk\u00e5k"
    ],
    "name:msa_x_preferred":[
        "Berk\u00e5k"
    ],
    "name:nld_x_preferred":[
        "Berk\u00e5k"
    ],
    "name:nno_x_preferred":[
        "Berk\u00e5k"
    ],
    "name:nob_x_preferred":[
        "Berk\u00e5k"
    ],
    "name:ron_x_preferred":[
        "Berk\u00e5k"
    ],
    "name:spa_x_preferred":[
        "Berk\u00e5k"
    ],
    "name:und_x_variant":[
        "Berkaak"
    ],
    "qs_pg:aaroncc":"NO",
    "qs_pg:gn_country":"NO",
    "qs_pg:gn_fcode":"PPLA2",
    "qs_pg:gn_pop":914,
    "qs_pg:name":"Berk\u00e5k",
    "qs_pg:photos_9r":0,
    "qs_pg:photos_sr":0,
    "qs_pg:pop_sr":2,
    "qs_pg:qs_pg_placetype":"locality",
    "wof:name":"Berk\u00e5k",
    "wof:placetype":"locality",
    "wof:population":914
},
  "geometry": {"coordinates":[10.01177,62.82496],"type":"Point"}
}