{
  "type": "Feature",
  "properties": {
    "gn:gn_country":"NO",
    "gn:gn_fcode":"PPLA2",
    "gn:gn_pop":914,
    "gn:population":914,
    "iso:country":"NO",
    "name:dut_x_preferred":[
        "Berk\u00e5k"
    ],
    "name:eng_x_preferred":[
        "Berk\u00e5k"
    ],
    "name:fre_x_preferred":[
        "Berk\u00e5k"
    ],
    "name:ger_x_preferred":[
        "Berk\u00e5k"
    ],
    "name:may_x_preferred":[
        "Berk\u00e5k"
    ],
    "name:nno_x_preferred":[
        "Berk\u00e5k"
    ],
    "name:nob_x_preferred":[
        "Berk\u00e5k"
    ],
    "name:rum_x_preferred":[
        "Berk\u00e5k"
    ],
    "name:unk_x_variant":[
        "Berkaak"
    ],
    "qs_pg:aaroncc":"NO",
    "qs_pg:gn_country":"NO",
    "qs_pg:gn_fcode":"PPLA2",
    "qs_pg:gn_pop":914,
    "qs_pg:name":"Berk\u00e5k",
    "qs_pg:photos_9r":0,
    "qs_pg:photos_sr":0,
    "qs_pg:pop_sr":2,
    "qs_pg:qs_pg_placetype":"locality",
    "wof:name":"Berk\u00e5k",
    "wof:placetype":"locality",
    "wof:population":914
},
  "geometry": {"coordinates":[10.01177,62.82496],"type":"Point"}
}