{
  "type": "Feature",
  "properties": {
    "gn:country":"NO",
    "gn:fcode":"PPL",
    "gn:population":0,
    "iso:country":"NO",
    "name:dan_x_preferred":[
        "Haukeli"
    ],
    "name:deu_x_preferred":[
        "Haukeli"
    ],
    "name:eng_x_preferred":[
        "Haukeli"
    ],
    "name:fra_x_preferred":[
        "Haukeli"
    ],
    "name:msa_x_preferred":[
        "Haukeligrend"
    ],
    "name:nld_x_preferred":[
        "Haukeli"
    ],
    "name:nno_x_preferred":[
        "Haukeli"
    ],
    "name:nob_x_preferred":[
        "Haukeli"
    ],
    "name:nor_x_preferred":[
        "Haukeli"
    ],
    "name:nor_x_variant":[
        "Haukeligrend"
    ],
    "qs_pg:aaroncc":"NO",
    "qs_pg:gn_country":"NO",
    "qs_pg:gn_fcode":"PPL",
    "qs_pg:gn_pop":0,
    "qs_pg:name":"Haukeligrend",
    "qs_pg:name_adm0":"Norge",
    "qs_pg:name_adm1":"Telemark Fylke",
    "qs_pg:photos":90,
    "qs_pg:photos_1k":18,
    "qs_pg:photos_9k":1,
    "qs_pg:photos_9r":3,
    "qs_pg:photos_all":90,
    "qs_pg:photos_sr":3,
    "qs_pg:pop_sr":0,
    "qs_pg:qs_pg_placetype":"locality",
    "qs_pg:qs_pg_placetype_gp":"Town",
    "qs_pg:woe_adm0":23424910,
    "woe:adm0_id":23424910,
    "woe:name_adm0":"Norge",
    "woe:name_adm1":"Telemark Fylke",
    "woe:placetype":"Town",
    "wof:name":"Haukeligrend",
    "wof:placetype":"locality"
},
  "geometry": {"coordinates":[7.51667,59.75],"type":"Point"}
}