{
  "type": "Feature",
  "properties": {
    "gn:gn_country":"NO",
    "gn:gn_fcode":"PPLX",
    "gn:gn_pop":0,
    "iso:country":"NO",
    "qs_pg:aaroncc":"NO",
    "qs_pg:gn_country":"NO",
    "qs_pg:gn_fcode":"PPLX",
    "qs_pg:gn_pop":0,
    "qs_pg:name":"Liabru",
    "qs_pg:name_adm0":"Norge",
    "qs_pg:name_adm1":"Oslo Fylke",
    "qs_pg:photos":26,
    "qs_pg:photos_1k":5,
    "qs_pg:photos_9k":1,
    "qs_pg:photos_9r":2,
    "qs_pg:photos_all":26,
    "qs_pg:photos_sr":2,
    "qs_pg:pop_sr":0,
    "qs_pg:qs_pg_placetype":"neighbourhood",
    "qs_pg:qs_pg_placetype_gp":"Suburb",
    "qs_pg:woe_adm0":23424910,
    "woe:adm0_id":23424910,
    "woe:name_adm0":"Norge",
    "woe:name_adm1":"Oslo Fylke",
    "woe:placetype":"Suburb",
    "wof:name":"Liabru",
    "wof:placetype":"neighbourhood"
},
  "geometry": {"coordinates":[10.81667,59.85],"type":"Point"}
}