{
  "type": "Feature",
  "properties": {
    "gn:admin1_code":"8.0",
    "gn:asciiname":"Ulsteinvik weather pws station",
    "gn:country_code":"NO",
    "gn:dem":60,
    "gn:elevation":"11.0",
    "gn:feature_class":"P",
    "gn:feature_code":"PPL",
    "gn:name":"Ulsteinvik weather pws station",
    "gn:population":5000,
    "gn:timezone":"Europe/Oslo",
    "iso:country":"NO",
    "name:eng_x_preferred":[
        "Ulsteinvik weather"
    ],
    "name:nor_x_preferred":[
        "Ulsteinvik veret"
    ],
    "name:nor_x_variant":[
        "ulsteinvik v\u00e6ret"
    ],
    "wof:name":"Ulsteinvik weather pws station",
    "wof:placetype":"locality",
    "wof:population":5000
},
  "geometry": {"coordinates":[5.84385,62.34338],"type":"Point"}
}