{
  "type": "Feature",
  "properties": {
    "gn:admin1_code":"5.0",
    "gn:admin2_code":"2022.0",
    "gn:asciiname":"Dyfjord",
    "gn:country_code":"NO",
    "gn:dem":1,
    "gn:feature_class":"P",
    "gn:feature_code":"PPL",
    "gn:name":"Dyfjord",
    "gn:population":0,
    "gn:timezone":"Europe/Oslo",
    "iso:country":"NO",
    "wof:name":"Dyfjord",
    "wof:placetype":"locality"
},
  "geometry": {"coordinates":[27.22335,70.89828],"type":"Point"}
}