{
  "type": "Feature",
  "properties": {
    "gn:admin1_code":"11.0",
    "gn:admin2_code":"522.0",
    "gn:asciiname":"Kidlia",
    "gn:country_code":"NO",
    "gn:dem":833,
    "gn:feature_class":"P",
    "gn:feature_code":"PPL",
    "gn:name":"Kidlia",
    "gn:population":0,
    "gn:timezone":"Europe/Oslo",
    "iso:country":"NO",
    "name:nor_x_preferred":[
        "Kidlia"
    ],
    "wof:name":"Kidlia",
    "wof:placetype":"locality"
},
  "geometry": {"coordinates":[10.1789,61.34834],"type":"Point"}
}