{
  "type": "Feature",
  "properties": {
    "gn:admin1_code":"18",
    "gn:admin2_code":"1925.0",
    "gn:asciiname":"Nordstraumen",
    "gn:cc2":"NO",
    "gn:country_code":"NO",
    "gn:dem":5,
    "gn:feature_class":"P",
    "gn:feature_code":"PPL",
    "gn:name":"Nordstraumen",
    "gn:population":0,
    "gn:timezone":"Europe/Oslo",
    "iso:country":"NO",
    "name:und_x_variant":[
        "Nordstrom",
        "Nordstraumen"
    ],
    "wof:name":"Nordstraumen",
    "wof:placetype":"neighbourhood"
},
  "geometry": {"coordinates":[18.17042,69.14153],"type":"Point"}
}