{
  "type": "Feature",
  "properties": {
    "gn:admin1_code":"7",
    "gn:admin2_code":"1252.0",
    "gn:asciiname":"Mostraum",
    "gn:country_code":"NO",
    "gn:dem":99,
    "gn:feature_class":"P",
    "gn:feature_code":"PPL",
    "gn:name":"Mostraum",
    "gn:population":0,
    "gn:timezone":"Europe/Oslo",
    "iso:country":"NO",
    "wof:name":"Mostraum",
    "wof:placetype":"locality"
},
  "geometry": {"coordinates":[5.73333,60.76667],"type":"Point"}
}