{
  "type": "Feature",
  "properties": {
    "gn:admin1_code":"11.0",
    "gn:admin2_code":"502.0",
    "gn:asciiname":"Redalen",
    "gn:country_code":"NO",
    "gn:dem":123,
    "gn:feature_class":"P",
    "gn:feature_code":"PPL",
    "gn:name":"Redalen",
    "gn:population":0,
    "gn:timezone":"Europe/Oslo",
    "iso:country":"NO",
    "wof:name":"Redalen",
    "wof:placetype":"locality"
},
  "geometry": {"coordinates":[10.66685,60.89175],"type":"Point"}
}