{
  "type": "Feature",
  "properties": {
    "gn:gn_country":"NO",
    "iso:country":"NO",
    "name:ara_x_preferred":[
        "\u0644\u064a\u0646\u062c\u0647"
    ],
    "name:bar_x_preferred":[
        "Linge"
    ],
    "name:ceb_x_preferred":[
        "Linge"
    ],
    "name:chv_x_preferred":[
        "\u041b\u0438\u043d\u0433\u0435"
    ],
    "name:deu_x_preferred":[
        "Linge"
    ],
    "name:fra_x_preferred":[
        "Linge"
    ],
    "name:ita_x_preferred":[
        "Linge"
    ],
    "name:kat_x_preferred":[
        "\u10da\u10d8\u10dc\u10d2\u10d4"
    ],
    "name:nld_x_preferred":[
        "Linge"
    ],
    "name:nno_x_preferred":[
        "Linge"
    ],
    "name:por_x_preferred":[
        "Rio Linge"
    ],
    "name:rus_x_preferred":[
        "\u041b\u0438\u043d\u0433\u0435"
    ],
    "qs_pg:aaroncc":"NO",
    "qs_pg:gn_country":"NO",
    "qs_pg:name":"Linge",
    "qs_pg:name_adm0":"Norge",
    "qs_pg:name_adm1":"M\u00f8re og Romsdal Fylke",
    "qs_pg:photos":26,
    "qs_pg:photos_1k":5,
    "qs_pg:photos_9k":1,
    "qs_pg:photos_9r":2,
    "qs_pg:photos_all":26,
    "qs_pg:photos_sr":2,
    "qs_pg:pop_sr":0,
    "qs_pg:qs_pg_placetype":"locality",
    "qs_pg:qs_pg_placetype_gp":"Town",
    "qs_pg:woe_adm0":23424910,
    "woe:adm0_id":23424910,
    "woe:name_adm0":"Norge",
    "woe:name_adm1":"M\u00f8re og Romsdal Fylke",
    "woe:placetype":"Town",
    "wof:name":"Linge",
    "wof:placetype":"locality"
},
  "geometry": {"coordinates":[7.189006,62.285491],"type":"Point"}
}