{
  "type": "Feature",
  "properties": {
    "gn:population":409,
    "iso:country":"NO",
    "name:bar_x_preferred":[
        "Henningsv\u00e6r"
    ],
    "name:ceb_x_preferred":[
        "Henningsv\u00e6r"
    ],
    "name:dan_x_preferred":[
        "Henningsv\u00e6r"
    ],
    "name:deu_x_preferred":[
        "Henningsv\u00e6r"
    ],
    "name:eng_x_preferred":[
        "Henningsvar"
    ],
    "name:eng_x_variant":[
        "Henningsv\u00e6r"
    ],
    "name:fin_x_preferred":[
        "Henningsv\u00e6r"
    ],
    "name:fra_x_preferred":[
        "Henningsv\u00e6r"
    ],
    "name:ita_x_preferred":[
        "Henningsvaer"
    ],
    "name:jav_x_preferred":[
        "Henningsv\u00e6r"
    ],
    "name:jpn_x_preferred":[
        "\u30d8\u30cb\u30f3\u30b0\u30b9\u30f4\u30a1\u30fc\u30eb"
    ],
    "name:msa_x_preferred":[
        "Henningsv\u00e6r"
    ],
    "name:nld_x_preferred":[
        "Henningsv\u00e6r"
    ],
    "name:nno_x_preferred":[
        "Henningsv\u00e6r"
    ],
    "name:nob_x_preferred":[
        "Henningsv\u00e6r"
    ],
    "name:nor_x_colloquial":[
        "Henningsvaer",
        "Henningsvaers"
    ],
    "name:nor_x_preferred":[
        "Henningsv\u00e6r"
    ],
    "name:nor_x_variant":[
        "Henningsv\u00e6rs"
    ],
    "name:por_x_preferred":[
        "Henningsv\u00e6r"
    ],
    "name:ron_x_preferred":[
        "Henningsv\u00e6r"
    ],
    "name:rus_x_preferred":[
        "\u0425\u0435\u043d\u043d\u0438\u043d\u0433\u0441\u0432\u0435\u0440"
    ],
    "name:spa_x_preferred":[
        "Henningsv\u00e6r"
    ],
    "name:zho_x_preferred":[
        "\u4ea8\u5b81\u65af\u97e6\u5c14"
    ],
    "qs:a0":"Norge",
    "qs:a1":"*Nordland",
    "qs:a1r":"0",
    "qs:adm0":"Norge",
    "qs:la_lc":"*",
    "qs:level":"locality",
    "qs:loc":"Henningsv\u00e6r",
    "qs:loc_alt":"Henningsvaer",
    "qs:pop":0,
    "qs:type":"buffered point",
    "wd:wordcount":171,
    "wof:lang":[
        "nor"
    ],
    "wof:name":"Henningsv\u00e6r",
    "wof:placetype":"locality",
    "wof:population":409
},
  "geometry": {"coordinates":[14.222271,68.168999],"type":"Point"}
}