{
  "type": "Feature",
  "properties": {
    "gn:admin1_code":"7.0",
    "gn:admin2_code":"1235.0",
    "gn:asciiname":"Gullfjordungen",
    "gn:country_code":"NO",
    "gn:dem":47,
    "gn:feature_class":"P",
    "gn:feature_code":"PPL",
    "gn:name":"Gullfjordungen",
    "gn:population":0,
    "gn:timezone":"Europe/Oslo",
    "iso:country":"NO",
    "name:nor_x_preferred":[
        "Gullfjordungen"
    ],
    "wof:name":"Gullfjordungen",
    "wof:placetype":"locality"
},
  "geometry": {"coordinates":[6.37628,60.62157],"type":"Point"}
}