{
  "type": "Feature",
  "properties": {
    "gn:admin1_code":"4.0",
    "gn:admin2_code":"619.0",
    "gn:asciiname":"Krakhamar",
    "gn:country_code":"NO",
    "gn:dem":1020,
    "gn:feature_class":"P",
    "gn:feature_code":"PPL",
    "gn:name":"Kr\u00e5khamar",
    "gn:population":0,
    "gn:timezone":"Europe/Oslo",
    "iso:country":"NO",
    "name:nor_x_preferred":[
        "Kr\u00e5khamar"
    ],
    "wof:name":"Krakhamar",
    "wof:placetype":"locality"
},
  "geometry": {"coordinates":[8.44431,60.74671],"type":"Point"}
}