{
  "type": "Feature",
  "properties": {
    "gn:admin1_code":"11",
    "gn:admin2_code":"520.0",
    "gn:asciiname":"Bjorge",
    "gn:country_code":"NO",
    "gn:dem":600,
    "gn:feature_class":"P",
    "gn:feature_code":"PPL",
    "gn:name":"Bj\u00f8rge",
    "gn:population":0,
    "gn:timezone":"Europe/Oslo",
    "iso:country":"NO",
    "wof:name":"Bjorge",
    "wof:placetype":"locality"
},
  "geometry": {"coordinates":[10.28333,61.38333000000001],"type":"Point"}
}