{
  "type": "Feature",
  "properties": {
    "gn:admin1_code":"9.0",
    "gn:admin2_code":"1839.0",
    "gn:asciiname":"Troalia",
    "gn:cc2":"NO",
    "gn:country_code":"NO",
    "gn:dem":120,
    "gn:feature_class":"P",
    "gn:feature_code":"PPL",
    "gn:name":"Tro\u00e5lia",
    "gn:population":0,
    "gn:timezone":"Europe/Oslo",
    "iso:country":"NO",
    "name:und_x_variant":[
        "Troaalien",
        "Tro\u00e5lia"
    ],
    "wof:name":"Troalia",
    "wof:placetype":"locality"
},
  "geometry": {"coordinates":[14.75,66.91667],"type":"Point"}
}