{
  "type": "Feature",
  "properties": {
    "gn:admin1_code":"21",
    "gn:admin2_code":"5013.0",
    "gn:asciiname":"Melandsjo",
    "gn:country_code":"NO",
    "gn:dem":20,
    "gn:feature_class":"P",
    "gn:feature_code":"PPL",
    "gn:name":"Melandsj\u00f8",
    "gn:population":0,
    "gn:timezone":"Europe/Oslo",
    "iso:country":"NO",
    "name:msa_x_preferred":[
        "Melandsj\u00f8"
    ],
    "name:nor_x_preferred":[
        "Melandsj\u00f8en"
    ],
    "name:und_x_variant":[
        "Melandsj\u00f8en"
    ],
    "wof:name":"Melandsjo",
    "wof:placetype":"locality"
},
  "geometry": {"coordinates":[8.73192,63.62909000000001],"type":"Point"}
}