{
  "type": "Feature",
  "properties": {
    "gn:country":"NO",
    "iso:country":"NO",
    "name:eng_x_preferred":[
        "Gausvik"
    ],
    "name:fra_x_preferred":[
        "Gausvik"
    ],
    "name:msa_x_preferred":[
        "Gausvik"
    ],
    "name:nld_x_preferred":[
        "Gausvik"
    ],
    "name:nno_x_preferred":[
        "Gausvik"
    ],
    "name:nob_x_preferred":[
        "Gausvik"
    ],
    "name:spa_x_preferred":[
        "Gausvik"
    ],
    "qs_pg:aaroncc":"NO",
    "qs_pg:gn_country":"NO",
    "qs_pg:name":"Gausvik",
    "qs_pg:name_adm0":"Norge",
    "qs_pg:name_adm1":"Troms Fylke",
    "qs_pg:photos":40,
    "qs_pg:photos_1k":8,
    "qs_pg:photos_9k":1,
    "qs_pg:photos_9r":2,
    "qs_pg:photos_all":40,
    "qs_pg:photos_sr":2,
    "qs_pg:pop_sr":0,
    "qs_pg:qs_pg_placetype":"locality",
    "qs_pg:qs_pg_placetype_gp":"Town",
    "qs_pg:woe_adm0":23424910,
    "woe:adm0_id":23424910,
    "woe:name_adm0":"Norge",
    "woe:name_adm1":"Troms Fylke",
    "woe:placetype":"Town",
    "wof:name":"Gausvik",
    "wof:placetype":"locality"
},
  "geometry": {"coordinates":[16.589097,68.62692800000001],"type":"Point"}
}