{
  "type": "Feature",
  "properties": {
    "gn:admin1_code":"21",
    "gn:admin2_code":"5045.0",
    "gn:asciiname":"Elstad",
    "gn:country_code":"NO",
    "gn:dem":80,
    "gn:feature_class":"P",
    "gn:feature_code":"PPL",
    "gn:name":"Elstad",
    "gn:population":0,
    "gn:timezone":"Europe/Oslo",
    "iso:country":"NO",
    "name:nor_x_preferred":[
        "Elstad"
    ],
    "wof:name":"Elstad",
    "wof:placetype":"locality"
},
  "geometry": {"coordinates":[12.43333,64.51666999999999],"type":"Point"}
}