{
  "type": "Feature",
  "properties": {
    "gn:admin1_code":"9",
    "gn:admin2_code":"1866.0",
    "gn:asciiname":"Marka",
    "gn:cc2":"NO",
    "gn:country_code":"NO",
    "gn:dem":28,
    "gn:feature_class":"P",
    "gn:feature_code":"PPL",
    "gn:name":"Marka",
    "gn:population":0,
    "gn:timezone":"Europe/Oslo",
    "iso:country":"NO",
    "name:und_x_variant":[
        "Marken",
        "Marka"
    ],
    "wof:name":"Marka",
    "wof:placetype":"locality"
},
  "geometry": {"coordinates":[15.03333,68.59999999999999],"type":"Point"}
}