{
  "type": "Feature",
  "properties": {
    "gn:country":"NO",
    "gn:fcode":"FRM",
    "gn:population":20,
    "iso:country":"NO",
    "qs_pg:aaroncc":"NO",
    "qs_pg:gn_country":"NO",
    "qs_pg:gn_fcode":"FRM",
    "qs_pg:gn_pop":20,
    "qs_pg:name":"Rognstad",
    "qs_pg:photos_9r":0,
    "qs_pg:photos_sr":0,
    "qs_pg:pop_sr":1,
    "qs_pg:qs_pg_placetype":"locality",
    "wof:name":"Rognstad",
    "wof:placetype":"locality",
    "wof:population":20
},
  "geometry": {"coordinates":[11.03323,60.44611],"type":"Point"}
}