{
  "type": "Feature",
  "properties": {
    "gn:admin1_code":"19",
    "gn:admin2_code":"1001",
    "gn:asciiname":"Ryen",
    "gn:country_code":"NO",
    "gn:dem":34,
    "gn:feature_class":"P",
    "gn:feature_code":"PPLL",
    "gn:name":"Ryen",
    "gn:population":0,
    "gn:timezone":"Europe/Oslo",
    "iso:country":"NO",
    "name:msa_x_preferred":[
        "Ryen"
    ],
    "name:nor_x_preferred":[
        "Ryen"
    ],
    "name:swe_x_preferred":[
        "Ryen"
    ],
    "wof:name":"Ryen",
    "wof:placetype":"neighbourhood"
},
  "geometry": {"coordinates":[8.10985,58.22357],"type":"Point"}
}