{
  "type": "Feature",
  "properties": {
    "gn:admin1_code":"1",
    "gn:admin2_code":"236",
    "gn:asciiname":"Brarud",
    "gn:country_code":"NO",
    "gn:dem":168,
    "gn:feature_class":"P",
    "gn:feature_code":"PPLL",
    "gn:name":"Br\u00e5rud",
    "gn:population":0,
    "gn:timezone":"Europe/Oslo",
    "iso:country":"NO",
    "name:ceb_x_preferred":[
        "Br\u00e5rud"
    ],
    "name:fra_x_preferred":[
        "Br\u00e5rud"
    ],
    "name:jav_x_preferred":[
        "Br\u00e5rud"
    ],
    "name:msa_x_preferred":[
        "Br\u00e5rud"
    ],
    "name:nld_x_preferred":[
        "Br\u00e5rud"
    ],
    "name:nno_x_preferred":[
        "Br\u00e5rud"
    ],
    "name:nor_x_preferred":[
        "Br\u00e5rud"
    ],
    "name:ron_x_preferred":[
        "Br\u00e5rud"
    ],
    "name:spa_x_preferred":[
        "Br\u00e5rud"
    ],
    "name:swe_x_preferred":[
        "Br\u00e5rud"
    ],
    "name:vie_x_preferred":[
        "Br\u00e5rud"
    ],
    "wof:name":"Brarud",
    "wof:placetype":"locality"
},
  "geometry": {"coordinates":[11.33348,60.20782],"type":"Point"}
}