{
  "type": "Feature",
  "properties": {
    "gn:admin1_code":"8.0",
    "gn:admin2_code":"1563.0",
    "gn:asciiname":"Bjorkan",
    "gn:country_code":"NO",
    "gn:dem":300,
    "gn:feature_class":"P",
    "gn:feature_code":"PPL",
    "gn:name":"Bj\u00f8rkan",
    "gn:population":0,
    "gn:timezone":"Europe/Oslo",
    "iso:country":"NO",
    "name:nor_x_preferred":[
        "Bj\u00f8rkan"
    ],
    "wof:name":"Bjorkan",
    "wof:placetype":"locality"
},
  "geometry": {"coordinates":[8.64621,62.65905],"type":"Point"}
}