{
  "type": "Feature",
  "properties": {
    "gn:admin1_code":"9",
    "gn:admin2_code":"1804.0",
    "gn:asciiname":"Alsos",
    "gn:country_code":"NO",
    "gn:dem":140,
    "gn:feature_class":"P",
    "gn:feature_code":"PPL",
    "gn:name":"Alsos",
    "gn:population":0,
    "gn:timezone":"Europe/Oslo",
    "iso:country":"NO",
    "wof:name":"Alsos",
    "wof:placetype":"locality"
},
  "geometry": {"coordinates":[14.81667,67.51666999999999],"type":"Point"}
}