{
  "type": "Feature",
  "properties": {
    "iso:country":"NO",
    "name:eng_x_preferred":[
        "Gyldenpris"
    ],
    "name:nno_x_preferred":[
        "Gyldenpris"
    ],
    "name:nob_x_preferred":[
        "Gyldenpris"
    ],
    "name:nor_x_preferred":[
        "Gyldenpris"
    ],
    "name:und_x_variant":[
        "Gyllenpris"
    ],
    "qs:gn_adm0_cc":"NO",
    "qs:gn_fcode":"PPLX",
    "qs:gn_local":3161732,
    "qs:gn_nam_loc":"Bergen, Bergen, Hordaland Fylke, NO",
    "qs:gn_namadm1":"07",
    "qs:gn_name":"Gyldenpris",
    "qs:local_max":5825,
    "qs:local_sum":38813,
    "qs:localhoods":24,
    "qs:name":"Gyldenpris",
    "qs:name_adm0":"Norge",
    "qs:name_adm1":"Hordaland Fylke",
    "qs:name_adm2":"Bergen Kommune",
    "qs:name_local":"Bergen",
    "qs:photo_max":54,
    "qs:photo_sum":250,
    "qs:placetype":"Suburb",
    "qs:quad_count":20,
    "qs:woe_adm0":23424910,
    "qs:woe_adm1":2346390,
    "qs:woe_adm2":12592658,
    "qs:woe_lau":0,
    "qs:woe_local":857105,
    "qs:woe_ver":"7.10.0",
    "wd:wordcount":735,
    "wof:lang":[
        "nor"
    ],
    "wof:name":"Gyldenpris",
    "wof:placetype":"neighbourhood"
},
  "geometry": {"coordinates":[5.327245,60.378169],"type":"Point"}
}