{
  "type": "Feature",
  "properties": {
    "iso:country":"NO",
    "name:ceb_x_preferred":[
        "Mer\u00e5ker"
    ],
    "name:eng_x_preferred":[
        "Midtbygda"
    ],
    "name:fra_x_preferred":[
        "Midtbygda"
    ],
    "name:jav_x_preferred":[
        "Midtbygda"
    ],
    "name:msa_x_preferred":[
        "Midtbygda"
    ],
    "name:nld_x_preferred":[
        "Mer\u00e5ker"
    ],
    "name:nno_x_preferred":[
        "Midtbygda i Mer\u00e5ker"
    ],
    "name:nob_x_preferred":[
        "Midtbygda"
    ],
    "name:ron_x_preferred":[
        "Midtbygda"
    ],
    "name:spa_x_preferred":[
        "Midtbygda"
    ],
    "qs_pg:aaroncc":"NO",
    "qs_pg:name":"Midtbygda",
    "qs_pg:name_adm0":"Norge",
    "qs_pg:name_adm1":"Nord-Tr\u00f8ndelag Fylke",
    "qs_pg:photos":27,
    "qs_pg:photos_1k":5,
    "qs_pg:photos_9k":1,
    "qs_pg:photos_9r":2,
    "qs_pg:photos_all":27,
    "qs_pg:photos_sr":2,
    "qs_pg:pop_sr":0,
    "qs_pg:qs_pg_placetype":"locality",
    "qs_pg:qs_pg_placetype_gp":"Town",
    "qs_pg:woe_adm0":23424910,
    "woe:adm0_id":23424910,
    "woe:name_adm0":"Norge",
    "woe:name_adm1":"Nord-Tr\u00f8ndelag Fylke",
    "woe:placetype":"Town",
    "wof:name":"Midtbygda",
    "wof:placetype":"locality"
},
  "geometry": {"coordinates":[11.694087,63.439362],"type":"Point"}
}