{
  "type": "Feature",
  "properties": {
    "gn:admin1_code":"21",
    "gn:admin2_code":"5004.0",
    "gn:asciiname":"Guin",
    "gn:country_code":"NO",
    "gn:dem":100,
    "gn:feature_class":"P",
    "gn:feature_code":"PPL",
    "gn:name":"Guin",
    "gn:population":0,
    "gn:timezone":"Europe/Oslo",
    "iso:country":"NO",
    "name:nor_x_preferred":[
        "Guin"
    ],
    "name:und_x_variant":[
        "Gudin"
    ],
    "wof:name":"Guin",
    "wof:placetype":"locality"
},
  "geometry": {"coordinates":[11.6984,64.14324999999999],"type":"Point"}
}