{
  "type": "Feature",
  "properties": {
    "gn:admin1_code":"7",
    "gn:admin2_code":"1241.0",
    "gn:asciiname":"Gjon",
    "gn:country_code":"NO",
    "gn:dem":331,
    "gn:feature_class":"P",
    "gn:feature_code":"PPL",
    "gn:name":"Gj\u00f8n",
    "gn:population":0,
    "gn:timezone":"Europe/Oslo",
    "iso:country":"NO",
    "wof:name":"Gjon",
    "wof:placetype":"locality"
},
  "geometry": {"coordinates":[5.86667,60.26667],"type":"Point"}
}