{
  "type": "Feature",
  "properties": {
    "gn:admin1_code":"7",
    "gn:admin2_code":"1256.0",
    "gn:asciiname":"Landsvik",
    "gn:country_code":"NO",
    "gn:dem":3,
    "gn:feature_class":"P",
    "gn:feature_code":"PPL",
    "gn:name":"Landsvik",
    "gn:population":0,
    "gn:timezone":"Europe/Oslo",
    "iso:country":"NO",
    "name:nor_x_preferred":[
        "Landsvik"
    ],
    "name:nor_x_variant":[
        "S\u00f8ra Landsvik"
    ],
    "wof:name":"Landsvik",
    "wof:placetype":"locality"
},
  "geometry": {"coordinates":[5.05354,60.60189],"type":"Point"}
}