{
  "type": "Feature",
  "properties": {
    "gn:admin1_code":"17.0",
    "gn:admin2_code":"805.0",
    "gn:asciiname":"Valler",
    "gn:country_code":"NO",
    "gn:dem":8,
    "gn:feature_class":"P",
    "gn:feature_code":"PPL",
    "gn:name":"Valler",
    "gn:population":0,
    "gn:timezone":"Europe/Oslo",
    "iso:country":"NO",
    "wof:name":"Valler",
    "wof:placetype":"locality"
},
  "geometry": {"coordinates":[9.68333,59.13333000000001],"type":"Point"}
}