{
  "type": "Feature",
  "properties": {
    "gn:admin1_code":"4",
    "gn:admin2_code":"618.0",
    "gn:asciiname":"Eikregardane",
    "gn:cc2":"NO",
    "gn:country_code":"NO",
    "gn:dem":750,
    "gn:feature_class":"P",
    "gn:feature_code":"PPL",
    "gn:name":"Eikregardane",
    "gn:population":0,
    "gn:timezone":"Europe/Oslo",
    "iso:country":"NO",
    "name:und_x_variant":[
        "Eikregardann",
        "Eikregardane"
    ],
    "wof:name":"Eikregardane",
    "wof:placetype":"locality"
},
  "geometry": {"coordinates":[8.73647,60.80624],"type":"Point"}
}