{
  "type": "Feature",
  "properties": {
    "gn:admin1_code":"8.0",
    "gn:admin2_code":"1576.0",
    "gn:asciiname":"Sagvagen",
    "gn:country_code":"NO",
    "gn:dem":20,
    "gn:feature_class":"P",
    "gn:feature_code":"PPL",
    "gn:name":"Sagv\u00e5gen",
    "gn:population":0,
    "gn:timezone":"Europe/Oslo",
    "iso:country":"NO",
    "name:nor_x_preferred":[
        "Sagv\u00e5gen"
    ],
    "wof:name":"Sagvagen",
    "wof:placetype":"locality"
},
  "geometry": {"coordinates":[8.32951,63.25326],"type":"Point"}
}