{
  "type": "Feature",
  "properties": {
    "gn:admin1_code":"21.0",
    "gn:admin2_code":"5053.0",
    "gn:asciiname":"Ulven",
    "gn:country_code":"NO",
    "gn:dem":96,
    "gn:feature_class":"P",
    "gn:feature_code":"PPL",
    "gn:name":"Ulven",
    "gn:population":0,
    "gn:timezone":"Europe/Oslo",
    "iso:country":"NO",
    "name:nor_x_preferred":[
        "Ulven"
    ],
    "wof:name":"Ulven",
    "wof:placetype":"locality"
},
  "geometry": {"coordinates":[11.13333,63.85],"type":"Point"}
}