{
  "type": "Feature",
  "properties": {
    "gn:admin1_code":"14",
    "gn:admin2_code":"1121.0",
    "gn:asciiname":"Eikjeland",
    "gn:cc2":"NO",
    "gn:country_code":"NO",
    "gn:dem":115,
    "gn:feature_class":"P",
    "gn:feature_code":"PPL",
    "gn:name":"Eikjeland",
    "gn:population":0,
    "gn:timezone":"Europe/Oslo",
    "iso:country":"NO",
    "name:und_x_variant":[
        "Eigeland",
        "Eikjeland"
    ],
    "wof:name":"Eikjeland",
    "wof:placetype":"locality"
},
  "geometry": {"coordinates":[5.81667,58.73333],"type":"Point"}
}