{
  "type": "Feature",
  "properties": {
    "gn:admin1_code":"1",
    "gn:admin2_code":"235.0",
    "gn:asciiname":"Nesti",
    "gn:cc2":"NO",
    "gn:country_code":"NO",
    "gn:dem":143,
    "gn:feature_class":"P",
    "gn:feature_code":"PPL",
    "gn:name":"Nesti",
    "gn:population":0,
    "gn:timezone":"Europe/Oslo",
    "iso:country":"NO",
    "name:und_x_variant":[
        "Nesten",
        "Nesti"
    ],
    "wof:name":"Nesti",
    "wof:placetype":"locality"
},
  "geometry": {"coordinates":[11.28333,60.11666999999999],"type":"Point"}
}