{
  "type": "Feature",
  "properties": {
    "gn:admin1_code":"15",
    "gn:admin2_code":"1424",
    "gn:asciiname":"Oyri",
    "gn:country_code":"NO",
    "gn:dem":60,
    "gn:feature_class":"P",
    "gn:feature_code":"PPLL",
    "gn:name":"\u00d8yri",
    "gn:population":0,
    "gn:timezone":"Europe/Oslo",
    "iso:country":"NO",
    "name:dan_x_preferred":[
        "Oyri"
    ],
    "name:deu_x_preferred":[
        "Oyri"
    ],
    "name:fao_x_preferred":[
        "Oyri"
    ],
    "name:hun_x_preferred":[
        "Oyri"
    ],
    "name:lit_x_preferred":[
        "Oyris"
    ],
    "name:nld_x_preferred":[
        "Oyri"
    ],
    "name:nor_x_preferred":[
        "\u00d8yri"
    ],
    "name:nor_x_variant":[
        "Oyri"
    ],
    "name:pol_x_preferred":[
        "Oyri"
    ],
    "name:ron_x_preferred":[
        "Oyri"
    ],
    "name:swe_x_preferred":[
        "Oyri"
    ],
    "wof:name":"Oyri",
    "wof:placetype":"neighbourhood"
},
  "geometry": {"coordinates":[7.79223,61.30897],"type":"Point"}
}