{
  "type": "Feature",
  "properties": {
    "gn:admin1_code":"9",
    "gn:admin2_code":"1852.0",
    "gn:asciiname":"Hov",
    "gn:country_code":"NO",
    "gn:dem":30,
    "gn:feature_class":"P",
    "gn:feature_code":"PPL",
    "gn:name":"Hov",
    "gn:population":0,
    "gn:timezone":"Europe/Oslo",
    "iso:country":"NO",
    "name:ceb_x_preferred":[
        "Hov"
    ],
    "name:dan_x_preferred":[
        "Hov"
    ],
    "name:deu_x_preferred":[
        "Hov"
    ],
    "name:fin_x_preferred":[
        "Hov"
    ],
    "name:fra_x_preferred":[
        "Hov"
    ],
    "name:nld_x_preferred":[
        "Hov"
    ],
    "name:nor_x_preferred":[
        "Hov"
    ],
    "name:swe_x_preferred":[
        "Hov"
    ],
    "wof:name":"Hov",
    "wof:placetype":"locality"
},
  "geometry": {"coordinates":[16.34934,68.55500000000001],"type":"Point"}
}