{
  "type": "Feature",
  "properties": {
    "gn:admin1_code":"6.0",
    "gn:admin2_code":"428.0",
    "gn:asciiname":"Volsaetra",
    "gn:country_code":"NO",
    "gn:dem":620,
    "gn:feature_class":"P",
    "gn:feature_code":"PPL",
    "gn:name":"Vols\u00e6tra",
    "gn:population":0,
    "gn:timezone":"Europe/Oslo",
    "iso:country":"NO",
    "name:nor_x_preferred":[
        "Vols\u00e6tra"
    ],
    "wof:name":"Volsaetra",
    "wof:placetype":"locality"
},
  "geometry": {"coordinates":[12.01209,61.43278000000001],"type":"Point"}
}