{
  "type": "Feature",
  "properties": {
    "gn:admin1_code":"14.0",
    "gn:admin2_code":"1114.0",
    "gn:asciiname":"Veen",
    "gn:country_code":"NO",
    "gn:dem":193,
    "gn:feature_class":"P",
    "gn:feature_code":"PPL",
    "gn:name":"Veen",
    "gn:population":0,
    "gn:timezone":"Europe/Oslo",
    "iso:country":"NO",
    "name:ceb_x_preferred":[
        "Veen"
    ],
    "name:deu_x_preferred":[
        "Veen"
    ],
    "name:fin_x_preferred":[
        "Veen"
    ],
    "name:nds_x_preferred":[
        "Veen"
    ],
    "name:nld_x_preferred":[
        "Veen"
    ],
    "wof:name":"Veen",
    "wof:placetype":"locality"
},
  "geometry": {"coordinates":[6.21667,58.75],"type":"Point"}
}