{
  "type": "Feature",
  "properties": {
    "gn:admin1_code":"9",
    "gn:admin2_code":"1824.0",
    "gn:asciiname":"Aufles",
    "gn:country_code":"NO",
    "gn:dem":80,
    "gn:feature_class":"P",
    "gn:feature_code":"PPL",
    "gn:name":"Aufles",
    "gn:population":0,
    "gn:timezone":"Europe/Oslo",
    "iso:country":"NO",
    "wof:name":"Aufles",
    "wof:placetype":"locality"
},
  "geometry": {"coordinates":[13.23333,65.78333000000001],"type":"Point"}
}