{
  "type": "Feature",
  "properties": {
    "gn:admin1_code":"17.0",
    "gn:admin2_code":"828.0",
    "gn:asciiname":"Sundbogrendi",
    "gn:country_code":"NO",
    "gn:dem":167,
    "gn:feature_class":"P",
    "gn:feature_code":"PPL",
    "gn:name":"Sundb\u00f8grendi",
    "gn:population":0,
    "gn:timezone":"Europe/Oslo",
    "iso:country":"NO",
    "name:nor_x_preferred":[
        "Sundb\u00f8grendi"
    ],
    "wof:name":"Sundbogrendi",
    "wof:placetype":"locality"
},
  "geometry": {"coordinates":[8.59519,59.55047],"type":"Point"}
}