{
  "type": "Feature",
  "properties": {
    "gn:admin1_code":"21.0",
    "gn:admin2_code":"5035.0",
    "gn:asciiname":"Gevingas",
    "gn:country_code":"NO",
    "gn:dem":160,
    "gn:feature_class":"P",
    "gn:feature_code":"PPL",
    "gn:name":"Geving\u00e5s",
    "gn:population":0,
    "gn:timezone":"Europe/Oslo",
    "iso:country":"NO",
    "name:nor_x_preferred":[
        "Geving\u00e5s"
    ],
    "name:nor_x_variant":[
        "Gjeving\u00e5sen"
    ],
    "wof:name":"Gevingas",
    "wof:placetype":"locality"
},
  "geometry": {"coordinates":[10.88503,63.44142],"type":"Point"}
}