{
  "type": "Feature",
  "properties": {
    "gn:admin1_code":"9.0",
    "gn:admin2_code":"1812.0",
    "gn:asciiname":"Sande",
    "gn:cc2":"NO",
    "gn:country_code":"NO",
    "gn:dem":20,
    "gn:feature_class":"P",
    "gn:feature_code":"PPL",
    "gn:name":"Sande",
    "gn:population":0,
    "gn:timezone":"Europe/Oslo",
    "iso:country":"NO",
    "name:und_x_variant":[
        "Sonde",
        "Sande"
    ],
    "wof:name":"Sande",
    "wof:placetype":"locality"
},
  "geometry": {"coordinates":[12.13333,65.28333000000001],"type":"Point"}
}