{
  "type": "Feature",
  "properties": {
    "gn:admin1_code":"9",
    "gn:admin2_code":"1833.0",
    "gn:asciiname":"Grubben",
    "gn:country_code":"NO",
    "gn:dem":40,
    "gn:feature_class":"P",
    "gn:feature_code":"PPL",
    "gn:name":"Grubben",
    "gn:population":0,
    "gn:timezone":"Europe/Oslo",
    "iso:country":"NO",
    "wof:name":"Grubben",
    "wof:placetype":"locality"
},
  "geometry": {"coordinates":[14.18333,66.31667],"type":"Point"}
}