{
  "type": "Feature",
  "properties": {
    "gn:admin1_code":"9",
    "gn:admin2_code":"1860.0",
    "gn:asciiname":"Hannberget",
    "gn:cc2":"NO",
    "gn:country_code":"NO",
    "gn:dem":307,
    "gn:feature_class":"P",
    "gn:feature_code":"PPL",
    "gn:name":"Hannberget",
    "gn:population":0,
    "gn:timezone":"Europe/Oslo",
    "iso:country":"NO",
    "name:und_x_variant":[
        "Hanberget",
        "Hannberget"
    ],
    "wof:name":"Hannberget",
    "wof:placetype":"locality"
},
  "geometry": {"coordinates":[13.81667,68.23333000000001],"type":"Point"}
}