{
  "type": "Feature",
  "properties": {
    "gn:admin1_code":"6.0",
    "gn:admin2_code":"430.0",
    "gn:asciiname":"Nordre Koppangskjolen",
    "gn:country_code":"NO",
    "gn:dem":787,
    "gn:feature_class":"P",
    "gn:feature_code":"PPL",
    "gn:name":"Nordre Koppangskj\u00f8len",
    "gn:population":0,
    "gn:timezone":"Europe/Oslo",
    "iso:country":"NO",
    "name:nor_x_preferred":[
        "Nordre Koppangskj\u00f8len"
    ],
    "wof:name":"Nordre Koppangskjolen",
    "wof:placetype":"locality"
},
  "geometry": {"coordinates":[10.95937,61.72541],"type":"Point"}
}