{
  "type": "Feature",
  "properties": {
    "gn:admin1_code":"9",
    "gn:admin2_code":"1849.0",
    "gn:asciiname":"Hamsund",
    "gn:country_code":"NO",
    "gn:dem":30,
    "gn:feature_class":"P",
    "gn:feature_code":"PPL",
    "gn:name":"Hamsund",
    "gn:population":0,
    "gn:timezone":"Europe/Oslo",
    "iso:country":"NO",
    "wof:name":"Hamsund",
    "wof:placetype":"locality"
},
  "geometry": {"coordinates":[15.51958,68.10281999999999],"type":"Point"}
}