{
  "type": "Feature",
  "properties": {
    "gn:admin1_code":"18",
    "gn:admin2_code":"1903.0",
    "gn:asciiname":"Aspaker",
    "gn:country_code":"NO",
    "gn:dem":1,
    "gn:feature_class":"P",
    "gn:feature_code":"PPL",
    "gn:name":"Aspaker",
    "gn:population":0,
    "gn:timezone":"Europe/Oslo",
    "iso:country":"NO",
    "wof:name":"Aspaker",
    "wof:placetype":"locality"
},
  "geometry": {"coordinates":[16.53556,68.71889],"type":"Point"}
}