{
  "type": "Feature",
  "properties": {
    "gn:admin1_code":"21.0",
    "gn:admin2_code":"5016.0",
    "gn:asciiname":"Selnes",
    "gn:country_code":"NO",
    "gn:dem":1,
    "gn:feature_class":"P",
    "gn:feature_code":"PPL",
    "gn:name":"Selnes",
    "gn:population":0,
    "gn:timezone":"Europe/Oslo",
    "iso:country":"NO",
    "name:ceb_x_preferred":[
        "Selnes"
    ],
    "name:nor_x_preferred":[
        "Selnes"
    ],
    "name:swe_x_preferred":[
        "Selnes"
    ],
    "wof:name":"Selnes",
    "wof:placetype":"locality"
},
  "geometry": {"coordinates":[9.81667,63.55],"type":"Point"}
}