{
  "type": "Feature",
  "properties": {
    "gn:admin1_code":"5.0",
    "gn:admin2_code":"2019.0",
    "gn:asciiname":"Indre Baklia",
    "gn:country_code":"NO",
    "gn:dem":-9999,
    "gn:feature_class":"P",
    "gn:feature_code":"PPL",
    "gn:name":"Indre Baklia",
    "gn:population":0,
    "gn:timezone":"Europe/Oslo",
    "iso:country":"NO",
    "wof:name":"Indre Baklia",
    "wof:placetype":"locality"
},
  "geometry": {"coordinates":[25.83333,70.97499999999999],"type":"Point"}
}