{
  "type": "Feature",
  "properties": {
    "gn:admin1_code":"8",
    "gn:admin2_code":"1554.0",
    "gn:asciiname":"Leite",
    "gn:country_code":"NO",
    "gn:dem":40,
    "gn:feature_class":"P",
    "gn:feature_code":"PPL",
    "gn:name":"Leite",
    "gn:population":0,
    "gn:timezone":"Europe/Oslo",
    "iso:country":"NO",
    "wof:name":"Leite",
    "wof:placetype":"locality"
},
  "geometry": {"coordinates":[7.46667,63.01667],"type":"Point"}
}