{
  "type": "Feature",
  "properties": {
    "gn:admin1_code":"18",
    "gn:admin2_code":"1933.0",
    "gn:asciiname":"Nordfjordbotn",
    "gn:country_code":"NO",
    "gn:dem":35,
    "gn:feature_class":"P",
    "gn:feature_code":"PPL",
    "gn:name":"Nordfjordbotn",
    "gn:population":0,
    "gn:timezone":"Europe/Oslo",
    "iso:country":"NO",
    "wof:name":"Nordfjordbotn",
    "wof:placetype":"locality"
},
  "geometry": {"coordinates":[19.00564,69.28723000000001],"type":"Point"}
}