{
  "type": "Feature",
  "properties": {
    "gn:admin1_code":"15",
    "gn:admin2_code":"1443.0",
    "gn:asciiname":"Hjelmeland",
    "gn:cc2":"NO",
    "gn:country_code":"NO",
    "gn:dem":174,
    "gn:feature_class":"P",
    "gn:feature_code":"PPL",
    "gn:name":"Hjelmeland",
    "gn:population":0,
    "gn:timezone":"Europe/Oslo",
    "iso:country":"NO",
    "name:und_x_variant":[
        "Hj\u00e6lmeland",
        "Hjelmeland"
    ],
    "wof:name":"Hjelmeland",
    "wof:placetype":"locality"
},
  "geometry": {"coordinates":[5.88333,61.95],"type":"Point"}
}