{
  "type": "Feature",
  "properties": {
    "gn:admin1_code":"5.0",
    "gn:admin2_code":"2018.0",
    "gn:asciiname":"Skavika",
    "gn:country_code":"NO",
    "gn:dem":1,
    "gn:feature_class":"P",
    "gn:feature_code":"PPL",
    "gn:name":"Skavika",
    "gn:population":0,
    "gn:timezone":"Europe/Oslo",
    "iso:country":"NO",
    "name:nor_x_preferred":[
        "Skavika"
    ],
    "wof:name":"Skavika",
    "wof:placetype":"locality"
},
  "geometry": {"coordinates":[24.56933,70.79065],"type":"Point"}
}