{
  "type": "Feature",
  "properties": {
    "gn:admin1_code":"2.0",
    "gn:admin2_code":"928.0",
    "gn:asciiname":"Vaeting",
    "gn:country_code":"NO",
    "gn:dem":244,
    "gn:feature_class":"P",
    "gn:feature_code":"PPL",
    "gn:name":"V\u00e6ting",
    "gn:population":0,
    "gn:timezone":"Europe/Oslo",
    "iso:country":"NO",
    "name:und_x_variant":[
        "V\u00e6ting"
    ],
    "wof:name":"Vaeting",
    "wof:placetype":"locality"
},
  "geometry": {"coordinates":[8.26667,58.46666999999999],"type":"Point"}
}