{
  "type": "Feature",
  "properties": {
    "gn:admin1_code":"15",
    "gn:admin2_code":"1433.0",
    "gn:asciiname":"Kleiva",
    "gn:cc2":"NO",
    "gn:country_code":"NO",
    "gn:dem":120,
    "gn:feature_class":"P",
    "gn:feature_code":"PPL",
    "gn:name":"Kleiva",
    "gn:population":0,
    "gn:timezone":"Europe/Oslo",
    "iso:country":"NO",
    "name:und_x_variant":[
        "Kleivane",
        "Kleiva"
    ],
    "wof:name":"Kleiva",
    "wof:placetype":"locality"
},
  "geometry": {"coordinates":[5.85,61.58333],"type":"Point"}
}