{
  "type": "Feature",
  "properties": {
    "gn:admin1_code":"15",
    "gn:admin2_code":"1433.0",
    "gn:asciiname":"Areklett",
    "gn:country_code":"NO",
    "gn:dem":1,
    "gn:feature_class":"P",
    "gn:feature_code":"PPL",
    "gn:name":"\u00c5reklett",
    "gn:population":0,
    "gn:timezone":"Europe/Oslo",
    "iso:country":"NO",
    "wof:name":"Areklett",
    "wof:placetype":"locality"
},
  "geometry": {"coordinates":[5.63333,61.48333],"type":"Point"}
}