{
  "type": "Feature",
  "properties": {
    "gn:admin1_code":"14",
    "gn:admin2_code":"1146.0",
    "gn:asciiname":"Espevik",
    "gn:country_code":"NO",
    "gn:dem":35,
    "gn:feature_class":"P",
    "gn:feature_code":"PPL",
    "gn:name":"Espevik",
    "gn:population":0,
    "gn:timezone":"Europe/Oslo",
    "iso:country":"NO",
    "wof:name":"Espevik",
    "wof:placetype":"locality"
},
  "geometry": {"coordinates":[5.67973,59.33742],"type":"Point"}
}