{
  "type": "Feature",
  "properties": {
    "gn:admin1_code":"5.0",
    "gn:admin2_code":"2012.0",
    "gn:asciiname":"Indre Vieluft",
    "gn:cc2":"NO",
    "gn:country_code":"NO",
    "gn:dem":180,
    "gn:feature_class":"P",
    "gn:feature_code":"PPL",
    "gn:name":"Indre Vieluft",
    "gn:population":0,
    "gn:timezone":"Europe/Oslo",
    "iso:country":"NO",
    "name:und_x_variant":[
        "Vieluft",
        "Indre Vieluft"
    ],
    "wof:name":"Indre Vieluft",
    "wof:placetype":"locality"
},
  "geometry": {"coordinates":[23.53333,70.28333000000001],"type":"Point"}
}