{
  "type": "Feature",
  "properties": {
    "gn:admin1_code":"1.0",
    "gn:admin2_code":"227.0",
    "gn:asciiname":"Vangen",
    "gn:country_code":"NO",
    "gn:dem":159,
    "gn:feature_class":"P",
    "gn:feature_code":"PPL",
    "gn:name":"Vangen",
    "gn:population":0,
    "gn:timezone":"Europe/Oslo",
    "iso:country":"NO",
    "name:nor_x_preferred":[
        "Vangen"
    ],
    "wof:name":"Vangen",
    "wof:placetype":"locality"
},
  "geometry": {"coordinates":[11.11735,59.94958000000001],"type":"Point"}
}