{
  "type": "Feature",
  "properties": {
    "gn:gn_country":"NO",
    "gn:gn_fcode":"PPL",
    "gn:gn_pop":245,
    "gn:population":245,
    "iso:country":"NO",
    "name:dut_x_preferred":[
        "Kvithammer"
    ],
    "name:eng_x_preferred":[
        "Kvithammer"
    ],
    "name:fre_x_preferred":[
        "Kvithammer"
    ],
    "name:jav_x_preferred":[
        "Kvithammer"
    ],
    "name:may_x_preferred":[
        "Kvithammer"
    ],
    "name:nno_x_preferred":[
        "Kvithammar"
    ],
    "name:nob_x_preferred":[
        "Kvithammer"
    ],
    "name:rum_x_preferred":[
        "Kvithammer"
    ],
    "name:unk_x_variant":[
        "Kvithammer"
    ],
    "qs_pg:aaroncc":"NO",
    "qs_pg:gn_country":"NO",
    "qs_pg:gn_fcode":"PPL",
    "qs_pg:gn_pop":245,
    "qs_pg:name":"Vikhamar",
    "qs_pg:name_adm0":"Norge",
    "qs_pg:name_adm1":"S\u00f8r-Tr\u00f8ndelag Fylke",
    "qs_pg:photos_9k":1,
    "qs_pg:photos_9r":1,
    "qs_pg:photos_all":1,
    "qs_pg:photos_sr":0,
    "qs_pg:pop_sr":2,
    "qs_pg:qs_pg_placetype":"locality",
    "qs_pg:qs_pg_placetype_gp":"Town",
    "qs_pg:woe_adm0":23424910,
    "woe:adm0_id":23424910,
    "woe:name_adm0":"Norge",
    "woe:name_adm1":"S\u00f8r-Tr\u00f8ndelag Fylke",
    "woe:placetype":"Town",
    "wof:name":"Vikhamar",
    "wof:placetype":"locality",
    "wof:population":245
},
  "geometry": {"coordinates":[10.88333,63.48333],"type":"Point"}
}