{
  "type": "Feature",
  "properties": {
    "gn:admin1_code":"18",
    "gn:admin2_code":"1936.0",
    "gn:asciiname":"Nordskard",
    "gn:cc2":"NO",
    "gn:country_code":"NO",
    "gn:dem":-9999,
    "gn:feature_class":"P",
    "gn:feature_code":"PPL",
    "gn:name":"Nordskard",
    "gn:population":0,
    "gn:timezone":"Europe/Oslo",
    "iso:country":"NO",
    "name:und_x_variant":[
        "Nordskar",
        "Nordskardet",
        "Nordskaret",
        "Nordskard"
    ],
    "wof:name":"Nordskard",
    "wof:placetype":"locality"
},
  "geometry": {"coordinates":[19.23333,70.21666999999999],"type":"Point"}
}