{
  "type": "Feature",
  "properties": {
    "gn:admin1_code":"15.0",
    "gn:admin2_code":"1411.0",
    "gn:asciiname":"Oppdal",
    "gn:country_code":"NO",
    "gn:dem":-9999,
    "gn:feature_class":"P",
    "gn:feature_code":"PPL",
    "gn:name":"Oppdal",
    "gn:population":0,
    "gn:timezone":"Europe/Oslo",
    "iso:country":"NO",
    "name:ara_x_preferred":[
        "\u0623\u0648\u0628\u062f\u0627\u0644"
    ],
    "name:bpy_x_preferred":[
        "\u0993\u09aa\u09cd\u09aa\u09a1\u09be\u09b2"
    ],
    "name:bul_x_preferred":[
        "\u041e\u043f\u0434\u0430\u043b"
    ],
    "name:cat_x_preferred":[
        "Oppdal"
    ],
    "name:ceb_x_preferred":[
        "Oppdal"
    ],
    "name:dan_x_preferred":[
        "Oppdal"
    ],
    "name:deu_x_preferred":[
        "Oppdal"
    ],
    "name:epo_x_preferred":[
        "Oppdal"
    ],
    "name:est_x_preferred":[
        "Oppdali vald"
    ],
    "name:eus_x_preferred":[
        "Oppdal"
    ],
    "name:fin_x_preferred":[
        "Oppdal"
    ],
    "name:fra_x_preferred":[
        "Oppdal"
    ],
    "name:hye_x_preferred":[
        "\u0555\u057a\u0564\u0561\u056c\u056b \u0570\u0561\u0574\u0561\u0575\u0576\u0584"
    ],
    "name:ita_x_preferred":[
        "Oppdal"
    ],
    "name:lat_x_preferred":[
        "Oppdal"
    ],
    "name:lim_x_preferred":[
        "Oppdal"
    ],
    "name:msa_x_preferred":[
        "Oppdal"
    ],
    "name:nds_x_preferred":[
        "Kommun Oppdal"
    ],
    "name:nld_x_preferred":[
        "Oppdal"
    ],
    "name:nno_x_preferred":[
        "Oppdal kommune"
    ],
    "name:nor_x_preferred":[
        "Oppdal"
    ],
    "name:pol_x_preferred":[
        "Oppdal"
    ],
    "name:por_x_preferred":[
        "Oppdal"
    ],
    "name:ron_x_preferred":[
        "Oppdal"
    ],
    "name:rus_x_preferred":[
        "\u041e\u043f\u043f\u0434\u0430\u043b"
    ],
    "name:slv_x_preferred":[
        "Oppdal"
    ],
    "name:sme_x_preferred":[
        "Oppdal"
    ],
    "name:spa_x_preferred":[
        "Oppdal"
    ],
    "name:sqi_x_preferred":[
        "Oppdal"
    ],
    "name:swe_x_preferred":[
        "Oppdals kommun"
    ],
    "name:vie_x_preferred":[
        "Oppdal"
    ],
    "name:war_x_preferred":[
        "Oppdal"
    ],
    "name:zho_x_preferred":[
        "\u5967\u666e\u9054\u723e"
    ],
    "wof:name":"Oppdal",
    "wof:placetype":"locality"
},
  "geometry": {"coordinates":[5.23333,60.96666999999999],"type":"Point"}
}