{
  "type": "Feature",
  "properties": {
    "gn:admin1_code":"15.0",
    "gn:admin2_code":"1411.0",
    "gn:asciiname":"Oppdal",
    "gn:country_code":"NO",
    "gn:dem":-9999,
    "gn:feature_class":"P",
    "gn:feature_code":"PPL",
    "gn:name":"Oppdal",
    "gn:population":0,
    "gn:timezone":"Europe/Oslo",
    "iso:country":"NO",
    "wof:name":"Oppdal",
    "wof:placetype":"locality"
},
  "geometry": {"coordinates":[5.23333,60.96666999999999],"type":"Point"}
}