{
  "type": "Feature",
  "properties": {
    "gn:admin1_code":"18",
    "gn:admin2_code":"1925.0",
    "gn:asciiname":"Djupvag",
    "gn:cc2":"NO",
    "gn:country_code":"NO",
    "gn:dem":51,
    "gn:feature_class":"P",
    "gn:feature_code":"PPL",
    "gn:name":"Djupv\u00e5g",
    "gn:population":0,
    "gn:timezone":"Europe/Oslo",
    "iso:country":"NO",
    "name:und_x_variant":[
        "Djupv\u00e5g",
        "Djupv\u00e5gen"
    ],
    "wof:name":"Djupvag",
    "wof:placetype":"locality"
},
  "geometry": {"coordinates":[18.11493,69.16991],"type":"Point"}
}