{
  "type": "Feature",
  "properties": {
    "gn:admin1_code":"5.0",
    "gn:admin2_code":"2003.0",
    "gn:asciiname":"Vaeret",
    "gn:country_code":"NO",
    "gn:dem":-9999,
    "gn:feature_class":"P",
    "gn:feature_code":"PPL",
    "gn:name":"V\u00e6ret",
    "gn:population":0,
    "gn:timezone":"Europe/Oslo",
    "iso:country":"NO",
    "name:nor_x_preferred":[
        "V\u00e6ret"
    ],
    "wof:name":"Vaeret",
    "wof:placetype":"locality"
},
  "geometry": {"coordinates":[30.00304,70.06963],"type":"Point"}
}