{
  "type": "Feature",
  "properties": {
    "gn:admin1_code":"20",
    "gn:admin2_code":"712.0",
    "gn:asciiname":"Amli",
    "gn:cc2":"NO",
    "gn:country_code":"NO",
    "gn:dem":28,
    "gn:feature_class":"P",
    "gn:feature_code":"PPL",
    "gn:name":"\u00c5mli",
    "gn:population":0,
    "gn:timezone":"Europe/Oslo",
    "iso:country":"NO",
    "name:ceb_x_preferred":[
        "Amli"
    ],
    "name:nld_x_preferred":[
        "Amli"
    ],
    "name:und_x_variant":[
        "Aamli",
        "\u00c5mli"
    ],
    "wof:name":"Amli",
    "wof:placetype":"locality"
},
  "geometry": {"coordinates":[9.85,58.98333],"type":"Point"}
}