{
  "type": "Feature",
  "properties": {
    "gn:admin1_code":"4",
    "gn:admin2_code":"604.0",
    "gn:asciiname":"Gravningsgrend",
    "gn:country_code":"NO",
    "gn:dem":319,
    "gn:feature_class":"P",
    "gn:feature_code":"PPL",
    "gn:name":"Gravningsgrend",
    "gn:population":0,
    "gn:timezone":"Europe/Oslo",
    "iso:country":"NO",
    "name:und_x_variant":[
        "Gravningsgrenda",
        "Gravningsgrend"
    ],
    "wof:name":"Gravningsgrend",
    "wof:placetype":"locality"
},
  "geometry": {"coordinates":[9.57725,59.71705],"type":"Point"}
}