{
  "type": "Feature",
  "properties": {
    "gn:admin1_code":"6.0",
    "gn:admin2_code":"417.0",
    "gn:asciiname":"Strandlykkja",
    "gn:cc2":"NO",
    "gn:country_code":"NO",
    "gn:dem":260,
    "gn:feature_class":"P",
    "gn:feature_code":"PPL",
    "gn:name":"Strandlykkja",
    "gn:population":0,
    "gn:timezone":"Europe/Oslo",
    "iso:country":"NO",
    "name:und_x_variant":[
        "Strandl\u00f8kka",
        "Strandlykkja"
    ],
    "wof:name":"Strandlykkja",
    "wof:placetype":"locality"
},
  "geometry": {"coordinates":[11.24437,60.51167],"type":"Point"}
}