{
  "type": "Feature",
  "properties": {
    "gn:admin1_code":"2",
    "gn:admin2_code":"912.0",
    "gn:asciiname":"Myre",
    "gn:country_code":"NO",
    "gn:dem":171,
    "gn:feature_class":"P",
    "gn:feature_code":"PPL",
    "gn:name":"Myre",
    "gn:population":0,
    "gn:timezone":"Europe/Oslo",
    "iso:country":"NO",
    "name:ceb_x_preferred":[
        "Myre"
    ],
    "name:fra_x_preferred":[
        "Myre"
    ],
    "name:nld_x_preferred":[
        "Myre"
    ],
    "name:spa_x_preferred":[
        "Myre"
    ],
    "wof:name":"Myre",
    "wof:placetype":"locality"
},
  "geometry": {"coordinates":[8.85,58.73333],"type":"Point"}
}