{
  "type": "Feature",
  "properties": {
    "gn:admin1_code":"15.0",
    "gn:admin2_code":"1413.0",
    "gn:asciiname":"Storaker",
    "gn:cc2":"NO",
    "gn:country_code":"NO",
    "gn:dem":-9999,
    "gn:feature_class":"P",
    "gn:feature_code":"PPL",
    "gn:name":"Storaker",
    "gn:population":0,
    "gn:timezone":"Europe/Oslo",
    "iso:country":"NO",
    "name:und_x_variant":[
        "Storakersund",
        "Storaker"
    ],
    "wof:name":"Storaker",
    "wof:placetype":"locality"
},
  "geometry": {"coordinates":[5.08333,61.18333000000001],"type":"Point"}
}