{
  "type": "Feature",
  "properties": {
    "gn:admin1_code":"18",
    "gn:admin2_code":"1925.0",
    "gn:asciiname":"Steinberg",
    "gn:country_code":"NO",
    "gn:dem":109,
    "gn:feature_class":"P",
    "gn:feature_code":"PPL",
    "gn:name":"Steinberg",
    "gn:population":0,
    "gn:timezone":"Europe/Oslo",
    "iso:country":"NO",
    "wof:name":"Steinberg",
    "wof:placetype":"locality"
},
  "geometry": {"coordinates":[18.07,69.20028000000001],"type":"Point"}
}