{
  "type": "Feature",
  "properties": {
    "gn:admin1_code":"1",
    "gn:admin2_code":"237",
    "gn:asciiname":"Finnbraten",
    "gn:country_code":"NO",
    "gn:dem":213,
    "gn:feature_class":"P",
    "gn:feature_code":"PPL",
    "gn:name":"Finnbr\u00e5ten",
    "gn:population":0,
    "gn:timezone":"Europe/Oslo",
    "iso:country":"NO",
    "name:ceb_x_preferred":[
        "Finnbr\u00e5ten"
    ],
    "name:jav_x_preferred":[
        "Finnbr\u00e5ten"
    ],
    "name:msa_x_preferred":[
        "Finnbr\u00e5ten"
    ],
    "name:nld_x_preferred":[
        "Finnbr\u00e5tan"
    ],
    "name:nno_x_preferred":[
        "Finnbr\u00e5tan"
    ],
    "name:nor_x_preferred":[
        "Finnbr\u00e5ten"
    ],
    "name:nor_x_variant":[
        "Finnbr\u00e5tengrenda",
        "Finnbr\u00e5tan"
    ],
    "name:ron_x_preferred":[
        "Finnbr\u00e5tan"
    ],
    "name:spa_x_preferred":[
        "Finnbr\u00e5tan"
    ],
    "name:swe_x_preferred":[
        "Finnbr\u00e5tan"
    ],
    "wof:name":"Finnbraten",
    "wof:placetype":"locality"
},
  "geometry": {"coordinates":[11.30402,60.33368000000001],"type":"Point"}
}