{
  "type": "Feature",
  "properties": {
    "gn:admin1_code":"9",
    "gn:admin2_code":"1813.0",
    "gn:asciiname":"Barstad",
    "gn:country_code":"NO",
    "gn:dem":200,
    "gn:feature_class":"P",
    "gn:feature_code":"PPL",
    "gn:name":"Barstad",
    "gn:population":0,
    "gn:timezone":"Europe/Oslo",
    "iso:country":"NO",
    "wof:name":"Barstad",
    "wof:placetype":"locality"
},
  "geometry": {"coordinates":[12.75,65.26666999999999],"type":"Point"}
}