{
  "type": "Feature",
  "properties": {
    "iso:country":"NO",
    "name:nor_x_preferred":[
        "Haukas",
        "Michael Hauk\u00e5s"
    ],
    "qs:gn_adm0_cc":"NO",
    "qs:gn_local":3160233,
    "qs:gn_nam_loc":"Breidstein, Bergen, Hordaland Fylke, NO",
    "qs:gn_namadm1":"07",
    "qs:local_max":172,
    "qs:local_sum":172,
    "qs:localhoods":1,
    "qs:name":"Haukas",
    "qs:name_adm0":"Norge",
    "qs:name_adm1":"Hordaland Fylke",
    "qs:name_adm2":"Bergen Kommune",
    "qs:name_local":"Breidstein",
    "qs:photo_max":55,
    "qs:photo_sum":172,
    "qs:placetype":"Suburb",
    "qs:quad_count":19,
    "qs:woe_adm0":23424910,
    "qs:woe_adm1":2346390,
    "qs:woe_adm2":12592658,
    "qs:woe_lau":0,
    "qs:woe_local":857514,
    "qs:woe_ver":"7.10.0",
    "wof:lang":[
        "nor"
    ],
    "wof:name":"Haukas",
    "wof:placetype":"neighbourhood"
},
  "geometry": {"coordinates":[5.382087,60.487506],"type":"Point"}
}