{
  "type": "Feature",
  "properties": {
    "gn:admin1_code":"5.0",
    "gn:admin2_code":"2030.0",
    "gn:asciiname":"Brattli",
    "gn:cc2":"NO",
    "gn:country_code":"NO",
    "gn:dem":21,
    "gn:feature_class":"P",
    "gn:feature_code":"PPL",
    "gn:name":"Brattli",
    "gn:population":0,
    "gn:timezone":"Europe/Oslo",
    "iso:country":"NO",
    "name:und_x_variant":[
        "Bratli",
        "Brattli"
    ],
    "wof:name":"Brattli",
    "wof:placetype":"locality"
},
  "geometry": {"coordinates":[30.07951,69.56461],"type":"Point"}
}