{
  "type": "Feature",
  "properties": {
    "gn:admin1_code":"21.0",
    "gn:admin2_code":"5025.0",
    "gn:asciiname":"Nordvika",
    "gn:country_code":"NO",
    "gn:dem":670,
    "gn:feature_class":"P",
    "gn:feature_code":"PPL",
    "gn:name":"Nordvika",
    "gn:population":0,
    "gn:timezone":"Europe/Oslo",
    "iso:country":"NO",
    "name:nor_x_preferred":[
        "Nordvika"
    ],
    "wof:name":"Nordvika",
    "wof:placetype":"locality"
},
  "geometry": {"coordinates":[11.9387,62.42403],"type":"Point"}
}