{
  "type": "Feature",
  "properties": {
    "gn:admin1_code":"21.0",
    "gn:admin2_code":"5049.0",
    "gn:asciiname":"Oppland",
    "gn:cc2":"NO",
    "gn:country_code":"NO",
    "gn:dem":90,
    "gn:feature_class":"P",
    "gn:feature_code":"PPL",
    "gn:name":"Oppland",
    "gn:population":0,
    "gn:timezone":"Europe/Oslo",
    "iso:country":"NO",
    "name:rus_x_preferred":[
        "\u041e\u043f\u043b\u0430\u043d\u043d"
    ],
    "name:und_x_variant":[
        "Opland",
        "Oppland"
    ],
    "wof:name":"Oppland",
    "wof:placetype":"locality"
},
  "geometry": {"coordinates":[10.86492,64.33774],"type":"Point"}
}