{
  "type": "Feature",
  "properties": {
    "gn:admin1_code":"2",
    "gn:admin2_code":"901",
    "gn:asciiname":"Tangen",
    "gn:country_code":"NO",
    "gn:dem":8,
    "gn:feature_class":"P",
    "gn:feature_code":"PPLL",
    "gn:name":"Tangen",
    "gn:population":0,
    "gn:timezone":"Europe/Oslo",
    "iso:country":"NO",
    "name:ceb_x_preferred":[
        "Tangen"
    ],
    "name:jav_x_preferred":[
        "Tangen"
    ],
    "name:nld_x_preferred":[
        "Tangen"
    ],
    "name:nor_x_preferred":[
        "Tangen"
    ],
    "name:ron_x_preferred":[
        "Tangen"
    ],
    "wof:name":"Tangen",
    "wof:placetype":"neighbourhood"
},
  "geometry": {"coordinates":[9.2392,58.71694],"type":"Point"}
}