{
  "type": "Feature",
  "properties": {
    "gn:admin1_code":"19.0",
    "gn:admin2_code":"1029.0",
    "gn:asciiname":"Haland",
    "gn:country_code":"NO",
    "gn:dem":270,
    "gn:feature_class":"P",
    "gn:feature_code":"PPL",
    "gn:name":"H\u00e5land",
    "gn:population":0,
    "gn:timezone":"Europe/Oslo",
    "iso:country":"NO",
    "name:nor_x_preferred":[
        "H\u00e5land"
    ],
    "wof:name":"Haland",
    "wof:placetype":"locality"
},
  "geometry": {"coordinates":[7.39809,58.18702],"type":"Point"}
}