{
  "type": "Feature",
  "properties": {
    "gn:admin1_code":"21.0",
    "gn:admin2_code":"5015.0",
    "gn:asciiname":"Nordlandet",
    "gn:country_code":"NO",
    "gn:dem":7,
    "gn:feature_class":"P",
    "gn:feature_code":"PPL",
    "gn:name":"Nordlandet",
    "gn:population":0,
    "gn:timezone":"Europe/Oslo",
    "iso:country":"NO",
    "name:ceb_x_preferred":[
        "Nordlandet"
    ],
    "name:nor_x_preferred":[
        "Nordlandet"
    ],
    "wof:name":"Nordlandet",
    "wof:placetype":"locality"
},
  "geometry": {"coordinates":[9.42477,63.67378000000001],"type":"Point"}
}