{
  "type": "Feature",
  "properties": {
    "gn:admin1_code":"2",
    "gn:admin2_code":"901.0",
    "gn:asciiname":"Bossvika",
    "gn:country_code":"NO",
    "gn:dem":30,
    "gn:feature_class":"P",
    "gn:feature_code":"PPL",
    "gn:name":"Bossvika",
    "gn:population":0,
    "gn:timezone":"Europe/Oslo",
    "iso:country":"NO",
    "name:ceb_x_preferred":[
        "Bossvika"
    ],
    "name:jav_x_preferred":[
        "Bossvika"
    ],
    "name:msa_x_preferred":[
        "Bossvika"
    ],
    "name:nor_x_preferred":[
        "Bossvika"
    ],
    "name:nor_x_variant":[
        "Bossvik"
    ],
    "wof:name":"Bossvika",
    "wof:placetype":"locality"
},
  "geometry": {"coordinates":[9.10463,58.71847],"type":"Point"}
}