{
  "type": "Feature",
  "properties": {
    "gn:admin1_code":"9.0",
    "gn:admin2_code":"1822.0",
    "gn:asciiname":"Oyjorden",
    "gn:country_code":"NO",
    "gn:dem":-9999,
    "gn:feature_class":"P",
    "gn:feature_code":"PPL",
    "gn:name":"\u00d8yjorden",
    "gn:population":0,
    "gn:timezone":"Europe/Oslo",
    "iso:country":"NO",
    "name:nor_x_preferred":[
        "\u00d8yjorden"
    ],
    "wof:name":"Oyjorden",
    "wof:placetype":"locality"
},
  "geometry": {"coordinates":[12.76036,66.06308],"type":"Point"}
}