{
  "type": "Feature",
  "properties": {
    "gn:admin1_code":"21",
    "gn:admin2_code":"5019.0",
    "gn:asciiname":"Hongsand",
    "gn:country_code":"NO",
    "gn:dem":4,
    "gn:feature_class":"P",
    "gn:feature_code":"PPL",
    "gn:name":"Hongsand",
    "gn:population":0,
    "gn:timezone":"Europe/Oslo",
    "iso:country":"NO",
    "wof:name":"Hongsand",
    "wof:placetype":"locality"
},
  "geometry": {"coordinates":[10.15895,64.14478000000001],"type":"Point"}
}