{
  "type": "Feature",
  "properties": {
    "gn:admin1_code":"4",
    "gn:admin2_code":"612.0",
    "gn:asciiname":"Gjesval",
    "gn:country_code":"NO",
    "gn:dem":134,
    "gn:feature_class":"P",
    "gn:feature_code":"PPL",
    "gn:name":"Gjesval",
    "gn:population":0,
    "gn:timezone":"Europe/Oslo",
    "iso:country":"NO",
    "wof:name":"Gjesval",
    "wof:placetype":"locality"
},
  "geometry": {"coordinates":[10.28333,60.06667],"type":"Point"}
}