{
  "type": "Feature",
  "properties": {
    "gn:admin1_code":"19.0",
    "gn:admin2_code":"1034.0",
    "gn:asciiname":"Nedre Lauen",
    "gn:country_code":"NO",
    "gn:dem":284,
    "gn:feature_class":"P",
    "gn:feature_code":"PPL",
    "gn:name":"Nedre Lauen",
    "gn:population":0,
    "gn:timezone":"Europe/Oslo",
    "iso:country":"NO",
    "name:nor_x_preferred":[
        "Nedre Lauen"
    ],
    "wof:name":"Nedre Lauen",
    "wof:placetype":"locality"
},
  "geometry": {"coordinates":[7.18312,58.39917],"type":"Point"}
}