{
  "type": "Feature",
  "properties": {
    "gn:admin1_code":"7.0",
    "gn:admin2_code":"1266.0",
    "gn:asciiname":"Sleire",
    "gn:country_code":"NO",
    "gn:dem":40,
    "gn:feature_class":"P",
    "gn:feature_code":"PPL",
    "gn:name":"Sleire",
    "gn:population":0,
    "gn:timezone":"Europe/Oslo",
    "iso:country":"NO",
    "wof:name":"Sleire",
    "wof:placetype":"locality"
},
  "geometry": {"coordinates":[5.23333,60.88333000000001],"type":"Point"}
}