{
  "type": "Feature",
  "properties": {
    "gn:admin1_code":"15",
    "gn:admin2_code":"1426",
    "gn:asciiname":"Marifjora",
    "gn:country_code":"NO",
    "gn:dem":20,
    "gn:feature_class":"P",
    "gn:feature_code":"PPLL",
    "gn:name":"Marifj\u00f8ra",
    "gn:population":0,
    "gn:timezone":"Europe/Oslo",
    "iso:country":"NO",
    "name:nor_x_preferred":[
        "Marifj\u00f8ra"
    ],
    "wof:name":"Marifjora",
    "wof:placetype":"locality"
},
  "geometry": {"coordinates":[7.30645,61.38121999999999],"type":"Point"}
}