{
  "type": "Feature",
  "properties": {
    "gn:admin1_code":"18.0",
    "gn:admin2_code":"1941.0",
    "gn:asciiname":"Hellnes",
    "gn:cc2":"NO",
    "gn:country_code":"NO",
    "gn:dem":245,
    "gn:feature_class":"P",
    "gn:feature_code":"PPL",
    "gn:name":"Hellnes",
    "gn:population":0,
    "gn:timezone":"Europe/Oslo",
    "iso:country":"NO",
    "name:und_x_variant":[
        "Helnoes",
        "Heln\u00e6s",
        "Helnes",
        "Hellnes"
    ],
    "wof:name":"Hellnes",
    "wof:placetype":"locality"
},
  "geometry": {"coordinates":[20.8096,70.14083000000001],"type":"Point"}
}