{
  "type": "Feature",
  "properties": {
    "gn:admin1_code":"7.0",
    "gn:admin2_code":"1243.0",
    "gn:asciiname":"Hattvik",
    "gn:country_code":"NO",
    "gn:dem":1,
    "gn:feature_class":"P",
    "gn:feature_code":"PPL",
    "gn:name":"Hattvik",
    "gn:population":0,
    "gn:timezone":"Europe/Oslo",
    "iso:country":"NO",
    "name:nor_x_preferred":[
        "Hattvik"
    ],
    "wof:name":"Hattvik",
    "wof:placetype":"locality"
},
  "geometry": {"coordinates":[5.53433,60.20623000000001],"type":"Point"}
}