{
  "type": "Feature",
  "properties": {
    "gn:admin1_code":"17.0",
    "gn:admin2_code":"826.0",
    "gn:asciiname":"Sauro",
    "gn:country_code":"NO",
    "gn:dem":546,
    "gn:feature_class":"P",
    "gn:feature_code":"PPL",
    "gn:name":"Sauro",
    "gn:population":0,
    "gn:timezone":"Europe/Oslo",
    "iso:country":"NO",
    "name:nor_x_preferred":[
        "Sauro"
    ],
    "wof:name":"Sauro",
    "wof:placetype":"locality"
},
  "geometry": {"coordinates":[9.02906,59.87232],"type":"Point"}
}