{
  "type": "Feature",
  "properties": {
    "gn:admin1_code":"9",
    "gn:admin2_code":"1840.0",
    "gn:asciiname":"Fiskvag",
    "gn:cc2":"NO",
    "gn:country_code":"NO",
    "gn:dem":20,
    "gn:feature_class":"P",
    "gn:feature_code":"PPL",
    "gn:name":"Fiskv\u00e5g",
    "gn:population":0,
    "gn:timezone":"Europe/Oslo",
    "iso:country":"NO",
    "name:und_x_variant":[
        "Fiskvaag",
        "Fiskv\u00e5g"
    ],
    "wof:name":"Fiskvag",
    "wof:placetype":"locality"
},
  "geometry": {"coordinates":[15.38333,67.08333],"type":"Point"}
}