{
  "type": "Feature",
  "properties": {
    "gn:admin1_code":"9",
    "gn:admin2_code":"1836",
    "gn:asciiname":"Sorfjorden",
    "gn:country_code":"NO",
    "gn:dem":40,
    "gn:feature_class":"P",
    "gn:feature_code":"PPL",
    "gn:name":"S\u00f8rfjorden",
    "gn:population":0,
    "gn:timezone":"Europe/Oslo",
    "iso:country":"NO",
    "name:nor_x_preferred":[
        "S\u00f8rfjorden"
    ],
    "wof:name":"Sorfjorden",
    "wof:placetype":"locality"
},
  "geometry": {"coordinates":[13.29109,66.48990000000001],"type":"Point"}
}