{
  "type": "Feature",
  "properties": {
    "gn:country":"NO",
    "gn:fcode":"PPL",
    "gn:population":0,
    "iso:country":"NO",
    "name:ast_x_preferred":[
        "Kvinesdal"
    ],
    "name:bpy_x_preferred":[
        "\u0995\u09ac\u09bf\u09a8\u09c7\u09b8\u09a1\u09be\u09b2"
    ],
    "name:cat_x_preferred":[
        "Kvinesdal"
    ],
    "name:ceb_x_preferred":[
        "Kvinesdal"
    ],
    "name:dan_x_preferred":[
        "Kvinesdal"
    ],
    "name:deu_x_preferred":[
        "Kvinesdal"
    ],
    "name:eng_x_preferred":[
        "Kvinesdal"
    ],
    "name:epo_x_preferred":[
        "Kvinesdal"
    ],
    "name:eus_x_preferred":[
        "Kvinesdal"
    ],
    "name:fin_x_preferred":[
        "Kvinesdal"
    ],
    "name:fra_x_preferred":[
        "Kvinesdal"
    ],
    "name:hun_x_preferred":[
        "Kvinesdal"
    ],
    "name:ita_x_preferred":[
        "Kvinesdal"
    ],
    "name:lat_x_preferred":[
        "Kvinesdal"
    ],
    "name:lim_x_preferred":[
        "Kvinesdal"
    ],
    "name:msa_x_preferred":[
        "Kvinesdal"
    ],
    "name:nan_x_preferred":[
        "Kvinesdal"
    ],
    "name:nds_x_preferred":[
        "Kommun Kvinesdal"
    ],
    "name:nld_x_preferred":[
        "Kvinesdal"
    ],
    "name:nno_x_preferred":[
        "Kvinesdal"
    ],
    "name:nob_x_preferred":[
        "Kvinesdal"
    ],
    "name:nor_x_preferred":[
        "Kvinesdal"
    ],
    "name:pol_x_preferred":[
        "Kvinesdal"
    ],
    "name:por_x_preferred":[
        "Kvinesdal"
    ],
    "name:ron_x_preferred":[
        "Kvinesdal"
    ],
    "name:rus_x_preferred":[
        "\u041a\u0432\u0438\u043d\u0435\u0441\u0434\u0430\u043b"
    ],
    "name:sme_x_preferred":[
        "Kvinesdal"
    ],
    "name:spa_x_preferred":[
        "Kvinesdal"
    ],
    "name:sqi_x_preferred":[
        "Kvinesdal"
    ],
    "name:swa_x_preferred":[
        "Kvinesdal"
    ],
    "name:swe_x_preferred":[
        "Kvinesdal kommun"
    ],
    "name:swe_x_variant":[
        "Kvinesdal"
    ],
    "name:vie_x_preferred":[
        "Kvinesdal"
    ],
    "name:war_x_preferred":[
        "Kvinesdal"
    ],
    "name:zho_x_preferred":[
        "\u514b\u7dad\u5167\u65af\u9054\u723e"
    ],
    "qs_pg:aaroncc":"NO",
    "qs_pg:gn_country":"NO",
    "qs_pg:gn_fcode":"PPL",
    "qs_pg:gn_pop":0,
    "qs_pg:name":"Kvinesdal",
    "qs_pg:name_adm0":"Norge",
    "qs_pg:name_adm1":"Vest-Agder Fylke",
    "qs_pg:photos":812,
    "qs_pg:photos_1k":165,
    "qs_pg:photos_9k":4,
    "qs_pg:photos_9r":6,
    "qs_pg:photos_all":812,
    "qs_pg:photos_sr":9,
    "qs_pg:pop_sr":0,
    "qs_pg:qs_pg_placetype":"locality",
    "qs_pg:qs_pg_placetype_gp":"Town",
    "qs_pg:woe_adm0":23424910,
    "woe:adm0_id":23424910,
    "woe:name_adm0":"Norge",
    "woe:name_adm1":"Vest-Agder Fylke",
    "woe:placetype":"Town",
    "wof:name":"Kvinesdal",
    "wof:placetype":"locality"
},
  "geometry": {"coordinates":[6.95,58.31667],"type":"Point"}
}