{
  "type": "Feature",
  "properties": {
    "gn:admin1_code":"9.0",
    "gn:admin2_code":"1835.0",
    "gn:asciiname":"Stangen",
    "gn:country_code":"NO",
    "gn:dem":-9999,
    "gn:feature_class":"P",
    "gn:feature_code":"PPL",
    "gn:name":"Stangen",
    "gn:population":0,
    "gn:timezone":"Europe/Oslo",
    "iso:country":"NO",
    "name:nor_x_preferred":[
        "Stangen"
    ],
    "wof:name":"Stangen",
    "wof:placetype":"locality"
},
  "geometry": {"coordinates":[12.22763,66.58568000000001],"type":"Point"}
}