{
  "type": "Feature",
  "properties": {
    "gn:admin1_code":"11.0",
    "gn:admin2_code":"501.0",
    "gn:asciiname":"Sjoga",
    "gn:country_code":"NO",
    "gn:dem":709,
    "gn:feature_class":"P",
    "gn:feature_code":"PPL",
    "gn:name":"Sjoga",
    "gn:population":0,
    "gn:timezone":"Europe/Oslo",
    "iso:country":"NO",
    "name:nor_x_preferred":[
        "Sjoga"
    ],
    "wof:name":"Sjoga",
    "wof:placetype":"locality"
},
  "geometry": {"coordinates":[10.24802,61.06707],"type":"Point"}
}