{
  "type": "Feature",
  "properties": {
    "gn:admin1_code":"11.0",
    "gn:admin2_code":"532.0",
    "gn:asciiname":"Onsaker",
    "gn:country_code":"NO",
    "gn:dem":135,
    "gn:feature_class":"P",
    "gn:feature_code":"PPL",
    "gn:name":"Onsaker",
    "gn:population":0,
    "gn:timezone":"Europe/Oslo",
    "iso:country":"NO",
    "wof:name":"Onsaker",
    "wof:placetype":"locality"
},
  "geometry": {"coordinates":[10.35,60.33333],"type":"Point"}
}