{
  "type": "Feature",
  "properties": {
    "gn:admin1_code":"7",
    "gn:admin2_code":"1201.0",
    "gn:asciiname":"Steinstoi",
    "gn:cc2":"NO",
    "gn:country_code":"NO",
    "gn:dem":13,
    "gn:feature_class":"P",
    "gn:feature_code":"PPLL",
    "gn:name":"Steinst\u00f8i",
    "gn:population":0,
    "gn:timezone":"Europe/Oslo",
    "iso:country":"NO",
    "name:und_x_variant":[
        "Steinest\u00f8",
        "Steinst\u00f6",
        "Steinst\u00f8i"
    ],
    "wof:name":"Steinstoi",
    "wof:placetype":"locality"
},
  "geometry": {"coordinates":[5.31417,60.52222],"type":"Point"}
}