{
  "type": "Feature",
  "properties": {
    "gn:admin1_code":"21.0",
    "gn:admin2_code":"5042.0",
    "gn:asciiname":"Skjeldbreia",
    "gn:country_code":"NO",
    "gn:dem":420,
    "gn:feature_class":"P",
    "gn:feature_code":"PPL",
    "gn:name":"Skjeldbreia",
    "gn:population":0,
    "gn:timezone":"Europe/Oslo",
    "iso:country":"NO",
    "name:nor_x_preferred":[
        "Skjeldbreia"
    ],
    "name:und_x_variant":[
        "Skjelbreid",
        "Skjelbred",
        "Skjelbrei",
        "Skjellbreid",
        "Brattlandsmoen"
    ],
    "wof:name":"Skjeldbreia",
    "wof:placetype":"locality"
},
  "geometry": {"coordinates":[13.41011,64.49254000000001],"type":"Point"}
}