{
  "type": "Feature",
  "properties": {
    "gn:admin1_code":"19.0",
    "gn:admin2_code":"1021.0",
    "gn:asciiname":"Haraldstad",
    "gn:country_code":"NO",
    "gn:dem":342,
    "gn:feature_class":"P",
    "gn:feature_code":"PPL",
    "gn:name":"Haraldstad",
    "gn:population":0,
    "gn:timezone":"Europe/Oslo",
    "iso:country":"NO",
    "name:nor_x_preferred":[
        "Haraldstad"
    ],
    "wof:name":"Haraldstad",
    "wof:placetype":"locality"
},
  "geometry": {"coordinates":[7.48466,58.3302],"type":"Point"}
}