{
  "type": "Feature",
  "properties": {
    "gn:admin1_code":"19.0",
    "gn:admin2_code":"1001.0",
    "gn:asciiname":"Aurebekk",
    "gn:country_code":"NO",
    "gn:dem":93,
    "gn:feature_class":"P",
    "gn:feature_code":"PPL",
    "gn:name":"Aurebekk",
    "gn:population":0,
    "gn:timezone":"Europe/Oslo",
    "iso:country":"NO",
    "name:nor_x_preferred":[
        "Aurebekk"
    ],
    "wof:name":"Aurebekk",
    "wof:placetype":"locality"
},
  "geometry": {"coordinates":[7.88208,58.20093000000001],"type":"Point"}
}