{
  "type": "Feature",
  "properties": {
    "iso:country":"NO",
    "qs_pg:aaroncc":"NO",
    "qs_pg:name":"Tj\u00f8rhom",
    "qs_pg:name_adm0":"Norge",
    "qs_pg:name_adm1":"Vest-Agder Fylke",
    "qs_pg:photos":144,
    "qs_pg:photos_1k":29,
    "qs_pg:photos_9k":1,
    "qs_pg:photos_9r":3,
    "qs_pg:photos_all":144,
    "qs_pg:photos_sr":3,
    "qs_pg:pop_sr":0,
    "qs_pg:qs_pg_placetype":"locality",
    "qs_pg:qs_pg_placetype_gp":"Town",
    "qs_pg:woe_adm0":23424910,
    "woe:adm0_id":23424910,
    "woe:name_adm0":"Norge",
    "woe:name_adm1":"Vest-Agder Fylke",
    "woe:placetype":"Town",
    "wof:name":"Tj\u00f8rhom",
    "wof:placetype":"locality"
},
  "geometry": {"coordinates":[6.863708,58.904291],"type":"Point"}
}