{
  "type": "Feature",
  "properties": {
    "gn:admin1_code":"17",
    "gn:admin2_code":"807",
    "gn:asciiname":"Svelgfoss",
    "gn:country_code":"NO",
    "gn:dem":139,
    "gn:feature_class":"P",
    "gn:feature_code":"PPLL",
    "gn:name":"Svelgfoss",
    "gn:population":0,
    "gn:timezone":"Europe/Oslo",
    "iso:country":"NO",
    "name:nor_x_preferred":[
        "Svelgfoss"
    ],
    "wof:name":"Svelgfoss",
    "wof:placetype":"locality"
},
  "geometry": {"coordinates":[9.27085,59.59665],"type":"Point"}
}