{
  "type": "Feature",
  "properties": {
    "gn:admin1_code":"15",
    "gn:admin2_code":"1433.0",
    "gn:asciiname":"Eikrem",
    "gn:cc2":"NO",
    "gn:country_code":"NO",
    "gn:dem":43,
    "gn:feature_class":"P",
    "gn:feature_code":"PPL",
    "gn:name":"Eikrem",
    "gn:population":0,
    "gn:timezone":"Europe/Oslo",
    "iso:country":"NO",
    "name:und_x_variant":[
        "Ekre",
        "Ekren",
        "Eikrem"
    ],
    "wof:name":"Eikrem",
    "wof:placetype":"locality"
},
  "geometry": {"coordinates":[5.78333,61.55],"type":"Point"}
}