{
  "type": "Feature",
  "properties": {
    "gn:admin1_code":"1",
    "gn:admin2_code":"226.0",
    "gn:asciiname":"Mork",
    "gn:cc2":"NO",
    "gn:country_code":"NO",
    "gn:dem":182,
    "gn:feature_class":"P",
    "gn:feature_code":"PPL",
    "gn:name":"Mork",
    "gn:population":0,
    "gn:timezone":"Europe/Oslo",
    "iso:country":"NO",
    "name:und_x_variant":[
        "Mork i Romerike",
        "Mork"
    ],
    "wof:name":"Mork",
    "wof:placetype":"locality"
},
  "geometry": {"coordinates":[11.31667,59.95],"type":"Point"}
}