{
  "type": "Feature",
  "properties": {
    "gn:admin1_code":"19",
    "gn:admin2_code":"1003.0",
    "gn:asciiname":"Nordberg",
    "gn:country_code":"NO",
    "gn:dem":60,
    "gn:feature_class":"P",
    "gn:feature_code":"PPL",
    "gn:name":"Nordberg",
    "gn:population":0,
    "gn:timezone":"Europe/Oslo",
    "iso:country":"NO",
    "name:jav_x_preferred":[
        "Nordberg"
    ],
    "name:msa_x_preferred":[
        "Nordberg"
    ],
    "name:nor_x_preferred":[
        "Nordberg"
    ],
    "wof:name":"Nordberg",
    "wof:placetype":"locality"
},
  "geometry": {"coordinates":[6.61667,58.13333000000001],"type":"Point"}
}