{
  "type": "Feature",
  "properties": {
    "gn:admin1_code":"6",
    "gn:admin2_code":"441.0",
    "gn:asciiname":"Narjordet",
    "gn:country_code":"NO",
    "gn:dem":740,
    "gn:feature_class":"P",
    "gn:feature_code":"PPL",
    "gn:name":"Narjordet",
    "gn:population":0,
    "gn:timezone":"Europe/Oslo",
    "iso:country":"NO",
    "wof:name":"Narjordet",
    "wof:placetype":"locality"
},
  "geometry": {"coordinates":[11.41351,62.43619],"type":"Point"}
}