{
  "type": "Feature",
  "properties": {
    "gn:admin1_code":"17",
    "gn:admin2_code":"830.0",
    "gn:asciiname":"Haugsjasund",
    "gn:country_code":"NO",
    "gn:dem":165,
    "gn:feature_class":"P",
    "gn:feature_code":"PPL",
    "gn:name":"Haugsj\u00e5sund",
    "gn:population":0,
    "gn:timezone":"Europe/Oslo",
    "iso:country":"NO",
    "wof:name":"Haugsjasund",
    "wof:placetype":"locality"
},
  "geometry": {"coordinates":[8.50545,58.94424],"type":"Point"}
}