{
  "type": "Feature",
  "properties": {
    "gn:admin1_code":"1",
    "gn:admin2_code":"216",
    "gn:asciiname":"Sjostrand",
    "gn:country_code":"NO",
    "gn:dem":32,
    "gn:feature_class":"P",
    "gn:feature_code":"PPLL",
    "gn:name":"Sj\u00f8strand",
    "gn:population":0,
    "gn:timezone":"Europe/Oslo",
    "iso:country":"NO",
    "name:nor_x_preferred":[
        "Sj\u00f8strand"
    ],
    "wof:name":"Sjostrand",
    "wof:placetype":"locality"
},
  "geometry": {"coordinates":[10.65201,59.85303],"type":"Point"}
}