{
  "type": "Feature",
  "properties": {
    "gn:admin1_code":"12.0",
    "gn:admin2_code":"301.0",
    "gn:asciiname":"Orebakken",
    "gn:country_code":"NO",
    "gn:dem":158,
    "gn:elevation":"170.0",
    "gn:feature_class":"P",
    "gn:feature_code":"PPLL",
    "gn:name":"Orebakken",
    "gn:population":0,
    "gn:timezone":"Europe/Oslo",
    "iso:country":"NO",
    "wof:name":"Orebakken",
    "wof:placetype":"neighbourhood"
},
  "geometry": {"coordinates":[10.6509,59.95261],"type":"Point"}
}