{
  "type": "Feature",
  "properties": {
    "gn:admin1_code":"21.0",
    "gn:admin2_code":"5026.0",
    "gn:asciiname":"Moan",
    "gn:country_code":"NO",
    "gn:dem":300,
    "gn:feature_class":"P",
    "gn:feature_code":"PPL",
    "gn:name":"Moan",
    "gn:population":0,
    "gn:timezone":"Europe/Oslo",
    "iso:country":"NO",
    "name:nor_x_preferred":[
        "Moan"
    ],
    "wof:name":"Moan",
    "wof:placetype":"locality"
},
  "geometry": {"coordinates":[11.10499,62.93303],"type":"Point"}
}