{
  "type": "Feature",
  "properties": {
    "gn:admin1_code":"7",
    "gn:admin2_code":"1223.0",
    "gn:asciiname":"Drange",
    "gn:country_code":"NO",
    "gn:dem":97,
    "gn:feature_class":"P",
    "gn:feature_code":"PPL",
    "gn:name":"Drange",
    "gn:population":0,
    "gn:timezone":"Europe/Oslo",
    "iso:country":"NO",
    "wof:name":"Drange",
    "wof:placetype":"locality"
},
  "geometry": {"coordinates":[5.4775,59.97],"type":"Point"}
}