{
  "type": "Feature",
  "properties": {
    "gn:admin1_code":"21",
    "gn:admin2_code":"5047.0",
    "gn:asciiname":"Homstad",
    "gn:cc2":"NO",
    "gn:country_code":"NO",
    "gn:dem":120,
    "gn:feature_class":"P",
    "gn:feature_code":"PPL",
    "gn:name":"Homstad",
    "gn:population":0,
    "gn:timezone":"Europe/Oslo",
    "iso:country":"NO",
    "name:und_x_variant":[
        "H\u00e5mstad",
        "Homstad"
    ],
    "wof:name":"Homstad",
    "wof:placetype":"locality"
},
  "geometry": {"coordinates":[11.83333,64.43333],"type":"Point"}
}