{
  "type": "Feature",
  "properties": {
    "gn:admin1_code":"7",
    "gn:admin2_code":"1260.0",
    "gn:asciiname":"Morki",
    "gn:country_code":"NO",
    "gn:dem":40,
    "gn:feature_class":"P",
    "gn:feature_code":"PPL",
    "gn:name":"Morki",
    "gn:population":0,
    "gn:timezone":"Europe/Oslo",
    "iso:country":"NO",
    "name:bul_x_preferred":[
        "\u041c\u043e\u0440\u043a\u0438"
    ],
    "name:ceb_x_preferred":[
        "Morki"
    ],
    "name:che_x_preferred":[
        "\u041c\u043e\u0440\u043a\u0438"
    ],
    "name:chv_x_preferred":[
        "\u041c\u043e\u0440\u043a\u0103"
    ],
    "name:deu_x_preferred":[
        "Morki"
    ],
    "name:fin_x_preferred":[
        "Morki"
    ],
    "name:hun_x_preferred":[
        "Morki"
    ],
    "name:hye_x_preferred":[
        "\u0544\u0578\u0580\u056f\u056b"
    ],
    "name:mhr_x_preferred":[
        "\u041c\u043e\u0440\u043a\u043e"
    ],
    "name:myv_x_preferred":[
        "\u041c\u043e\u0440\u043a\u0438"
    ],
    "name:pol_x_preferred":[
        "Morki"
    ],
    "name:rus_x_preferred":[
        "\u041c\u043e\u0440\u043a\u0438"
    ],
    "name:tat_x_preferred":[
        "\u041c\u043e\u0440\u043a\u0435"
    ],
    "wof:name":"Morki",
    "wof:placetype":"locality"
},
  "geometry": {"coordinates":[5.06944,60.63306],"type":"Point"}
}