{
  "type": "Feature",
  "properties": {
    "gn:admin1_code":"7.0",
    "gn:admin2_code":"1256.0",
    "gn:asciiname":"Saetre",
    "gn:country_code":"NO",
    "gn:dem":20,
    "gn:feature_class":"P",
    "gn:feature_code":"PPL",
    "gn:name":"S\u00e6tre",
    "gn:population":0,
    "gn:timezone":"Europe/Oslo",
    "iso:country":"NO",
    "wof:name":"Saetre",
    "wof:placetype":"locality"
},
  "geometry": {"coordinates":[4.99083,60.59389],"type":"Point"}
}