{
  "type": "Feature",
  "properties": {
    "gn:admin1_code":"4",
    "gn:admin2_code":"623.0",
    "gn:asciiname":"Bjorndalen",
    "gn:country_code":"NO",
    "gn:dem":104,
    "gn:feature_class":"P",
    "gn:feature_code":"PPL",
    "gn:name":"Bj\u00f8rndalen",
    "gn:population":0,
    "gn:timezone":"Europe/Oslo",
    "iso:country":"NO",
    "wof:name":"Bjorndalen",
    "wof:placetype":"locality"
},
  "geometry": {"coordinates":[9.83333,59.95],"type":"Point"}
}