{
  "type": "Feature",
  "properties": {
    "gn:admin1_code":"18",
    "gn:admin2_code":"1920.0",
    "gn:asciiname":"Gamvik",
    "gn:country_code":"NO",
    "gn:dem":-9999,
    "gn:feature_class":"P",
    "gn:feature_code":"PPL",
    "gn:name":"Gamvik",
    "gn:population":0,
    "gn:timezone":"Europe/Oslo",
    "iso:country":"NO",
    "wof:name":"Gamvik",
    "wof:placetype":"locality"
},
  "geometry": {"coordinates":[17.75,68.78333000000001],"type":"Point"}
}