{
  "type": "Feature",
  "properties": {
    "gn:admin1_code":"18",
    "gn:admin2_code":"1920.0",
    "gn:asciiname":"Gamvik",
    "gn:country_code":"NO",
    "gn:dem":-9999,
    "gn:feature_class":"P",
    "gn:feature_code":"PPL",
    "gn:name":"Gamvik",
    "gn:population":0,
    "gn:timezone":"Europe/Oslo",
    "iso:country":"NO",
    "name:ara_x_preferred":[
        "\u063a\u0627\u0645\u0641\u064a\u0643"
    ],
    "name:bpy_x_preferred":[
        "\u0997\u09be\u09ae\u09ad\u09bf\u0995"
    ],
    "name:cat_x_preferred":[
        "Gamvik"
    ],
    "name:ceb_x_preferred":[
        "Gamvik"
    ],
    "name:dan_x_preferred":[
        "Gamvik"
    ],
    "name:deu_x_preferred":[
        "Gamvik"
    ],
    "name:epo_x_preferred":[
        "Gamvik"
    ],
    "name:est_x_preferred":[
        "Gamviki vald"
    ],
    "name:eus_x_preferred":[
        "Gamvik"
    ],
    "name:fas_x_preferred":[
        "\u06af\u0627\u0645\u0648\u06cc\u06a9"
    ],
    "name:fin_x_preferred":[
        "Gamvik"
    ],
    "name:fra_x_preferred":[
        "Gamvik"
    ],
    "name:hye_x_preferred":[
        "\u0533\u0561\u0574\u057e\u056b\u056f"
    ],
    "name:ita_x_preferred":[
        "Gamvik"
    ],
    "name:jav_x_preferred":[
        "Gamvik"
    ],
    "name:jpn_x_preferred":[
        "\u30ac\u30f3\u30f4\u30a3\u30af"
    ],
    "name:lat_x_preferred":[
        "Gamvik"
    ],
    "name:lim_x_preferred":[
        "Gamvik"
    ],
    "name:msa_x_preferred":[
        "Gamvik"
    ],
    "name:nds_x_preferred":[
        "Kommun Gamvik"
    ],
    "name:nld_x_preferred":[
        "Gamvik"
    ],
    "name:nno_x_preferred":[
        "Gamvik kommune"
    ],
    "name:nor_x_preferred":[
        "Gamvik"
    ],
    "name:pol_x_preferred":[
        "Gamvik"
    ],
    "name:por_x_preferred":[
        "Gamvik"
    ],
    "name:ron_x_preferred":[
        "Gamvik"
    ],
    "name:rus_x_preferred":[
        "\u0413\u0430\u043c\u0432\u0438\u043a"
    ],
    "name:slv_x_preferred":[
        "Gamvik"
    ],
    "name:sme_x_preferred":[
        "G\u00e1\u014bgaviika"
    ],
    "name:spa_x_preferred":[
        "Gamvik"
    ],
    "name:sqi_x_preferred":[
        "Gamvik"
    ],
    "name:swe_x_preferred":[
        "Gamviks kommun"
    ],
    "name:tur_x_preferred":[
        "Gamvik"
    ],
    "name:ukr_x_preferred":[
        "\u0490\u0430\u043c\u0432\u0456\u043a"
    ],
    "name:vie_x_preferred":[
        "Gamvik"
    ],
    "name:war_x_preferred":[
        "Gamvik"
    ],
    "name:zho_x_preferred":[
        "\u52a0\u59c6\u7dad\u514b"
    ],
    "wof:name":"Gamvik",
    "wof:placetype":"locality"
},
  "geometry": {"coordinates":[17.75,68.78333000000001],"type":"Point"}
}