{
  "type": "Feature",
  "properties": {
    "gn:admin1_code":"15.0",
    "gn:admin2_code":"1449.0",
    "gn:asciiname":"Olden",
    "gn:country_code":"NO",
    "gn:dem":20,
    "gn:elevation":"3.0",
    "gn:feature_class":"P",
    "gn:feature_code":"PPL",
    "gn:name":"Olden",
    "gn:population":0,
    "gn:timezone":"Europe/Oslo",
    "iso:country":"NO",
    "wof:name":"Olden",
    "wof:placetype":"locality"
},
  "geometry": {"coordinates":[6.80655,61.83655],"type":"Point"}
}