{
  "type": "Feature",
  "properties": {
    "gn:admin1_code":"18.0",
    "gn:admin2_code":"1933.0",
    "gn:asciiname":"Vollan",
    "gn:cc2":"NO",
    "gn:country_code":"NO",
    "gn:dem":46,
    "gn:feature_class":"P",
    "gn:feature_code":"PPL",
    "gn:name":"Vollan",
    "gn:population":0,
    "gn:timezone":"Europe/Oslo",
    "iso:country":"NO",
    "name:und_x_variant":[
        "Vollen",
        "Voldane",
        "Vollan"
    ],
    "wof:name":"Vollan",
    "wof:placetype":"neighbourhood"
},
  "geometry": {"coordinates":[19.56667,69.21666999999999],"type":"Point"}
}