{
  "type": "Feature",
  "properties": {
    "gn:admin1_code":"11.0",
    "gn:admin2_code":"517.0",
    "gn:asciiname":"Sagdalen",
    "gn:country_code":"NO",
    "gn:dem":380,
    "gn:feature_class":"P",
    "gn:feature_code":"PPL",
    "gn:name":"Sagdalen",
    "gn:population":0,
    "gn:timezone":"Europe/Oslo",
    "iso:country":"NO",
    "name:nor_x_preferred":[
        "Sagdalen"
    ],
    "wof:name":"Sagdalen",
    "wof:placetype":"locality"
},
  "geometry": {"coordinates":[9.39479,61.83574],"type":"Point"}
}