{
  "type": "Feature",
  "properties": {
    "gn:admin1_code":"4",
    "gn:admin2_code":"623.0",
    "gn:asciiname":"Kjolstad",
    "gn:country_code":"NO",
    "gn:dem":102,
    "gn:feature_class":"P",
    "gn:feature_code":"PPL",
    "gn:name":"Kj\u00f8lstad",
    "gn:population":0,
    "gn:timezone":"Europe/Oslo",
    "iso:country":"NO",
    "wof:name":"Kjolstad",
    "wof:placetype":"locality"
},
  "geometry": {"coordinates":[9.96667,59.95],"type":"Point"}
}