{
  "type": "Feature",
  "properties": {
    "gn:admin1_code":"9.0",
    "gn:admin2_code":"1832.0",
    "gn:asciiname":"Sund",
    "gn:country_code":"NO",
    "gn:dem":22,
    "gn:feature_class":"P",
    "gn:feature_code":"PPL",
    "gn:name":"Sund",
    "gn:population":0,
    "gn:timezone":"Europe/Oslo",
    "iso:country":"NO",
    "name:fra_x_preferred":[
        "Sund"
    ],
    "name:jav_x_preferred":[
        "Sund"
    ],
    "name:msa_x_preferred":[
        "Sund"
    ],
    "wof:name":"Sund",
    "wof:placetype":"locality"
},
  "geometry": {"coordinates":[13.64435,66.20732],"type":"Point"}
}