{
  "type": "Feature",
  "properties": {
    "gn:admin1_code":"18",
    "gn:admin2_code":"1902.0",
    "gn:asciiname":"Lakselv",
    "gn:country_code":"NO",
    "gn:dem":265,
    "gn:feature_class":"P",
    "gn:feature_code":"PPL",
    "gn:name":"Lakselv",
    "gn:population":0,
    "gn:timezone":"Europe/Oslo",
    "iso:country":"NO",
    "wof:name":"Lakselv",
    "wof:placetype":"locality"
},
  "geometry": {"coordinates":[19.66667,69.43333],"type":"Point"}
}