{
  "type": "Feature",
  "properties": {
    "gn:admin1_code":"18",
    "gn:admin2_code":"1902.0",
    "gn:asciiname":"Lakselv",
    "gn:country_code":"NO",
    "gn:dem":265,
    "gn:feature_class":"P",
    "gn:feature_code":"PPL",
    "gn:name":"Lakselv",
    "gn:population":0,
    "gn:timezone":"Europe/Oslo",
    "iso:country":"NO",
    "name:bar_x_preferred":[
        "Lakselv"
    ],
    "name:bel_x_preferred":[
        "\u041b\u0430\u043a\u0441\u044d\u043b\u044c\u0432"
    ],
    "name:bul_x_preferred":[
        "\u041b\u0430\u043a\u0441\u0435\u043b\u0432"
    ],
    "name:cat_x_preferred":[
        "Lakselv"
    ],
    "name:ceb_x_preferred":[
        "Lakselv"
    ],
    "name:dan_x_preferred":[
        "Lakselv"
    ],
    "name:deu_x_preferred":[
        "Lakselv"
    ],
    "name:fin_x_preferred":[
        "Lemmijoki"
    ],
    "name:fra_x_preferred":[
        "Lakselv"
    ],
    "name:hun_x_preferred":[
        "Lakselv"
    ],
    "name:ita_x_preferred":[
        "Lakselv"
    ],
    "name:jav_x_preferred":[
        "Lakselv"
    ],
    "name:msa_x_preferred":[
        "Lakselv"
    ],
    "name:nld_x_preferred":[
        "Lakselv"
    ],
    "name:nno_x_preferred":[
        "Lakselv"
    ],
    "name:nor_x_preferred":[
        "Lakselv"
    ],
    "name:por_x_preferred":[
        "Lakselv"
    ],
    "name:ron_x_preferred":[
        "Lakselv"
    ],
    "name:rus_x_preferred":[
        "\u041b\u0430\u043a\u0441\u044d\u043b\u044c\u0432"
    ],
    "name:sme_x_preferred":[
        "Leavdnja"
    ],
    "name:spa_x_preferred":[
        "Lakselv"
    ],
    "name:swe_x_preferred":[
        "Lakselv"
    ],
    "name:urd_x_preferred":[
        "\u0644\u0627\u06a9\u0633\u06cc\u0644\u0648"
    ],
    "name:zho_x_preferred":[
        "\u62c9\u514b\u585e\u723e\u592b"
    ],
    "wof:name":"Lakselv",
    "wof:placetype":"locality"
},
  "geometry": {"coordinates":[19.66667,69.43333],"type":"Point"}
}