{
  "type": "Feature",
  "properties": {
    "gn:country":"NO",
    "gn:fcode":"PPLA2",
    "gn:population":0,
    "iso:country":"NO",
    "name:dan_x_preferred":[
        "Orkanger"
    ],
    "name:ell_x_preferred":[
        "\u038c\u03c1\u03ba\u03b1\u03bd\u03b3\u03ba\u03b5\u03c1"
    ],
    "name:eng_x_preferred":[
        "Orkanger"
    ],
    "name:fas_x_preferred":[
        "\u0627\u0648\u0631\u06a9\u0627\u0646\u06af\u0631"
    ],
    "name:fra_x_preferred":[
        "Orkanger"
    ],
    "name:ita_x_preferred":[
        "Orkanger"
    ],
    "name:msa_x_preferred":[
        "Orkanger"
    ],
    "name:nld_x_preferred":[
        "Orkanger"
    ],
    "name:nno_x_preferred":[
        "Orkanger"
    ],
    "name:nob_x_preferred":[
        "Orkanger"
    ],
    "name:ron_x_preferred":[
        "Orkanger"
    ],
    "name:spa_x_preferred":[
        "Orkanger"
    ],
    "name:srp_x_preferred":[
        "\u041e\u0440\u043a\u0430\u043d\u0433\u0435\u0440"
    ],
    "name:swe_x_preferred":[
        "Orkanger"
    ],
    "qs_pg:aaroncc":"NO",
    "qs_pg:gn_country":"NO",
    "qs_pg:gn_fcode":"PPLA2",
    "qs_pg:gn_pop":0,
    "qs_pg:name":"Orkanger",
    "qs_pg:name_adm0":"Norge",
    "qs_pg:name_adm1":"S\u00f8r-Tr\u00f8ndelag Fylke",
    "qs_pg:photos":255,
    "qs_pg:photos_1k":52,
    "qs_pg:photos_9k":1,
    "qs_pg:photos_9r":4,
    "qs_pg:photos_all":255,
    "qs_pg:photos_sr":5,
    "qs_pg:pop_sr":4,
    "qs_pg:qs_pg_placetype":"locality",
    "qs_pg:qs_pg_placetype_gp":"Town",
    "qs_pg:woe_adm0":23424910,
    "woe:adm0_id":23424910,
    "woe:name_adm0":"Norge",
    "woe:name_adm1":"S\u00f8r-Tr\u00f8ndelag Fylke",
    "woe:placetype":"Town",
    "wof:name":"Orkanger",
    "wof:placetype":"neighbourhood"
},
  "geometry": {"coordinates":[9.85352,63.31223],"type":"Point"}
}