{
  "type": "Feature",
  "properties": {
    "gn:admin1_code":"9",
    "gn:admin2_code":"1850.0",
    "gn:asciiname":"Gielkka",
    "gn:country_code":"NO",
    "gn:dem":52,
    "gn:feature_class":"P",
    "gn:feature_code":"PPL",
    "gn:name":"Gielkk\u00e1",
    "gn:population":0,
    "gn:timezone":"Europe/Oslo",
    "iso:country":"NO",
    "name:nor_x_preferred":[
        "Kjelkvika"
    ],
    "name:smj_x_preferred":[
        "Gielkk\u00e1"
    ],
    "name:smj_x_variant":[
        "Gielkkat"
    ],
    "wof:name":"Gielkka",
    "wof:placetype":"locality"
},
  "geometry": {"coordinates":[16.34765,68.14331999999999],"type":"Point"}
}