{
  "type": "Feature",
  "properties": {
    "gn:admin1_code":"1.0",
    "gn:admin2_code":"237.0",
    "gn:asciiname":"Sorli",
    "gn:country_code":"NO",
    "gn:dem":330,
    "gn:feature_class":"P",
    "gn:feature_code":"PPL",
    "gn:name":"S\u00f8rli",
    "gn:population":0,
    "gn:timezone":"Europe/Oslo",
    "iso:country":"NO",
    "wof:name":"Sorli",
    "wof:placetype":"locality"
},
  "geometry": {"coordinates":[11.35,60.36666999999999],"type":"Point"}
}