{
  "type": "Feature",
  "properties": {
    "gn:admin1_code":"21",
    "gn:admin2_code":"5021.0",
    "gn:asciiname":"Hol",
    "gn:country_code":"NO",
    "gn:dem":500,
    "gn:feature_class":"P",
    "gn:feature_code":"PPL",
    "gn:name":"Hol",
    "gn:population":0,
    "gn:timezone":"Europe/Oslo",
    "iso:country":"NO",
    "name:nor_x_preferred":[
        "Hol"
    ],
    "wof:name":"Hol",
    "wof:placetype":"locality"
},
  "geometry": {"coordinates":[9.63333,62.56667],"type":"Point"}
}