{
  "type": "Feature",
  "properties": {
    "iso:country":"NO",
    "name:bre_x_preferred":[
        "Marken"
    ],
    "name:ceb_x_preferred":[
        "Marken"
    ],
    "name:dan_x_preferred":[
        "Marken"
    ],
    "name:deu_x_preferred":[
        "Marken"
    ],
    "name:epo_x_preferred":[
        "Marken"
    ],
    "name:fas_x_preferred":[
        "\u0645\u0627\u0631\u06a9\u0646"
    ],
    "name:fra_x_preferred":[
        "Marken"
    ],
    "name:fry_x_preferred":[
        "Marken"
    ],
    "name:ita_x_preferred":[
        "Marken"
    ],
    "name:nld_x_preferred":[
        "Marken"
    ],
    "name:nor_x_preferred":[
        "Marken"
    ],
    "name:pol_x_preferred":[
        "Marken"
    ],
    "name:por_x_preferred":[
        "Marken"
    ],
    "name:rus_x_preferred":[
        "\u041c\u0430\u0440\u043a\u0435\u043d"
    ],
    "name:spa_x_preferred":[
        "Marken"
    ],
    "name:swe_x_preferred":[
        "Marken"
    ],
    "name:tur_x_preferred":[
        "Marken"
    ],
    "name:ukr_x_preferred":[
        "\u041c\u0430\u0440\u043a\u0435\u043d"
    ],
    "name:unk_x_variant":[
        "Marken"
    ],
    "qs:gn_adm0_cc":"NO",
    "qs:gn_local":3161732,
    "qs:gn_nam_loc":"Bergen, Bergen, Hordaland Fylke, NO",
    "qs:gn_namadm1":"07",
    "qs:local_max":5825,
    "qs:local_sum":38813,
    "qs:localhoods":24,
    "qs:name":"Marken",
    "qs:name_adm0":"Norge",
    "qs:name_adm1":"Hordaland Fylke",
    "qs:name_adm2":"Bergen Kommune",
    "qs:name_local":"Bergen",
    "qs:photo_max":1519,
    "qs:photo_sum":4479,
    "qs:placetype":"Suburb",
    "qs:quad_count":33,
    "qs:woe_adm0":23424910,
    "qs:woe_adm1":2346390,
    "qs:woe_adm2":12592658,
    "qs:woe_lau":0,
    "qs:woe_local":857105,
    "qs:woe_ver":"7.10.0",
    "wof:lang":[
        "nor"
    ],
    "wof:name":"Marken",
    "wof:placetype":"neighbourhood"
},
  "geometry": {"coordinates":[5.326278,60.389595],"type":"Point"}
}