{
  "type": "Feature",
  "properties": {
    "gn:admin1_code":"9",
    "gn:admin2_code":"1860.0",
    "gn:asciiname":"Karijorden",
    "gn:country_code":"NO",
    "gn:dem":73,
    "gn:feature_class":"P",
    "gn:feature_code":"PPL",
    "gn:name":"Karijorden",
    "gn:population":0,
    "gn:timezone":"Europe/Oslo",
    "iso:country":"NO",
    "wof:name":"Karijorden",
    "wof:placetype":"locality"
},
  "geometry": {"coordinates":[13.76667,68.15000000000001],"type":"Point"}
}