{
  "type": "Feature",
  "properties": {
    "gn:admin1_code":"4.0",
    "gn:admin2_code":"605.0",
    "gn:asciiname":"Somma",
    "gn:country_code":"NO",
    "gn:dem":173,
    "gn:feature_class":"P",
    "gn:feature_code":"PPL",
    "gn:name":"Somma",
    "gn:population":0,
    "gn:timezone":"Europe/Oslo",
    "iso:country":"NO",
    "name:nor_x_preferred":[
        "Somma"
    ],
    "wof:name":"Somma",
    "wof:placetype":"locality"
},
  "geometry": {"coordinates":[10.15481,60.31208],"type":"Point"}
}