{
  "type": "Feature",
  "properties": {
    "gn:admin1_code":"5.0",
    "gn:admin2_code":"2030.0",
    "gn:asciiname":"Kotala",
    "gn:country_code":"NO",
    "gn:dem":40,
    "gn:feature_class":"P",
    "gn:feature_code":"PPL",
    "gn:name":"Kotala",
    "gn:population":0,
    "gn:timezone":"Europe/Oslo",
    "iso:country":"NO",
    "name:fkv_x_preferred":[
        "Kotala"
    ],
    "wof:name":"Kotala",
    "wof:placetype":"locality"
},
  "geometry": {"coordinates":[29.43005,69.70193],"type":"Point"}
}