{
  "type": "Feature",
  "properties": {
    "gn:admin1_code":"21",
    "gn:admin2_code":"5018.0",
    "gn:asciiname":"Arnes",
    "gn:cc2":"NO",
    "gn:country_code":"NO",
    "gn:dem":60,
    "gn:feature_class":"P",
    "gn:feature_code":"PPLA2",
    "gn:name":"\u00c5rnes",
    "gn:population":0,
    "gn:timezone":"Europe/Oslo",
    "iso:country":"NO",
    "name:ceb_x_preferred":[
        "Arnes"
    ],
    "name:deu_x_preferred":[
        "Arnes"
    ],
    "name:eus_x_preferred":[
        "Arnes"
    ],
    "name:fra_x_preferred":[
        "Arnes"
    ],
    "name:nld_x_preferred":[
        "Arnes"
    ],
    "name:slv_x_preferred":[
        "Arnes"
    ],
    "name:swe_x_preferred":[
        "Arnes"
    ],
    "name:und_x_variant":[
        "Aarnes",
        "\u00c5rnes"
    ],
    "wof:name":"Arnes",
    "wof:placetype":"neighbourhood"
},
  "geometry": {"coordinates":[10.22601,63.96114],"type":"Point"}
}