{
  "type": "Feature",
  "properties": {
    "gn:admin1_code":"8.0",
    "gn:admin2_code":"1520.0",
    "gn:asciiname":"Oye",
    "gn:cc2":"NO",
    "gn:country_code":"NO",
    "gn:dem":40,
    "gn:feature_class":"P",
    "gn:feature_code":"PPL",
    "gn:name":"\u00d8ye",
    "gn:population":0,
    "gn:timezone":"Europe/Oslo",
    "iso:country":"NO",
    "name:ceb_x_preferred":[
        "Oye"
    ],
    "name:deu_x_preferred":[
        "Oye"
    ],
    "name:fra_x_preferred":[
        "Oye"
    ],
    "name:por_x_preferred":[
        "Oye"
    ],
    "name:swe_x_preferred":[
        "Oye"
    ],
    "name:und_x_variant":[
        "\u00d6ie",
        "\u00d8ye"
    ],
    "name:vie_x_preferred":[
        "Oye"
    ],
    "wof:name":"Oye",
    "wof:placetype":"locality"
},
  "geometry": {"coordinates":[6.66634,62.19001],"type":"Point"}
}