{
  "type": "Feature",
  "properties": {
    "gn:admin1_code":"6",
    "gn:admin2_code":"415",
    "gn:asciiname":"Brenneriroa",
    "gn:country_code":"NO",
    "gn:dem":240,
    "gn:feature_class":"P",
    "gn:feature_code":"PPLL",
    "gn:name":"Brenneriroa",
    "gn:population":0,
    "gn:timezone":"Europe/Oslo",
    "iso:country":"NO",
    "name:nor_x_preferred":[
        "Brenneriroa"
    ],
    "wof:name":"Brenneriroa",
    "wof:placetype":"locality"
},
  "geometry": {"coordinates":[11.3033,60.82753],"type":"Point"}
}