{
  "type": "Feature",
  "properties": {
    "gn:admin1_code":"18.0",
    "gn:admin2_code":"1911.0",
    "gn:asciiname":"Vebostad",
    "gn:country_code":"NO",
    "gn:dem":100,
    "gn:feature_class":"P",
    "gn:feature_code":"PPL",
    "gn:name":"Vebostad",
    "gn:population":0,
    "gn:timezone":"Europe/Oslo",
    "iso:country":"NO",
    "wof:name":"Vebostad",
    "wof:placetype":"locality"
},
  "geometry": {"coordinates":[16.13808,68.75239000000001],"type":"Point"}
}