{
  "type": "Feature",
  "properties": {
    "gn:admin1_code":"1.0",
    "gn:admin2_code":"237.0",
    "gn:asciiname":"Holstangen",
    "gn:country_code":"NO",
    "gn:dem":140,
    "gn:feature_class":"P",
    "gn:feature_code":"PPL",
    "gn:name":"Holstangen",
    "gn:population":0,
    "gn:timezone":"Europe/Oslo",
    "iso:country":"NO",
    "name:nor_x_preferred":[
        "Holstangen"
    ],
    "wof:name":"Holstangen",
    "wof:placetype":"neighbourhood"
},
  "geometry": {"coordinates":[11.24434,60.33028],"type":"Point"}
}