{
  "type": "Feature",
  "properties": {
    "gn:admin1_code":"21",
    "gn:admin2_code":"5004.0",
    "gn:asciiname":"Fossem",
    "gn:country_code":"NO",
    "gn:dem":18,
    "gn:feature_class":"P",
    "gn:feature_code":"PPL",
    "gn:name":"Fossem",
    "gn:population":0,
    "gn:timezone":"Europe/Oslo",
    "iso:country":"NO",
    "name:nor_x_preferred":[
        "Fossem"
    ],
    "wof:name":"Fossem",
    "wof:placetype":"locality"
},
  "geometry": {"coordinates":[11.60242,64.05274],"type":"Point"}
}