{
  "type": "Feature",
  "properties": {
    "gn:admin1_code":"14",
    "gn:admin2_code":"1103.0",
    "gn:asciiname":"Byhaugen",
    "gn:cc2":"NO",
    "gn:country_code":"NO",
    "gn:dem":15,
    "gn:feature_class":"P",
    "gn:feature_code":"PPL",
    "gn:name":"Byhaugen",
    "gn:population":0,
    "gn:timezone":"Europe/Oslo",
    "iso:country":"NO",
    "name:und_x_variant":[
        "Byhaug",
        "Byhaugen"
    ],
    "wof:name":"Byhaugen",
    "wof:placetype":"neighbourhood"
},
  "geometry": {"coordinates":[5.68333,58.96666999999999],"type":"Point"}
}