{
  "type": "Feature",
  "properties": {
    "gn:admin1_code":"20",
    "gn:admin2_code":"710.0",
    "gn:asciiname":"Lahelle",
    "gn:country_code":"NO",
    "gn:dem":10,
    "gn:feature_class":"P",
    "gn:feature_code":"PPL",
    "gn:name":"Lahelle",
    "gn:population":0,
    "gn:timezone":"Europe/Oslo",
    "iso:country":"NO",
    "wof:name":"Lahelle",
    "wof:placetype":"locality"
},
  "geometry": {"coordinates":[10.28339,59.1345],"type":"Point"}
}