{
  "type": "Feature",
  "properties": {
    "gn:admin1_code":"15",
    "gn:admin2_code":"1428.0",
    "gn:asciiname":"Grov",
    "gn:country_code":"NO",
    "gn:dem":3,
    "gn:feature_class":"P",
    "gn:feature_code":"PPL",
    "gn:name":"Grov",
    "gn:population":0,
    "gn:timezone":"Europe/Oslo",
    "iso:country":"NO",
    "name:ceb_x_preferred":[
        "Grov"
    ],
    "name:nor_x_preferred":[
        "Grov"
    ],
    "name:spa_x_preferred":[
        "Grov"
    ],
    "wof:name":"Grov",
    "wof:placetype":"locality"
},
  "geometry": {"coordinates":[5.01667,61.33333],"type":"Point"}
}