{
  "type": "Feature",
  "properties": {
    "gn:admin1_code":"14",
    "gn:admin2_code":"1141.0",
    "gn:asciiname":"Nesheimsviki",
    "gn:country_code":"NO",
    "gn:dem":36,
    "gn:feature_class":"P",
    "gn:feature_code":"PPL",
    "gn:name":"Nesheimsviki",
    "gn:population":0,
    "gn:timezone":"Europe/Oslo",
    "iso:country":"NO",
    "wof:name":"Nesheimsviki",
    "wof:placetype":"locality"
},
  "geometry": {"coordinates":[5.88333,59.26667],"type":"Point"}
}