{
  "type": "Feature",
  "properties": {
    "gn:admin1_code":"14",
    "gn:admin2_code":"1133.0",
    "gn:asciiname":"Ingvaldstad",
    "gn:country_code":"NO",
    "gn:dem":467,
    "gn:feature_class":"P",
    "gn:feature_code":"PPL",
    "gn:name":"Ingvaldstad",
    "gn:population":0,
    "gn:timezone":"Europe/Oslo",
    "iso:country":"NO",
    "wof:name":"Ingvaldstad",
    "wof:placetype":"locality"
},
  "geometry": {"coordinates":[6.16667,59.18333000000001],"type":"Point"}
}