{
  "type": "Feature",
  "properties": {
    "gn:admin1_code":"13.0",
    "gn:admin2_code":"136.0",
    "gn:asciiname":"Radeskogen",
    "gn:country_code":"NO",
    "gn:dem":40,
    "gn:feature_class":"P",
    "gn:feature_code":"PPL",
    "gn:name":"R\u00e5deskogen",
    "gn:population":0,
    "gn:timezone":"Europe/Oslo",
    "iso:country":"NO",
    "name:nor_x_preferred":[
        "R\u00e5deskogen"
    ],
    "wof:name":"Radeskogen",
    "wof:placetype":"locality"
},
  "geometry": {"coordinates":[10.76672,59.39226],"type":"Point"}
}