{
  "type": "Feature",
  "properties": {
    "gn:admin1_code":"7",
    "gn:admin2_code":"1231.0",
    "gn:asciiname":"Indre Alsaker",
    "gn:cc2":"NO",
    "gn:country_code":"NO",
    "gn:dem":330,
    "gn:feature_class":"P",
    "gn:feature_code":"PPL",
    "gn:name":"Indre Als\u00e5ker",
    "gn:population":0,
    "gn:timezone":"Europe/Oslo",
    "iso:country":"NO",
    "name:und_x_variant":[
        "Indre Alsaaker",
        "Indre Als\u00e5ker"
    ],
    "wof:name":"Indre Alsaker",
    "wof:placetype":"locality"
},
  "geometry": {"coordinates":[6.50324,60.39745],"type":"Point"}
}