{
  "type": "Feature",
  "properties": {
    "gn:admin1_code":"1",
    "gn:admin2_code":"211.0",
    "gn:asciiname":"Hvitsten",
    "gn:cc2":"NO",
    "gn:country_code":"NO",
    "gn:dem":8,
    "gn:feature_class":"P",
    "gn:feature_code":"PPL",
    "gn:name":"Hvitsten",
    "gn:population":0,
    "gn:timezone":"Europe/Oslo",
    "iso:country":"NO",
    "name:und_x_variant":[
        "Hvitstein",
        "Hvitsen",
        "Hvitsten"
    ],
    "wof:name":"Hvitsten",
    "wof:placetype":"locality"
},
  "geometry": {"coordinates":[10.65545,59.59863000000001],"type":"Point"}
}