{
  "type": "Feature",
  "properties": {
    "gn:admin1_code":"18.0",
    "gn:admin2_code":"1903.0",
    "gn:asciiname":"Yttersundsvoll",
    "gn:country_code":"NO",
    "gn:dem":7,
    "gn:feature_class":"P",
    "gn:feature_code":"PPL",
    "gn:name":"Yttersundsvoll",
    "gn:population":0,
    "gn:timezone":"Europe/Oslo",
    "iso:country":"NO",
    "name:nor_x_preferred":[
        "Yttersundsvoll"
    ],
    "wof:name":"Yttersundsvoll",
    "wof:placetype":"locality"
},
  "geometry": {"coordinates":[16.50644,69.01810999999999],"type":"Point"}
}