{
  "type": "Feature",
  "properties": {
    "gn:admin1_code":"21",
    "gn:admin2_code":"5001",
    "gn:asciiname":"Lilleby",
    "gn:country_code":"NO",
    "gn:dem":36,
    "gn:feature_class":"P",
    "gn:feature_code":"PPLL",
    "gn:name":"Lilleby",
    "gn:population":0,
    "gn:timezone":"Europe/Oslo",
    "iso:country":"NO",
    "name:nor_x_preferred":[
        "Lilleby"
    ],
    "wof:name":"Lilleby",
    "wof:placetype":"locality"
},
  "geometry": {"coordinates":[10.43399,63.44095],"type":"Point"}
}