{
  "type": "Feature",
  "properties": {
    "gn:admin1_code":"21",
    "gn:admin2_code":"5013.0",
    "gn:asciiname":"Barman",
    "gn:country_code":"NO",
    "gn:dem":3,
    "gn:feature_class":"P",
    "gn:feature_code":"PPL",
    "gn:name":"Barman",
    "gn:population":0,
    "gn:timezone":"Europe/Oslo",
    "iso:country":"NO",
    "name:nor_x_preferred":[
        "Barman"
    ],
    "wof:name":"Barman",
    "wof:placetype":"locality"
},
  "geometry": {"coordinates":[8.85,63.63333000000001],"type":"Point"}
}