{
  "type": "Feature",
  "properties": {
    "gn:admin1_code":"9",
    "gn:admin2_code":"1837.0",
    "gn:asciiname":"Haugvik",
    "gn:cc2":"NO",
    "gn:country_code":"NO",
    "gn:dem":-9999,
    "gn:feature_class":"P",
    "gn:feature_code":"PPL",
    "gn:name":"Haugvik",
    "gn:population":0,
    "gn:timezone":"Europe/Oslo",
    "iso:country":"NO",
    "name:und_x_variant":[
        "Glomfjord",
        "Haugvik"
    ],
    "wof:name":"Haugvik",
    "wof:placetype":"locality"
},
  "geometry": {"coordinates":[13.94598,66.81614],"type":"Point"}
}