{
  "type": "Feature",
  "properties": {
    "gn:admin1_code":"21",
    "gn:admin2_code":"5054.0",
    "gn:asciiname":"Frengen",
    "gn:country_code":"NO",
    "gn:dem":60,
    "gn:feature_class":"P",
    "gn:feature_code":"PPL",
    "gn:name":"Frengen",
    "gn:population":0,
    "gn:timezone":"Europe/Oslo",
    "iso:country":"NO",
    "wof:name":"Frengen",
    "wof:placetype":"locality"
},
  "geometry": {"coordinates":[9.91414,63.69642],"type":"Point"}
}