{
  "type": "Feature",
  "properties": {
    "gn:admin1_code":"7.0",
    "gn:admin2_code":"1251.0",
    "gn:asciiname":"Dalegarden",
    "gn:country_code":"NO",
    "gn:dem":40,
    "gn:feature_class":"P",
    "gn:feature_code":"PPL",
    "gn:name":"Dalegarden",
    "gn:population":0,
    "gn:timezone":"Europe/Oslo",
    "iso:country":"NO",
    "name:jav_x_preferred":[
        "Dalegarden"
    ],
    "name:msa_x_preferred":[
        "Dalegarden"
    ],
    "name:nor_x_preferred":[
        "Dalegarden"
    ],
    "wof:name":"Dalegarden",
    "wof:placetype":"locality"
},
  "geometry": {"coordinates":[5.79376,60.58119],"type":"Point"}
}