{
  "type": "Feature",
  "properties": {
    "gn:admin1_code":"9",
    "gn:admin2_code":"1825.0",
    "gn:asciiname":"Fallmoen",
    "gn:cc2":"NO",
    "gn:country_code":"NO",
    "gn:dem":220,
    "gn:feature_class":"P",
    "gn:feature_code":"PPL",
    "gn:name":"Fallmoen",
    "gn:population":0,
    "gn:timezone":"Europe/Oslo",
    "iso:country":"NO",
    "name:und_x_variant":[
        "Faldmoen",
        "Fallmoen"
    ],
    "wof:name":"Fallmoen",
    "wof:placetype":"locality"
},
  "geometry": {"coordinates":[13.28333,65.68333],"type":"Point"}
}