{
  "type": "Feature",
  "properties": {
    "gn:admin1_code":"13.0",
    "gn:admin2_code":"106.0",
    "gn:asciiname":"Kuhaugen",
    "gn:country_code":"NO",
    "gn:dem":31,
    "gn:feature_class":"P",
    "gn:feature_code":"PPL",
    "gn:name":"Kuhaugen",
    "gn:population":0,
    "gn:timezone":"Europe/Oslo",
    "iso:country":"NO",
    "name:nor_x_preferred":[
        "Kuhaugen"
    ],
    "wof:name":"Kuhaugen",
    "wof:placetype":"locality"
},
  "geometry": {"coordinates":[11.07545,59.18261999999999],"type":"Point"}
}