{
  "type": "Feature",
  "properties": {
    "gn:admin1_code":"11.0",
    "gn:admin2_code":"522.0",
    "gn:asciiname":"Storfjellroa",
    "gn:country_code":"NO",
    "gn:dem":1000,
    "gn:feature_class":"P",
    "gn:feature_code":"PPL",
    "gn:name":"Storfjellroa",
    "gn:population":0,
    "gn:timezone":"Europe/Oslo",
    "iso:country":"NO",
    "name:nor_x_preferred":[
        "Storfjellroa"
    ],
    "wof:name":"Storfjellroa",
    "wof:placetype":"locality"
},
  "geometry": {"coordinates":[9.63966,61.38535],"type":"Point"}
}