{
  "type": "Feature",
  "properties": {
    "gn:admin1_code":"11.0",
    "gn:admin2_code":"502.0",
    "gn:asciiname":"Stokke",
    "gn:country_code":"NO",
    "gn:dem":220,
    "gn:feature_class":"P",
    "gn:feature_code":"PPL",
    "gn:name":"Stokke",
    "gn:population":0,
    "gn:timezone":"Europe/Oslo",
    "iso:country":"NO",
    "wof:name":"Stokke",
    "wof:placetype":"locality"
},
  "geometry": {"coordinates":[10.66667,60.88333000000001],"type":"Point"}
}