{
  "type": "Feature",
  "properties": {
    "gn:admin1_code":"11.0",
    "gn:admin2_code":"534.0",
    "gn:asciiname":"Granavollen",
    "gn:country_code":"NO",
    "gn:dem":310,
    "gn:feature_class":"P",
    "gn:feature_code":"PPL",
    "gn:name":"Granavollen",
    "gn:population":0,
    "gn:timezone":"Europe/Oslo",
    "iso:country":"NO",
    "name:nor_x_preferred":[
        "Granavollen"
    ],
    "wof:name":"Granavollen",
    "wof:placetype":"locality"
},
  "geometry": {"coordinates":[10.52861,60.36682],"type":"Point"}
}