{
  "type": "Feature",
  "properties": {
    "gn:admin1_code":"2",
    "gn:admin2_code":"906.0",
    "gn:asciiname":"Nordstrand",
    "gn:country_code":"NO",
    "gn:dem":42,
    "gn:feature_class":"P",
    "gn:feature_code":"PPL",
    "gn:name":"Nordstrand",
    "gn:population":0,
    "gn:timezone":"Europe/Oslo",
    "iso:country":"NO",
    "name:ara_x_preferred":[
        "\u0646\u0648\u0631\u062f\u0633\u062a\u0631\u0627\u0646\u062f"
    ],
    "name:ceb_x_preferred":[
        "Nordstrand"
    ],
    "name:deu_x_preferred":[
        "Nordstrand"
    ],
    "name:nld_x_preferred":[
        "Nordstrand"
    ],
    "name:nor_x_preferred":[
        "Nordstrand"
    ],
    "name:pol_x_preferred":[
        "Nordstrand"
    ],
    "name:slv_x_preferred":[
        "Nordstrand"
    ],
    "name:swe_x_preferred":[
        "Nordstrand"
    ],
    "wof:name":"Nordstrand",
    "wof:placetype":"locality"
},
  "geometry": {"coordinates":[8.94417,58.52694],"type":"Point"}
}