{
  "type": "Feature",
  "properties": {
    "gn:admin1_code":"5.0",
    "gn:admin2_code":"2012.0",
    "gn:asciiname":"Nygard",
    "gn:country_code":"NO",
    "gn:dem":100,
    "gn:feature_class":"P",
    "gn:feature_code":"PPL",
    "gn:name":"Nyg\u00e5rd",
    "gn:population":0,
    "gn:timezone":"Europe/Oslo",
    "iso:country":"NO",
    "name:nor_x_preferred":[
        "Nyg\u00e5rd"
    ],
    "wof:name":"Nygard",
    "wof:placetype":"locality"
},
  "geometry": {"coordinates":[23.37646,70.26543000000001],"type":"Point"}
}