{
  "type": "Feature",
  "properties": {
    "gn:country":"NO",
    "gn:fcode":"PPL",
    "gn:population":334,
    "iso:country":"NO",
    "qs_pg:aaroncc":"NO",
    "qs_pg:gn_country":"NO",
    "qs_pg:gn_fcode":"PPL",
    "qs_pg:gn_pop":334,
    "qs_pg:name":"Skogrand",
    "qs_pg:name_adm0":"Norge",
    "qs_pg:name_adm1":"Akershus Fylke",
    "qs_pg:photos":17,
    "qs_pg:photos_1k":3,
    "qs_pg:photos_9k":1,
    "qs_pg:photos_9r":1,
    "qs_pg:photos_all":17,
    "qs_pg:photos_sr":1,
    "qs_pg:pop_sr":2,
    "qs_pg:qs_pg_placetype":"locality",
    "qs_pg:qs_pg_placetype_gp":"Town",
    "qs_pg:woe_adm0":23424910,
    "woe:adm0_id":23424910,
    "woe:name_adm0":"Norge",
    "woe:name_adm1":"Akershus Fylke",
    "woe:placetype":"Town",
    "wof:name":"Skogrand",
    "wof:placetype":"locality",
    "wof:population":334
},
  "geometry": {"coordinates":[11.52346,60.23231],"type":"Point"}
}