{
  "type": "Feature",
  "properties": {
    "gn:admin1_code":"18",
    "gn:admin2_code":"1933.0",
    "gn:asciiname":"Kjerkevik",
    "gn:cc2":"NO",
    "gn:country_code":"NO",
    "gn:dem":27,
    "gn:feature_class":"P",
    "gn:feature_code":"PPL",
    "gn:name":"Kjerkevik",
    "gn:population":0,
    "gn:timezone":"Europe/Oslo",
    "iso:country":"NO",
    "name:und_x_variant":[
        "Kirkevik",
        "Kjerkevik"
    ],
    "wof:name":"Kjerkevik",
    "wof:placetype":"locality"
},
  "geometry": {"coordinates":[18.75,69.31667],"type":"Point"}
}