{
  "type": "Feature",
  "properties": {
    "gn:admin1_code":"2.0",
    "gn:admin2_code":"929.0",
    "gn:asciiname":"Rostveit",
    "gn:country_code":"NO",
    "gn:dem":261,
    "gn:feature_class":"P",
    "gn:feature_code":"PPL",
    "gn:name":"Rostveit",
    "gn:population":0,
    "gn:timezone":"Europe/Oslo",
    "iso:country":"NO",
    "wof:name":"Rostveit",
    "wof:placetype":"locality"
},
  "geometry": {"coordinates":[8.36667,58.71666999999999],"type":"Point"}
}