{
  "type": "Feature",
  "properties": {
    "gn:admin1_code":"18.0",
    "gn:admin2_code":"1931.0",
    "gn:asciiname":"Olsborg",
    "gn:cc2":"NO",
    "gn:country_code":"NO",
    "gn:dem":1,
    "gn:feature_class":"P",
    "gn:feature_code":"PPL",
    "gn:name":"Olsborg",
    "gn:population":0,
    "gn:timezone":"Europe/Oslo",
    "iso:country":"NO",
    "name:und_x_variant":[
        "Olborg",
        "Olsborg"
    ],
    "wof:name":"Olsborg",
    "wof:placetype":"locality"
},
  "geometry": {"coordinates":[17.95722,69.255],"type":"Point"}
}