{
  "type": "Feature",
  "properties": {
    "gn:admin1_code":"5",
    "gn:admin2_code":"2012",
    "gn:asciiname":"Jemmeluft",
    "gn:country_code":"NO",
    "gn:dem":56,
    "gn:feature_class":"P",
    "gn:feature_code":"PPLL",
    "gn:name":"Jemmeluft",
    "gn:population":0,
    "gn:timezone":"Europe/Oslo",
    "iso:country":"NO",
    "name:nor_x_preferred":[
        "Jemmeluft"
    ],
    "name:nor_x_variant":[
        "Hjemmeluft"
    ],
    "wof:name":"Jemmeluft",
    "wof:placetype":"locality"
},
  "geometry": {"coordinates":[23.18799,69.94591],"type":"Point"}
}