{
  "type": "Feature",
  "properties": {
    "gn:admin1_code":"9",
    "gn:admin2_code":"1837.0",
    "gn:asciiname":"Mesoy",
    "gn:cc2":"NO",
    "gn:country_code":"NO",
    "gn:dem":-9999,
    "gn:feature_class":"P",
    "gn:feature_code":"PPL",
    "gn:name":"Mes\u00f8y",
    "gn:population":0,
    "gn:timezone":"Europe/Oslo",
    "iso:country":"NO",
    "name:und_x_variant":[
        "Mes\u00f6en",
        "Mes\u00f8y"
    ],
    "wof:name":"Mesoy",
    "wof:placetype":"locality"
},
  "geometry": {"coordinates":[13.63333,66.86667],"type":"Point"}
}