{
  "type": "Feature",
  "properties": {
    "gn:gn_country":"NO",
    "gn:gn_fcode":"PPL",
    "gn:gn_pop":0,
    "iso:country":"NO",
    "name:eng_x_preferred":[
        "Rinnan"
    ],
    "name:fra_x_preferred":[
        "Rinnan"
    ],
    "name:jav_x_preferred":[
        "Rinnan"
    ],
    "name:msa_x_preferred":[
        "Rinnan"
    ],
    "name:nld_x_preferred":[
        "Rinnan"
    ],
    "name:unk_x_variant":[
        "Rindan"
    ],
    "qs_pg:aaroncc":"NO",
    "qs_pg:gn_country":"NO",
    "qs_pg:gn_fcode":"PPL",
    "qs_pg:gn_pop":0,
    "qs_pg:name":"Rinnan",
    "qs_pg:name_adm0":"Norge",
    "qs_pg:name_adm1":"Nord-Tr\u00f8ndelag Fylke",
    "qs_pg:photos":102,
    "qs_pg:photos_1k":21,
    "qs_pg:photos_9k":1,
    "qs_pg:photos_9r":3,
    "qs_pg:photos_all":102,
    "qs_pg:photos_sr":3,
    "qs_pg:pop_sr":0,
    "qs_pg:qs_pg_placetype":"locality",
    "qs_pg:qs_pg_placetype_gp":"Town",
    "qs_pg:woe_adm0":23424910,
    "woe:adm0_id":23424910,
    "woe:name_adm0":"Norge",
    "woe:name_adm1":"Nord-Tr\u00f8ndelag Fylke",
    "woe:placetype":"Town",
    "wof:name":"Rinnan",
    "wof:placetype":"locality"
},
  "geometry": {"coordinates":[11.43333,63.76667],"type":"Point"}
}