{
  "type": "Feature",
  "properties": {
    "iso:country":"NO",
    "name:eng_x_preferred":[
        "Oldedalen"
    ],
    "name:est_x_preferred":[
        "Oldedalen"
    ],
    "name:fin_x_preferred":[
        "Oldedalen"
    ],
    "name:nob_x_preferred":[
        "Oldedalen"
    ],
    "name:swe_x_preferred":[
        "Oldedalen"
    ],
    "name:tur_x_preferred":[
        "Oldedalen"
    ],
    "qs_pg:aaroncc":"NO",
    "qs_pg:name":"Oldedalen",
    "qs_pg:name_adm0":"Norge",
    "qs_pg:name_adm1":"Sogn og Fjordane Fylke",
    "qs_pg:photos":541,
    "qs_pg:photos_1k":110,
    "qs_pg:photos_9k":2,
    "qs_pg:photos_9r":5,
    "qs_pg:photos_all":541,
    "qs_pg:photos_sr":7,
    "qs_pg:pop_sr":0,
    "qs_pg:qs_pg_placetype":"locality",
    "qs_pg:qs_pg_placetype_gp":"Town",
    "qs_pg:woe_adm0":23424910,
    "woe:adm0_id":23424910,
    "woe:name_adm0":"Norge",
    "woe:name_adm1":"Sogn og Fjordane Fylke",
    "woe:placetype":"Town",
    "wof:name":"Oldedalen",
    "wof:placetype":"locality"
},
  "geometry": {"coordinates":[6.824054,61.670968],"type":"Point"}
}