{
  "type": "Feature",
  "properties": {
    "gn:admin1_code":"21",
    "gn:admin2_code":"5050.0",
    "gn:asciiname":"Lauvoyvagen",
    "gn:cc2":"NO",
    "gn:country_code":"NO",
    "gn:dem":1,
    "gn:feature_class":"P",
    "gn:feature_code":"PPL",
    "gn:name":"Lauv\u00f8yv\u00e5gen",
    "gn:population":0,
    "gn:timezone":"Europe/Oslo",
    "iso:country":"NO",
    "name:und_x_variant":[
        "Lauv\u00f6yv\u00e5g",
        "Lauv\u00f8yv\u00e5gen"
    ],
    "wof:name":"Lauvoyvagen",
    "wof:placetype":"locality"
},
  "geometry": {"coordinates":[11.31667,64.91667],"type":"Point"}
}