{
  "type": "Feature",
  "properties": {
    "gn:admin1_code":"9",
    "gn:admin2_code":"1840.0",
    "gn:asciiname":"Evenesdal",
    "gn:cc2":"NO",
    "gn:country_code":"NO",
    "gn:dem":360,
    "gn:feature_class":"P",
    "gn:feature_code":"PPL",
    "gn:name":"Evenesdal",
    "gn:population":0,
    "gn:timezone":"Europe/Oslo",
    "iso:country":"NO",
    "name:und_x_variant":[
        "Evenesdalen",
        "Evenesdal"
    ],
    "wof:name":"Evenesdal",
    "wof:placetype":"locality"
},
  "geometry": {"coordinates":[15.45,66.93333],"type":"Point"}
}