{
  "type": "Feature",
  "properties": {
    "gn:admin1_code":"20",
    "gn:admin2_code":"729",
    "gn:asciiname":"Hjemseng",
    "gn:country_code":"NO",
    "gn:dem":11,
    "gn:feature_class":"P",
    "gn:feature_code":"PPL",
    "gn:name":"Hjemseng",
    "gn:population":0,
    "gn:timezone":"Europe/Oslo",
    "iso:country":"NO",
    "name:nor_x_preferred":[
        "Hjemseng"
    ],
    "wof:name":"Hjemseng",
    "wof:placetype":"locality"
},
  "geometry": {"coordinates":[10.44049,59.22247],"type":"Point"}
}