{
  "type": "Feature",
  "properties": {
    "gn:admin1_code":"1.0",
    "gn:admin2_code":"214.0",
    "gn:asciiname":"Blafjellet",
    "gn:country_code":"NO",
    "gn:dem":107,
    "gn:feature_class":"P",
    "gn:feature_code":"PPL",
    "gn:name":"Bl\u00e5fjellet",
    "gn:population":0,
    "gn:timezone":"Europe/Oslo",
    "iso:country":"NO",
    "name:nor_x_preferred":[
        "Bl\u00e5fjellet"
    ],
    "wof:name":"Blafjellet",
    "wof:placetype":"locality"
},
  "geometry": {"coordinates":[10.80239,59.65415],"type":"Point"}
}