{
  "type": "Feature",
  "properties": {
    "gn:admin1_code":"6",
    "gn:admin2_code":"402.0",
    "gn:asciiname":"Kjerkhus",
    "gn:cc2":"NO",
    "gn:country_code":"NO",
    "gn:dem":170,
    "gn:feature_class":"P",
    "gn:feature_code":"PPL",
    "gn:name":"Kjerkhus",
    "gn:population":0,
    "gn:timezone":"Europe/Oslo",
    "iso:country":"NO",
    "name:und_x_variant":[
        "Kirkhus",
        "Kjerkhus"
    ],
    "wof:name":"Kjerkhus",
    "wof:placetype":"locality"
},
  "geometry": {"coordinates":[12.01667,60.33333],"type":"Point"}
}