{
  "type": "Feature",
  "properties": {
    "iso:country":"NO",
    "name:ceb_x_preferred":[
        "F\u00f8rde Airport"
    ],
    "name:dan_x_preferred":[
        "F\u00f8rde Lufthavn"
    ],
    "name:deu_x_preferred":[
        "Flughafen F\u00f8rde"
    ],
    "name:eng_x_preferred":[
        "F\u00f8rde Airport"
    ],
    "name:eng_x_variant":[
        "FDE",
        "ENBL"
    ],
    "name:fas_x_preferred":[
        "\u0641\u0631\u0648\u062f\u06af\u0627\u0647 \u0641\u0631\u0648\u062f\u0647\u060c \u0628\u0631\u06cc\u0646\u06af\u0644\u0646\u062f"
    ],
    "name:fas_x_variant":[
        "\u0641\u0631\u0648\u062f\u06af\u0627\u0647 \u0641\u0631\u0648\u062f\u0647"
    ],
    "name:msa_x_preferred":[
        "Lapangan Terbang Bringeland"
    ],
    "name:nld_x_preferred":[
        "Luchthaven F\u00f8rde Bringeland"
    ],
    "name:nno_x_preferred":[
        "F\u00f8rde lufthamn"
    ],
    "name:nob_x_preferred":[
        "F\u00f8rde lufthamn"
    ],
    "name:nor_x_preferred":[
        "F\u00f8rde lufthamn"
    ],
    "name:pol_x_preferred":[
        "Port lotniczy F\u00f8rde"
    ],
    "name:ron_x_preferred":[
        "Aeroportul F\u00f8rde"
    ],
    "name:spa_x_preferred":[
        "Aeropuerto de F\u00f8rde-Bringeland"
    ],
    "name:swe_x_preferred":[
        "F\u00f8rde flygplats"
    ],
    "name:tgk_x_preferred":[
        "\u0424\u0443\u0440\u0443\u0434\u0433\u043e\u04b3\u0438 \u0444\u0440\u0443\u0434\u04b3"
    ],
    "name:vie_x_preferred":[
        "S\u00e2n bay F\u00f8rde"
    ],
    "name:zho_x_preferred":[
        "\u5f17\u52d2Bringeland\u6a5f\u5834"
    ],
    "oa:elevation_ft":"1046",
    "oa:type":"small_airport",
    "wd:wordcount":1217,
    "woe:hierarchy":{
        "country_id":23424910,
        "county_id":12592844,
        "planet_id":1,
        "state_id":2346398
    },
    "wof:name":"F\u00f8rde lufthamn Bringeland",
    "wof:placetype":"campus"
},
  "geometry": {"coordinates":[5.756944,61.391111],"type":"Point"}
}