{
  "type": "Feature",
  "properties": {
    "gn:gn_country":"NO",
    "gn:gn_fcode":"PPL",
    "gn:gn_pop":0,
    "iso:country":"NO",
    "name:dan_x_preferred":[
        "Son"
    ],
    "name:dut_x_preferred":[
        "Son"
    ],
    "name:eng_x_preferred":[
        "Son"
    ],
    "name:fre_x_preferred":[
        "Son"
    ],
    "name:ita_x_preferred":[
        "Son"
    ],
    "name:jav_x_preferred":[
        "Son"
    ],
    "name:may_x_preferred":[
        "Son"
    ],
    "name:nno_x_preferred":[
        "Son"
    ],
    "name:nob_x_preferred":[
        "Son"
    ],
    "name:spa_x_preferred":[
        "Son"
    ],
    "name:swe_x_preferred":[
        "Son"
    ],
    "name:unk_x_variant":[
        "Soon"
    ],
    "qs_pg:aaroncc":"NO",
    "qs_pg:gn_country":"NO",
    "qs_pg:gn_fcode":"PPL",
    "qs_pg:gn_pop":0,
    "qs_pg:name":"Son",
    "qs_pg:name_adm0":"Norge",
    "qs_pg:name_adm1":"Akershus Fylke",
    "qs_pg:photos":550,
    "qs_pg:photos_1k":111,
    "qs_pg:photos_9k":2,
    "qs_pg:photos_9r":5,
    "qs_pg:photos_all":550,
    "qs_pg:photos_sr":7,
    "qs_pg:pop_sr":0,
    "qs_pg:qs_pg_placetype":"locality",
    "qs_pg:qs_pg_placetype_gp":"Town",
    "qs_pg:woe_adm0":23424910,
    "woe:adm0_id":23424910,
    "woe:name_adm0":"Norge",
    "woe:name_adm1":"Akershus Fylke",
    "woe:placetype":"Town",
    "wof:name":"Son",
    "wof:placetype":"locality"
},
  "geometry": {"coordinates":[10.68917,59.52306],"type":"Point"}
}