{
  "type": "Feature",
  "properties": {
    "gn:admin1_code":"21.0",
    "gn:admin2_code":"5005.0",
    "gn:asciiname":"Saevik",
    "gn:cc2":"NO",
    "gn:country_code":"NO",
    "gn:dem":60,
    "gn:feature_class":"P",
    "gn:feature_code":"PPL",
    "gn:name":"S\u00e6vik",
    "gn:population":0,
    "gn:timezone":"Europe/Oslo",
    "iso:country":"NO",
    "name:und_x_variant":[
        "Sevik",
        "S\u00e6vik"
    ],
    "name:urd_x_preferred":[
        "\u0633\u0627\u0648\u06a9"
    ],
    "wof:name":"Saevik",
    "wof:placetype":"locality"
},
  "geometry": {"coordinates":[11.48333,64.43333],"type":"Point"}
}