{
  "type": "Feature",
  "properties": {
    "iso:country":"NO",
    "name:deu_x_preferred":[
        "Buvika/Ilhaugen"
    ],
    "name:eng_x_preferred":[
        "Buvika/Ilhaugen"
    ],
    "name:fra_x_preferred":[
        "Buvika/Ilhaugen"
    ],
    "name:nld_x_preferred":[
        "Buvika/Ilhaugen"
    ],
    "name:nno_x_preferred":[
        "Buvika/Ilhaugen"
    ],
    "name:nob_x_preferred":[
        "Buvika/Ilhaugen"
    ],
    "name:ron_x_preferred":[
        "Buvika/Ilhaugen"
    ],
    "name:und_x_variant":[
        "Buviken"
    ],
    "qs:a0":"Norge",
    "qs:a1":"*S\u00f8r-Tr\u00f8ndelag",
    "qs:a1r":"0",
    "qs:adm0":"Norge",
    "qs:la_lc":"*",
    "qs:level":"locality",
    "qs:loc":"Buvika/Ilhaugen",
    "qs:loc_alt":"Buvika/Ilhaugen",
    "qs:pop":0,
    "qs:type":"buffered point",
    "wof:name":"Buvika/Ilhaugen",
    "wof:placetype":"locality"
},
  "geometry": {"coordinates":[10.169455,63.309281],"type":"Point"}
}