{
  "type": "Feature",
  "properties": {
    "gn:admin1_code":"18",
    "gn:admin2_code":"1924.0",
    "gn:asciiname":"Divimoen",
    "gn:cc2":"NO",
    "gn:country_code":"NO",
    "gn:dem":100,
    "gn:feature_class":"P",
    "gn:feature_code":"PPL",
    "gn:name":"Divimoen",
    "gn:population":0,
    "gn:timezone":"Europe/Oslo",
    "iso:country":"NO",
    "name:und_x_variant":[
        "Divimo",
        "Divimoen"
    ],
    "wof:name":"Divimoen",
    "wof:placetype":"locality"
},
  "geometry": {"coordinates":[19.45,69.01666999999999],"type":"Point"}
}