{
  "type": "Feature",
  "properties": {
    "gn:admin1_code":"20",
    "gn:admin2_code":"712",
    "gn:asciiname":"Verningen",
    "gn:country_code":"NO",
    "gn:dem":83,
    "gn:feature_class":"P",
    "gn:feature_code":"PPL",
    "gn:name":"Verningen",
    "gn:population":0,
    "gn:timezone":"Europe/Oslo",
    "iso:country":"NO",
    "name:nld_x_preferred":[
        "Verningen"
    ],
    "name:nno_x_preferred":[
        "Verningen"
    ],
    "name:nor_x_preferred":[
        "Verningen"
    ],
    "name:ron_x_preferred":[
        "Verningen"
    ],
    "name:spa_x_preferred":[
        "Verningen"
    ],
    "wof:name":"Verningen",
    "wof:placetype":"locality"
},
  "geometry": {"coordinates":[10.10208,59.09212],"type":"Point"}
}