{
  "type": "Feature",
  "properties": {
    "gn:admin1_code":"8.0",
    "gn:admin2_code":"1557.0",
    "gn:asciiname":"Stokke",
    "gn:country_code":"NO",
    "gn:dem":1,
    "gn:feature_class":"P",
    "gn:feature_code":"PPL",
    "gn:name":"Stokke",
    "gn:population":0,
    "gn:timezone":"Europe/Oslo",
    "iso:country":"NO",
    "wof:name":"Stokke",
    "wof:placetype":"locality"
},
  "geometry": {"coordinates":[7.68333,62.96666999999999],"type":"Point"}
}