{
  "type": "Feature",
  "properties": {
    "gn:admin1_code":"8.0",
    "gn:admin2_code":"1557.0",
    "gn:asciiname":"Stokke",
    "gn:country_code":"NO",
    "gn:dem":1,
    "gn:feature_class":"P",
    "gn:feature_code":"PPL",
    "gn:name":"Stokke",
    "gn:population":0,
    "gn:timezone":"Europe/Oslo",
    "iso:country":"NO",
    "name:bar_x_preferred":[
        "Stokke"
    ],
    "name:bpy_x_preferred":[
        "\u09b8\u09cd\u099f\u09cb\u0995\u09cd\u0995\u09c7"
    ],
    "name:cat_x_preferred":[
        "Stokke"
    ],
    "name:ceb_x_preferred":[
        "Stokke"
    ],
    "name:dan_x_preferred":[
        "Stokke"
    ],
    "name:deu_x_preferred":[
        "Stokke"
    ],
    "name:epo_x_preferred":[
        "Stokke"
    ],
    "name:eus_x_preferred":[
        "Stokke"
    ],
    "name:fin_x_preferred":[
        "Stokke"
    ],
    "name:fra_x_preferred":[
        "Stokke"
    ],
    "name:ita_x_preferred":[
        "Stokke"
    ],
    "name:lat_x_preferred":[
        "Stokke"
    ],
    "name:lim_x_preferred":[
        "Stokke"
    ],
    "name:nds_x_preferred":[
        "Kommun Stokke"
    ],
    "name:nld_x_preferred":[
        "Stokke"
    ],
    "name:nno_x_preferred":[
        "Stokke"
    ],
    "name:nor_x_preferred":[
        "Stokke"
    ],
    "name:pol_x_preferred":[
        "Stokke"
    ],
    "name:por_x_preferred":[
        "Stokke"
    ],
    "name:ron_x_preferred":[
        "Stokke"
    ],
    "name:rus_x_preferred":[
        "\u0421\u0442\u043e\u043a\u043a\u0435"
    ],
    "name:sme_x_preferred":[
        "Stokke"
    ],
    "name:spa_x_preferred":[
        "Stokke"
    ],
    "name:sqi_x_preferred":[
        "Stokke"
    ],
    "name:swe_x_preferred":[
        "Stokke kommun"
    ],
    "name:vie_x_preferred":[
        "Stokke"
    ],
    "name:war_x_preferred":[
        "Stokke"
    ],
    "name:zho_x_preferred":[
        "\u65af\u6258\u514b"
    ],
    "wof:name":"Stokke",
    "wof:placetype":"locality"
},
  "geometry": {"coordinates":[7.68333,62.96666999999999],"type":"Point"}
}