{
  "type": "Feature",
  "properties": {
    "gn:admin1_code":"5.0",
    "gn:admin2_code":"2025.0",
    "gn:asciiname":"Garggogeahci",
    "gn:country_code":"NO",
    "gn:dem":-9999,
    "gn:feature_class":"P",
    "gn:feature_code":"PPL",
    "gn:name":"G\u00e1rggogeah\u010di",
    "gn:population":0,
    "gn:timezone":"Europe/Oslo",
    "iso:country":"NO",
    "name:sme_x_preferred":[
        "G\u00e1rggogeah\u010di"
    ],
    "wof:name":"Garggogeahci",
    "wof:placetype":"locality"
},
  "geometry": {"coordinates":[27.87061,70.45854],"type":"Point"}
}