{
  "type": "Feature",
  "properties": {
    "gn:admin1_code":"5.0",
    "gn:admin2_code":"2018.0",
    "gn:asciiname":"Gappi",
    "gn:country_code":"NO",
    "gn:dem":-9999,
    "gn:feature_class":"P",
    "gn:feature_code":"PPL",
    "gn:name":"G\u00e5ppi",
    "gn:population":0,
    "gn:timezone":"Europe/Oslo",
    "iso:country":"NO",
    "name:nor_x_preferred":[
        "Latteren"
    ],
    "name:nor_x_variant":[
        "Latter"
    ],
    "name:sme_x_preferred":[
        "G\u00e5ppi"
    ],
    "name:sme_x_variant":[
        "Lattar",
        "Gohppi",
        "L\u00e1htt\u00e1r"
    ],
    "wof:name":"Gappi",
    "wof:placetype":"locality"
},
  "geometry": {"coordinates":[24.57878,70.71429999999999],"type":"Point"}
}