{
  "type": "Feature",
  "properties": {
    "gn:admin1_code":"18.0",
    "gn:admin2_code":"1943.0",
    "gn:asciiname":"Leirbukt",
    "gn:country_code":"NO",
    "gn:dem":7,
    "gn:feature_class":"P",
    "gn:feature_code":"PPL",
    "gn:name":"Leirbukt",
    "gn:population":0,
    "gn:timezone":"Europe/Oslo",
    "iso:country":"NO",
    "name:nor_x_preferred":[
        "Leirbukt"
    ],
    "wof:name":"Leirbukt",
    "wof:placetype":"locality"
},
  "geometry": {"coordinates":[22.01114,69.73671],"type":"Point"}
}