{
  "type": "Feature",
  "properties": {
    "gn:admin1_code":"9.0",
    "gn:admin2_code":"1849.0",
    "gn:asciiname":"Straumshamn",
    "gn:country_code":"NO",
    "gn:dem":1,
    "gn:feature_class":"P",
    "gn:feature_code":"PPL",
    "gn:name":"Straumshamn",
    "gn:population":0,
    "gn:timezone":"Europe/Oslo",
    "iso:country":"NO",
    "name:jav_x_preferred":[
        "Straumshamn"
    ],
    "name:msa_x_preferred":[
        "Straumshamn"
    ],
    "wof:name":"Straumshamn",
    "wof:placetype":"locality"
},
  "geometry": {"coordinates":[15.37983,68.1061],"type":"Point"}
}