{
  "type": "Feature",
  "properties": {
    "gn:admin1_code":"4",
    "gn:admin2_code":"605.0",
    "gn:asciiname":"Brekkebygda",
    "gn:country_code":"NO",
    "gn:dem":310,
    "gn:feature_class":"P",
    "gn:feature_code":"PPL",
    "gn:name":"Brekkebygda",
    "gn:population":0,
    "gn:timezone":"Europe/Oslo",
    "iso:country":"NO",
    "wof:name":"Brekkebygda",
    "wof:placetype":"locality"
},
  "geometry": {"coordinates":[9.76021,60.2952],"type":"Point"}
}