{
  "type": "Feature",
  "properties": {
    "gn:admin1_code":"21",
    "gn:admin2_code":"5016.0",
    "gn:asciiname":"Nedre Tennel",
    "gn:cc2":"NO",
    "gn:country_code":"NO",
    "gn:dem":120,
    "gn:feature_class":"P",
    "gn:feature_code":"PPL",
    "gn:name":"Nedre Tennel",
    "gn:population":0,
    "gn:timezone":"Europe/Oslo",
    "iso:country":"NO",
    "name:und_x_variant":[
        "T\u00f6nnel",
        "Nedre T\u00f8nnel",
        "Tennel",
        "Nedre Tennel"
    ],
    "wof:name":"Nedre Tennel",
    "wof:placetype":"locality"
},
  "geometry": {"coordinates":[9.85,63.48333],"type":"Point"}
}