{
  "type": "Feature",
  "properties": {
    "gn:gn_country":"NO",
    "gn:gn_fcode":"PPL",
    "gn:gn_pop":454,
    "gn:population":454,
    "iso:country":"NO",
    "name:ceb_x_preferred":[
        "Harpefoss"
    ],
    "name:eng_x_preferred":[
        "Harpefoss"
    ],
    "name:fra_x_preferred":[
        "Harpefoss"
    ],
    "name:jav_x_preferred":[
        "Harpefoss"
    ],
    "name:msa_x_preferred":[
        "Harpefoss"
    ],
    "name:nld_x_preferred":[
        "Harpefoss"
    ],
    "name:nno_x_preferred":[
        "Harpefoss"
    ],
    "name:nob_x_preferred":[
        "Harpefoss"
    ],
    "name:ron_x_preferred":[
        "Harpefoss"
    ],
    "name:spa_x_preferred":[
        "Harpefoss"
    ],
    "qs_pg:aaroncc":"NO",
    "qs_pg:gn_country":"NO",
    "qs_pg:gn_fcode":"PPL",
    "qs_pg:gn_pop":454,
    "qs_pg:name":"Harpefoss",
    "qs_pg:name_adm0":"Norge",
    "qs_pg:name_adm1":"Oppland Fylke",
    "qs_pg:photos":78,
    "qs_pg:photos_1k":16,
    "qs_pg:photos_9k":1,
    "qs_pg:photos_9r":3,
    "qs_pg:photos_all":78,
    "qs_pg:photos_sr":3,
    "qs_pg:pop_sr":2,
    "qs_pg:qs_pg_placetype":"locality",
    "qs_pg:qs_pg_placetype_gp":"Town",
    "qs_pg:woe_adm0":23424910,
    "woe:adm0_id":23424910,
    "woe:name_adm0":"Norge",
    "woe:name_adm1":"Oppland Fylke",
    "woe:placetype":"Town",
    "wof:name":"Harpefoss",
    "wof:placetype":"locality",
    "wof:population":454
},
  "geometry": {"coordinates":[9.85,61.58333],"type":"Point"}
}