{
  "type": "Feature",
  "properties": {
    "gn:admin1_code":"1.0",
    "gn:admin2_code":"230.0",
    "gn:asciiname":"Skarer",
    "gn:country_code":"NO",
    "gn:dem":196,
    "gn:feature_class":"P",
    "gn:feature_code":"PPL",
    "gn:name":"Sk\u00e5rer",
    "gn:population":0,
    "gn:timezone":"Europe/Oslo",
    "iso:country":"NO",
    "name:nor_x_preferred":[
        "Sk\u00e5rer"
    ],
    "wof:name":"Skarer",
    "wof:placetype":"locality"
},
  "geometry": {"coordinates":[10.96181,59.91899],"type":"Point"}
}