{
  "type": "Feature",
  "properties": {
    "gn:admin1_code":"1",
    "gn:admin2_code":"226.0",
    "gn:asciiname":"Egner",
    "gn:country_code":"NO",
    "gn:dem":150,
    "gn:feature_class":"P",
    "gn:feature_code":"PPL",
    "gn:name":"Egner",
    "gn:population":0,
    "gn:timezone":"Europe/Oslo",
    "iso:country":"NO",
    "wof:name":"Egner",
    "wof:placetype":"locality"
},
  "geometry": {"coordinates":[11.25,60.06667],"type":"Point"}
}