{
  "type": "Feature",
  "properties": {
    "gn:admin1_code":"7.0",
    "gn:admin2_code":"1251.0",
    "gn:asciiname":"Flatkval",
    "gn:country_code":"NO",
    "gn:dem":302,
    "gn:feature_class":"P",
    "gn:feature_code":"PPL",
    "gn:name":"Flatkv\u00e5l",
    "gn:population":0,
    "gn:timezone":"Europe/Oslo",
    "iso:country":"NO",
    "name:jav_x_preferred":[
        "Flatkv\u00e5l"
    ],
    "name:msa_x_preferred":[
        "Flatkv\u00e5l"
    ],
    "name:nor_x_preferred":[
        "Flatkv\u00e5l"
    ],
    "wof:name":"Flatkval",
    "wof:placetype":"locality"
},
  "geometry": {"coordinates":[5.95852,60.78549],"type":"Point"}
}