{
  "type": "Feature",
  "properties": {
    "iso:country":"NO",
    "name:deu_x_preferred":[
        "Nerlands\u00f8ya"
    ],
    "name:nno_x_preferred":[
        "Nerlands\u00f8ya"
    ],
    "name:nor_x_preferred":[
        "Storevarden",
        "Nerlands\u00f8ya"
    ],
    "name:spa_x_preferred":[
        "Nerlands\u00f8ya"
    ],
    "qs:gn_adm0_cc":"NO",
    "qs:gn_local":3134656,
    "qs:gn_nam_loc":"Tertnes, Bergen, Hordaland Fylke, NO",
    "qs:gn_namadm1":"07",
    "qs:local_max":158,
    "qs:local_sum":158,
    "qs:localhoods":1,
    "qs:name":"Storevarden",
    "qs:name_adm0":"Norge",
    "qs:name_adm1":"Hordaland Fylke",
    "qs:name_adm2":"Bergen Kommune",
    "qs:name_local":"Tertnes",
    "qs:photo_max":38,
    "qs:photo_sum":158,
    "qs:placetype":"Suburb",
    "qs:quad_count":36,
    "qs:woe_adm0":23424910,
    "qs:woe_adm1":2346390,
    "qs:woe_adm2":12592658,
    "qs:woe_lau":0,
    "qs:woe_local":864936,
    "qs:woe_ver":"7.10.0",
    "wof:lang":[
        "nor"
    ],
    "wof:name":"Storevarden",
    "wof:placetype":"neighbourhood"
},
  "geometry": {"coordinates":[5.280269,60.455321],"type":"Point"}
}