{
  "type": "Feature",
  "properties": {
    "gn:admin1_code":"6.0",
    "gn:admin2_code":"425.0",
    "gn:asciiname":"Eierholen",
    "gn:country_code":"NO",
    "gn:dem":213,
    "gn:feature_class":"P",
    "gn:feature_code":"PPL",
    "gn:name":"Eierholen",
    "gn:population":0,
    "gn:timezone":"Europe/Oslo",
    "iso:country":"NO",
    "name:nor_x_preferred":[
        "Eierholen"
    ],
    "wof:name":"Eierholen",
    "wof:placetype":"locality"
},
  "geometry": {"coordinates":[11.91955,60.54579],"type":"Point"}
}