{
  "type": "Feature",
  "properties": {
    "gn:admin1_code":"21",
    "gn:admin2_code":"5024",
    "gn:asciiname":"Smaoran",
    "gn:country_code":"NO",
    "gn:dem":1,
    "gn:feature_class":"P",
    "gn:feature_code":"PPLL",
    "gn:name":"Sm\u00e5\u00f8ran",
    "gn:population":0,
    "gn:timezone":"Europe/Oslo",
    "iso:country":"NO",
    "name:nor_x_preferred":[
        "Sm\u00e5\u00f8ran"
    ],
    "wof:name":"Smaoran",
    "wof:placetype":"locality"
},
  "geometry": {"coordinates":[9.81902,63.31911],"type":"Point"}
}