{
  "type": "Feature",
  "properties": {
    "gn:admin1_code":"5.0",
    "gn:admin2_code":"2030.0",
    "gn:asciiname":"Isomukka",
    "gn:country_code":"NO",
    "gn:dem":26,
    "gn:feature_class":"P",
    "gn:feature_code":"PPL",
    "gn:name":"Isomukka",
    "gn:population":0,
    "gn:timezone":"Europe/Oslo",
    "iso:country":"NO",
    "name:fkv_x_preferred":[
        "Isomukka"
    ],
    "name:nor_x_preferred":[
        "Storbukt"
    ],
    "name:sme_x_preferred":[
        "Stuorragohppi"
    ],
    "wof:name":"Isomukka",
    "wof:placetype":"locality"
},
  "geometry": {"coordinates":[30.45772,69.6857],"type":"Point"}
}