{
  "type": "Feature",
  "properties": {
    "gn:admin1_code":"6",
    "gn:admin2_code":"427.0",
    "gn:asciiname":"Moystad",
    "gn:cc2":"NO",
    "gn:country_code":"NO",
    "gn:dem":296,
    "gn:feature_class":"P",
    "gn:feature_code":"PPL",
    "gn:name":"M\u00f8ystad",
    "gn:population":0,
    "gn:timezone":"Europe/Oslo",
    "iso:country":"NO",
    "name:und_x_variant":[
        "M\u00f6jstad",
        "M\u00f6istad",
        "M\u00f8ystad"
    ],
    "wof:name":"Moystad",
    "wof:placetype":"locality"
},
  "geometry": {"coordinates":[11.61667,60.93333000000001],"type":"Point"}
}