{
  "type": "Feature",
  "properties": {
    "iso:country":"NO",
    "name:eng_x_preferred":[
        "Nord-Sel"
    ],
    "name:fra_x_preferred":[
        "Nord-Sel"
    ],
    "name:jav_x_preferred":[
        "Nord-Sel"
    ],
    "name:msa_x_preferred":[
        "Nord-Sel"
    ],
    "name:nld_x_preferred":[
        "Nord-Sel"
    ],
    "name:nno_x_preferred":[
        "Bygda Sel"
    ],
    "name:nob_x_preferred":[
        "Nord-Sel"
    ],
    "name:ron_x_preferred":[
        "Nord-Sel"
    ],
    "qs_pg:aaroncc":"NO",
    "qs_pg:name":"Nord-sel",
    "qs_pg:name_adm0":"Norge",
    "qs_pg:name_adm1":"Oppland Fylke",
    "qs_pg:photos":81,
    "qs_pg:photos_1k":16,
    "qs_pg:photos_9k":1,
    "qs_pg:photos_9r":3,
    "qs_pg:photos_all":81,
    "qs_pg:photos_sr":3,
    "qs_pg:pop_sr":0,
    "qs_pg:qs_pg_placetype":"locality",
    "qs_pg:qs_pg_placetype_gp":"Town",
    "qs_pg:woe_adm0":23424910,
    "woe:adm0_id":23424910,
    "woe:name_adm0":"Norge",
    "woe:name_adm1":"Oppland Fylke",
    "woe:placetype":"Town",
    "wof:name":"Nord-sel",
    "wof:placetype":"locality"
},
  "geometry": {"coordinates":[9.429101,61.847709],"type":"Point"}
}