{
  "type": "Feature",
  "properties": {
    "gn:admin1_code":"6.0",
    "gn:admin2_code":"402.0",
    "gn:asciiname":"Karterud",
    "gn:country_code":"NO",
    "gn:dem":180,
    "gn:feature_class":"P",
    "gn:feature_code":"PPL",
    "gn:name":"Karterud",
    "gn:population":0,
    "gn:timezone":"Europe/Oslo",
    "iso:country":"NO",
    "name:nor_x_preferred":[
        "Karterud"
    ],
    "wof:name":"Karterud",
    "wof:placetype":"locality"
},
  "geometry": {"coordinates":[12.36528,60.06541],"type":"Point"}
}