{
  "type": "Feature",
  "properties": {
    "gn:admin1_code":"1.0",
    "gn:admin2_code":"228.0",
    "gn:asciiname":"Oppsal",
    "gn:country_code":"NO",
    "gn:dem":210,
    "gn:feature_class":"P",
    "gn:feature_code":"PPL",
    "gn:name":"Oppsal",
    "gn:population":0,
    "gn:timezone":"Europe/Oslo",
    "iso:country":"NO",
    "name:nor_x_preferred":[
        "Oppsal"
    ],
    "wof:name":"Oppsal",
    "wof:placetype":"locality"
},
  "geometry": {"coordinates":[11.09244,59.90133],"type":"Point"}
}