{
  "type": "Feature",
  "properties": {
    "gn:admin1_code":"7.0",
    "gn:admin2_code":"1235.0",
    "gn:asciiname":"Skulestadmo",
    "gn:country_code":"NO",
    "gn:dem":80,
    "gn:feature_class":"P",
    "gn:feature_code":"PPL",
    "gn:name":"Skulestadmo",
    "gn:population":0,
    "gn:timezone":"Europe/Oslo",
    "iso:country":"NO",
    "wof:name":"Skulestadmo",
    "wof:placetype":"locality"
},
  "geometry": {"coordinates":[6.42966,60.65841999999999],"type":"Point"}
}