{
  "type": "Feature",
  "properties": {
    "gn:admin1_code":"21.0",
    "gn:admin2_code":"5039.0",
    "gn:asciiname":"Tverras",
    "gn:cc2":"NO",
    "gn:country_code":"NO",
    "gn:dem":160,
    "gn:feature_class":"P",
    "gn:feature_code":"PPL",
    "gn:name":"Tverr\u00e5s",
    "gn:population":0,
    "gn:timezone":"Europe/Oslo",
    "iso:country":"NO",
    "name:und_x_variant":[
        "Tveraas",
        "Tverr\u00e5s"
    ],
    "wof:name":"Tverras",
    "wof:placetype":"locality"
},
  "geometry": {"coordinates":[11.23333,64.09999999999999],"type":"Point"}
}