{
  "type": "Feature",
  "properties": {
    "gn:admin1_code":"7.0",
    "gn:admin2_code":"1238.0",
    "gn:asciiname":"Ytre Alvik",
    "gn:cc2":"NO",
    "gn:country_code":"NO",
    "gn:dem":215,
    "gn:feature_class":"P",
    "gn:feature_code":"PPL",
    "gn:name":"Ytre \u00c5lvik",
    "gn:population":0,
    "gn:timezone":"Europe/Oslo",
    "iso:country":"NO",
    "name:und_x_variant":[
        "\u00c5lvik",
        "Ytre Aalvik",
        "Ytre \u00c5lvik"
    ],
    "wof:name":"Ytre Alvik",
    "wof:placetype":"locality"
},
  "geometry": {"coordinates":[6.36667,60.41667],"type":"Point"}
}