{
  "type": "Feature",
  "properties": {
    "gn:admin1_code":"17",
    "gn:admin2_code":"805.0",
    "gn:asciiname":"Kjorholt",
    "gn:country_code":"NO",
    "gn:dem":112,
    "gn:feature_class":"P",
    "gn:feature_code":"PPL",
    "gn:name":"Kj\u00f8rholt",
    "gn:population":0,
    "gn:timezone":"Europe/Oslo",
    "iso:country":"NO",
    "wof:name":"Kjorholt",
    "wof:placetype":"locality"
},
  "geometry": {"coordinates":[9.66667,59.06667],"type":"Point"}
}