{
  "type": "Feature",
  "properties": {
    "gn:admin1_code":"11.0",
    "gn:admin2_code":"516.0",
    "gn:asciiname":"Oldalen,nordre",
    "gn:country_code":"NO",
    "gn:dem":793,
    "gn:feature_class":"P",
    "gn:feature_code":"PPL",
    "gn:name":"\u00d8ldalen,nordre",
    "gn:population":0,
    "gn:timezone":"Europe/Oslo",
    "iso:country":"NO",
    "name:nor_x_preferred":[
        "\u00d8ldalen,nordre"
    ],
    "wof:name":"Oldalen,nordre",
    "wof:placetype":"locality"
},
  "geometry": {"coordinates":[9.61169,61.63279],"type":"Point"}
}