{
  "type": "Feature",
  "properties": {
    "gn:admin1_code":"9.0",
    "gn:admin2_code":"1852.0",
    "gn:asciiname":"Laukvik",
    "gn:country_code":"NO",
    "gn:dem":1,
    "gn:feature_class":"P",
    "gn:feature_code":"PPL",
    "gn:name":"Laukvik",
    "gn:population":0,
    "gn:timezone":"Europe/Oslo",
    "iso:country":"NO",
    "name:nor_x_preferred":[
        "Laukvik"
    ],
    "wof:name":"Laukvik",
    "wof:placetype":"locality"
},
  "geometry": {"coordinates":[16.23323,68.56229],"type":"Point"}
}