{
  "type": "Feature",
  "properties": {
    "gn:admin1_code":"15.0",
    "gn:admin2_code":"1412.0",
    "gn:asciiname":"Rake",
    "gn:country_code":"NO",
    "gn:dem":110,
    "gn:feature_class":"P",
    "gn:feature_code":"PPL",
    "gn:name":"R\u00e5ke",
    "gn:population":0,
    "gn:timezone":"Europe/Oslo",
    "iso:country":"NO",
    "name:ceb_x_preferred":[
        "Rake"
    ],
    "name:deu_x_preferred":[
        "Rake"
    ],
    "name:fra_x_preferred":[
        "Rake"
    ],
    "name:ita_x_preferred":[
        "Rake"
    ],
    "name:nld_x_preferred":[
        "Rake"
    ],
    "name:pol_x_preferred":[
        "Rake"
    ],
    "name:sco_x_preferred":[
        "Rake"
    ],
    "name:spa_x_preferred":[
        "Rake"
    ],
    "name:swe_x_preferred":[
        "Rake"
    ],
    "name:urd_x_preferred":[
        "\u062c\u0631\u0627\u0641\u06c1"
    ],
    "wof:name":"Rake",
    "wof:placetype":"locality"
},
  "geometry": {"coordinates":[4.83333,61.11666999999999],"type":"Point"}
}