{
  "type": "Feature",
  "properties": {
    "gn:admin1_code":"9.0",
    "gn:admin2_code":"1866.0",
    "gn:asciiname":"Kvanntoelva",
    "gn:country_code":"NO",
    "gn:dem":40,
    "gn:feature_class":"P",
    "gn:feature_code":"PPL",
    "gn:name":"Kvanntoelva",
    "gn:population":0,
    "gn:timezone":"Europe/Oslo",
    "iso:country":"NO",
    "name:nor_x_preferred":[
        "Kvanntoelva"
    ],
    "wof:name":"Kvanntoelva",
    "wof:placetype":"locality"
},
  "geometry": {"coordinates":[15.28971,68.57290999999999],"type":"Point"}
}