{
  "type": "Feature",
  "properties": {
    "gn:admin1_code":"21",
    "gn:admin2_code":"5049.0",
    "gn:asciiname":"Frosendal",
    "gn:cc2":"NO",
    "gn:country_code":"NO",
    "gn:dem":-9999,
    "gn:feature_class":"P",
    "gn:feature_code":"PPL",
    "gn:name":"Fr\u00f8sendal",
    "gn:population":0,
    "gn:timezone":"Europe/Oslo",
    "iso:country":"NO",
    "name:und_x_variant":[
        "Fr\u00f6ssendal",
        "Fr\u00f8sendal"
    ],
    "wof:name":"Frosendal",
    "wof:placetype":"locality"
},
  "geometry": {"coordinates":[10.94917,64.55778000000001],"type":"Point"}
}