{
  "type": "Feature",
  "properties": {
    "gn:admin1_code":"7",
    "gn:admin2_code":"1235.0",
    "gn:asciiname":"Dukstad",
    "gn:country_code":"NO",
    "gn:dem":180,
    "gn:feature_class":"P",
    "gn:feature_code":"PPL",
    "gn:name":"Dukstad",
    "gn:population":0,
    "gn:timezone":"Europe/Oslo",
    "iso:country":"NO",
    "wof:name":"Dukstad",
    "wof:placetype":"locality"
},
  "geometry": {"coordinates":[6.43333,60.66667],"type":"Point"}
}