{
  "type": "Feature",
  "properties": {
    "gn:admin1_code":"17",
    "gn:admin2_code":"806.0",
    "gn:asciiname":"Bo",
    "gn:country_code":"NO",
    "gn:dem":35,
    "gn:feature_class":"P",
    "gn:feature_code":"PPL",
    "gn:name":"B\u00f8",
    "gn:population":0,
    "gn:timezone":"Europe/Oslo",
    "iso:country":"NO",
    "name:dan_x_preferred":[
        "Bo"
    ],
    "name:hye_x_preferred":[
        "\u0532\u0578"
    ],
    "name:lit_x_preferred":[
        "Bo"
    ],
    "wof:name":"Bo",
    "wof:placetype":"locality"
},
  "geometry": {"coordinates":[9.55,59.26667],"type":"Point"}
}