{
  "type": "Feature",
  "properties": {
    "gn:country":"NO",
    "gn:fcode":"PPL",
    "gn:population":0,
    "iso:country":"NO",
    "name:eng_x_preferred":[
        "N\u00e6rsnes"
    ],
    "name:fra_x_preferred":[
        "N\u00e6rsnes"
    ],
    "name:jav_x_preferred":[
        "N\u00e6rsnes"
    ],
    "name:msa_x_preferred":[
        "N\u00e6rsnes"
    ],
    "name:nld_x_preferred":[
        "N\u00e6rsnes"
    ],
    "name:nno_x_preferred":[
        "N\u00e6rsnes"
    ],
    "name:nob_x_preferred":[
        "N\u00e6rsnes"
    ],
    "name:nor_x_preferred":[
        "Nersnes"
    ],
    "name:nor_x_variant":[
        "N\u00e6rsnes"
    ],
    "name:spa_x_preferred":[
        "N\u00e6rsnes"
    ],
    "name:swe_x_preferred":[
        "N\u00e6rsnes"
    ],
    "qs_pg:aaroncc":"NO",
    "qs_pg:gn_country":"NO",
    "qs_pg:gn_fcode":"PPL",
    "qs_pg:gn_pop":0,
    "qs_pg:name":"Nersnes",
    "qs_pg:name_adm0":"Norge",
    "qs_pg:name_adm1":"Buskerud Fylke",
    "qs_pg:photos":365,
    "qs_pg:photos_1k":74,
    "qs_pg:photos_9k":2,
    "qs_pg:photos_9r":5,
    "qs_pg:photos_all":365,
    "qs_pg:photos_sr":6,
    "qs_pg:pop_sr":0,
    "qs_pg:qs_pg_placetype":"locality",
    "qs_pg:qs_pg_placetype_gp":"Town",
    "qs_pg:woe_adm0":23424910,
    "woe:adm0_id":23424910,
    "woe:name_adm0":"Norge",
    "woe:name_adm1":"Buskerud Fylke",
    "woe:placetype":"Town",
    "wof:name":"Nersnes",
    "wof:placetype":"locality"
},
  "geometry": {"coordinates":[10.49833,59.76],"type":"Point"}
}