{
  "type": "Feature",
  "properties": {
    "gn:admin1_code":"21.0",
    "gn:admin2_code":"5026.0",
    "gn:asciiname":"Nora",
    "gn:country_code":"NO",
    "gn:dem":460,
    "gn:feature_class":"P",
    "gn:feature_code":"PPL",
    "gn:name":"N\u00f8ra",
    "gn:population":0,
    "gn:timezone":"Europe/Oslo",
    "iso:country":"NO",
    "name:nor_x_preferred":[
        "N\u00f8ra"
    ],
    "wof:name":"Nora",
    "wof:placetype":"locality"
},
  "geometry": {"coordinates":[11.30389,62.84275],"type":"Point"}
}