{
  "type": "Feature",
  "properties": {
    "gn:admin1_code":"4.0",
    "gn:admin2_code":"616.0",
    "gn:asciiname":"Svenkerud",
    "gn:country_code":"NO",
    "gn:dem":200,
    "gn:feature_class":"P",
    "gn:feature_code":"PPL",
    "gn:name":"Svenkerud",
    "gn:population":0,
    "gn:timezone":"Europe/Oslo",
    "iso:country":"NO",
    "wof:name":"Svenkerud",
    "wof:placetype":"locality"
},
  "geometry": {"coordinates":[9.05,60.64824],"type":"Point"}
}