{
  "type": "Feature",
  "properties": {
    "gn:admin1_code":"18.0",
    "gn:admin2_code":"1938.0",
    "gn:asciiname":"Polleidet",
    "gn:country_code":"NO",
    "gn:dem":25,
    "gn:feature_class":"P",
    "gn:feature_code":"PPL",
    "gn:name":"Polleidet",
    "gn:population":0,
    "gn:timezone":"Europe/Oslo",
    "iso:country":"NO",
    "name:nor_x_preferred":[
        "Polleidet"
    ],
    "name:und_x_variant":[
        "Pollen"
    ],
    "wof:name":"Polleidet",
    "wof:placetype":"locality"
},
  "geometry": {"coordinates":[20.19512000000001,69.49338],"type":"Point"}
}