{
  "type": "Feature",
  "properties": {
    "gn:admin1_code":"21.0",
    "gn:admin2_code":"5042.0",
    "gn:asciiname":"Ulland",
    "gn:country_code":"NO",
    "gn:dem":400,
    "gn:feature_class":"P",
    "gn:feature_code":"PPL",
    "gn:name":"Ulland",
    "gn:population":0,
    "gn:timezone":"Europe/Oslo",
    "iso:country":"NO",
    "name:nor_x_preferred":[
        "Ulland"
    ],
    "wof:name":"Ulland",
    "wof:placetype":"locality"
},
  "geometry": {"coordinates":[13.68333,64.26666999999999],"type":"Point"}
}