{
  "type": "Feature",
  "properties": {
    "gn:admin1_code":"8",
    "gn:admin2_code":"1534.0",
    "gn:asciiname":"Kjerstad",
    "gn:country_code":"NO",
    "gn:dem":1,
    "gn:feature_class":"P",
    "gn:feature_code":"PPL",
    "gn:name":"Kjerstad",
    "gn:population":0,
    "gn:timezone":"Europe/Oslo",
    "iso:country":"NO",
    "wof:name":"Kjerstad",
    "wof:placetype":"locality"
},
  "geometry": {"coordinates":[6.21703,62.61696],"type":"Point"}
}