{
  "type": "Feature",
  "properties": {
    "gn:admin1_code":"18.0",
    "gn:admin2_code":"1942.0",
    "gn:asciiname":"Arildseng",
    "gn:country_code":"NO",
    "gn:dem":37,
    "gn:feature_class":"P",
    "gn:feature_code":"PPL",
    "gn:name":"Arildseng",
    "gn:population":0,
    "gn:timezone":"Europe/Oslo",
    "iso:country":"NO",
    "wof:name":"Arildseng",
    "wof:placetype":"locality"
},
  "geometry": {"coordinates":[21.2925,69.9175],"type":"Point"}
}