{
  "type": "Feature",
  "properties": {
    "iso:country":"NO",
    "qs_pg:aaroncc":"NO",
    "qs_pg:name":"Midtsandan",
    "qs_pg:name_adm0":"Norge",
    "qs_pg:name_adm1":"S\u00f8r-Tr\u00f8ndelag Fylke",
    "qs_pg:photos":109,
    "qs_pg:photos_1k":22,
    "qs_pg:photos_9k":1,
    "qs_pg:photos_9r":3,
    "qs_pg:photos_all":109,
    "qs_pg:photos_sr":3,
    "qs_pg:pop_sr":0,
    "qs_pg:qs_pg_placetype":"locality",
    "qs_pg:qs_pg_placetype_gp":"Town",
    "qs_pg:woe_adm0":23424910,
    "woe:adm0_id":23424910,
    "woe:name_adm0":"Norge",
    "woe:name_adm1":"S\u00f8r-Tr\u00f8ndelag Fylke",
    "woe:placetype":"Town",
    "wof:name":"Midtsandan",
    "wof:placetype":"locality"
},
  "geometry": {"coordinates":[10.744628,63.411044],"type":"Point"}
}