{
  "type": "Feature",
  "properties": {
    "gn:admin1_code":"9.0",
    "gn:admin2_code":"1860.0",
    "gn:asciiname":"Over-Steine",
    "gn:country_code":"NO",
    "gn:dem":-9999,
    "gn:feature_class":"P",
    "gn:feature_code":"PPL",
    "gn:name":"\u00d8ver-Steine",
    "gn:population":0,
    "gn:timezone":"Europe/Oslo",
    "iso:country":"NO",
    "name:nor_x_preferred":[
        "\u00d8ver-Steine"
    ],
    "wof:name":"Over-Steine",
    "wof:placetype":"locality"
},
  "geometry": {"coordinates":[13.78267,68.12116],"type":"Point"}
}