{
  "type": "Feature",
  "properties": {
    "gn:gn_country":"NO",
    "gn:gn_fcode":"PPL",
    "gn:gn_pop":581,
    "gn:population":581,
    "iso:country":"NO",
    "name:ceb_x_preferred":[
        "Kolbu"
    ],
    "name:eng_x_preferred":[
        "Kolbu"
    ],
    "name:fra_x_preferred":[
        "Kolbu"
    ],
    "name:jav_x_preferred":[
        "Kolbu"
    ],
    "name:msa_x_preferred":[
        "Kolbu"
    ],
    "name:nld_x_preferred":[
        "Kolbu"
    ],
    "name:nno_x_preferred":[
        "Kolbu"
    ],
    "name:nob_x_preferred":[
        "Kolbu"
    ],
    "name:ron_x_preferred":[
        "Kolbu"
    ],
    "name:spa_x_preferred":[
        "Kolbu"
    ],
    "qs_pg:aaroncc":"NO",
    "qs_pg:gn_country":"NO",
    "qs_pg:gn_fcode":"PPL",
    "qs_pg:gn_pop":581,
    "qs_pg:name":"Kolbu",
    "qs_pg:name_adm0":"Norge",
    "qs_pg:name_adm1":"Oppland Fylke",
    "qs_pg:photos":18,
    "qs_pg:photos_1k":4,
    "qs_pg:photos_9k":1,
    "qs_pg:photos_9r":1,
    "qs_pg:photos_all":18,
    "qs_pg:photos_sr":1,
    "qs_pg:pop_sr":2,
    "qs_pg:qs_pg_placetype":"locality",
    "qs_pg:qs_pg_placetype_gp":"Town",
    "qs_pg:woe_adm0":23424910,
    "woe:adm0_id":23424910,
    "woe:name_adm0":"Norge",
    "woe:name_adm1":"Oppland Fylke",
    "woe:placetype":"Town",
    "wof:name":"Kolbu",
    "wof:placetype":"locality",
    "wof:population":581
},
  "geometry": {"coordinates":[10.76667,60.61667],"type":"Point"}
}