{
  "type": "Feature",
  "properties": {
    "gn:admin1_code":"15.0",
    "gn:admin2_code":"1432.0",
    "gn:asciiname":"Sundsdalen",
    "gn:country_code":"NO",
    "gn:dem":180,
    "gn:feature_class":"P",
    "gn:feature_code":"PPL",
    "gn:name":"Sundsdalen",
    "gn:population":0,
    "gn:timezone":"Europe/Oslo",
    "iso:country":"NO",
    "wof:name":"Sundsdalen",
    "wof:placetype":"locality"
},
  "geometry": {"coordinates":[5.91667,61.41667],"type":"Point"}
}