{
  "type": "Feature",
  "properties": {
    "gn:admin1_code":"18",
    "gn:admin2_code":"1924.0",
    "gn:asciiname":"Dalem",
    "gn:country_code":"NO",
    "gn:dem":70,
    "gn:feature_class":"P",
    "gn:feature_code":"PPL",
    "gn:name":"Dalem",
    "gn:population":0,
    "gn:timezone":"Europe/Oslo",
    "iso:country":"NO",
    "name:ceb_x_preferred":[
        "Dalem"
    ],
    "name:fra_x_preferred":[
        "Dalem"
    ],
    "name:lim_x_preferred":[
        "Dalem"
    ],
    "name:ltz_x_preferred":[
        "Dalem"
    ],
    "name:nld_x_preferred":[
        "Dalem"
    ],
    "name:rus_x_preferred":[
        "\u0414\u0430\u043b\u0435\u043c"
    ],
    "name:srp_x_preferred":[
        "\u0414\u0430\u043b\u0435\u043c"
    ],
    "wof:name":"Dalem",
    "wof:placetype":"neighbourhood"
},
  "geometry": {"coordinates":[18.51667,69.06667],"type":"Point"}
}