{
  "type": "Feature",
  "properties": {
    "gn:admin1_code":"21.0",
    "gn:admin2_code":"5028.0",
    "gn:asciiname":"Naevsgrenda",
    "gn:country_code":"NO",
    "gn:dem":367,
    "gn:feature_class":"P",
    "gn:feature_code":"PPL",
    "gn:name":"N\u00e6vsgrenda",
    "gn:population":0,
    "gn:timezone":"Europe/Oslo",
    "iso:country":"NO",
    "name:nor_x_preferred":[
        "N\u00e6vsgrenda"
    ],
    "wof:name":"Naevsgrenda",
    "wof:placetype":"locality"
},
  "geometry": {"coordinates":[9.92342,63.09529000000001],"type":"Point"}
}