{
  "type": "Feature",
  "properties": {
    "gn:admin1_code":"9",
    "gn:admin2_code":"1849.0",
    "gn:asciiname":"Fitje",
    "gn:country_code":"NO",
    "gn:dem":15,
    "gn:feature_class":"P",
    "gn:feature_code":"PPL",
    "gn:name":"Fitje",
    "gn:population":0,
    "gn:timezone":"Europe/Oslo",
    "iso:country":"NO",
    "wof:name":"Fitje",
    "wof:placetype":"locality"
},
  "geometry": {"coordinates":[15.44083,68.13916999999999],"type":"Point"}
}