{
  "type": "Feature",
  "properties": {
    "gn:admin1_code":"9",
    "gn:admin2_code":"1812.0",
    "gn:asciiname":"Hjelmset",
    "gn:country_code":"NO",
    "gn:dem":80,
    "gn:feature_class":"P",
    "gn:feature_code":"PPL",
    "gn:name":"Hjelmset",
    "gn:population":0,
    "gn:timezone":"Europe/Oslo",
    "iso:country":"NO",
    "wof:name":"Hjelmset",
    "wof:placetype":"locality"
},
  "geometry": {"coordinates":[12.16667,65.25],"type":"Point"}
}