{
  "type": "Feature",
  "properties": {
    "gn:admin1_code":"21",
    "gn:admin2_code":"5046.0",
    "gn:asciiname":"Borstad",
    "gn:country_code":"NO",
    "gn:dem":50,
    "gn:feature_class":"P",
    "gn:feature_code":"PPL",
    "gn:name":"B\u00f8rstad",
    "gn:population":0,
    "gn:timezone":"Europe/Oslo",
    "iso:country":"NO",
    "name:nor_x_preferred":[
        "B\u00f8rstad"
    ],
    "wof:name":"Borstad",
    "wof:placetype":"locality"
},
  "geometry": {"coordinates":[12.28333,64.63333],"type":"Point"}
}