{
  "type": "Feature",
  "properties": {
    "gn:admin1_code":"21.0",
    "gn:admin2_code":"5020.0",
    "gn:asciiname":"Vingsand",
    "gn:country_code":"NO",
    "gn:dem":30,
    "gn:feature_class":"P",
    "gn:feature_code":"PPL",
    "gn:name":"Vingsand",
    "gn:population":0,
    "gn:timezone":"Europe/Oslo",
    "iso:country":"NO",
    "wof:name":"Vingsand",
    "wof:placetype":"locality"
},
  "geometry": {"coordinates":[10.46358,64.34772],"type":"Point"}
}