{
  "type": "Feature",
  "properties": {
    "gn:admin1_code":"21",
    "gn:admin2_code":"5026.0",
    "gn:asciiname":"Droyvollen",
    "gn:cc2":"NO",
    "gn:country_code":"NO",
    "gn:dem":780,
    "gn:feature_class":"P",
    "gn:feature_code":"PPL",
    "gn:name":"Dr\u00f8yvollen",
    "gn:population":0,
    "gn:timezone":"Europe/Oslo",
    "iso:country":"NO",
    "name:und_x_variant":[
        "Dr\u00f6ivold",
        "Dr\u00f8ia",
        "Dr\u00f8yvollen"
    ],
    "wof:name":"Droyvollen",
    "wof:placetype":"locality"
},
  "geometry": {"coordinates":[11.21667,62.91667],"type":"Point"}
}