{
  "type": "Feature",
  "properties": {
    "gn:admin1_code":"20",
    "gn:admin2_code":"713.0",
    "gn:asciiname":"Orevika",
    "gn:country_code":"NO",
    "gn:dem":15,
    "gn:feature_class":"P",
    "gn:feature_code":"PPL",
    "gn:name":"Orevika",
    "gn:population":0,
    "gn:timezone":"Europe/Oslo",
    "iso:country":"NO",
    "wof:name":"Orevika",
    "wof:placetype":"locality"
},
  "geometry": {"coordinates":[10.28583,59.55416999999999],"type":"Point"}
}