{
  "type": "Feature",
  "properties": {
    "gn:country":"NO",
    "iso:country":"NO",
    "name:ast_x_preferred":[
        "Hadsel"
    ],
    "name:bpy_x_preferred":[
        "\u09b9\u09be\u09a1\u09b8\u09c7\u09b2"
    ],
    "name:bul_x_preferred":[
        "\u0425\u0430\u0434\u0441\u0435\u043b"
    ],
    "name:cat_x_preferred":[
        "Hadsel"
    ],
    "name:ceb_x_preferred":[
        "Hadsel"
    ],
    "name:dan_x_preferred":[
        "Hadsel"
    ],
    "name:deu_x_preferred":[
        "Hadsel"
    ],
    "name:eng_x_preferred":[
        "Hadsel"
    ],
    "name:epo_x_preferred":[
        "Hadsel"
    ],
    "name:eus_x_preferred":[
        "Hadsel"
    ],
    "name:fin_x_preferred":[
        "Hadsel"
    ],
    "name:fra_x_preferred":[
        "Hadsel"
    ],
    "name:ita_x_preferred":[
        "Hadsel"
    ],
    "name:jav_x_preferred":[
        "Hadsel"
    ],
    "name:jpn_x_preferred":[
        "\u30cf\u30c3\u30bb\u30eb"
    ],
    "name:lat_x_preferred":[
        "Hadsel"
    ],
    "name:lim_x_preferred":[
        "Hadsel"
    ],
    "name:mkd_x_preferred":[
        "\u0425\u0430\u0434\u0441\u0435\u043d"
    ],
    "name:msa_x_preferred":[
        "Hadsel"
    ],
    "name:nan_x_preferred":[
        "Hadsel"
    ],
    "name:nds_x_preferred":[
        "Kommun Hadsel"
    ],
    "name:nld_x_preferred":[
        "Hadsel"
    ],
    "name:nno_x_preferred":[
        "Hadsel"
    ],
    "name:nob_x_preferred":[
        "Hadsel"
    ],
    "name:pol_x_preferred":[
        "Hadsel"
    ],
    "name:por_x_preferred":[
        "Hadsel"
    ],
    "name:ron_x_preferred":[
        "Hadsel"
    ],
    "name:rus_x_preferred":[
        "\u0425\u0430\u0434\u0441\u0435\u043b\u044c"
    ],
    "name:slv_x_preferred":[
        "Hadsel"
    ],
    "name:sme_x_preferred":[
        "V\u00e1lafierda"
    ],
    "name:spa_x_preferred":[
        "Hadsel"
    ],
    "name:sqi_x_preferred":[
        "Hadsel"
    ],
    "name:swa_x_preferred":[
        "Hadsel"
    ],
    "name:swe_x_preferred":[
        "Hadsel"
    ],
    "name:vie_x_preferred":[
        "Hadsel"
    ],
    "name:war_x_preferred":[
        "Hadsel"
    ],
    "name:zho_x_preferred":[
        "\u54c8\u5fb7\u745f\u723e"
    ],
    "qs_pg:aaroncc":"NO",
    "qs_pg:gn_country":"NO",
    "qs_pg:name":"Hadsel",
    "qs_pg:name_adm0":"Norge",
    "qs_pg:name_adm1":"Nordland Fylke",
    "qs_pg:photos":5,
    "qs_pg:photos_1k":1,
    "qs_pg:photos_9k":1,
    "qs_pg:photos_9r":1,
    "qs_pg:photos_all":5,
    "qs_pg:photos_sr":1,
    "qs_pg:pop_sr":0,
    "qs_pg:qs_pg_placetype":"locality",
    "qs_pg:qs_pg_placetype_gp":"Town",
    "qs_pg:woe_adm0":23424910,
    "woe:adm0_id":23424910,
    "woe:name_adm0":"Norge",
    "woe:name_adm1":"Nordland Fylke",
    "woe:placetype":"Town",
    "wof:name":"Hadsel",
    "wof:placetype":"locality"
},
  "geometry": {"coordinates":[14.980373,68.541442],"type":"Point"}
}