{
  "type": "Feature",
  "properties": {
    "gn:admin1_code":"19",
    "gn:admin2_code":"1004.0",
    "gn:asciiname":"Ersdal",
    "gn:country_code":"NO",
    "gn:dem":251,
    "gn:feature_class":"P",
    "gn:feature_code":"PPL",
    "gn:name":"Ersdal",
    "gn:population":0,
    "gn:timezone":"Europe/Oslo",
    "iso:country":"NO",
    "wof:name":"Ersdal",
    "wof:placetype":"locality"
},
  "geometry": {"coordinates":[6.68908,58.43888000000001],"type":"Point"}
}