{
  "type": "Feature",
  "properties": {
    "gn:admin1_code":"20",
    "gn:admin2_code":"710",
    "gn:asciiname":"Sollokka",
    "gn:country_code":"NO",
    "gn:dem":16,
    "gn:feature_class":"P",
    "gn:feature_code":"PPLL",
    "gn:name":"Soll\u00f8kka",
    "gn:population":0,
    "gn:timezone":"Europe/Oslo",
    "iso:country":"NO",
    "name:nor_x_preferred":[
        "Soll\u00f8kka"
    ],
    "wof:name":"Sollokka",
    "wof:placetype":"locality"
},
  "geometry": {"coordinates":[10.29554,59.14075],"type":"Point"}
}