{
  "type": "Feature",
  "properties": {
    "gn:admin1_code":"14",
    "gn:admin2_code":"1102.0",
    "gn:asciiname":"Froyland",
    "gn:cc2":"NO",
    "gn:country_code":"NO",
    "gn:dem":67,
    "gn:feature_class":"P",
    "gn:feature_code":"PPL",
    "gn:name":"Fr\u00f8yland",
    "gn:population":0,
    "gn:timezone":"Europe/Oslo",
    "iso:country":"NO",
    "name:und_x_variant":[
        "Fr\u00f6iland",
        "Fr\u00f8yland"
    ],
    "wof:name":"Froyland",
    "wof:placetype":"locality"
},
  "geometry": {"coordinates":[5.85,58.91667],"type":"Point"}
}