{
  "type": "Feature",
  "properties": {
    "gn:admin1_code":"2.0",
    "gn:admin2_code":"929.0",
    "gn:asciiname":"Skjeggedal",
    "gn:country_code":"NO",
    "gn:dem":352,
    "gn:feature_class":"P",
    "gn:feature_code":"PPL",
    "gn:name":"Skjeggedal",
    "gn:population":0,
    "gn:timezone":"Europe/Oslo",
    "iso:country":"NO",
    "wof:name":"Skjeggedal",
    "wof:placetype":"locality"
},
  "geometry": {"coordinates":[8.13333,58.75],"type":"Point"}
}