{
  "type": "Feature",
  "properties": {
    "gn:admin1_code":"7.0",
    "gn:admin2_code":"1216.0",
    "gn:asciiname":"Valevag",
    "gn:country_code":"NO",
    "gn:dem":15,
    "gn:feature_class":"P",
    "gn:feature_code":"PPL",
    "gn:name":"Valev\u00e5g",
    "gn:population":0,
    "gn:timezone":"Europe/Oslo",
    "iso:country":"NO",
    "name:nno_x_preferred":[
        "Valev\u00e5g"
    ],
    "name:nor_x_preferred":[
        "Valev\u00e5g"
    ],
    "wof:name":"Valevag",
    "wof:placetype":"locality"
},
  "geometry": {"coordinates":[5.47241,59.69946],"type":"Point"}
}