{
  "type": "Feature",
  "properties": {
    "gn:admin1_code":"21.0",
    "gn:admin2_code":"5051.0",
    "gn:asciiname":"Teplingan",
    "gn:country_code":"NO",
    "gn:dem":60,
    "gn:feature_class":"P",
    "gn:feature_code":"PPL",
    "gn:name":"Teplingan",
    "gn:population":0,
    "gn:timezone":"Europe/Oslo",
    "iso:country":"NO",
    "name:nor_x_preferred":[
        "Teplingan"
    ],
    "wof:name":"Teplingan",
    "wof:placetype":"locality"
},
  "geometry": {"coordinates":[12.31667,64.95],"type":"Point"}
}