{
  "type": "Feature",
  "properties": {
    "gn:admin1_code":"18",
    "gn:admin2_code":"1924.0",
    "gn:asciiname":"Karlstad",
    "gn:country_code":"NO",
    "gn:dem":5,
    "gn:feature_class":"P",
    "gn:feature_code":"PPL",
    "gn:name":"Karlstad",
    "gn:population":0,
    "gn:timezone":"Europe/Oslo",
    "iso:country":"NO",
    "wof:name":"Karlstad",
    "wof:placetype":"locality"
},
  "geometry": {"coordinates":[18.47012,69.21349000000001],"type":"Point"}
}