{
  "type": "Feature",
  "properties": {
    "gn:admin1_code":"9.0",
    "gn:admin2_code":"1850.0",
    "gn:asciiname":"Straumen",
    "gn:country_code":"NO",
    "gn:dem":1,
    "gn:feature_class":"P",
    "gn:feature_code":"PPL",
    "gn:name":"Straumen",
    "gn:population":0,
    "gn:timezone":"Europe/Oslo",
    "iso:country":"NO",
    "name:ceb_x_preferred":[
        "Straumen"
    ],
    "name:deu_x_preferred":[
        "Straumen"
    ],
    "name:ita_x_preferred":[
        "Straumen"
    ],
    "name:nld_x_preferred":[
        "Straumen"
    ],
    "name:nno_x_preferred":[
        "Straumen"
    ],
    "name:nor_x_preferred":[
        "Straumen"
    ],
    "name:ron_x_preferred":[
        "Straumen"
    ],
    "name:smj_x_preferred":[
        "Str\u00e1vve"
    ],
    "name:spa_x_preferred":[
        "Straumen"
    ],
    "wof:name":"Straumen",
    "wof:placetype":"locality"
},
  "geometry": {"coordinates":[16.68341,68.09116999999999],"type":"Point"}
}