{
  "type": "Feature",
  "properties": {
    "gn:admin1_code":"7",
    "gn:admin2_code":"1243.0",
    "gn:asciiname":"Loynningdal",
    "gn:country_code":"NO",
    "gn:dem":200,
    "gn:feature_class":"P",
    "gn:feature_code":"PPL",
    "gn:name":"L\u00f8ynningdal",
    "gn:population":0,
    "gn:timezone":"Europe/Oslo",
    "iso:country":"NO",
    "wof:name":"Loynningdal",
    "wof:placetype":"locality"
},
  "geometry": {"coordinates":[5.55972,60.26833000000001],"type":"Point"}
}