{
  "type": "Feature",
  "properties": {
    "gn:admin1_code":"6.0",
    "gn:admin2_code":"412.0",
    "gn:asciiname":"Torsaeter",
    "gn:cc2":"NO",
    "gn:country_code":"NO",
    "gn:dem":420,
    "gn:feature_class":"P",
    "gn:feature_code":"PPL",
    "gn:name":"Tors\u00e6ter",
    "gn:population":0,
    "gn:timezone":"Europe/Oslo",
    "iso:country":"NO",
    "name:und_x_variant":[
        "Tors\u00e6teren",
        "Tors\u00e6ter"
    ],
    "wof:name":"Torsaeter",
    "wof:placetype":"locality"
},
  "geometry": {"coordinates":[10.96667,60.93333000000001],"type":"Point"}
}