{
  "type": "Feature",
  "properties": {
    "gn:admin1_code":"7.0",
    "gn:admin2_code":"1224.0",
    "gn:asciiname":"Skeie",
    "gn:country_code":"NO",
    "gn:dem":306,
    "gn:feature_class":"P",
    "gn:feature_code":"PPL",
    "gn:name":"Skeie",
    "gn:population":0,
    "gn:timezone":"Europe/Oslo",
    "iso:country":"NO",
    "wof:name":"Skeie",
    "wof:placetype":"locality"
},
  "geometry": {"coordinates":[6.03333,59.96666999999999],"type":"Point"}
}