{
  "type": "Feature",
  "properties": {
    "gn:admin1_code":"5.0",
    "gn:admin2_code":"2012.0",
    "gn:asciiname":"Mella",
    "gn:country_code":"NO",
    "gn:dem":30,
    "gn:feature_class":"P",
    "gn:feature_code":"PPL",
    "gn:name":"Mella",
    "gn:population":0,
    "gn:timezone":"Europe/Oslo",
    "iso:country":"NO",
    "name:ceb_x_preferred":[
        "Mella"
    ],
    "name:deu_x_preferred":[
        "Mella"
    ],
    "name:fra_x_preferred":[
        "Mella"
    ],
    "name:glg_x_preferred":[
        "Mella"
    ],
    "name:ita_x_preferred":[
        "Mella"
    ],
    "name:por_x_preferred":[
        "Mella"
    ],
    "name:spa_x_preferred":[
        "Mella"
    ],
    "name:srp_x_preferred":[
        "Mella"
    ],
    "name:swe_x_preferred":[
        "Mella"
    ],
    "name:vie_x_preferred":[
        "Mella"
    ],
    "wof:name":"Mella",
    "wof:placetype":"locality"
},
  "geometry": {"coordinates":[23.53333,70.01666999999999],"type":"Point"}
}