{
  "type": "Feature",
  "properties": {
    "gn:admin1_code":"19.0",
    "gn:admin2_code":"1026.0",
    "gn:asciiname":"Tjaldal",
    "gn:cc2":"NO",
    "gn:country_code":"NO",
    "gn:dem":422,
    "gn:feature_class":"P",
    "gn:feature_code":"PPL",
    "gn:name":"Tjaldal",
    "gn:population":0,
    "gn:timezone":"Europe/Oslo",
    "iso:country":"NO",
    "name:und_x_variant":[
        "Tjalddal",
        "Tjaldal"
    ],
    "wof:name":"Tjaldal",
    "wof:placetype":"locality"
},
  "geometry": {"coordinates":[7.4877,58.79384],"type":"Point"}
}