{
  "type": "Feature",
  "properties": {
    "gn:admin1_code":"11.0",
    "gn:admin2_code":"522.0",
    "gn:asciiname":"Druktjornhaugen",
    "gn:country_code":"NO",
    "gn:dem":880,
    "gn:feature_class":"P",
    "gn:feature_code":"PPL",
    "gn:name":"Druktj\u00f8rnhaugen",
    "gn:population":0,
    "gn:timezone":"Europe/Oslo",
    "iso:country":"NO",
    "name:nor_x_preferred":[
        "Druktj\u00f8rnhaugen"
    ],
    "wof:name":"Druktjornhaugen",
    "wof:placetype":"locality"
},
  "geometry": {"coordinates":[9.72254,61.23365],"type":"Point"}
}