{
  "type": "Feature",
  "properties": {
    "gn:country":"NO",
    "iso:country":"NO",
    "qs_pg:aaroncc":"NO",
    "qs_pg:gn_country":"NO",
    "qs_pg:name":"H\u00f8nseby",
    "qs_pg:name_adm0":"Norge",
    "qs_pg:name_adm1":"Finnmark Fylke",
    "qs_pg:photos":50,
    "qs_pg:photos_1k":10,
    "qs_pg:photos_9k":1,
    "qs_pg:photos_9r":2,
    "qs_pg:photos_all":50,
    "qs_pg:photos_sr":2,
    "qs_pg:pop_sr":0,
    "qs_pg:qs_pg_placetype":"locality",
    "qs_pg:qs_pg_placetype_gp":"Town",
    "qs_pg:woe_adm0":23424910,
    "woe:adm0_id":23424910,
    "woe:name_adm0":"Norge",
    "woe:name_adm1":"Finnmark Fylke",
    "woe:placetype":"Town",
    "wof:name":"H\u00f8nseby",
    "wof:placetype":"locality"
},
  "geometry": {"coordinates":[23.4595435,70.574027],"type":"Point"}
}