{
  "type": "Feature",
  "properties": {
    "gn:admin1_code":"19.0",
    "gn:admin2_code":"1003.0",
    "gn:asciiname":"Skeibrokk",
    "gn:country_code":"NO",
    "gn:dem":81,
    "gn:feature_class":"P",
    "gn:feature_code":"PPL",
    "gn:name":"Skeibrokk",
    "gn:population":0,
    "gn:timezone":"Europe/Oslo",
    "iso:country":"NO",
    "name:nor_x_preferred":[
        "Skeibrokk"
    ],
    "wof:name":"Skeibrokk",
    "wof:placetype":"locality"
},
  "geometry": {"coordinates":[6.62474,58.13249],"type":"Point"}
}