{
  "type": "Feature",
  "properties": {
    "gn:admin1_code":"18.0",
    "gn:admin2_code":"1942.0",
    "gn:asciiname":"Mattisnes",
    "gn:country_code":"NO",
    "gn:dem":-9999,
    "gn:feature_class":"P",
    "gn:feature_code":"PPL",
    "gn:name":"Mattisnes",
    "gn:population":0,
    "gn:timezone":"Europe/Oslo",
    "iso:country":"NO",
    "wof:name":"Mattisnes",
    "wof:placetype":"locality"
},
  "geometry": {"coordinates":[20.98667,69.92166999999999],"type":"Point"}
}