{
  "type": "Feature",
  "properties": {
    "gn:admin1_code":"1.0",
    "gn:admin2_code":"221.0",
    "gn:asciiname":"Solum",
    "gn:country_code":"NO",
    "gn:dem":141,
    "gn:feature_class":"P",
    "gn:feature_code":"PPL",
    "gn:name":"Solum",
    "gn:population":0,
    "gn:timezone":"Europe/Oslo",
    "iso:country":"NO",
    "name:deu_x_preferred":[
        "Solum"
    ],
    "name:ind_x_preferred":[
        "Solum"
    ],
    "name:nor_x_preferred":[
        "Solum"
    ],
    "wof:name":"Solum",
    "wof:placetype":"locality"
},
  "geometry": {"coordinates":[11.40842,59.72823],"type":"Point"}
}