{
  "type": "Feature",
  "properties": {
    "gn:admin1_code":"11",
    "gn:admin2_code":"528.0",
    "gn:asciiname":"Fjellhaug",
    "gn:cc2":"NO",
    "gn:country_code":"NO",
    "gn:dem":320,
    "gn:feature_class":"P",
    "gn:feature_code":"PPL",
    "gn:name":"Fjellhaug",
    "gn:population":0,
    "gn:timezone":"Europe/Oslo",
    "iso:country":"NO",
    "name:und_x_variant":[
        "Fjeldhaug",
        "Fjellhaug"
    ],
    "wof:name":"Fjellhaug",
    "wof:placetype":"locality"
},
  "geometry": {"coordinates":[11.08333,60.61666999999999],"type":"Point"}
}