{
  "type": "Feature",
  "properties": {
    "gn:admin1_code":"15",
    "gn:admin2_code":"1429.0",
    "gn:asciiname":"Flekke",
    "gn:cc2":"NO",
    "gn:country_code":"NO",
    "gn:dem":120,
    "gn:feature_class":"P",
    "gn:feature_code":"PPL",
    "gn:name":"Flekke",
    "gn:population":0,
    "gn:timezone":"Europe/Oslo",
    "iso:country":"NO",
    "name:und_x_variant":[
        "Flekke i Sunnfjord",
        "Flekke"
    ],
    "wof:name":"Flekke",
    "wof:placetype":"locality"
},
  "geometry": {"coordinates":[5.36336,61.31535],"type":"Point"}
}