{
  "type": "Feature",
  "properties": {
    "gn:country":"NO",
    "gn:fcode":"PPL",
    "gn:population":347,
    "iso:country":"NO",
    "name:ceb_x_preferred":[
        "Holvika"
    ],
    "name:eng_x_preferred":[
        "Holvik"
    ],
    "name:fra_x_preferred":[
        "Holvik"
    ],
    "name:msa_x_preferred":[
        "Holvik"
    ],
    "name:nld_x_preferred":[
        "Holevik"
    ],
    "name:nno_x_preferred":[
        "Holvika"
    ],
    "name:nob_x_preferred":[
        "Holvik"
    ],
    "name:pol_x_preferred":[
        "Holvika"
    ],
    "name:ron_x_preferred":[
        "Holvik"
    ],
    "name:rus_x_preferred":[
        "\u0425\u043e\u043b\u044c\u0432\u0438\u043a"
    ],
    "name:spa_x_preferred":[
        "Holevik"
    ],
    "name:und_x_variant":[
        "Hollevik"
    ],
    "qs_pg:aaroncc":"NO",
    "qs_pg:gn_country":"NO",
    "qs_pg:gn_fcode":"PPL",
    "qs_pg:gn_pop":347,
    "qs_pg:name":"Holevik",
    "qs_pg:name_adm0":"Norge",
    "qs_pg:name_adm1":"Sogn og Fjordane Fylke",
    "qs_pg:photos_9k":1,
    "qs_pg:photos_9r":1,
    "qs_pg:photos_all":3,
    "qs_pg:photos_sr":0,
    "qs_pg:pop_sr":2,
    "qs_pg:qs_pg_placetype":"locality",
    "qs_pg:qs_pg_placetype_gp":"Town",
    "qs_pg:woe_adm0":23424910,
    "woe:adm0_id":23424910,
    "woe:name_adm0":"Norge",
    "woe:name_adm1":"Sogn og Fjordane Fylke",
    "woe:placetype":"Town",
    "wof:name":"Holevik",
    "wof:placetype":"locality",
    "wof:population":347
},
  "geometry": {"coordinates":[5.07972,61.92889],"type":"Point"}
}